"Class","Method","Depth","Trace Instruction(s) ...","Java Code Representation","Code Merged","Access Control Level"
"Lcom/android/server/PersistentDataBlockService$1","setOemUnlockEnabled(Z)V","0","4 = invokestatic < Application, Landroid/app/ActivityManager, isUserAMonkey()Z > @0 exception:3,
conditional branch(eq, to iindex=-1) 4,5,
return,","depth : 0
-----
","public void setOemUnlockEnabled(boolean p1){
	boolean v1 = ActivityManager.isUserAMonkey();
	if (v1 == 0) {
		return;
	}
}
","SYS_OR_SIG"
"Lcom/android/server/PersistentDataBlockService$1","setOemUnlockEnabled(Z)V","0","4 = invokestatic < Application, Landroid/app/ActivityManager, isUserAMonkey()Z > @0 exception:3,
conditional branch(eq, to iindex=-1) 4,5,
6 = getfield < Application, Lcom/android/server/PersistentDataBlockService$1, this$0, <Application,Lcom/android/server/PersistentDataBlockService> > 1,
invokestatic < Application, Lcom/android/server/PersistentDataBlockService, -$$Nest$menforceOemUnlockWritePermission(Lcom/android/server/PersistentDataBlockService;)V > 6 @9 exception:7,
8 = getfield < Application, Lcom/android/server/PersistentDataBlockService$1, this$0, <Application,Lcom/android/server/PersistentDataBlockService> > 1,
invokestatic < Application, Lcom/android/server/PersistentDataBlockService, -$$Nest$menforceIsAdmin(Lcom/android/server/PersistentDataBlockService;)V > 8 @14 exception:9,
conditional branch(eq, to iindex=-1) 2,5,
10 = getfield < Application, Lcom/android/server/PersistentDataBlockService$1, this$0, <Application,Lcom/android/server/PersistentDataBlockService> > 1,
invokestatic < Application, Lcom/android/server/PersistentDataBlockService, -$$Nest$menforceUserRestriction(Lcom/android/server/PersistentDataBlockService;Ljava/lang/String;)V > 10,11 @24 exception:12,
13 = getfield < Application, Lcom/android/server/PersistentDataBlockService$1, this$0, <Application,Lcom/android/server/PersistentDataBlockService> > 1,
invokestatic < Application, Lcom/android/server/PersistentDataBlockService, -$$Nest$menforceUserRestriction(Lcom/android/server/PersistentDataBlockService;Ljava/lang/String;)V > 13,14 @32 exception:15,
18 = getfield < Application, Lcom/android/server/PersistentDataBlockService$1, this$0, <Application,Lcom/android/server/PersistentDataBlockService> > 1,
20 = invokestatic < Application, Lcom/android/server/PersistentDataBlockService, -$$Nest$fgetmLock(Lcom/android/server/PersistentDataBlockService;)Ljava/lang/Object; > 18 @37 exception:19,
monitorenter 20,
21 = getfield < Application, Lcom/android/server/PersistentDataBlockService$1, this$0, <Application,Lcom/android/server/PersistentDataBlockService> > 1,
invokestatic < Application, Lcom/android/server/PersistentDataBlockService, -$$Nest$mdoSetOemUnlockEnabledLocked(Lcom/android/server/PersistentDataBlockService;Z)V > 21,2 @44 exception:22,
23 = getfield < Application, Lcom/android/server/PersistentDataBlockService$1, this$0, <Application,Lcom/android/server/PersistentDataBlockService> > 1,
25 = invokestatic < Application, Lcom/android/server/PersistentDataBlockService, -$$Nest$mcomputeAndWriteDigestLocked(Lcom/android/server/PersistentDataBlockService;)Z > 23 @49 exception:24,
monitorexit 20,
return,","depth : 0
-----
","public void setOemUnlockEnabled(boolean p1){
	boolean v1 = ActivityManager.isUserAMonkey();
	if (v1 == 0) {
		PersistentDataBlockService.-$$Nest$menforceIsAdmin(this.this$0);
		if (p1 == 0) {
			PersistentDataBlockService.-$$Nest$menforceUserRestriction(this.this$0, ""no_oem_unlock"");
			PersistentDataBlockService.-$$Nest$menforceUserRestriction(this.this$0, ""no_factory_reset"");
			Object v6 = PersistentDataBlockService.-$$Nest$fgetmLock(this.this$0);
			PersistentDataBlockService.-$$Nest$mdoSetOemUnlockEnabledLocked(this.this$0, p1);
			boolean v8 = PersistentDataBlockService.-$$Nest$mcomputeAndWriteDigestLocked(this.this$0);
			return;
		}
	}
}
","SYS_OR_SIG"
"Lcom/android/server/PersistentDataBlockService$1","setOemUnlockEnabled(Z)V","1","4 = invokestatic < Application, Landroid/app/ActivityManager, isUserAMonkey()Z > @0 exception:3,
conditional branch(eq, to iindex=-1) 4,5,
6 = getfield < Application, Lcom/android/server/PersistentDataBlockService$1, this$0, <Application,Lcom/android/server/PersistentDataBlockService> > 1,
invokestatic < Application, Lcom/android/server/PersistentDataBlockService, -$$Nest$menforceOemUnlockWritePermission(Lcom/android/server/PersistentDataBlockService;)V > 6 @9 exception:7,
8 = getfield < Application, Lcom/android/server/PersistentDataBlockService$1, this$0, <Application,Lcom/android/server/PersistentDataBlockService> > 1,
invokestatic < Application, Lcom/android/server/PersistentDataBlockService, -$$Nest$menforceIsAdmin(Lcom/android/server/PersistentDataBlockService;)V > 8 @14 exception:9,
invokevirtual < Application, Lcom/android/server/PersistentDataBlockService, enforceIsAdmin()V > 1 @0 exception:2,
return,
conditional branch(eq, to iindex=-1) 2,5,
10 = getfield < Application, Lcom/android/server/PersistentDataBlockService$1, this$0, <Application,Lcom/android/server/PersistentDataBlockService> > 1,
invokestatic < Application, Lcom/android/server/PersistentDataBlockService, -$$Nest$menforceUserRestriction(Lcom/android/server/PersistentDataBlockService;Ljava/lang/String;)V > 10,11 @24 exception:12,
invokevirtual < Application, Lcom/android/server/PersistentDataBlockService, enforceUserRestriction(Ljava/lang/String;)V > 1,2 @0 exception:3,
return,
13 = getfield < Application, Lcom/android/server/PersistentDataBlockService$1, this$0, <Application,Lcom/android/server/PersistentDataBlockService> > 1,
invokestatic < Application, Lcom/android/server/PersistentDataBlockService, -$$Nest$menforceUserRestriction(Lcom/android/server/PersistentDataBlockService;Ljava/lang/String;)V > 13,14 @32 exception:15,
invokevirtual < Application, Lcom/android/server/PersistentDataBlockService, enforceUserRestriction(Ljava/lang/String;)V > 1,2 @0 exception:3,
return,
18 = getfield < Application, Lcom/android/server/PersistentDataBlockService$1, this$0, <Application,Lcom/android/server/PersistentDataBlockService> > 1,
20 = invokestatic < Application, Lcom/android/server/PersistentDataBlockService, -$$Nest$fgetmLock(Lcom/android/server/PersistentDataBlockService;)Ljava/lang/Object; > 18 @37 exception:19,
2 = getfield < Application, Lcom/android/server/PersistentDataBlockService, mLock, <Application,Ljava/lang/Object> > 1,
return 2,
monitorenter 20,
21 = getfield < Application, Lcom/android/server/PersistentDataBlockService$1, this$0, <Application,Lcom/android/server/PersistentDataBlockService> > 1,
invokestatic < Application, Lcom/android/server/PersistentDataBlockService, -$$Nest$mdoSetOemUnlockEnabledLocked(Lcom/android/server/PersistentDataBlockService;Z)V > 21,2 @44 exception:22,
invokevirtual < Application, Lcom/android/server/PersistentDataBlockService, doSetOemUnlockEnabledLocked(Z)V > 1,2 @0 exception:3,
return,
23 = getfield < Application, Lcom/android/server/PersistentDataBlockService$1, this$0, <Application,Lcom/android/server/PersistentDataBlockService> > 1,
25 = invokestatic < Application, Lcom/android/server/PersistentDataBlockService, -$$Nest$mcomputeAndWriteDigestLocked(Lcom/android/server/PersistentDataBlockService;)Z > 23 @49 exception:24,
3 = invokevirtual < Application, Lcom/android/server/PersistentDataBlockService, computeAndWriteDigestLocked()Z > 1 @0 exception:2,
return 3,
monitorexit 20,
return,","depth : 0
-----
depth : 1
-----
depth : 1
-----
depth : 1
-----
depth : 1
-----
depth : 1
-----
depth : 1
-----
","public void setOemUnlockEnabled(boolean p1){
	boolean v1 = ActivityManager.isUserAMonkey();
	if (v1 == 0) {
		this.this$0.enforceIsAdmin();
		if (p1 == 0) {
			this.this$0.enforceUserRestriction(""no_oem_unlock"");
			this.this$0.enforceUserRestriction(""no_factory_reset"");
			Object v9 = this.mLock;
			this.this$0.doSetOemUnlockEnabledLocked(p1);
			boolean v13 = this.this$0.computeAndWriteDigestLocked();
			boolean v12 = v13;
			return;
		}
	}
}
","SYS_OR_SIG"
"Lcom/android/server/PersistentDataBlockService$1","setOemUnlockEnabled(Z)V","2","4 = invokestatic < Application, Landroid/app/ActivityManager, isUserAMonkey()Z > @0 exception:3,
conditional branch(eq, to iindex=-1) 4,5,
6 = getfield < Application, Lcom/android/server/PersistentDataBlockService$1, this$0, <Application,Lcom/android/server/PersistentDataBlockService> > 1,
invokestatic < Application, Lcom/android/server/PersistentDataBlockService, -$$Nest$menforceOemUnlockWritePermission(Lcom/android/server/PersistentDataBlockService;)V > 6 @9 exception:7,
8 = getfield < Application, Lcom/android/server/PersistentDataBlockService$1, this$0, <Application,Lcom/android/server/PersistentDataBlockService> > 1,
invokestatic < Application, Lcom/android/server/PersistentDataBlockService, -$$Nest$menforceIsAdmin(Lcom/android/server/PersistentDataBlockService;)V > 8 @14 exception:9,
invokevirtual < Application, Lcom/android/server/PersistentDataBlockService, enforceIsAdmin()V > 1 @0 exception:2,
3 = invokestatic < Application, Landroid/os/UserHandle, getCallingUserId()I > @0 exception:2,
4 = getfield < Application, Lcom/android/server/PersistentDataBlockService, mContext, <Application,Landroid/content/Context> > 1,
6 = invokestatic < Application, Landroid/os/UserManager, get(Landroid/content/Context;)Landroid/os/UserManager; > 4 @6 exception:5,
8 = invokevirtual < Application, Landroid/os/UserManager, isUserAdmin(I)Z > 6,3 @10 exception:7,
conditional branch(eq, to iindex=-1) 8,9,
return,
return,
conditional branch(eq, to iindex=-1) 2,5,
10 = getfield < Application, Lcom/android/server/PersistentDataBlockService$1, this$0, <Application,Lcom/android/server/PersistentDataBlockService> > 1,
invokestatic < Application, Lcom/android/server/PersistentDataBlockService, -$$Nest$menforceUserRestriction(Lcom/android/server/PersistentDataBlockService;Ljava/lang/String;)V > 10,11 @24 exception:12,
invokevirtual < Application, Lcom/android/server/PersistentDataBlockService, enforceUserRestriction(Ljava/lang/String;)V > 1,2 @0 exception:3,
3 = getfield < Application, Lcom/android/server/PersistentDataBlockService, mContext, <Application,Landroid/content/Context> > 1,
5 = invokestatic < Application, Landroid/os/UserManager, get(Landroid/content/Context;)Landroid/os/UserManager; > 3 @2 exception:4,
7 = invokevirtual < Application, Landroid/os/UserManager, hasUserRestriction(Ljava/lang/String;)Z > 5,2 @6 exception:6,
conditional branch(ne, to iindex=-1) 7,8,
return,
return,
13 = getfield < Application, Lcom/android/server/PersistentDataBlockService$1, this$0, <Application,Lcom/android/server/PersistentDataBlockService> > 1,
invokestatic < Application, Lcom/android/server/PersistentDataBlockService, -$$Nest$menforceUserRestriction(Lcom/android/server/PersistentDataBlockService;Ljava/lang/String;)V > 13,14 @32 exception:15,
invokevirtual < Application, Lcom/android/server/PersistentDataBlockService, enforceUserRestriction(Ljava/lang/String;)V > 1,2 @0 exception:3,
3 = getfield < Application, Lcom/android/server/PersistentDataBlockService, mContext, <Application,Landroid/content/Context> > 1,
5 = invokestatic < Application, Landroid/os/UserManager, get(Landroid/content/Context;)Landroid/os/UserManager; > 3 @2 exception:4,
7 = invokevirtual < Application, Landroid/os/UserManager, hasUserRestriction(Ljava/lang/String;)Z > 5,2 @6 exception:6,
conditional branch(ne, to iindex=-1) 7,8,
return,
return,
18 = getfield < Application, Lcom/android/server/PersistentDataBlockService$1, this$0, <Application,Lcom/android/server/PersistentDataBlockService> > 1,
20 = invokestatic < Application, Lcom/android/server/PersistentDataBlockService, -$$Nest$fgetmLock(Lcom/android/server/PersistentDataBlockService;)Ljava/lang/Object; > 18 @37 exception:19,
monitorenter 20,
21 = getfield < Application, Lcom/android/server/PersistentDataBlockService$1, this$0, <Application,Lcom/android/server/PersistentDataBlockService> > 1,
invokestatic < Application, Lcom/android/server/PersistentDataBlockService, -$$Nest$mdoSetOemUnlockEnabledLocked(Lcom/android/server/PersistentDataBlockService;Z)V > 21,2 @44 exception:22,
invokevirtual < Application, Lcom/android/server/PersistentDataBlockService, doSetOemUnlockEnabledLocked(Z)V > 1,2 @0 exception:3,
7 = invokevirtual < Application, Lcom/android/server/PersistentDataBlockService, getBlockOutputChannel()Ljava/nio/channels/FileChannel; > 1 @7 exception:6,
9 = invokevirtual < Application, Lcom/android/server/PersistentDataBlockService, getBlockDeviceSize()J > 1 @11 exception:8,
11 = binaryop(sub) 9 , 10,
13 = invokevirtual < Application, Ljava/nio/channels/FileChannel, position(J)Ljava/nio/channels/FileChannel; > 7,11 @18 exception:12,
16 = invokestatic < Application, Ljava/nio/ByteBuffer, allocate(I)Ljava/nio/ByteBuffer; > 14 @22 exception:15,
conditional branch(eq, to iindex=-1) 2,17,
goto (from iindex= 15 to iindex = 2),
18 = phi  14,17,
20 = invokevirtual < Application, Ljava/nio/ByteBuffer, put(B)Ljava/nio/ByteBuffer; > 16,18 @31 exception:19,
22 = invokevirtual < Application, Ljava/nio/ByteBuffer, flip()Ljava/nio/Buffer; > 16 @34 exception:21,
24 = invokevirtual < Application, Ljava/nio/channels/FileChannel, write(Ljava/nio/ByteBuffer;)I > 7,16 @37 exception:23,
invokevirtual < Application, Ljava/nio/channels/FileChannel, force(Z)V > 7,14 @40 exception:25,
conditional branch(eq, to iindex=-1) 2,17,
goto (from iindex= 22 to iindex = 2),
47 = phi  3,4,
invokestatic < Application, Landroid/os/SystemProperties, set(Ljava/lang/String;Ljava/lang/String;)V > 5,47 @47 exception:48,
return,
return,
23 = getfield < Application, Lcom/android/server/PersistentDataBlockService$1, this$0, <Application,Lcom/android/server/PersistentDataBlockService> > 1,
25 = invokestatic < Application, Lcom/android/server/PersistentDataBlockService, -$$Nest$mcomputeAndWriteDigestLocked(Lcom/android/server/PersistentDataBlockService;)Z > 23 @49 exception:24,
3 = invokevirtual < Application, Lcom/android/server/PersistentDataBlockService, computeAndWriteDigestLocked()Z > 1 @0 exception:2,
4 = invokevirtual < Application, Lcom/android/server/PersistentDataBlockService, computeDigestLocked([B)[B > 1,2 @1 exception:3,
conditional branch(eq, to iindex=-1) 4,2,
6 = invokevirtual < Application, Lcom/android/server/PersistentDataBlockService, getBlockOutputChannel()Ljava/nio/channels/FileChannel; > 1 @8 exception:5,
18 = invokestatic < Application, Ljava/nio/ByteBuffer, allocate(I)Ljava/nio/ByteBuffer; > 16 @14 exception:17,
20 = invokevirtual < Application, Ljava/nio/ByteBuffer, put([B)Ljava/nio/ByteBuffer; > 18,4 @18 exception:19,
22 = invokevirtual < Application, Ljava/nio/ByteBuffer, flip()Ljava/nio/Buffer; > 18 @21 exception:21,
24 = invokevirtual < Application, Ljava/nio/channels/FileChannel, write(Ljava/nio/ByteBuffer;)I > 6,18 @24 exception:23,
invokevirtual < Application, Ljava/nio/channels/FileChannel, force(Z)V > 6,25 @28 exception:26,
return 25,
return 3,
monitorexit 20,
return,","depth : 0
-----
depth : 1
-----
depth : 2
-----
depth : 1
-----
depth : 2
-----
depth : 1
-----
depth : 2
-----
depth : 1
-----
depth : 2
-----
depth : 1
-----
depth : 2
-----
","public void setOemUnlockEnabled(boolean p1){
	boolean v1 = ActivityManager.isUserAMonkey();
	if (v1 == 0) {
		int v5 = UserHandle.getCallingUserId();
		UserManager v6 = UserManager.get(this.mContext);
		boolean v7 = v6.isUserAdmin(v5);
		if (v7 == 0) {
			if (p1 == 0) {
				Object v16 = PersistentDataBlockService.-$$Nest$fgetmLock(this.this$0);
				FileChannel v19 = PersistentDataBlockService.getBlockOutputChannel();
				long v20 = PersistentDataBlockService.getBlockDeviceSize();
				FileChannel v21 = v19.position((v20 - 1));
				ByteBuffer v22 = ByteBuffer.allocate(1);
				if (p1 == 0) {
					ByteBuffer v23 = v22.put(1);
					Buffer v24 = v22.flip();
					int v25 = v19.write(v22);
					v19.force(1);
					if (p1 == 0) {
						SystemProperties.set(""sys.oem_unlock_allowed"", ""1"");
						byte[] v30 = PersistentDataBlockService.computeDigestLocked(0);
						if (v30 == 0) {
							FileChannel v31 = PersistentDataBlockService.getBlockOutputChannel();
							ByteBuffer v32 = ByteBuffer.allocate(32);
							ByteBuffer v33 = v32.put(v30);
							Buffer v34 = v32.flip();
							int v35 = v31.write(v32);
							v31.force(1);
							boolean v29 = 1;
							boolean v28 = v29;
							return;
						}
					}
				}
			}
		}
	}
}
","SYS_OR_SIG"
"Lcom/android/server/PersistentDataBlockService$1","setOemUnlockEnabled(Z)V","2","4 = invokestatic < Application, Landroid/app/ActivityManager, isUserAMonkey()Z > @0 exception:3,
conditional branch(eq, to iindex=-1) 4,5,
6 = getfield < Application, Lcom/android/server/PersistentDataBlockService$1, this$0, <Application,Lcom/android/server/PersistentDataBlockService> > 1,
invokestatic < Application, Lcom/android/server/PersistentDataBlockService, -$$Nest$menforceOemUnlockWritePermission(Lcom/android/server/PersistentDataBlockService;)V > 6 @9 exception:7,
8 = getfield < Application, Lcom/android/server/PersistentDataBlockService$1, this$0, <Application,Lcom/android/server/PersistentDataBlockService> > 1,
invokestatic < Application, Lcom/android/server/PersistentDataBlockService, -$$Nest$menforceIsAdmin(Lcom/android/server/PersistentDataBlockService;)V > 8 @14 exception:9,
invokevirtual < Application, Lcom/android/server/PersistentDataBlockService, enforceIsAdmin()V > 1 @0 exception:2,
3 = invokestatic < Application, Landroid/os/UserHandle, getCallingUserId()I > @0 exception:2,
4 = getfield < Application, Lcom/android/server/PersistentDataBlockService, mContext, <Application,Landroid/content/Context> > 1,
6 = invokestatic < Application, Landroid/os/UserManager, get(Landroid/content/Context;)Landroid/os/UserManager; > 4 @6 exception:5,
8 = invokevirtual < Application, Landroid/os/UserManager, isUserAdmin(I)Z > 6,3 @10 exception:7,
conditional branch(eq, to iindex=-1) 8,9,
return,
return,
conditional branch(eq, to iindex=-1) 2,5,
10 = getfield < Application, Lcom/android/server/PersistentDataBlockService$1, this$0, <Application,Lcom/android/server/PersistentDataBlockService> > 1,
invokestatic < Application, Lcom/android/server/PersistentDataBlockService, -$$Nest$menforceUserRestriction(Lcom/android/server/PersistentDataBlockService;Ljava/lang/String;)V > 10,11 @24 exception:12,
invokevirtual < Application, Lcom/android/server/PersistentDataBlockService, enforceUserRestriction(Ljava/lang/String;)V > 1,2 @0 exception:3,
3 = getfield < Application, Lcom/android/server/PersistentDataBlockService, mContext, <Application,Landroid/content/Context> > 1,
5 = invokestatic < Application, Landroid/os/UserManager, get(Landroid/content/Context;)Landroid/os/UserManager; > 3 @2 exception:4,
7 = invokevirtual < Application, Landroid/os/UserManager, hasUserRestriction(Ljava/lang/String;)Z > 5,2 @6 exception:6,
conditional branch(ne, to iindex=-1) 7,8,
return,
return,
13 = getfield < Application, Lcom/android/server/PersistentDataBlockService$1, this$0, <Application,Lcom/android/server/PersistentDataBlockService> > 1,
invokestatic < Application, Lcom/android/server/PersistentDataBlockService, -$$Nest$menforceUserRestriction(Lcom/android/server/PersistentDataBlockService;Ljava/lang/String;)V > 13,14 @32 exception:15,
invokevirtual < Application, Lcom/android/server/PersistentDataBlockService, enforceUserRestriction(Ljava/lang/String;)V > 1,2 @0 exception:3,
3 = getfield < Application, Lcom/android/server/PersistentDataBlockService, mContext, <Application,Landroid/content/Context> > 1,
5 = invokestatic < Application, Landroid/os/UserManager, get(Landroid/content/Context;)Landroid/os/UserManager; > 3 @2 exception:4,
7 = invokevirtual < Application, Landroid/os/UserManager, hasUserRestriction(Ljava/lang/String;)Z > 5,2 @6 exception:6,
conditional branch(ne, to iindex=-1) 7,8,
return,
return,
18 = getfield < Application, Lcom/android/server/PersistentDataBlockService$1, this$0, <Application,Lcom/android/server/PersistentDataBlockService> > 1,
20 = invokestatic < Application, Lcom/android/server/PersistentDataBlockService, -$$Nest$fgetmLock(Lcom/android/server/PersistentDataBlockService;)Ljava/lang/Object; > 18 @37 exception:19,
monitorenter 20,
21 = getfield < Application, Lcom/android/server/PersistentDataBlockService$1, this$0, <Application,Lcom/android/server/PersistentDataBlockService> > 1,
invokestatic < Application, Lcom/android/server/PersistentDataBlockService, -$$Nest$mdoSetOemUnlockEnabledLocked(Lcom/android/server/PersistentDataBlockService;Z)V > 21,2 @44 exception:22,
invokevirtual < Application, Lcom/android/server/PersistentDataBlockService, doSetOemUnlockEnabledLocked(Z)V > 1,2 @0 exception:3,
7 = invokevirtual < Application, Lcom/android/server/PersistentDataBlockService, getBlockOutputChannel()Ljava/nio/channels/FileChannel; > 1 @7 exception:6,
9 = invokevirtual < Application, Lcom/android/server/PersistentDataBlockService, getBlockDeviceSize()J > 1 @11 exception:8,
11 = binaryop(sub) 9 , 10,
13 = invokevirtual < Application, Ljava/nio/channels/FileChannel, position(J)Ljava/nio/channels/FileChannel; > 7,11 @18 exception:12,
16 = invokestatic < Application, Ljava/nio/ByteBuffer, allocate(I)Ljava/nio/ByteBuffer; > 14 @22 exception:15,
conditional branch(eq, to iindex=-1) 2,17,
goto (from iindex= 15 to iindex = 2),
18 = phi  14,17,
20 = invokevirtual < Application, Ljava/nio/ByteBuffer, put(B)Ljava/nio/ByteBuffer; > 16,18 @31 exception:19,
22 = invokevirtual < Application, Ljava/nio/ByteBuffer, flip()Ljava/nio/Buffer; > 16 @34 exception:21,
24 = invokevirtual < Application, Ljava/nio/channels/FileChannel, write(Ljava/nio/ByteBuffer;)I > 7,16 @37 exception:23,
invokevirtual < Application, Ljava/nio/channels/FileChannel, force(Z)V > 7,14 @40 exception:25,
conditional branch(eq, to iindex=-1) 2,17,
goto (from iindex= 22 to iindex = 2),
47 = phi  3,4,
invokestatic < Application, Landroid/os/SystemProperties, set(Ljava/lang/String;Ljava/lang/String;)V > 5,47 @47 exception:48,
return,
return,
23 = getfield < Application, Lcom/android/server/PersistentDataBlockService$1, this$0, <Application,Lcom/android/server/PersistentDataBlockService> > 1,
25 = invokestatic < Application, Lcom/android/server/PersistentDataBlockService, -$$Nest$mcomputeAndWriteDigestLocked(Lcom/android/server/PersistentDataBlockService;)Z > 23 @49 exception:24,
3 = invokevirtual < Application, Lcom/android/server/PersistentDataBlockService, computeAndWriteDigestLocked()Z > 1 @0 exception:2,
4 = invokevirtual < Application, Lcom/android/server/PersistentDataBlockService, computeDigestLocked([B)[B > 1,2 @1 exception:3,
conditional branch(eq, to iindex=-1) 4,2,
return 2,
return 3,
monitorexit 20,
return,","depth : 0
-----
depth : 1
-----
depth : 2
-----
depth : 1
-----
depth : 2
-----
depth : 1
-----
depth : 2
-----
depth : 1
-----
depth : 2
-----
depth : 1
-----
depth : 2
-----
","public void setOemUnlockEnabled(boolean p1){
	boolean v1 = ActivityManager.isUserAMonkey();
	if (v1 == 0) {
		int v5 = UserHandle.getCallingUserId();
		UserManager v6 = UserManager.get(this.mContext);
		boolean v7 = v6.isUserAdmin(v5);
		if (v7 == 0) {
			if (p1 == 0) {
				Object v16 = PersistentDataBlockService.-$$Nest$fgetmLock(this.this$0);
				FileChannel v19 = PersistentDataBlockService.getBlockOutputChannel();
				long v20 = PersistentDataBlockService.getBlockDeviceSize();
				FileChannel v21 = v19.position((v20 - 1));
				ByteBuffer v22 = ByteBuffer.allocate(1);
				if (p1 == 0) {
					ByteBuffer v23 = v22.put(1);
					Buffer v24 = v22.flip();
					int v25 = v19.write(v22);
					v19.force(1);
					if (p1 == 0) {
						SystemProperties.set(""sys.oem_unlock_allowed"", ""1"");
						byte[] v30 = PersistentDataBlockService.computeDigestLocked(0);
						if (v30 == 0) {
							boolean v29 = 0;
							boolean v28 = v29;
							return;
						}
					}
				}
			}
		}
	}
}
","SYS_OR_SIG"

"Lcom/android/server/PersistentDataBlockService$1","getMaximumDataBlockSize()J","0","2 = getfield < Application, Lcom/android/server/PersistentDataBlockService$1, this$0, <Application,Lcom/android/server/PersistentDataBlockService> > 1,
4 = invokestatic < Application, Landroid/os/Binder, getCallingUid()I > @2 exception:3,
invokestatic < Application, Lcom/android/server/PersistentDataBlockService, -$$Nest$menforceUid(Lcom/android/server/PersistentDataBlockService;I)V > 2,4 @6 exception:5,
6 = getfield < Application, Lcom/android/server/PersistentDataBlockService$1, this$0, <Application,Lcom/android/server/PersistentDataBlockService> > 1,
8 = invokestatic < Application, Lcom/android/server/PersistentDataBlockService, -$$Nest$mdoGetMaximumDataBlockSize(Lcom/android/server/PersistentDataBlockService;)J > 6 @11 exception:7,
return 8,","depth : 0
-----
","public long getMaximumDataBlockSize(){
	int v1 = Binder.getCallingUid();
	PersistentDataBlockService.-$$Nest$menforceUid(this.this$0, v1);
	long v3 = PersistentDataBlockService.-$$Nest$mdoGetMaximumDataBlockSize(this.this$0);
	return v3;
}
","NONE"
"Lcom/android/server/PersistentDataBlockService$1","getMaximumDataBlockSize()J","1","2 = getfield < Application, Lcom/android/server/PersistentDataBlockService$1, this$0, <Application,Lcom/android/server/PersistentDataBlockService> > 1,
4 = invokestatic < Application, Landroid/os/Binder, getCallingUid()I > @2 exception:3,
invokestatic < Application, Lcom/android/server/PersistentDataBlockService, -$$Nest$menforceUid(Lcom/android/server/PersistentDataBlockService;I)V > 2,4 @6 exception:5,
invokevirtual < Application, Lcom/android/server/PersistentDataBlockService, enforceUid(I)V > 1,2 @0 exception:3,
return,
6 = getfield < Application, Lcom/android/server/PersistentDataBlockService$1, this$0, <Application,Lcom/android/server/PersistentDataBlockService> > 1,
8 = invokestatic < Application, Lcom/android/server/PersistentDataBlockService, -$$Nest$mdoGetMaximumDataBlockSize(Lcom/android/server/PersistentDataBlockService;)J > 6 @11 exception:7,
3 = invokevirtual < Application, Lcom/android/server/PersistentDataBlockService, doGetMaximumDataBlockSize()J > 1 @0 exception:2,
return 3,
return 8,","depth : 0
-----
depth : 1
-----
depth : 1
-----
","public long getMaximumDataBlockSize(){
	int v1 = Binder.getCallingUid();
	this.this$0.enforceUid(v1);
	long v5 = this.this$0.doGetMaximumDataBlockSize();
	long v4 = v5;
	return v4;
}
","NONE"
"Lcom/android/server/PersistentDataBlockService$1","getMaximumDataBlockSize()J","2","2 = getfield < Application, Lcom/android/server/PersistentDataBlockService$1, this$0, <Application,Lcom/android/server/PersistentDataBlockService> > 1,
4 = invokestatic < Application, Landroid/os/Binder, getCallingUid()I > @2 exception:3,
invokestatic < Application, Lcom/android/server/PersistentDataBlockService, -$$Nest$menforceUid(Lcom/android/server/PersistentDataBlockService;I)V > 2,4 @6 exception:5,
invokevirtual < Application, Lcom/android/server/PersistentDataBlockService, enforceUid(I)V > 1,2 @0 exception:3,
3 = getfield < Application, Lcom/android/server/PersistentDataBlockService, mAllowedUid, <Primordial,I> > 1,
conditional branch(ne, to iindex=-1) 2,3,
return,
return,
6 = getfield < Application, Lcom/android/server/PersistentDataBlockService$1, this$0, <Application,Lcom/android/server/PersistentDataBlockService> > 1,
8 = invokestatic < Application, Lcom/android/server/PersistentDataBlockService, -$$Nest$mdoGetMaximumDataBlockSize(Lcom/android/server/PersistentDataBlockService;)J > 6 @11 exception:7,
3 = invokevirtual < Application, Lcom/android/server/PersistentDataBlockService, doGetMaximumDataBlockSize()J > 1 @0 exception:2,
3 = invokevirtual < Application, Lcom/android/server/PersistentDataBlockService, getBlockDeviceSize()J > 1 @0 exception:2,
5 = binaryop(sub) 3 , 4,
7 = binaryop(sub) 5 , 6,
9 = binaryop(sub) 7 , 8,
11 = binaryop(sub) 9 , 10,
13 = binaryop(sub) 11 , 12,
15 = binaryop(lt) 13 , 14,
conditional branch(gt, to iindex=-1) 15,16,
goto (from iindex= 15 to iindex = 2),
17 = phi  13,14,
return 17,
return 3,
return 8,","depth : 0
-----
depth : 1
-----
depth : 2
-----
depth : 1
-----
depth : 2
-----
","public long getMaximumDataBlockSize(){
	int v1 = Binder.getCallingUid();
	if (v1 != this.mAllowedUid) {
		long v6 = PersistentDataBlockService.getBlockDeviceSize();
		if (((((((v6 - 8) - 32) - 10000) - 1000) - 1) < 102400) > 0) {
			long v5 = (((((v6 - 8) - 32) - 10000) - 1000) - 1);
			long v4 = v5;
			return v4;
		}
	}
}
","NONE"

"Lcom/android/server/PersistentDataBlockService$1","write([B)I","0","3 = getfield < Application, Lcom/android/server/PersistentDataBlockService$1, this$0, <Application,Lcom/android/server/PersistentDataBlockService> > 1,
5 = invokestatic < Application, Landroid/os/Binder, getCallingUid()I > @2 exception:4,
invokestatic < Application, Lcom/android/server/PersistentDataBlockService, -$$Nest$menforceUid(Lcom/android/server/PersistentDataBlockService;I)V > 3,5 @6 exception:6,
7 = getfield < Application, Lcom/android/server/PersistentDataBlockService$1, this$0, <Application,Lcom/android/server/PersistentDataBlockService> > 1,
9 = invokestatic < Application, Lcom/android/server/PersistentDataBlockService, -$$Nest$mdoGetMaximumDataBlockSize(Lcom/android/server/PersistentDataBlockService;)J > 7 @11 exception:8,
10 = arraylength 2,
11 = conversion(J) 10,
12 = binaryop(lt) 11 , 9,
conditional branch(le, to iindex=-1) 12,13,
15 = getfield < Application, Lcom/android/server/PersistentDataBlockService$1, this$0, <Application,Lcom/android/server/PersistentDataBlockService> > 1,
17 = invokestatic < Application, Lcom/android/server/PersistentDataBlockService, -$$Nest$mgetBlockOutputChannel(Lcom/android/server/PersistentDataBlockService;)Ljava/nio/channels/FileChannel; > 15 @27 exception:16,
26 = arraylength 2,
28 = binaryop(add) 26 , 27,
30 = binaryop(add) 28 , 29,
32 = invokestatic < Application, Ljava/nio/ByteBuffer, allocate(I)Ljava/nio/ByteBuffer; > 30 @37 exception:31,
33 = new <Primordial,[B>@4129 ,
35 = invokevirtual < Application, Ljava/nio/ByteBuffer, put([B)Ljava/nio/ByteBuffer; > 32,33 @43 exception:34,
38 = invokevirtual < Application, Ljava/nio/ByteBuffer, putInt(I)Ljava/nio/ByteBuffer; > 32,36 @49 exception:37,
39 = arraylength 2,
41 = invokevirtual < Application, Ljava/nio/ByteBuffer, putInt(I)Ljava/nio/ByteBuffer; > 32,39 @53 exception:40,
43 = invokevirtual < Application, Ljava/nio/ByteBuffer, put([B)Ljava/nio/ByteBuffer; > 32,2 @56 exception:42,
45 = invokevirtual < Application, Ljava/nio/ByteBuffer, flip()Ljava/nio/Buffer; > 32 @59 exception:44,
46 = getfield < Application, Lcom/android/server/PersistentDataBlockService$1, this$0, <Application,Lcom/android/server/PersistentDataBlockService> > 1,
48 = invokestatic < Application, Lcom/android/server/PersistentDataBlockService, -$$Nest$fgetmLock(Lcom/android/server/PersistentDataBlockService;)Ljava/lang/Object; > 46 @64 exception:47,
monitorenter 48,
49 = getfield < Application, Lcom/android/server/PersistentDataBlockService$1, this$0, <Application,Lcom/android/server/PersistentDataBlockService> > 1,
51 = invokestatic < Application, Lcom/android/server/PersistentDataBlockService, -$$Nest$fgetmIsWritable(Lcom/android/server/PersistentDataBlockService;)Z > 49 @71 exception:50,
conditional branch(ne, to iindex=-1) 51,13,
53 = invokevirtual < Application, Ljava/nio/channels/FileChannel, write(Ljava/nio/ByteBuffer;)I > 17,32 @79 exception:52,
invokevirtual < Application, Ljava/nio/channels/FileChannel, force(Z)V > 17,54 @83 exception:55,
64 = getfield < Application, Lcom/android/server/PersistentDataBlockService$1, this$0, <Application,Lcom/android/server/PersistentDataBlockService> > 1,
66 = invokestatic < Application, Lcom/android/server/PersistentDataBlockService, -$$Nest$mcomputeAndWriteDigestLocked(Lcom/android/server/PersistentDataBlockService;)Z > 64 @88 exception:65,
conditional branch(eq, to iindex=-1) 66,13,
67 = arraylength 2,
monitorexit 48,
return 67,","depth : 0
-----
","public int write(byte[] p1){
	int v1 = Binder.getCallingUid();
	PersistentDataBlockService.-$$Nest$menforceUid(this.this$0, v1);
	long v3 = PersistentDataBlockService.-$$Nest$mdoGetMaximumDataBlockSize(this.this$0);
	if ((p1.length < v3) <= 0) {
		FileChannel v4 = PersistentDataBlockService.-$$Nest$mgetBlockOutputChannel(this.this$0);
		ByteBuffer v5 = ByteBuffer.allocate(((p1.length + 8) + 32));
		[B v6 = new [B(32);
		ByteBuffer v7 = v5.put(v6);
		ByteBuffer v8 = v5.putInt(428873843);
		ByteBuffer v9 = v5.putInt(p1.length);
		ByteBuffer v10 = v5.put(p1);
		Buffer v11 = v5.flip();
		Object v12 = PersistentDataBlockService.-$$Nest$fgetmLock(this.this$0);
		boolean v13 = PersistentDataBlockService.-$$Nest$fgetmIsWritable(this.this$0);
		if (v13 != 0) {
			int v14 = v4.write(v5);
			v4.force(1);
			boolean v16 = PersistentDataBlockService.-$$Nest$mcomputeAndWriteDigestLocked(this.this$0);
			if (v16 == 0) {
				return p1.length;
			}
		}
	}
}
","NONE"
"Lcom/android/server/PersistentDataBlockService$1","write([B)I","1","3 = getfield < Application, Lcom/android/server/PersistentDataBlockService$1, this$0, <Application,Lcom/android/server/PersistentDataBlockService> > 1,
5 = invokestatic < Application, Landroid/os/Binder, getCallingUid()I > @2 exception:4,
invokestatic < Application, Lcom/android/server/PersistentDataBlockService, -$$Nest$menforceUid(Lcom/android/server/PersistentDataBlockService;I)V > 3,5 @6 exception:6,
invokevirtual < Application, Lcom/android/server/PersistentDataBlockService, enforceUid(I)V > 1,2 @0 exception:3,
return,
7 = getfield < Application, Lcom/android/server/PersistentDataBlockService$1, this$0, <Application,Lcom/android/server/PersistentDataBlockService> > 1,
9 = invokestatic < Application, Lcom/android/server/PersistentDataBlockService, -$$Nest$mdoGetMaximumDataBlockSize(Lcom/android/server/PersistentDataBlockService;)J > 7 @11 exception:8,
3 = invokevirtual < Application, Lcom/android/server/PersistentDataBlockService, doGetMaximumDataBlockSize()J > 1 @0 exception:2,
return 3,
10 = arraylength 2,
11 = conversion(J) 10,
12 = binaryop(lt) 11 , 9,
conditional branch(le, to iindex=-1) 12,13,
15 = getfield < Application, Lcom/android/server/PersistentDataBlockService$1, this$0, <Application,Lcom/android/server/PersistentDataBlockService> > 1,
17 = invokestatic < Application, Lcom/android/server/PersistentDataBlockService, -$$Nest$mgetBlockOutputChannel(Lcom/android/server/PersistentDataBlockService;)Ljava/nio/channels/FileChannel; > 15 @27 exception:16,
3 = invokevirtual < Application, Lcom/android/server/PersistentDataBlockService, getBlockOutputChannel()Ljava/nio/channels/FileChannel; > 1 @0 exception:2,
return 3,
26 = arraylength 2,
28 = binaryop(add) 26 , 27,
30 = binaryop(add) 28 , 29,
32 = invokestatic < Application, Ljava/nio/ByteBuffer, allocate(I)Ljava/nio/ByteBuffer; > 30 @37 exception:31,
33 = new <Primordial,[B>@4129 ,
35 = invokevirtual < Application, Ljava/nio/ByteBuffer, put([B)Ljava/nio/ByteBuffer; > 32,33 @43 exception:34,
38 = invokevirtual < Application, Ljava/nio/ByteBuffer, putInt(I)Ljava/nio/ByteBuffer; > 32,36 @49 exception:37,
39 = arraylength 2,
41 = invokevirtual < Application, Ljava/nio/ByteBuffer, putInt(I)Ljava/nio/ByteBuffer; > 32,39 @53 exception:40,
43 = invokevirtual < Application, Ljava/nio/ByteBuffer, put([B)Ljava/nio/ByteBuffer; > 32,2 @56 exception:42,
45 = invokevirtual < Application, Ljava/nio/ByteBuffer, flip()Ljava/nio/Buffer; > 32 @59 exception:44,
46 = getfield < Application, Lcom/android/server/PersistentDataBlockService$1, this$0, <Application,Lcom/android/server/PersistentDataBlockService> > 1,
48 = invokestatic < Application, Lcom/android/server/PersistentDataBlockService, -$$Nest$fgetmLock(Lcom/android/server/PersistentDataBlockService;)Ljava/lang/Object; > 46 @64 exception:47,
2 = getfield < Application, Lcom/android/server/PersistentDataBlockService, mLock, <Application,Ljava/lang/Object> > 1,
return 2,
monitorenter 48,
49 = getfield < Application, Lcom/android/server/PersistentDataBlockService$1, this$0, <Application,Lcom/android/server/PersistentDataBlockService> > 1,
51 = invokestatic < Application, Lcom/android/server/PersistentDataBlockService, -$$Nest$fgetmIsWritable(Lcom/android/server/PersistentDataBlockService;)Z > 49 @71 exception:50,
2 = getfield < Application, Lcom/android/server/PersistentDataBlockService, mIsWritable, <Primordial,Z> > 1,
return 2,
conditional branch(ne, to iindex=-1) 51,13,
53 = invokevirtual < Application, Ljava/nio/channels/FileChannel, write(Ljava/nio/ByteBuffer;)I > 17,32 @79 exception:52,
invokevirtual < Application, Ljava/nio/channels/FileChannel, force(Z)V > 17,54 @83 exception:55,
64 = getfield < Application, Lcom/android/server/PersistentDataBlockService$1, this$0, <Application,Lcom/android/server/PersistentDataBlockService> > 1,
66 = invokestatic < Application, Lcom/android/server/PersistentDataBlockService, -$$Nest$mcomputeAndWriteDigestLocked(Lcom/android/server/PersistentDataBlockService;)Z > 64 @88 exception:65,
3 = invokevirtual < Application, Lcom/android/server/PersistentDataBlockService, computeAndWriteDigestLocked()Z > 1 @0 exception:2,
return 3,
conditional branch(eq, to iindex=-1) 66,13,
67 = arraylength 2,
monitorexit 48,
return 67,","depth : 0
-----
depth : 1
-----
depth : 1
-----
depth : 1
-----
depth : 1
-----
depth : 1
-----
depth : 1
-----
","public int write(byte[] p1){
	int v1 = Binder.getCallingUid();
	this.this$0.enforceUid(v1);
	long v5 = this.this$0.doGetMaximumDataBlockSize();
	long v4 = v5;
	if ((p1.length < v4) <= 0) {
		FileChannel v7 = this.this$0.getBlockOutputChannel();
		FileChannel v6 = v7;
		ByteBuffer v8 = ByteBuffer.allocate(((p1.length + 8) + 32));
		[B v9 = new [B(32);
		ByteBuffer v10 = v8.put(v9);
		ByteBuffer v11 = v8.putInt(428873843);
		ByteBuffer v12 = v8.putInt(p1.length);
		ByteBuffer v13 = v8.put(p1);
		Buffer v14 = v8.flip();
		Object v15 = this.mLock;
		boolean v16 = this.mIsWritable;
		if (v16 != 0) {
			int v17 = v6.write(v8);
			v6.force(1);
			boolean v20 = this.this$0.computeAndWriteDigestLocked();
			boolean v19 = v20;
			if (v19 == 0) {
				return p1.length;
			}
		}
	}
}
","NONE"
"Lcom/android/server/PersistentDataBlockService$1","write([B)I","1","3 = getfield < Application, Lcom/android/server/PersistentDataBlockService$1, this$0, <Application,Lcom/android/server/PersistentDataBlockService> > 1,
5 = invokestatic < Application, Landroid/os/Binder, getCallingUid()I > @2 exception:4,
invokestatic < Application, Lcom/android/server/PersistentDataBlockService, -$$Nest$menforceUid(Lcom/android/server/PersistentDataBlockService;I)V > 3,5 @6 exception:6,
invokevirtual < Application, Lcom/android/server/PersistentDataBlockService, enforceUid(I)V > 1,2 @0 exception:3,
return,
7 = getfield < Application, Lcom/android/server/PersistentDataBlockService$1, this$0, <Application,Lcom/android/server/PersistentDataBlockService> > 1,
9 = invokestatic < Application, Lcom/android/server/PersistentDataBlockService, -$$Nest$mdoGetMaximumDataBlockSize(Lcom/android/server/PersistentDataBlockService;)J > 7 @11 exception:8,
3 = invokevirtual < Application, Lcom/android/server/PersistentDataBlockService, doGetMaximumDataBlockSize()J > 1 @0 exception:2,
return 3,
10 = arraylength 2,
11 = conversion(J) 10,
12 = binaryop(lt) 11 , 9,
conditional branch(le, to iindex=-1) 12,13,
15 = getfield < Application, Lcom/android/server/PersistentDataBlockService$1, this$0, <Application,Lcom/android/server/PersistentDataBlockService> > 1,
17 = invokestatic < Application, Lcom/android/server/PersistentDataBlockService, -$$Nest$mgetBlockOutputChannel(Lcom/android/server/PersistentDataBlockService;)Ljava/nio/channels/FileChannel; > 15 @27 exception:16,
3 = invokevirtual < Application, Lcom/android/server/PersistentDataBlockService, getBlockOutputChannel()Ljava/nio/channels/FileChannel; > 1 @0 exception:2,
return 3,
26 = arraylength 2,
28 = binaryop(add) 26 , 27,
30 = binaryop(add) 28 , 29,
32 = invokestatic < Application, Ljava/nio/ByteBuffer, allocate(I)Ljava/nio/ByteBuffer; > 30 @37 exception:31,
33 = new <Primordial,[B>@4129 ,
35 = invokevirtual < Application, Ljava/nio/ByteBuffer, put([B)Ljava/nio/ByteBuffer; > 32,33 @43 exception:34,
38 = invokevirtual < Application, Ljava/nio/ByteBuffer, putInt(I)Ljava/nio/ByteBuffer; > 32,36 @49 exception:37,
39 = arraylength 2,
41 = invokevirtual < Application, Ljava/nio/ByteBuffer, putInt(I)Ljava/nio/ByteBuffer; > 32,39 @53 exception:40,
43 = invokevirtual < Application, Ljava/nio/ByteBuffer, put([B)Ljava/nio/ByteBuffer; > 32,2 @56 exception:42,
45 = invokevirtual < Application, Ljava/nio/ByteBuffer, flip()Ljava/nio/Buffer; > 32 @59 exception:44,
46 = getfield < Application, Lcom/android/server/PersistentDataBlockService$1, this$0, <Application,Lcom/android/server/PersistentDataBlockService> > 1,
48 = invokestatic < Application, Lcom/android/server/PersistentDataBlockService, -$$Nest$fgetmLock(Lcom/android/server/PersistentDataBlockService;)Ljava/lang/Object; > 46 @64 exception:47,
2 = getfield < Application, Lcom/android/server/PersistentDataBlockService, mLock, <Application,Ljava/lang/Object> > 1,
return 2,
monitorenter 48,
49 = getfield < Application, Lcom/android/server/PersistentDataBlockService$1, this$0, <Application,Lcom/android/server/PersistentDataBlockService> > 1,
51 = invokestatic < Application, Lcom/android/server/PersistentDataBlockService, -$$Nest$fgetmIsWritable(Lcom/android/server/PersistentDataBlockService;)Z > 49 @71 exception:50,
2 = getfield < Application, Lcom/android/server/PersistentDataBlockService, mIsWritable, <Primordial,Z> > 1,
return 2,
conditional branch(ne, to iindex=-1) 51,13,
53 = invokevirtual < Application, Ljava/nio/channels/FileChannel, write(Ljava/nio/ByteBuffer;)I > 17,32 @79 exception:52,
invokevirtual < Application, Ljava/nio/channels/FileChannel, force(Z)V > 17,54 @83 exception:55,
64 = getfield < Application, Lcom/android/server/PersistentDataBlockService$1, this$0, <Application,Lcom/android/server/PersistentDataBlockService> > 1,
66 = invokestatic < Application, Lcom/android/server/PersistentDataBlockService, -$$Nest$mcomputeAndWriteDigestLocked(Lcom/android/server/PersistentDataBlockService;)Z > 64 @88 exception:65,
3 = invokevirtual < Application, Lcom/android/server/PersistentDataBlockService, computeAndWriteDigestLocked()Z > 1 @0 exception:2,
return 3,
conditional branch(eq, to iindex=-1) 66,13,
monitorexit 48,
return 14,","depth : 0
-----
depth : 1
-----
depth : 1
-----
depth : 1
-----
depth : 1
-----
depth : 1
-----
depth : 1
-----
","public int write(byte[] p1){
	int v1 = Binder.getCallingUid();
	this.this$0.enforceUid(v1);
	long v5 = this.this$0.doGetMaximumDataBlockSize();
	long v4 = v5;
	if ((p1.length < v4) <= 0) {
		FileChannel v7 = this.this$0.getBlockOutputChannel();
		FileChannel v6 = v7;
		ByteBuffer v8 = ByteBuffer.allocate(((p1.length + 8) + 32));
		[B v9 = new [B(32);
		ByteBuffer v10 = v8.put(v9);
		ByteBuffer v11 = v8.putInt(428873843);
		ByteBuffer v12 = v8.putInt(p1.length);
		ByteBuffer v13 = v8.put(p1);
		Buffer v14 = v8.flip();
		Object v15 = this.mLock;
		boolean v16 = this.mIsWritable;
		if (v16 != 0) {
			int v17 = v6.write(v8);
			v6.force(1);
			boolean v20 = this.this$0.computeAndWriteDigestLocked();
			boolean v19 = v20;
			if (v19 == 0) {
				return -1;
			}
		}
	}
}
","NONE"
"Lcom/android/server/PersistentDataBlockService$1","write([B)I","2","3 = getfield < Application, Lcom/android/server/PersistentDataBlockService$1, this$0, <Application,Lcom/android/server/PersistentDataBlockService> > 1,
5 = invokestatic < Application, Landroid/os/Binder, getCallingUid()I > @2 exception:4,
invokestatic < Application, Lcom/android/server/PersistentDataBlockService, -$$Nest$menforceUid(Lcom/android/server/PersistentDataBlockService;I)V > 3,5 @6 exception:6,
invokevirtual < Application, Lcom/android/server/PersistentDataBlockService, enforceUid(I)V > 1,2 @0 exception:3,
3 = getfield < Application, Lcom/android/server/PersistentDataBlockService, mAllowedUid, <Primordial,I> > 1,
conditional branch(ne, to iindex=-1) 2,3,
return,
return,
7 = getfield < Application, Lcom/android/server/PersistentDataBlockService$1, this$0, <Application,Lcom/android/server/PersistentDataBlockService> > 1,
9 = invokestatic < Application, Lcom/android/server/PersistentDataBlockService, -$$Nest$mdoGetMaximumDataBlockSize(Lcom/android/server/PersistentDataBlockService;)J > 7 @11 exception:8,
3 = invokevirtual < Application, Lcom/android/server/PersistentDataBlockService, doGetMaximumDataBlockSize()J > 1 @0 exception:2,
3 = invokevirtual < Application, Lcom/android/server/PersistentDataBlockService, getBlockDeviceSize()J > 1 @0 exception:2,
5 = binaryop(sub) 3 , 4,
7 = binaryop(sub) 5 , 6,
9 = binaryop(sub) 7 , 8,
11 = binaryop(sub) 9 , 10,
13 = binaryop(sub) 11 , 12,
15 = binaryop(lt) 13 , 14,
conditional branch(gt, to iindex=-1) 15,16,
goto (from iindex= 15 to iindex = 2),
17 = phi  13,14,
return 17,
return 3,
10 = arraylength 2,
11 = conversion(J) 10,
12 = binaryop(lt) 11 , 9,
conditional branch(le, to iindex=-1) 12,13,
15 = getfield < Application, Lcom/android/server/PersistentDataBlockService$1, this$0, <Application,Lcom/android/server/PersistentDataBlockService> > 1,
17 = invokestatic < Application, Lcom/android/server/PersistentDataBlockService, -$$Nest$mgetBlockOutputChannel(Lcom/android/server/PersistentDataBlockService;)Ljava/nio/channels/FileChannel; > 15 @27 exception:16,
3 = invokevirtual < Application, Lcom/android/server/PersistentDataBlockService, getBlockOutputChannel()Ljava/nio/channels/FileChannel; > 1 @0 exception:2,
2 = new <Application,Ljava/io/RandomAccessFile>@0,
3 = getfield < Application, Lcom/android/server/PersistentDataBlockService, mDataBlockFile, <Application,Ljava/lang/String> > 1,
invokespecial < Application, Ljava/io/RandomAccessFile, <init>(Ljava/lang/String;Ljava/lang/String;)V > 2,3,4 @7 exception:5,
7 = invokevirtual < Application, Ljava/io/RandomAccessFile, getChannel()Ljava/nio/channels/FileChannel; > 2 @10 exception:6,
return 7,
return 3,
26 = arraylength 2,
28 = binaryop(add) 26 , 27,
30 = binaryop(add) 28 , 29,
32 = invokestatic < Application, Ljava/nio/ByteBuffer, allocate(I)Ljava/nio/ByteBuffer; > 30 @37 exception:31,
33 = new <Primordial,[B>@4129 ,
35 = invokevirtual < Application, Ljava/nio/ByteBuffer, put([B)Ljava/nio/ByteBuffer; > 32,33 @43 exception:34,
38 = invokevirtual < Application, Ljava/nio/ByteBuffer, putInt(I)Ljava/nio/ByteBuffer; > 32,36 @49 exception:37,
39 = arraylength 2,
41 = invokevirtual < Application, Ljava/nio/ByteBuffer, putInt(I)Ljava/nio/ByteBuffer; > 32,39 @53 exception:40,
43 = invokevirtual < Application, Ljava/nio/ByteBuffer, put([B)Ljava/nio/ByteBuffer; > 32,2 @56 exception:42,
45 = invokevirtual < Application, Ljava/nio/ByteBuffer, flip()Ljava/nio/Buffer; > 32 @59 exception:44,
46 = getfield < Application, Lcom/android/server/PersistentDataBlockService$1, this$0, <Application,Lcom/android/server/PersistentDataBlockService> > 1,
48 = invokestatic < Application, Lcom/android/server/PersistentDataBlockService, -$$Nest$fgetmLock(Lcom/android/server/PersistentDataBlockService;)Ljava/lang/Object; > 46 @64 exception:47,
monitorenter 48,
49 = getfield < Application, Lcom/android/server/PersistentDataBlockService$1, this$0, <Application,Lcom/android/server/PersistentDataBlockService> > 1,
51 = invokestatic < Application, Lcom/android/server/PersistentDataBlockService, -$$Nest$fgetmIsWritable(Lcom/android/server/PersistentDataBlockService;)Z > 49 @71 exception:50,
conditional branch(ne, to iindex=-1) 51,13,
53 = invokevirtual < Application, Ljava/nio/channels/FileChannel, write(Ljava/nio/ByteBuffer;)I > 17,32 @79 exception:52,
invokevirtual < Application, Ljava/nio/channels/FileChannel, force(Z)V > 17,54 @83 exception:55,
64 = getfield < Application, Lcom/android/server/PersistentDataBlockService$1, this$0, <Application,Lcom/android/server/PersistentDataBlockService> > 1,
66 = invokestatic < Application, Lcom/android/server/PersistentDataBlockService, -$$Nest$mcomputeAndWriteDigestLocked(Lcom/android/server/PersistentDataBlockService;)Z > 64 @88 exception:65,
3 = invokevirtual < Application, Lcom/android/server/PersistentDataBlockService, computeAndWriteDigestLocked()Z > 1 @0 exception:2,
4 = invokevirtual < Application, Lcom/android/server/PersistentDataBlockService, computeDigestLocked([B)[B > 1,2 @1 exception:3,
conditional branch(eq, to iindex=-1) 4,2,
6 = invokevirtual < Application, Lcom/android/server/PersistentDataBlockService, getBlockOutputChannel()Ljava/nio/channels/FileChannel; > 1 @8 exception:5,
18 = invokestatic < Application, Ljava/nio/ByteBuffer, allocate(I)Ljava/nio/ByteBuffer; > 16 @14 exception:17,
20 = invokevirtual < Application, Ljava/nio/ByteBuffer, put([B)Ljava/nio/ByteBuffer; > 18,4 @18 exception:19,
22 = invokevirtual < Application, Ljava/nio/ByteBuffer, flip()Ljava/nio/Buffer; > 18 @21 exception:21,
24 = invokevirtual < Application, Ljava/nio/channels/FileChannel, write(Ljava/nio/ByteBuffer;)I > 6,18 @24 exception:23,
invokevirtual < Application, Ljava/nio/channels/FileChannel, force(Z)V > 6,25 @28 exception:26,
return 25,
return 3,
conditional branch(eq, to iindex=-1) 66,13,
67 = arraylength 2,
monitorexit 48,
return 67,","depth : 0
-----
depth : 1
-----
depth : 2
-----
depth : 1
-----
depth : 2
-----
depth : 1
-----
depth : 2
-----
depth : 1
-----
depth : 2
-----
","public int write(byte[] p1){
	int v1 = Binder.getCallingUid();
	if (v1 != this.mAllowedUid) {
		long v6 = PersistentDataBlockService.getBlockDeviceSize();
		if (((((((v6 - 8) - 32) - 10000) - 1000) - 1) < 102400) > 0) {
			long v5 = (((((v6 - 8) - 32) - 10000) - 1000) - 1);
			long v4 = v5;
			if ((p1.length < v4) <= 0) {
				RandomAccessFile v9 = new RandomAccessFile(this.mDataBlockFile,""rw"");
				FileChannel v11 = v9.getChannel();
				FileChannel v8 = v11;
				FileChannel v7 = v8;
				ByteBuffer v12 = ByteBuffer.allocate(((p1.length + 8) + 32));
				[B v13 = new [B(32);
				ByteBuffer v14 = v12.put(v13);
				ByteBuffer v15 = v12.putInt(428873843);
				ByteBuffer v16 = v12.putInt(p1.length);
				ByteBuffer v17 = v12.put(p1);
				Buffer v18 = v12.flip();
				Object v19 = PersistentDataBlockService.-$$Nest$fgetmLock(this.this$0);
				boolean v20 = PersistentDataBlockService.-$$Nest$fgetmIsWritable(this.this$0);
				if (v20 != 0) {
					int v21 = v7.write(v12);
					v7.force(1);
					byte[] v25 = PersistentDataBlockService.computeDigestLocked(0);
					if (v25 == 0) {
						FileChannel v26 = PersistentDataBlockService.getBlockOutputChannel();
						ByteBuffer v27 = ByteBuffer.allocate(32);
						ByteBuffer v28 = v27.put(v25);
						Buffer v29 = v27.flip();
						int v30 = v26.write(v27);
						v26.force(1);
						boolean v24 = 1;
						boolean v23 = v24;
						if (v23 == 0) {
							return p1.length;
						}
					}
				}
			}
		}
	}
}
","NONE"
"Lcom/android/server/PersistentDataBlockService$1","write([B)I","2","3 = getfield < Application, Lcom/android/server/PersistentDataBlockService$1, this$0, <Application,Lcom/android/server/PersistentDataBlockService> > 1,
5 = invokestatic < Application, Landroid/os/Binder, getCallingUid()I > @2 exception:4,
invokestatic < Application, Lcom/android/server/PersistentDataBlockService, -$$Nest$menforceUid(Lcom/android/server/PersistentDataBlockService;I)V > 3,5 @6 exception:6,
invokevirtual < Application, Lcom/android/server/PersistentDataBlockService, enforceUid(I)V > 1,2 @0 exception:3,
3 = getfield < Application, Lcom/android/server/PersistentDataBlockService, mAllowedUid, <Primordial,I> > 1,
conditional branch(ne, to iindex=-1) 2,3,
return,
return,
7 = getfield < Application, Lcom/android/server/PersistentDataBlockService$1, this$0, <Application,Lcom/android/server/PersistentDataBlockService> > 1,
9 = invokestatic < Application, Lcom/android/server/PersistentDataBlockService, -$$Nest$mdoGetMaximumDataBlockSize(Lcom/android/server/PersistentDataBlockService;)J > 7 @11 exception:8,
3 = invokevirtual < Application, Lcom/android/server/PersistentDataBlockService, doGetMaximumDataBlockSize()J > 1 @0 exception:2,
3 = invokevirtual < Application, Lcom/android/server/PersistentDataBlockService, getBlockDeviceSize()J > 1 @0 exception:2,
5 = binaryop(sub) 3 , 4,
7 = binaryop(sub) 5 , 6,
9 = binaryop(sub) 7 , 8,
11 = binaryop(sub) 9 , 10,
13 = binaryop(sub) 11 , 12,
15 = binaryop(lt) 13 , 14,
conditional branch(gt, to iindex=-1) 15,16,
goto (from iindex= 15 to iindex = 2),
17 = phi  13,14,
return 17,
return 3,
10 = arraylength 2,
11 = conversion(J) 10,
12 = binaryop(lt) 11 , 9,
conditional branch(le, to iindex=-1) 12,13,
15 = getfield < Application, Lcom/android/server/PersistentDataBlockService$1, this$0, <Application,Lcom/android/server/PersistentDataBlockService> > 1,
17 = invokestatic < Application, Lcom/android/server/PersistentDataBlockService, -$$Nest$mgetBlockOutputChannel(Lcom/android/server/PersistentDataBlockService;)Ljava/nio/channels/FileChannel; > 15 @27 exception:16,
3 = invokevirtual < Application, Lcom/android/server/PersistentDataBlockService, getBlockOutputChannel()Ljava/nio/channels/FileChannel; > 1 @0 exception:2,
2 = new <Application,Ljava/io/RandomAccessFile>@0,
3 = getfield < Application, Lcom/android/server/PersistentDataBlockService, mDataBlockFile, <Application,Ljava/lang/String> > 1,
invokespecial < Application, Ljava/io/RandomAccessFile, <init>(Ljava/lang/String;Ljava/lang/String;)V > 2,3,4 @7 exception:5,
7 = invokevirtual < Application, Ljava/io/RandomAccessFile, getChannel()Ljava/nio/channels/FileChannel; > 2 @10 exception:6,
return 7,
return 3,
26 = arraylength 2,
28 = binaryop(add) 26 , 27,
30 = binaryop(add) 28 , 29,
32 = invokestatic < Application, Ljava/nio/ByteBuffer, allocate(I)Ljava/nio/ByteBuffer; > 30 @37 exception:31,
33 = new <Primordial,[B>@4129 ,
35 = invokevirtual < Application, Ljava/nio/ByteBuffer, put([B)Ljava/nio/ByteBuffer; > 32,33 @43 exception:34,
38 = invokevirtual < Application, Ljava/nio/ByteBuffer, putInt(I)Ljava/nio/ByteBuffer; > 32,36 @49 exception:37,
39 = arraylength 2,
41 = invokevirtual < Application, Ljava/nio/ByteBuffer, putInt(I)Ljava/nio/ByteBuffer; > 32,39 @53 exception:40,
43 = invokevirtual < Application, Ljava/nio/ByteBuffer, put([B)Ljava/nio/ByteBuffer; > 32,2 @56 exception:42,
45 = invokevirtual < Application, Ljava/nio/ByteBuffer, flip()Ljava/nio/Buffer; > 32 @59 exception:44,
46 = getfield < Application, Lcom/android/server/PersistentDataBlockService$1, this$0, <Application,Lcom/android/server/PersistentDataBlockService> > 1,
48 = invokestatic < Application, Lcom/android/server/PersistentDataBlockService, -$$Nest$fgetmLock(Lcom/android/server/PersistentDataBlockService;)Ljava/lang/Object; > 46 @64 exception:47,
monitorenter 48,
49 = getfield < Application, Lcom/android/server/PersistentDataBlockService$1, this$0, <Application,Lcom/android/server/PersistentDataBlockService> > 1,
51 = invokestatic < Application, Lcom/android/server/PersistentDataBlockService, -$$Nest$fgetmIsWritable(Lcom/android/server/PersistentDataBlockService;)Z > 49 @71 exception:50,
conditional branch(ne, to iindex=-1) 51,13,
53 = invokevirtual < Application, Ljava/nio/channels/FileChannel, write(Ljava/nio/ByteBuffer;)I > 17,32 @79 exception:52,
invokevirtual < Application, Ljava/nio/channels/FileChannel, force(Z)V > 17,54 @83 exception:55,
64 = getfield < Application, Lcom/android/server/PersistentDataBlockService$1, this$0, <Application,Lcom/android/server/PersistentDataBlockService> > 1,
66 = invokestatic < Application, Lcom/android/server/PersistentDataBlockService, -$$Nest$mcomputeAndWriteDigestLocked(Lcom/android/server/PersistentDataBlockService;)Z > 64 @88 exception:65,
3 = invokevirtual < Application, Lcom/android/server/PersistentDataBlockService, computeAndWriteDigestLocked()Z > 1 @0 exception:2,
4 = invokevirtual < Application, Lcom/android/server/PersistentDataBlockService, computeDigestLocked([B)[B > 1,2 @1 exception:3,
conditional branch(eq, to iindex=-1) 4,2,
6 = invokevirtual < Application, Lcom/android/server/PersistentDataBlockService, getBlockOutputChannel()Ljava/nio/channels/FileChannel; > 1 @8 exception:5,
18 = invokestatic < Application, Ljava/nio/ByteBuffer, allocate(I)Ljava/nio/ByteBuffer; > 16 @14 exception:17,
20 = invokevirtual < Application, Ljava/nio/ByteBuffer, put([B)Ljava/nio/ByteBuffer; > 18,4 @18 exception:19,
22 = invokevirtual < Application, Ljava/nio/ByteBuffer, flip()Ljava/nio/Buffer; > 18 @21 exception:21,
24 = invokevirtual < Application, Ljava/nio/channels/FileChannel, write(Ljava/nio/ByteBuffer;)I > 6,18 @24 exception:23,
invokevirtual < Application, Ljava/nio/channels/FileChannel, force(Z)V > 6,25 @28 exception:26,
return 25,
return 3,
conditional branch(eq, to iindex=-1) 66,13,
monitorexit 48,
return 14,","depth : 0
-----
depth : 1
-----
depth : 2
-----
depth : 1
-----
depth : 2
-----
depth : 1
-----
depth : 2
-----
depth : 1
-----
depth : 2
-----
","public int write(byte[] p1){
	int v1 = Binder.getCallingUid();
	if (v1 != this.mAllowedUid) {
		long v6 = PersistentDataBlockService.getBlockDeviceSize();
		if (((((((v6 - 8) - 32) - 10000) - 1000) - 1) < 102400) > 0) {
			long v5 = (((((v6 - 8) - 32) - 10000) - 1000) - 1);
			long v4 = v5;
			if ((p1.length < v4) <= 0) {
				RandomAccessFile v9 = new RandomAccessFile(this.mDataBlockFile,""rw"");
				FileChannel v11 = v9.getChannel();
				FileChannel v8 = v11;
				FileChannel v7 = v8;
				ByteBuffer v12 = ByteBuffer.allocate(((p1.length + 8) + 32));
				[B v13 = new [B(32);
				ByteBuffer v14 = v12.put(v13);
				ByteBuffer v15 = v12.putInt(428873843);
				ByteBuffer v16 = v12.putInt(p1.length);
				ByteBuffer v17 = v12.put(p1);
				Buffer v18 = v12.flip();
				Object v19 = PersistentDataBlockService.-$$Nest$fgetmLock(this.this$0);
				boolean v20 = PersistentDataBlockService.-$$Nest$fgetmIsWritable(this.this$0);
				if (v20 != 0) {
					int v21 = v7.write(v12);
					v7.force(1);
					byte[] v25 = PersistentDataBlockService.computeDigestLocked(0);
					if (v25 == 0) {
						FileChannel v26 = PersistentDataBlockService.getBlockOutputChannel();
						ByteBuffer v27 = ByteBuffer.allocate(32);
						ByteBuffer v28 = v27.put(v25);
						Buffer v29 = v27.flip();
						int v30 = v26.write(v27);
						v26.force(1);
						boolean v24 = 1;
						boolean v23 = v24;
						if (v23 == 0) {
							return -1;
						}
					}
				}
			}
		}
	}
}
","NONE"
"Lcom/android/server/PersistentDataBlockService$1","write([B)I","2","3 = getfield < Application, Lcom/android/server/PersistentDataBlockService$1, this$0, <Application,Lcom/android/server/PersistentDataBlockService> > 1,
5 = invokestatic < Application, Landroid/os/Binder, getCallingUid()I > @2 exception:4,
invokestatic < Application, Lcom/android/server/PersistentDataBlockService, -$$Nest$menforceUid(Lcom/android/server/PersistentDataBlockService;I)V > 3,5 @6 exception:6,
invokevirtual < Application, Lcom/android/server/PersistentDataBlockService, enforceUid(I)V > 1,2 @0 exception:3,
3 = getfield < Application, Lcom/android/server/PersistentDataBlockService, mAllowedUid, <Primordial,I> > 1,
conditional branch(ne, to iindex=-1) 2,3,
return,
return,
7 = getfield < Application, Lcom/android/server/PersistentDataBlockService$1, this$0, <Application,Lcom/android/server/PersistentDataBlockService> > 1,
9 = invokestatic < Application, Lcom/android/server/PersistentDataBlockService, -$$Nest$mdoGetMaximumDataBlockSize(Lcom/android/server/PersistentDataBlockService;)J > 7 @11 exception:8,
3 = invokevirtual < Application, Lcom/android/server/PersistentDataBlockService, doGetMaximumDataBlockSize()J > 1 @0 exception:2,
3 = invokevirtual < Application, Lcom/android/server/PersistentDataBlockService, getBlockDeviceSize()J > 1 @0 exception:2,
5 = binaryop(sub) 3 , 4,
7 = binaryop(sub) 5 , 6,
9 = binaryop(sub) 7 , 8,
11 = binaryop(sub) 9 , 10,
13 = binaryop(sub) 11 , 12,
15 = binaryop(lt) 13 , 14,
conditional branch(gt, to iindex=-1) 15,16,
goto (from iindex= 15 to iindex = 2),
17 = phi  13,14,
return 17,
return 3,
10 = arraylength 2,
11 = conversion(J) 10,
12 = binaryop(lt) 11 , 9,
conditional branch(le, to iindex=-1) 12,13,
15 = getfield < Application, Lcom/android/server/PersistentDataBlockService$1, this$0, <Application,Lcom/android/server/PersistentDataBlockService> > 1,
17 = invokestatic < Application, Lcom/android/server/PersistentDataBlockService, -$$Nest$mgetBlockOutputChannel(Lcom/android/server/PersistentDataBlockService;)Ljava/nio/channels/FileChannel; > 15 @27 exception:16,
3 = invokevirtual < Application, Lcom/android/server/PersistentDataBlockService, getBlockOutputChannel()Ljava/nio/channels/FileChannel; > 1 @0 exception:2,
2 = new <Application,Ljava/io/RandomAccessFile>@0,
3 = getfield < Application, Lcom/android/server/PersistentDataBlockService, mDataBlockFile, <Application,Ljava/lang/String> > 1,
invokespecial < Application, Ljava/io/RandomAccessFile, <init>(Ljava/lang/String;Ljava/lang/String;)V > 2,3,4 @7 exception:5,
7 = invokevirtual < Application, Ljava/io/RandomAccessFile, getChannel()Ljava/nio/channels/FileChannel; > 2 @10 exception:6,
return 7,
return 3,
26 = arraylength 2,
28 = binaryop(add) 26 , 27,
30 = binaryop(add) 28 , 29,
32 = invokestatic < Application, Ljava/nio/ByteBuffer, allocate(I)Ljava/nio/ByteBuffer; > 30 @37 exception:31,
33 = new <Primordial,[B>@4129 ,
35 = invokevirtual < Application, Ljava/nio/ByteBuffer, put([B)Ljava/nio/ByteBuffer; > 32,33 @43 exception:34,
38 = invokevirtual < Application, Ljava/nio/ByteBuffer, putInt(I)Ljava/nio/ByteBuffer; > 32,36 @49 exception:37,
39 = arraylength 2,
41 = invokevirtual < Application, Ljava/nio/ByteBuffer, putInt(I)Ljava/nio/ByteBuffer; > 32,39 @53 exception:40,
43 = invokevirtual < Application, Ljava/nio/ByteBuffer, put([B)Ljava/nio/ByteBuffer; > 32,2 @56 exception:42,
45 = invokevirtual < Application, Ljava/nio/ByteBuffer, flip()Ljava/nio/Buffer; > 32 @59 exception:44,
46 = getfield < Application, Lcom/android/server/PersistentDataBlockService$1, this$0, <Application,Lcom/android/server/PersistentDataBlockService> > 1,
48 = invokestatic < Application, Lcom/android/server/PersistentDataBlockService, -$$Nest$fgetmLock(Lcom/android/server/PersistentDataBlockService;)Ljava/lang/Object; > 46 @64 exception:47,
monitorenter 48,
49 = getfield < Application, Lcom/android/server/PersistentDataBlockService$1, this$0, <Application,Lcom/android/server/PersistentDataBlockService> > 1,
51 = invokestatic < Application, Lcom/android/server/PersistentDataBlockService, -$$Nest$fgetmIsWritable(Lcom/android/server/PersistentDataBlockService;)Z > 49 @71 exception:50,
conditional branch(ne, to iindex=-1) 51,13,
53 = invokevirtual < Application, Ljava/nio/channels/FileChannel, write(Ljava/nio/ByteBuffer;)I > 17,32 @79 exception:52,
invokevirtual < Application, Ljava/nio/channels/FileChannel, force(Z)V > 17,54 @83 exception:55,
64 = getfield < Application, Lcom/android/server/PersistentDataBlockService$1, this$0, <Application,Lcom/android/server/PersistentDataBlockService> > 1,
66 = invokestatic < Application, Lcom/android/server/PersistentDataBlockService, -$$Nest$mcomputeAndWriteDigestLocked(Lcom/android/server/PersistentDataBlockService;)Z > 64 @88 exception:65,
3 = invokevirtual < Application, Lcom/android/server/PersistentDataBlockService, computeAndWriteDigestLocked()Z > 1 @0 exception:2,
4 = invokevirtual < Application, Lcom/android/server/PersistentDataBlockService, computeDigestLocked([B)[B > 1,2 @1 exception:3,
conditional branch(eq, to iindex=-1) 4,2,
return 2,
return 3,
conditional branch(eq, to iindex=-1) 66,13,
67 = arraylength 2,
monitorexit 48,
return 67,","depth : 0
-----
depth : 1
-----
depth : 2
-----
depth : 1
-----
depth : 2
-----
depth : 1
-----
depth : 2
-----
depth : 1
-----
depth : 2
-----
","public int write(byte[] p1){
	int v1 = Binder.getCallingUid();
	if (v1 != this.mAllowedUid) {
		long v6 = PersistentDataBlockService.getBlockDeviceSize();
		if (((((((v6 - 8) - 32) - 10000) - 1000) - 1) < 102400) > 0) {
			long v5 = (((((v6 - 8) - 32) - 10000) - 1000) - 1);
			long v4 = v5;
			if ((p1.length < v4) <= 0) {
				RandomAccessFile v9 = new RandomAccessFile(this.mDataBlockFile,""rw"");
				FileChannel v11 = v9.getChannel();
				FileChannel v8 = v11;
				FileChannel v7 = v8;
				ByteBuffer v12 = ByteBuffer.allocate(((p1.length + 8) + 32));
				[B v13 = new [B(32);
				ByteBuffer v14 = v12.put(v13);
				ByteBuffer v15 = v12.putInt(428873843);
				ByteBuffer v16 = v12.putInt(p1.length);
				ByteBuffer v17 = v12.put(p1);
				Buffer v18 = v12.flip();
				Object v19 = PersistentDataBlockService.-$$Nest$fgetmLock(this.this$0);
				boolean v20 = PersistentDataBlockService.-$$Nest$fgetmIsWritable(this.this$0);
				if (v20 != 0) {
					int v21 = v7.write(v12);
					v7.force(1);
					byte[] v25 = PersistentDataBlockService.computeDigestLocked(0);
					if (v25 == 0) {
						boolean v24 = 0;
						boolean v23 = v24;
						if (v23 == 0) {
							return p1.length;
						}
					}
				}
			}
		}
	}
}
","NONE"

"Lcom/android/server/PersistentDataBlockService$1","getDataBlockSize()I","0","invokevirtual < Application, Lcom/android/server/PersistentDataBlockService$1, enforcePersistentDataBlockAccess()V > 1 @0 exception:2,
4 = new <Application,Ljava/io/DataInputStream>@4,
5 = new <Application,Ljava/io/FileInputStream>@6,
6 = new <Application,Ljava/io/File>@8,
7 = getfield < Application, Lcom/android/server/PersistentDataBlockService$1, this$0, <Application,Lcom/android/server/PersistentDataBlockService> > 1,
9 = invokestatic < Application, Lcom/android/server/PersistentDataBlockService, -$$Nest$fgetmDataBlockFile(Lcom/android/server/PersistentDataBlockService;)Ljava/lang/String; > 7 @12 exception:8,
invokespecial < Application, Ljava/io/File, <init>(Ljava/lang/String;)V > 6,9 @16 exception:10,
invokespecial < Application, Ljava/io/FileInputStream, <init>(Ljava/io/File;)V > 5,6 @19 exception:11,
invokespecial < Application, Ljava/io/DataInputStream, <init>(Ljava/io/InputStream;)V > 4,5 @22 exception:12,
20 = getfield < Application, Lcom/android/server/PersistentDataBlockService$1, this$0, <Application,Lcom/android/server/PersistentDataBlockService> > 1,
22 = invokestatic < Application, Lcom/android/server/PersistentDataBlockService, -$$Nest$fgetmLock(Lcom/android/server/PersistentDataBlockService;)Ljava/lang/Object; > 20 @27 exception:21,
monitorenter 22,
23 = getfield < Application, Lcom/android/server/PersistentDataBlockService$1, this$0, <Application,Lcom/android/server/PersistentDataBlockService> > 1,
25 = invokestatic < Application, Lcom/android/server/PersistentDataBlockService, -$$Nest$mgetTotalDataSizeLocked(Lcom/android/server/PersistentDataBlockService;Ljava/io/DataInputStream;)I > 23,4 @34 exception:24,
monitorexit 22,
invokestatic < Application, Llibcore/io/IoUtils, closeQuietly(Ljava/lang/AutoCloseable;)V > 4 @39 exception:46,
return 25,","depth : 0
-----
","public int getDataBlockSize(){
	p0.enforcePersistentDataBlockAccess();
	DataInputStream v2 = new DataInputStream(v3);
	FileInputStream v3 = new FileInputStream(v4);
	File v4 = new File(v5);
	String v5 = PersistentDataBlockService.-$$Nest$fgetmDataBlockFile(this.this$0);
	Object v9 = PersistentDataBlockService.-$$Nest$fgetmLock(this.this$0);
	int v10 = PersistentDataBlockService.-$$Nest$mgetTotalDataSizeLocked(this.this$0, v2);
	IoUtils.closeQuietly(v2);
	return v10;
}
","SYS_OR_SIG"
"Lcom/android/server/PersistentDataBlockService$1","getDataBlockSize()I","1","invokevirtual < Application, Lcom/android/server/PersistentDataBlockService$1, enforcePersistentDataBlockAccess()V > 1 @0 exception:2,
2 = getfield < Application, Lcom/android/server/PersistentDataBlockService$1, this$0, <Application,Lcom/android/server/PersistentDataBlockService> > 1,
4 = invokestatic < Application, Lcom/android/server/PersistentDataBlockService, -$$Nest$fgetmContext(Lcom/android/server/PersistentDataBlockService;)Landroid/content/Context; > 2 @2 exception:3,
7 = invokevirtual < Application, Landroid/content/Context, checkCallingPermission(Ljava/lang/String;)I > 4,5 @8 exception:6,
conditional branch(eq, to iindex=-1) 7,8,
9 = getfield < Application, Lcom/android/server/PersistentDataBlockService$1, this$0, <Application,Lcom/android/server/PersistentDataBlockService> > 1,
11 = invokestatic < Application, Landroid/os/Binder, getCallingUid()I > @16 exception:10,
invokestatic < Application, Lcom/android/server/PersistentDataBlockService, -$$Nest$menforceUid(Lcom/android/server/PersistentDataBlockService;I)V > 9,11 @20 exception:12,
return,
4 = new <Application,Ljava/io/DataInputStream>@4,
5 = new <Application,Ljava/io/FileInputStream>@6,
6 = new <Application,Ljava/io/File>@8,
7 = getfield < Application, Lcom/android/server/PersistentDataBlockService$1, this$0, <Application,Lcom/android/server/PersistentDataBlockService> > 1,
9 = invokestatic < Application, Lcom/android/server/PersistentDataBlockService, -$$Nest$fgetmDataBlockFile(Lcom/android/server/PersistentDataBlockService;)Ljava/lang/String; > 7 @12 exception:8,
2 = getfield < Application, Lcom/android/server/PersistentDataBlockService, mDataBlockFile, <Application,Ljava/lang/String> > 1,
return 2,
invokespecial < Application, Ljava/io/File, <init>(Ljava/lang/String;)V > 6,9 @16 exception:10,
invokespecial < Application, Ljava/io/FileInputStream, <init>(Ljava/io/File;)V > 5,6 @19 exception:11,
invokespecial < Application, Ljava/io/DataInputStream, <init>(Ljava/io/InputStream;)V > 4,5 @22 exception:12,
20 = getfield < Application, Lcom/android/server/PersistentDataBlockService$1, this$0, <Application,Lcom/android/server/PersistentDataBlockService> > 1,
22 = invokestatic < Application, Lcom/android/server/PersistentDataBlockService, -$$Nest$fgetmLock(Lcom/android/server/PersistentDataBlockService;)Ljava/lang/Object; > 20 @27 exception:21,
2 = getfield < Application, Lcom/android/server/PersistentDataBlockService, mLock, <Application,Ljava/lang/Object> > 1,
return 2,
monitorenter 22,
23 = getfield < Application, Lcom/android/server/PersistentDataBlockService$1, this$0, <Application,Lcom/android/server/PersistentDataBlockService> > 1,
25 = invokestatic < Application, Lcom/android/server/PersistentDataBlockService, -$$Nest$mgetTotalDataSizeLocked(Lcom/android/server/PersistentDataBlockService;Ljava/io/DataInputStream;)I > 23,4 @34 exception:24,
4 = invokevirtual < Application, Lcom/android/server/PersistentDataBlockService, getTotalDataSizeLocked(Ljava/io/DataInputStream;)I > 1,2 @0 exception:3,
return 4,
monitorexit 22,
invokestatic < Application, Llibcore/io/IoUtils, closeQuietly(Ljava/lang/AutoCloseable;)V > 4 @39 exception:46,
return 25,","depth : 0
-----
depth : 1
-----
depth : 1
-----
depth : 1
-----
depth : 1
-----
","public int getDataBlockSize(){
	if (v3 == 0) {
		int v4 = Binder.getCallingUid();
		PersistentDataBlockService.-$$Nest$menforceUid(this.this$0, v4);
		DataInputStream v6 = new DataInputStream(v7);
		FileInputStream v7 = new FileInputStream(v8);
		File v8 = new File(v9);
		String v9 = this.mDataBlockFile;
		Object v13 = this.mLock;
		int v15 = this.this$0.getTotalDataSizeLocked(v6);
		int v14 = v15;
		IoUtils.closeQuietly(v6);
		return v14;
	}
}
","SYS_OR_SIG"
"Lcom/android/server/PersistentDataBlockService$1","getDataBlockSize()I","2","invokevirtual < Application, Lcom/android/server/PersistentDataBlockService$1, enforcePersistentDataBlockAccess()V > 1 @0 exception:2,
2 = getfield < Application, Lcom/android/server/PersistentDataBlockService$1, this$0, <Application,Lcom/android/server/PersistentDataBlockService> > 1,
4 = invokestatic < Application, Lcom/android/server/PersistentDataBlockService, -$$Nest$fgetmContext(Lcom/android/server/PersistentDataBlockService;)Landroid/content/Context; > 2 @2 exception:3,
7 = invokevirtual < Application, Landroid/content/Context, checkCallingPermission(Ljava/lang/String;)I > 4,5 @8 exception:6,
conditional branch(eq, to iindex=-1) 7,8,
9 = getfield < Application, Lcom/android/server/PersistentDataBlockService$1, this$0, <Application,Lcom/android/server/PersistentDataBlockService> > 1,
11 = invokestatic < Application, Landroid/os/Binder, getCallingUid()I > @16 exception:10,
invokestatic < Application, Lcom/android/server/PersistentDataBlockService, -$$Nest$menforceUid(Lcom/android/server/PersistentDataBlockService;I)V > 9,11 @20 exception:12,
invokevirtual < Application, Lcom/android/server/PersistentDataBlockService, enforceUid(I)V > 1,2 @0 exception:3,
return,
return,
4 = new <Application,Ljava/io/DataInputStream>@4,
5 = new <Application,Ljava/io/FileInputStream>@6,
6 = new <Application,Ljava/io/File>@8,
7 = getfield < Application, Lcom/android/server/PersistentDataBlockService$1, this$0, <Application,Lcom/android/server/PersistentDataBlockService> > 1,
9 = invokestatic < Application, Lcom/android/server/PersistentDataBlockService, -$$Nest$fgetmDataBlockFile(Lcom/android/server/PersistentDataBlockService;)Ljava/lang/String; > 7 @12 exception:8,
invokespecial < Application, Ljava/io/File, <init>(Ljava/lang/String;)V > 6,9 @16 exception:10,
invokespecial < Application, Ljava/io/FileInputStream, <init>(Ljava/io/File;)V > 5,6 @19 exception:11,
invokespecial < Application, Ljava/io/DataInputStream, <init>(Ljava/io/InputStream;)V > 4,5 @22 exception:12,
20 = getfield < Application, Lcom/android/server/PersistentDataBlockService$1, this$0, <Application,Lcom/android/server/PersistentDataBlockService> > 1,
22 = invokestatic < Application, Lcom/android/server/PersistentDataBlockService, -$$Nest$fgetmLock(Lcom/android/server/PersistentDataBlockService;)Ljava/lang/Object; > 20 @27 exception:21,
monitorenter 22,
23 = getfield < Application, Lcom/android/server/PersistentDataBlockService$1, this$0, <Application,Lcom/android/server/PersistentDataBlockService> > 1,
25 = invokestatic < Application, Lcom/android/server/PersistentDataBlockService, -$$Nest$mgetTotalDataSizeLocked(Lcom/android/server/PersistentDataBlockService;Ljava/io/DataInputStream;)I > 23,4 @34 exception:24,
monitorexit 22,
invokestatic < Application, Llibcore/io/IoUtils, closeQuietly(Ljava/lang/AutoCloseable;)V > 4 @39 exception:46,
return 25,","depth : 0
-----
depth : 1
-----
depth : 2
-----
","public int getDataBlockSize(){
	if (v3 == 0) {
		int v4 = Binder.getCallingUid();
		this.this$0.enforceUid(v4);
		DataInputStream v7 = new DataInputStream(v8);
		FileInputStream v8 = new FileInputStream(v9);
		File v9 = new File(v10);
		String v10 = PersistentDataBlockService.-$$Nest$fgetmDataBlockFile(this.this$0);
		Object v14 = PersistentDataBlockService.-$$Nest$fgetmLock(this.this$0);
		int v15 = PersistentDataBlockService.-$$Nest$mgetTotalDataSizeLocked(this.this$0, v7);
		IoUtils.closeQuietly(v7);
		return v15;
	}
}
","SYS_OR_SIG"

"Lcom/android/server/PersistentDataBlockService$1","getOemUnlockEnabled()Z","0","2 = getfield < Application, Lcom/android/server/PersistentDataBlockService$1, this$0, <Application,Lcom/android/server/PersistentDataBlockService> > 1,
invokestatic < Application, Lcom/android/server/PersistentDataBlockService, -$$Nest$menforceOemUnlockReadPermission(Lcom/android/server/PersistentDataBlockService;)V > 2 @2 exception:3,
4 = getfield < Application, Lcom/android/server/PersistentDataBlockService$1, this$0, <Application,Lcom/android/server/PersistentDataBlockService> > 1,
6 = invokestatic < Application, Lcom/android/server/PersistentDataBlockService, -$$Nest$mdoGetOemUnlockEnabled(Lcom/android/server/PersistentDataBlockService;)Z > 4 @7 exception:5,
return 6,","depth : 0
-----
","public boolean getOemUnlockEnabled(){
	boolean v2 = PersistentDataBlockService.-$$Nest$mdoGetOemUnlockEnabled(this.this$0);
	return v2;
}
","SYS_OR_SIG"
"Lcom/android/server/PersistentDataBlockService$1","getOemUnlockEnabled()Z","1","2 = getfield < Application, Lcom/android/server/PersistentDataBlockService$1, this$0, <Application,Lcom/android/server/PersistentDataBlockService> > 1,
invokestatic < Application, Lcom/android/server/PersistentDataBlockService, -$$Nest$menforceOemUnlockReadPermission(Lcom/android/server/PersistentDataBlockService;)V > 2 @2 exception:3,
4 = getfield < Application, Lcom/android/server/PersistentDataBlockService$1, this$0, <Application,Lcom/android/server/PersistentDataBlockService> > 1,
6 = invokestatic < Application, Lcom/android/server/PersistentDataBlockService, -$$Nest$mdoGetOemUnlockEnabled(Lcom/android/server/PersistentDataBlockService;)Z > 4 @7 exception:5,
3 = invokevirtual < Application, Lcom/android/server/PersistentDataBlockService, doGetOemUnlockEnabled()Z > 1 @0 exception:2,
return 3,
return 6,","depth : 0
-----
depth : 1
-----
","public boolean getOemUnlockEnabled(){
	boolean v3 = this.this$0.doGetOemUnlockEnabled();
	boolean v2 = v3;
	return v2;
}
","SYS_OR_SIG"
"Lcom/android/server/PersistentDataBlockService$1","getOemUnlockEnabled()Z","2","2 = getfield < Application, Lcom/android/server/PersistentDataBlockService$1, this$0, <Application,Lcom/android/server/PersistentDataBlockService> > 1,
invokestatic < Application, Lcom/android/server/PersistentDataBlockService, -$$Nest$menforceOemUnlockReadPermission(Lcom/android/server/PersistentDataBlockService;)V > 2 @2 exception:3,
4 = getfield < Application, Lcom/android/server/PersistentDataBlockService$1, this$0, <Application,Lcom/android/server/PersistentDataBlockService> > 1,
6 = invokestatic < Application, Lcom/android/server/PersistentDataBlockService, -$$Nest$mdoGetOemUnlockEnabled(Lcom/android/server/PersistentDataBlockService;)Z > 4 @7 exception:5,
3 = invokevirtual < Application, Lcom/android/server/PersistentDataBlockService, doGetOemUnlockEnabled()Z > 1 @0 exception:2,
3 = new <Application,Ljava/io/DataInputStream>@1,
4 = new <Application,Ljava/io/FileInputStream>@3,
5 = new <Application,Ljava/io/File>@5,
6 = getfield < Application, Lcom/android/server/PersistentDataBlockService, mDataBlockFile, <Application,Ljava/lang/String> > 1,
invokespecial < Application, Ljava/io/File, <init>(Ljava/lang/String;)V > 5,6 @9 exception:7,
invokespecial < Application, Ljava/io/FileInputStream, <init>(Ljava/io/File;)V > 4,5 @12 exception:8,
invokespecial < Application, Ljava/io/DataInputStream, <init>(Ljava/io/InputStream;)V > 3,4 @15 exception:9,
15 = getfield < Application, Lcom/android/server/PersistentDataBlockService, mLock, <Application,Ljava/lang/Object> > 1,
monitorenter 15,
17 = invokevirtual < Application, Lcom/android/server/PersistentDataBlockService, getBlockDeviceSize()J > 1 @21 exception:16,
19 = binaryop(sub) 17 , 18,
21 = invokevirtual < Application, Ljava/io/DataInputStream, skip(J)J > 3,19 @28 exception:20,
23 = invokevirtual < Application, Ljava/io/DataInputStream, readByte()B > 3 @31 exception:22,
conditional branch(eq, to iindex=-1) 23,2,
goto (from iindex= 19 to iindex = 2),
25 = phi  24,2,
monitorexit 15,
invokestatic < Application, Llibcore/io/IoUtils, closeQuietly(Ljava/lang/AutoCloseable;)V > 3 @41 exception:50,
return 25,
return 3,
return 6,","depth : 0
-----
depth : 1
-----
depth : 2
-----
","public boolean getOemUnlockEnabled(){
	DataInputStream v4 = new DataInputStream(v5);
	FileInputStream v5 = new FileInputStream(v6);
	File v6 = new File(this.mDataBlockFile);
	long v10 = PersistentDataBlockService.getBlockDeviceSize();
	long v11 = v4.skip((v10 - 1));
	byte v12 = v4.readByte();
	if (v12 == 0) {
		IoUtils.closeQuietly(v4);
		boolean v3 = 1;
		boolean v2 = v3;
		return v2;
	}
}
","SYS_OR_SIG"

"Lcom/android/server/PersistentDataBlockService$1","getPersistentDataPackageName()Ljava/lang/String;","0","invokevirtual < Application, Lcom/android/server/PersistentDataBlockService$1, enforcePersistentDataBlockAccess()V > 1 @0 exception:2,
3 = getfield < Application, Lcom/android/server/PersistentDataBlockService$1, this$0, <Application,Lcom/android/server/PersistentDataBlockService> > 1,
5 = invokestatic < Application, Lcom/android/server/PersistentDataBlockService, -$$Nest$fgetmContext(Lcom/android/server/PersistentDataBlockService;)Landroid/content/Context; > 3 @5 exception:4,
8 = invokevirtual < Application, Landroid/content/Context, getString(I)Ljava/lang/String; > 5,6 @12 exception:7,
return 8,","depth : 0
-----
","public String getPersistentDataPackageName(){
	p0.enforcePersistentDataBlockAccess();
	Context v2 = PersistentDataBlockService.-$$Nest$fgetmContext(this.this$0);
	String v3 = v2.getString(17040017);
	return v3;
}
","SYS_OR_SIG"
"Lcom/android/server/PersistentDataBlockService$1","getPersistentDataPackageName()Ljava/lang/String;","1","invokevirtual < Application, Lcom/android/server/PersistentDataBlockService$1, enforcePersistentDataBlockAccess()V > 1 @0 exception:2,
2 = getfield < Application, Lcom/android/server/PersistentDataBlockService$1, this$0, <Application,Lcom/android/server/PersistentDataBlockService> > 1,
4 = invokestatic < Application, Lcom/android/server/PersistentDataBlockService, -$$Nest$fgetmContext(Lcom/android/server/PersistentDataBlockService;)Landroid/content/Context; > 2 @2 exception:3,
7 = invokevirtual < Application, Landroid/content/Context, checkCallingPermission(Ljava/lang/String;)I > 4,5 @8 exception:6,
conditional branch(eq, to iindex=-1) 7,8,
9 = getfield < Application, Lcom/android/server/PersistentDataBlockService$1, this$0, <Application,Lcom/android/server/PersistentDataBlockService> > 1,
11 = invokestatic < Application, Landroid/os/Binder, getCallingUid()I > @16 exception:10,
invokestatic < Application, Lcom/android/server/PersistentDataBlockService, -$$Nest$menforceUid(Lcom/android/server/PersistentDataBlockService;I)V > 9,11 @20 exception:12,
return,
3 = getfield < Application, Lcom/android/server/PersistentDataBlockService$1, this$0, <Application,Lcom/android/server/PersistentDataBlockService> > 1,
5 = invokestatic < Application, Lcom/android/server/PersistentDataBlockService, -$$Nest$fgetmContext(Lcom/android/server/PersistentDataBlockService;)Landroid/content/Context; > 3 @5 exception:4,
2 = getfield < Application, Lcom/android/server/PersistentDataBlockService, mContext, <Application,Landroid/content/Context> > 1,
return 2,
8 = invokevirtual < Application, Landroid/content/Context, getString(I)Ljava/lang/String; > 5,6 @12 exception:7,
return 8,","depth : 0
-----
depth : 1
-----
depth : 1
-----
","public String getPersistentDataPackageName(){
	if (v3 == 0) {
		int v4 = Binder.getCallingUid();
		PersistentDataBlockService.-$$Nest$menforceUid(this.this$0, v4);
		Context v6 = this.mContext;
		String v7 = v6.getString(17040017);
		return v7;
	}
}
","SYS_OR_SIG"
"Lcom/android/server/PersistentDataBlockService$1","getPersistentDataPackageName()Ljava/lang/String;","2","invokevirtual < Application, Lcom/android/server/PersistentDataBlockService$1, enforcePersistentDataBlockAccess()V > 1 @0 exception:2,
2 = getfield < Application, Lcom/android/server/PersistentDataBlockService$1, this$0, <Application,Lcom/android/server/PersistentDataBlockService> > 1,
4 = invokestatic < Application, Lcom/android/server/PersistentDataBlockService, -$$Nest$fgetmContext(Lcom/android/server/PersistentDataBlockService;)Landroid/content/Context; > 2 @2 exception:3,
7 = invokevirtual < Application, Landroid/content/Context, checkCallingPermission(Ljava/lang/String;)I > 4,5 @8 exception:6,
conditional branch(eq, to iindex=-1) 7,8,
9 = getfield < Application, Lcom/android/server/PersistentDataBlockService$1, this$0, <Application,Lcom/android/server/PersistentDataBlockService> > 1,
11 = invokestatic < Application, Landroid/os/Binder, getCallingUid()I > @16 exception:10,
invokestatic < Application, Lcom/android/server/PersistentDataBlockService, -$$Nest$menforceUid(Lcom/android/server/PersistentDataBlockService;I)V > 9,11 @20 exception:12,
invokevirtual < Application, Lcom/android/server/PersistentDataBlockService, enforceUid(I)V > 1,2 @0 exception:3,
return,
return,
3 = getfield < Application, Lcom/android/server/PersistentDataBlockService$1, this$0, <Application,Lcom/android/server/PersistentDataBlockService> > 1,
5 = invokestatic < Application, Lcom/android/server/PersistentDataBlockService, -$$Nest$fgetmContext(Lcom/android/server/PersistentDataBlockService;)Landroid/content/Context; > 3 @5 exception:4,
8 = invokevirtual < Application, Landroid/content/Context, getString(I)Ljava/lang/String; > 5,6 @12 exception:7,
return 8,","depth : 0
-----
depth : 1
-----
depth : 2
-----
","public String getPersistentDataPackageName(){
	if (v3 == 0) {
		int v4 = Binder.getCallingUid();
		this.this$0.enforceUid(v4);
		Context v7 = PersistentDataBlockService.-$$Nest$fgetmContext(this.this$0);
		String v8 = v7.getString(17040017);
		return v8;
	}
}
","SYS_OR_SIG"

"Lcom/android/server/PersistentDataBlockService$1","wipe()V","0","2 = getfield < Application, Lcom/android/server/PersistentDataBlockService$1, this$0, <Application,Lcom/android/server/PersistentDataBlockService> > 1,
invokestatic < Application, Lcom/android/server/PersistentDataBlockService, -$$Nest$menforceOemUnlockWritePermission(Lcom/android/server/PersistentDataBlockService;)V > 2 @2 exception:3,
4 = getfield < Application, Lcom/android/server/PersistentDataBlockService$1, this$0, <Application,Lcom/android/server/PersistentDataBlockService> > 1,
6 = invokestatic < Application, Lcom/android/server/PersistentDataBlockService, -$$Nest$fgetmLock(Lcom/android/server/PersistentDataBlockService;)Ljava/lang/Object; > 4 @7 exception:5,
monitorenter 6,
7 = getfield < Application, Lcom/android/server/PersistentDataBlockService$1, this$0, <Application,Lcom/android/server/PersistentDataBlockService> > 1,
9 = invokestatic < Application, Lcom/android/server/PersistentDataBlockService, -$$Nest$fgetmDataBlockFile(Lcom/android/server/PersistentDataBlockService;)Ljava/lang/String; > 7 @14 exception:8,
11 = invokestatic < Application, Lcom/android/server/PersistentDataBlockService, -$$Nest$mnativeWipe(Lcom/android/server/PersistentDataBlockService;Ljava/lang/String;)I > 7,9 @18 exception:10,
conditional branch(ge, to iindex=-1) 11,12,
13 = getfield < Application, Lcom/android/server/PersistentDataBlockService$1, this$0, <Application,Lcom/android/server/PersistentDataBlockService> > 1,
invokestatic < Application, Lcom/android/server/PersistentDataBlockService, -$$Nest$fputmIsWritable(Lcom/android/server/PersistentDataBlockService;Z)V > 13,12 @37 exception:14,
16 = invokestatic < Application, Lcom/android/server/PersistentDataBlockService, -$$Nest$sfgetTAG()Ljava/lang/String; > @40 exception:15,
19 = invokestatic < Application, Landroid/util/Slog, i(Ljava/lang/String;Ljava/lang/String;)I > 16,17 @47 exception:18,
monitorexit 6,
return,","depth : 0
-----
","public void wipe(){
	Object v2 = PersistentDataBlockService.-$$Nest$fgetmLock(this.this$0);
	String v3 = PersistentDataBlockService.-$$Nest$fgetmDataBlockFile(this.this$0);
	int v4 = PersistentDataBlockService.-$$Nest$mnativeWipe(this.this$0, v3);
	if (v4 >= 0) {
		PersistentDataBlockService.-$$Nest$fputmIsWritable(this.this$0, 0);
		return;
	}
}
","SYS_OR_SIG"
"Lcom/android/server/PersistentDataBlockService$1","wipe()V","1","2 = getfield < Application, Lcom/android/server/PersistentDataBlockService$1, this$0, <Application,Lcom/android/server/PersistentDataBlockService> > 1,
invokestatic < Application, Lcom/android/server/PersistentDataBlockService, -$$Nest$menforceOemUnlockWritePermission(Lcom/android/server/PersistentDataBlockService;)V > 2 @2 exception:3,
4 = getfield < Application, Lcom/android/server/PersistentDataBlockService$1, this$0, <Application,Lcom/android/server/PersistentDataBlockService> > 1,
6 = invokestatic < Application, Lcom/android/server/PersistentDataBlockService, -$$Nest$fgetmLock(Lcom/android/server/PersistentDataBlockService;)Ljava/lang/Object; > 4 @7 exception:5,
2 = getfield < Application, Lcom/android/server/PersistentDataBlockService, mLock, <Application,Ljava/lang/Object> > 1,
return 2,
monitorenter 6,
7 = getfield < Application, Lcom/android/server/PersistentDataBlockService$1, this$0, <Application,Lcom/android/server/PersistentDataBlockService> > 1,
9 = invokestatic < Application, Lcom/android/server/PersistentDataBlockService, -$$Nest$fgetmDataBlockFile(Lcom/android/server/PersistentDataBlockService;)Ljava/lang/String; > 7 @14 exception:8,
2 = getfield < Application, Lcom/android/server/PersistentDataBlockService, mDataBlockFile, <Application,Ljava/lang/String> > 1,
return 2,
11 = invokestatic < Application, Lcom/android/server/PersistentDataBlockService, -$$Nest$mnativeWipe(Lcom/android/server/PersistentDataBlockService;Ljava/lang/String;)I > 7,9 @18 exception:10,
4 = invokespecial < Application, Lcom/android/server/PersistentDataBlockService, nativeWipe(Ljava/lang/String;)I > 1,2 @0 exception:3,
return 4,
conditional branch(ge, to iindex=-1) 11,12,
13 = getfield < Application, Lcom/android/server/PersistentDataBlockService$1, this$0, <Application,Lcom/android/server/PersistentDataBlockService> > 1,
invokestatic < Application, Lcom/android/server/PersistentDataBlockService, -$$Nest$fputmIsWritable(Lcom/android/server/PersistentDataBlockService;Z)V > 13,12 @37 exception:14,
putfield 1.< Application, Lcom/android/server/PersistentDataBlockService, mIsWritable, <Primordial,Z> > = 2,
return,
16 = invokestatic < Application, Lcom/android/server/PersistentDataBlockService, -$$Nest$sfgetTAG()Ljava/lang/String; > @40 exception:15,
1 = getstatic < Application, Lcom/android/server/PersistentDataBlockService, TAG, <Application,Ljava/lang/String> >,
return 1,
19 = invokestatic < Application, Landroid/util/Slog, i(Ljava/lang/String;Ljava/lang/String;)I > 16,17 @47 exception:18,
monitorexit 6,
return,","depth : 0
-----
depth : 1
-----
depth : 1
-----
depth : 1
-----
depth : 1
-----
depth : 1
-----
","public void wipe(){
	Object v2 = this.mLock;
	String v3 = this.mDataBlockFile;
	int v5 = this.this$0.nativeWipe(v3);
	int v4 = v5;
	if (v4 >= 0) {
		this.mIsWritable = 0;
		String v7 = this.TAG;
		return;
	}
}
","SYS_OR_SIG"

"Lcom/android/server/PersistentDataBlockService$1","hasFrpCredentialHandle()Z","0","invokevirtual < Application, Lcom/android/server/PersistentDataBlockService$1, enforcePersistentDataBlockAccess()V > 1 @0 exception:2,
3 = getfield < Application, Lcom/android/server/PersistentDataBlockService$1, this$0, <Application,Lcom/android/server/PersistentDataBlockService> > 1,
5 = invokestatic < Application, Lcom/android/server/PersistentDataBlockService, -$$Nest$fgetmInternalService(Lcom/android/server/PersistentDataBlockService;)Lcom/android/server/PersistentDataBlockManagerInternal; > 3 @5 exception:4,
7 = invokeinterface < Application, Lcom/android/server/PersistentDataBlockManagerInternal, getFrpCredentialHandle()[B > 5 @9 exception:6,
conditional branch(eq, to iindex=-1) 7,20,
goto (from iindex= 8 to iindex = 2),
22 = phi  21,20,
return 22,","depth : 0
-----
","public boolean hasFrpCredentialHandle(){
	p0.enforcePersistentDataBlockAccess();
	PersistentDataBlockManagerInternal v2 = PersistentDataBlockService.-$$Nest$fgetmInternalService(this.this$0);
	byte[] v3 = v2.getFrpCredentialHandle();
	if (v3 == 0) {
		return 1;
	}
}
","SYS_OR_SIG"
"Lcom/android/server/PersistentDataBlockService$1","hasFrpCredentialHandle()Z","1","invokevirtual < Application, Lcom/android/server/PersistentDataBlockService$1, enforcePersistentDataBlockAccess()V > 1 @0 exception:2,
2 = getfield < Application, Lcom/android/server/PersistentDataBlockService$1, this$0, <Application,Lcom/android/server/PersistentDataBlockService> > 1,
4 = invokestatic < Application, Lcom/android/server/PersistentDataBlockService, -$$Nest$fgetmContext(Lcom/android/server/PersistentDataBlockService;)Landroid/content/Context; > 2 @2 exception:3,
7 = invokevirtual < Application, Landroid/content/Context, checkCallingPermission(Ljava/lang/String;)I > 4,5 @8 exception:6,
conditional branch(eq, to iindex=-1) 7,8,
9 = getfield < Application, Lcom/android/server/PersistentDataBlockService$1, this$0, <Application,Lcom/android/server/PersistentDataBlockService> > 1,
11 = invokestatic < Application, Landroid/os/Binder, getCallingUid()I > @16 exception:10,
invokestatic < Application, Lcom/android/server/PersistentDataBlockService, -$$Nest$menforceUid(Lcom/android/server/PersistentDataBlockService;I)V > 9,11 @20 exception:12,
return,
3 = getfield < Application, Lcom/android/server/PersistentDataBlockService$1, this$0, <Application,Lcom/android/server/PersistentDataBlockService> > 1,
5 = invokestatic < Application, Lcom/android/server/PersistentDataBlockService, -$$Nest$fgetmInternalService(Lcom/android/server/PersistentDataBlockService;)Lcom/android/server/PersistentDataBlockManagerInternal; > 3 @5 exception:4,
2 = getfield < Application, Lcom/android/server/PersistentDataBlockService, mInternalService, <Application,Lcom/android/server/PersistentDataBlockManagerInternal> > 1,
return 2,
7 = invokeinterface < Application, Lcom/android/server/PersistentDataBlockManagerInternal, getFrpCredentialHandle()[B > 5 @9 exception:6,
conditional branch(eq, to iindex=-1) 7,20,
goto (from iindex= 8 to iindex = 2),
22 = phi  21,20,
return 22,","depth : 0
-----
depth : 1
-----
depth : 1
-----
","public boolean hasFrpCredentialHandle(){
	if (v3 == 0) {
		int v4 = Binder.getCallingUid();
		PersistentDataBlockService.-$$Nest$menforceUid(this.this$0, v4);
		PersistentDataBlockManagerInternal v6 = this.mInternalService;
		byte[] v7 = v6.getFrpCredentialHandle();
		if (v7 == 0) {
			return 1;
		}
	}
}
","SYS_OR_SIG"
"Lcom/android/server/PersistentDataBlockService$1","hasFrpCredentialHandle()Z","2","invokevirtual < Application, Lcom/android/server/PersistentDataBlockService$1, enforcePersistentDataBlockAccess()V > 1 @0 exception:2,
2 = getfield < Application, Lcom/android/server/PersistentDataBlockService$1, this$0, <Application,Lcom/android/server/PersistentDataBlockService> > 1,
4 = invokestatic < Application, Lcom/android/server/PersistentDataBlockService, -$$Nest$fgetmContext(Lcom/android/server/PersistentDataBlockService;)Landroid/content/Context; > 2 @2 exception:3,
7 = invokevirtual < Application, Landroid/content/Context, checkCallingPermission(Ljava/lang/String;)I > 4,5 @8 exception:6,
conditional branch(eq, to iindex=-1) 7,8,
9 = getfield < Application, Lcom/android/server/PersistentDataBlockService$1, this$0, <Application,Lcom/android/server/PersistentDataBlockService> > 1,
11 = invokestatic < Application, Landroid/os/Binder, getCallingUid()I > @16 exception:10,
invokestatic < Application, Lcom/android/server/PersistentDataBlockService, -$$Nest$menforceUid(Lcom/android/server/PersistentDataBlockService;I)V > 9,11 @20 exception:12,
invokevirtual < Application, Lcom/android/server/PersistentDataBlockService, enforceUid(I)V > 1,2 @0 exception:3,
return,
return,
3 = getfield < Application, Lcom/android/server/PersistentDataBlockService$1, this$0, <Application,Lcom/android/server/PersistentDataBlockService> > 1,
5 = invokestatic < Application, Lcom/android/server/PersistentDataBlockService, -$$Nest$fgetmInternalService(Lcom/android/server/PersistentDataBlockService;)Lcom/android/server/PersistentDataBlockManagerInternal; > 3 @5 exception:4,
7 = invokeinterface < Application, Lcom/android/server/PersistentDataBlockManagerInternal, getFrpCredentialHandle()[B > 5 @9 exception:6,
conditional branch(eq, to iindex=-1) 7,20,
goto (from iindex= 8 to iindex = 2),
22 = phi  21,20,
return 22,","depth : 0
-----
depth : 1
-----
depth : 2
-----
","public boolean hasFrpCredentialHandle(){
	if (v3 == 0) {
		int v4 = Binder.getCallingUid();
		this.this$0.enforceUid(v4);
		PersistentDataBlockManagerInternal v7 = PersistentDataBlockService.-$$Nest$fgetmInternalService(this.this$0);
		byte[] v8 = v7.getFrpCredentialHandle();
		if (v8 == 0) {
			return 1;
		}
	}
}
","SYS_OR_SIG"

"Lcom/android/server/PersistentDataBlockService$1","read()[B","0","2 = getfield < Application, Lcom/android/server/PersistentDataBlockService$1, this$0, <Application,Lcom/android/server/PersistentDataBlockService> > 1,
4 = invokestatic < Application, Landroid/os/Binder, getCallingUid()I > @2 exception:3,
invokestatic < Application, Lcom/android/server/PersistentDataBlockService, -$$Nest$menforceUid(Lcom/android/server/PersistentDataBlockService;I)V > 2,4 @6 exception:5,
6 = getfield < Application, Lcom/android/server/PersistentDataBlockService$1, this$0, <Application,Lcom/android/server/PersistentDataBlockService> > 1,
8 = invokestatic < Application, Lcom/android/server/PersistentDataBlockService, -$$Nest$menforceChecksumValidity(Lcom/android/server/PersistentDataBlockService;)Z > 6 @11 exception:7,
conditional branch(ne, to iindex=-1) 8,9,
10 = new <Application,Ljava/io/DataInputStream>@22,
11 = new <Application,Ljava/io/FileInputStream>@24,
12 = new <Application,Ljava/io/File>@26,
13 = getfield < Application, Lcom/android/server/PersistentDataBlockService$1, this$0, <Application,Lcom/android/server/PersistentDataBlockService> > 1,
15 = invokestatic < Application, Lcom/android/server/PersistentDataBlockService, -$$Nest$fgetmDataBlockFile(Lcom/android/server/PersistentDataBlockService;)Ljava/lang/String; > 13 @30 exception:14,
invokespecial < Application, Ljava/io/File, <init>(Ljava/lang/String;)V > 12,15 @34 exception:16,
invokespecial < Application, Ljava/io/FileInputStream, <init>(Ljava/io/File;)V > 11,12 @37 exception:17,
invokespecial < Application, Ljava/io/DataInputStream, <init>(Ljava/io/InputStream;)V > 10,11 @40 exception:18,
28 = getfield < Application, Lcom/android/server/PersistentDataBlockService$1, this$0, <Application,Lcom/android/server/PersistentDataBlockService> > 1,
30 = invokestatic < Application, Lcom/android/server/PersistentDataBlockService, -$$Nest$fgetmLock(Lcom/android/server/PersistentDataBlockService;)Ljava/lang/Object; > 28 @45 exception:29,
monitorenter 30,
31 = getfield < Application, Lcom/android/server/PersistentDataBlockService$1, this$0, <Application,Lcom/android/server/PersistentDataBlockService> > 1,
33 = invokestatic < Application, Lcom/android/server/PersistentDataBlockService, -$$Nest$mgetTotalDataSizeLocked(Lcom/android/server/PersistentDataBlockService;Ljava/io/DataInputStream;)I > 31,10 @52 exception:32,
conditional branch(ne, to iindex=-1) 33,9,
34 = new <Primordial,[B>@7533 ,
36 = invokevirtual < Application, Ljava/io/DataInputStream, read([BII)I > 10,34,9,33 @77 exception:35,
conditional branch(ge, to iindex=-1) 36,33,
monitorexit 30,
invokevirtual < Application, Ljava/io/DataInputStream, close()V > 10 @131 exception:37,
goto (from iindex= 65 to iindex = 10),
return 34,","depth : 0
-----
","public byte[] read(){
	int v1 = Binder.getCallingUid();
	PersistentDataBlockService.-$$Nest$menforceUid(this.this$0, v1);
	boolean v3 = PersistentDataBlockService.-$$Nest$menforceChecksumValidity(this.this$0);
	if (v3 != 0) {
		DataInputStream v4 = new DataInputStream(v5);
		FileInputStream v5 = new FileInputStream(v6);
		File v6 = new File(v7);
		String v7 = PersistentDataBlockService.-$$Nest$fgetmDataBlockFile(this.this$0);
		Object v11 = PersistentDataBlockService.-$$Nest$fgetmLock(this.this$0);
		int v12 = PersistentDataBlockService.-$$Nest$mgetTotalDataSizeLocked(this.this$0, v4);
		if (v12 != 0) {
			[B v13 = new [B(v12);
			int v14 = v4.read(v13, 0, v12);
			if (v14 >= v12) {
				v4.close();
				return v13;
			}
		}
	}
}
","NONE"
"Lcom/android/server/PersistentDataBlockService$1","read()[B","1","2 = getfield < Application, Lcom/android/server/PersistentDataBlockService$1, this$0, <Application,Lcom/android/server/PersistentDataBlockService> > 1,
4 = invokestatic < Application, Landroid/os/Binder, getCallingUid()I > @2 exception:3,
invokestatic < Application, Lcom/android/server/PersistentDataBlockService, -$$Nest$menforceUid(Lcom/android/server/PersistentDataBlockService;I)V > 2,4 @6 exception:5,
invokevirtual < Application, Lcom/android/server/PersistentDataBlockService, enforceUid(I)V > 1,2 @0 exception:3,
return,
6 = getfield < Application, Lcom/android/server/PersistentDataBlockService$1, this$0, <Application,Lcom/android/server/PersistentDataBlockService> > 1,
8 = invokestatic < Application, Lcom/android/server/PersistentDataBlockService, -$$Nest$menforceChecksumValidity(Lcom/android/server/PersistentDataBlockService;)Z > 6 @11 exception:7,
3 = invokevirtual < Application, Lcom/android/server/PersistentDataBlockService, enforceChecksumValidity()Z > 1 @0 exception:2,
return 3,
conditional branch(ne, to iindex=-1) 8,9,
10 = new <Application,Ljava/io/DataInputStream>@22,
11 = new <Application,Ljava/io/FileInputStream>@24,
12 = new <Application,Ljava/io/File>@26,
13 = getfield < Application, Lcom/android/server/PersistentDataBlockService$1, this$0, <Application,Lcom/android/server/PersistentDataBlockService> > 1,
15 = invokestatic < Application, Lcom/android/server/PersistentDataBlockService, -$$Nest$fgetmDataBlockFile(Lcom/android/server/PersistentDataBlockService;)Ljava/lang/String; > 13 @30 exception:14,
2 = getfield < Application, Lcom/android/server/PersistentDataBlockService, mDataBlockFile, <Application,Ljava/lang/String> > 1,
return 2,
invokespecial < Application, Ljava/io/File, <init>(Ljava/lang/String;)V > 12,15 @34 exception:16,
invokespecial < Application, Ljava/io/FileInputStream, <init>(Ljava/io/File;)V > 11,12 @37 exception:17,
invokespecial < Application, Ljava/io/DataInputStream, <init>(Ljava/io/InputStream;)V > 10,11 @40 exception:18,
28 = getfield < Application, Lcom/android/server/PersistentDataBlockService$1, this$0, <Application,Lcom/android/server/PersistentDataBlockService> > 1,
30 = invokestatic < Application, Lcom/android/server/PersistentDataBlockService, -$$Nest$fgetmLock(Lcom/android/server/PersistentDataBlockService;)Ljava/lang/Object; > 28 @45 exception:29,
2 = getfield < Application, Lcom/android/server/PersistentDataBlockService, mLock, <Application,Ljava/lang/Object> > 1,
return 2,
monitorenter 30,
31 = getfield < Application, Lcom/android/server/PersistentDataBlockService$1, this$0, <Application,Lcom/android/server/PersistentDataBlockService> > 1,
33 = invokestatic < Application, Lcom/android/server/PersistentDataBlockService, -$$Nest$mgetTotalDataSizeLocked(Lcom/android/server/PersistentDataBlockService;Ljava/io/DataInputStream;)I > 31,10 @52 exception:32,
4 = invokevirtual < Application, Lcom/android/server/PersistentDataBlockService, getTotalDataSizeLocked(Ljava/io/DataInputStream;)I > 1,2 @0 exception:3,
return 4,
conditional branch(ne, to iindex=-1) 33,9,
34 = new <Primordial,[B>@7533 ,
36 = invokevirtual < Application, Ljava/io/DataInputStream, read([BII)I > 10,34,9,33 @77 exception:35,
conditional branch(ge, to iindex=-1) 36,33,
monitorexit 30,
invokevirtual < Application, Ljava/io/DataInputStream, close()V > 10 @131 exception:37,
goto (from iindex= 65 to iindex = 10),
return 34,","depth : 0
-----
depth : 1
-----
depth : 1
-----
depth : 1
-----
depth : 1
-----
depth : 1
-----
","public byte[] read(){
	int v1 = Binder.getCallingUid();
	this.this$0.enforceUid(v1);
	boolean v5 = this.this$0.enforceChecksumValidity();
	boolean v4 = v5;
	if (v4 != 0) {
		DataInputStream v6 = new DataInputStream(v7);
		FileInputStream v7 = new FileInputStream(v8);
		File v8 = new File(v9);
		String v9 = this.mDataBlockFile;
		Object v13 = this.mLock;
		int v15 = this.this$0.getTotalDataSizeLocked(v6);
		int v14 = v15;
		if (v14 != 0) {
			[B v16 = new [B(v14);
			int v17 = v6.read(v16, 0, v14);
			if (v17 >= v14) {
				v6.close();
				return v16;
			}
		}
	}
}
","NONE"
"Lcom/android/server/PersistentDataBlockService$1","read()[B","1","2 = getfield < Application, Lcom/android/server/PersistentDataBlockService$1, this$0, <Application,Lcom/android/server/PersistentDataBlockService> > 1,
4 = invokestatic < Application, Landroid/os/Binder, getCallingUid()I > @2 exception:3,
invokestatic < Application, Lcom/android/server/PersistentDataBlockService, -$$Nest$menforceUid(Lcom/android/server/PersistentDataBlockService;I)V > 2,4 @6 exception:5,
invokevirtual < Application, Lcom/android/server/PersistentDataBlockService, enforceUid(I)V > 1,2 @0 exception:3,
return,
6 = getfield < Application, Lcom/android/server/PersistentDataBlockService$1, this$0, <Application,Lcom/android/server/PersistentDataBlockService> > 1,
8 = invokestatic < Application, Lcom/android/server/PersistentDataBlockService, -$$Nest$menforceChecksumValidity(Lcom/android/server/PersistentDataBlockService;)Z > 6 @11 exception:7,
3 = invokevirtual < Application, Lcom/android/server/PersistentDataBlockService, enforceChecksumValidity()Z > 1 @0 exception:2,
return 3,
conditional branch(ne, to iindex=-1) 8,9,
10 = new <Application,Ljava/io/DataInputStream>@22,
11 = new <Application,Ljava/io/FileInputStream>@24,
12 = new <Application,Ljava/io/File>@26,
13 = getfield < Application, Lcom/android/server/PersistentDataBlockService$1, this$0, <Application,Lcom/android/server/PersistentDataBlockService> > 1,
15 = invokestatic < Application, Lcom/android/server/PersistentDataBlockService, -$$Nest$fgetmDataBlockFile(Lcom/android/server/PersistentDataBlockService;)Ljava/lang/String; > 13 @30 exception:14,
2 = getfield < Application, Lcom/android/server/PersistentDataBlockService, mDataBlockFile, <Application,Ljava/lang/String> > 1,
return 2,
invokespecial < Application, Ljava/io/File, <init>(Ljava/lang/String;)V > 12,15 @34 exception:16,
invokespecial < Application, Ljava/io/FileInputStream, <init>(Ljava/io/File;)V > 11,12 @37 exception:17,
invokespecial < Application, Ljava/io/DataInputStream, <init>(Ljava/io/InputStream;)V > 10,11 @40 exception:18,
28 = getfield < Application, Lcom/android/server/PersistentDataBlockService$1, this$0, <Application,Lcom/android/server/PersistentDataBlockService> > 1,
30 = invokestatic < Application, Lcom/android/server/PersistentDataBlockService, -$$Nest$fgetmLock(Lcom/android/server/PersistentDataBlockService;)Ljava/lang/Object; > 28 @45 exception:29,
2 = getfield < Application, Lcom/android/server/PersistentDataBlockService, mLock, <Application,Ljava/lang/Object> > 1,
return 2,
monitorenter 30,
31 = getfield < Application, Lcom/android/server/PersistentDataBlockService$1, this$0, <Application,Lcom/android/server/PersistentDataBlockService> > 1,
33 = invokestatic < Application, Lcom/android/server/PersistentDataBlockService, -$$Nest$mgetTotalDataSizeLocked(Lcom/android/server/PersistentDataBlockService;Ljava/io/DataInputStream;)I > 31,10 @52 exception:32,
4 = invokevirtual < Application, Lcom/android/server/PersistentDataBlockService, getTotalDataSizeLocked(Ljava/io/DataInputStream;)I > 1,2 @0 exception:3,
return 4,
conditional branch(ne, to iindex=-1) 33,9,
74 = new <Primordial,[B>@589 ,
monitorexit 30,
invokevirtual < Application, Ljava/io/DataInputStream, close()V > 10 @61 exception:121,
goto (from iindex= 32 to iindex = 10),
return 74,","depth : 0
-----
depth : 1
-----
depth : 1
-----
depth : 1
-----
depth : 1
-----
depth : 1
-----
","public byte[] read(){
	int v1 = Binder.getCallingUid();
	this.this$0.enforceUid(v1);
	boolean v5 = this.this$0.enforceChecksumValidity();
	boolean v4 = v5;
	if (v4 != 0) {
		DataInputStream v6 = new DataInputStream(v7);
		FileInputStream v7 = new FileInputStream(v8);
		File v8 = new File(v9);
		String v9 = this.mDataBlockFile;
		Object v13 = this.mLock;
		int v15 = this.this$0.getTotalDataSizeLocked(v6);
		int v14 = v15;
		if (v14 != 0) {
			[B v16 = new [B(0);
			v6.close();
			return v16;
		}
	}
}
","NONE"
"Lcom/android/server/PersistentDataBlockService$1","read()[B","2","2 = getfield < Application, Lcom/android/server/PersistentDataBlockService$1, this$0, <Application,Lcom/android/server/PersistentDataBlockService> > 1,
4 = invokestatic < Application, Landroid/os/Binder, getCallingUid()I > @2 exception:3,
invokestatic < Application, Lcom/android/server/PersistentDataBlockService, -$$Nest$menforceUid(Lcom/android/server/PersistentDataBlockService;I)V > 2,4 @6 exception:5,
invokevirtual < Application, Lcom/android/server/PersistentDataBlockService, enforceUid(I)V > 1,2 @0 exception:3,
3 = getfield < Application, Lcom/android/server/PersistentDataBlockService, mAllowedUid, <Primordial,I> > 1,
conditional branch(ne, to iindex=-1) 2,3,
return,
return,
6 = getfield < Application, Lcom/android/server/PersistentDataBlockService$1, this$0, <Application,Lcom/android/server/PersistentDataBlockService> > 1,
8 = invokestatic < Application, Lcom/android/server/PersistentDataBlockService, -$$Nest$menforceChecksumValidity(Lcom/android/server/PersistentDataBlockService;)Z > 6 @11 exception:7,
3 = invokevirtual < Application, Lcom/android/server/PersistentDataBlockService, enforceChecksumValidity()Z > 1 @0 exception:2,
3 = new <Primordial,[B>@22 ,
4 = getfield < Application, Lcom/android/server/PersistentDataBlockService, mLock, <Application,Ljava/lang/Object> > 1,
monitorenter 4,
6 = invokevirtual < Application, Lcom/android/server/PersistentDataBlockService, computeDigestLocked([B)[B > 1,3 @7 exception:5,
conditional branch(eq, to iindex=-1) 6,7,
9 = invokestatic < Application, Ljava/util/Arrays, equals([B[B)Z > 3,6 @13 exception:8,
conditional branch(ne, to iindex=-1) 9,7,
goto (from iindex= 10 to iindex = 4),
14 = getstatic < Application, Lcom/android/server/PersistentDataBlockService, TAG, <Application,Ljava/lang/String> >,
17 = invokestatic < Application, Landroid/util/Slog, i(Ljava/lang/String;Ljava/lang/String;)I > 14,15 @27 exception:16,
invokevirtual < Application, Lcom/android/server/PersistentDataBlockService, formatPartitionLocked(Z)V > 1,7 @31 exception:18,
monitorexit 4,
return 7,
return 3,
conditional branch(ne, to iindex=-1) 8,9,
10 = new <Application,Ljava/io/DataInputStream>@22,
11 = new <Application,Ljava/io/FileInputStream>@24,
12 = new <Application,Ljava/io/File>@26,
13 = getfield < Application, Lcom/android/server/PersistentDataBlockService$1, this$0, <Application,Lcom/android/server/PersistentDataBlockService> > 1,
15 = invokestatic < Application, Lcom/android/server/PersistentDataBlockService, -$$Nest$fgetmDataBlockFile(Lcom/android/server/PersistentDataBlockService;)Ljava/lang/String; > 13 @30 exception:14,
invokespecial < Application, Ljava/io/File, <init>(Ljava/lang/String;)V > 12,15 @34 exception:16,
invokespecial < Application, Ljava/io/FileInputStream, <init>(Ljava/io/File;)V > 11,12 @37 exception:17,
invokespecial < Application, Ljava/io/DataInputStream, <init>(Ljava/io/InputStream;)V > 10,11 @40 exception:18,
28 = getfield < Application, Lcom/android/server/PersistentDataBlockService$1, this$0, <Application,Lcom/android/server/PersistentDataBlockService> > 1,
30 = invokestatic < Application, Lcom/android/server/PersistentDataBlockService, -$$Nest$fgetmLock(Lcom/android/server/PersistentDataBlockService;)Ljava/lang/Object; > 28 @45 exception:29,
monitorenter 30,
31 = getfield < Application, Lcom/android/server/PersistentDataBlockService$1, this$0, <Application,Lcom/android/server/PersistentDataBlockService> > 1,
33 = invokestatic < Application, Lcom/android/server/PersistentDataBlockService, -$$Nest$mgetTotalDataSizeLocked(Lcom/android/server/PersistentDataBlockService;Ljava/io/DataInputStream;)I > 31,10 @52 exception:32,
conditional branch(ne, to iindex=-1) 33,9,
34 = new <Primordial,[B>@7533 ,
36 = invokevirtual < Application, Ljava/io/DataInputStream, read([BII)I > 10,34,9,33 @77 exception:35,
conditional branch(ge, to iindex=-1) 36,33,
monitorexit 30,
invokevirtual < Application, Ljava/io/DataInputStream, close()V > 10 @131 exception:37,
goto (from iindex= 65 to iindex = 10),
return 34,","depth : 0
-----
depth : 1
-----
depth : 2
-----
depth : 1
-----
depth : 2
-----
","public byte[] read(){
	int v1 = Binder.getCallingUid();
	if (v1 != this.mAllowedUid) {
		[B v6 = new [B(32);
		byte[] v7 = PersistentDataBlockService.computeDigestLocked(v6);
		if (v7 == 0) {
			boolean v8 = Arrays.equals(v6, v7);
			if (v8 != 0) {
				PersistentDataBlockService.formatPartitionLocked(0);
				boolean v5 = 0;
				boolean v4 = v5;
				if (v4 != 0) {
					DataInputStream v11 = new DataInputStream(v12);
					FileInputStream v12 = new FileInputStream(v13);
					File v13 = new File(v14);
					String v14 = PersistentDataBlockService.-$$Nest$fgetmDataBlockFile(this.this$0);
					Object v18 = PersistentDataBlockService.-$$Nest$fgetmLock(this.this$0);
					int v19 = PersistentDataBlockService.-$$Nest$mgetTotalDataSizeLocked(this.this$0, v11);
					if (v19 != 0) {
						[B v20 = new [B(v19);
						int v21 = v11.read(v20, 0, v19);
						if (v21 >= v19) {
							v11.close();
							return v20;
						}
					}
				}
			}
		}
	}
}
","NONE"
"Lcom/android/server/PersistentDataBlockService$1","read()[B","2","2 = getfield < Application, Lcom/android/server/PersistentDataBlockService$1, this$0, <Application,Lcom/android/server/PersistentDataBlockService> > 1,
4 = invokestatic < Application, Landroid/os/Binder, getCallingUid()I > @2 exception:3,
invokestatic < Application, Lcom/android/server/PersistentDataBlockService, -$$Nest$menforceUid(Lcom/android/server/PersistentDataBlockService;I)V > 2,4 @6 exception:5,
invokevirtual < Application, Lcom/android/server/PersistentDataBlockService, enforceUid(I)V > 1,2 @0 exception:3,
3 = getfield < Application, Lcom/android/server/PersistentDataBlockService, mAllowedUid, <Primordial,I> > 1,
conditional branch(ne, to iindex=-1) 2,3,
return,
return,
6 = getfield < Application, Lcom/android/server/PersistentDataBlockService$1, this$0, <Application,Lcom/android/server/PersistentDataBlockService> > 1,
8 = invokestatic < Application, Lcom/android/server/PersistentDataBlockService, -$$Nest$menforceChecksumValidity(Lcom/android/server/PersistentDataBlockService;)Z > 6 @11 exception:7,
3 = invokevirtual < Application, Lcom/android/server/PersistentDataBlockService, enforceChecksumValidity()Z > 1 @0 exception:2,
3 = new <Primordial,[B>@22 ,
4 = getfield < Application, Lcom/android/server/PersistentDataBlockService, mLock, <Application,Ljava/lang/Object> > 1,
monitorenter 4,
6 = invokevirtual < Application, Lcom/android/server/PersistentDataBlockService, computeDigestLocked([B)[B > 1,3 @7 exception:5,
conditional branch(eq, to iindex=-1) 6,7,
9 = invokestatic < Application, Ljava/util/Arrays, equals([B[B)Z > 3,6 @13 exception:8,
conditional branch(ne, to iindex=-1) 9,7,
goto (from iindex= 10 to iindex = 4),
14 = getstatic < Application, Lcom/android/server/PersistentDataBlockService, TAG, <Application,Ljava/lang/String> >,
17 = invokestatic < Application, Landroid/util/Slog, i(Ljava/lang/String;Ljava/lang/String;)I > 14,15 @27 exception:16,
invokevirtual < Application, Lcom/android/server/PersistentDataBlockService, formatPartitionLocked(Z)V > 1,7 @31 exception:18,
monitorexit 4,
return 7,
return 3,
conditional branch(ne, to iindex=-1) 8,9,
10 = new <Application,Ljava/io/DataInputStream>@22,
11 = new <Application,Ljava/io/FileInputStream>@24,
12 = new <Application,Ljava/io/File>@26,
13 = getfield < Application, Lcom/android/server/PersistentDataBlockService$1, this$0, <Application,Lcom/android/server/PersistentDataBlockService> > 1,
15 = invokestatic < Application, Lcom/android/server/PersistentDataBlockService, -$$Nest$fgetmDataBlockFile(Lcom/android/server/PersistentDataBlockService;)Ljava/lang/String; > 13 @30 exception:14,
invokespecial < Application, Ljava/io/File, <init>(Ljava/lang/String;)V > 12,15 @34 exception:16,
invokespecial < Application, Ljava/io/FileInputStream, <init>(Ljava/io/File;)V > 11,12 @37 exception:17,
invokespecial < Application, Ljava/io/DataInputStream, <init>(Ljava/io/InputStream;)V > 10,11 @40 exception:18,
28 = getfield < Application, Lcom/android/server/PersistentDataBlockService$1, this$0, <Application,Lcom/android/server/PersistentDataBlockService> > 1,
30 = invokestatic < Application, Lcom/android/server/PersistentDataBlockService, -$$Nest$fgetmLock(Lcom/android/server/PersistentDataBlockService;)Ljava/lang/Object; > 28 @45 exception:29,
monitorenter 30,
31 = getfield < Application, Lcom/android/server/PersistentDataBlockService$1, this$0, <Application,Lcom/android/server/PersistentDataBlockService> > 1,
33 = invokestatic < Application, Lcom/android/server/PersistentDataBlockService, -$$Nest$mgetTotalDataSizeLocked(Lcom/android/server/PersistentDataBlockService;Ljava/io/DataInputStream;)I > 31,10 @52 exception:32,
conditional branch(ne, to iindex=-1) 33,9,
74 = new <Primordial,[B>@589 ,
monitorexit 30,
invokevirtual < Application, Ljava/io/DataInputStream, close()V > 10 @61 exception:121,
goto (from iindex= 32 to iindex = 10),
return 74,","depth : 0
-----
depth : 1
-----
depth : 2
-----
depth : 1
-----
depth : 2
-----
","public byte[] read(){
	int v1 = Binder.getCallingUid();
	if (v1 != this.mAllowedUid) {
		[B v6 = new [B(32);
		byte[] v7 = PersistentDataBlockService.computeDigestLocked(v6);
		if (v7 == 0) {
			boolean v8 = Arrays.equals(v6, v7);
			if (v8 != 0) {
				PersistentDataBlockService.formatPartitionLocked(0);
				boolean v5 = 0;
				boolean v4 = v5;
				if (v4 != 0) {
					DataInputStream v11 = new DataInputStream(v12);
					FileInputStream v12 = new FileInputStream(v13);
					File v13 = new File(v14);
					String v14 = PersistentDataBlockService.-$$Nest$fgetmDataBlockFile(this.this$0);
					Object v18 = PersistentDataBlockService.-$$Nest$fgetmLock(this.this$0);
					int v19 = PersistentDataBlockService.-$$Nest$mgetTotalDataSizeLocked(this.this$0, v11);
					if (v19 != 0) {
						[B v20 = new [B(0);
						v11.close();
						return v20;
					}
				}
			}
		}
	}
}
","NONE"
"Lcom/android/server/PersistentDataBlockService$1","read()[B","2","2 = getfield < Application, Lcom/android/server/PersistentDataBlockService$1, this$0, <Application,Lcom/android/server/PersistentDataBlockService> > 1,
4 = invokestatic < Application, Landroid/os/Binder, getCallingUid()I > @2 exception:3,
invokestatic < Application, Lcom/android/server/PersistentDataBlockService, -$$Nest$menforceUid(Lcom/android/server/PersistentDataBlockService;I)V > 2,4 @6 exception:5,
invokevirtual < Application, Lcom/android/server/PersistentDataBlockService, enforceUid(I)V > 1,2 @0 exception:3,
3 = getfield < Application, Lcom/android/server/PersistentDataBlockService, mAllowedUid, <Primordial,I> > 1,
conditional branch(ne, to iindex=-1) 2,3,
return,
return,
6 = getfield < Application, Lcom/android/server/PersistentDataBlockService$1, this$0, <Application,Lcom/android/server/PersistentDataBlockService> > 1,
8 = invokestatic < Application, Lcom/android/server/PersistentDataBlockService, -$$Nest$menforceChecksumValidity(Lcom/android/server/PersistentDataBlockService;)Z > 6 @11 exception:7,
3 = invokevirtual < Application, Lcom/android/server/PersistentDataBlockService, enforceChecksumValidity()Z > 1 @0 exception:2,
3 = new <Primordial,[B>@22 ,
4 = getfield < Application, Lcom/android/server/PersistentDataBlockService, mLock, <Application,Ljava/lang/Object> > 1,
monitorenter 4,
6 = invokevirtual < Application, Lcom/android/server/PersistentDataBlockService, computeDigestLocked([B)[B > 1,3 @7 exception:5,
conditional branch(eq, to iindex=-1) 6,7,
9 = invokestatic < Application, Ljava/util/Arrays, equals([B[B)Z > 3,6 @13 exception:8,
conditional branch(ne, to iindex=-1) 9,7,
monitorexit 4,
return 10,
return 3,
conditional branch(ne, to iindex=-1) 8,9,
10 = new <Application,Ljava/io/DataInputStream>@22,
11 = new <Application,Ljava/io/FileInputStream>@24,
12 = new <Application,Ljava/io/File>@26,
13 = getfield < Application, Lcom/android/server/PersistentDataBlockService$1, this$0, <Application,Lcom/android/server/PersistentDataBlockService> > 1,
15 = invokestatic < Application, Lcom/android/server/PersistentDataBlockService, -$$Nest$fgetmDataBlockFile(Lcom/android/server/PersistentDataBlockService;)Ljava/lang/String; > 13 @30 exception:14,
invokespecial < Application, Ljava/io/File, <init>(Ljava/lang/String;)V > 12,15 @34 exception:16,
invokespecial < Application, Ljava/io/FileInputStream, <init>(Ljava/io/File;)V > 11,12 @37 exception:17,
invokespecial < Application, Ljava/io/DataInputStream, <init>(Ljava/io/InputStream;)V > 10,11 @40 exception:18,
28 = getfield < Application, Lcom/android/server/PersistentDataBlockService$1, this$0, <Application,Lcom/android/server/PersistentDataBlockService> > 1,
30 = invokestatic < Application, Lcom/android/server/PersistentDataBlockService, -$$Nest$fgetmLock(Lcom/android/server/PersistentDataBlockService;)Ljava/lang/Object; > 28 @45 exception:29,
monitorenter 30,
31 = getfield < Application, Lcom/android/server/PersistentDataBlockService$1, this$0, <Application,Lcom/android/server/PersistentDataBlockService> > 1,
33 = invokestatic < Application, Lcom/android/server/PersistentDataBlockService, -$$Nest$mgetTotalDataSizeLocked(Lcom/android/server/PersistentDataBlockService;Ljava/io/DataInputStream;)I > 31,10 @52 exception:32,
conditional branch(ne, to iindex=-1) 33,9,
34 = new <Primordial,[B>@7533 ,
36 = invokevirtual < Application, Ljava/io/DataInputStream, read([BII)I > 10,34,9,33 @77 exception:35,
conditional branch(ge, to iindex=-1) 36,33,
monitorexit 30,
invokevirtual < Application, Ljava/io/DataInputStream, close()V > 10 @131 exception:37,
goto (from iindex= 65 to iindex = 10),
return 34,","depth : 0
-----
depth : 1
-----
depth : 2
-----
depth : 1
-----
depth : 2
-----
","public byte[] read(){
	int v1 = Binder.getCallingUid();
	if (v1 != this.mAllowedUid) {
		[B v6 = new [B(32);
		byte[] v7 = PersistentDataBlockService.computeDigestLocked(v6);
		if (v7 == 0) {
			boolean v8 = Arrays.equals(v6, v7);
			if (v8 != 0) {
				boolean v5 = 1;
				boolean v4 = v5;
				if (v4 != 0) {
					DataInputStream v9 = new DataInputStream(v10);
					FileInputStream v10 = new FileInputStream(v11);
					File v11 = new File(v12);
					String v12 = PersistentDataBlockService.-$$Nest$fgetmDataBlockFile(this.this$0);
					Object v16 = PersistentDataBlockService.-$$Nest$fgetmLock(this.this$0);
					int v17 = PersistentDataBlockService.-$$Nest$mgetTotalDataSizeLocked(this.this$0, v9);
					if (v17 != 0) {
						[B v18 = new [B(v17);
						int v19 = v9.read(v18, 0, v17);
						if (v19 >= v17) {
							v9.close();
							return v18;
						}
					}
				}
			}
		}
	}
}
","NONE"

"Lcom/android/server/PersistentDataBlockService$1","getFlashLockState()I","0","2 = getfield < Application, Lcom/android/server/PersistentDataBlockService$1, this$0, <Application,Lcom/android/server/PersistentDataBlockService> > 1,
invokestatic < Application, Lcom/android/server/PersistentDataBlockService, -$$Nest$menforceOemUnlockReadPermission(Lcom/android/server/PersistentDataBlockService;)V > 2 @2 exception:3,
6 = invokestatic < Application, Landroid/os/SystemProperties, get(Ljava/lang/String;)Ljava/lang/String; > 4 @8 exception:5,
8 = invokevirtual < Application, Ljava/lang/String, hashCode()I > 6 @12 exception:7,
11 = invokevirtual < Application, Ljava/lang/String, equals(Ljava/lang/Object;)Z > 6,9 @17 exception:10,
conditional branch(ne, to iindex=-1) 11,12,
15 = invokevirtual < Application, Ljava/lang/String, equals(Ljava/lang/Object;)Z > 6,13 @25 exception:14,
conditional branch(ne, to iindex=-1) 15,12,
return 17,","depth : 0
-----
","public int getFlashLockState(){
	String v2 = SystemProperties.get(""ro.boot.flash.locked"");
	int v3 = v2.hashCode();
	boolean v4 = v2.equals(""0"");
	if (v4 != 0) {
		boolean v5 = v2.equals(""1"");
		if (v5 != 0) {
			return -1;
		}
	}
}
","SYS_OR_SIG"
"Lcom/android/server/PersistentDataBlockService$1","getFlashLockState()I","0","2 = getfield < Application, Lcom/android/server/PersistentDataBlockService$1, this$0, <Application,Lcom/android/server/PersistentDataBlockService> > 1,
invokestatic < Application, Lcom/android/server/PersistentDataBlockService, -$$Nest$menforceOemUnlockReadPermission(Lcom/android/server/PersistentDataBlockService;)V > 2 @2 exception:3,
6 = invokestatic < Application, Landroid/os/SystemProperties, get(Ljava/lang/String;)Ljava/lang/String; > 4 @8 exception:5,
8 = invokevirtual < Application, Ljava/lang/String, hashCode()I > 6 @12 exception:7,
11 = invokevirtual < Application, Ljava/lang/String, equals(Ljava/lang/Object;)Z > 6,9 @17 exception:10,
conditional branch(ne, to iindex=-1) 11,12,
15 = invokevirtual < Application, Ljava/lang/String, equals(Ljava/lang/Object;)Z > 6,13 @25 exception:14,
conditional branch(ne, to iindex=-1) 15,12,
return 16,","depth : 0
-----
","public int getFlashLockState(){
	String v2 = SystemProperties.get(""ro.boot.flash.locked"");
	int v3 = v2.hashCode();
	boolean v4 = v2.equals(""0"");
	if (v4 != 0) {
		boolean v5 = v2.equals(""1"");
		if (v5 != 0) {
			return 1;
		}
	}
}
","SYS_OR_SIG"
"Lcom/android/server/PersistentDataBlockService$1","getFlashLockState()I","0","2 = getfield < Application, Lcom/android/server/PersistentDataBlockService$1, this$0, <Application,Lcom/android/server/PersistentDataBlockService> > 1,
invokestatic < Application, Lcom/android/server/PersistentDataBlockService, -$$Nest$menforceOemUnlockReadPermission(Lcom/android/server/PersistentDataBlockService;)V > 2 @2 exception:3,
6 = invokestatic < Application, Landroid/os/SystemProperties, get(Ljava/lang/String;)Ljava/lang/String; > 4 @8 exception:5,
8 = invokevirtual < Application, Ljava/lang/String, hashCode()I > 6 @12 exception:7,
11 = invokevirtual < Application, Ljava/lang/String, equals(Ljava/lang/Object;)Z > 6,9 @17 exception:10,
conditional branch(ne, to iindex=-1) 11,12,
return 12,","depth : 0
-----
","public int getFlashLockState(){
	String v2 = SystemProperties.get(""ro.boot.flash.locked"");
	int v3 = v2.hashCode();
	boolean v4 = v2.equals(""0"");
	if (v4 != 0) {
		return 0;
	}
}
","SYS_OR_SIG"

