"Class","Method","Depth","Trace Instruction(s) ...","Java Code Representation","Code Merged","Access Control Level"
"Lcom/android/server/VcnManagementService","clearVcnConfig(Landroid/os/ParcelUuid;Ljava/lang/String;)V","0","6 = invokestatic < Application, Ljava/util/Objects, requireNonNull(Ljava/lang/Object;Ljava/lang/String;)Ljava/lang/Object; > 2,4 @3 exception:5,
9 = invokestatic < Application, Ljava/util/Objects, requireNonNull(Ljava/lang/Object;Ljava/lang/String;)Ljava/lang/Object; > 3,7 @9 exception:8,
10 = new <Application,Ljava/lang/StringBuilder>@12,
invokespecial < Application, Ljava/lang/StringBuilder, <init>()V > 10 @14 exception:11,
14 = invokevirtual < Application, Ljava/lang/StringBuilder, append(Ljava/lang/String;)Ljava/lang/StringBuilder; > 10,12 @19 exception:13,
16 = invokevirtual < Application, Ljava/lang/StringBuilder, append(Ljava/lang/Object;)Ljava/lang/StringBuilder; > 10,2 @22 exception:15,
18 = invokevirtual < Application, Ljava/lang/StringBuilder, toString()Ljava/lang/String; > 10 @25 exception:17,
invokevirtual < Application, Lcom/android/server/VcnManagementService, logInfo(Ljava/lang/String;)V > 1,18 @29 exception:19,
20 = getfield < Application, Lcom/android/server/VcnManagementService, mContext, <Application,Landroid/content/Context> > 1,
21 = load_metadata: <Application,Landroid/app/AppOpsManager>, <Primordial,Ljava/lang/Class>,
23 = invokevirtual < Application, Landroid/content/Context, getSystemService(Ljava/lang/Class;)Ljava/lang/Object; > 20,21 @36 exception:22,
24 = checkcast <Application,Landroid/app/AppOpsManager>23 <Application,Landroid/app/AppOpsManager>,
25 = getfield < Application, Lcom/android/server/VcnManagementService, mDeps, <Application,Lcom/android/server/VcnManagementService$Dependencies> > 1,
27 = invokevirtual < Application, Lcom/android/server/VcnManagementService$Dependencies, getBinderCallingUid()I > 25 @44 exception:26,
invokevirtual < Application, Landroid/app/AppOpsManager, checkPackage(ILjava/lang/String;)V > 24,27,3 @48 exception:28,
invokevirtual < Application, Lcom/android/server/VcnManagementService, enforceCarrierPrivilegeOrProvisioningPackage(Landroid/os/ParcelUuid;Ljava/lang/String;)V > 1,2,3 @51 exception:29,
30 = new <Application,Lcom/android/server/VcnManagementService$$ExternalSyntheticLambda5>@54,
invokespecial < Application, Lcom/android/server/VcnManagementService$$ExternalSyntheticLambda5, <init>(Lcom/android/server/VcnManagementService;Landroid/os/ParcelUuid;)V > 30,1,2 @56 exception:31,
invokestatic < Application, Landroid/os/Binder, withCleanCallingIdentity(Lcom/android/internal/util/FunctionalUtils$ThrowingRunnable;)V > 30 @59 exception:32,
return,","depth : 0
public void clearVcnConfig(ParcelUuid p1, String p2){
	p0.enforceCarrierPrivilegeOrProvisioningPackage(p1, p2);
	VcnManagementService$$ExternalSyntheticLambda5 v11 = new VcnManagementService$$ExternalSyntheticLambda5(p0,p1);
	Binder.withCleanCallingIdentity(v11);
	return;
}
-----
","public void clearVcnConfig(ParcelUuid p1, String p2){
	p0.enforceCarrierPrivilegeOrProvisioningPackage(p1, p2);
	VcnManagementService$$ExternalSyntheticLambda5 v13 = new VcnManagementService$$ExternalSyntheticLambda5(p0,p1);
	Binder.withCleanCallingIdentity(v13);
	return;
}
","NONE"
"Lcom/android/server/VcnManagementService","clearVcnConfig(Landroid/os/ParcelUuid;Ljava/lang/String;)V","1","6 = invokestatic < Application, Ljava/util/Objects, requireNonNull(Ljava/lang/Object;Ljava/lang/String;)Ljava/lang/Object; > 2,4 @3 exception:5,
9 = invokestatic < Application, Ljava/util/Objects, requireNonNull(Ljava/lang/Object;Ljava/lang/String;)Ljava/lang/Object; > 3,7 @9 exception:8,
10 = new <Application,Ljava/lang/StringBuilder>@12,
invokespecial < Application, Ljava/lang/StringBuilder, <init>()V > 10 @14 exception:11,
14 = invokevirtual < Application, Ljava/lang/StringBuilder, append(Ljava/lang/String;)Ljava/lang/StringBuilder; > 10,12 @19 exception:13,
16 = invokevirtual < Application, Ljava/lang/StringBuilder, append(Ljava/lang/Object;)Ljava/lang/StringBuilder; > 10,2 @22 exception:15,
18 = invokevirtual < Application, Ljava/lang/StringBuilder, toString()Ljava/lang/String; > 10 @25 exception:17,
invokevirtual < Application, Lcom/android/server/VcnManagementService, logInfo(Ljava/lang/String;)V > 1,18 @29 exception:19,
20 = getfield < Application, Lcom/android/server/VcnManagementService, mContext, <Application,Landroid/content/Context> > 1,
21 = load_metadata: <Application,Landroid/app/AppOpsManager>, <Primordial,Ljava/lang/Class>,
23 = invokevirtual < Application, Landroid/content/Context, getSystemService(Ljava/lang/Class;)Ljava/lang/Object; > 20,21 @36 exception:22,
24 = checkcast <Application,Landroid/app/AppOpsManager>23 <Application,Landroid/app/AppOpsManager>,
25 = getfield < Application, Lcom/android/server/VcnManagementService, mDeps, <Application,Lcom/android/server/VcnManagementService$Dependencies> > 1,
27 = invokevirtual < Application, Lcom/android/server/VcnManagementService$Dependencies, getBinderCallingUid()I > 25 @44 exception:26,
invokevirtual < Application, Landroid/app/AppOpsManager, checkPackage(ILjava/lang/String;)V > 24,27,3 @48 exception:28,
invokevirtual < Application, Lcom/android/server/VcnManagementService, enforceCarrierPrivilegeOrProvisioningPackage(Landroid/os/ParcelUuid;Ljava/lang/String;)V > 1,2,3 @51 exception:29,
invokevirtual < Application, Lcom/android/server/VcnManagementService, enforcePrimaryUser()V > 1 @0 exception:4,
6 = invokevirtual < Application, Lcom/android/server/VcnManagementService, isProvisioningPackageForConfig(Landroid/os/ParcelUuid;Ljava/lang/String;)Z > 1,2,3 @3 exception:5,
conditional branch(eq, to iindex=-1) 6,7,
invokevirtual < Application, Lcom/android/server/VcnManagementService, enforceCallingUserAndCarrierPrivilege(Landroid/os/ParcelUuid;Ljava/lang/String;)V > 1,2,3 @10 exception:8,
return,
30 = new <Application,Lcom/android/server/VcnManagementService$$ExternalSyntheticLambda5>@54,
invokespecial < Application, Lcom/android/server/VcnManagementService$$ExternalSyntheticLambda5, <init>(Lcom/android/server/VcnManagementService;Landroid/os/ParcelUuid;)V > 30,1,2 @56 exception:31,
invokestatic < Application, Landroid/os/Binder, withCleanCallingIdentity(Lcom/android/internal/util/FunctionalUtils$ThrowingRunnable;)V > 30 @59 exception:32,
return,","depth : 0
public void clearVcnConfig(ParcelUuid p1, String p2){
	p0.enforceCarrierPrivilegeOrProvisioningPackage(p1, p2);
	VcnManagementService$$ExternalSyntheticLambda5 v11 = new VcnManagementService$$ExternalSyntheticLambda5(p0,p1);
	Binder.withCleanCallingIdentity(v11);
	return;
}
-----
depth : 1
public void enforceCarrierPrivilegeOrProvisioningPackage(ParcelUuid p1, String p2){
	p0.enforcePrimaryUser();
	boolean v2 = p0.isProvisioningPackageForConfig(p1, p2);
	p0.enforceCallingUserAndCarrierPrivilege(p1, p2);
	return;
}
-----
","public void clearVcnConfig(ParcelUuid p1, String p2){
	VcnManagementService.enforcePrimaryUser();
	boolean v14 = VcnManagementService.isProvisioningPackageForConfig(p1, p2);
	VcnManagementService.enforceCallingUserAndCarrierPrivilege(p1, p2);
	VcnManagementService$$ExternalSyntheticLambda5 v16 = new VcnManagementService$$ExternalSyntheticLambda5(p0,p1);
	Binder.withCleanCallingIdentity(v16);
	return;
}
","NONE"
"Lcom/android/server/VcnManagementService","clearVcnConfig(Landroid/os/ParcelUuid;Ljava/lang/String;)V","2","6 = invokestatic < Application, Ljava/util/Objects, requireNonNull(Ljava/lang/Object;Ljava/lang/String;)Ljava/lang/Object; > 2,4 @3 exception:5,
9 = invokestatic < Application, Ljava/util/Objects, requireNonNull(Ljava/lang/Object;Ljava/lang/String;)Ljava/lang/Object; > 3,7 @9 exception:8,
10 = new <Application,Ljava/lang/StringBuilder>@12,
invokespecial < Application, Ljava/lang/StringBuilder, <init>()V > 10 @14 exception:11,
14 = invokevirtual < Application, Ljava/lang/StringBuilder, append(Ljava/lang/String;)Ljava/lang/StringBuilder; > 10,12 @19 exception:13,
16 = invokevirtual < Application, Ljava/lang/StringBuilder, append(Ljava/lang/Object;)Ljava/lang/StringBuilder; > 10,2 @22 exception:15,
18 = invokevirtual < Application, Ljava/lang/StringBuilder, toString()Ljava/lang/String; > 10 @25 exception:17,
invokevirtual < Application, Lcom/android/server/VcnManagementService, logInfo(Ljava/lang/String;)V > 1,18 @29 exception:19,
20 = getfield < Application, Lcom/android/server/VcnManagementService, mContext, <Application,Landroid/content/Context> > 1,
21 = load_metadata: <Application,Landroid/app/AppOpsManager>, <Primordial,Ljava/lang/Class>,
23 = invokevirtual < Application, Landroid/content/Context, getSystemService(Ljava/lang/Class;)Ljava/lang/Object; > 20,21 @36 exception:22,
24 = checkcast <Application,Landroid/app/AppOpsManager>23 <Application,Landroid/app/AppOpsManager>,
25 = getfield < Application, Lcom/android/server/VcnManagementService, mDeps, <Application,Lcom/android/server/VcnManagementService$Dependencies> > 1,
27 = invokevirtual < Application, Lcom/android/server/VcnManagementService$Dependencies, getBinderCallingUid()I > 25 @44 exception:26,
invokevirtual < Application, Landroid/app/AppOpsManager, checkPackage(ILjava/lang/String;)V > 24,27,3 @48 exception:28,
invokevirtual < Application, Lcom/android/server/VcnManagementService, enforceCarrierPrivilegeOrProvisioningPackage(Landroid/os/ParcelUuid;Ljava/lang/String;)V > 1,2,3 @51 exception:29,
invokevirtual < Application, Lcom/android/server/VcnManagementService, enforcePrimaryUser()V > 1 @0 exception:4,
2 = getfield < Application, Lcom/android/server/VcnManagementService, mDeps, <Application,Lcom/android/server/VcnManagementService$Dependencies> > 1,
4 = invokevirtual < Application, Lcom/android/server/VcnManagementService$Dependencies, getBinderCallingUid()I > 2 @2 exception:3,
conditional branch(eq, to iindex=-1) 4,5,
10 = invokestatic < Application, Landroid/os/UserHandle, getUserHandleForUid(I)Landroid/os/UserHandle; > 4 @10 exception:9,
12 = invokevirtual < Application, Landroid/os/UserHandle, isSystem()Z > 10 @14 exception:11,
conditional branch(eq, to iindex=-1) 12,13,
return,
6 = invokevirtual < Application, Lcom/android/server/VcnManagementService, isProvisioningPackageForConfig(Landroid/os/ParcelUuid;Ljava/lang/String;)Z > 1,2,3 @3 exception:5,
5 = invokestatic < Application, Landroid/os/Binder, clearCallingIdentity()J > @0 exception:4,
6 = getfield < Application, Lcom/android/server/VcnManagementService, mLock, <Application,Ljava/lang/Object> > 1,
monitorenter 6,
7 = getfield < Application, Lcom/android/server/VcnManagementService, mConfigs, <Application,Ljava/util/Map> > 1,
9 = invokeinterface < Application, Ljava/util/Map, get(Ljava/lang/Object;)Ljava/lang/Object; > 7,2 @9 exception:8,
10 = checkcast <Application,Landroid/net/vcn/VcnConfig>9 <Application,Landroid/net/vcn/VcnConfig>,
conditional branch(eq, to iindex=-1) 10,11,
13 = invokevirtual < Application, Landroid/net/vcn/VcnConfig, getProvisioningPackageName()Ljava/lang/String; > 10 @17 exception:12,
15 = invokevirtual < Application, Ljava/lang/String, equals(Ljava/lang/Object;)Z > 3,13 @21 exception:14,
conditional branch(eq, to iindex=-1) 15,11,
monitorexit 6,
invokestatic < Application, Landroid/os/Binder, restoreCallingIdentity(J)V > 5 @29 exception:30,
return 20,
conditional branch(eq, to iindex=-1) 6,7,
invokevirtual < Application, Lcom/android/server/VcnManagementService, enforceCallingUserAndCarrierPrivilege(Landroid/os/ParcelUuid;Ljava/lang/String;)V > 1,2,3 @10 exception:8,
invokevirtual < Application, Lcom/android/server/VcnManagementService, enforcePrimaryUser()V > 1 @0 exception:4,
5 = getfield < Application, Lcom/android/server/VcnManagementService, mContext, <Application,Landroid/content/Context> > 1,
6 = load_metadata: <Application,Landroid/telephony/SubscriptionManager>, <Primordial,Ljava/lang/Class>,
8 = invokevirtual < Application, Landroid/content/Context, getSystemService(Ljava/lang/Class;)Ljava/lang/Object; > 5,6 @7 exception:7,
9 = checkcast <Application,Landroid/telephony/SubscriptionManager>8 <Application,Landroid/telephony/SubscriptionManager>,
10 = new <Application,Ljava/util/ArrayList>@13,
invokespecial < Application, Ljava/util/ArrayList, <init>()V > 10 @15 exception:11,
12 = new <Application,Lcom/android/server/VcnManagementService$$ExternalSyntheticLambda11>@18,
invokespecial < Application, Lcom/android/server/VcnManagementService$$ExternalSyntheticLambda11, <init>(Ljava/util/List;Landroid/telephony/SubscriptionManager;Landroid/os/ParcelUuid;)V > 12,10,9,2 @20 exception:13,
invokestatic < Application, Landroid/os/Binder, withCleanCallingIdentity(Lcom/android/internal/util/FunctionalUtils$ThrowingRunnable;)V > 12 @23 exception:14,
16 = invokeinterface < Application, Ljava/util/List, iterator()Ljava/util/Iterator; > 10 @26 exception:15,
18 = invokeinterface < Application, Ljava/util/Iterator, hasNext()Z > 16 @30 exception:17,
conditional branch(eq, to iindex=-1) 18,19,
21 = invokeinterface < Application, Ljava/util/Iterator, next()Ljava/lang/Object; > 16 @36 exception:20,
22 = checkcast <Application,Landroid/telephony/SubscriptionInfo>21 <Application,Landroid/telephony/SubscriptionInfo>,
23 = getfield < Application, Lcom/android/server/VcnManagementService, mContext, <Application,Landroid/content/Context> > 1,
24 = load_metadata: <Application,Landroid/telephony/TelephonyManager>, <Primordial,Ljava/lang/Class>,
26 = invokevirtual < Application, Landroid/content/Context, getSystemService(Ljava/lang/Class;)Ljava/lang/Object; > 23,24 @46 exception:25,
27 = checkcast <Application,Landroid/telephony/TelephonyManager>26 <Application,Landroid/telephony/TelephonyManager>,
29 = invokevirtual < Application, Landroid/telephony/SubscriptionInfo, getSubscriptionId()I > 22 @52 exception:28,
31 = invokevirtual < Application, Landroid/telephony/TelephonyManager, createForSubscriptionId(I)Landroid/telephony/TelephonyManager; > 27,29 @56 exception:30,
33 = invokevirtual < Application, Landroid/telephony/SubscriptionInfo, getSimSlotIndex()I > 22 @60 exception:32,
35 = invokestatic < Application, Landroid/telephony/SubscriptionManager, isValidSlotIndex(I)Z > 33 @64 exception:34,
conditional branch(eq, to iindex=-1) 35,19,
42 = invokevirtual < Application, Landroid/telephony/TelephonyManager, checkCarrierPrivilegesForPackage(Ljava/lang/String;)I > 31,3 @70 exception:41,
conditional branch(ne, to iindex=-1) 42,43,
return,
return,
30 = new <Application,Lcom/android/server/VcnManagementService$$ExternalSyntheticLambda5>@54,
invokespecial < Application, Lcom/android/server/VcnManagementService$$ExternalSyntheticLambda5, <init>(Lcom/android/server/VcnManagementService;Landroid/os/ParcelUuid;)V > 30,1,2 @56 exception:31,
invokestatic < Application, Landroid/os/Binder, withCleanCallingIdentity(Lcom/android/internal/util/FunctionalUtils$ThrowingRunnable;)V > 30 @59 exception:32,
return,","depth : 0
public void clearVcnConfig(ParcelUuid p1, String p2){
	p0.enforceCarrierPrivilegeOrProvisioningPackage(p1, p2);
	VcnManagementService$$ExternalSyntheticLambda5 v11 = new VcnManagementService$$ExternalSyntheticLambda5(p0,p1);
	Binder.withCleanCallingIdentity(v11);
	return;
}
-----
depth : 1
public void enforceCarrierPrivilegeOrProvisioningPackage(ParcelUuid p1, String p2){
	p0.enforcePrimaryUser();
	boolean v2 = p0.isProvisioningPackageForConfig(p1, p2);
	p0.enforceCallingUserAndCarrierPrivilege(p1, p2);
	return;
}
-----
depth : 2
public void enforcePrimaryUser(){
	int v1 = this.mDeps.getBinderCallingUid();
	UserHandle v2 = UserHandle.getUserHandleForUid(v1);
	boolean v3 = v2.isSystem();
	return;
}
-----
depth : 2
public boolean isProvisioningPackageForConfig(ParcelUuid p1, String p2){
	long v1 = Binder.clearCallingIdentity();
	Object v2 = this.mConfigs.get(p1);
	String v3 = v2.getProvisioningPackageName();
	boolean v4 = p2.equals(v3);
	Binder.restoreCallingIdentity(v1);
	return 1;
}
-----
depth : 2
public void enforceCallingUserAndCarrierPrivilege(ParcelUuid p1, String p2){
	p0.enforcePrimaryUser();
	Object v2 = this.mContext.getSystemService(SubscriptionManage.class);
	ArrayList v2 = new ArrayList();
	VcnManagementService$$ExternalSyntheticLambda11 v3 = new VcnManagementService$$ExternalSyntheticLambda11(v2,v2,p1);
	Binder.withCleanCallingIdentity(v3);
	Iterator v6 = v2.iterator();
	boolean v7 = v6.hasNext();
	Object v8 = v6.next();
	Object v9 = this.mContext.getSystemService(TelephonyManage.class);
	int v10 = v8.getSubscriptionId();
	TelephonyManager v11 = v9.createForSubscriptionId(v10);
	int v12 = v8.getSimSlotIndex();
	boolean v13 = SubscriptionManager.isValidSlotIndex(v12);
	int v14 = v11.checkCarrierPrivilegesForPackage(p2);
	return;
}
-----
","public void clearVcnConfig(ParcelUuid p1, String p2){
	int v14 = this.mDeps.getBinderCallingUid();
	UserHandle v15 = UserHandle.getUserHandleForUid(v14);
	boolean v16 = v15.isSystem();
	long v18 = Binder.clearCallingIdentity();
	Object v19 = this.mConfigs.get(p1);
	String v20 = v19.getProvisioningPackageName();
	boolean v21 = p2.equals(v20);
	Binder.restoreCallingIdentity(v18);
	boolean v17 = 1;
	VcnManagementService.enforcePrimaryUser();
	Object v25 = this.mContext.getSystemService(SubscriptionManage.class);
	ArrayList v26 = new ArrayList();
	VcnManagementService$$ExternalSyntheticLambda11 v28 = new VcnManagementService$$ExternalSyntheticLambda11(v26,v25,p1);
	Binder.withCleanCallingIdentity(v28);
	Iterator v31 = v26.iterator();
	boolean v32 = v31.hasNext();
	Object v33 = v31.next();
	Object v34 = this.mContext.getSystemService(TelephonyManage.class);
	int v35 = v33.getSubscriptionId();
	TelephonyManager v36 = v34.createForSubscriptionId(v35);
	int v37 = v33.getSimSlotIndex();
	boolean v38 = SubscriptionManager.isValidSlotIndex(v37);
	int v39 = v36.checkCarrierPrivilegesForPackage(p2);
	VcnManagementService$$ExternalSyntheticLambda5 v40 = new VcnManagementService$$ExternalSyntheticLambda5(p0,p1);
	Binder.withCleanCallingIdentity(v40);
	return;
}
","NONE"
"Lcom/android/server/VcnManagementService","clearVcnConfig(Landroid/os/ParcelUuid;Ljava/lang/String;)V","2","6 = invokestatic < Application, Ljava/util/Objects, requireNonNull(Ljava/lang/Object;Ljava/lang/String;)Ljava/lang/Object; > 2,4 @3 exception:5,
9 = invokestatic < Application, Ljava/util/Objects, requireNonNull(Ljava/lang/Object;Ljava/lang/String;)Ljava/lang/Object; > 3,7 @9 exception:8,
10 = new <Application,Ljava/lang/StringBuilder>@12,
invokespecial < Application, Ljava/lang/StringBuilder, <init>()V > 10 @14 exception:11,
14 = invokevirtual < Application, Ljava/lang/StringBuilder, append(Ljava/lang/String;)Ljava/lang/StringBuilder; > 10,12 @19 exception:13,
16 = invokevirtual < Application, Ljava/lang/StringBuilder, append(Ljava/lang/Object;)Ljava/lang/StringBuilder; > 10,2 @22 exception:15,
18 = invokevirtual < Application, Ljava/lang/StringBuilder, toString()Ljava/lang/String; > 10 @25 exception:17,
invokevirtual < Application, Lcom/android/server/VcnManagementService, logInfo(Ljava/lang/String;)V > 1,18 @29 exception:19,
20 = getfield < Application, Lcom/android/server/VcnManagementService, mContext, <Application,Landroid/content/Context> > 1,
21 = load_metadata: <Application,Landroid/app/AppOpsManager>, <Primordial,Ljava/lang/Class>,
23 = invokevirtual < Application, Landroid/content/Context, getSystemService(Ljava/lang/Class;)Ljava/lang/Object; > 20,21 @36 exception:22,
24 = checkcast <Application,Landroid/app/AppOpsManager>23 <Application,Landroid/app/AppOpsManager>,
25 = getfield < Application, Lcom/android/server/VcnManagementService, mDeps, <Application,Lcom/android/server/VcnManagementService$Dependencies> > 1,
27 = invokevirtual < Application, Lcom/android/server/VcnManagementService$Dependencies, getBinderCallingUid()I > 25 @44 exception:26,
invokevirtual < Application, Landroid/app/AppOpsManager, checkPackage(ILjava/lang/String;)V > 24,27,3 @48 exception:28,
invokevirtual < Application, Lcom/android/server/VcnManagementService, enforceCarrierPrivilegeOrProvisioningPackage(Landroid/os/ParcelUuid;Ljava/lang/String;)V > 1,2,3 @51 exception:29,
invokevirtual < Application, Lcom/android/server/VcnManagementService, enforcePrimaryUser()V > 1 @0 exception:4,
2 = getfield < Application, Lcom/android/server/VcnManagementService, mDeps, <Application,Lcom/android/server/VcnManagementService$Dependencies> > 1,
4 = invokevirtual < Application, Lcom/android/server/VcnManagementService$Dependencies, getBinderCallingUid()I > 2 @2 exception:3,
conditional branch(eq, to iindex=-1) 4,5,
10 = invokestatic < Application, Landroid/os/UserHandle, getUserHandleForUid(I)Landroid/os/UserHandle; > 4 @10 exception:9,
12 = invokevirtual < Application, Landroid/os/UserHandle, isSystem()Z > 10 @14 exception:11,
conditional branch(eq, to iindex=-1) 12,13,
return,
6 = invokevirtual < Application, Lcom/android/server/VcnManagementService, isProvisioningPackageForConfig(Landroid/os/ParcelUuid;Ljava/lang/String;)Z > 1,2,3 @3 exception:5,
5 = invokestatic < Application, Landroid/os/Binder, clearCallingIdentity()J > @0 exception:4,
6 = getfield < Application, Lcom/android/server/VcnManagementService, mLock, <Application,Ljava/lang/Object> > 1,
monitorenter 6,
7 = getfield < Application, Lcom/android/server/VcnManagementService, mConfigs, <Application,Ljava/util/Map> > 1,
9 = invokeinterface < Application, Ljava/util/Map, get(Ljava/lang/Object;)Ljava/lang/Object; > 7,2 @9 exception:8,
10 = checkcast <Application,Landroid/net/vcn/VcnConfig>9 <Application,Landroid/net/vcn/VcnConfig>,
conditional branch(eq, to iindex=-1) 10,11,
13 = invokevirtual < Application, Landroid/net/vcn/VcnConfig, getProvisioningPackageName()Ljava/lang/String; > 10 @17 exception:12,
15 = invokevirtual < Application, Ljava/lang/String, equals(Ljava/lang/Object;)Z > 3,13 @21 exception:14,
conditional branch(eq, to iindex=-1) 15,11,
monitorexit 6,
invokestatic < Application, Landroid/os/Binder, restoreCallingIdentity(J)V > 5 @34 exception:19,
return 11,
conditional branch(eq, to iindex=-1) 6,7,
invokevirtual < Application, Lcom/android/server/VcnManagementService, enforceCallingUserAndCarrierPrivilege(Landroid/os/ParcelUuid;Ljava/lang/String;)V > 1,2,3 @10 exception:8,
invokevirtual < Application, Lcom/android/server/VcnManagementService, enforcePrimaryUser()V > 1 @0 exception:4,
5 = getfield < Application, Lcom/android/server/VcnManagementService, mContext, <Application,Landroid/content/Context> > 1,
6 = load_metadata: <Application,Landroid/telephony/SubscriptionManager>, <Primordial,Ljava/lang/Class>,
8 = invokevirtual < Application, Landroid/content/Context, getSystemService(Ljava/lang/Class;)Ljava/lang/Object; > 5,6 @7 exception:7,
9 = checkcast <Application,Landroid/telephony/SubscriptionManager>8 <Application,Landroid/telephony/SubscriptionManager>,
10 = new <Application,Ljava/util/ArrayList>@13,
invokespecial < Application, Ljava/util/ArrayList, <init>()V > 10 @15 exception:11,
12 = new <Application,Lcom/android/server/VcnManagementService$$ExternalSyntheticLambda11>@18,
invokespecial < Application, Lcom/android/server/VcnManagementService$$ExternalSyntheticLambda11, <init>(Ljava/util/List;Landroid/telephony/SubscriptionManager;Landroid/os/ParcelUuid;)V > 12,10,9,2 @20 exception:13,
invokestatic < Application, Landroid/os/Binder, withCleanCallingIdentity(Lcom/android/internal/util/FunctionalUtils$ThrowingRunnable;)V > 12 @23 exception:14,
16 = invokeinterface < Application, Ljava/util/List, iterator()Ljava/util/Iterator; > 10 @26 exception:15,
18 = invokeinterface < Application, Ljava/util/Iterator, hasNext()Z > 16 @30 exception:17,
conditional branch(eq, to iindex=-1) 18,19,
21 = invokeinterface < Application, Ljava/util/Iterator, next()Ljava/lang/Object; > 16 @36 exception:20,
22 = checkcast <Application,Landroid/telephony/SubscriptionInfo>21 <Application,Landroid/telephony/SubscriptionInfo>,
23 = getfield < Application, Lcom/android/server/VcnManagementService, mContext, <Application,Landroid/content/Context> > 1,
24 = load_metadata: <Application,Landroid/telephony/TelephonyManager>, <Primordial,Ljava/lang/Class>,
26 = invokevirtual < Application, Landroid/content/Context, getSystemService(Ljava/lang/Class;)Ljava/lang/Object; > 23,24 @46 exception:25,
27 = checkcast <Application,Landroid/telephony/TelephonyManager>26 <Application,Landroid/telephony/TelephonyManager>,
29 = invokevirtual < Application, Landroid/telephony/SubscriptionInfo, getSubscriptionId()I > 22 @52 exception:28,
31 = invokevirtual < Application, Landroid/telephony/TelephonyManager, createForSubscriptionId(I)Landroid/telephony/TelephonyManager; > 27,29 @56 exception:30,
33 = invokevirtual < Application, Landroid/telephony/SubscriptionInfo, getSimSlotIndex()I > 22 @60 exception:32,
35 = invokestatic < Application, Landroid/telephony/SubscriptionManager, isValidSlotIndex(I)Z > 33 @64 exception:34,
conditional branch(eq, to iindex=-1) 35,19,
42 = invokevirtual < Application, Landroid/telephony/TelephonyManager, checkCarrierPrivilegesForPackage(Ljava/lang/String;)I > 31,3 @70 exception:41,
conditional branch(ne, to iindex=-1) 42,43,
return,
return,
30 = new <Application,Lcom/android/server/VcnManagementService$$ExternalSyntheticLambda5>@54,
invokespecial < Application, Lcom/android/server/VcnManagementService$$ExternalSyntheticLambda5, <init>(Lcom/android/server/VcnManagementService;Landroid/os/ParcelUuid;)V > 30,1,2 @56 exception:31,
invokestatic < Application, Landroid/os/Binder, withCleanCallingIdentity(Lcom/android/internal/util/FunctionalUtils$ThrowingRunnable;)V > 30 @59 exception:32,
return,","depth : 0
public void clearVcnConfig(ParcelUuid p1, String p2){
	p0.enforceCarrierPrivilegeOrProvisioningPackage(p1, p2);
	VcnManagementService$$ExternalSyntheticLambda5 v11 = new VcnManagementService$$ExternalSyntheticLambda5(p0,p1);
	Binder.withCleanCallingIdentity(v11);
	return;
}
-----
depth : 1
public void enforceCarrierPrivilegeOrProvisioningPackage(ParcelUuid p1, String p2){
	p0.enforcePrimaryUser();
	boolean v2 = p0.isProvisioningPackageForConfig(p1, p2);
	p0.enforceCallingUserAndCarrierPrivilege(p1, p2);
	return;
}
-----
depth : 2
public void enforcePrimaryUser(){
	int v1 = this.mDeps.getBinderCallingUid();
	UserHandle v2 = UserHandle.getUserHandleForUid(v1);
	boolean v3 = v2.isSystem();
	return;
}
-----
depth : 2
public boolean isProvisioningPackageForConfig(ParcelUuid p1, String p2){
	long v1 = Binder.clearCallingIdentity();
	Object v2 = this.mConfigs.get(p1);
	String v3 = v2.getProvisioningPackageName();
	boolean v4 = p2.equals(v3);
	Binder.restoreCallingIdentity(v1);
	return 0;
}
-----
depth : 2
public void enforceCallingUserAndCarrierPrivilege(ParcelUuid p1, String p2){
	p0.enforcePrimaryUser();
	Object v2 = this.mContext.getSystemService(SubscriptionManage.class);
	ArrayList v2 = new ArrayList();
	VcnManagementService$$ExternalSyntheticLambda11 v3 = new VcnManagementService$$ExternalSyntheticLambda11(v2,v2,p1);
	Binder.withCleanCallingIdentity(v3);
	Iterator v6 = v2.iterator();
	boolean v7 = v6.hasNext();
	Object v8 = v6.next();
	Object v9 = this.mContext.getSystemService(TelephonyManage.class);
	int v10 = v8.getSubscriptionId();
	TelephonyManager v11 = v9.createForSubscriptionId(v10);
	int v12 = v8.getSimSlotIndex();
	boolean v13 = SubscriptionManager.isValidSlotIndex(v12);
	int v14 = v11.checkCarrierPrivilegesForPackage(p2);
	return;
}
-----
","public void clearVcnConfig(ParcelUuid p1, String p2){
	int v14 = this.mDeps.getBinderCallingUid();
	UserHandle v15 = UserHandle.getUserHandleForUid(v14);
	boolean v16 = v15.isSystem();
	long v18 = Binder.clearCallingIdentity();
	Object v19 = this.mConfigs.get(p1);
	String v20 = v19.getProvisioningPackageName();
	boolean v21 = p2.equals(v20);
	Binder.restoreCallingIdentity(v18);
	boolean v17 = 0;
	VcnManagementService.enforcePrimaryUser();
	Object v25 = this.mContext.getSystemService(SubscriptionManage.class);
	ArrayList v26 = new ArrayList();
	VcnManagementService$$ExternalSyntheticLambda11 v28 = new VcnManagementService$$ExternalSyntheticLambda11(v26,v25,p1);
	Binder.withCleanCallingIdentity(v28);
	Iterator v31 = v26.iterator();
	boolean v32 = v31.hasNext();
	Object v33 = v31.next();
	Object v34 = this.mContext.getSystemService(TelephonyManage.class);
	int v35 = v33.getSubscriptionId();
	TelephonyManager v36 = v34.createForSubscriptionId(v35);
	int v37 = v33.getSimSlotIndex();
	boolean v38 = SubscriptionManager.isValidSlotIndex(v37);
	int v39 = v36.checkCarrierPrivilegesForPackage(p2);
	VcnManagementService$$ExternalSyntheticLambda5 v40 = new VcnManagementService$$ExternalSyntheticLambda5(p0,p1);
	Binder.withCleanCallingIdentity(v40);
	return;
}
","NONE"

"Lcom/android/server/VcnManagementService","addVcnUnderlyingNetworkPolicyListener(Landroid/net/vcn/IVcnUnderlyingNetworkPolicyListener;)V","0","5 = invokestatic < Application, Ljava/util/Objects, requireNonNull(Ljava/lang/Object;Ljava/lang/String;)Ljava/lang/Object; > 2,3 @2 exception:4,
6 = getfield < Application, Lcom/android/server/VcnManagementService, mContext, <Application,Landroid/content/Context> > 1,
9 = new <Application,[Ljava/lang/String>@1110 ,
invokestatic < Application, Lcom/android/net/module/util/PermissionUtils, enforceAnyPermissionOf(Landroid/content/Context;[Ljava/lang/String;)V > 6,9 @15 exception:11,
12 = new <Application,Lcom/android/server/VcnManagementService$$ExternalSyntheticLambda2>@18,
invokespecial < Application, Lcom/android/server/VcnManagementService$$ExternalSyntheticLambda2, <init>(Lcom/android/server/VcnManagementService;Landroid/net/vcn/IVcnUnderlyingNetworkPolicyListener;)V > 12,1,2 @20 exception:13,
invokestatic < Application, Landroid/os/Binder, withCleanCallingIdentity(Lcom/android/internal/util/FunctionalUtils$ThrowingRunnable;)V > 12 @23 exception:14,
return,","depth : 0
public void addVcnUnderlyingNetworkPolicyListener(IVcnUnderlyingNetworkPolicyListener p1){
	VcnManagementService$$ExternalSyntheticLambda2 v2 = new VcnManagementService$$ExternalSyntheticLambda2(p0,p1);
	Binder.withCleanCallingIdentity(v2);
	return;
}
-----
","public void addVcnUnderlyingNetworkPolicyListener(IVcnUnderlyingNetworkPolicyListener p1){
	VcnManagementService$$ExternalSyntheticLambda2 v4 = new VcnManagementService$$ExternalSyntheticLambda2(p0,p1);
	Binder.withCleanCallingIdentity(v4);
	return;
}
","NORMAL"

"Lcom/android/server/VcnManagementService","removeVcnUnderlyingNetworkPolicyListener(Landroid/net/vcn/IVcnUnderlyingNetworkPolicyListener;)V","0","5 = invokestatic < Application, Ljava/util/Objects, requireNonNull(Ljava/lang/Object;Ljava/lang/String;)Ljava/lang/Object; > 2,3 @2 exception:4,
6 = getfield < Application, Lcom/android/server/VcnManagementService, mContext, <Application,Landroid/content/Context> > 1,
9 = new <Application,[Ljava/lang/String>@1110 ,
invokestatic < Application, Lcom/android/net/module/util/PermissionUtils, enforceAnyPermissionOf(Landroid/content/Context;[Ljava/lang/String;)V > 6,9 @15 exception:11,
12 = new <Application,Lcom/android/server/VcnManagementService$$ExternalSyntheticLambda3>@18,
invokespecial < Application, Lcom/android/server/VcnManagementService$$ExternalSyntheticLambda3, <init>(Lcom/android/server/VcnManagementService;Landroid/net/vcn/IVcnUnderlyingNetworkPolicyListener;)V > 12,1,2 @20 exception:13,
invokestatic < Application, Landroid/os/Binder, withCleanCallingIdentity(Lcom/android/internal/util/FunctionalUtils$ThrowingRunnable;)V > 12 @23 exception:14,
return,","depth : 0
public void removeVcnUnderlyingNetworkPolicyListener(IVcnUnderlyingNetworkPolicyListener p1){
	VcnManagementService$$ExternalSyntheticLambda3 v2 = new VcnManagementService$$ExternalSyntheticLambda3(p0,p1);
	Binder.withCleanCallingIdentity(v2);
	return;
}
-----
","public void removeVcnUnderlyingNetworkPolicyListener(IVcnUnderlyingNetworkPolicyListener p1){
	VcnManagementService$$ExternalSyntheticLambda3 v4 = new VcnManagementService$$ExternalSyntheticLambda3(p0,p1);
	Binder.withCleanCallingIdentity(v4);
	return;
}
","NORMAL"

"Lcom/android/server/VcnManagementService","setVcnConfig(Landroid/os/ParcelUuid;Landroid/net/vcn/VcnConfig;Ljava/lang/String;)V","0","7 = invokestatic < Application, Ljava/util/Objects, requireNonNull(Ljava/lang/Object;Ljava/lang/String;)Ljava/lang/Object; > 2,5 @3 exception:6,
10 = invokestatic < Application, Ljava/util/Objects, requireNonNull(Ljava/lang/Object;Ljava/lang/String;)Ljava/lang/Object; > 3,8 @8 exception:9,
13 = invokestatic < Application, Ljava/util/Objects, requireNonNull(Ljava/lang/Object;Ljava/lang/String;)Ljava/lang/Object; > 4,11 @14 exception:12,
15 = invokevirtual < Application, Landroid/net/vcn/VcnConfig, getProvisioningPackageName()Ljava/lang/String; > 3 @17 exception:14,
17 = invokevirtual < Application, Ljava/lang/String, equals(Ljava/lang/Object;)Z > 15,4 @21 exception:16,
conditional branch(eq, to iindex=-1) 17,18,
22 = new <Application,Ljava/lang/StringBuilder>@27,
invokespecial < Application, Ljava/lang/StringBuilder, <init>()V > 22 @29 exception:23,
26 = invokevirtual < Application, Ljava/lang/StringBuilder, append(Ljava/lang/String;)Ljava/lang/StringBuilder; > 22,24 @34 exception:25,
28 = invokevirtual < Application, Ljava/lang/StringBuilder, append(Ljava/lang/Object;)Ljava/lang/StringBuilder; > 22,2 @37 exception:27,
30 = invokevirtual < Application, Ljava/lang/StringBuilder, toString()Ljava/lang/String; > 22 @40 exception:29,
invokevirtual < Application, Lcom/android/server/VcnManagementService, logInfo(Ljava/lang/String;)V > 1,30 @44 exception:31,
32 = getfield < Application, Lcom/android/server/VcnManagementService, mContext, <Application,Landroid/content/Context> > 1,
33 = load_metadata: <Application,Landroid/app/AppOpsManager>, <Primordial,Ljava/lang/Class>,
35 = invokevirtual < Application, Landroid/content/Context, getSystemService(Ljava/lang/Class;)Ljava/lang/Object; > 32,33 @51 exception:34,
36 = checkcast <Application,Landroid/app/AppOpsManager>35 <Application,Landroid/app/AppOpsManager>,
37 = getfield < Application, Lcom/android/server/VcnManagementService, mDeps, <Application,Lcom/android/server/VcnManagementService$Dependencies> > 1,
39 = invokevirtual < Application, Lcom/android/server/VcnManagementService$Dependencies, getBinderCallingUid()I > 37 @59 exception:38,
41 = invokevirtual < Application, Landroid/net/vcn/VcnConfig, getProvisioningPackageName()Ljava/lang/String; > 3 @63 exception:40,
invokevirtual < Application, Landroid/app/AppOpsManager, checkPackage(ILjava/lang/String;)V > 36,39,41 @67 exception:42,
invokevirtual < Application, Lcom/android/server/VcnManagementService, enforceManageTestNetworksForTestMode(Landroid/net/vcn/VcnConfig;)V > 1,3 @70 exception:43,
invokevirtual < Application, Lcom/android/server/VcnManagementService, enforceCallingUserAndCarrierPrivilege(Landroid/os/ParcelUuid;Ljava/lang/String;)V > 1,2,4 @73 exception:44,
45 = new <Application,Lcom/android/server/VcnManagementService$$ExternalSyntheticLambda4>@76,
invokespecial < Application, Lcom/android/server/VcnManagementService$$ExternalSyntheticLambda4, <init>(Lcom/android/server/VcnManagementService;Landroid/os/ParcelUuid;Landroid/net/vcn/VcnConfig;)V > 45,1,2,3 @78 exception:46,
invokestatic < Application, Landroid/os/Binder, withCleanCallingIdentity(Lcom/android/internal/util/FunctionalUtils$ThrowingRunnable;)V > 45 @81 exception:47,
return,","depth : 0
public void setVcnConfig(ParcelUuid p1, VcnConfig p2, String p3){
	p0.enforceManageTestNetworksForTestMode(p2);
	p0.enforceCallingUserAndCarrierPrivilege(p1, p3);
	VcnManagementService$$ExternalSyntheticLambda4 v16 = new VcnManagementService$$ExternalSyntheticLambda4(p0,p1,p2);
	Binder.withCleanCallingIdentity(v16);
	return;
}
-----
","public void setVcnConfig(ParcelUuid p1, VcnConfig p2, String p3){
	p0.enforceManageTestNetworksForTestMode(p2);
	p0.enforceCallingUserAndCarrierPrivilege(p1, p3);
	VcnManagementService$$ExternalSyntheticLambda4 v18 = new VcnManagementService$$ExternalSyntheticLambda4(p0,p1,p2);
	Binder.withCleanCallingIdentity(v18);
	return;
}
","SYS_OR_SIG"
"Lcom/android/server/VcnManagementService","setVcnConfig(Landroid/os/ParcelUuid;Landroid/net/vcn/VcnConfig;Ljava/lang/String;)V","1","7 = invokestatic < Application, Ljava/util/Objects, requireNonNull(Ljava/lang/Object;Ljava/lang/String;)Ljava/lang/Object; > 2,5 @3 exception:6,
10 = invokestatic < Application, Ljava/util/Objects, requireNonNull(Ljava/lang/Object;Ljava/lang/String;)Ljava/lang/Object; > 3,8 @8 exception:9,
13 = invokestatic < Application, Ljava/util/Objects, requireNonNull(Ljava/lang/Object;Ljava/lang/String;)Ljava/lang/Object; > 4,11 @14 exception:12,
15 = invokevirtual < Application, Landroid/net/vcn/VcnConfig, getProvisioningPackageName()Ljava/lang/String; > 3 @17 exception:14,
17 = invokevirtual < Application, Ljava/lang/String, equals(Ljava/lang/Object;)Z > 15,4 @21 exception:16,
conditional branch(eq, to iindex=-1) 17,18,
22 = new <Application,Ljava/lang/StringBuilder>@27,
invokespecial < Application, Ljava/lang/StringBuilder, <init>()V > 22 @29 exception:23,
26 = invokevirtual < Application, Ljava/lang/StringBuilder, append(Ljava/lang/String;)Ljava/lang/StringBuilder; > 22,24 @34 exception:25,
28 = invokevirtual < Application, Ljava/lang/StringBuilder, append(Ljava/lang/Object;)Ljava/lang/StringBuilder; > 22,2 @37 exception:27,
30 = invokevirtual < Application, Ljava/lang/StringBuilder, toString()Ljava/lang/String; > 22 @40 exception:29,
invokevirtual < Application, Lcom/android/server/VcnManagementService, logInfo(Ljava/lang/String;)V > 1,30 @44 exception:31,
32 = getfield < Application, Lcom/android/server/VcnManagementService, mContext, <Application,Landroid/content/Context> > 1,
33 = load_metadata: <Application,Landroid/app/AppOpsManager>, <Primordial,Ljava/lang/Class>,
35 = invokevirtual < Application, Landroid/content/Context, getSystemService(Ljava/lang/Class;)Ljava/lang/Object; > 32,33 @51 exception:34,
36 = checkcast <Application,Landroid/app/AppOpsManager>35 <Application,Landroid/app/AppOpsManager>,
37 = getfield < Application, Lcom/android/server/VcnManagementService, mDeps, <Application,Lcom/android/server/VcnManagementService$Dependencies> > 1,
39 = invokevirtual < Application, Lcom/android/server/VcnManagementService$Dependencies, getBinderCallingUid()I > 37 @59 exception:38,
41 = invokevirtual < Application, Landroid/net/vcn/VcnConfig, getProvisioningPackageName()Ljava/lang/String; > 3 @63 exception:40,
invokevirtual < Application, Landroid/app/AppOpsManager, checkPackage(ILjava/lang/String;)V > 36,39,41 @67 exception:42,
invokevirtual < Application, Lcom/android/server/VcnManagementService, enforceManageTestNetworksForTestMode(Landroid/net/vcn/VcnConfig;)V > 1,3 @70 exception:43,
4 = invokevirtual < Application, Landroid/net/vcn/VcnConfig, isTestModeProfile()Z > 2 @0 exception:3,
conditional branch(eq, to iindex=-1) 4,5,
6 = getfield < Application, Lcom/android/server/VcnManagementService, mContext, <Application,Landroid/content/Context> > 1,
invokevirtual < Application, Landroid/content/Context, enforceCallingPermission(Ljava/lang/String;Ljava/lang/String;)V > 6,7,8 @12 exception:9,
return,
invokevirtual < Application, Lcom/android/server/VcnManagementService, enforceCallingUserAndCarrierPrivilege(Landroid/os/ParcelUuid;Ljava/lang/String;)V > 1,2,4 @73 exception:44,
invokevirtual < Application, Lcom/android/server/VcnManagementService, enforcePrimaryUser()V > 1 @0 exception:4,
5 = getfield < Application, Lcom/android/server/VcnManagementService, mContext, <Application,Landroid/content/Context> > 1,
6 = load_metadata: <Application,Landroid/telephony/SubscriptionManager>, <Primordial,Ljava/lang/Class>,
8 = invokevirtual < Application, Landroid/content/Context, getSystemService(Ljava/lang/Class;)Ljava/lang/Object; > 5,6 @7 exception:7,
9 = checkcast <Application,Landroid/telephony/SubscriptionManager>8 <Application,Landroid/telephony/SubscriptionManager>,
10 = new <Application,Ljava/util/ArrayList>@13,
invokespecial < Application, Ljava/util/ArrayList, <init>()V > 10 @15 exception:11,
12 = new <Application,Lcom/android/server/VcnManagementService$$ExternalSyntheticLambda11>@18,
invokespecial < Application, Lcom/android/server/VcnManagementService$$ExternalSyntheticLambda11, <init>(Ljava/util/List;Landroid/telephony/SubscriptionManager;Landroid/os/ParcelUuid;)V > 12,10,9,2 @20 exception:13,
invokestatic < Application, Landroid/os/Binder, withCleanCallingIdentity(Lcom/android/internal/util/FunctionalUtils$ThrowingRunnable;)V > 12 @23 exception:14,
16 = invokeinterface < Application, Ljava/util/List, iterator()Ljava/util/Iterator; > 10 @26 exception:15,
18 = invokeinterface < Application, Ljava/util/Iterator, hasNext()Z > 16 @30 exception:17,
conditional branch(eq, to iindex=-1) 18,19,
21 = invokeinterface < Application, Ljava/util/Iterator, next()Ljava/lang/Object; > 16 @36 exception:20,
22 = checkcast <Application,Landroid/telephony/SubscriptionInfo>21 <Application,Landroid/telephony/SubscriptionInfo>,
23 = getfield < Application, Lcom/android/server/VcnManagementService, mContext, <Application,Landroid/content/Context> > 1,
24 = load_metadata: <Application,Landroid/telephony/TelephonyManager>, <Primordial,Ljava/lang/Class>,
26 = invokevirtual < Application, Landroid/content/Context, getSystemService(Ljava/lang/Class;)Ljava/lang/Object; > 23,24 @46 exception:25,
27 = checkcast <Application,Landroid/telephony/TelephonyManager>26 <Application,Landroid/telephony/TelephonyManager>,
29 = invokevirtual < Application, Landroid/telephony/SubscriptionInfo, getSubscriptionId()I > 22 @52 exception:28,
31 = invokevirtual < Application, Landroid/telephony/TelephonyManager, createForSubscriptionId(I)Landroid/telephony/TelephonyManager; > 27,29 @56 exception:30,
33 = invokevirtual < Application, Landroid/telephony/SubscriptionInfo, getSimSlotIndex()I > 22 @60 exception:32,
35 = invokestatic < Application, Landroid/telephony/SubscriptionManager, isValidSlotIndex(I)Z > 33 @64 exception:34,
conditional branch(eq, to iindex=-1) 35,19,
42 = invokevirtual < Application, Landroid/telephony/TelephonyManager, checkCarrierPrivilegesForPackage(Ljava/lang/String;)I > 31,3 @70 exception:41,
conditional branch(ne, to iindex=-1) 42,43,
return,
45 = new <Application,Lcom/android/server/VcnManagementService$$ExternalSyntheticLambda4>@76,
invokespecial < Application, Lcom/android/server/VcnManagementService$$ExternalSyntheticLambda4, <init>(Lcom/android/server/VcnManagementService;Landroid/os/ParcelUuid;Landroid/net/vcn/VcnConfig;)V > 45,1,2,3 @78 exception:46,
invokestatic < Application, Landroid/os/Binder, withCleanCallingIdentity(Lcom/android/internal/util/FunctionalUtils$ThrowingRunnable;)V > 45 @81 exception:47,
return,","depth : 0
public void setVcnConfig(ParcelUuid p1, VcnConfig p2, String p3){
	p0.enforceManageTestNetworksForTestMode(p2);
	p0.enforceCallingUserAndCarrierPrivilege(p1, p3);
	VcnManagementService$$ExternalSyntheticLambda4 v16 = new VcnManagementService$$ExternalSyntheticLambda4(p0,p1,p2);
	Binder.withCleanCallingIdentity(v16);
	return;
}
-----
depth : 1
public void enforceManageTestNetworksForTestMode(VcnConfig p1){
	return;
}
-----
depth : 1
public void enforceCallingUserAndCarrierPrivilege(ParcelUuid p1, String p2){
	p0.enforcePrimaryUser();
	Object v2 = this.mContext.getSystemService(SubscriptionManage.class);
	ArrayList v2 = new ArrayList();
	VcnManagementService$$ExternalSyntheticLambda11 v3 = new VcnManagementService$$ExternalSyntheticLambda11(v2,v2,p1);
	Binder.withCleanCallingIdentity(v3);
	Iterator v6 = v2.iterator();
	boolean v7 = v6.hasNext();
	Object v8 = v6.next();
	Object v9 = this.mContext.getSystemService(TelephonyManage.class);
	int v10 = v8.getSubscriptionId();
	TelephonyManager v11 = v9.createForSubscriptionId(v10);
	int v12 = v8.getSimSlotIndex();
	boolean v13 = SubscriptionManager.isValidSlotIndex(v12);
	int v14 = v11.checkCarrierPrivilegesForPackage(p2);
	return;
}
-----
","public void setVcnConfig(ParcelUuid p1, VcnConfig p2, String p3){
	VcnManagementService.enforcePrimaryUser();
	Object v21 = this.mContext.getSystemService(SubscriptionManage.class);
	ArrayList v22 = new ArrayList();
	VcnManagementService$$ExternalSyntheticLambda11 v24 = new VcnManagementService$$ExternalSyntheticLambda11(v22,v21,p1);
	Binder.withCleanCallingIdentity(v24);
	Iterator v27 = v22.iterator();
	boolean v28 = v27.hasNext();
	Object v29 = v27.next();
	Object v30 = this.mContext.getSystemService(TelephonyManage.class);
	int v31 = v29.getSubscriptionId();
	TelephonyManager v32 = v30.createForSubscriptionId(v31);
	int v33 = v29.getSimSlotIndex();
	boolean v34 = SubscriptionManager.isValidSlotIndex(v33);
	int v35 = v32.checkCarrierPrivilegesForPackage(p3);
	VcnManagementService$$ExternalSyntheticLambda4 v36 = new VcnManagementService$$ExternalSyntheticLambda4(p0,p1,p2);
	Binder.withCleanCallingIdentity(v36);
	return;
}
","SYS_OR_SIG"
"Lcom/android/server/VcnManagementService","setVcnConfig(Landroid/os/ParcelUuid;Landroid/net/vcn/VcnConfig;Ljava/lang/String;)V","1","7 = invokestatic < Application, Ljava/util/Objects, requireNonNull(Ljava/lang/Object;Ljava/lang/String;)Ljava/lang/Object; > 2,5 @3 exception:6,
10 = invokestatic < Application, Ljava/util/Objects, requireNonNull(Ljava/lang/Object;Ljava/lang/String;)Ljava/lang/Object; > 3,8 @8 exception:9,
13 = invokestatic < Application, Ljava/util/Objects, requireNonNull(Ljava/lang/Object;Ljava/lang/String;)Ljava/lang/Object; > 4,11 @14 exception:12,
15 = invokevirtual < Application, Landroid/net/vcn/VcnConfig, getProvisioningPackageName()Ljava/lang/String; > 3 @17 exception:14,
17 = invokevirtual < Application, Ljava/lang/String, equals(Ljava/lang/Object;)Z > 15,4 @21 exception:16,
conditional branch(eq, to iindex=-1) 17,18,
22 = new <Application,Ljava/lang/StringBuilder>@27,
invokespecial < Application, Ljava/lang/StringBuilder, <init>()V > 22 @29 exception:23,
26 = invokevirtual < Application, Ljava/lang/StringBuilder, append(Ljava/lang/String;)Ljava/lang/StringBuilder; > 22,24 @34 exception:25,
28 = invokevirtual < Application, Ljava/lang/StringBuilder, append(Ljava/lang/Object;)Ljava/lang/StringBuilder; > 22,2 @37 exception:27,
30 = invokevirtual < Application, Ljava/lang/StringBuilder, toString()Ljava/lang/String; > 22 @40 exception:29,
invokevirtual < Application, Lcom/android/server/VcnManagementService, logInfo(Ljava/lang/String;)V > 1,30 @44 exception:31,
32 = getfield < Application, Lcom/android/server/VcnManagementService, mContext, <Application,Landroid/content/Context> > 1,
33 = load_metadata: <Application,Landroid/app/AppOpsManager>, <Primordial,Ljava/lang/Class>,
35 = invokevirtual < Application, Landroid/content/Context, getSystemService(Ljava/lang/Class;)Ljava/lang/Object; > 32,33 @51 exception:34,
36 = checkcast <Application,Landroid/app/AppOpsManager>35 <Application,Landroid/app/AppOpsManager>,
37 = getfield < Application, Lcom/android/server/VcnManagementService, mDeps, <Application,Lcom/android/server/VcnManagementService$Dependencies> > 1,
39 = invokevirtual < Application, Lcom/android/server/VcnManagementService$Dependencies, getBinderCallingUid()I > 37 @59 exception:38,
41 = invokevirtual < Application, Landroid/net/vcn/VcnConfig, getProvisioningPackageName()Ljava/lang/String; > 3 @63 exception:40,
invokevirtual < Application, Landroid/app/AppOpsManager, checkPackage(ILjava/lang/String;)V > 36,39,41 @67 exception:42,
invokevirtual < Application, Lcom/android/server/VcnManagementService, enforceManageTestNetworksForTestMode(Landroid/net/vcn/VcnConfig;)V > 1,3 @70 exception:43,
4 = invokevirtual < Application, Landroid/net/vcn/VcnConfig, isTestModeProfile()Z > 2 @0 exception:3,
conditional branch(eq, to iindex=-1) 4,5,
return,
invokevirtual < Application, Lcom/android/server/VcnManagementService, enforceCallingUserAndCarrierPrivilege(Landroid/os/ParcelUuid;Ljava/lang/String;)V > 1,2,4 @73 exception:44,
invokevirtual < Application, Lcom/android/server/VcnManagementService, enforcePrimaryUser()V > 1 @0 exception:4,
5 = getfield < Application, Lcom/android/server/VcnManagementService, mContext, <Application,Landroid/content/Context> > 1,
6 = load_metadata: <Application,Landroid/telephony/SubscriptionManager>, <Primordial,Ljava/lang/Class>,
8 = invokevirtual < Application, Landroid/content/Context, getSystemService(Ljava/lang/Class;)Ljava/lang/Object; > 5,6 @7 exception:7,
9 = checkcast <Application,Landroid/telephony/SubscriptionManager>8 <Application,Landroid/telephony/SubscriptionManager>,
10 = new <Application,Ljava/util/ArrayList>@13,
invokespecial < Application, Ljava/util/ArrayList, <init>()V > 10 @15 exception:11,
12 = new <Application,Lcom/android/server/VcnManagementService$$ExternalSyntheticLambda11>@18,
invokespecial < Application, Lcom/android/server/VcnManagementService$$ExternalSyntheticLambda11, <init>(Ljava/util/List;Landroid/telephony/SubscriptionManager;Landroid/os/ParcelUuid;)V > 12,10,9,2 @20 exception:13,
invokestatic < Application, Landroid/os/Binder, withCleanCallingIdentity(Lcom/android/internal/util/FunctionalUtils$ThrowingRunnable;)V > 12 @23 exception:14,
16 = invokeinterface < Application, Ljava/util/List, iterator()Ljava/util/Iterator; > 10 @26 exception:15,
18 = invokeinterface < Application, Ljava/util/Iterator, hasNext()Z > 16 @30 exception:17,
conditional branch(eq, to iindex=-1) 18,19,
21 = invokeinterface < Application, Ljava/util/Iterator, next()Ljava/lang/Object; > 16 @36 exception:20,
22 = checkcast <Application,Landroid/telephony/SubscriptionInfo>21 <Application,Landroid/telephony/SubscriptionInfo>,
23 = getfield < Application, Lcom/android/server/VcnManagementService, mContext, <Application,Landroid/content/Context> > 1,
24 = load_metadata: <Application,Landroid/telephony/TelephonyManager>, <Primordial,Ljava/lang/Class>,
26 = invokevirtual < Application, Landroid/content/Context, getSystemService(Ljava/lang/Class;)Ljava/lang/Object; > 23,24 @46 exception:25,
27 = checkcast <Application,Landroid/telephony/TelephonyManager>26 <Application,Landroid/telephony/TelephonyManager>,
29 = invokevirtual < Application, Landroid/telephony/SubscriptionInfo, getSubscriptionId()I > 22 @52 exception:28,
31 = invokevirtual < Application, Landroid/telephony/TelephonyManager, createForSubscriptionId(I)Landroid/telephony/TelephonyManager; > 27,29 @56 exception:30,
33 = invokevirtual < Application, Landroid/telephony/SubscriptionInfo, getSimSlotIndex()I > 22 @60 exception:32,
35 = invokestatic < Application, Landroid/telephony/SubscriptionManager, isValidSlotIndex(I)Z > 33 @64 exception:34,
conditional branch(eq, to iindex=-1) 35,19,
42 = invokevirtual < Application, Landroid/telephony/TelephonyManager, checkCarrierPrivilegesForPackage(Ljava/lang/String;)I > 31,3 @70 exception:41,
conditional branch(ne, to iindex=-1) 42,43,
return,
45 = new <Application,Lcom/android/server/VcnManagementService$$ExternalSyntheticLambda4>@76,
invokespecial < Application, Lcom/android/server/VcnManagementService$$ExternalSyntheticLambda4, <init>(Lcom/android/server/VcnManagementService;Landroid/os/ParcelUuid;Landroid/net/vcn/VcnConfig;)V > 45,1,2,3 @78 exception:46,
invokestatic < Application, Landroid/os/Binder, withCleanCallingIdentity(Lcom/android/internal/util/FunctionalUtils$ThrowingRunnable;)V > 45 @81 exception:47,
return,","depth : 0
public void setVcnConfig(ParcelUuid p1, VcnConfig p2, String p3){
	p0.enforceManageTestNetworksForTestMode(p2);
	p0.enforceCallingUserAndCarrierPrivilege(p1, p3);
	VcnManagementService$$ExternalSyntheticLambda4 v16 = new VcnManagementService$$ExternalSyntheticLambda4(p0,p1,p2);
	Binder.withCleanCallingIdentity(v16);
	return;
}
-----
depth : 1
public void enforceManageTestNetworksForTestMode(VcnConfig p1){
	boolean v1 = p1.isTestModeProfile();
	return;
}
-----
depth : 1
public void enforceCallingUserAndCarrierPrivilege(ParcelUuid p1, String p2){
	p0.enforcePrimaryUser();
	Object v2 = this.mContext.getSystemService(SubscriptionManage.class);
	ArrayList v2 = new ArrayList();
	VcnManagementService$$ExternalSyntheticLambda11 v3 = new VcnManagementService$$ExternalSyntheticLambda11(v2,v2,p1);
	Binder.withCleanCallingIdentity(v3);
	Iterator v6 = v2.iterator();
	boolean v7 = v6.hasNext();
	Object v8 = v6.next();
	Object v9 = this.mContext.getSystemService(TelephonyManage.class);
	int v10 = v8.getSubscriptionId();
	TelephonyManager v11 = v9.createForSubscriptionId(v10);
	int v12 = v8.getSimSlotIndex();
	boolean v13 = SubscriptionManager.isValidSlotIndex(v12);
	int v14 = v11.checkCarrierPrivilegesForPackage(p2);
	return;
}
-----
","public void setVcnConfig(ParcelUuid p1, VcnConfig p2, String p3){
	boolean v17 = p2.isTestModeProfile();
	VcnManagementService.enforcePrimaryUser();
	Object v20 = this.mContext.getSystemService(SubscriptionManage.class);
	ArrayList v21 = new ArrayList();
	VcnManagementService$$ExternalSyntheticLambda11 v23 = new VcnManagementService$$ExternalSyntheticLambda11(v21,v20,p1);
	Binder.withCleanCallingIdentity(v23);
	Iterator v26 = v21.iterator();
	boolean v27 = v26.hasNext();
	Object v28 = v26.next();
	Object v29 = this.mContext.getSystemService(TelephonyManage.class);
	int v30 = v28.getSubscriptionId();
	TelephonyManager v31 = v29.createForSubscriptionId(v30);
	int v32 = v28.getSimSlotIndex();
	boolean v33 = SubscriptionManager.isValidSlotIndex(v32);
	int v34 = v31.checkCarrierPrivilegesForPackage(p3);
	VcnManagementService$$ExternalSyntheticLambda4 v35 = new VcnManagementService$$ExternalSyntheticLambda4(p0,p1,p2);
	Binder.withCleanCallingIdentity(v35);
	return;
}
","SYS_OR_SIG"
"Lcom/android/server/VcnManagementService","setVcnConfig(Landroid/os/ParcelUuid;Landroid/net/vcn/VcnConfig;Ljava/lang/String;)V","2","7 = invokestatic < Application, Ljava/util/Objects, requireNonNull(Ljava/lang/Object;Ljava/lang/String;)Ljava/lang/Object; > 2,5 @3 exception:6,
10 = invokestatic < Application, Ljava/util/Objects, requireNonNull(Ljava/lang/Object;Ljava/lang/String;)Ljava/lang/Object; > 3,8 @8 exception:9,
13 = invokestatic < Application, Ljava/util/Objects, requireNonNull(Ljava/lang/Object;Ljava/lang/String;)Ljava/lang/Object; > 4,11 @14 exception:12,
15 = invokevirtual < Application, Landroid/net/vcn/VcnConfig, getProvisioningPackageName()Ljava/lang/String; > 3 @17 exception:14,
17 = invokevirtual < Application, Ljava/lang/String, equals(Ljava/lang/Object;)Z > 15,4 @21 exception:16,
conditional branch(eq, to iindex=-1) 17,18,
22 = new <Application,Ljava/lang/StringBuilder>@27,
invokespecial < Application, Ljava/lang/StringBuilder, <init>()V > 22 @29 exception:23,
26 = invokevirtual < Application, Ljava/lang/StringBuilder, append(Ljava/lang/String;)Ljava/lang/StringBuilder; > 22,24 @34 exception:25,
28 = invokevirtual < Application, Ljava/lang/StringBuilder, append(Ljava/lang/Object;)Ljava/lang/StringBuilder; > 22,2 @37 exception:27,
30 = invokevirtual < Application, Ljava/lang/StringBuilder, toString()Ljava/lang/String; > 22 @40 exception:29,
invokevirtual < Application, Lcom/android/server/VcnManagementService, logInfo(Ljava/lang/String;)V > 1,30 @44 exception:31,
32 = getfield < Application, Lcom/android/server/VcnManagementService, mContext, <Application,Landroid/content/Context> > 1,
33 = load_metadata: <Application,Landroid/app/AppOpsManager>, <Primordial,Ljava/lang/Class>,
35 = invokevirtual < Application, Landroid/content/Context, getSystemService(Ljava/lang/Class;)Ljava/lang/Object; > 32,33 @51 exception:34,
36 = checkcast <Application,Landroid/app/AppOpsManager>35 <Application,Landroid/app/AppOpsManager>,
37 = getfield < Application, Lcom/android/server/VcnManagementService, mDeps, <Application,Lcom/android/server/VcnManagementService$Dependencies> > 1,
39 = invokevirtual < Application, Lcom/android/server/VcnManagementService$Dependencies, getBinderCallingUid()I > 37 @59 exception:38,
41 = invokevirtual < Application, Landroid/net/vcn/VcnConfig, getProvisioningPackageName()Ljava/lang/String; > 3 @63 exception:40,
invokevirtual < Application, Landroid/app/AppOpsManager, checkPackage(ILjava/lang/String;)V > 36,39,41 @67 exception:42,
invokevirtual < Application, Lcom/android/server/VcnManagementService, enforceManageTestNetworksForTestMode(Landroid/net/vcn/VcnConfig;)V > 1,3 @70 exception:43,
4 = invokevirtual < Application, Landroid/net/vcn/VcnConfig, isTestModeProfile()Z > 2 @0 exception:3,
2 = getfield < Application, Landroid/net/vcn/VcnConfig, mIsTestModeProfile, <Primordial,Z> > 1,
return 2,
conditional branch(eq, to iindex=-1) 4,5,
return,
invokevirtual < Application, Lcom/android/server/VcnManagementService, enforceCallingUserAndCarrierPrivilege(Landroid/os/ParcelUuid;Ljava/lang/String;)V > 1,2,4 @73 exception:44,
invokevirtual < Application, Lcom/android/server/VcnManagementService, enforcePrimaryUser()V > 1 @0 exception:4,
2 = getfield < Application, Lcom/android/server/VcnManagementService, mDeps, <Application,Lcom/android/server/VcnManagementService$Dependencies> > 1,
4 = invokevirtual < Application, Lcom/android/server/VcnManagementService$Dependencies, getBinderCallingUid()I > 2 @2 exception:3,
conditional branch(eq, to iindex=-1) 4,5,
10 = invokestatic < Application, Landroid/os/UserHandle, getUserHandleForUid(I)Landroid/os/UserHandle; > 4 @10 exception:9,
12 = invokevirtual < Application, Landroid/os/UserHandle, isSystem()Z > 10 @14 exception:11,
conditional branch(eq, to iindex=-1) 12,13,
return,
5 = getfield < Application, Lcom/android/server/VcnManagementService, mContext, <Application,Landroid/content/Context> > 1,
6 = load_metadata: <Application,Landroid/telephony/SubscriptionManager>, <Primordial,Ljava/lang/Class>,
8 = invokevirtual < Application, Landroid/content/Context, getSystemService(Ljava/lang/Class;)Ljava/lang/Object; > 5,6 @7 exception:7,
9 = checkcast <Application,Landroid/telephony/SubscriptionManager>8 <Application,Landroid/telephony/SubscriptionManager>,
10 = new <Application,Ljava/util/ArrayList>@13,
invokespecial < Application, Ljava/util/ArrayList, <init>()V > 10 @15 exception:11,
12 = new <Application,Lcom/android/server/VcnManagementService$$ExternalSyntheticLambda11>@18,
invokespecial < Application, Lcom/android/server/VcnManagementService$$ExternalSyntheticLambda11, <init>(Ljava/util/List;Landroid/telephony/SubscriptionManager;Landroid/os/ParcelUuid;)V > 12,10,9,2 @20 exception:13,
invokestatic < Application, Landroid/os/Binder, withCleanCallingIdentity(Lcom/android/internal/util/FunctionalUtils$ThrowingRunnable;)V > 12 @23 exception:14,
16 = invokeinterface < Application, Ljava/util/List, iterator()Ljava/util/Iterator; > 10 @26 exception:15,
18 = invokeinterface < Application, Ljava/util/Iterator, hasNext()Z > 16 @30 exception:17,
conditional branch(eq, to iindex=-1) 18,19,
21 = invokeinterface < Application, Ljava/util/Iterator, next()Ljava/lang/Object; > 16 @36 exception:20,
22 = checkcast <Application,Landroid/telephony/SubscriptionInfo>21 <Application,Landroid/telephony/SubscriptionInfo>,
23 = getfield < Application, Lcom/android/server/VcnManagementService, mContext, <Application,Landroid/content/Context> > 1,
24 = load_metadata: <Application,Landroid/telephony/TelephonyManager>, <Primordial,Ljava/lang/Class>,
26 = invokevirtual < Application, Landroid/content/Context, getSystemService(Ljava/lang/Class;)Ljava/lang/Object; > 23,24 @46 exception:25,
27 = checkcast <Application,Landroid/telephony/TelephonyManager>26 <Application,Landroid/telephony/TelephonyManager>,
29 = invokevirtual < Application, Landroid/telephony/SubscriptionInfo, getSubscriptionId()I > 22 @52 exception:28,
31 = invokevirtual < Application, Landroid/telephony/TelephonyManager, createForSubscriptionId(I)Landroid/telephony/TelephonyManager; > 27,29 @56 exception:30,
33 = invokevirtual < Application, Landroid/telephony/SubscriptionInfo, getSimSlotIndex()I > 22 @60 exception:32,
35 = invokestatic < Application, Landroid/telephony/SubscriptionManager, isValidSlotIndex(I)Z > 33 @64 exception:34,
conditional branch(eq, to iindex=-1) 35,19,
42 = invokevirtual < Application, Landroid/telephony/TelephonyManager, checkCarrierPrivilegesForPackage(Ljava/lang/String;)I > 31,3 @70 exception:41,
conditional branch(ne, to iindex=-1) 42,43,
return,
45 = new <Application,Lcom/android/server/VcnManagementService$$ExternalSyntheticLambda4>@76,
invokespecial < Application, Lcom/android/server/VcnManagementService$$ExternalSyntheticLambda4, <init>(Lcom/android/server/VcnManagementService;Landroid/os/ParcelUuid;Landroid/net/vcn/VcnConfig;)V > 45,1,2,3 @78 exception:46,
invokestatic < Application, Landroid/os/Binder, withCleanCallingIdentity(Lcom/android/internal/util/FunctionalUtils$ThrowingRunnable;)V > 45 @81 exception:47,
return,","depth : 0
public void setVcnConfig(ParcelUuid p1, VcnConfig p2, String p3){
	p0.enforceManageTestNetworksForTestMode(p2);
	p0.enforceCallingUserAndCarrierPrivilege(p1, p3);
	VcnManagementService$$ExternalSyntheticLambda4 v16 = new VcnManagementService$$ExternalSyntheticLambda4(p0,p1,p2);
	Binder.withCleanCallingIdentity(v16);
	return;
}
-----
depth : 1
public void enforceManageTestNetworksForTestMode(VcnConfig p1){
	boolean v1 = p1.isTestModeProfile();
	return;
}
-----
depth : 2
public boolean isTestModeProfile(){
	return this.mIsTestModeProfile;
}
-----
depth : 1
public void enforceCallingUserAndCarrierPrivilege(ParcelUuid p1, String p2){
	p0.enforcePrimaryUser();
	Object v2 = this.mContext.getSystemService(SubscriptionManage.class);
	ArrayList v2 = new ArrayList();
	VcnManagementService$$ExternalSyntheticLambda11 v3 = new VcnManagementService$$ExternalSyntheticLambda11(v2,v2,p1);
	Binder.withCleanCallingIdentity(v3);
	Iterator v6 = v2.iterator();
	boolean v7 = v6.hasNext();
	Object v8 = v6.next();
	Object v9 = this.mContext.getSystemService(TelephonyManage.class);
	int v10 = v8.getSubscriptionId();
	TelephonyManager v11 = v9.createForSubscriptionId(v10);
	int v12 = v8.getSimSlotIndex();
	boolean v13 = SubscriptionManager.isValidSlotIndex(v12);
	int v14 = v11.checkCarrierPrivilegesForPackage(p2);
	return;
}
-----
depth : 2
public void enforcePrimaryUser(){
	int v1 = this.mDeps.getBinderCallingUid();
	UserHandle v2 = UserHandle.getUserHandleForUid(v1);
	boolean v3 = v2.isSystem();
	return;
}
-----
","public void setVcnConfig(ParcelUuid p1, VcnConfig p2, String p3){
	boolean v17 = this.mIsTestModeProfile;
	int v20 = this.mDeps.getBinderCallingUid();
	UserHandle v21 = UserHandle.getUserHandleForUid(v20);
	boolean v22 = v21.isSystem();
	Object v23 = this.mContext.getSystemService(SubscriptionManage.class);
	ArrayList v24 = new ArrayList();
	VcnManagementService$$ExternalSyntheticLambda11 v26 = new VcnManagementService$$ExternalSyntheticLambda11(v24,v23,p1);
	Binder.withCleanCallingIdentity(v26);
	Iterator v29 = v24.iterator();
	boolean v30 = v29.hasNext();
	Object v31 = v29.next();
	Object v32 = this.mContext.getSystemService(TelephonyManage.class);
	int v33 = v31.getSubscriptionId();
	TelephonyManager v34 = v32.createForSubscriptionId(v33);
	int v35 = v31.getSimSlotIndex();
	boolean v36 = SubscriptionManager.isValidSlotIndex(v35);
	int v37 = v34.checkCarrierPrivilegesForPackage(p3);
	VcnManagementService$$ExternalSyntheticLambda4 v38 = new VcnManagementService$$ExternalSyntheticLambda4(p0,p1,p2);
	Binder.withCleanCallingIdentity(v38);
	return;
}
","SYS_OR_SIG"

"Lcom/android/server/VcnManagementService","getConfiguredSubscriptionGroups(Ljava/lang/String;)Ljava/util/List;","0","5 = invokestatic < Application, Ljava/util/Objects, requireNonNull(Ljava/lang/Object;Ljava/lang/String;)Ljava/lang/Object; > 2,3 @3 exception:4,
6 = getfield < Application, Lcom/android/server/VcnManagementService, mContext, <Application,Landroid/content/Context> > 1,
7 = load_metadata: <Application,Landroid/app/AppOpsManager>, <Primordial,Ljava/lang/Class>,
9 = invokevirtual < Application, Landroid/content/Context, getSystemService(Ljava/lang/Class;)Ljava/lang/Object; > 6,7 @10 exception:8,
10 = checkcast <Application,Landroid/app/AppOpsManager>9 <Application,Landroid/app/AppOpsManager>,
11 = getfield < Application, Lcom/android/server/VcnManagementService, mDeps, <Application,Lcom/android/server/VcnManagementService$Dependencies> > 1,
13 = invokevirtual < Application, Lcom/android/server/VcnManagementService$Dependencies, getBinderCallingUid()I > 11 @18 exception:12,
invokevirtual < Application, Landroid/app/AppOpsManager, checkPackage(ILjava/lang/String;)V > 10,13,2 @22 exception:14,
invokevirtual < Application, Lcom/android/server/VcnManagementService, enforcePrimaryUser()V > 1 @25 exception:15,
16 = new <Application,Ljava/util/ArrayList>@28,
invokespecial < Application, Ljava/util/ArrayList, <init>()V > 16 @30 exception:17,
18 = getfield < Application, Lcom/android/server/VcnManagementService, mLock, <Application,Ljava/lang/Object> > 1,
monitorenter 18,
19 = getfield < Application, Lcom/android/server/VcnManagementService, mConfigs, <Application,Ljava/util/Map> > 1,
21 = invokeinterface < Application, Ljava/util/Map, keySet()Ljava/util/Set; > 19 @38 exception:20,
23 = invokeinterface < Application, Ljava/util/Set, iterator()Ljava/util/Iterator; > 21 @42 exception:22,
25 = invokeinterface < Application, Ljava/util/Iterator, hasNext()Z > 23 @46 exception:24,
conditional branch(eq, to iindex=-1) 25,26,
monitorexit 18,
return 16,","depth : 0
public List getConfiguredSubscriptionGroups(String p1){
	p0.enforcePrimaryUser();
	ArrayList v5 = new ArrayList();
	Set v7 = this.mConfigs.keySet();
	Iterator v8 = v7.iterator();
	boolean v9 = v8.hasNext();
	return v5;
}
-----
","public List getConfiguredSubscriptionGroups(String p1){
	p0.enforcePrimaryUser();
	ArrayList v6 = new ArrayList();
	Set v8 = this.mConfigs.keySet();
	Iterator v9 = v8.iterator();
	boolean v10 = v9.hasNext();
	return v6;
}
","NONE"
"Lcom/android/server/VcnManagementService","getConfiguredSubscriptionGroups(Ljava/lang/String;)Ljava/util/List;","1","5 = invokestatic < Application, Ljava/util/Objects, requireNonNull(Ljava/lang/Object;Ljava/lang/String;)Ljava/lang/Object; > 2,3 @3 exception:4,
6 = getfield < Application, Lcom/android/server/VcnManagementService, mContext, <Application,Landroid/content/Context> > 1,
7 = load_metadata: <Application,Landroid/app/AppOpsManager>, <Primordial,Ljava/lang/Class>,
9 = invokevirtual < Application, Landroid/content/Context, getSystemService(Ljava/lang/Class;)Ljava/lang/Object; > 6,7 @10 exception:8,
10 = checkcast <Application,Landroid/app/AppOpsManager>9 <Application,Landroid/app/AppOpsManager>,
11 = getfield < Application, Lcom/android/server/VcnManagementService, mDeps, <Application,Lcom/android/server/VcnManagementService$Dependencies> > 1,
13 = invokevirtual < Application, Lcom/android/server/VcnManagementService$Dependencies, getBinderCallingUid()I > 11 @18 exception:12,
invokevirtual < Application, Landroid/app/AppOpsManager, checkPackage(ILjava/lang/String;)V > 10,13,2 @22 exception:14,
invokevirtual < Application, Lcom/android/server/VcnManagementService, enforcePrimaryUser()V > 1 @25 exception:15,
2 = getfield < Application, Lcom/android/server/VcnManagementService, mDeps, <Application,Lcom/android/server/VcnManagementService$Dependencies> > 1,
4 = invokevirtual < Application, Lcom/android/server/VcnManagementService$Dependencies, getBinderCallingUid()I > 2 @2 exception:3,
conditional branch(eq, to iindex=-1) 4,5,
10 = invokestatic < Application, Landroid/os/UserHandle, getUserHandleForUid(I)Landroid/os/UserHandle; > 4 @10 exception:9,
12 = invokevirtual < Application, Landroid/os/UserHandle, isSystem()Z > 10 @14 exception:11,
conditional branch(eq, to iindex=-1) 12,13,
return,
16 = new <Application,Ljava/util/ArrayList>@28,
invokespecial < Application, Ljava/util/ArrayList, <init>()V > 16 @30 exception:17,
18 = getfield < Application, Lcom/android/server/VcnManagementService, mLock, <Application,Ljava/lang/Object> > 1,
monitorenter 18,
19 = getfield < Application, Lcom/android/server/VcnManagementService, mConfigs, <Application,Ljava/util/Map> > 1,
21 = invokeinterface < Application, Ljava/util/Map, keySet()Ljava/util/Set; > 19 @38 exception:20,
23 = invokeinterface < Application, Ljava/util/Set, iterator()Ljava/util/Iterator; > 21 @42 exception:22,
25 = invokeinterface < Application, Ljava/util/Iterator, hasNext()Z > 23 @46 exception:24,
conditional branch(eq, to iindex=-1) 25,26,
monitorexit 18,
return 16,","depth : 0
public List getConfiguredSubscriptionGroups(String p1){
	p0.enforcePrimaryUser();
	ArrayList v5 = new ArrayList();
	Set v7 = this.mConfigs.keySet();
	Iterator v8 = v7.iterator();
	boolean v9 = v8.hasNext();
	return v5;
}
-----
depth : 1
public void enforcePrimaryUser(){
	int v1 = this.mDeps.getBinderCallingUid();
	UserHandle v2 = UserHandle.getUserHandleForUid(v1);
	boolean v3 = v2.isSystem();
	return;
}
-----
","public List getConfiguredSubscriptionGroups(String p1){
	int v6 = this.mDeps.getBinderCallingUid();
	UserHandle v7 = UserHandle.getUserHandleForUid(v6);
	boolean v8 = v7.isSystem();
	ArrayList v9 = new ArrayList();
	Set v11 = this.mConfigs.keySet();
	Iterator v12 = v11.iterator();
	boolean v13 = v12.hasNext();
	return v9;
}
","NONE"
"Lcom/android/server/VcnManagementService","getConfiguredSubscriptionGroups(Ljava/lang/String;)Ljava/util/List;","2","5 = invokestatic < Application, Ljava/util/Objects, requireNonNull(Ljava/lang/Object;Ljava/lang/String;)Ljava/lang/Object; > 2,3 @3 exception:4,
6 = getfield < Application, Lcom/android/server/VcnManagementService, mContext, <Application,Landroid/content/Context> > 1,
7 = load_metadata: <Application,Landroid/app/AppOpsManager>, <Primordial,Ljava/lang/Class>,
9 = invokevirtual < Application, Landroid/content/Context, getSystemService(Ljava/lang/Class;)Ljava/lang/Object; > 6,7 @10 exception:8,
10 = checkcast <Application,Landroid/app/AppOpsManager>9 <Application,Landroid/app/AppOpsManager>,
11 = getfield < Application, Lcom/android/server/VcnManagementService, mDeps, <Application,Lcom/android/server/VcnManagementService$Dependencies> > 1,
13 = invokevirtual < Application, Lcom/android/server/VcnManagementService$Dependencies, getBinderCallingUid()I > 11 @18 exception:12,
invokevirtual < Application, Landroid/app/AppOpsManager, checkPackage(ILjava/lang/String;)V > 10,13,2 @22 exception:14,
invokevirtual < Application, Lcom/android/server/VcnManagementService, enforcePrimaryUser()V > 1 @25 exception:15,
2 = getfield < Application, Lcom/android/server/VcnManagementService, mDeps, <Application,Lcom/android/server/VcnManagementService$Dependencies> > 1,
4 = invokevirtual < Application, Lcom/android/server/VcnManagementService$Dependencies, getBinderCallingUid()I > 2 @2 exception:3,
3 = invokestatic < Application, Landroid/os/Binder, getCallingUid()I > @0 exception:2,
return 3,
conditional branch(eq, to iindex=-1) 4,5,
10 = invokestatic < Application, Landroid/os/UserHandle, getUserHandleForUid(I)Landroid/os/UserHandle; > 4 @10 exception:9,
12 = invokevirtual < Application, Landroid/os/UserHandle, isSystem()Z > 10 @14 exception:11,
conditional branch(eq, to iindex=-1) 12,13,
return,
16 = new <Application,Ljava/util/ArrayList>@28,
invokespecial < Application, Ljava/util/ArrayList, <init>()V > 16 @30 exception:17,
18 = getfield < Application, Lcom/android/server/VcnManagementService, mLock, <Application,Ljava/lang/Object> > 1,
monitorenter 18,
19 = getfield < Application, Lcom/android/server/VcnManagementService, mConfigs, <Application,Ljava/util/Map> > 1,
21 = invokeinterface < Application, Ljava/util/Map, keySet()Ljava/util/Set; > 19 @38 exception:20,
23 = invokeinterface < Application, Ljava/util/Set, iterator()Ljava/util/Iterator; > 21 @42 exception:22,
25 = invokeinterface < Application, Ljava/util/Iterator, hasNext()Z > 23 @46 exception:24,
conditional branch(eq, to iindex=-1) 25,26,
monitorexit 18,
return 16,","depth : 0
public List getConfiguredSubscriptionGroups(String p1){
	p0.enforcePrimaryUser();
	ArrayList v5 = new ArrayList();
	Set v7 = this.mConfigs.keySet();
	Iterator v8 = v7.iterator();
	boolean v9 = v8.hasNext();
	return v5;
}
-----
depth : 1
public void enforcePrimaryUser(){
	int v1 = this.mDeps.getBinderCallingUid();
	UserHandle v2 = UserHandle.getUserHandleForUid(v1);
	boolean v3 = v2.isSystem();
	return;
}
-----
depth : 2
public int getBinderCallingUid(){
	int v1 = Binder.getCallingUid();
	return v1;
}
-----
","public List getConfiguredSubscriptionGroups(String p1){
	int v7 = Binder.getCallingUid();
	int v6 = v7;
	UserHandle v8 = UserHandle.getUserHandleForUid(v6);
	boolean v9 = v8.isSystem();
	ArrayList v10 = new ArrayList();
	Set v12 = this.mConfigs.keySet();
	Iterator v13 = v12.iterator();
	boolean v14 = v13.hasNext();
	return v10;
}
","NONE"

"Lcom/android/server/VcnManagementService","registerVcnStatusCallback(Landroid/os/ParcelUuid;Landroid/net/vcn/IVcnStatusCallback;Ljava/lang/String;)V","0","5 = getfield < Application, Lcom/android/server/VcnManagementService, mDeps, <Application,Lcom/android/server/VcnManagementService$Dependencies> > 1,
7 = invokevirtual < Application, Lcom/android/server/VcnManagementService$Dependencies, getBinderCallingUid()I > 5 @2 exception:6,
9 = invokestatic < Application, Landroid/os/Binder, clearCallingIdentity()J > @6 exception:8,
12 = invokestatic < Application, Ljava/util/Objects, requireNonNull(Ljava/lang/Object;Ljava/lang/String;)Ljava/lang/Object; > 2,10 @13 exception:11,
15 = invokestatic < Application, Ljava/util/Objects, requireNonNull(Ljava/lang/Object;Ljava/lang/String;)Ljava/lang/Object; > 3,13 @18 exception:14,
18 = invokestatic < Application, Ljava/util/Objects, requireNonNull(Ljava/lang/Object;Ljava/lang/String;)Ljava/lang/Object; > 4,16 @24 exception:17,
19 = getfield < Application, Lcom/android/server/VcnManagementService, mContext, <Application,Landroid/content/Context> > 1,
20 = load_metadata: <Application,Landroid/app/AppOpsManager>, <Primordial,Ljava/lang/Class>,
22 = invokevirtual < Application, Landroid/content/Context, getSystemService(Ljava/lang/Class;)Ljava/lang/Object; > 19,20 @31 exception:21,
23 = checkcast <Application,Landroid/app/AppOpsManager>22 <Application,Landroid/app/AppOpsManager>,
invokevirtual < Application, Landroid/app/AppOpsManager, checkPackage(ILjava/lang/String;)V > 23,7,4 @37 exception:24,
26 = invokeinterface < Application, Landroid/net/vcn/IVcnStatusCallback, asBinder()Landroid/os/IBinder; > 3 @40 exception:25,
27 = new <Application,Lcom/android/server/VcnManagementService$VcnStatusCallbackInfo>@44,
invokespecial < Application, Lcom/android/server/VcnManagementService$VcnStatusCallbackInfo, <init>(Lcom/android/server/VcnManagementService;Landroid/os/ParcelUuid;Landroid/net/vcn/IVcnStatusCallback;Ljava/lang/String;ILcom/android/server/VcnManagementService$VcnStatusCallbackInfo-IA;)V > 27,1,2,3,4,7,28 @52 exception:29,
invokeinterface < Application, Landroid/os/IBinder, linkToDeath(Landroid/os/IBinder$DeathRecipient;I)V > 26,27,28 @56 exception:30,
32 = getfield < Application, Lcom/android/server/VcnManagementService, mLock, <Application,Ljava/lang/Object> > 1,
monitorenter 32,
33 = getfield < Application, Lcom/android/server/VcnManagementService, mRegisteredStatusCallbacks, <Application,Ljava/util/Map> > 1,
35 = invokeinterface < Application, Ljava/util/Map, containsKey(Ljava/lang/Object;)Z > 33,26 @64 exception:34,
conditional branch(ne, to iindex=-1) 35,28,
39 = getfield < Application, Lcom/android/server/VcnManagementService, mRegisteredStatusCallbacks, <Application,Ljava/util/Map> > 1,
41 = invokeinterface < Application, Ljava/util/Map, put(Ljava/lang/Object;Ljava/lang/Object;)Ljava/lang/Object; > 39,26,27 @72 exception:40,
42 = getfield < Application, Lcom/android/server/VcnManagementService, mConfigs, <Application,Ljava/util/Map> > 1,
44 = invokeinterface < Application, Ljava/util/Map, get(Ljava/lang/Object;)Ljava/lang/Object; > 42,2 @77 exception:43,
45 = checkcast <Application,Landroid/net/vcn/VcnConfig>44 <Application,Landroid/net/vcn/VcnConfig>,
46 = getfield < Application, Lcom/android/server/VcnManagementService, mVcns, <Application,Ljava/util/Map> > 1,
48 = invokeinterface < Application, Ljava/util/Map, get(Ljava/lang/Object;)Ljava/lang/Object; > 46,2 @85 exception:47,
49 = checkcast <Application,Lcom/android/server/vcn/Vcn>48 <Application,Lcom/android/server/vcn/Vcn>,
conditional branch(ne, to iindex=-1) 49,28,
goto (from iindex= 47 to iindex = 5),
52 = phi  28,51,
conditional branch(eq, to iindex=-1) 45,28,
56 = invokevirtual < Application, Lcom/android/server/VcnManagementService, isCallbackPermissioned(Lcom/android/server/VcnManagementService$VcnStatusCallbackInfo;Landroid/os/ParcelUuid;)Z > 1,27,2 @101 exception:55,
conditional branch(ne, to iindex=-1) 56,28,
conditional branch(ne, to iindex=-1) 49,28,
conditional branch(eq, to iindex=-1) 52,57,
conditional branch(ne, to iindex=-1) 52,58,
goto (from iindex= 62 to iindex = 22),
73 = phi  28,28,70,28,52,
76 = getfield < Application, Lcom/android/server/VcnManagementService$VcnStatusCallbackInfo, mCallback, <Application,Landroid/net/vcn/IVcnStatusCallback> > 27,
invokeinterface < Application, Landroid/net/vcn/IVcnStatusCallback, onVcnStatusChanged(I)V > 76,73 @143 exception:77,
78 = getCaughtException ,
invokevirtual < Application, Lcom/android/server/VcnManagementService, logDbg(Ljava/lang/String;Ljava/lang/Throwable;)V > 1,79,78 @150 exception:80,
monitorexit 32,
invokestatic < Application, Landroid/os/Binder, restoreCallingIdentity(J)V > 9 @154 exception:104,
return,","depth : 0
public void registerVcnStatusCallback(ParcelUuid p1, IVcnStatusCallback p2, String p3){
	IBinder v8 = p2.asBinder();
	VcnManagementService$VcnStatusCallbackInfo v8 = new VcnManagementService$VcnStatusCallbackInfo(p0,p1,p2,p3,v1,0);
	v8.linkToDeath(v8, 0);
	boolean v11 = this.mRegisteredStatusCallbacks.containsKey(v8);
	Object v12 = this.mRegisteredStatusCallbacks.put(v8, v8);
	Object v13 = this.mConfigs.get(p1);
	Object v14 = this.mVcns.get(p1);
	boolean v15 = p0.isCallbackPermissioned(v8, p1);
	VcnManagementService$VcnStatusCallbackInfo.mCallback.onVcnStatusChanged(phiInstruction);
	p0.logDbg(""VcnStatusCallback threw on VCN status change"", caughtException);
	Binder.restoreCallingIdentity(v2);
	return;
}
-----
","public void registerVcnStatusCallback(ParcelUuid p1, IVcnStatusCallback p2, String p3){
	IBinder v8 = p2.asBinder();
	VcnManagementService$VcnStatusCallbackInfo v9 = new VcnManagementService$VcnStatusCallbackInfo(p0,p1,p2,p3,v1,0);
	v8.linkToDeath(v9, 0);
	boolean v12 = this.mRegisteredStatusCallbacks.containsKey(v8);
	Object v13 = this.mRegisteredStatusCallbacks.put(v8, v9);
	Object v14 = this.mConfigs.get(p1);
	Object v15 = this.mVcns.get(p1);
	boolean v16 = p0.isCallbackPermissioned(v9, p1);
	VcnManagementService$VcnStatusCallbackInfo.mCallback.onVcnStatusChanged(phiInstruction);
	p0.logDbg(""VcnStatusCallback threw on VCN status change"", caughtException);
	Binder.restoreCallingIdentity(v2);
	return;
}
","NONE"
"Lcom/android/server/VcnManagementService","registerVcnStatusCallback(Landroid/os/ParcelUuid;Landroid/net/vcn/IVcnStatusCallback;Ljava/lang/String;)V","1","5 = getfield < Application, Lcom/android/server/VcnManagementService, mDeps, <Application,Lcom/android/server/VcnManagementService$Dependencies> > 1,
7 = invokevirtual < Application, Lcom/android/server/VcnManagementService$Dependencies, getBinderCallingUid()I > 5 @2 exception:6,
9 = invokestatic < Application, Landroid/os/Binder, clearCallingIdentity()J > @6 exception:8,
12 = invokestatic < Application, Ljava/util/Objects, requireNonNull(Ljava/lang/Object;Ljava/lang/String;)Ljava/lang/Object; > 2,10 @13 exception:11,
15 = invokestatic < Application, Ljava/util/Objects, requireNonNull(Ljava/lang/Object;Ljava/lang/String;)Ljava/lang/Object; > 3,13 @18 exception:14,
18 = invokestatic < Application, Ljava/util/Objects, requireNonNull(Ljava/lang/Object;Ljava/lang/String;)Ljava/lang/Object; > 4,16 @24 exception:17,
19 = getfield < Application, Lcom/android/server/VcnManagementService, mContext, <Application,Landroid/content/Context> > 1,
20 = load_metadata: <Application,Landroid/app/AppOpsManager>, <Primordial,Ljava/lang/Class>,
22 = invokevirtual < Application, Landroid/content/Context, getSystemService(Ljava/lang/Class;)Ljava/lang/Object; > 19,20 @31 exception:21,
23 = checkcast <Application,Landroid/app/AppOpsManager>22 <Application,Landroid/app/AppOpsManager>,
invokevirtual < Application, Landroid/app/AppOpsManager, checkPackage(ILjava/lang/String;)V > 23,7,4 @37 exception:24,
26 = invokeinterface < Application, Landroid/net/vcn/IVcnStatusCallback, asBinder()Landroid/os/IBinder; > 3 @40 exception:25,
27 = new <Application,Lcom/android/server/VcnManagementService$VcnStatusCallbackInfo>@44,
invokespecial < Application, Lcom/android/server/VcnManagementService$VcnStatusCallbackInfo, <init>(Lcom/android/server/VcnManagementService;Landroid/os/ParcelUuid;Landroid/net/vcn/IVcnStatusCallback;Ljava/lang/String;ILcom/android/server/VcnManagementService$VcnStatusCallbackInfo-IA;)V > 27,1,2,3,4,7,28 @52 exception:29,
invokeinterface < Application, Landroid/os/IBinder, linkToDeath(Landroid/os/IBinder$DeathRecipient;I)V > 26,27,28 @56 exception:30,
32 = getfield < Application, Lcom/android/server/VcnManagementService, mLock, <Application,Ljava/lang/Object> > 1,
monitorenter 32,
33 = getfield < Application, Lcom/android/server/VcnManagementService, mRegisteredStatusCallbacks, <Application,Ljava/util/Map> > 1,
35 = invokeinterface < Application, Ljava/util/Map, containsKey(Ljava/lang/Object;)Z > 33,26 @64 exception:34,
conditional branch(ne, to iindex=-1) 35,28,
39 = getfield < Application, Lcom/android/server/VcnManagementService, mRegisteredStatusCallbacks, <Application,Ljava/util/Map> > 1,
41 = invokeinterface < Application, Ljava/util/Map, put(Ljava/lang/Object;Ljava/lang/Object;)Ljava/lang/Object; > 39,26,27 @72 exception:40,
42 = getfield < Application, Lcom/android/server/VcnManagementService, mConfigs, <Application,Ljava/util/Map> > 1,
44 = invokeinterface < Application, Ljava/util/Map, get(Ljava/lang/Object;)Ljava/lang/Object; > 42,2 @77 exception:43,
45 = checkcast <Application,Landroid/net/vcn/VcnConfig>44 <Application,Landroid/net/vcn/VcnConfig>,
46 = getfield < Application, Lcom/android/server/VcnManagementService, mVcns, <Application,Ljava/util/Map> > 1,
48 = invokeinterface < Application, Ljava/util/Map, get(Ljava/lang/Object;)Ljava/lang/Object; > 46,2 @85 exception:47,
49 = checkcast <Application,Lcom/android/server/vcn/Vcn>48 <Application,Lcom/android/server/vcn/Vcn>,
conditional branch(ne, to iindex=-1) 49,28,
goto (from iindex= 47 to iindex = 5),
52 = phi  28,51,
conditional branch(eq, to iindex=-1) 45,28,
56 = invokevirtual < Application, Lcom/android/server/VcnManagementService, isCallbackPermissioned(Lcom/android/server/VcnManagementService$VcnStatusCallbackInfo;Landroid/os/ParcelUuid;)Z > 1,27,2 @101 exception:55,
4 = getfield < Application, Lcom/android/server/VcnManagementService$VcnStatusCallbackInfo, mSubGroup, <Application,Landroid/os/ParcelUuid> > 2,
6 = invokevirtual < Application, Landroid/os/ParcelUuid, equals(Ljava/lang/Object;)Z > 3,4 @2 exception:5,
conditional branch(ne, to iindex=-1) 6,7,
8 = getfield < Application, Lcom/android/server/VcnManagementService, mLastSnapshot, <Application,Lcom/android/server/vcn/TelephonySubscriptionTracker$TelephonySubscriptionSnapshot> > 1,
9 = getfield < Application, Lcom/android/server/VcnManagementService$VcnStatusCallbackInfo, mPkgName, <Application,Ljava/lang/String> > 2,
11 = invokevirtual < Application, Lcom/android/server/vcn/TelephonySubscriptionTracker$TelephonySubscriptionSnapshot, packageHasPermissionsForSubscriptionGroup(Landroid/os/ParcelUuid;Ljava/lang/String;)Z > 8,3,9 @14 exception:10,
conditional branch(ne, to iindex=-1) 11,7,
return 7,
conditional branch(ne, to iindex=-1) 56,28,
conditional branch(ne, to iindex=-1) 49,28,
conditional branch(eq, to iindex=-1) 52,57,
conditional branch(ne, to iindex=-1) 52,58,
goto (from iindex= 62 to iindex = 22),
73 = phi  28,28,70,28,52,
76 = getfield < Application, Lcom/android/server/VcnManagementService$VcnStatusCallbackInfo, mCallback, <Application,Landroid/net/vcn/IVcnStatusCallback> > 27,
invokeinterface < Application, Landroid/net/vcn/IVcnStatusCallback, onVcnStatusChanged(I)V > 76,73 @143 exception:77,
78 = getCaughtException ,
invokevirtual < Application, Lcom/android/server/VcnManagementService, logDbg(Ljava/lang/String;Ljava/lang/Throwable;)V > 1,79,78 @150 exception:80,
4 = getstatic < Application, Lcom/android/server/VcnManagementService, TAG, <Application,Ljava/lang/String> >,
6 = invokestatic < Application, Landroid/util/Slog, d(Ljava/lang/String;Ljava/lang/String;Ljava/lang/Throwable;)I > 4,2,3 @2 exception:5,
return,
monitorexit 32,
invokestatic < Application, Landroid/os/Binder, restoreCallingIdentity(J)V > 9 @154 exception:104,
return,","depth : 0
public void registerVcnStatusCallback(ParcelUuid p1, IVcnStatusCallback p2, String p3){
	IBinder v8 = p2.asBinder();
	VcnManagementService$VcnStatusCallbackInfo v8 = new VcnManagementService$VcnStatusCallbackInfo(p0,p1,p2,p3,v1,0);
	v8.linkToDeath(v8, 0);
	boolean v11 = this.mRegisteredStatusCallbacks.containsKey(v8);
	Object v12 = this.mRegisteredStatusCallbacks.put(v8, v8);
	Object v13 = this.mConfigs.get(p1);
	Object v14 = this.mVcns.get(p1);
	boolean v15 = p0.isCallbackPermissioned(v8, p1);
	VcnManagementService$VcnStatusCallbackInfo.mCallback.onVcnStatusChanged(phiInstruction);
	p0.logDbg(""VcnStatusCallback threw on VCN status change"", caughtException);
	Binder.restoreCallingIdentity(v2);
	return;
}
-----
depth : 1
public boolean isCallbackPermissioned(VcnManagementService$VcnStatusCallbackInfo p1, ParcelUuid p2){
	boolean v1 = p2.equals(VcnManagementService$VcnStatusCallbackInfo.mSubGroup);
	boolean v2 = this.mLastSnapshot.packageHasPermissionsForSubscriptionGroup(p2, VcnManagementService$VcnStatusCallbackInfo.mPkgName);
	return 0;
}
-----
depth : 1
public void logDbg(String p1, Throwable p2){
	int v1 = Slog.d(this.TAG, p1, p2);
	return;
}
-----
","public void registerVcnStatusCallback(ParcelUuid p1, IVcnStatusCallback p2, String p3){
	IBinder v8 = p2.asBinder();
	VcnManagementService$VcnStatusCallbackInfo v9 = new VcnManagementService$VcnStatusCallbackInfo(p0,p1,p2,p3,v1,0);
	v8.linkToDeath(v9, 0);
	boolean v12 = this.mRegisteredStatusCallbacks.containsKey(v8);
	Object v13 = this.mRegisteredStatusCallbacks.put(v8, v9);
	Object v14 = this.mConfigs.get(p1);
	Object v15 = this.mVcns.get(p1);
	boolean v17 = p1.equals(VcnManagementService$VcnStatusCallbackInfo.mSubGroup);
	boolean v18 = this.mLastSnapshot.packageHasPermissionsForSubscriptionGroup(p1, VcnManagementService$VcnStatusCallbackInfo.mPkgName);
	boolean v16 = 0;
	VcnManagementService$VcnStatusCallbackInfo.mCallback.onVcnStatusChanged(phiInstruction);
	Binder.restoreCallingIdentity(v2);
	return;
}
","NONE"
"Lcom/android/server/VcnManagementService","registerVcnStatusCallback(Landroid/os/ParcelUuid;Landroid/net/vcn/IVcnStatusCallback;Ljava/lang/String;)V","1","5 = getfield < Application, Lcom/android/server/VcnManagementService, mDeps, <Application,Lcom/android/server/VcnManagementService$Dependencies> > 1,
7 = invokevirtual < Application, Lcom/android/server/VcnManagementService$Dependencies, getBinderCallingUid()I > 5 @2 exception:6,
9 = invokestatic < Application, Landroid/os/Binder, clearCallingIdentity()J > @6 exception:8,
12 = invokestatic < Application, Ljava/util/Objects, requireNonNull(Ljava/lang/Object;Ljava/lang/String;)Ljava/lang/Object; > 2,10 @13 exception:11,
15 = invokestatic < Application, Ljava/util/Objects, requireNonNull(Ljava/lang/Object;Ljava/lang/String;)Ljava/lang/Object; > 3,13 @18 exception:14,
18 = invokestatic < Application, Ljava/util/Objects, requireNonNull(Ljava/lang/Object;Ljava/lang/String;)Ljava/lang/Object; > 4,16 @24 exception:17,
19 = getfield < Application, Lcom/android/server/VcnManagementService, mContext, <Application,Landroid/content/Context> > 1,
20 = load_metadata: <Application,Landroid/app/AppOpsManager>, <Primordial,Ljava/lang/Class>,
22 = invokevirtual < Application, Landroid/content/Context, getSystemService(Ljava/lang/Class;)Ljava/lang/Object; > 19,20 @31 exception:21,
23 = checkcast <Application,Landroid/app/AppOpsManager>22 <Application,Landroid/app/AppOpsManager>,
invokevirtual < Application, Landroid/app/AppOpsManager, checkPackage(ILjava/lang/String;)V > 23,7,4 @37 exception:24,
26 = invokeinterface < Application, Landroid/net/vcn/IVcnStatusCallback, asBinder()Landroid/os/IBinder; > 3 @40 exception:25,
27 = new <Application,Lcom/android/server/VcnManagementService$VcnStatusCallbackInfo>@44,
invokespecial < Application, Lcom/android/server/VcnManagementService$VcnStatusCallbackInfo, <init>(Lcom/android/server/VcnManagementService;Landroid/os/ParcelUuid;Landroid/net/vcn/IVcnStatusCallback;Ljava/lang/String;ILcom/android/server/VcnManagementService$VcnStatusCallbackInfo-IA;)V > 27,1,2,3,4,7,28 @52 exception:29,
invokeinterface < Application, Landroid/os/IBinder, linkToDeath(Landroid/os/IBinder$DeathRecipient;I)V > 26,27,28 @56 exception:30,
32 = getfield < Application, Lcom/android/server/VcnManagementService, mLock, <Application,Ljava/lang/Object> > 1,
monitorenter 32,
33 = getfield < Application, Lcom/android/server/VcnManagementService, mRegisteredStatusCallbacks, <Application,Ljava/util/Map> > 1,
35 = invokeinterface < Application, Ljava/util/Map, containsKey(Ljava/lang/Object;)Z > 33,26 @64 exception:34,
conditional branch(ne, to iindex=-1) 35,28,
39 = getfield < Application, Lcom/android/server/VcnManagementService, mRegisteredStatusCallbacks, <Application,Ljava/util/Map> > 1,
41 = invokeinterface < Application, Ljava/util/Map, put(Ljava/lang/Object;Ljava/lang/Object;)Ljava/lang/Object; > 39,26,27 @72 exception:40,
42 = getfield < Application, Lcom/android/server/VcnManagementService, mConfigs, <Application,Ljava/util/Map> > 1,
44 = invokeinterface < Application, Ljava/util/Map, get(Ljava/lang/Object;)Ljava/lang/Object; > 42,2 @77 exception:43,
45 = checkcast <Application,Landroid/net/vcn/VcnConfig>44 <Application,Landroid/net/vcn/VcnConfig>,
46 = getfield < Application, Lcom/android/server/VcnManagementService, mVcns, <Application,Ljava/util/Map> > 1,
48 = invokeinterface < Application, Ljava/util/Map, get(Ljava/lang/Object;)Ljava/lang/Object; > 46,2 @85 exception:47,
49 = checkcast <Application,Lcom/android/server/vcn/Vcn>48 <Application,Lcom/android/server/vcn/Vcn>,
conditional branch(ne, to iindex=-1) 49,28,
goto (from iindex= 47 to iindex = 5),
52 = phi  28,51,
conditional branch(eq, to iindex=-1) 45,28,
56 = invokevirtual < Application, Lcom/android/server/VcnManagementService, isCallbackPermissioned(Lcom/android/server/VcnManagementService$VcnStatusCallbackInfo;Landroid/os/ParcelUuid;)Z > 1,27,2 @101 exception:55,
4 = getfield < Application, Lcom/android/server/VcnManagementService$VcnStatusCallbackInfo, mSubGroup, <Application,Landroid/os/ParcelUuid> > 2,
6 = invokevirtual < Application, Landroid/os/ParcelUuid, equals(Ljava/lang/Object;)Z > 3,4 @2 exception:5,
conditional branch(ne, to iindex=-1) 6,7,
8 = getfield < Application, Lcom/android/server/VcnManagementService, mLastSnapshot, <Application,Lcom/android/server/vcn/TelephonySubscriptionTracker$TelephonySubscriptionSnapshot> > 1,
9 = getfield < Application, Lcom/android/server/VcnManagementService$VcnStatusCallbackInfo, mPkgName, <Application,Ljava/lang/String> > 2,
11 = invokevirtual < Application, Lcom/android/server/vcn/TelephonySubscriptionTracker$TelephonySubscriptionSnapshot, packageHasPermissionsForSubscriptionGroup(Landroid/os/ParcelUuid;Ljava/lang/String;)Z > 8,3,9 @14 exception:10,
conditional branch(ne, to iindex=-1) 11,7,
return 7,
conditional branch(ne, to iindex=-1) 56,28,
conditional branch(ne, to iindex=-1) 49,28,
goto (from iindex= 57 to iindex = 30),
73 = phi  28,28,70,28,52,
76 = getfield < Application, Lcom/android/server/VcnManagementService$VcnStatusCallbackInfo, mCallback, <Application,Landroid/net/vcn/IVcnStatusCallback> > 27,
invokeinterface < Application, Landroid/net/vcn/IVcnStatusCallback, onVcnStatusChanged(I)V > 76,73 @143 exception:77,
78 = getCaughtException ,
invokevirtual < Application, Lcom/android/server/VcnManagementService, logDbg(Ljava/lang/String;Ljava/lang/Throwable;)V > 1,79,78 @150 exception:80,
4 = getstatic < Application, Lcom/android/server/VcnManagementService, TAG, <Application,Ljava/lang/String> >,
6 = invokestatic < Application, Landroid/util/Slog, d(Ljava/lang/String;Ljava/lang/String;Ljava/lang/Throwable;)I > 4,2,3 @2 exception:5,
return,
monitorexit 32,
invokestatic < Application, Landroid/os/Binder, restoreCallingIdentity(J)V > 9 @154 exception:104,
return,","depth : 0
public void registerVcnStatusCallback(ParcelUuid p1, IVcnStatusCallback p2, String p3){
	IBinder v8 = p2.asBinder();
	VcnManagementService$VcnStatusCallbackInfo v8 = new VcnManagementService$VcnStatusCallbackInfo(p0,p1,p2,p3,v1,0);
	v8.linkToDeath(v8, 0);
	boolean v11 = this.mRegisteredStatusCallbacks.containsKey(v8);
	Object v12 = this.mRegisteredStatusCallbacks.put(v8, v8);
	Object v13 = this.mConfigs.get(p1);
	Object v14 = this.mVcns.get(p1);
	boolean v15 = p0.isCallbackPermissioned(v8, p1);
	VcnManagementService$VcnStatusCallbackInfo.mCallback.onVcnStatusChanged(phiInstruction);
	p0.logDbg(""VcnStatusCallback threw on VCN status change"", caughtException);
	Binder.restoreCallingIdentity(v2);
	return;
}
-----
depth : 1
public boolean isCallbackPermissioned(VcnManagementService$VcnStatusCallbackInfo p1, ParcelUuid p2){
	boolean v1 = p2.equals(VcnManagementService$VcnStatusCallbackInfo.mSubGroup);
	boolean v2 = this.mLastSnapshot.packageHasPermissionsForSubscriptionGroup(p2, VcnManagementService$VcnStatusCallbackInfo.mPkgName);
	return 0;
}
-----
depth : 1
public void logDbg(String p1, Throwable p2){
	int v1 = Slog.d(this.TAG, p1, p2);
	return;
}
-----
","public void registerVcnStatusCallback(ParcelUuid p1, IVcnStatusCallback p2, String p3){
	IBinder v8 = p2.asBinder();
	VcnManagementService$VcnStatusCallbackInfo v9 = new VcnManagementService$VcnStatusCallbackInfo(p0,p1,p2,p3,v1,0);
	v8.linkToDeath(v9, 0);
	boolean v12 = this.mRegisteredStatusCallbacks.containsKey(v8);
	Object v13 = this.mRegisteredStatusCallbacks.put(v8, v9);
	Object v14 = this.mConfigs.get(p1);
	Object v15 = this.mVcns.get(p1);
	boolean v17 = p1.equals(VcnManagementService$VcnStatusCallbackInfo.mSubGroup);
	boolean v18 = this.mLastSnapshot.packageHasPermissionsForSubscriptionGroup(p1, VcnManagementService$VcnStatusCallbackInfo.mPkgName);
	boolean v16 = 0;
	VcnManagementService$VcnStatusCallbackInfo.mCallback.onVcnStatusChanged(phiInstruction);
	Binder.restoreCallingIdentity(v2);
	return;
}
","NONE"
"Lcom/android/server/VcnManagementService","registerVcnStatusCallback(Landroid/os/ParcelUuid;Landroid/net/vcn/IVcnStatusCallback;Ljava/lang/String;)V","2","5 = getfield < Application, Lcom/android/server/VcnManagementService, mDeps, <Application,Lcom/android/server/VcnManagementService$Dependencies> > 1,
7 = invokevirtual < Application, Lcom/android/server/VcnManagementService$Dependencies, getBinderCallingUid()I > 5 @2 exception:6,
9 = invokestatic < Application, Landroid/os/Binder, clearCallingIdentity()J > @6 exception:8,
12 = invokestatic < Application, Ljava/util/Objects, requireNonNull(Ljava/lang/Object;Ljava/lang/String;)Ljava/lang/Object; > 2,10 @13 exception:11,
15 = invokestatic < Application, Ljava/util/Objects, requireNonNull(Ljava/lang/Object;Ljava/lang/String;)Ljava/lang/Object; > 3,13 @18 exception:14,
18 = invokestatic < Application, Ljava/util/Objects, requireNonNull(Ljava/lang/Object;Ljava/lang/String;)Ljava/lang/Object; > 4,16 @24 exception:17,
19 = getfield < Application, Lcom/android/server/VcnManagementService, mContext, <Application,Landroid/content/Context> > 1,
20 = load_metadata: <Application,Landroid/app/AppOpsManager>, <Primordial,Ljava/lang/Class>,
22 = invokevirtual < Application, Landroid/content/Context, getSystemService(Ljava/lang/Class;)Ljava/lang/Object; > 19,20 @31 exception:21,
23 = checkcast <Application,Landroid/app/AppOpsManager>22 <Application,Landroid/app/AppOpsManager>,
invokevirtual < Application, Landroid/app/AppOpsManager, checkPackage(ILjava/lang/String;)V > 23,7,4 @37 exception:24,
26 = invokeinterface < Application, Landroid/net/vcn/IVcnStatusCallback, asBinder()Landroid/os/IBinder; > 3 @40 exception:25,
27 = new <Application,Lcom/android/server/VcnManagementService$VcnStatusCallbackInfo>@44,
invokespecial < Application, Lcom/android/server/VcnManagementService$VcnStatusCallbackInfo, <init>(Lcom/android/server/VcnManagementService;Landroid/os/ParcelUuid;Landroid/net/vcn/IVcnStatusCallback;Ljava/lang/String;ILcom/android/server/VcnManagementService$VcnStatusCallbackInfo-IA;)V > 27,1,2,3,4,7,28 @52 exception:29,
invokeinterface < Application, Landroid/os/IBinder, linkToDeath(Landroid/os/IBinder$DeathRecipient;I)V > 26,27,28 @56 exception:30,
32 = getfield < Application, Lcom/android/server/VcnManagementService, mLock, <Application,Ljava/lang/Object> > 1,
monitorenter 32,
33 = getfield < Application, Lcom/android/server/VcnManagementService, mRegisteredStatusCallbacks, <Application,Ljava/util/Map> > 1,
35 = invokeinterface < Application, Ljava/util/Map, containsKey(Ljava/lang/Object;)Z > 33,26 @64 exception:34,
conditional branch(ne, to iindex=-1) 35,28,
39 = getfield < Application, Lcom/android/server/VcnManagementService, mRegisteredStatusCallbacks, <Application,Ljava/util/Map> > 1,
41 = invokeinterface < Application, Ljava/util/Map, put(Ljava/lang/Object;Ljava/lang/Object;)Ljava/lang/Object; > 39,26,27 @72 exception:40,
42 = getfield < Application, Lcom/android/server/VcnManagementService, mConfigs, <Application,Ljava/util/Map> > 1,
44 = invokeinterface < Application, Ljava/util/Map, get(Ljava/lang/Object;)Ljava/lang/Object; > 42,2 @77 exception:43,
45 = checkcast <Application,Landroid/net/vcn/VcnConfig>44 <Application,Landroid/net/vcn/VcnConfig>,
46 = getfield < Application, Lcom/android/server/VcnManagementService, mVcns, <Application,Ljava/util/Map> > 1,
48 = invokeinterface < Application, Ljava/util/Map, get(Ljava/lang/Object;)Ljava/lang/Object; > 46,2 @85 exception:47,
49 = checkcast <Application,Lcom/android/server/vcn/Vcn>48 <Application,Lcom/android/server/vcn/Vcn>,
conditional branch(ne, to iindex=-1) 49,28,
goto (from iindex= 47 to iindex = 5),
52 = phi  28,51,
conditional branch(eq, to iindex=-1) 45,28,
56 = invokevirtual < Application, Lcom/android/server/VcnManagementService, isCallbackPermissioned(Lcom/android/server/VcnManagementService$VcnStatusCallbackInfo;Landroid/os/ParcelUuid;)Z > 1,27,2 @101 exception:55,
4 = getfield < Application, Lcom/android/server/VcnManagementService$VcnStatusCallbackInfo, mSubGroup, <Application,Landroid/os/ParcelUuid> > 2,
6 = invokevirtual < Application, Landroid/os/ParcelUuid, equals(Ljava/lang/Object;)Z > 3,4 @2 exception:5,
conditional branch(ne, to iindex=-1) 6,7,
8 = getfield < Application, Lcom/android/server/VcnManagementService, mLastSnapshot, <Application,Lcom/android/server/vcn/TelephonySubscriptionTracker$TelephonySubscriptionSnapshot> > 1,
9 = getfield < Application, Lcom/android/server/VcnManagementService$VcnStatusCallbackInfo, mPkgName, <Application,Ljava/lang/String> > 2,
11 = invokevirtual < Application, Lcom/android/server/vcn/TelephonySubscriptionTracker$TelephonySubscriptionSnapshot, packageHasPermissionsForSubscriptionGroup(Landroid/os/ParcelUuid;Ljava/lang/String;)Z > 8,3,9 @14 exception:10,
4 = getfield < Application, Lcom/android/server/vcn/TelephonySubscriptionTracker$TelephonySubscriptionSnapshot, mPrivilegedPackages, <Application,Ljava/util/Map> > 1,
6 = invokeinterface < Application, Ljava/util/Map, get(Ljava/lang/Object;)Ljava/lang/Object; > 4,2 @2 exception:5,
7 = checkcast <Application,Ljava/util/Set>6 <Application,Ljava/util/Set>,
conditional branch(eq, to iindex=-1) 7,8,
10 = invokeinterface < Application, Ljava/util/Set, contains(Ljava/lang/Object;)Z > 7,3 @10 exception:9,
conditional branch(eq, to iindex=-1) 10,8,
goto (from iindex= 9 to iindex = 2),
15 = phi  14,8,
return 15,
conditional branch(ne, to iindex=-1) 11,7,
return 7,
conditional branch(ne, to iindex=-1) 56,28,
conditional branch(ne, to iindex=-1) 49,28,
conditional branch(eq, to iindex=-1) 52,57,
conditional branch(ne, to iindex=-1) 52,58,
goto (from iindex= 62 to iindex = 22),
73 = phi  28,28,70,28,52,
76 = getfield < Application, Lcom/android/server/VcnManagementService$VcnStatusCallbackInfo, mCallback, <Application,Landroid/net/vcn/IVcnStatusCallback> > 27,
invokeinterface < Application, Landroid/net/vcn/IVcnStatusCallback, onVcnStatusChanged(I)V > 76,73 @143 exception:77,
78 = getCaughtException ,
invokevirtual < Application, Lcom/android/server/VcnManagementService, logDbg(Ljava/lang/String;Ljava/lang/Throwable;)V > 1,79,78 @150 exception:80,
monitorexit 32,
invokestatic < Application, Landroid/os/Binder, restoreCallingIdentity(J)V > 9 @154 exception:104,
return,","depth : 0
public void registerVcnStatusCallback(ParcelUuid p1, IVcnStatusCallback p2, String p3){
	IBinder v8 = p2.asBinder();
	VcnManagementService$VcnStatusCallbackInfo v8 = new VcnManagementService$VcnStatusCallbackInfo(p0,p1,p2,p3,v1,0);
	v8.linkToDeath(v8, 0);
	boolean v11 = this.mRegisteredStatusCallbacks.containsKey(v8);
	Object v12 = this.mRegisteredStatusCallbacks.put(v8, v8);
	Object v13 = this.mConfigs.get(p1);
	Object v14 = this.mVcns.get(p1);
	boolean v15 = p0.isCallbackPermissioned(v8, p1);
	VcnManagementService$VcnStatusCallbackInfo.mCallback.onVcnStatusChanged(phiInstruction);
	p0.logDbg(""VcnStatusCallback threw on VCN status change"", caughtException);
	Binder.restoreCallingIdentity(v2);
	return;
}
-----
depth : 1
public boolean isCallbackPermissioned(VcnManagementService$VcnStatusCallbackInfo p1, ParcelUuid p2){
	boolean v1 = p2.equals(VcnManagementService$VcnStatusCallbackInfo.mSubGroup);
	boolean v2 = this.mLastSnapshot.packageHasPermissionsForSubscriptionGroup(p2, VcnManagementService$VcnStatusCallbackInfo.mPkgName);
	return 0;
}
-----
depth : 2
public boolean packageHasPermissionsForSubscriptionGroup(ParcelUuid p1, String p2){
	Object v1 = this.mPrivilegedPackages.get(p1);
	boolean v2 = v1.contains(p2);
	return phiInstruction;
}
-----
","public void registerVcnStatusCallback(ParcelUuid p1, IVcnStatusCallback p2, String p3){
	IBinder v8 = p2.asBinder();
	VcnManagementService$VcnStatusCallbackInfo v9 = new VcnManagementService$VcnStatusCallbackInfo(p0,p1,p2,p3,v1,0);
	v8.linkToDeath(v9, 0);
	boolean v12 = this.mRegisteredStatusCallbacks.containsKey(v8);
	Object v13 = this.mRegisteredStatusCallbacks.put(v8, v9);
	Object v14 = this.mConfigs.get(p1);
	Object v15 = this.mVcns.get(p1);
	boolean v17 = p1.equals(VcnManagementService$VcnStatusCallbackInfo.mSubGroup);
	Object v19 = this.mPrivilegedPackages.get(p2);
	boolean v20 = v19.contains(VcnManagementService$VcnStatusCallbackInfo.mPkgName);
	boolean v18 = phiInstruction;
	boolean v16 = 0;
	VcnManagementService$VcnStatusCallbackInfo.mCallback.onVcnStatusChanged(phiInstruction);
	p0.logDbg(""VcnStatusCallback threw on VCN status change"", caughtException);
	Binder.restoreCallingIdentity(v2);
	return;
}
","NONE"
"Lcom/android/server/VcnManagementService","registerVcnStatusCallback(Landroid/os/ParcelUuid;Landroid/net/vcn/IVcnStatusCallback;Ljava/lang/String;)V","2","5 = getfield < Application, Lcom/android/server/VcnManagementService, mDeps, <Application,Lcom/android/server/VcnManagementService$Dependencies> > 1,
7 = invokevirtual < Application, Lcom/android/server/VcnManagementService$Dependencies, getBinderCallingUid()I > 5 @2 exception:6,
9 = invokestatic < Application, Landroid/os/Binder, clearCallingIdentity()J > @6 exception:8,
12 = invokestatic < Application, Ljava/util/Objects, requireNonNull(Ljava/lang/Object;Ljava/lang/String;)Ljava/lang/Object; > 2,10 @13 exception:11,
15 = invokestatic < Application, Ljava/util/Objects, requireNonNull(Ljava/lang/Object;Ljava/lang/String;)Ljava/lang/Object; > 3,13 @18 exception:14,
18 = invokestatic < Application, Ljava/util/Objects, requireNonNull(Ljava/lang/Object;Ljava/lang/String;)Ljava/lang/Object; > 4,16 @24 exception:17,
19 = getfield < Application, Lcom/android/server/VcnManagementService, mContext, <Application,Landroid/content/Context> > 1,
20 = load_metadata: <Application,Landroid/app/AppOpsManager>, <Primordial,Ljava/lang/Class>,
22 = invokevirtual < Application, Landroid/content/Context, getSystemService(Ljava/lang/Class;)Ljava/lang/Object; > 19,20 @31 exception:21,
23 = checkcast <Application,Landroid/app/AppOpsManager>22 <Application,Landroid/app/AppOpsManager>,
invokevirtual < Application, Landroid/app/AppOpsManager, checkPackage(ILjava/lang/String;)V > 23,7,4 @37 exception:24,
26 = invokeinterface < Application, Landroid/net/vcn/IVcnStatusCallback, asBinder()Landroid/os/IBinder; > 3 @40 exception:25,
27 = new <Application,Lcom/android/server/VcnManagementService$VcnStatusCallbackInfo>@44,
invokespecial < Application, Lcom/android/server/VcnManagementService$VcnStatusCallbackInfo, <init>(Lcom/android/server/VcnManagementService;Landroid/os/ParcelUuid;Landroid/net/vcn/IVcnStatusCallback;Ljava/lang/String;ILcom/android/server/VcnManagementService$VcnStatusCallbackInfo-IA;)V > 27,1,2,3,4,7,28 @52 exception:29,
invokeinterface < Application, Landroid/os/IBinder, linkToDeath(Landroid/os/IBinder$DeathRecipient;I)V > 26,27,28 @56 exception:30,
32 = getfield < Application, Lcom/android/server/VcnManagementService, mLock, <Application,Ljava/lang/Object> > 1,
monitorenter 32,
33 = getfield < Application, Lcom/android/server/VcnManagementService, mRegisteredStatusCallbacks, <Application,Ljava/util/Map> > 1,
35 = invokeinterface < Application, Ljava/util/Map, containsKey(Ljava/lang/Object;)Z > 33,26 @64 exception:34,
conditional branch(ne, to iindex=-1) 35,28,
39 = getfield < Application, Lcom/android/server/VcnManagementService, mRegisteredStatusCallbacks, <Application,Ljava/util/Map> > 1,
41 = invokeinterface < Application, Ljava/util/Map, put(Ljava/lang/Object;Ljava/lang/Object;)Ljava/lang/Object; > 39,26,27 @72 exception:40,
42 = getfield < Application, Lcom/android/server/VcnManagementService, mConfigs, <Application,Ljava/util/Map> > 1,
44 = invokeinterface < Application, Ljava/util/Map, get(Ljava/lang/Object;)Ljava/lang/Object; > 42,2 @77 exception:43,
45 = checkcast <Application,Landroid/net/vcn/VcnConfig>44 <Application,Landroid/net/vcn/VcnConfig>,
46 = getfield < Application, Lcom/android/server/VcnManagementService, mVcns, <Application,Ljava/util/Map> > 1,
48 = invokeinterface < Application, Ljava/util/Map, get(Ljava/lang/Object;)Ljava/lang/Object; > 46,2 @85 exception:47,
49 = checkcast <Application,Lcom/android/server/vcn/Vcn>48 <Application,Lcom/android/server/vcn/Vcn>,
conditional branch(ne, to iindex=-1) 49,28,
goto (from iindex= 47 to iindex = 5),
52 = phi  28,51,
conditional branch(eq, to iindex=-1) 45,28,
56 = invokevirtual < Application, Lcom/android/server/VcnManagementService, isCallbackPermissioned(Lcom/android/server/VcnManagementService$VcnStatusCallbackInfo;Landroid/os/ParcelUuid;)Z > 1,27,2 @101 exception:55,
4 = getfield < Application, Lcom/android/server/VcnManagementService$VcnStatusCallbackInfo, mSubGroup, <Application,Landroid/os/ParcelUuid> > 2,
6 = invokevirtual < Application, Landroid/os/ParcelUuid, equals(Ljava/lang/Object;)Z > 3,4 @2 exception:5,
conditional branch(ne, to iindex=-1) 6,7,
8 = getfield < Application, Lcom/android/server/VcnManagementService, mLastSnapshot, <Application,Lcom/android/server/vcn/TelephonySubscriptionTracker$TelephonySubscriptionSnapshot> > 1,
9 = getfield < Application, Lcom/android/server/VcnManagementService$VcnStatusCallbackInfo, mPkgName, <Application,Ljava/lang/String> > 2,
11 = invokevirtual < Application, Lcom/android/server/vcn/TelephonySubscriptionTracker$TelephonySubscriptionSnapshot, packageHasPermissionsForSubscriptionGroup(Landroid/os/ParcelUuid;Ljava/lang/String;)Z > 8,3,9 @14 exception:10,
4 = getfield < Application, Lcom/android/server/vcn/TelephonySubscriptionTracker$TelephonySubscriptionSnapshot, mPrivilegedPackages, <Application,Ljava/util/Map> > 1,
6 = invokeinterface < Application, Ljava/util/Map, get(Ljava/lang/Object;)Ljava/lang/Object; > 4,2 @2 exception:5,
7 = checkcast <Application,Ljava/util/Set>6 <Application,Ljava/util/Set>,
conditional branch(eq, to iindex=-1) 7,8,
10 = invokeinterface < Application, Ljava/util/Set, contains(Ljava/lang/Object;)Z > 7,3 @10 exception:9,
conditional branch(eq, to iindex=-1) 10,8,
goto (from iindex= 9 to iindex = 2),
15 = phi  14,8,
return 15,
conditional branch(ne, to iindex=-1) 11,7,
return 12,
conditional branch(ne, to iindex=-1) 56,28,
conditional branch(ne, to iindex=-1) 49,28,
conditional branch(eq, to iindex=-1) 52,57,
conditional branch(ne, to iindex=-1) 52,58,
goto (from iindex= 62 to iindex = 22),
73 = phi  28,28,70,28,52,
76 = getfield < Application, Lcom/android/server/VcnManagementService$VcnStatusCallbackInfo, mCallback, <Application,Landroid/net/vcn/IVcnStatusCallback> > 27,
invokeinterface < Application, Landroid/net/vcn/IVcnStatusCallback, onVcnStatusChanged(I)V > 76,73 @143 exception:77,
78 = getCaughtException ,
invokevirtual < Application, Lcom/android/server/VcnManagementService, logDbg(Ljava/lang/String;Ljava/lang/Throwable;)V > 1,79,78 @150 exception:80,
monitorexit 32,
invokestatic < Application, Landroid/os/Binder, restoreCallingIdentity(J)V > 9 @154 exception:104,
return,","depth : 0
public void registerVcnStatusCallback(ParcelUuid p1, IVcnStatusCallback p2, String p3){
	IBinder v8 = p2.asBinder();
	VcnManagementService$VcnStatusCallbackInfo v8 = new VcnManagementService$VcnStatusCallbackInfo(p0,p1,p2,p3,v1,0);
	v8.linkToDeath(v8, 0);
	boolean v11 = this.mRegisteredStatusCallbacks.containsKey(v8);
	Object v12 = this.mRegisteredStatusCallbacks.put(v8, v8);
	Object v13 = this.mConfigs.get(p1);
	Object v14 = this.mVcns.get(p1);
	boolean v15 = p0.isCallbackPermissioned(v8, p1);
	VcnManagementService$VcnStatusCallbackInfo.mCallback.onVcnStatusChanged(phiInstruction);
	p0.logDbg(""VcnStatusCallback threw on VCN status change"", caughtException);
	Binder.restoreCallingIdentity(v2);
	return;
}
-----
depth : 1
public boolean isCallbackPermissioned(VcnManagementService$VcnStatusCallbackInfo p1, ParcelUuid p2){
	boolean v1 = p2.equals(VcnManagementService$VcnStatusCallbackInfo.mSubGroup);
	boolean v2 = this.mLastSnapshot.packageHasPermissionsForSubscriptionGroup(p2, VcnManagementService$VcnStatusCallbackInfo.mPkgName);
	return 1;
}
-----
depth : 2
public boolean packageHasPermissionsForSubscriptionGroup(ParcelUuid p1, String p2){
	Object v1 = this.mPrivilegedPackages.get(p1);
	boolean v2 = v1.contains(p2);
	return phiInstruction;
}
-----
","public void registerVcnStatusCallback(ParcelUuid p1, IVcnStatusCallback p2, String p3){
	IBinder v8 = p2.asBinder();
	VcnManagementService$VcnStatusCallbackInfo v9 = new VcnManagementService$VcnStatusCallbackInfo(p0,p1,p2,p3,v1,0);
	v8.linkToDeath(v9, 0);
	boolean v12 = this.mRegisteredStatusCallbacks.containsKey(v8);
	Object v13 = this.mRegisteredStatusCallbacks.put(v8, v9);
	Object v14 = this.mConfigs.get(p1);
	Object v15 = this.mVcns.get(p1);
	boolean v17 = p1.equals(VcnManagementService$VcnStatusCallbackInfo.mSubGroup);
	Object v19 = this.mPrivilegedPackages.get(p2);
	boolean v20 = v19.contains(VcnManagementService$VcnStatusCallbackInfo.mPkgName);
	boolean v18 = phiInstruction;
	boolean v16 = 1;
	VcnManagementService$VcnStatusCallbackInfo.mCallback.onVcnStatusChanged(phiInstruction);
	p0.logDbg(""VcnStatusCallback threw on VCN status change"", caughtException);
	Binder.restoreCallingIdentity(v2);
	return;
}
","NONE"
"Lcom/android/server/VcnManagementService","registerVcnStatusCallback(Landroid/os/ParcelUuid;Landroid/net/vcn/IVcnStatusCallback;Ljava/lang/String;)V","2","5 = getfield < Application, Lcom/android/server/VcnManagementService, mDeps, <Application,Lcom/android/server/VcnManagementService$Dependencies> > 1,
7 = invokevirtual < Application, Lcom/android/server/VcnManagementService$Dependencies, getBinderCallingUid()I > 5 @2 exception:6,
9 = invokestatic < Application, Landroid/os/Binder, clearCallingIdentity()J > @6 exception:8,
12 = invokestatic < Application, Ljava/util/Objects, requireNonNull(Ljava/lang/Object;Ljava/lang/String;)Ljava/lang/Object; > 2,10 @13 exception:11,
15 = invokestatic < Application, Ljava/util/Objects, requireNonNull(Ljava/lang/Object;Ljava/lang/String;)Ljava/lang/Object; > 3,13 @18 exception:14,
18 = invokestatic < Application, Ljava/util/Objects, requireNonNull(Ljava/lang/Object;Ljava/lang/String;)Ljava/lang/Object; > 4,16 @24 exception:17,
19 = getfield < Application, Lcom/android/server/VcnManagementService, mContext, <Application,Landroid/content/Context> > 1,
20 = load_metadata: <Application,Landroid/app/AppOpsManager>, <Primordial,Ljava/lang/Class>,
22 = invokevirtual < Application, Landroid/content/Context, getSystemService(Ljava/lang/Class;)Ljava/lang/Object; > 19,20 @31 exception:21,
23 = checkcast <Application,Landroid/app/AppOpsManager>22 <Application,Landroid/app/AppOpsManager>,
invokevirtual < Application, Landroid/app/AppOpsManager, checkPackage(ILjava/lang/String;)V > 23,7,4 @37 exception:24,
26 = invokeinterface < Application, Landroid/net/vcn/IVcnStatusCallback, asBinder()Landroid/os/IBinder; > 3 @40 exception:25,
27 = new <Application,Lcom/android/server/VcnManagementService$VcnStatusCallbackInfo>@44,
invokespecial < Application, Lcom/android/server/VcnManagementService$VcnStatusCallbackInfo, <init>(Lcom/android/server/VcnManagementService;Landroid/os/ParcelUuid;Landroid/net/vcn/IVcnStatusCallback;Ljava/lang/String;ILcom/android/server/VcnManagementService$VcnStatusCallbackInfo-IA;)V > 27,1,2,3,4,7,28 @52 exception:29,
invokeinterface < Application, Landroid/os/IBinder, linkToDeath(Landroid/os/IBinder$DeathRecipient;I)V > 26,27,28 @56 exception:30,
32 = getfield < Application, Lcom/android/server/VcnManagementService, mLock, <Application,Ljava/lang/Object> > 1,
monitorenter 32,
33 = getfield < Application, Lcom/android/server/VcnManagementService, mRegisteredStatusCallbacks, <Application,Ljava/util/Map> > 1,
35 = invokeinterface < Application, Ljava/util/Map, containsKey(Ljava/lang/Object;)Z > 33,26 @64 exception:34,
conditional branch(ne, to iindex=-1) 35,28,
39 = getfield < Application, Lcom/android/server/VcnManagementService, mRegisteredStatusCallbacks, <Application,Ljava/util/Map> > 1,
41 = invokeinterface < Application, Ljava/util/Map, put(Ljava/lang/Object;Ljava/lang/Object;)Ljava/lang/Object; > 39,26,27 @72 exception:40,
42 = getfield < Application, Lcom/android/server/VcnManagementService, mConfigs, <Application,Ljava/util/Map> > 1,
44 = invokeinterface < Application, Ljava/util/Map, get(Ljava/lang/Object;)Ljava/lang/Object; > 42,2 @77 exception:43,
45 = checkcast <Application,Landroid/net/vcn/VcnConfig>44 <Application,Landroid/net/vcn/VcnConfig>,
46 = getfield < Application, Lcom/android/server/VcnManagementService, mVcns, <Application,Ljava/util/Map> > 1,
48 = invokeinterface < Application, Ljava/util/Map, get(Ljava/lang/Object;)Ljava/lang/Object; > 46,2 @85 exception:47,
49 = checkcast <Application,Lcom/android/server/vcn/Vcn>48 <Application,Lcom/android/server/vcn/Vcn>,
conditional branch(ne, to iindex=-1) 49,28,
goto (from iindex= 47 to iindex = 5),
52 = phi  28,51,
conditional branch(eq, to iindex=-1) 45,28,
56 = invokevirtual < Application, Lcom/android/server/VcnManagementService, isCallbackPermissioned(Lcom/android/server/VcnManagementService$VcnStatusCallbackInfo;Landroid/os/ParcelUuid;)Z > 1,27,2 @101 exception:55,
4 = getfield < Application, Lcom/android/server/VcnManagementService$VcnStatusCallbackInfo, mSubGroup, <Application,Landroid/os/ParcelUuid> > 2,
6 = invokevirtual < Application, Landroid/os/ParcelUuid, equals(Ljava/lang/Object;)Z > 3,4 @2 exception:5,
conditional branch(ne, to iindex=-1) 6,7,
8 = getfield < Application, Lcom/android/server/VcnManagementService, mLastSnapshot, <Application,Lcom/android/server/vcn/TelephonySubscriptionTracker$TelephonySubscriptionSnapshot> > 1,
9 = getfield < Application, Lcom/android/server/VcnManagementService$VcnStatusCallbackInfo, mPkgName, <Application,Ljava/lang/String> > 2,
11 = invokevirtual < Application, Lcom/android/server/vcn/TelephonySubscriptionTracker$TelephonySubscriptionSnapshot, packageHasPermissionsForSubscriptionGroup(Landroid/os/ParcelUuid;Ljava/lang/String;)Z > 8,3,9 @14 exception:10,
4 = getfield < Application, Lcom/android/server/vcn/TelephonySubscriptionTracker$TelephonySubscriptionSnapshot, mPrivilegedPackages, <Application,Ljava/util/Map> > 1,
6 = invokeinterface < Application, Ljava/util/Map, get(Ljava/lang/Object;)Ljava/lang/Object; > 4,2 @2 exception:5,
7 = checkcast <Application,Ljava/util/Set>6 <Application,Ljava/util/Set>,
conditional branch(eq, to iindex=-1) 7,8,
10 = invokeinterface < Application, Ljava/util/Set, contains(Ljava/lang/Object;)Z > 7,3 @10 exception:9,
conditional branch(eq, to iindex=-1) 10,8,
goto (from iindex= 9 to iindex = 2),
15 = phi  14,8,
return 15,
conditional branch(ne, to iindex=-1) 11,7,
return 7,
conditional branch(ne, to iindex=-1) 56,28,
conditional branch(ne, to iindex=-1) 49,28,
goto (from iindex= 57 to iindex = 30),
73 = phi  28,28,70,28,52,
76 = getfield < Application, Lcom/android/server/VcnManagementService$VcnStatusCallbackInfo, mCallback, <Application,Landroid/net/vcn/IVcnStatusCallback> > 27,
invokeinterface < Application, Landroid/net/vcn/IVcnStatusCallback, onVcnStatusChanged(I)V > 76,73 @143 exception:77,
78 = getCaughtException ,
invokevirtual < Application, Lcom/android/server/VcnManagementService, logDbg(Ljava/lang/String;Ljava/lang/Throwable;)V > 1,79,78 @150 exception:80,
monitorexit 32,
invokestatic < Application, Landroid/os/Binder, restoreCallingIdentity(J)V > 9 @154 exception:104,
return,","depth : 0
public void registerVcnStatusCallback(ParcelUuid p1, IVcnStatusCallback p2, String p3){
	IBinder v8 = p2.asBinder();
	VcnManagementService$VcnStatusCallbackInfo v8 = new VcnManagementService$VcnStatusCallbackInfo(p0,p1,p2,p3,v1,0);
	v8.linkToDeath(v8, 0);
	boolean v11 = this.mRegisteredStatusCallbacks.containsKey(v8);
	Object v12 = this.mRegisteredStatusCallbacks.put(v8, v8);
	Object v13 = this.mConfigs.get(p1);
	Object v14 = this.mVcns.get(p1);
	boolean v15 = p0.isCallbackPermissioned(v8, p1);
	VcnManagementService$VcnStatusCallbackInfo.mCallback.onVcnStatusChanged(phiInstruction);
	p0.logDbg(""VcnStatusCallback threw on VCN status change"", caughtException);
	Binder.restoreCallingIdentity(v2);
	return;
}
-----
depth : 1
public boolean isCallbackPermissioned(VcnManagementService$VcnStatusCallbackInfo p1, ParcelUuid p2){
	boolean v1 = p2.equals(VcnManagementService$VcnStatusCallbackInfo.mSubGroup);
	boolean v2 = this.mLastSnapshot.packageHasPermissionsForSubscriptionGroup(p2, VcnManagementService$VcnStatusCallbackInfo.mPkgName);
	return 0;
}
-----
depth : 2
public boolean packageHasPermissionsForSubscriptionGroup(ParcelUuid p1, String p2){
	Object v1 = this.mPrivilegedPackages.get(p1);
	boolean v2 = v1.contains(p2);
	return phiInstruction;
}
-----
","public void registerVcnStatusCallback(ParcelUuid p1, IVcnStatusCallback p2, String p3){
	IBinder v8 = p2.asBinder();
	VcnManagementService$VcnStatusCallbackInfo v9 = new VcnManagementService$VcnStatusCallbackInfo(p0,p1,p2,p3,v1,0);
	v8.linkToDeath(v9, 0);
	boolean v12 = this.mRegisteredStatusCallbacks.containsKey(v8);
	Object v13 = this.mRegisteredStatusCallbacks.put(v8, v9);
	Object v14 = this.mConfigs.get(p1);
	Object v15 = this.mVcns.get(p1);
	boolean v17 = p1.equals(VcnManagementService$VcnStatusCallbackInfo.mSubGroup);
	Object v19 = this.mPrivilegedPackages.get(p2);
	boolean v20 = v19.contains(VcnManagementService$VcnStatusCallbackInfo.mPkgName);
	boolean v18 = phiInstruction;
	boolean v16 = 0;
	VcnManagementService$VcnStatusCallbackInfo.mCallback.onVcnStatusChanged(phiInstruction);
	p0.logDbg(""VcnStatusCallback threw on VCN status change"", caughtException);
	Binder.restoreCallingIdentity(v2);
	return;
}
","NONE"

"Lcom/android/server/VcnManagementService","unregisterVcnStatusCallback(Landroid/net/vcn/IVcnStatusCallback;)V","0","4 = invokestatic < Application, Landroid/os/Binder, clearCallingIdentity()J > @0 exception:3,
7 = invokestatic < Application, Ljava/util/Objects, requireNonNull(Ljava/lang/Object;Ljava/lang/String;)Ljava/lang/Object; > 2,5 @6 exception:6,
9 = invokeinterface < Application, Landroid/net/vcn/IVcnStatusCallback, asBinder()Landroid/os/IBinder; > 2 @9 exception:8,
10 = getfield < Application, Lcom/android/server/VcnManagementService, mLock, <Application,Ljava/lang/Object> > 1,
monitorenter 10,
11 = getfield < Application, Lcom/android/server/VcnManagementService, mRegisteredStatusCallbacks, <Application,Ljava/util/Map> > 1,
13 = invokeinterface < Application, Ljava/util/Map, remove(Ljava/lang/Object;)Ljava/lang/Object; > 11,9 @18 exception:12,
14 = checkcast <Application,Lcom/android/server/VcnManagementService$VcnStatusCallbackInfo>13 <Application,Lcom/android/server/VcnManagementService$VcnStatusCallbackInfo>,
conditional branch(eq, to iindex=-1) 14,15,
17 = invokeinterface < Application, Landroid/os/IBinder, unlinkToDeath(Landroid/os/IBinder$DeathRecipient;I)Z > 9,14,15 @27 exception:16,
monitorexit 10,
invokestatic < Application, Landroid/os/Binder, restoreCallingIdentity(J)V > 4 @31 exception:31,
return,","depth : 0
public void unregisterVcnStatusCallback(IVcnStatusCallback p1){
	long v1 = Binder.clearCallingIdentity();
	Object v2 = Objects.requireNonNull(p1, ""callback must not be null"");
	IBinder v3 = p1.asBinder();
	Object v4 = this.mRegisteredStatusCallbacks.remove(v3);
	boolean v5 = v3.unlinkToDeath(v4, 0);
	Binder.restoreCallingIdentity(v1);
	return;
}
-----
","public void unregisterVcnStatusCallback(IVcnStatusCallback p1){
	long v1 = Binder.clearCallingIdentity();
	Object v2 = Objects.requireNonNull(p1, ""callback must not be null"");
	IBinder v3 = p1.asBinder();
	Object v4 = this.mRegisteredStatusCallbacks.remove(v3);
	boolean v5 = v3.unlinkToDeath(v4, 0);
	Binder.restoreCallingIdentity(v1);
	return;
}
","NONE"
"Lcom/android/server/VcnManagementService","unregisterVcnStatusCallback(Landroid/net/vcn/IVcnStatusCallback;)V","0","4 = invokestatic < Application, Landroid/os/Binder, clearCallingIdentity()J > @0 exception:3,
7 = invokestatic < Application, Ljava/util/Objects, requireNonNull(Ljava/lang/Object;Ljava/lang/String;)Ljava/lang/Object; > 2,5 @6 exception:6,
9 = invokeinterface < Application, Landroid/net/vcn/IVcnStatusCallback, asBinder()Landroid/os/IBinder; > 2 @9 exception:8,
10 = getfield < Application, Lcom/android/server/VcnManagementService, mLock, <Application,Ljava/lang/Object> > 1,
monitorenter 10,
11 = getfield < Application, Lcom/android/server/VcnManagementService, mRegisteredStatusCallbacks, <Application,Ljava/util/Map> > 1,
13 = invokeinterface < Application, Ljava/util/Map, remove(Ljava/lang/Object;)Ljava/lang/Object; > 11,9 @18 exception:12,
14 = checkcast <Application,Lcom/android/server/VcnManagementService$VcnStatusCallbackInfo>13 <Application,Lcom/android/server/VcnManagementService$VcnStatusCallbackInfo>,
conditional branch(eq, to iindex=-1) 14,15,
monitorexit 10,
invokestatic < Application, Landroid/os/Binder, restoreCallingIdentity(J)V > 4 @31 exception:31,
return,","depth : 0
public void unregisterVcnStatusCallback(IVcnStatusCallback p1){
	long v1 = Binder.clearCallingIdentity();
	Object v2 = Objects.requireNonNull(p1, ""callback must not be null"");
	IBinder v3 = p1.asBinder();
	Object v4 = this.mRegisteredStatusCallbacks.remove(v3);
	Binder.restoreCallingIdentity(v1);
	return;
}
-----
","public void unregisterVcnStatusCallback(IVcnStatusCallback p1){
	long v1 = Binder.clearCallingIdentity();
	Object v2 = Objects.requireNonNull(p1, ""callback must not be null"");
	IBinder v3 = p1.asBinder();
	Object v4 = this.mRegisteredStatusCallbacks.remove(v3);
	Binder.restoreCallingIdentity(v1);
	return;
}
","NONE"

