"Class","Method","Depth","Trace Instruction(s) ...","Java Code Representation","Code Merged","Access Control Level"
"Lcom/android/server/incident/IncidentCompanionService$BinderService","deleteIncidentReports(Ljava/lang/String;Ljava/lang/String;Ljava/lang/String;)V","0","conditional branch(eq, to iindex=-1) 2,5,
conditional branch(eq, to iindex=-1) 3,5,
conditional branch(eq, to iindex=-1) 4,5,
7 = invokevirtual < Application, Ljava/lang/String, length()I > 2 @6 exception:6,
conditional branch(eq, to iindex=-1) 7,5,
9 = invokevirtual < Application, Ljava/lang/String, length()I > 3 @12 exception:8,
conditional branch(eq, to iindex=-1) 9,5,
11 = invokevirtual < Application, Ljava/lang/String, length()I > 4 @18 exception:10,
conditional branch(eq, to iindex=-1) 11,5,
invokevirtual < Application, Lcom/android/server/incident/IncidentCompanionService$BinderService, enforceAccessReportsPermissions(Ljava/lang/String;)V > 1,2 @24 exception:18,
20 = invokestatic < Application, Landroid/os/Binder, clearCallingIdentity()J > @27 exception:19,
21 = getfield < Application, Lcom/android/server/incident/IncidentCompanionService$BinderService, this$0, <Application,Lcom/android/server/incident/IncidentCompanionService> > 1,
23 = invokestatic < Application, Lcom/android/server/incident/IncidentCompanionService, -$$Nest$mgetIIncidentManager(Lcom/android/server/incident/IncidentCompanionService;)Landroid/os/IIncidentManager; > 21 @33 exception:22,
invokeinterface < Application, Landroid/os/IIncidentManager, deleteIncidentReports(Ljava/lang/String;Ljava/lang/String;Ljava/lang/String;)V > 23,2,3,4 @37 exception:24,
invokestatic < Application, Landroid/os/Binder, restoreCallingIdentity(J)V > 20 @40 exception:30,
return,","depth : 0
-----
","public void deleteIncidentReports(String p1, String p2, String p3){
	if (p1 == 0) {
		if (p2 == 0) {
			if (p3 == 0) {
				int v1 = p1.length();
				if (v1 == 0) {
					int v2 = p2.length();
					if (v2 == 0) {
						int v3 = p3.length();
						if (v3 == 0) {
							long v5 = Binder.clearCallingIdentity();
							IIncidentManager v6 = IncidentCompanionService.-$$Nest$mgetIIncidentManager(this.this$0);
							v6.deleteIncidentReports(p1, p2, p3);
							Binder.restoreCallingIdentity(v5);
							return;
						}
					}
				}
			}
		}
	}
}
","SYS_OR_SIG"
"Lcom/android/server/incident/IncidentCompanionService$BinderService","deleteIncidentReports(Ljava/lang/String;Ljava/lang/String;Ljava/lang/String;)V","1","conditional branch(eq, to iindex=-1) 2,5,
conditional branch(eq, to iindex=-1) 3,5,
conditional branch(eq, to iindex=-1) 4,5,
7 = invokevirtual < Application, Ljava/lang/String, length()I > 2 @6 exception:6,
conditional branch(eq, to iindex=-1) 7,5,
9 = invokevirtual < Application, Ljava/lang/String, length()I > 3 @12 exception:8,
conditional branch(eq, to iindex=-1) 9,5,
11 = invokevirtual < Application, Ljava/lang/String, length()I > 4 @18 exception:10,
conditional branch(eq, to iindex=-1) 11,5,
invokevirtual < Application, Lcom/android/server/incident/IncidentCompanionService$BinderService, enforceAccessReportsPermissions(Ljava/lang/String;)V > 1,2 @24 exception:18,
20 = invokestatic < Application, Landroid/os/Binder, clearCallingIdentity()J > @27 exception:19,
21 = getfield < Application, Lcom/android/server/incident/IncidentCompanionService$BinderService, this$0, <Application,Lcom/android/server/incident/IncidentCompanionService> > 1,
23 = invokestatic < Application, Lcom/android/server/incident/IncidentCompanionService, -$$Nest$mgetIIncidentManager(Lcom/android/server/incident/IncidentCompanionService;)Landroid/os/IIncidentManager; > 21 @33 exception:22,
3 = invokevirtual < Application, Lcom/android/server/incident/IncidentCompanionService, getIIncidentManager()Landroid/os/IIncidentManager; > 1 @0 exception:2,
return 3,
invokeinterface < Application, Landroid/os/IIncidentManager, deleteIncidentReports(Ljava/lang/String;Ljava/lang/String;Ljava/lang/String;)V > 23,2,3,4 @37 exception:24,
invokestatic < Application, Landroid/os/Binder, restoreCallingIdentity(J)V > 20 @40 exception:30,
return,","depth : 0
-----
depth : 1
-----
","public void deleteIncidentReports(String p1, String p2, String p3){
	if (p1 == 0) {
		if (p2 == 0) {
			if (p3 == 0) {
				int v1 = p1.length();
				if (v1 == 0) {
					int v2 = p2.length();
					if (v2 == 0) {
						int v3 = p3.length();
						if (v3 == 0) {
							long v5 = Binder.clearCallingIdentity();
							IIncidentManager v7 = this.this$0.getIIncidentManager();
							IIncidentManager v6 = v7;
							v6.deleteIncidentReports(p1, p2, p3);
							Binder.restoreCallingIdentity(v5);
							return;
						}
					}
				}
			}
		}
	}
}
","SYS_OR_SIG"
"Lcom/android/server/incident/IncidentCompanionService$BinderService","deleteIncidentReports(Ljava/lang/String;Ljava/lang/String;Ljava/lang/String;)V","2","conditional branch(eq, to iindex=-1) 2,5,
conditional branch(eq, to iindex=-1) 3,5,
conditional branch(eq, to iindex=-1) 4,5,
7 = invokevirtual < Application, Ljava/lang/String, length()I > 2 @6 exception:6,
conditional branch(eq, to iindex=-1) 7,5,
9 = invokevirtual < Application, Ljava/lang/String, length()I > 3 @12 exception:8,
conditional branch(eq, to iindex=-1) 9,5,
11 = invokevirtual < Application, Ljava/lang/String, length()I > 4 @18 exception:10,
conditional branch(eq, to iindex=-1) 11,5,
invokevirtual < Application, Lcom/android/server/incident/IncidentCompanionService$BinderService, enforceAccessReportsPermissions(Ljava/lang/String;)V > 1,2 @24 exception:18,
20 = invokestatic < Application, Landroid/os/Binder, clearCallingIdentity()J > @27 exception:19,
21 = getfield < Application, Lcom/android/server/incident/IncidentCompanionService$BinderService, this$0, <Application,Lcom/android/server/incident/IncidentCompanionService> > 1,
23 = invokestatic < Application, Lcom/android/server/incident/IncidentCompanionService, -$$Nest$mgetIIncidentManager(Lcom/android/server/incident/IncidentCompanionService;)Landroid/os/IIncidentManager; > 21 @33 exception:22,
3 = invokevirtual < Application, Lcom/android/server/incident/IncidentCompanionService, getIIncidentManager()Landroid/os/IIncidentManager; > 1 @0 exception:2,
4 = invokestatic < Application, Landroid/os/ServiceManager, getService(Ljava/lang/String;)Landroid/os/IBinder; > 2 @2 exception:3,
6 = invokestatic < Application, Landroid/os/IIncidentManager$Stub, asInterface(Landroid/os/IBinder;)Landroid/os/IIncidentManager; > 4 @6 exception:5,
return 6,
return 3,
invokeinterface < Application, Landroid/os/IIncidentManager, deleteIncidentReports(Ljava/lang/String;Ljava/lang/String;Ljava/lang/String;)V > 23,2,3,4 @37 exception:24,
invokestatic < Application, Landroid/os/Binder, restoreCallingIdentity(J)V > 20 @40 exception:30,
return,","depth : 0
-----
depth : 1
-----
depth : 2
-----
","public void deleteIncidentReports(String p1, String p2, String p3){
	if (p1 == 0) {
		if (p2 == 0) {
			if (p3 == 0) {
				int v1 = p1.length();
				if (v1 == 0) {
					int v2 = p2.length();
					if (v2 == 0) {
						int v3 = p3.length();
						if (v3 == 0) {
							long v5 = Binder.clearCallingIdentity();
							IBinder v8 = ServiceManager.getService(""incident"");
							IIncidentManager v9 = IIncidentManager$Stub.asInterface(v8);
							IIncidentManager v7 = v9;
							IIncidentManager v6 = v7;
							v6.deleteIncidentReports(p1, p2, p3);
							Binder.restoreCallingIdentity(v5);
							return;
						}
					}
				}
			}
		}
	}
}
","SYS_OR_SIG"

"Lcom/android/server/incident/IncidentCompanionService$BinderService","getIncidentReport(Ljava/lang/String;Ljava/lang/String;Ljava/lang/String;)Landroid/os/IncidentManager$IncidentReport;","0","conditional branch(eq, to iindex=-1) 2,5,
conditional branch(eq, to iindex=-1) 3,5,
conditional branch(eq, to iindex=-1) 4,5,
7 = invokevirtual < Application, Ljava/lang/String, length()I > 2 @6 exception:6,
conditional branch(eq, to iindex=-1) 7,5,
9 = invokevirtual < Application, Ljava/lang/String, length()I > 3 @12 exception:8,
conditional branch(eq, to iindex=-1) 9,5,
11 = invokevirtual < Application, Ljava/lang/String, length()I > 4 @18 exception:10,
conditional branch(eq, to iindex=-1) 11,5,
invokevirtual < Application, Lcom/android/server/incident/IncidentCompanionService$BinderService, enforceAccessReportsPermissions(Ljava/lang/String;)V > 1,2 @24 exception:18,
20 = invokestatic < Application, Landroid/os/Binder, clearCallingIdentity()J > @27 exception:19,
21 = getfield < Application, Lcom/android/server/incident/IncidentCompanionService$BinderService, this$0, <Application,Lcom/android/server/incident/IncidentCompanionService> > 1,
23 = invokestatic < Application, Lcom/android/server/incident/IncidentCompanionService, -$$Nest$mgetIIncidentManager(Lcom/android/server/incident/IncidentCompanionService;)Landroid/os/IIncidentManager; > 21 @33 exception:22,
25 = invokeinterface < Application, Landroid/os/IIncidentManager, getIncidentReport(Ljava/lang/String;Ljava/lang/String;Ljava/lang/String;)Landroid/os/IncidentManager$IncidentReport; > 23,2,3,4 @37 exception:24,
invokestatic < Application, Landroid/os/Binder, restoreCallingIdentity(J)V > 20 @41 exception:31,
return 25,","depth : 0
-----
","public IncidentManager$IncidentReport getIncidentReport(String p1, String p2, String p3){
	if (p1 == 0) {
		if (p2 == 0) {
			if (p3 == 0) {
				int v1 = p1.length();
				if (v1 == 0) {
					int v2 = p2.length();
					if (v2 == 0) {
						int v3 = p3.length();
						if (v3 == 0) {
							long v5 = Binder.clearCallingIdentity();
							IIncidentManager v6 = IncidentCompanionService.-$$Nest$mgetIIncidentManager(this.this$0);
							IncidentManager$IncidentReport v7 = v6.getIncidentReport(p1, p2, p3);
							Binder.restoreCallingIdentity(v5);
							return v7;
						}
					}
				}
			}
		}
	}
}
","SYS_OR_SIG"
"Lcom/android/server/incident/IncidentCompanionService$BinderService","getIncidentReport(Ljava/lang/String;Ljava/lang/String;Ljava/lang/String;)Landroid/os/IncidentManager$IncidentReport;","1","conditional branch(eq, to iindex=-1) 2,5,
conditional branch(eq, to iindex=-1) 3,5,
conditional branch(eq, to iindex=-1) 4,5,
7 = invokevirtual < Application, Ljava/lang/String, length()I > 2 @6 exception:6,
conditional branch(eq, to iindex=-1) 7,5,
9 = invokevirtual < Application, Ljava/lang/String, length()I > 3 @12 exception:8,
conditional branch(eq, to iindex=-1) 9,5,
11 = invokevirtual < Application, Ljava/lang/String, length()I > 4 @18 exception:10,
conditional branch(eq, to iindex=-1) 11,5,
invokevirtual < Application, Lcom/android/server/incident/IncidentCompanionService$BinderService, enforceAccessReportsPermissions(Ljava/lang/String;)V > 1,2 @24 exception:18,
20 = invokestatic < Application, Landroid/os/Binder, clearCallingIdentity()J > @27 exception:19,
21 = getfield < Application, Lcom/android/server/incident/IncidentCompanionService$BinderService, this$0, <Application,Lcom/android/server/incident/IncidentCompanionService> > 1,
23 = invokestatic < Application, Lcom/android/server/incident/IncidentCompanionService, -$$Nest$mgetIIncidentManager(Lcom/android/server/incident/IncidentCompanionService;)Landroid/os/IIncidentManager; > 21 @33 exception:22,
3 = invokevirtual < Application, Lcom/android/server/incident/IncidentCompanionService, getIIncidentManager()Landroid/os/IIncidentManager; > 1 @0 exception:2,
return 3,
25 = invokeinterface < Application, Landroid/os/IIncidentManager, getIncidentReport(Ljava/lang/String;Ljava/lang/String;Ljava/lang/String;)Landroid/os/IncidentManager$IncidentReport; > 23,2,3,4 @37 exception:24,
invokestatic < Application, Landroid/os/Binder, restoreCallingIdentity(J)V > 20 @41 exception:31,
return 25,","depth : 0
-----
depth : 1
-----
","public IncidentManager$IncidentReport getIncidentReport(String p1, String p2, String p3){
	if (p1 == 0) {
		if (p2 == 0) {
			if (p3 == 0) {
				int v1 = p1.length();
				if (v1 == 0) {
					int v2 = p2.length();
					if (v2 == 0) {
						int v3 = p3.length();
						if (v3 == 0) {
							long v5 = Binder.clearCallingIdentity();
							IIncidentManager v7 = this.this$0.getIIncidentManager();
							IIncidentManager v6 = v7;
							IncidentManager$IncidentReport v8 = v6.getIncidentReport(p1, p2, p3);
							Binder.restoreCallingIdentity(v5);
							return v8;
						}
					}
				}
			}
		}
	}
}
","SYS_OR_SIG"
"Lcom/android/server/incident/IncidentCompanionService$BinderService","getIncidentReport(Ljava/lang/String;Ljava/lang/String;Ljava/lang/String;)Landroid/os/IncidentManager$IncidentReport;","2","conditional branch(eq, to iindex=-1) 2,5,
conditional branch(eq, to iindex=-1) 3,5,
conditional branch(eq, to iindex=-1) 4,5,
7 = invokevirtual < Application, Ljava/lang/String, length()I > 2 @6 exception:6,
conditional branch(eq, to iindex=-1) 7,5,
9 = invokevirtual < Application, Ljava/lang/String, length()I > 3 @12 exception:8,
conditional branch(eq, to iindex=-1) 9,5,
11 = invokevirtual < Application, Ljava/lang/String, length()I > 4 @18 exception:10,
conditional branch(eq, to iindex=-1) 11,5,
invokevirtual < Application, Lcom/android/server/incident/IncidentCompanionService$BinderService, enforceAccessReportsPermissions(Ljava/lang/String;)V > 1,2 @24 exception:18,
20 = invokestatic < Application, Landroid/os/Binder, clearCallingIdentity()J > @27 exception:19,
21 = getfield < Application, Lcom/android/server/incident/IncidentCompanionService$BinderService, this$0, <Application,Lcom/android/server/incident/IncidentCompanionService> > 1,
23 = invokestatic < Application, Lcom/android/server/incident/IncidentCompanionService, -$$Nest$mgetIIncidentManager(Lcom/android/server/incident/IncidentCompanionService;)Landroid/os/IIncidentManager; > 21 @33 exception:22,
3 = invokevirtual < Application, Lcom/android/server/incident/IncidentCompanionService, getIIncidentManager()Landroid/os/IIncidentManager; > 1 @0 exception:2,
4 = invokestatic < Application, Landroid/os/ServiceManager, getService(Ljava/lang/String;)Landroid/os/IBinder; > 2 @2 exception:3,
6 = invokestatic < Application, Landroid/os/IIncidentManager$Stub, asInterface(Landroid/os/IBinder;)Landroid/os/IIncidentManager; > 4 @6 exception:5,
return 6,
return 3,
25 = invokeinterface < Application, Landroid/os/IIncidentManager, getIncidentReport(Ljava/lang/String;Ljava/lang/String;Ljava/lang/String;)Landroid/os/IncidentManager$IncidentReport; > 23,2,3,4 @37 exception:24,
invokestatic < Application, Landroid/os/Binder, restoreCallingIdentity(J)V > 20 @41 exception:31,
return 25,","depth : 0
-----
depth : 1
-----
depth : 2
-----
","public IncidentManager$IncidentReport getIncidentReport(String p1, String p2, String p3){
	if (p1 == 0) {
		if (p2 == 0) {
			if (p3 == 0) {
				int v1 = p1.length();
				if (v1 == 0) {
					int v2 = p2.length();
					if (v2 == 0) {
						int v3 = p3.length();
						if (v3 == 0) {
							long v5 = Binder.clearCallingIdentity();
							IBinder v8 = ServiceManager.getService(""incident"");
							IIncidentManager v9 = IIncidentManager$Stub.asInterface(v8);
							IIncidentManager v7 = v9;
							IIncidentManager v6 = v7;
							IncidentManager$IncidentReport v10 = v6.getIncidentReport(p1, p2, p3);
							Binder.restoreCallingIdentity(v5);
							return v10;
						}
					}
				}
			}
		}
	}
}
","SYS_OR_SIG"

"Lcom/android/server/incident/IncidentCompanionService$BinderService","cancelAuthorization(Landroid/os/IIncidentAuthListener;)V","0","invokevirtual < Application, Lcom/android/server/incident/IncidentCompanionService$BinderService, enforceRequestAuthorizationPermission()V > 1 @0 exception:3,
5 = invokestatic < Application, Landroid/os/Binder, clearCallingIdentity()J > @3 exception:4,
6 = getfield < Application, Lcom/android/server/incident/IncidentCompanionService$BinderService, this$0, <Application,Lcom/android/server/incident/IncidentCompanionService> > 1,
8 = invokestatic < Application, Lcom/android/server/incident/IncidentCompanionService, -$$Nest$fgetmPendingReports(Lcom/android/server/incident/IncidentCompanionService;)Lcom/android/server/incident/PendingReports; > 6 @9 exception:7,
invokevirtual < Application, Lcom/android/server/incident/PendingReports, cancelAuthorization(Landroid/os/IIncidentAuthListener;)V > 8,2 @13 exception:9,
invokestatic < Application, Landroid/os/Binder, restoreCallingIdentity(J)V > 5 @16 exception:15,
return,","depth : 0
-----
","public void cancelAuthorization(IIncidentAuthListener p1){
	long v2 = Binder.clearCallingIdentity();
	PendingReports v3 = IncidentCompanionService.-$$Nest$fgetmPendingReports(this.this$0);
	v3.cancelAuthorization(p1);
	Binder.restoreCallingIdentity(v2);
	return;
}
","SYS_OR_SIG"
"Lcom/android/server/incident/IncidentCompanionService$BinderService","cancelAuthorization(Landroid/os/IIncidentAuthListener;)V","1","invokevirtual < Application, Lcom/android/server/incident/IncidentCompanionService$BinderService, enforceRequestAuthorizationPermission()V > 1 @0 exception:3,
5 = invokestatic < Application, Landroid/os/Binder, clearCallingIdentity()J > @3 exception:4,
6 = getfield < Application, Lcom/android/server/incident/IncidentCompanionService$BinderService, this$0, <Application,Lcom/android/server/incident/IncidentCompanionService> > 1,
8 = invokestatic < Application, Lcom/android/server/incident/IncidentCompanionService, -$$Nest$fgetmPendingReports(Lcom/android/server/incident/IncidentCompanionService;)Lcom/android/server/incident/PendingReports; > 6 @9 exception:7,
2 = getfield < Application, Lcom/android/server/incident/IncidentCompanionService, mPendingReports, <Application,Lcom/android/server/incident/PendingReports> > 1,
return 2,
invokevirtual < Application, Lcom/android/server/incident/PendingReports, cancelAuthorization(Landroid/os/IIncidentAuthListener;)V > 8,2 @13 exception:9,
3 = getfield < Application, Lcom/android/server/incident/PendingReports, mRequestQueue, <Application,Lcom/android/server/incident/RequestQueue> > 1,
5 = invokeinterface < Application, Landroid/os/IIncidentAuthListener, asBinder()Landroid/os/IBinder; > 2 @2 exception:4,
6 = new <Application,Lcom/android/server/incident/PendingReports$$ExternalSyntheticLambda1>@6,
invokespecial < Application, Lcom/android/server/incident/PendingReports$$ExternalSyntheticLambda1, <init>(Lcom/android/server/incident/PendingReports;Landroid/os/IIncidentAuthListener;)V > 6,1,2 @8 exception:7,
invokevirtual < Application, Lcom/android/server/incident/RequestQueue, enqueue(Landroid/os/IBinder;ZLjava/lang/Runnable;)V > 3,5,8,6 @12 exception:9,
return,
invokestatic < Application, Landroid/os/Binder, restoreCallingIdentity(J)V > 5 @16 exception:15,
return,","depth : 0
-----
depth : 1
-----
depth : 1
-----
","public void cancelAuthorization(IIncidentAuthListener p1){
	long v2 = Binder.clearCallingIdentity();
	PendingReports v3 = this.mPendingReports;
	IBinder v5 = p1.asBinder();
	PendingReports$$ExternalSyntheticLambda1 v6 = new PendingReports$$ExternalSyntheticLambda1(PendingReports,p1);
	this.mRequestQueue.enqueue(v5, 0, v6);
	Binder.restoreCallingIdentity(v2);
	return;
}
","SYS_OR_SIG"
"Lcom/android/server/incident/IncidentCompanionService$BinderService","cancelAuthorization(Landroid/os/IIncidentAuthListener;)V","2","invokevirtual < Application, Lcom/android/server/incident/IncidentCompanionService$BinderService, enforceRequestAuthorizationPermission()V > 1 @0 exception:3,
5 = invokestatic < Application, Landroid/os/Binder, clearCallingIdentity()J > @3 exception:4,
6 = getfield < Application, Lcom/android/server/incident/IncidentCompanionService$BinderService, this$0, <Application,Lcom/android/server/incident/IncidentCompanionService> > 1,
8 = invokestatic < Application, Lcom/android/server/incident/IncidentCompanionService, -$$Nest$fgetmPendingReports(Lcom/android/server/incident/IncidentCompanionService;)Lcom/android/server/incident/PendingReports; > 6 @9 exception:7,
2 = getfield < Application, Lcom/android/server/incident/IncidentCompanionService, mPendingReports, <Application,Lcom/android/server/incident/PendingReports> > 1,
return 2,
invokevirtual < Application, Lcom/android/server/incident/PendingReports, cancelAuthorization(Landroid/os/IIncidentAuthListener;)V > 8,2 @13 exception:9,
3 = getfield < Application, Lcom/android/server/incident/PendingReports, mRequestQueue, <Application,Lcom/android/server/incident/RequestQueue> > 1,
5 = invokeinterface < Application, Landroid/os/IIncidentAuthListener, asBinder()Landroid/os/IBinder; > 2 @2 exception:4,
6 = new <Application,Lcom/android/server/incident/PendingReports$$ExternalSyntheticLambda1>@6,
invokespecial < Application, Lcom/android/server/incident/PendingReports$$ExternalSyntheticLambda1, <init>(Lcom/android/server/incident/PendingReports;Landroid/os/IIncidentAuthListener;)V > 6,1,2 @8 exception:7,
invokevirtual < Application, Lcom/android/server/incident/RequestQueue, enqueue(Landroid/os/IBinder;ZLjava/lang/Runnable;)V > 3,5,8,6 @12 exception:9,
5 = getfield < Application, Lcom/android/server/incident/RequestQueue, mPending, <Application,Ljava/util/ArrayList> > 1,
monitorenter 5,
conditional branch(ne, to iindex=-1) 3,6,
8 = getfield < Application, Lcom/android/server/incident/RequestQueue, mPending, <Application,Ljava/util/ArrayList> > 1,
10 = invokevirtual < Application, Ljava/util/ArrayList, size()I > 8 @9 exception:9,
11 = binaryop(sub) 10 , 7,
21 = phi  20,11,
conditional branch(lt, to iindex=-1) 21,6,
12 = getfield < Application, Lcom/android/server/incident/RequestQueue, mPending, <Application,Ljava/util/ArrayList> > 1,
14 = invokevirtual < Application, Ljava/util/ArrayList, get(I)Ljava/lang/Object; > 12,21 @18 exception:13,
15 = checkcast <Application,Lcom/android/server/incident/RequestQueue$Rec>14 <Application,Lcom/android/server/incident/RequestQueue$Rec>,
16 = getfield < Application, Lcom/android/server/incident/RequestQueue$Rec, key, <Application,Landroid/os/IBinder> > 15,
conditional branch(ne, to iindex=-1) 16,2,
17 = getfield < Application, Lcom/android/server/incident/RequestQueue$Rec, value, <Primordial,Z> > 15,
conditional branch(eq, to iindex=-1) 17,6,
20 = binaryop(add) 21 , 19,
goto (from iindex= 23 to iindex = -27),
21 = phi  20,11,
conditional branch(lt, to iindex=-1) 21,6,
12 = getfield < Application, Lcom/android/server/incident/RequestQueue, mPending, <Application,Ljava/util/ArrayList> > 1,
14 = invokevirtual < Application, Ljava/util/ArrayList, get(I)Ljava/lang/Object; > 12,21 @18 exception:13,
15 = checkcast <Application,Lcom/android/server/incident/RequestQueue$Rec>14 <Application,Lcom/android/server/incident/RequestQueue$Rec>,
16 = getfield < Application, Lcom/android/server/incident/RequestQueue$Rec, key, <Application,Landroid/os/IBinder> > 15,
conditional branch(ne, to iindex=-1) 16,2,
17 = getfield < Application, Lcom/android/server/incident/RequestQueue$Rec, value, <Primordial,Z> > 15,
conditional branch(eq, to iindex=-1) 17,6,
24 = getfield < Application, Lcom/android/server/incident/RequestQueue, mPending, <Application,Ljava/util/ArrayList> > 1,
26 = invokevirtual < Application, Ljava/util/ArrayList, remove(I)Ljava/lang/Object; > 24,21 @34 exception:25,
goto (from iindex= 21 to iindex = 6),
27 = phi  6,6,7,
conditional branch(ne, to iindex=-1) 27,6,
31 = getfield < Application, Lcom/android/server/incident/RequestQueue, mPending, <Application,Ljava/util/ArrayList> > 1,
32 = new <Application,Lcom/android/server/incident/RequestQueue$Rec>@48,
invokespecial < Application, Lcom/android/server/incident/RequestQueue$Rec, <init>(Lcom/android/server/incident/RequestQueue;Landroid/os/IBinder;ZLjava/lang/Runnable;)V > 32,1,2,3,4 @50 exception:33,
35 = invokevirtual < Application, Ljava/util/ArrayList, add(Ljava/lang/Object;)Z > 31,32 @53 exception:34,
40 = getfield < Application, Lcom/android/server/incident/RequestQueue, mStarted, <Primordial,Z> > 1,
conditional branch(eq, to iindex=-1) 40,6,
41 = getfield < Application, Lcom/android/server/incident/RequestQueue, mHandler, <Application,Landroid/os/Handler> > 1,
42 = getfield < Application, Lcom/android/server/incident/RequestQueue, mWorker, <Application,Ljava/lang/Runnable> > 1,
44 = invokevirtual < Application, Landroid/os/Handler, post(Ljava/lang/Runnable;)Z > 41,42 @64 exception:43,
monitorexit 5,
return,
return,
invokestatic < Application, Landroid/os/Binder, restoreCallingIdentity(J)V > 5 @16 exception:15,
return,","depth : 0
-----
depth : 1
-----
depth : 1
-----
depth : 2
-----
","public void cancelAuthorization(IIncidentAuthListener p1){
	long v2 = Binder.clearCallingIdentity();
	PendingReports v3 = this.mPendingReports;
	IBinder v5 = p1.asBinder();
	PendingReports$$ExternalSyntheticLambda1 v6 = new PendingReports$$ExternalSyntheticLambda1(PendingReports,p1);
	if (0 != 0) {
		int v9 = this.mPending.size();
		if ((v9 - 1) < 0) {
			Object v10 = this.mPending.get((v9 - 1));
			if (RequestQueue$Rec.key != v5) {
				if (RequestQueue$Rec.value == 0) {
					if (((v9 - 1) + -1) < 0) {
						Object v11 = this.mPending.get(((v9 - 1) + -1));
						if (RequestQueue$Rec.key != v5) {
							if (RequestQueue$Rec.value == 0) {
								Object v12 = this.mPending.remove(((v9 - 1) + -1));
								if (0 != 0) {
									RequestQueue$Rec v13 = new RequestQueue$Rec(RequestQueue,v5,0,v6);
									boolean v15 = this.mPending.add(v13);
									if (this.mStarted == 0) {
										boolean v16 = this.mHandler.post(this.mWorker);
										Binder.restoreCallingIdentity(v2);
										return;
									}
								}
							}
						}
					}
				}
			}
		}
	}
}
","SYS_OR_SIG"

"Lcom/android/server/incident/IncidentCompanionService$BinderService","sendReportReadyBroadcast(Ljava/lang/String;Ljava/lang/String;)V","0","invokevirtual < Application, Lcom/android/server/incident/IncidentCompanionService$BinderService, enforceRequestAuthorizationPermission()V > 1 @0 exception:4,
6 = invokestatic < Application, Landroid/os/Binder, clearCallingIdentity()J > @3 exception:5,
7 = getfield < Application, Lcom/android/server/incident/IncidentCompanionService$BinderService, this$0, <Application,Lcom/android/server/incident/IncidentCompanionService> > 1,
9 = invokevirtual < Application, Lcom/android/server/SystemService, getContext()Landroid/content/Context; > 7 @9 exception:8,
11 = invokestatic < Application, Lcom/android/server/incident/IncidentCompanionService, getAndValidateUser(Landroid/content/Context;)I > 9 @13 exception:10,
conditional branch(ne, to iindex=-1) 11,12,
invokestatic < Application, Landroid/os/Binder, restoreCallingIdentity(J)V > 6 @21 exception:58,
return,","depth : 0
-----
","public void sendReportReadyBroadcast(String p1, String p2){
	long v2 = Binder.clearCallingIdentity();
	Context v3 = this.this$0.getContext();
	int v4 = IncidentCompanionService.getAndValidateUser(v3);
	if (v4 != -10000) {
		Binder.restoreCallingIdentity(v2);
		return;
	}
}
","SYS_OR_SIG"
"Lcom/android/server/incident/IncidentCompanionService$BinderService","sendReportReadyBroadcast(Ljava/lang/String;Ljava/lang/String;)V","0","invokevirtual < Application, Lcom/android/server/incident/IncidentCompanionService$BinderService, enforceRequestAuthorizationPermission()V > 1 @0 exception:4,
6 = invokestatic < Application, Landroid/os/Binder, clearCallingIdentity()J > @3 exception:5,
7 = getfield < Application, Lcom/android/server/incident/IncidentCompanionService$BinderService, this$0, <Application,Lcom/android/server/incident/IncidentCompanionService> > 1,
9 = invokevirtual < Application, Lcom/android/server/SystemService, getContext()Landroid/content/Context; > 7 @9 exception:8,
11 = invokestatic < Application, Lcom/android/server/incident/IncidentCompanionService, getAndValidateUser(Landroid/content/Context;)I > 9 @13 exception:10,
conditional branch(ne, to iindex=-1) 11,12,
13 = new <Application,Landroid/content/Intent>@25,
invokespecial < Application, Landroid/content/Intent, <init>(Ljava/lang/String;)V > 13,14 @29 exception:15,
16 = new <Application,Landroid/content/ComponentName>@32,
invokespecial < Application, Landroid/content/ComponentName, <init>(Ljava/lang/String;Ljava/lang/String;)V > 16,2,3 @34 exception:17,
19 = invokevirtual < Application, Landroid/content/Intent, setComponent(Landroid/content/ComponentName;)Landroid/content/Intent; > 13,16 @37 exception:18,
21 = new <Application,Ljava/lang/StringBuilder>@42,
invokespecial < Application, Ljava/lang/StringBuilder, <init>()V > 21 @44 exception:22,
25 = invokevirtual < Application, Ljava/lang/StringBuilder, append(Ljava/lang/String;)Ljava/lang/StringBuilder; > 21,23 @50 exception:24,
27 = invokevirtual < Application, Ljava/lang/StringBuilder, append(I)Ljava/lang/StringBuilder; > 21,11 @53 exception:26,
30 = invokevirtual < Application, Ljava/lang/StringBuilder, append(Ljava/lang/String;)Ljava/lang/StringBuilder; > 21,28 @58 exception:29,
32 = invokestatic < Application, Landroid/os/UserHandle, getUserHandleForUid(I)Landroid/os/UserHandle; > 11 @61 exception:31,
34 = invokevirtual < Application, Ljava/lang/StringBuilder, append(Ljava/lang/Object;)Ljava/lang/StringBuilder; > 21,32 @65 exception:33,
37 = invokevirtual < Application, Ljava/lang/StringBuilder, append(Ljava/lang/String;)Ljava/lang/StringBuilder; > 21,35 @70 exception:36,
39 = invokevirtual < Application, Ljava/lang/StringBuilder, append(Ljava/lang/Object;)Ljava/lang/StringBuilder; > 21,13 @73 exception:38,
41 = invokevirtual < Application, Ljava/lang/StringBuilder, toString()Ljava/lang/String; > 21 @76 exception:40,
43 = invokestatic < Application, Landroid/util/Log, d(Ljava/lang/String;Ljava/lang/String;)I > 20,41 @80 exception:42,
45 = invokestatic < Application, Landroid/os/UserHandle, getUserHandleForUid(I)Landroid/os/UserHandle; > 11 @83 exception:44,
47 = invokestatic < Application, Lcom/android/server/incident/IncidentCompanionService, -$$Nest$sfgetDUMP_AND_USAGE_STATS_PERMISSIONS()[Ljava/lang/String; > @87 exception:46,
invokevirtual < Application, Landroid/content/Context, sendBroadcastAsUserMultiplePermissions(Landroid/content/Intent;Landroid/os/UserHandle;[Ljava/lang/String;)V > 9,13,45,47 @91 exception:48,
invokestatic < Application, Landroid/os/Binder, restoreCallingIdentity(J)V > 6 @94 exception:57,
return,","depth : 0
-----
","public void sendReportReadyBroadcast(String p1, String p2){
	long v2 = Binder.clearCallingIdentity();
	Context v3 = this.this$0.getContext();
	int v4 = IncidentCompanionService.getAndValidateUser(v3);
	if (v4 != -10000) {
		Intent v5 = new Intent(""android.intent.action.INCIDENT_REPORT_READY"");
		ComponentName v7 = new ComponentName(p1,p2);
		Intent v9 = v5.setComponent(v7);
		UserHandle v15 = UserHandle.getUserHandleForUid(v4);
		UserHandle v21 = UserHandle.getUserHandleForUid(v4);
		v3.sendBroadcastAsUserMultiplePermissions(v5, v21, v22);
		Binder.restoreCallingIdentity(v2);
		return;
	}
}
","SYS_OR_SIG"
"Lcom/android/server/incident/IncidentCompanionService$BinderService","sendReportReadyBroadcast(Ljava/lang/String;Ljava/lang/String;)V","1","invokevirtual < Application, Lcom/android/server/incident/IncidentCompanionService$BinderService, enforceRequestAuthorizationPermission()V > 1 @0 exception:4,
6 = invokestatic < Application, Landroid/os/Binder, clearCallingIdentity()J > @3 exception:5,
7 = getfield < Application, Lcom/android/server/incident/IncidentCompanionService$BinderService, this$0, <Application,Lcom/android/server/incident/IncidentCompanionService> > 1,
9 = invokevirtual < Application, Lcom/android/server/SystemService, getContext()Landroid/content/Context; > 7 @9 exception:8,
11 = invokestatic < Application, Lcom/android/server/incident/IncidentCompanionService, getAndValidateUser(Landroid/content/Context;)I > 9 @13 exception:10,
3 = invokestatic < Application, Landroid/app/ActivityManager, getService()Landroid/app/IActivityManager; > @0 exception:2,
5 = invokeinterface < Application, Landroid/app/IActivityManager, getCurrentUser()Landroid/content/pm/UserInfo; > 3 @4 exception:4,
12 = invokestatic < Application, Landroid/os/UserManager, get(Landroid/content/Context;)Landroid/os/UserManager; > 1 @8 exception:11,
14 = invokevirtual < Application, Landroid/os/UserManager, getPrimaryUser()Landroid/content/pm/UserInfo; > 12 @12 exception:13,
conditional branch(ne, to iindex=-1) 5,17,
conditional branch(ne, to iindex=-1) 14,17,
18 = getfield < Application, Landroid/content/pm/UserInfo, id, <Primordial,I> > 14,
19 = getfield < Application, Landroid/content/pm/UserInfo, id, <Primordial,I> > 5,
conditional branch(eq, to iindex=-1) 18,19,
return 18,
conditional branch(ne, to iindex=-1) 11,12,
invokestatic < Application, Landroid/os/Binder, restoreCallingIdentity(J)V > 6 @21 exception:58,
return,","depth : 0
-----
depth : 1
-----
","public void sendReportReadyBroadcast(String p1, String p2){
	long v2 = Binder.clearCallingIdentity();
	Context v3 = this.this$0.getContext();
	if (v8 != 0) {
		if (UserInfo.id == UserInfo.id) {
			int v4 = UserInfo.id;
			if (v4 != -10000) {
				Binder.restoreCallingIdentity(v2);
				return;
			}
		}
	}
}
","SYS_OR_SIG"
"Lcom/android/server/incident/IncidentCompanionService$BinderService","sendReportReadyBroadcast(Ljava/lang/String;Ljava/lang/String;)V","1","invokevirtual < Application, Lcom/android/server/incident/IncidentCompanionService$BinderService, enforceRequestAuthorizationPermission()V > 1 @0 exception:4,
6 = invokestatic < Application, Landroid/os/Binder, clearCallingIdentity()J > @3 exception:5,
7 = getfield < Application, Lcom/android/server/incident/IncidentCompanionService$BinderService, this$0, <Application,Lcom/android/server/incident/IncidentCompanionService> > 1,
9 = invokevirtual < Application, Lcom/android/server/SystemService, getContext()Landroid/content/Context; > 7 @9 exception:8,
11 = invokestatic < Application, Lcom/android/server/incident/IncidentCompanionService, getAndValidateUser(Landroid/content/Context;)I > 9 @13 exception:10,
3 = invokestatic < Application, Landroid/app/ActivityManager, getService()Landroid/app/IActivityManager; > @0 exception:2,
5 = invokeinterface < Application, Landroid/app/IActivityManager, getCurrentUser()Landroid/content/pm/UserInfo; > 3 @4 exception:4,
12 = invokestatic < Application, Landroid/os/UserManager, get(Landroid/content/Context;)Landroid/os/UserManager; > 1 @8 exception:11,
14 = invokevirtual < Application, Landroid/os/UserManager, getPrimaryUser()Landroid/content/pm/UserInfo; > 12 @12 exception:13,
conditional branch(ne, to iindex=-1) 5,17,
conditional branch(ne, to iindex=-1) 14,17,
18 = getfield < Application, Landroid/content/pm/UserInfo, id, <Primordial,I> > 14,
19 = getfield < Application, Landroid/content/pm/UserInfo, id, <Primordial,I> > 5,
conditional branch(eq, to iindex=-1) 18,19,
return 18,
conditional branch(ne, to iindex=-1) 11,12,
13 = new <Application,Landroid/content/Intent>@25,
invokespecial < Application, Landroid/content/Intent, <init>(Ljava/lang/String;)V > 13,14 @29 exception:15,
16 = new <Application,Landroid/content/ComponentName>@32,
invokespecial < Application, Landroid/content/ComponentName, <init>(Ljava/lang/String;Ljava/lang/String;)V > 16,2,3 @34 exception:17,
19 = invokevirtual < Application, Landroid/content/Intent, setComponent(Landroid/content/ComponentName;)Landroid/content/Intent; > 13,16 @37 exception:18,
21 = new <Application,Ljava/lang/StringBuilder>@42,
invokespecial < Application, Ljava/lang/StringBuilder, <init>()V > 21 @44 exception:22,
25 = invokevirtual < Application, Ljava/lang/StringBuilder, append(Ljava/lang/String;)Ljava/lang/StringBuilder; > 21,23 @50 exception:24,
27 = invokevirtual < Application, Ljava/lang/StringBuilder, append(I)Ljava/lang/StringBuilder; > 21,11 @53 exception:26,
30 = invokevirtual < Application, Ljava/lang/StringBuilder, append(Ljava/lang/String;)Ljava/lang/StringBuilder; > 21,28 @58 exception:29,
32 = invokestatic < Application, Landroid/os/UserHandle, getUserHandleForUid(I)Landroid/os/UserHandle; > 11 @61 exception:31,
34 = invokevirtual < Application, Ljava/lang/StringBuilder, append(Ljava/lang/Object;)Ljava/lang/StringBuilder; > 21,32 @65 exception:33,
37 = invokevirtual < Application, Ljava/lang/StringBuilder, append(Ljava/lang/String;)Ljava/lang/StringBuilder; > 21,35 @70 exception:36,
39 = invokevirtual < Application, Ljava/lang/StringBuilder, append(Ljava/lang/Object;)Ljava/lang/StringBuilder; > 21,13 @73 exception:38,
41 = invokevirtual < Application, Ljava/lang/StringBuilder, toString()Ljava/lang/String; > 21 @76 exception:40,
43 = invokestatic < Application, Landroid/util/Log, d(Ljava/lang/String;Ljava/lang/String;)I > 20,41 @80 exception:42,
45 = invokestatic < Application, Landroid/os/UserHandle, getUserHandleForUid(I)Landroid/os/UserHandle; > 11 @83 exception:44,
47 = invokestatic < Application, Lcom/android/server/incident/IncidentCompanionService, -$$Nest$sfgetDUMP_AND_USAGE_STATS_PERMISSIONS()[Ljava/lang/String; > @87 exception:46,
invokevirtual < Application, Landroid/content/Context, sendBroadcastAsUserMultiplePermissions(Landroid/content/Intent;Landroid/os/UserHandle;[Ljava/lang/String;)V > 9,13,45,47 @91 exception:48,
invokestatic < Application, Landroid/os/Binder, restoreCallingIdentity(J)V > 6 @94 exception:57,
return,","depth : 0
-----
depth : 1
-----
","public void sendReportReadyBroadcast(String p1, String p2){
	long v2 = Binder.clearCallingIdentity();
	Context v3 = this.this$0.getContext();
	if (v8 != 0) {
		if (UserInfo.id == UserInfo.id) {
			int v4 = UserInfo.id;
			if (v4 != -10000) {
				Intent v9 = new Intent(""android.intent.action.INCIDENT_REPORT_READY"");
				ComponentName v11 = new ComponentName(p1,p2);
				Intent v13 = v9.setComponent(v11);
				UserHandle v19 = UserHandle.getUserHandleForUid(v4);
				UserHandle v25 = UserHandle.getUserHandleForUid(v4);
				v3.sendBroadcastAsUserMultiplePermissions(v9, v25, v26);
				Binder.restoreCallingIdentity(v2);
				return;
			}
		}
	}
}
","SYS_OR_SIG"

"Lcom/android/server/incident/IncidentCompanionService$BinderService","authorizeReport(ILjava/lang/String;Ljava/lang/String;Ljava/lang/String;ILandroid/os/IIncidentAuthListener;)V","0","invokevirtual < Application, Lcom/android/server/incident/IncidentCompanionService$BinderService, enforceRequestAuthorizationPermission()V > 1 @0 exception:8,
10 = invokestatic < Application, Landroid/os/Binder, clearCallingIdentity()J > @3 exception:9,
11 = getfield < Application, Lcom/android/server/incident/IncidentCompanionService$BinderService, this$0, <Application,Lcom/android/server/incident/IncidentCompanionService> > 1,
13 = invokestatic < Application, Lcom/android/server/incident/IncidentCompanionService, -$$Nest$fgetmPendingReports(Lcom/android/server/incident/IncidentCompanionService;)Lcom/android/server/incident/PendingReports; > 11 @9 exception:12,
invokevirtual < Application, Lcom/android/server/incident/PendingReports, authorizeReport(ILjava/lang/String;Ljava/lang/String;Ljava/lang/String;ILandroid/os/IIncidentAuthListener;)V > 13,2,3,4,5,6,7 @19 exception:14,
invokestatic < Application, Landroid/os/Binder, restoreCallingIdentity(J)V > 10 @22 exception:19,
return,","depth : 0
-----
","public void authorizeReport(int p1, String p2, String p3, String p4, int p5, IIncidentAuthListener p6){
	long v2 = Binder.clearCallingIdentity();
	PendingReports v3 = IncidentCompanionService.-$$Nest$fgetmPendingReports(this.this$0);
	v3.authorizeReport(p1, p2, p3, p4, p5, p6);
	Binder.restoreCallingIdentity(v2);
	return;
}
","SYS_OR_SIG"
"Lcom/android/server/incident/IncidentCompanionService$BinderService","authorizeReport(ILjava/lang/String;Ljava/lang/String;Ljava/lang/String;ILandroid/os/IIncidentAuthListener;)V","1","invokevirtual < Application, Lcom/android/server/incident/IncidentCompanionService$BinderService, enforceRequestAuthorizationPermission()V > 1 @0 exception:8,
10 = invokestatic < Application, Landroid/os/Binder, clearCallingIdentity()J > @3 exception:9,
11 = getfield < Application, Lcom/android/server/incident/IncidentCompanionService$BinderService, this$0, <Application,Lcom/android/server/incident/IncidentCompanionService> > 1,
13 = invokestatic < Application, Lcom/android/server/incident/IncidentCompanionService, -$$Nest$fgetmPendingReports(Lcom/android/server/incident/IncidentCompanionService;)Lcom/android/server/incident/PendingReports; > 11 @9 exception:12,
2 = getfield < Application, Lcom/android/server/incident/IncidentCompanionService, mPendingReports, <Application,Lcom/android/server/incident/PendingReports> > 1,
return 2,
invokevirtual < Application, Lcom/android/server/incident/PendingReports, authorizeReport(ILjava/lang/String;Ljava/lang/String;Ljava/lang/String;ILandroid/os/IIncidentAuthListener;)V > 13,2,3,4,5,6,7 @19 exception:14,
8 = getfield < Application, Lcom/android/server/incident/PendingReports, mRequestQueue, <Application,Lcom/android/server/incident/RequestQueue> > 1,
10 = invokeinterface < Application, Landroid/os/IIncidentAuthListener, asBinder()Landroid/os/IBinder; > 7 @3 exception:9,
11 = new <Application,Lcom/android/server/incident/PendingReports$$ExternalSyntheticLambda0>@7,
invokespecial < Application, Lcom/android/server/incident/PendingReports$$ExternalSyntheticLambda0, <init>(Lcom/android/server/incident/PendingReports;ILjava/lang/String;Ljava/lang/String;Ljava/lang/String;ILandroid/os/IIncidentAuthListener;)V > 11,1,2,3,4,5,6,7 @18 exception:12,
invokevirtual < Application, Lcom/android/server/incident/RequestQueue, enqueue(Landroid/os/IBinder;ZLjava/lang/Runnable;)V > 8,10,13,11 @22 exception:14,
return,
invokestatic < Application, Landroid/os/Binder, restoreCallingIdentity(J)V > 10 @22 exception:19,
return,","depth : 0
-----
depth : 1
-----
depth : 1
-----
","public void authorizeReport(int p1, String p2, String p3, String p4, int p5, IIncidentAuthListener p6){
	long v2 = Binder.clearCallingIdentity();
	PendingReports v3 = this.mPendingReports;
	IBinder v5 = p6.asBinder();
	PendingReports$$ExternalSyntheticLambda0 v6 = new PendingReports$$ExternalSyntheticLambda0(PendingReports,p1,p2,p3,p4,p5,p6);
	this.mRequestQueue.enqueue(v5, 1, v6);
	Binder.restoreCallingIdentity(v2);
	return;
}
","SYS_OR_SIG"
"Lcom/android/server/incident/IncidentCompanionService$BinderService","authorizeReport(ILjava/lang/String;Ljava/lang/String;Ljava/lang/String;ILandroid/os/IIncidentAuthListener;)V","2","invokevirtual < Application, Lcom/android/server/incident/IncidentCompanionService$BinderService, enforceRequestAuthorizationPermission()V > 1 @0 exception:8,
10 = invokestatic < Application, Landroid/os/Binder, clearCallingIdentity()J > @3 exception:9,
11 = getfield < Application, Lcom/android/server/incident/IncidentCompanionService$BinderService, this$0, <Application,Lcom/android/server/incident/IncidentCompanionService> > 1,
13 = invokestatic < Application, Lcom/android/server/incident/IncidentCompanionService, -$$Nest$fgetmPendingReports(Lcom/android/server/incident/IncidentCompanionService;)Lcom/android/server/incident/PendingReports; > 11 @9 exception:12,
2 = getfield < Application, Lcom/android/server/incident/IncidentCompanionService, mPendingReports, <Application,Lcom/android/server/incident/PendingReports> > 1,
return 2,
invokevirtual < Application, Lcom/android/server/incident/PendingReports, authorizeReport(ILjava/lang/String;Ljava/lang/String;Ljava/lang/String;ILandroid/os/IIncidentAuthListener;)V > 13,2,3,4,5,6,7 @19 exception:14,
8 = getfield < Application, Lcom/android/server/incident/PendingReports, mRequestQueue, <Application,Lcom/android/server/incident/RequestQueue> > 1,
10 = invokeinterface < Application, Landroid/os/IIncidentAuthListener, asBinder()Landroid/os/IBinder; > 7 @3 exception:9,
11 = new <Application,Lcom/android/server/incident/PendingReports$$ExternalSyntheticLambda0>@7,
invokespecial < Application, Lcom/android/server/incident/PendingReports$$ExternalSyntheticLambda0, <init>(Lcom/android/server/incident/PendingReports;ILjava/lang/String;Ljava/lang/String;Ljava/lang/String;ILandroid/os/IIncidentAuthListener;)V > 11,1,2,3,4,5,6,7 @18 exception:12,
invokevirtual < Application, Lcom/android/server/incident/RequestQueue, enqueue(Landroid/os/IBinder;ZLjava/lang/Runnable;)V > 8,10,13,11 @22 exception:14,
5 = getfield < Application, Lcom/android/server/incident/RequestQueue, mPending, <Application,Ljava/util/ArrayList> > 1,
monitorenter 5,
conditional branch(ne, to iindex=-1) 3,6,
8 = getfield < Application, Lcom/android/server/incident/RequestQueue, mPending, <Application,Ljava/util/ArrayList> > 1,
10 = invokevirtual < Application, Ljava/util/ArrayList, size()I > 8 @9 exception:9,
11 = binaryop(sub) 10 , 7,
21 = phi  20,11,
conditional branch(lt, to iindex=-1) 21,6,
12 = getfield < Application, Lcom/android/server/incident/RequestQueue, mPending, <Application,Ljava/util/ArrayList> > 1,
14 = invokevirtual < Application, Ljava/util/ArrayList, get(I)Ljava/lang/Object; > 12,21 @18 exception:13,
15 = checkcast <Application,Lcom/android/server/incident/RequestQueue$Rec>14 <Application,Lcom/android/server/incident/RequestQueue$Rec>,
16 = getfield < Application, Lcom/android/server/incident/RequestQueue$Rec, key, <Application,Landroid/os/IBinder> > 15,
conditional branch(ne, to iindex=-1) 16,2,
17 = getfield < Application, Lcom/android/server/incident/RequestQueue$Rec, value, <Primordial,Z> > 15,
conditional branch(eq, to iindex=-1) 17,6,
20 = binaryop(add) 21 , 19,
goto (from iindex= 23 to iindex = -27),
21 = phi  20,11,
conditional branch(lt, to iindex=-1) 21,6,
12 = getfield < Application, Lcom/android/server/incident/RequestQueue, mPending, <Application,Ljava/util/ArrayList> > 1,
14 = invokevirtual < Application, Ljava/util/ArrayList, get(I)Ljava/lang/Object; > 12,21 @18 exception:13,
15 = checkcast <Application,Lcom/android/server/incident/RequestQueue$Rec>14 <Application,Lcom/android/server/incident/RequestQueue$Rec>,
16 = getfield < Application, Lcom/android/server/incident/RequestQueue$Rec, key, <Application,Landroid/os/IBinder> > 15,
conditional branch(ne, to iindex=-1) 16,2,
17 = getfield < Application, Lcom/android/server/incident/RequestQueue$Rec, value, <Primordial,Z> > 15,
conditional branch(eq, to iindex=-1) 17,6,
24 = getfield < Application, Lcom/android/server/incident/RequestQueue, mPending, <Application,Ljava/util/ArrayList> > 1,
26 = invokevirtual < Application, Ljava/util/ArrayList, remove(I)Ljava/lang/Object; > 24,21 @34 exception:25,
goto (from iindex= 21 to iindex = 6),
27 = phi  6,6,7,
conditional branch(ne, to iindex=-1) 27,6,
31 = getfield < Application, Lcom/android/server/incident/RequestQueue, mPending, <Application,Ljava/util/ArrayList> > 1,
32 = new <Application,Lcom/android/server/incident/RequestQueue$Rec>@48,
invokespecial < Application, Lcom/android/server/incident/RequestQueue$Rec, <init>(Lcom/android/server/incident/RequestQueue;Landroid/os/IBinder;ZLjava/lang/Runnable;)V > 32,1,2,3,4 @50 exception:33,
35 = invokevirtual < Application, Ljava/util/ArrayList, add(Ljava/lang/Object;)Z > 31,32 @53 exception:34,
40 = getfield < Application, Lcom/android/server/incident/RequestQueue, mStarted, <Primordial,Z> > 1,
conditional branch(eq, to iindex=-1) 40,6,
41 = getfield < Application, Lcom/android/server/incident/RequestQueue, mHandler, <Application,Landroid/os/Handler> > 1,
42 = getfield < Application, Lcom/android/server/incident/RequestQueue, mWorker, <Application,Ljava/lang/Runnable> > 1,
44 = invokevirtual < Application, Landroid/os/Handler, post(Ljava/lang/Runnable;)Z > 41,42 @64 exception:43,
monitorexit 5,
return,
return,
invokestatic < Application, Landroid/os/Binder, restoreCallingIdentity(J)V > 10 @22 exception:19,
return,","depth : 0
-----
depth : 1
-----
depth : 1
-----
depth : 2
-----
","public void authorizeReport(int p1, String p2, String p3, String p4, int p5, IIncidentAuthListener p6){
	long v2 = Binder.clearCallingIdentity();
	PendingReports v3 = this.mPendingReports;
	IBinder v5 = p6.asBinder();
	PendingReports$$ExternalSyntheticLambda0 v6 = new PendingReports$$ExternalSyntheticLambda0(PendingReports,p1,p2,p3,p4,p5,p6);
	if (1 != 0) {
		int v9 = this.mPending.size();
		if ((v9 - 1) < 0) {
			Object v10 = this.mPending.get((v9 - 1));
			if (RequestQueue$Rec.key != v5) {
				if (RequestQueue$Rec.value == 0) {
					if (((v9 - 1) + -1) < 0) {
						Object v11 = this.mPending.get(((v9 - 1) + -1));
						if (RequestQueue$Rec.key != v5) {
							if (RequestQueue$Rec.value == 0) {
								Object v12 = this.mPending.remove(((v9 - 1) + -1));
								if (0 != 0) {
									RequestQueue$Rec v13 = new RequestQueue$Rec(RequestQueue,v5,1,v6);
									boolean v15 = this.mPending.add(v13);
									if (this.mStarted == 0) {
										boolean v16 = this.mHandler.post(this.mWorker);
										Binder.restoreCallingIdentity(v2);
										return;
									}
								}
							}
						}
					}
				}
			}
		}
	}
}
","SYS_OR_SIG"

"Lcom/android/server/incident/IncidentCompanionService$BinderService","denyReport(Ljava/lang/String;)V","0","invokevirtual < Application, Lcom/android/server/incident/IncidentCompanionService$BinderService, enforceAuthorizePermission()V > 1 @0 exception:3,
5 = invokestatic < Application, Landroid/os/Binder, clearCallingIdentity()J > @3 exception:4,
6 = getfield < Application, Lcom/android/server/incident/IncidentCompanionService$BinderService, this$0, <Application,Lcom/android/server/incident/IncidentCompanionService> > 1,
8 = invokestatic < Application, Lcom/android/server/incident/IncidentCompanionService, -$$Nest$fgetmPendingReports(Lcom/android/server/incident/IncidentCompanionService;)Lcom/android/server/incident/PendingReports; > 6 @9 exception:7,
invokevirtual < Application, Lcom/android/server/incident/PendingReports, denyReport(Ljava/lang/String;)V > 8,2 @13 exception:9,
invokestatic < Application, Landroid/os/Binder, restoreCallingIdentity(J)V > 5 @16 exception:15,
return,","depth : 0
-----
","public void denyReport(String p1){
	long v2 = Binder.clearCallingIdentity();
	PendingReports v3 = IncidentCompanionService.-$$Nest$fgetmPendingReports(this.this$0);
	v3.denyReport(p1);
	Binder.restoreCallingIdentity(v2);
	return;
}
","SYS_OR_SIG"
"Lcom/android/server/incident/IncidentCompanionService$BinderService","denyReport(Ljava/lang/String;)V","1","invokevirtual < Application, Lcom/android/server/incident/IncidentCompanionService$BinderService, enforceAuthorizePermission()V > 1 @0 exception:3,
5 = invokestatic < Application, Landroid/os/Binder, clearCallingIdentity()J > @3 exception:4,
6 = getfield < Application, Lcom/android/server/incident/IncidentCompanionService$BinderService, this$0, <Application,Lcom/android/server/incident/IncidentCompanionService> > 1,
8 = invokestatic < Application, Lcom/android/server/incident/IncidentCompanionService, -$$Nest$fgetmPendingReports(Lcom/android/server/incident/IncidentCompanionService;)Lcom/android/server/incident/PendingReports; > 6 @9 exception:7,
2 = getfield < Application, Lcom/android/server/incident/IncidentCompanionService, mPendingReports, <Application,Lcom/android/server/incident/PendingReports> > 1,
return 2,
invokevirtual < Application, Lcom/android/server/incident/PendingReports, denyReport(Ljava/lang/String;)V > 8,2 @13 exception:9,
3 = getfield < Application, Lcom/android/server/incident/PendingReports, mLock, <Application,Ljava/lang/Object> > 1,
monitorenter 3,
5 = invokevirtual < Application, Lcom/android/server/incident/PendingReports, findAndRemovePendingReportRecLocked(Ljava/lang/String;)Lcom/android/server/incident/PendingReports$PendingReportRec; > 1,2 @3 exception:4,
conditional branch(ne, to iindex=-1) 5,6,
monitorexit 3,
invokevirtual < Application, Lcom/android/server/incident/PendingReports, sendBroadcast()V > 1 @34 exception:7,
9 = new <Application,Ljava/lang/StringBuilder>@39,
invokespecial < Application, Ljava/lang/StringBuilder, <init>()V > 9 @41 exception:10,
13 = invokevirtual < Application, Ljava/lang/StringBuilder, append(Ljava/lang/String;)Ljava/lang/StringBuilder; > 9,11 @46 exception:12,
15 = invokevirtual < Application, Ljava/lang/StringBuilder, append(Ljava/lang/String;)Ljava/lang/StringBuilder; > 9,2 @49 exception:14,
17 = invokevirtual < Application, Ljava/lang/StringBuilder, toString()Ljava/lang/String; > 9 @52 exception:16,
19 = invokestatic < Application, Landroid/util/Log, i(Ljava/lang/String;Ljava/lang/String;)I > 8,17 @56 exception:18,
20 = getfield < Application, Lcom/android/server/incident/PendingReports$PendingReportRec, listener, <Application,Landroid/os/IIncidentAuthListener> > 5,
invokeinterface < Application, Landroid/os/IIncidentAuthListener, onReportDenied()V > 20 @61 exception:21,
goto (from iindex= 29 to iindex = 24),
return,
invokestatic < Application, Landroid/os/Binder, restoreCallingIdentity(J)V > 5 @16 exception:15,
return,","depth : 0
-----
depth : 1
-----
depth : 1
-----
","public void denyReport(String p1){
	long v2 = Binder.clearCallingIdentity();
	PendingReports v3 = this.mPendingReports;
	PendingReports$PendingReportRec v5 = PendingReports.findAndRemovePendingReportRecLocked(p1);
	if (v5 != 0) {
		PendingReports.sendBroadcast();
		PendingReports$PendingReportRec.listener.onReportDenied();
		Binder.restoreCallingIdentity(v2);
		return;
	}
}
","SYS_OR_SIG"
"Lcom/android/server/incident/IncidentCompanionService$BinderService","denyReport(Ljava/lang/String;)V","2","invokevirtual < Application, Lcom/android/server/incident/IncidentCompanionService$BinderService, enforceAuthorizePermission()V > 1 @0 exception:3,
5 = invokestatic < Application, Landroid/os/Binder, clearCallingIdentity()J > @3 exception:4,
6 = getfield < Application, Lcom/android/server/incident/IncidentCompanionService$BinderService, this$0, <Application,Lcom/android/server/incident/IncidentCompanionService> > 1,
8 = invokestatic < Application, Lcom/android/server/incident/IncidentCompanionService, -$$Nest$fgetmPendingReports(Lcom/android/server/incident/IncidentCompanionService;)Lcom/android/server/incident/PendingReports; > 6 @9 exception:7,
2 = getfield < Application, Lcom/android/server/incident/IncidentCompanionService, mPendingReports, <Application,Lcom/android/server/incident/PendingReports> > 1,
return 2,
invokevirtual < Application, Lcom/android/server/incident/PendingReports, denyReport(Ljava/lang/String;)V > 8,2 @13 exception:9,
3 = getfield < Application, Lcom/android/server/incident/PendingReports, mLock, <Application,Ljava/lang/Object> > 1,
monitorenter 3,
5 = invokevirtual < Application, Lcom/android/server/incident/PendingReports, findAndRemovePendingReportRecLocked(Ljava/lang/String;)Lcom/android/server/incident/PendingReports$PendingReportRec; > 1,2 @3 exception:4,
4 = invokestatic < Application, Landroid/net/Uri, parse(Ljava/lang/String;)Landroid/net/Uri; > 2 @0 exception:3,
8 = invokevirtual < Application, Landroid/net/Uri, getQueryParameter(Ljava/lang/String;)Ljava/lang/String; > 4,6 @7 exception:7,
10 = invokestatic < Application, Ljava/lang/Integer, parseInt(Ljava/lang/String;)I > 8 @11 exception:9,
26 = getfield < Application, Lcom/android/server/incident/PendingReports, mPending, <Application,Ljava/util/ArrayList> > 1,
28 = invokevirtual < Application, Ljava/util/ArrayList, iterator()Ljava/util/Iterator; > 26 @17 exception:27,
30 = invokeinterface < Application, Ljava/util/Iterator, hasNext()Z > 28 @21 exception:29,
conditional branch(eq, to iindex=-1) 30,5,
32 = invokeinterface < Application, Ljava/util/Iterator, next()Ljava/lang/Object; > 28 @27 exception:31,
33 = checkcast <Application,Lcom/android/server/incident/PendingReports$PendingReportRec>32 <Application,Lcom/android/server/incident/PendingReports$PendingReportRec>,
34 = getfield < Application, Lcom/android/server/incident/PendingReports$PendingReportRec, id, <Primordial,I> > 33,
conditional branch(ne, to iindex=-1) 34,10,
30 = invokeinterface < Application, Ljava/util/Iterator, hasNext()Z > 28 @21 exception:29,
conditional branch(eq, to iindex=-1) 30,5,
32 = invokeinterface < Application, Ljava/util/Iterator, next()Ljava/lang/Object; > 28 @27 exception:31,
33 = checkcast <Application,Lcom/android/server/incident/PendingReports$PendingReportRec>32 <Application,Lcom/android/server/incident/PendingReports$PendingReportRec>,
34 = getfield < Application, Lcom/android/server/incident/PendingReports$PendingReportRec, id, <Primordial,I> > 33,
conditional branch(ne, to iindex=-1) 34,10,
invokeinterface < Application, Ljava/util/Iterator, remove()V > 28 @37 exception:39,
return 33,
conditional branch(ne, to iindex=-1) 5,6,
monitorexit 3,
invokevirtual < Application, Lcom/android/server/incident/PendingReports, sendBroadcast()V > 1 @34 exception:7,
3 = invokevirtual < Application, Lcom/android/server/incident/PendingReports, getAndValidateUser()I > 1 @0 exception:2,
conditional branch(ne, to iindex=-1) 3,4,
6 = invokevirtual < Application, Lcom/android/server/incident/PendingReports, getApproverComponent(I)Landroid/content/ComponentName; > 1,3 @9 exception:5,
conditional branch(ne, to iindex=-1) 6,7,
invokevirtual < Application, Lcom/android/server/incident/PendingReports, sendBroadcast(Landroid/content/ComponentName;I)V > 1,6,3 @16 exception:8,
return,
9 = new <Application,Ljava/lang/StringBuilder>@39,
invokespecial < Application, Ljava/lang/StringBuilder, <init>()V > 9 @41 exception:10,
13 = invokevirtual < Application, Ljava/lang/StringBuilder, append(Ljava/lang/String;)Ljava/lang/StringBuilder; > 9,11 @46 exception:12,
15 = invokevirtual < Application, Ljava/lang/StringBuilder, append(Ljava/lang/String;)Ljava/lang/StringBuilder; > 9,2 @49 exception:14,
17 = invokevirtual < Application, Ljava/lang/StringBuilder, toString()Ljava/lang/String; > 9 @52 exception:16,
19 = invokestatic < Application, Landroid/util/Log, i(Ljava/lang/String;Ljava/lang/String;)I > 8,17 @56 exception:18,
20 = getfield < Application, Lcom/android/server/incident/PendingReports$PendingReportRec, listener, <Application,Landroid/os/IIncidentAuthListener> > 5,
invokeinterface < Application, Landroid/os/IIncidentAuthListener, onReportDenied()V > 20 @61 exception:21,
goto (from iindex= 29 to iindex = 24),
return,
invokestatic < Application, Landroid/os/Binder, restoreCallingIdentity(J)V > 5 @16 exception:15,
return,","depth : 0
-----
depth : 1
-----
depth : 1
-----
depth : 2
-----
depth : 2
-----
","public void denyReport(String p1){
	long v2 = Binder.clearCallingIdentity();
	PendingReports v3 = this.mPendingReports;
	Uri v6 = Uri.parse(p1);
	String v7 = v6.getQueryParameter(""id"");
	int v8 = Integer.parseInt(v7);
	Iterator v9 = this.mPending.iterator();
	boolean v10 = v9.hasNext();
	if (v10 == 0) {
		Object v11 = v9.next();
		if (PendingReports$PendingReportRec.id != v8) {
			boolean v12 = v9.hasNext();
			if (v12 == 0) {
				Object v13 = v9.next();
				if (PendingReports$PendingReportRec.id != v8) {
					v9.remove();
					PendingReports$PendingReportRec v5 = v13;
					if (v5 != 0) {
						int v16 = PendingReports.getAndValidateUser();
						if (v16 != -10000) {
							ComponentName v17 = PendingReports.getApproverComponent(v16);
							if (v17 != 0) {
								PendingReports.sendBroadcast(v17, v16);
								PendingReports$PendingReportRec.listener.onReportDenied();
								Binder.restoreCallingIdentity(v2);
								return;
							}
						}
					}
				}
			}
		}
	}
}
","SYS_OR_SIG"
"Lcom/android/server/incident/IncidentCompanionService$BinderService","denyReport(Ljava/lang/String;)V","2","invokevirtual < Application, Lcom/android/server/incident/IncidentCompanionService$BinderService, enforceAuthorizePermission()V > 1 @0 exception:3,
5 = invokestatic < Application, Landroid/os/Binder, clearCallingIdentity()J > @3 exception:4,
6 = getfield < Application, Lcom/android/server/incident/IncidentCompanionService$BinderService, this$0, <Application,Lcom/android/server/incident/IncidentCompanionService> > 1,
8 = invokestatic < Application, Lcom/android/server/incident/IncidentCompanionService, -$$Nest$fgetmPendingReports(Lcom/android/server/incident/IncidentCompanionService;)Lcom/android/server/incident/PendingReports; > 6 @9 exception:7,
2 = getfield < Application, Lcom/android/server/incident/IncidentCompanionService, mPendingReports, <Application,Lcom/android/server/incident/PendingReports> > 1,
return 2,
invokevirtual < Application, Lcom/android/server/incident/PendingReports, denyReport(Ljava/lang/String;)V > 8,2 @13 exception:9,
3 = getfield < Application, Lcom/android/server/incident/PendingReports, mLock, <Application,Ljava/lang/Object> > 1,
monitorenter 3,
5 = invokevirtual < Application, Lcom/android/server/incident/PendingReports, findAndRemovePendingReportRecLocked(Ljava/lang/String;)Lcom/android/server/incident/PendingReports$PendingReportRec; > 1,2 @3 exception:4,
4 = invokestatic < Application, Landroid/net/Uri, parse(Ljava/lang/String;)Landroid/net/Uri; > 2 @0 exception:3,
8 = invokevirtual < Application, Landroid/net/Uri, getQueryParameter(Ljava/lang/String;)Ljava/lang/String; > 4,6 @7 exception:7,
10 = invokestatic < Application, Ljava/lang/Integer, parseInt(Ljava/lang/String;)I > 8 @11 exception:9,
26 = getfield < Application, Lcom/android/server/incident/PendingReports, mPending, <Application,Ljava/util/ArrayList> > 1,
28 = invokevirtual < Application, Ljava/util/ArrayList, iterator()Ljava/util/Iterator; > 26 @17 exception:27,
30 = invokeinterface < Application, Ljava/util/Iterator, hasNext()Z > 28 @21 exception:29,
conditional branch(eq, to iindex=-1) 30,5,
32 = invokeinterface < Application, Ljava/util/Iterator, next()Ljava/lang/Object; > 28 @27 exception:31,
33 = checkcast <Application,Lcom/android/server/incident/PendingReports$PendingReportRec>32 <Application,Lcom/android/server/incident/PendingReports$PendingReportRec>,
34 = getfield < Application, Lcom/android/server/incident/PendingReports$PendingReportRec, id, <Primordial,I> > 33,
conditional branch(ne, to iindex=-1) 34,10,
30 = invokeinterface < Application, Ljava/util/Iterator, hasNext()Z > 28 @21 exception:29,
conditional branch(eq, to iindex=-1) 30,5,
32 = invokeinterface < Application, Ljava/util/Iterator, next()Ljava/lang/Object; > 28 @27 exception:31,
33 = checkcast <Application,Lcom/android/server/incident/PendingReports$PendingReportRec>32 <Application,Lcom/android/server/incident/PendingReports$PendingReportRec>,
34 = getfield < Application, Lcom/android/server/incident/PendingReports$PendingReportRec, id, <Primordial,I> > 33,
conditional branch(ne, to iindex=-1) 34,10,
invokeinterface < Application, Ljava/util/Iterator, remove()V > 28 @37 exception:39,
return 33,
conditional branch(ne, to iindex=-1) 5,6,
monitorexit 3,
invokevirtual < Application, Lcom/android/server/incident/PendingReports, sendBroadcast()V > 1 @34 exception:7,
3 = invokevirtual < Application, Lcom/android/server/incident/PendingReports, getAndValidateUser()I > 1 @0 exception:2,
conditional branch(ne, to iindex=-1) 3,4,
6 = invokevirtual < Application, Lcom/android/server/incident/PendingReports, getApproverComponent(I)Landroid/content/ComponentName; > 1,3 @9 exception:5,
conditional branch(ne, to iindex=-1) 6,7,
return,
9 = new <Application,Ljava/lang/StringBuilder>@39,
invokespecial < Application, Ljava/lang/StringBuilder, <init>()V > 9 @41 exception:10,
13 = invokevirtual < Application, Ljava/lang/StringBuilder, append(Ljava/lang/String;)Ljava/lang/StringBuilder; > 9,11 @46 exception:12,
15 = invokevirtual < Application, Ljava/lang/StringBuilder, append(Ljava/lang/String;)Ljava/lang/StringBuilder; > 9,2 @49 exception:14,
17 = invokevirtual < Application, Ljava/lang/StringBuilder, toString()Ljava/lang/String; > 9 @52 exception:16,
19 = invokestatic < Application, Landroid/util/Log, i(Ljava/lang/String;Ljava/lang/String;)I > 8,17 @56 exception:18,
20 = getfield < Application, Lcom/android/server/incident/PendingReports$PendingReportRec, listener, <Application,Landroid/os/IIncidentAuthListener> > 5,
invokeinterface < Application, Landroid/os/IIncidentAuthListener, onReportDenied()V > 20 @61 exception:21,
goto (from iindex= 29 to iindex = 24),
return,
invokestatic < Application, Landroid/os/Binder, restoreCallingIdentity(J)V > 5 @16 exception:15,
return,","depth : 0
-----
depth : 1
-----
depth : 1
-----
depth : 2
-----
depth : 2
-----
","public void denyReport(String p1){
	long v2 = Binder.clearCallingIdentity();
	PendingReports v3 = this.mPendingReports;
	Uri v6 = Uri.parse(p1);
	String v7 = v6.getQueryParameter(""id"");
	int v8 = Integer.parseInt(v7);
	Iterator v9 = this.mPending.iterator();
	boolean v10 = v9.hasNext();
	if (v10 == 0) {
		Object v11 = v9.next();
		if (PendingReports$PendingReportRec.id != v8) {
			boolean v12 = v9.hasNext();
			if (v12 == 0) {
				Object v13 = v9.next();
				if (PendingReports$PendingReportRec.id != v8) {
					v9.remove();
					PendingReports$PendingReportRec v5 = v13;
					if (v5 != 0) {
						int v16 = PendingReports.getAndValidateUser();
						if (v16 != -10000) {
							ComponentName v17 = PendingReports.getApproverComponent(v16);
							if (v17 != 0) {
								PendingReports$PendingReportRec.listener.onReportDenied();
								Binder.restoreCallingIdentity(v2);
								return;
							}
						}
					}
				}
			}
		}
	}
}
","SYS_OR_SIG"

"Lcom/android/server/incident/IncidentCompanionService$BinderService","getPendingReports()Ljava/util/List;","0","invokevirtual < Application, Lcom/android/server/incident/IncidentCompanionService$BinderService, enforceAuthorizePermission()V > 1 @0 exception:2,
3 = getfield < Application, Lcom/android/server/incident/IncidentCompanionService$BinderService, this$0, <Application,Lcom/android/server/incident/IncidentCompanionService> > 1,
5 = invokestatic < Application, Lcom/android/server/incident/IncidentCompanionService, -$$Nest$fgetmPendingReports(Lcom/android/server/incident/IncidentCompanionService;)Lcom/android/server/incident/PendingReports; > 3 @5 exception:4,
7 = invokevirtual < Application, Lcom/android/server/incident/PendingReports, getPendingReports()Ljava/util/List; > 5 @9 exception:6,
return 7,","depth : 0
-----
","public List getPendingReports(){
	PendingReports v2 = IncidentCompanionService.-$$Nest$fgetmPendingReports(this.this$0);
	List v3 = v2.getPendingReports();
	return v3;
}
","SYS_OR_SIG"
"Lcom/android/server/incident/IncidentCompanionService$BinderService","getPendingReports()Ljava/util/List;","1","invokevirtual < Application, Lcom/android/server/incident/IncidentCompanionService$BinderService, enforceAuthorizePermission()V > 1 @0 exception:2,
3 = getfield < Application, Lcom/android/server/incident/IncidentCompanionService$BinderService, this$0, <Application,Lcom/android/server/incident/IncidentCompanionService> > 1,
5 = invokestatic < Application, Lcom/android/server/incident/IncidentCompanionService, -$$Nest$fgetmPendingReports(Lcom/android/server/incident/IncidentCompanionService;)Lcom/android/server/incident/PendingReports; > 3 @5 exception:4,
2 = getfield < Application, Lcom/android/server/incident/IncidentCompanionService, mPendingReports, <Application,Lcom/android/server/incident/PendingReports> > 1,
return 2,
7 = invokevirtual < Application, Lcom/android/server/incident/PendingReports, getPendingReports()Ljava/util/List; > 5 @9 exception:6,
2 = getfield < Application, Lcom/android/server/incident/PendingReports, mLock, <Application,Ljava/lang/Object> > 1,
monitorenter 2,
3 = getfield < Application, Lcom/android/server/incident/PendingReports, mPending, <Application,Ljava/util/ArrayList> > 1,
5 = invokevirtual < Application, Ljava/util/ArrayList, size()I > 3 @5 exception:4,
6 = new <Application,Ljava/util/ArrayList>@9,
invokespecial < Application, Ljava/util/ArrayList, <init>(I)V > 6,5 @11 exception:7,
21 = phi  20,8,
conditional branch(ge, to iindex=-1) 21,5,
9 = getfield < Application, Lcom/android/server/incident/PendingReports, mPending, <Application,Ljava/util/ArrayList> > 1,
11 = invokevirtual < Application, Ljava/util/ArrayList, get(I)Ljava/lang/Object; > 9,21 @19 exception:10,
12 = checkcast <Application,Lcom/android/server/incident/PendingReports$PendingReportRec>11 <Application,Lcom/android/server/incident/PendingReports$PendingReportRec>,
14 = invokevirtual < Application, Lcom/android/server/incident/PendingReports$PendingReportRec, getUri()Landroid/net/Uri; > 12 @25 exception:13,
16 = invokevirtual < Application, Landroid/net/Uri, toString()Ljava/lang/String; > 14 @29 exception:15,
18 = invokevirtual < Application, Ljava/util/ArrayList, add(Ljava/lang/Object;)Z > 6,16 @33 exception:17,
20 = binaryop(add) 21 , 19,
goto (from iindex= 19 to iindex = -23),
21 = phi  20,8,
conditional branch(ge, to iindex=-1) 21,5,
monitorexit 2,
return 6,
return 7,","depth : 0
-----
depth : 1
-----
depth : 1
-----
","public List getPendingReports(){
	PendingReports v2 = this.mPendingReports;
	int v4 = this.mPending.size();
	ArrayList v5 = new ArrayList(v4);
	if (0 >= v4) {
		Object v7 = this.mPending.get(0);
		Uri v8 = v7.getUri();
		String v9 = v8.toString();
		boolean v10 = v5.add(v9);
		if ((0 + 1) >= v4) {
			List v3 = v5;
			return v3;
		}
	}
}
","SYS_OR_SIG"
"Lcom/android/server/incident/IncidentCompanionService$BinderService","getPendingReports()Ljava/util/List;","2","invokevirtual < Application, Lcom/android/server/incident/IncidentCompanionService$BinderService, enforceAuthorizePermission()V > 1 @0 exception:2,
3 = getfield < Application, Lcom/android/server/incident/IncidentCompanionService$BinderService, this$0, <Application,Lcom/android/server/incident/IncidentCompanionService> > 1,
5 = invokestatic < Application, Lcom/android/server/incident/IncidentCompanionService, -$$Nest$fgetmPendingReports(Lcom/android/server/incident/IncidentCompanionService;)Lcom/android/server/incident/PendingReports; > 3 @5 exception:4,
2 = getfield < Application, Lcom/android/server/incident/IncidentCompanionService, mPendingReports, <Application,Lcom/android/server/incident/PendingReports> > 1,
return 2,
7 = invokevirtual < Application, Lcom/android/server/incident/PendingReports, getPendingReports()Ljava/util/List; > 5 @9 exception:6,
2 = getfield < Application, Lcom/android/server/incident/PendingReports, mLock, <Application,Ljava/lang/Object> > 1,
monitorenter 2,
3 = getfield < Application, Lcom/android/server/incident/PendingReports, mPending, <Application,Ljava/util/ArrayList> > 1,
5 = invokevirtual < Application, Ljava/util/ArrayList, size()I > 3 @5 exception:4,
6 = new <Application,Ljava/util/ArrayList>@9,
invokespecial < Application, Ljava/util/ArrayList, <init>(I)V > 6,5 @11 exception:7,
21 = phi  20,8,
conditional branch(ge, to iindex=-1) 21,5,
9 = getfield < Application, Lcom/android/server/incident/PendingReports, mPending, <Application,Ljava/util/ArrayList> > 1,
11 = invokevirtual < Application, Ljava/util/ArrayList, get(I)Ljava/lang/Object; > 9,21 @19 exception:10,
12 = checkcast <Application,Lcom/android/server/incident/PendingReports$PendingReportRec>11 <Application,Lcom/android/server/incident/PendingReports$PendingReportRec>,
14 = invokevirtual < Application, Lcom/android/server/incident/PendingReports$PendingReportRec, getUri()Landroid/net/Uri; > 12 @25 exception:13,
2 = new <Application,Landroid/net/Uri$Builder>@0,
invokespecial < Application, Landroid/net/Uri$Builder, <init>()V > 2 @2 exception:3,
6 = invokevirtual < Application, Landroid/net/Uri$Builder, scheme(Ljava/lang/String;)Landroid/net/Uri$Builder; > 2,4 @7 exception:5,
9 = invokevirtual < Application, Landroid/net/Uri$Builder, authority(Ljava/lang/String;)Landroid/net/Uri$Builder; > 6,7 @13 exception:8,
12 = invokevirtual < Application, Landroid/net/Uri$Builder, path(Ljava/lang/String;)Landroid/net/Uri$Builder; > 9,10 @19 exception:11,
13 = getfield < Application, Lcom/android/server/incident/PendingReports$PendingReportRec, id, <Primordial,I> > 1,
15 = invokestatic < Application, Ljava/lang/Integer, toString(I)Ljava/lang/String; > 13 @25 exception:14,
18 = invokevirtual < Application, Landroid/net/Uri$Builder, appendQueryParameter(Ljava/lang/String;Ljava/lang/String;)Landroid/net/Uri$Builder; > 12,16,15 @31 exception:17,
19 = getfield < Application, Lcom/android/server/incident/PendingReports$PendingReportRec, callingPackage, <Application,Ljava/lang/String> > 1,
22 = invokevirtual < Application, Landroid/net/Uri$Builder, appendQueryParameter(Ljava/lang/String;Ljava/lang/String;)Landroid/net/Uri$Builder; > 18,20,19 @40 exception:21,
23 = getfield < Application, Lcom/android/server/incident/PendingReports$PendingReportRec, flags, <Primordial,I> > 1,
25 = invokestatic < Application, Ljava/lang/Integer, toString(I)Ljava/lang/String; > 23 @46 exception:24,
28 = invokevirtual < Application, Landroid/net/Uri$Builder, appendQueryParameter(Ljava/lang/String;Ljava/lang/String;)Landroid/net/Uri$Builder; > 22,26,25 @52 exception:27,
29 = getfield < Application, Lcom/android/server/incident/PendingReports$PendingReportRec, addedWalltime, <Primordial,J> > 1,
31 = invokestatic < Application, Ljava/lang/Long, toString(J)Ljava/lang/String; > 29 @58 exception:30,
34 = invokevirtual < Application, Landroid/net/Uri$Builder, appendQueryParameter(Ljava/lang/String;Ljava/lang/String;)Landroid/net/Uri$Builder; > 28,32,31 @65 exception:33,
35 = getfield < Application, Lcom/android/server/incident/PendingReports$PendingReportRec, receiverClass, <Application,Ljava/lang/String> > 1,
conditional branch(eq, to iindex=-1) 35,36,
38 = invokevirtual < Application, Ljava/lang/String, length()I > 35 @73 exception:37,
conditional branch(le, to iindex=-1) 38,36,
39 = getfield < Application, Lcom/android/server/incident/PendingReports$PendingReportRec, receiverClass, <Application,Ljava/lang/String> > 1,
42 = invokevirtual < Application, Landroid/net/Uri$Builder, appendQueryParameter(Ljava/lang/String;Ljava/lang/String;)Landroid/net/Uri$Builder; > 34,40,39 @84 exception:41,
47 = getfield < Application, Lcom/android/server/incident/PendingReports$PendingReportRec, reportId, <Application,Ljava/lang/String> > 1,
conditional branch(eq, to iindex=-1) 47,36,
49 = invokevirtual < Application, Ljava/lang/String, length()I > 47 @91 exception:48,
conditional branch(le, to iindex=-1) 49,36,
50 = getfield < Application, Lcom/android/server/incident/PendingReports$PendingReportRec, reportId, <Application,Ljava/lang/String> > 1,
53 = invokevirtual < Application, Landroid/net/Uri$Builder, appendQueryParameter(Ljava/lang/String;Ljava/lang/String;)Landroid/net/Uri$Builder; > 34,51,50 @102 exception:52,
59 = invokevirtual < Application, Landroid/net/Uri$Builder, build()Landroid/net/Uri; > 34 @105 exception:58,
return 59,
16 = invokevirtual < Application, Landroid/net/Uri, toString()Ljava/lang/String; > 14 @29 exception:15,
18 = invokevirtual < Application, Ljava/util/ArrayList, add(Ljava/lang/Object;)Z > 6,16 @33 exception:17,
20 = binaryop(add) 21 , 19,
goto (from iindex= 19 to iindex = -23),
21 = phi  20,8,
conditional branch(ge, to iindex=-1) 21,5,
monitorexit 2,
return 6,
return 7,","depth : 0
-----
depth : 1
-----
depth : 1
-----
depth : 2
-----
","public List getPendingReports(){
	PendingReports v2 = this.mPendingReports;
	int v4 = this.mPending.size();
	ArrayList v5 = new ArrayList(v4);
	if (0 >= v4) {
		Object v7 = this.mPending.get(0);
		Uri$Builder v9 = new Uri$Builder();
		Uri$Builder v11 = v9.scheme(""content"");
		Uri$Builder v12 = v11.authority(""android.os.IncidentManager"");
		Uri$Builder v13 = v12.path(""/pending"");
		String v14 = Integer.toString(this.id);
		Uri$Builder v15 = v13.appendQueryParameter(""id"", v14);
		Uri$Builder v16 = v15.appendQueryParameter(""pkg"", this.callingPackage);
		String v17 = Integer.toString(this.flags);
		Uri$Builder v18 = v16.appendQueryParameter(""flags"", v17);
		String v19 = Long.toString(this.addedWalltime);
		Uri$Builder v20 = v18.appendQueryParameter(""t"", v19);
		if (this.receiverClass == 0) {
			int v21 = this.receiverClass.length();
			if (v21 <= 0) {
				Uri$Builder v22 = v20.appendQueryParameter(""receiver"", this.receiverClass);
				if (this.reportId == 0) {
					int v23 = this.reportId.length();
					if (v23 <= 0) {
						Uri$Builder v24 = v20.appendQueryParameter(""r"", this.reportId);
						Uri v25 = v20.build();
						Uri v8 = v25;
						String v26 = v8.toString();
						boolean v27 = v5.add(v26);
						if ((0 + 1) >= v4) {
							List v3 = v5;
							return v3;
						}
					}
				}
			}
		}
	}
}
","SYS_OR_SIG"

"Lcom/android/server/incident/IncidentCompanionService$BinderService","getIncidentReportList(Ljava/lang/String;Ljava/lang/String;)Ljava/util/List;","0","invokevirtual < Application, Lcom/android/server/incident/IncidentCompanionService$BinderService, enforceAccessReportsPermissions(Ljava/lang/String;)V > 1,4 @1 exception:5,
7 = invokestatic < Application, Landroid/os/Binder, clearCallingIdentity()J > @4 exception:6,
8 = getfield < Application, Lcom/android/server/incident/IncidentCompanionService$BinderService, this$0, <Application,Lcom/android/server/incident/IncidentCompanionService> > 1,
10 = invokestatic < Application, Lcom/android/server/incident/IncidentCompanionService, -$$Nest$mgetIIncidentManager(Lcom/android/server/incident/IncidentCompanionService;)Landroid/os/IIncidentManager; > 8 @10 exception:9,
12 = invokeinterface < Application, Landroid/os/IIncidentManager, getIncidentReportList(Ljava/lang/String;Ljava/lang/String;)Ljava/util/List; > 10,2,3 @14 exception:11,
invokestatic < Application, Landroid/os/Binder, restoreCallingIdentity(J)V > 7 @18 exception:18,
return 12,","depth : 0
-----
","public List getIncidentReportList(String p1, String p2){
	long v2 = Binder.clearCallingIdentity();
	IIncidentManager v3 = IncidentCompanionService.-$$Nest$mgetIIncidentManager(this.this$0);
	List v4 = v3.getIncidentReportList(p1, p2);
	Binder.restoreCallingIdentity(v2);
	return v4;
}
","SYS_OR_SIG"
"Lcom/android/server/incident/IncidentCompanionService$BinderService","getIncidentReportList(Ljava/lang/String;Ljava/lang/String;)Ljava/util/List;","1","invokevirtual < Application, Lcom/android/server/incident/IncidentCompanionService$BinderService, enforceAccessReportsPermissions(Ljava/lang/String;)V > 1,4 @1 exception:5,
7 = invokestatic < Application, Landroid/os/Binder, clearCallingIdentity()J > @4 exception:6,
8 = getfield < Application, Lcom/android/server/incident/IncidentCompanionService$BinderService, this$0, <Application,Lcom/android/server/incident/IncidentCompanionService> > 1,
10 = invokestatic < Application, Lcom/android/server/incident/IncidentCompanionService, -$$Nest$mgetIIncidentManager(Lcom/android/server/incident/IncidentCompanionService;)Landroid/os/IIncidentManager; > 8 @10 exception:9,
3 = invokevirtual < Application, Lcom/android/server/incident/IncidentCompanionService, getIIncidentManager()Landroid/os/IIncidentManager; > 1 @0 exception:2,
return 3,
12 = invokeinterface < Application, Landroid/os/IIncidentManager, getIncidentReportList(Ljava/lang/String;Ljava/lang/String;)Ljava/util/List; > 10,2,3 @14 exception:11,
invokestatic < Application, Landroid/os/Binder, restoreCallingIdentity(J)V > 7 @18 exception:18,
return 12,","depth : 0
-----
depth : 1
-----
","public List getIncidentReportList(String p1, String p2){
	long v2 = Binder.clearCallingIdentity();
	IIncidentManager v4 = this.this$0.getIIncidentManager();
	IIncidentManager v3 = v4;
	List v5 = v3.getIncidentReportList(p1, p2);
	Binder.restoreCallingIdentity(v2);
	return v5;
}
","SYS_OR_SIG"
"Lcom/android/server/incident/IncidentCompanionService$BinderService","getIncidentReportList(Ljava/lang/String;Ljava/lang/String;)Ljava/util/List;","2","invokevirtual < Application, Lcom/android/server/incident/IncidentCompanionService$BinderService, enforceAccessReportsPermissions(Ljava/lang/String;)V > 1,4 @1 exception:5,
7 = invokestatic < Application, Landroid/os/Binder, clearCallingIdentity()J > @4 exception:6,
8 = getfield < Application, Lcom/android/server/incident/IncidentCompanionService$BinderService, this$0, <Application,Lcom/android/server/incident/IncidentCompanionService> > 1,
10 = invokestatic < Application, Lcom/android/server/incident/IncidentCompanionService, -$$Nest$mgetIIncidentManager(Lcom/android/server/incident/IncidentCompanionService;)Landroid/os/IIncidentManager; > 8 @10 exception:9,
3 = invokevirtual < Application, Lcom/android/server/incident/IncidentCompanionService, getIIncidentManager()Landroid/os/IIncidentManager; > 1 @0 exception:2,
4 = invokestatic < Application, Landroid/os/ServiceManager, getService(Ljava/lang/String;)Landroid/os/IBinder; > 2 @2 exception:3,
6 = invokestatic < Application, Landroid/os/IIncidentManager$Stub, asInterface(Landroid/os/IBinder;)Landroid/os/IIncidentManager; > 4 @6 exception:5,
return 6,
return 3,
12 = invokeinterface < Application, Landroid/os/IIncidentManager, getIncidentReportList(Ljava/lang/String;Ljava/lang/String;)Ljava/util/List; > 10,2,3 @14 exception:11,
invokestatic < Application, Landroid/os/Binder, restoreCallingIdentity(J)V > 7 @18 exception:18,
return 12,","depth : 0
-----
depth : 1
-----
depth : 2
-----
","public List getIncidentReportList(String p1, String p2){
	long v2 = Binder.clearCallingIdentity();
	IBinder v5 = ServiceManager.getService(""incident"");
	IIncidentManager v6 = IIncidentManager$Stub.asInterface(v5);
	IIncidentManager v4 = v6;
	IIncidentManager v3 = v4;
	List v7 = v3.getIncidentReportList(p1, p2);
	Binder.restoreCallingIdentity(v2);
	return v7;
}
","SYS_OR_SIG"

"Lcom/android/server/incident/IncidentCompanionService$BinderService","approveReport(Ljava/lang/String;)V","0","invokevirtual < Application, Lcom/android/server/incident/IncidentCompanionService$BinderService, enforceAuthorizePermission()V > 1 @0 exception:3,
5 = invokestatic < Application, Landroid/os/Binder, clearCallingIdentity()J > @3 exception:4,
6 = getfield < Application, Lcom/android/server/incident/IncidentCompanionService$BinderService, this$0, <Application,Lcom/android/server/incident/IncidentCompanionService> > 1,
8 = invokestatic < Application, Lcom/android/server/incident/IncidentCompanionService, -$$Nest$fgetmPendingReports(Lcom/android/server/incident/IncidentCompanionService;)Lcom/android/server/incident/PendingReports; > 6 @9 exception:7,
invokevirtual < Application, Lcom/android/server/incident/PendingReports, approveReport(Ljava/lang/String;)V > 8,2 @13 exception:9,
invokestatic < Application, Landroid/os/Binder, restoreCallingIdentity(J)V > 5 @16 exception:15,
return,","depth : 0
-----
","public void approveReport(String p1){
	long v2 = Binder.clearCallingIdentity();
	PendingReports v3 = IncidentCompanionService.-$$Nest$fgetmPendingReports(this.this$0);
	v3.approveReport(p1);
	Binder.restoreCallingIdentity(v2);
	return;
}
","SYS_OR_SIG"
"Lcom/android/server/incident/IncidentCompanionService$BinderService","approveReport(Ljava/lang/String;)V","1","invokevirtual < Application, Lcom/android/server/incident/IncidentCompanionService$BinderService, enforceAuthorizePermission()V > 1 @0 exception:3,
5 = invokestatic < Application, Landroid/os/Binder, clearCallingIdentity()J > @3 exception:4,
6 = getfield < Application, Lcom/android/server/incident/IncidentCompanionService$BinderService, this$0, <Application,Lcom/android/server/incident/IncidentCompanionService> > 1,
8 = invokestatic < Application, Lcom/android/server/incident/IncidentCompanionService, -$$Nest$fgetmPendingReports(Lcom/android/server/incident/IncidentCompanionService;)Lcom/android/server/incident/PendingReports; > 6 @9 exception:7,
2 = getfield < Application, Lcom/android/server/incident/IncidentCompanionService, mPendingReports, <Application,Lcom/android/server/incident/PendingReports> > 1,
return 2,
invokevirtual < Application, Lcom/android/server/incident/PendingReports, approveReport(Ljava/lang/String;)V > 8,2 @13 exception:9,
3 = getfield < Application, Lcom/android/server/incident/PendingReports, mLock, <Application,Ljava/lang/Object> > 1,
monitorenter 3,
5 = invokevirtual < Application, Lcom/android/server/incident/PendingReports, findAndRemovePendingReportRecLocked(Ljava/lang/String;)Lcom/android/server/incident/PendingReports$PendingReportRec; > 1,2 @3 exception:4,
conditional branch(ne, to iindex=-1) 5,6,
monitorexit 3,
invokevirtual < Application, Lcom/android/server/incident/PendingReports, sendBroadcast()V > 1 @34 exception:7,
9 = new <Application,Ljava/lang/StringBuilder>@39,
invokespecial < Application, Ljava/lang/StringBuilder, <init>()V > 9 @41 exception:10,
13 = invokevirtual < Application, Ljava/lang/StringBuilder, append(Ljava/lang/String;)Ljava/lang/StringBuilder; > 9,11 @46 exception:12,
15 = invokevirtual < Application, Ljava/lang/StringBuilder, append(Ljava/lang/String;)Ljava/lang/StringBuilder; > 9,2 @49 exception:14,
17 = invokevirtual < Application, Ljava/lang/StringBuilder, toString()Ljava/lang/String; > 9 @52 exception:16,
19 = invokestatic < Application, Landroid/util/Log, i(Ljava/lang/String;Ljava/lang/String;)I > 8,17 @56 exception:18,
20 = getfield < Application, Lcom/android/server/incident/PendingReports$PendingReportRec, listener, <Application,Landroid/os/IIncidentAuthListener> > 5,
invokeinterface < Application, Landroid/os/IIncidentAuthListener, onReportApproved()V > 20 @61 exception:21,
goto (from iindex= 29 to iindex = 24),
return,
invokestatic < Application, Landroid/os/Binder, restoreCallingIdentity(J)V > 5 @16 exception:15,
return,","depth : 0
-----
depth : 1
-----
depth : 1
-----
","public void approveReport(String p1){
	long v2 = Binder.clearCallingIdentity();
	PendingReports v3 = this.mPendingReports;
	PendingReports$PendingReportRec v5 = PendingReports.findAndRemovePendingReportRecLocked(p1);
	if (v5 != 0) {
		PendingReports.sendBroadcast();
		PendingReports$PendingReportRec.listener.onReportApproved();
		Binder.restoreCallingIdentity(v2);
		return;
	}
}
","SYS_OR_SIG"
"Lcom/android/server/incident/IncidentCompanionService$BinderService","approveReport(Ljava/lang/String;)V","2","invokevirtual < Application, Lcom/android/server/incident/IncidentCompanionService$BinderService, enforceAuthorizePermission()V > 1 @0 exception:3,
5 = invokestatic < Application, Landroid/os/Binder, clearCallingIdentity()J > @3 exception:4,
6 = getfield < Application, Lcom/android/server/incident/IncidentCompanionService$BinderService, this$0, <Application,Lcom/android/server/incident/IncidentCompanionService> > 1,
8 = invokestatic < Application, Lcom/android/server/incident/IncidentCompanionService, -$$Nest$fgetmPendingReports(Lcom/android/server/incident/IncidentCompanionService;)Lcom/android/server/incident/PendingReports; > 6 @9 exception:7,
2 = getfield < Application, Lcom/android/server/incident/IncidentCompanionService, mPendingReports, <Application,Lcom/android/server/incident/PendingReports> > 1,
return 2,
invokevirtual < Application, Lcom/android/server/incident/PendingReports, approveReport(Ljava/lang/String;)V > 8,2 @13 exception:9,
3 = getfield < Application, Lcom/android/server/incident/PendingReports, mLock, <Application,Ljava/lang/Object> > 1,
monitorenter 3,
5 = invokevirtual < Application, Lcom/android/server/incident/PendingReports, findAndRemovePendingReportRecLocked(Ljava/lang/String;)Lcom/android/server/incident/PendingReports$PendingReportRec; > 1,2 @3 exception:4,
4 = invokestatic < Application, Landroid/net/Uri, parse(Ljava/lang/String;)Landroid/net/Uri; > 2 @0 exception:3,
8 = invokevirtual < Application, Landroid/net/Uri, getQueryParameter(Ljava/lang/String;)Ljava/lang/String; > 4,6 @7 exception:7,
10 = invokestatic < Application, Ljava/lang/Integer, parseInt(Ljava/lang/String;)I > 8 @11 exception:9,
26 = getfield < Application, Lcom/android/server/incident/PendingReports, mPending, <Application,Ljava/util/ArrayList> > 1,
28 = invokevirtual < Application, Ljava/util/ArrayList, iterator()Ljava/util/Iterator; > 26 @17 exception:27,
30 = invokeinterface < Application, Ljava/util/Iterator, hasNext()Z > 28 @21 exception:29,
conditional branch(eq, to iindex=-1) 30,5,
32 = invokeinterface < Application, Ljava/util/Iterator, next()Ljava/lang/Object; > 28 @27 exception:31,
33 = checkcast <Application,Lcom/android/server/incident/PendingReports$PendingReportRec>32 <Application,Lcom/android/server/incident/PendingReports$PendingReportRec>,
34 = getfield < Application, Lcom/android/server/incident/PendingReports$PendingReportRec, id, <Primordial,I> > 33,
conditional branch(ne, to iindex=-1) 34,10,
30 = invokeinterface < Application, Ljava/util/Iterator, hasNext()Z > 28 @21 exception:29,
conditional branch(eq, to iindex=-1) 30,5,
32 = invokeinterface < Application, Ljava/util/Iterator, next()Ljava/lang/Object; > 28 @27 exception:31,
33 = checkcast <Application,Lcom/android/server/incident/PendingReports$PendingReportRec>32 <Application,Lcom/android/server/incident/PendingReports$PendingReportRec>,
34 = getfield < Application, Lcom/android/server/incident/PendingReports$PendingReportRec, id, <Primordial,I> > 33,
conditional branch(ne, to iindex=-1) 34,10,
invokeinterface < Application, Ljava/util/Iterator, remove()V > 28 @37 exception:39,
return 33,
conditional branch(ne, to iindex=-1) 5,6,
monitorexit 3,
invokevirtual < Application, Lcom/android/server/incident/PendingReports, sendBroadcast()V > 1 @34 exception:7,
3 = invokevirtual < Application, Lcom/android/server/incident/PendingReports, getAndValidateUser()I > 1 @0 exception:2,
conditional branch(ne, to iindex=-1) 3,4,
6 = invokevirtual < Application, Lcom/android/server/incident/PendingReports, getApproverComponent(I)Landroid/content/ComponentName; > 1,3 @9 exception:5,
conditional branch(ne, to iindex=-1) 6,7,
invokevirtual < Application, Lcom/android/server/incident/PendingReports, sendBroadcast(Landroid/content/ComponentName;I)V > 1,6,3 @16 exception:8,
return,
9 = new <Application,Ljava/lang/StringBuilder>@39,
invokespecial < Application, Ljava/lang/StringBuilder, <init>()V > 9 @41 exception:10,
13 = invokevirtual < Application, Ljava/lang/StringBuilder, append(Ljava/lang/String;)Ljava/lang/StringBuilder; > 9,11 @46 exception:12,
15 = invokevirtual < Application, Ljava/lang/StringBuilder, append(Ljava/lang/String;)Ljava/lang/StringBuilder; > 9,2 @49 exception:14,
17 = invokevirtual < Application, Ljava/lang/StringBuilder, toString()Ljava/lang/String; > 9 @52 exception:16,
19 = invokestatic < Application, Landroid/util/Log, i(Ljava/lang/String;Ljava/lang/String;)I > 8,17 @56 exception:18,
20 = getfield < Application, Lcom/android/server/incident/PendingReports$PendingReportRec, listener, <Application,Landroid/os/IIncidentAuthListener> > 5,
invokeinterface < Application, Landroid/os/IIncidentAuthListener, onReportApproved()V > 20 @61 exception:21,
goto (from iindex= 29 to iindex = 24),
return,
invokestatic < Application, Landroid/os/Binder, restoreCallingIdentity(J)V > 5 @16 exception:15,
return,","depth : 0
-----
depth : 1
-----
depth : 1
-----
depth : 2
-----
depth : 2
-----
","public void approveReport(String p1){
	long v2 = Binder.clearCallingIdentity();
	PendingReports v3 = this.mPendingReports;
	Uri v6 = Uri.parse(p1);
	String v7 = v6.getQueryParameter(""id"");
	int v8 = Integer.parseInt(v7);
	Iterator v9 = this.mPending.iterator();
	boolean v10 = v9.hasNext();
	if (v10 == 0) {
		Object v11 = v9.next();
		if (PendingReports$PendingReportRec.id != v8) {
			boolean v12 = v9.hasNext();
			if (v12 == 0) {
				Object v13 = v9.next();
				if (PendingReports$PendingReportRec.id != v8) {
					v9.remove();
					PendingReports$PendingReportRec v5 = v13;
					if (v5 != 0) {
						int v16 = PendingReports.getAndValidateUser();
						if (v16 != -10000) {
							ComponentName v17 = PendingReports.getApproverComponent(v16);
							if (v17 != 0) {
								PendingReports.sendBroadcast(v17, v16);
								PendingReports$PendingReportRec.listener.onReportApproved();
								Binder.restoreCallingIdentity(v2);
								return;
							}
						}
					}
				}
			}
		}
	}
}
","SYS_OR_SIG"
"Lcom/android/server/incident/IncidentCompanionService$BinderService","approveReport(Ljava/lang/String;)V","2","invokevirtual < Application, Lcom/android/server/incident/IncidentCompanionService$BinderService, enforceAuthorizePermission()V > 1 @0 exception:3,
5 = invokestatic < Application, Landroid/os/Binder, clearCallingIdentity()J > @3 exception:4,
6 = getfield < Application, Lcom/android/server/incident/IncidentCompanionService$BinderService, this$0, <Application,Lcom/android/server/incident/IncidentCompanionService> > 1,
8 = invokestatic < Application, Lcom/android/server/incident/IncidentCompanionService, -$$Nest$fgetmPendingReports(Lcom/android/server/incident/IncidentCompanionService;)Lcom/android/server/incident/PendingReports; > 6 @9 exception:7,
2 = getfield < Application, Lcom/android/server/incident/IncidentCompanionService, mPendingReports, <Application,Lcom/android/server/incident/PendingReports> > 1,
return 2,
invokevirtual < Application, Lcom/android/server/incident/PendingReports, approveReport(Ljava/lang/String;)V > 8,2 @13 exception:9,
3 = getfield < Application, Lcom/android/server/incident/PendingReports, mLock, <Application,Ljava/lang/Object> > 1,
monitorenter 3,
5 = invokevirtual < Application, Lcom/android/server/incident/PendingReports, findAndRemovePendingReportRecLocked(Ljava/lang/String;)Lcom/android/server/incident/PendingReports$PendingReportRec; > 1,2 @3 exception:4,
4 = invokestatic < Application, Landroid/net/Uri, parse(Ljava/lang/String;)Landroid/net/Uri; > 2 @0 exception:3,
8 = invokevirtual < Application, Landroid/net/Uri, getQueryParameter(Ljava/lang/String;)Ljava/lang/String; > 4,6 @7 exception:7,
10 = invokestatic < Application, Ljava/lang/Integer, parseInt(Ljava/lang/String;)I > 8 @11 exception:9,
26 = getfield < Application, Lcom/android/server/incident/PendingReports, mPending, <Application,Ljava/util/ArrayList> > 1,
28 = invokevirtual < Application, Ljava/util/ArrayList, iterator()Ljava/util/Iterator; > 26 @17 exception:27,
30 = invokeinterface < Application, Ljava/util/Iterator, hasNext()Z > 28 @21 exception:29,
conditional branch(eq, to iindex=-1) 30,5,
32 = invokeinterface < Application, Ljava/util/Iterator, next()Ljava/lang/Object; > 28 @27 exception:31,
33 = checkcast <Application,Lcom/android/server/incident/PendingReports$PendingReportRec>32 <Application,Lcom/android/server/incident/PendingReports$PendingReportRec>,
34 = getfield < Application, Lcom/android/server/incident/PendingReports$PendingReportRec, id, <Primordial,I> > 33,
conditional branch(ne, to iindex=-1) 34,10,
30 = invokeinterface < Application, Ljava/util/Iterator, hasNext()Z > 28 @21 exception:29,
conditional branch(eq, to iindex=-1) 30,5,
32 = invokeinterface < Application, Ljava/util/Iterator, next()Ljava/lang/Object; > 28 @27 exception:31,
33 = checkcast <Application,Lcom/android/server/incident/PendingReports$PendingReportRec>32 <Application,Lcom/android/server/incident/PendingReports$PendingReportRec>,
34 = getfield < Application, Lcom/android/server/incident/PendingReports$PendingReportRec, id, <Primordial,I> > 33,
conditional branch(ne, to iindex=-1) 34,10,
invokeinterface < Application, Ljava/util/Iterator, remove()V > 28 @37 exception:39,
return 33,
conditional branch(ne, to iindex=-1) 5,6,
monitorexit 3,
invokevirtual < Application, Lcom/android/server/incident/PendingReports, sendBroadcast()V > 1 @34 exception:7,
3 = invokevirtual < Application, Lcom/android/server/incident/PendingReports, getAndValidateUser()I > 1 @0 exception:2,
conditional branch(ne, to iindex=-1) 3,4,
6 = invokevirtual < Application, Lcom/android/server/incident/PendingReports, getApproverComponent(I)Landroid/content/ComponentName; > 1,3 @9 exception:5,
conditional branch(ne, to iindex=-1) 6,7,
return,
9 = new <Application,Ljava/lang/StringBuilder>@39,
invokespecial < Application, Ljava/lang/StringBuilder, <init>()V > 9 @41 exception:10,
13 = invokevirtual < Application, Ljava/lang/StringBuilder, append(Ljava/lang/String;)Ljava/lang/StringBuilder; > 9,11 @46 exception:12,
15 = invokevirtual < Application, Ljava/lang/StringBuilder, append(Ljava/lang/String;)Ljava/lang/StringBuilder; > 9,2 @49 exception:14,
17 = invokevirtual < Application, Ljava/lang/StringBuilder, toString()Ljava/lang/String; > 9 @52 exception:16,
19 = invokestatic < Application, Landroid/util/Log, i(Ljava/lang/String;Ljava/lang/String;)I > 8,17 @56 exception:18,
20 = getfield < Application, Lcom/android/server/incident/PendingReports$PendingReportRec, listener, <Application,Landroid/os/IIncidentAuthListener> > 5,
invokeinterface < Application, Landroid/os/IIncidentAuthListener, onReportApproved()V > 20 @61 exception:21,
goto (from iindex= 29 to iindex = 24),
return,
invokestatic < Application, Landroid/os/Binder, restoreCallingIdentity(J)V > 5 @16 exception:15,
return,","depth : 0
-----
depth : 1
-----
depth : 1
-----
depth : 2
-----
depth : 2
-----
","public void approveReport(String p1){
	long v2 = Binder.clearCallingIdentity();
	PendingReports v3 = this.mPendingReports;
	Uri v6 = Uri.parse(p1);
	String v7 = v6.getQueryParameter(""id"");
	int v8 = Integer.parseInt(v7);
	Iterator v9 = this.mPending.iterator();
	boolean v10 = v9.hasNext();
	if (v10 == 0) {
		Object v11 = v9.next();
		if (PendingReports$PendingReportRec.id != v8) {
			boolean v12 = v9.hasNext();
			if (v12 == 0) {
				Object v13 = v9.next();
				if (PendingReports$PendingReportRec.id != v8) {
					v9.remove();
					PendingReports$PendingReportRec v5 = v13;
					if (v5 != 0) {
						int v16 = PendingReports.getAndValidateUser();
						if (v16 != -10000) {
							ComponentName v17 = PendingReports.getApproverComponent(v16);
							if (v17 != 0) {
								PendingReports$PendingReportRec.listener.onReportApproved();
								Binder.restoreCallingIdentity(v2);
								return;
							}
						}
					}
				}
			}
		}
	}
}
","SYS_OR_SIG"

"Lcom/android/server/incident/IncidentCompanionService$BinderService","deleteAllIncidentReports(Ljava/lang/String;)V","0","conditional branch(eq, to iindex=-1) 2,3,
5 = invokevirtual < Application, Ljava/lang/String, length()I > 2 @2 exception:4,
conditional branch(eq, to iindex=-1) 5,3,
invokevirtual < Application, Lcom/android/server/incident/IncidentCompanionService$BinderService, enforceAccessReportsPermissions(Ljava/lang/String;)V > 1,2 @8 exception:9,
11 = invokestatic < Application, Landroid/os/Binder, clearCallingIdentity()J > @11 exception:10,
12 = getfield < Application, Lcom/android/server/incident/IncidentCompanionService$BinderService, this$0, <Application,Lcom/android/server/incident/IncidentCompanionService> > 1,
14 = invokestatic < Application, Lcom/android/server/incident/IncidentCompanionService, -$$Nest$mgetIIncidentManager(Lcom/android/server/incident/IncidentCompanionService;)Landroid/os/IIncidentManager; > 12 @17 exception:13,
invokeinterface < Application, Landroid/os/IIncidentManager, deleteAllIncidentReports(Ljava/lang/String;)V > 14,2 @21 exception:15,
invokestatic < Application, Landroid/os/Binder, restoreCallingIdentity(J)V > 11 @24 exception:21,
return,","depth : 0
-----
","public void deleteAllIncidentReports(String p1){
	if (p1 == 0) {
		int v1 = p1.length();
		if (v1 == 0) {
			long v3 = Binder.clearCallingIdentity();
			IIncidentManager v4 = IncidentCompanionService.-$$Nest$mgetIIncidentManager(this.this$0);
			v4.deleteAllIncidentReports(p1);
			Binder.restoreCallingIdentity(v3);
			return;
		}
	}
}
","SYS_OR_SIG"
"Lcom/android/server/incident/IncidentCompanionService$BinderService","deleteAllIncidentReports(Ljava/lang/String;)V","1","conditional branch(eq, to iindex=-1) 2,3,
5 = invokevirtual < Application, Ljava/lang/String, length()I > 2 @2 exception:4,
conditional branch(eq, to iindex=-1) 5,3,
invokevirtual < Application, Lcom/android/server/incident/IncidentCompanionService$BinderService, enforceAccessReportsPermissions(Ljava/lang/String;)V > 1,2 @8 exception:9,
11 = invokestatic < Application, Landroid/os/Binder, clearCallingIdentity()J > @11 exception:10,
12 = getfield < Application, Lcom/android/server/incident/IncidentCompanionService$BinderService, this$0, <Application,Lcom/android/server/incident/IncidentCompanionService> > 1,
14 = invokestatic < Application, Lcom/android/server/incident/IncidentCompanionService, -$$Nest$mgetIIncidentManager(Lcom/android/server/incident/IncidentCompanionService;)Landroid/os/IIncidentManager; > 12 @17 exception:13,
3 = invokevirtual < Application, Lcom/android/server/incident/IncidentCompanionService, getIIncidentManager()Landroid/os/IIncidentManager; > 1 @0 exception:2,
return 3,
invokeinterface < Application, Landroid/os/IIncidentManager, deleteAllIncidentReports(Ljava/lang/String;)V > 14,2 @21 exception:15,
invokestatic < Application, Landroid/os/Binder, restoreCallingIdentity(J)V > 11 @24 exception:21,
return,","depth : 0
-----
depth : 1
-----
","public void deleteAllIncidentReports(String p1){
	if (p1 == 0) {
		int v1 = p1.length();
		if (v1 == 0) {
			long v3 = Binder.clearCallingIdentity();
			IIncidentManager v5 = this.this$0.getIIncidentManager();
			IIncidentManager v4 = v5;
			v4.deleteAllIncidentReports(p1);
			Binder.restoreCallingIdentity(v3);
			return;
		}
	}
}
","SYS_OR_SIG"
"Lcom/android/server/incident/IncidentCompanionService$BinderService","deleteAllIncidentReports(Ljava/lang/String;)V","2","conditional branch(eq, to iindex=-1) 2,3,
5 = invokevirtual < Application, Ljava/lang/String, length()I > 2 @2 exception:4,
conditional branch(eq, to iindex=-1) 5,3,
invokevirtual < Application, Lcom/android/server/incident/IncidentCompanionService$BinderService, enforceAccessReportsPermissions(Ljava/lang/String;)V > 1,2 @8 exception:9,
11 = invokestatic < Application, Landroid/os/Binder, clearCallingIdentity()J > @11 exception:10,
12 = getfield < Application, Lcom/android/server/incident/IncidentCompanionService$BinderService, this$0, <Application,Lcom/android/server/incident/IncidentCompanionService> > 1,
14 = invokestatic < Application, Lcom/android/server/incident/IncidentCompanionService, -$$Nest$mgetIIncidentManager(Lcom/android/server/incident/IncidentCompanionService;)Landroid/os/IIncidentManager; > 12 @17 exception:13,
3 = invokevirtual < Application, Lcom/android/server/incident/IncidentCompanionService, getIIncidentManager()Landroid/os/IIncidentManager; > 1 @0 exception:2,
4 = invokestatic < Application, Landroid/os/ServiceManager, getService(Ljava/lang/String;)Landroid/os/IBinder; > 2 @2 exception:3,
6 = invokestatic < Application, Landroid/os/IIncidentManager$Stub, asInterface(Landroid/os/IBinder;)Landroid/os/IIncidentManager; > 4 @6 exception:5,
return 6,
return 3,
invokeinterface < Application, Landroid/os/IIncidentManager, deleteAllIncidentReports(Ljava/lang/String;)V > 14,2 @21 exception:15,
invokestatic < Application, Landroid/os/Binder, restoreCallingIdentity(J)V > 11 @24 exception:21,
return,","depth : 0
-----
depth : 1
-----
depth : 2
-----
","public void deleteAllIncidentReports(String p1){
	if (p1 == 0) {
		int v1 = p1.length();
		if (v1 == 0) {
			long v3 = Binder.clearCallingIdentity();
			IBinder v6 = ServiceManager.getService(""incident"");
			IIncidentManager v7 = IIncidentManager$Stub.asInterface(v6);
			IIncidentManager v5 = v7;
			IIncidentManager v4 = v5;
			v4.deleteAllIncidentReports(p1);
			Binder.restoreCallingIdentity(v3);
			return;
		}
	}
}
","SYS_OR_SIG"

