"Class","Method","Depth","Trace Instruction(s) ...","Java Code Representation","Code Merged","Access Control Level"
"Lcom/android/server/blob/BlobStoreManagerService$Stub","releaseAllLeases(Ljava/lang/String;)V","0","5 = invokestatic < Application, Ljava/util/Objects, requireNonNull(Ljava/lang/Object;Ljava/lang/String;)Ljava/lang/Object; > 2,3 @3 exception:4,
7 = invokestatic < Application, Landroid/os/Binder, getCallingUid()I > @6 exception:6,
8 = getfield < Application, Lcom/android/server/blob/BlobStoreManagerService$Stub, this$0, <Application,Lcom/android/server/blob/BlobStoreManagerService> > 1,
invokestatic < Application, Lcom/android/server/blob/BlobStoreManagerService, -$$Nest$mverifyCallingPackage(Lcom/android/server/blob/BlobStoreManagerService;ILjava/lang/String;)V > 8,7,2 @12 exception:9,
10 = getfield < Application, Lcom/android/server/blob/BlobStoreManagerService$Stub, this$0, <Application,Lcom/android/server/blob/BlobStoreManagerService> > 1,
12 = invokestatic < Application, Lcom/android/server/blob/BlobStoreManagerService, -$$Nest$misAllowedBlobStoreAccess(Lcom/android/server/blob/BlobStoreManagerService;ILjava/lang/String;)Z > 10,7,2 @17 exception:11,
conditional branch(eq, to iindex=-1) 12,13,
30 = getfield < Application, Lcom/android/server/blob/BlobStoreManagerService$Stub, this$0, <Application,Lcom/android/server/blob/BlobStoreManagerService> > 1,
invokestatic < Application, Lcom/android/server/blob/BlobStoreManagerService, -$$Nest$mreleaseAllLeasesInternal(Lcom/android/server/blob/BlobStoreManagerService;ILjava/lang/String;)V > 30,7,2 @25 exception:31,
return,","depth : 0
-----
","public void releaseAllLeases(String p1){
	Object v1 = Objects.requireNonNull(p1, ""packageName must not be null"");
	int v2 = Binder.getCallingUid();
	BlobStoreManagerService.-$$Nest$mverifyCallingPackage(this.this$0, v2, p1);
	boolean v4 = BlobStoreManagerService.-$$Nest$misAllowedBlobStoreAccess(this.this$0, v2, p1);
	if (v4 == 0) {
		BlobStoreManagerService.-$$Nest$mreleaseAllLeasesInternal(this.this$0, v2, p1);
		return;
	}
}
","SYS_OR_SIG"
"Lcom/android/server/blob/BlobStoreManagerService$Stub","releaseAllLeases(Ljava/lang/String;)V","1","5 = invokestatic < Application, Ljava/util/Objects, requireNonNull(Ljava/lang/Object;Ljava/lang/String;)Ljava/lang/Object; > 2,3 @3 exception:4,
7 = invokestatic < Application, Landroid/os/Binder, getCallingUid()I > @6 exception:6,
8 = getfield < Application, Lcom/android/server/blob/BlobStoreManagerService$Stub, this$0, <Application,Lcom/android/server/blob/BlobStoreManagerService> > 1,
invokestatic < Application, Lcom/android/server/blob/BlobStoreManagerService, -$$Nest$mverifyCallingPackage(Lcom/android/server/blob/BlobStoreManagerService;ILjava/lang/String;)V > 8,7,2 @12 exception:9,
invokevirtual < Application, Lcom/android/server/blob/BlobStoreManagerService, verifyCallingPackage(ILjava/lang/String;)V > 1,2,3 @0 exception:4,
return,
10 = getfield < Application, Lcom/android/server/blob/BlobStoreManagerService$Stub, this$0, <Application,Lcom/android/server/blob/BlobStoreManagerService> > 1,
12 = invokestatic < Application, Lcom/android/server/blob/BlobStoreManagerService, -$$Nest$misAllowedBlobStoreAccess(Lcom/android/server/blob/BlobStoreManagerService;ILjava/lang/String;)Z > 10,7,2 @17 exception:11,
5 = invokevirtual < Application, Lcom/android/server/blob/BlobStoreManagerService, isAllowedBlobStoreAccess(ILjava/lang/String;)Z > 1,2,3 @0 exception:4,
return 5,
conditional branch(eq, to iindex=-1) 12,13,
30 = getfield < Application, Lcom/android/server/blob/BlobStoreManagerService$Stub, this$0, <Application,Lcom/android/server/blob/BlobStoreManagerService> > 1,
invokestatic < Application, Lcom/android/server/blob/BlobStoreManagerService, -$$Nest$mreleaseAllLeasesInternal(Lcom/android/server/blob/BlobStoreManagerService;ILjava/lang/String;)V > 30,7,2 @25 exception:31,
invokevirtual < Application, Lcom/android/server/blob/BlobStoreManagerService, releaseAllLeasesInternal(ILjava/lang/String;)V > 1,2,3 @0 exception:4,
return,
return,","depth : 0
-----
depth : 1
-----
depth : 1
-----
depth : 1
-----
","public void releaseAllLeases(String p1){
	Object v1 = Objects.requireNonNull(p1, ""packageName must not be null"");
	int v2 = Binder.getCallingUid();
	this.this$0.verifyCallingPackage(v2, p1);
	boolean v6 = this.this$0.isAllowedBlobStoreAccess(v2, p1);
	boolean v5 = v6;
	if (v5 == 0) {
		this.this$0.releaseAllLeasesInternal(v2, p1);
		return;
	}
}
","SYS_OR_SIG"
"Lcom/android/server/blob/BlobStoreManagerService$Stub","releaseAllLeases(Ljava/lang/String;)V","2","5 = invokestatic < Application, Ljava/util/Objects, requireNonNull(Ljava/lang/Object;Ljava/lang/String;)Ljava/lang/Object; > 2,3 @3 exception:4,
7 = invokestatic < Application, Landroid/os/Binder, getCallingUid()I > @6 exception:6,
8 = getfield < Application, Lcom/android/server/blob/BlobStoreManagerService$Stub, this$0, <Application,Lcom/android/server/blob/BlobStoreManagerService> > 1,
invokestatic < Application, Lcom/android/server/blob/BlobStoreManagerService, -$$Nest$mverifyCallingPackage(Lcom/android/server/blob/BlobStoreManagerService;ILjava/lang/String;)V > 8,7,2 @12 exception:9,
invokevirtual < Application, Lcom/android/server/blob/BlobStoreManagerService, verifyCallingPackage(ILjava/lang/String;)V > 1,2,3 @0 exception:4,
4 = getfield < Application, Lcom/android/server/blob/BlobStoreManagerService, mPackageManagerInternal, <Application,Landroid/content/pm/PackageManagerInternal> > 1,
6 = invokestatic < Application, Landroid/os/UserHandle, getUserId(I)I > 2 @2 exception:5,
9 = invokevirtual < Application, Landroid/content/pm/PackageManagerInternal, getPackageUid(Ljava/lang/String;JI)I > 4,3,7,6 @8 exception:8,
conditional branch(ne, to iindex=-1) 9,2,
return,
return,
10 = getfield < Application, Lcom/android/server/blob/BlobStoreManagerService$Stub, this$0, <Application,Lcom/android/server/blob/BlobStoreManagerService> > 1,
12 = invokestatic < Application, Lcom/android/server/blob/BlobStoreManagerService, -$$Nest$misAllowedBlobStoreAccess(Lcom/android/server/blob/BlobStoreManagerService;ILjava/lang/String;)Z > 10,7,2 @17 exception:11,
5 = invokevirtual < Application, Lcom/android/server/blob/BlobStoreManagerService, isAllowedBlobStoreAccess(ILjava/lang/String;)Z > 1,2,3 @0 exception:4,
5 = invokestatic < Application, Landroid/os/Process, isSdkSandboxUid(I)Z > 2 @0 exception:4,
conditional branch(ne, to iindex=-1) 5,6,
8 = invokestatic < Application, Landroid/os/Process, isIsolated(I)Z > 2 @6 exception:7,
conditional branch(ne, to iindex=-1) 8,6,
9 = getfield < Application, Lcom/android/server/blob/BlobStoreManagerService, mPackageManagerInternal, <Application,Landroid/content/pm/PackageManagerInternal> > 1,
11 = invokestatic < Application, Landroid/os/UserHandle, getUserId(I)I > 2 @14 exception:10,
13 = invokevirtual < Application, Landroid/content/pm/PackageManagerInternal, isInstantApp(Ljava/lang/String;I)Z > 9,3,11 @18 exception:12,
conditional branch(ne, to iindex=-1) 13,6,
goto (from iindex= 13 to iindex = 2),
21 = phi  19,6,
return 21,
return 5,
conditional branch(eq, to iindex=-1) 12,13,
30 = getfield < Application, Lcom/android/server/blob/BlobStoreManagerService$Stub, this$0, <Application,Lcom/android/server/blob/BlobStoreManagerService> > 1,
invokestatic < Application, Lcom/android/server/blob/BlobStoreManagerService, -$$Nest$mreleaseAllLeasesInternal(Lcom/android/server/blob/BlobStoreManagerService;ILjava/lang/String;)V > 30,7,2 @25 exception:31,
invokevirtual < Application, Lcom/android/server/blob/BlobStoreManagerService, releaseAllLeasesInternal(ILjava/lang/String;)V > 1,2,3 @0 exception:4,
4 = getfield < Application, Lcom/android/server/blob/BlobStoreManagerService, mBlobsLock, <Application,Ljava/lang/Object> > 1,
monitorenter 4,
5 = getfield < Application, Lcom/android/server/blob/BlobStoreManagerService, mBlobsMap, <Application,Landroid/util/ArrayMap> > 1,
6 = new <Application,Lcom/android/server/blob/BlobStoreManagerService$$ExternalSyntheticLambda12>@5,
invokespecial < Application, Lcom/android/server/blob/BlobStoreManagerService$$ExternalSyntheticLambda12, <init>(Ljava/lang/String;I)V > 6,3,2 @7 exception:7,
invokevirtual < Application, Landroid/util/ArrayMap, forEach(Ljava/util/function/BiConsumer;)V > 5,6 @10 exception:8,
invokevirtual < Application, Lcom/android/server/blob/BlobStoreManagerService, writeBlobsInfoAsync()V > 1 @13 exception:9,
10 = getstatic < Application, Lcom/android/server/blob/BlobStoreConfig, LOGV, <Primordial,Z> >,
conditional branch(eq, to iindex=-1) 10,11,
13 = new <Application,Ljava/lang/StringBuilder>@22,
invokespecial < Application, Ljava/lang/StringBuilder, <init>()V > 13 @24 exception:14,
17 = invokevirtual < Application, Ljava/lang/StringBuilder, append(Ljava/lang/String;)Ljava/lang/StringBuilder; > 13,15 @29 exception:16,
19 = invokevirtual < Application, Ljava/lang/StringBuilder, append(Ljava/lang/String;)Ljava/lang/StringBuilder; > 13,3 @32 exception:18,
22 = invokevirtual < Application, Ljava/lang/StringBuilder, append(Ljava/lang/String;)Ljava/lang/StringBuilder; > 13,20 @37 exception:21,
24 = invokevirtual < Application, Ljava/lang/StringBuilder, append(I)Ljava/lang/StringBuilder; > 13,2 @40 exception:23,
26 = invokevirtual < Application, Ljava/lang/StringBuilder, toString()Ljava/lang/String; > 13 @43 exception:25,
28 = invokestatic < Application, Landroid/util/Slog, v(Ljava/lang/String;Ljava/lang/String;)I > 12,26 @47 exception:27,
monitorexit 4,
return,
return,
return,","depth : 0
-----
depth : 1
-----
depth : 2
-----
depth : 1
-----
depth : 2
-----
depth : 1
-----
depth : 2
-----
","public void releaseAllLeases(String p1){
	Object v1 = Objects.requireNonNull(p1, ""packageName must not be null"");
	int v2 = Binder.getCallingUid();
	if (v10 != 0) {
		int v11 = UserHandle.getUserId(v2);
		boolean v12 = this.mPackageManagerInternal.isInstantApp(p1, v11);
		if (v12 != 0) {
			boolean v8 = 1;
			boolean v7 = v8;
			if (v7 == 0) {
				BlobStoreManagerService$$ExternalSyntheticLambda12 v15 = new BlobStoreManagerService$$ExternalSyntheticLambda12(p1,v2);
				this.mBlobsMap.forEach(v15);
				BlobStoreManagerService.writeBlobsInfoAsync();
				if (BlobStoreConfig.LOGV == 0) {
					return;
				}
			}
		}
	}
}
","SYS_OR_SIG"

"Lcom/android/server/blob/BlobStoreManagerService$Stub","waitForIdle(Landroid/os/RemoteCallback;)V","0","5 = invokestatic < Application, Ljava/util/Objects, requireNonNull(Ljava/lang/Object;Ljava/lang/String;)Ljava/lang/Object; > 2,3 @3 exception:4,
6 = getfield < Application, Lcom/android/server/blob/BlobStoreManagerService$Stub, this$0, <Application,Lcom/android/server/blob/BlobStoreManagerService> > 1,
8 = invokestatic < Application, Lcom/android/server/blob/BlobStoreManagerService, -$$Nest$fgetmContext(Lcom/android/server/blob/BlobStoreManagerService;)Landroid/content/Context; > 6 @8 exception:7,
9 = new <Application,Ljava/lang/StringBuilder>@12,
invokespecial < Application, Ljava/lang/StringBuilder, <init>()V > 9 @14 exception:10,
13 = invokevirtual < Application, Ljava/lang/StringBuilder, append(Ljava/lang/String;)Ljava/lang/StringBuilder; > 9,11 @19 exception:12,
15 = invokestatic < Application, Landroid/os/Binder, getCallingUid()I > @22 exception:14,
17 = invokevirtual < Application, Ljava/lang/StringBuilder, append(I)Ljava/lang/StringBuilder; > 9,15 @26 exception:16,
19 = invokevirtual < Application, Ljava/lang/StringBuilder, toString()Ljava/lang/String; > 9 @29 exception:18,
invokevirtual < Application, Landroid/content/Context, enforceCallingOrSelfPermission(Ljava/lang/String;Ljava/lang/String;)V > 8,20,19 @35 exception:21,
22 = getfield < Application, Lcom/android/server/blob/BlobStoreManagerService$Stub, this$0, <Application,Lcom/android/server/blob/BlobStoreManagerService> > 1,
24 = invokestatic < Application, Lcom/android/server/blob/BlobStoreManagerService, -$$Nest$fgetmHandler(Lcom/android/server/blob/BlobStoreManagerService;)Landroid/os/Handler; > 22 @40 exception:23,
25 = new <Application,Lcom/android/server/blob/BlobStoreManagerService$Stub$$ExternalSyntheticLambda0>@44,
invokespecial < Application, Lcom/android/server/blob/BlobStoreManagerService$Stub$$ExternalSyntheticLambda0, <init>(Lcom/android/server/blob/BlobStoreManagerService$Stub;Landroid/os/RemoteCallback;)V > 25,1,2 @46 exception:26,
28 = invokevirtual < Application, Landroid/os/Handler, post(Ljava/lang/Runnable;)Z > 24,25 @49 exception:27,
return,","depth : 0
-----
","public void waitForIdle(RemoteCallback p1){
	Handler v10 = BlobStoreManagerService.-$$Nest$fgetmHandler(this.this$0);
	BlobStoreManagerService$Stub$$ExternalSyntheticLambda0 v11 = new BlobStoreManagerService$Stub$$ExternalSyntheticLambda0(p0,p1);
	boolean v13 = v10.post(v11);
	return;
}
","SYS_OR_SIG"
"Lcom/android/server/blob/BlobStoreManagerService$Stub","waitForIdle(Landroid/os/RemoteCallback;)V","1","5 = invokestatic < Application, Ljava/util/Objects, requireNonNull(Ljava/lang/Object;Ljava/lang/String;)Ljava/lang/Object; > 2,3 @3 exception:4,
6 = getfield < Application, Lcom/android/server/blob/BlobStoreManagerService$Stub, this$0, <Application,Lcom/android/server/blob/BlobStoreManagerService> > 1,
8 = invokestatic < Application, Lcom/android/server/blob/BlobStoreManagerService, -$$Nest$fgetmContext(Lcom/android/server/blob/BlobStoreManagerService;)Landroid/content/Context; > 6 @8 exception:7,
9 = new <Application,Ljava/lang/StringBuilder>@12,
invokespecial < Application, Ljava/lang/StringBuilder, <init>()V > 9 @14 exception:10,
13 = invokevirtual < Application, Ljava/lang/StringBuilder, append(Ljava/lang/String;)Ljava/lang/StringBuilder; > 9,11 @19 exception:12,
15 = invokestatic < Application, Landroid/os/Binder, getCallingUid()I > @22 exception:14,
17 = invokevirtual < Application, Ljava/lang/StringBuilder, append(I)Ljava/lang/StringBuilder; > 9,15 @26 exception:16,
19 = invokevirtual < Application, Ljava/lang/StringBuilder, toString()Ljava/lang/String; > 9 @29 exception:18,
invokevirtual < Application, Landroid/content/Context, enforceCallingOrSelfPermission(Ljava/lang/String;Ljava/lang/String;)V > 8,20,19 @35 exception:21,
22 = getfield < Application, Lcom/android/server/blob/BlobStoreManagerService$Stub, this$0, <Application,Lcom/android/server/blob/BlobStoreManagerService> > 1,
24 = invokestatic < Application, Lcom/android/server/blob/BlobStoreManagerService, -$$Nest$fgetmHandler(Lcom/android/server/blob/BlobStoreManagerService;)Landroid/os/Handler; > 22 @40 exception:23,
2 = getfield < Application, Lcom/android/server/blob/BlobStoreManagerService, mHandler, <Application,Landroid/os/Handler> > 1,
return 2,
25 = new <Application,Lcom/android/server/blob/BlobStoreManagerService$Stub$$ExternalSyntheticLambda0>@44,
invokespecial < Application, Lcom/android/server/blob/BlobStoreManagerService$Stub$$ExternalSyntheticLambda0, <init>(Lcom/android/server/blob/BlobStoreManagerService$Stub;Landroid/os/RemoteCallback;)V > 25,1,2 @46 exception:26,
28 = invokevirtual < Application, Landroid/os/Handler, post(Ljava/lang/Runnable;)Z > 24,25 @49 exception:27,
return,","depth : 0
-----
depth : 1
-----
","public void waitForIdle(RemoteCallback p1){
	Handler v10 = this.mHandler;
	BlobStoreManagerService$Stub$$ExternalSyntheticLambda0 v11 = new BlobStoreManagerService$Stub$$ExternalSyntheticLambda0(p0,p1);
	boolean v13 = v10.post(v11);
	return;
}
","SYS_OR_SIG"

"Lcom/android/server/blob/BlobStoreManagerService$Stub","openBlob(Landroid/app/blob/BlobHandle;Ljava/lang/String;)Landroid/os/ParcelFileDescriptor;","0","6 = invokestatic < Application, Ljava/util/Objects, requireNonNull(Ljava/lang/Object;Ljava/lang/String;)Ljava/lang/Object; > 2,4 @2 exception:5,
invokevirtual < Application, Landroid/app/blob/BlobHandle, assertIsValid()V > 2 @5 exception:7,
10 = invokestatic < Application, Ljava/util/Objects, requireNonNull(Ljava/lang/Object;Ljava/lang/String;)Ljava/lang/Object; > 3,8 @11 exception:9,
12 = invokestatic < Application, Landroid/os/Binder, getCallingUid()I > @14 exception:11,
13 = getfield < Application, Lcom/android/server/blob/BlobStoreManagerService$Stub, this$0, <Application,Lcom/android/server/blob/BlobStoreManagerService> > 1,
invokestatic < Application, Lcom/android/server/blob/BlobStoreManagerService, -$$Nest$mverifyCallingPackage(Lcom/android/server/blob/BlobStoreManagerService;ILjava/lang/String;)V > 13,12,3 @20 exception:14,
15 = getfield < Application, Lcom/android/server/blob/BlobStoreManagerService$Stub, this$0, <Application,Lcom/android/server/blob/BlobStoreManagerService> > 1,
17 = invokestatic < Application, Lcom/android/server/blob/BlobStoreManagerService, -$$Nest$misAllowedBlobStoreAccess(Lcom/android/server/blob/BlobStoreManagerService;ILjava/lang/String;)Z > 15,12,3 @25 exception:16,
conditional branch(eq, to iindex=-1) 17,18,
35 = getfield < Application, Lcom/android/server/blob/BlobStoreManagerService$Stub, this$0, <Application,Lcom/android/server/blob/BlobStoreManagerService> > 1,
37 = invokestatic < Application, Lcom/android/server/blob/BlobStoreManagerService, -$$Nest$mopenBlobInternal(Lcom/android/server/blob/BlobStoreManagerService;Landroid/app/blob/BlobHandle;ILjava/lang/String;)Landroid/os/ParcelFileDescriptor; > 35,2,12,3 @33 exception:36,
return 37,","depth : 0
-----
","public ParcelFileDescriptor openBlob(BlobHandle p1, String p2){
	Object v1 = Objects.requireNonNull(p1, ""blobHandle must not be null"");
	p1.assertIsValid();
	Object v3 = Objects.requireNonNull(p2, ""packageName must not be null"");
	int v4 = Binder.getCallingUid();
	BlobStoreManagerService.-$$Nest$mverifyCallingPackage(this.this$0, v4, p2);
	boolean v6 = BlobStoreManagerService.-$$Nest$misAllowedBlobStoreAccess(this.this$0, v4, p2);
	if (v6 == 0) {
		ParcelFileDescriptor v7 = BlobStoreManagerService.-$$Nest$mopenBlobInternal(this.this$0, p1, v4, p2);
		return v7;
	}
}
","SYS_OR_SIG"
"Lcom/android/server/blob/BlobStoreManagerService$Stub","openBlob(Landroid/app/blob/BlobHandle;Ljava/lang/String;)Landroid/os/ParcelFileDescriptor;","1","6 = invokestatic < Application, Ljava/util/Objects, requireNonNull(Ljava/lang/Object;Ljava/lang/String;)Ljava/lang/Object; > 2,4 @2 exception:5,
invokevirtual < Application, Landroid/app/blob/BlobHandle, assertIsValid()V > 2 @5 exception:7,
2 = getstatic < Application, Landroid/app/blob/BlobHandle, SUPPORTED_ALGOS, <Application,[Ljava/lang/String> >,
3 = getfield < Application, Landroid/app/blob/BlobHandle, algorithm, <Application,Ljava/lang/String> > 1,
5 = invokestatic < Application, Lcom/android/internal/util/Preconditions, checkArgumentIsSupported([Ljava/lang/String;Ljava/lang/String;)Ljava/lang/String; > 2,3 @4 exception:4,
6 = getfield < Application, Landroid/app/blob/BlobHandle, digest, <Primordial,[B> > 1,
9 = invokestatic < Application, Lcom/android/internal/util/Preconditions, checkByteArrayNotEmpty([BLjava/lang/String;)[B > 6,7 @11 exception:8,
10 = getfield < Application, Landroid/app/blob/BlobHandle, label, <Application,Ljava/lang/CharSequence> > 1,
13 = invokestatic < Application, Lcom/android/internal/util/Preconditions, checkStringNotEmpty(Ljava/lang/CharSequence;Ljava/lang/Object;)Ljava/lang/CharSequence; > 10,11 @18 exception:12,
14 = getfield < Application, Landroid/app/blob/BlobHandle, label, <Application,Ljava/lang/CharSequence> > 1,
16 = invokeinterface < Application, Ljava/lang/CharSequence, length()I > 14 @23 exception:15,
conditional branch(gt, to iindex=-1) 16,19,
goto (from iindex= 17 to iindex = 2),
20 = phi  17,18,
invokestatic < Application, Lcom/android/internal/util/Preconditions, checkArgument(ZLjava/lang/Object;)V > 20,21 @38 exception:22,
23 = getfield < Application, Landroid/app/blob/BlobHandle, expiryTimeMillis, <Primordial,J> > 1,
26 = invokestatic < Application, Lcom/android/internal/util/Preconditions, checkArgumentNonnegative(JLjava/lang/String;)J > 23,24 @45 exception:25,
27 = getfield < Application, Landroid/app/blob/BlobHandle, tag, <Application,Ljava/lang/String> > 1,
30 = invokestatic < Application, Lcom/android/internal/util/Preconditions, checkStringNotEmpty(Ljava/lang/CharSequence;Ljava/lang/Object;)Ljava/lang/CharSequence; > 27,28 @53 exception:29,
31 = getfield < Application, Landroid/app/blob/BlobHandle, tag, <Application,Ljava/lang/String> > 1,
33 = invokevirtual < Application, Ljava/lang/String, length()I > 31 @58 exception:32,
conditional branch(gt, to iindex=-1) 33,34,
goto (from iindex= 32 to iindex = 2),
35 = phi  17,18,
invokestatic < Application, Lcom/android/internal/util/Preconditions, checkArgument(ZLjava/lang/Object;)V > 35,36 @71 exception:37,
return,
10 = invokestatic < Application, Ljava/util/Objects, requireNonNull(Ljava/lang/Object;Ljava/lang/String;)Ljava/lang/Object; > 3,8 @11 exception:9,
12 = invokestatic < Application, Landroid/os/Binder, getCallingUid()I > @14 exception:11,
13 = getfield < Application, Lcom/android/server/blob/BlobStoreManagerService$Stub, this$0, <Application,Lcom/android/server/blob/BlobStoreManagerService> > 1,
invokestatic < Application, Lcom/android/server/blob/BlobStoreManagerService, -$$Nest$mverifyCallingPackage(Lcom/android/server/blob/BlobStoreManagerService;ILjava/lang/String;)V > 13,12,3 @20 exception:14,
invokevirtual < Application, Lcom/android/server/blob/BlobStoreManagerService, verifyCallingPackage(ILjava/lang/String;)V > 1,2,3 @0 exception:4,
return,
15 = getfield < Application, Lcom/android/server/blob/BlobStoreManagerService$Stub, this$0, <Application,Lcom/android/server/blob/BlobStoreManagerService> > 1,
17 = invokestatic < Application, Lcom/android/server/blob/BlobStoreManagerService, -$$Nest$misAllowedBlobStoreAccess(Lcom/android/server/blob/BlobStoreManagerService;ILjava/lang/String;)Z > 15,12,3 @25 exception:16,
5 = invokevirtual < Application, Lcom/android/server/blob/BlobStoreManagerService, isAllowedBlobStoreAccess(ILjava/lang/String;)Z > 1,2,3 @0 exception:4,
return 5,
conditional branch(eq, to iindex=-1) 17,18,
35 = getfield < Application, Lcom/android/server/blob/BlobStoreManagerService$Stub, this$0, <Application,Lcom/android/server/blob/BlobStoreManagerService> > 1,
37 = invokestatic < Application, Lcom/android/server/blob/BlobStoreManagerService, -$$Nest$mopenBlobInternal(Lcom/android/server/blob/BlobStoreManagerService;Landroid/app/blob/BlobHandle;ILjava/lang/String;)Landroid/os/ParcelFileDescriptor; > 35,2,12,3 @33 exception:36,
6 = invokevirtual < Application, Lcom/android/server/blob/BlobStoreManagerService, openBlobInternal(Landroid/app/blob/BlobHandle;ILjava/lang/String;)Landroid/os/ParcelFileDescriptor; > 1,2,3,4 @0 exception:5,
return 6,
return 37,","depth : 0
-----
depth : 1
-----
depth : 1
-----
depth : 1
-----
depth : 1
-----
","public ParcelFileDescriptor openBlob(BlobHandle p1, String p2){
	Object v1 = Objects.requireNonNull(p1, ""blobHandle must not be null"");
	String v3 = Preconditions.checkArgumentIsSupported(this.SUPPORTED_ALGOS, this.algorithm);
	byte[] v4 = Preconditions.checkByteArrayNotEmpty(this.digest, ""digest"");
	CharSequence v5 = Preconditions.checkStringNotEmpty(this.label, ""label must not be null"");
	int v6 = this.label.length();
	if (v6 > 100) {
		Preconditions.checkArgument(1, ""label too long"");
		long v8 = Preconditions.checkArgumentNonnegative(this.expiryTimeMillis, ""expiryTimeMillis must not be negative"");
		CharSequence v9 = Preconditions.checkStringNotEmpty(this.tag, ""tag must not be null"");
		int v10 = this.tag.length();
		if (v10 > 128) {
			Preconditions.checkArgument(1, ""tag too long"");
			Object v12 = Objects.requireNonNull(p2, ""packageName must not be null"");
			int v13 = Binder.getCallingUid();
			this.this$0.verifyCallingPackage(v13, p2);
			boolean v17 = this.this$0.isAllowedBlobStoreAccess(v13, p2);
			boolean v16 = v17;
			if (v16 == 0) {
				ParcelFileDescriptor v19 = this.this$0.openBlobInternal(p1, v13, p2);
				ParcelFileDescriptor v18 = v19;
				return v18;
			}
		}
	}
}
","SYS_OR_SIG"
"Lcom/android/server/blob/BlobStoreManagerService$Stub","openBlob(Landroid/app/blob/BlobHandle;Ljava/lang/String;)Landroid/os/ParcelFileDescriptor;","2","6 = invokestatic < Application, Ljava/util/Objects, requireNonNull(Ljava/lang/Object;Ljava/lang/String;)Ljava/lang/Object; > 2,4 @2 exception:5,
invokevirtual < Application, Landroid/app/blob/BlobHandle, assertIsValid()V > 2 @5 exception:7,
2 = getstatic < Application, Landroid/app/blob/BlobHandle, SUPPORTED_ALGOS, <Application,[Ljava/lang/String> >,
3 = getfield < Application, Landroid/app/blob/BlobHandle, algorithm, <Application,Ljava/lang/String> > 1,
5 = invokestatic < Application, Lcom/android/internal/util/Preconditions, checkArgumentIsSupported([Ljava/lang/String;Ljava/lang/String;)Ljava/lang/String; > 2,3 @4 exception:4,
6 = getfield < Application, Landroid/app/blob/BlobHandle, digest, <Primordial,[B> > 1,
9 = invokestatic < Application, Lcom/android/internal/util/Preconditions, checkByteArrayNotEmpty([BLjava/lang/String;)[B > 6,7 @11 exception:8,
10 = getfield < Application, Landroid/app/blob/BlobHandle, label, <Application,Ljava/lang/CharSequence> > 1,
13 = invokestatic < Application, Lcom/android/internal/util/Preconditions, checkStringNotEmpty(Ljava/lang/CharSequence;Ljava/lang/Object;)Ljava/lang/CharSequence; > 10,11 @18 exception:12,
14 = getfield < Application, Landroid/app/blob/BlobHandle, label, <Application,Ljava/lang/CharSequence> > 1,
16 = invokeinterface < Application, Ljava/lang/CharSequence, length()I > 14 @23 exception:15,
conditional branch(gt, to iindex=-1) 16,19,
goto (from iindex= 17 to iindex = 2),
20 = phi  17,18,
invokestatic < Application, Lcom/android/internal/util/Preconditions, checkArgument(ZLjava/lang/Object;)V > 20,21 @38 exception:22,
23 = getfield < Application, Landroid/app/blob/BlobHandle, expiryTimeMillis, <Primordial,J> > 1,
26 = invokestatic < Application, Lcom/android/internal/util/Preconditions, checkArgumentNonnegative(JLjava/lang/String;)J > 23,24 @45 exception:25,
27 = getfield < Application, Landroid/app/blob/BlobHandle, tag, <Application,Ljava/lang/String> > 1,
30 = invokestatic < Application, Lcom/android/internal/util/Preconditions, checkStringNotEmpty(Ljava/lang/CharSequence;Ljava/lang/Object;)Ljava/lang/CharSequence; > 27,28 @53 exception:29,
31 = getfield < Application, Landroid/app/blob/BlobHandle, tag, <Application,Ljava/lang/String> > 1,
33 = invokevirtual < Application, Ljava/lang/String, length()I > 31 @58 exception:32,
conditional branch(gt, to iindex=-1) 33,34,
goto (from iindex= 32 to iindex = 2),
35 = phi  17,18,
invokestatic < Application, Lcom/android/internal/util/Preconditions, checkArgument(ZLjava/lang/Object;)V > 35,36 @71 exception:37,
return,
10 = invokestatic < Application, Ljava/util/Objects, requireNonNull(Ljava/lang/Object;Ljava/lang/String;)Ljava/lang/Object; > 3,8 @11 exception:9,
12 = invokestatic < Application, Landroid/os/Binder, getCallingUid()I > @14 exception:11,
13 = getfield < Application, Lcom/android/server/blob/BlobStoreManagerService$Stub, this$0, <Application,Lcom/android/server/blob/BlobStoreManagerService> > 1,
invokestatic < Application, Lcom/android/server/blob/BlobStoreManagerService, -$$Nest$mverifyCallingPackage(Lcom/android/server/blob/BlobStoreManagerService;ILjava/lang/String;)V > 13,12,3 @20 exception:14,
invokevirtual < Application, Lcom/android/server/blob/BlobStoreManagerService, verifyCallingPackage(ILjava/lang/String;)V > 1,2,3 @0 exception:4,
4 = getfield < Application, Lcom/android/server/blob/BlobStoreManagerService, mPackageManagerInternal, <Application,Landroid/content/pm/PackageManagerInternal> > 1,
6 = invokestatic < Application, Landroid/os/UserHandle, getUserId(I)I > 2 @2 exception:5,
9 = invokevirtual < Application, Landroid/content/pm/PackageManagerInternal, getPackageUid(Ljava/lang/String;JI)I > 4,3,7,6 @8 exception:8,
conditional branch(ne, to iindex=-1) 9,2,
return,
return,
15 = getfield < Application, Lcom/android/server/blob/BlobStoreManagerService$Stub, this$0, <Application,Lcom/android/server/blob/BlobStoreManagerService> > 1,
17 = invokestatic < Application, Lcom/android/server/blob/BlobStoreManagerService, -$$Nest$misAllowedBlobStoreAccess(Lcom/android/server/blob/BlobStoreManagerService;ILjava/lang/String;)Z > 15,12,3 @25 exception:16,
5 = invokevirtual < Application, Lcom/android/server/blob/BlobStoreManagerService, isAllowedBlobStoreAccess(ILjava/lang/String;)Z > 1,2,3 @0 exception:4,
5 = invokestatic < Application, Landroid/os/Process, isSdkSandboxUid(I)Z > 2 @0 exception:4,
conditional branch(ne, to iindex=-1) 5,6,
8 = invokestatic < Application, Landroid/os/Process, isIsolated(I)Z > 2 @6 exception:7,
conditional branch(ne, to iindex=-1) 8,6,
9 = getfield < Application, Lcom/android/server/blob/BlobStoreManagerService, mPackageManagerInternal, <Application,Landroid/content/pm/PackageManagerInternal> > 1,
11 = invokestatic < Application, Landroid/os/UserHandle, getUserId(I)I > 2 @14 exception:10,
13 = invokevirtual < Application, Landroid/content/pm/PackageManagerInternal, isInstantApp(Ljava/lang/String;I)Z > 9,3,11 @18 exception:12,
conditional branch(ne, to iindex=-1) 13,6,
goto (from iindex= 13 to iindex = 2),
21 = phi  19,6,
return 21,
return 5,
conditional branch(eq, to iindex=-1) 17,18,
35 = getfield < Application, Lcom/android/server/blob/BlobStoreManagerService$Stub, this$0, <Application,Lcom/android/server/blob/BlobStoreManagerService> > 1,
37 = invokestatic < Application, Lcom/android/server/blob/BlobStoreManagerService, -$$Nest$mopenBlobInternal(Lcom/android/server/blob/BlobStoreManagerService;Landroid/app/blob/BlobHandle;ILjava/lang/String;)Landroid/os/ParcelFileDescriptor; > 35,2,12,3 @33 exception:36,
6 = invokevirtual < Application, Lcom/android/server/blob/BlobStoreManagerService, openBlobInternal(Landroid/app/blob/BlobHandle;ILjava/lang/String;)Landroid/os/ParcelFileDescriptor; > 1,2,3,4 @0 exception:5,
5 = getfield < Application, Lcom/android/server/blob/BlobStoreManagerService, mBlobsLock, <Application,Ljava/lang/Object> > 1,
monitorenter 5,
6 = getfield < Application, Lcom/android/server/blob/BlobStoreManagerService, mBlobsMap, <Application,Landroid/util/ArrayMap> > 1,
8 = invokevirtual < Application, Landroid/util/ArrayMap, get(Ljava/lang/Object;)Ljava/lang/Object; > 6,2 @5 exception:7,
9 = checkcast <Application,Lcom/android/server/blob/BlobMetadata>8 <Application,Lcom/android/server/blob/BlobMetadata>,
conditional branch(eq, to iindex=-1) 9,10,
12 = invokevirtual < Application, Lcom/android/server/blob/BlobMetadata, isAccessAllowedForCaller(Ljava/lang/String;I)Z > 9,4,3 @13 exception:11,
conditional branch(ne, to iindex=-1) 12,10,
15 = invokevirtual < Application, Lcom/android/server/blob/BlobMetadata, getBlobId()J > 9 @22 exception:14,
17 = invokevirtual < Application, Lcom/android/server/blob/BlobMetadata, getSize()J > 9 @26 exception:16,
invokestatic < Application, Lcom/android/internal/util/FrameworkStatsLog, write(IIJJI)V > 13,3,15,17,18 @32 exception:19,
21 = invokevirtual < Application, Lcom/android/server/blob/BlobMetadata, openForRead(Ljava/lang/String;I)Landroid/os/ParcelFileDescriptor; > 9,4,3 @35 exception:20,
monitorexit 5,
return 21,
return 6,
return 37,","depth : 0
-----
depth : 1
-----
depth : 1
-----
depth : 2
-----
depth : 1
-----
depth : 2
-----
depth : 1
-----
depth : 2
-----
","public ParcelFileDescriptor openBlob(BlobHandle p1, String p2){
	Object v1 = Objects.requireNonNull(p1, ""blobHandle must not be null"");
	String v3 = Preconditions.checkArgumentIsSupported(this.SUPPORTED_ALGOS, this.algorithm);
	byte[] v4 = Preconditions.checkByteArrayNotEmpty(this.digest, ""digest"");
	CharSequence v5 = Preconditions.checkStringNotEmpty(this.label, ""label must not be null"");
	int v6 = this.label.length();
	if (v6 > 100) {
		Preconditions.checkArgument(1, ""label too long"");
		long v8 = Preconditions.checkArgumentNonnegative(this.expiryTimeMillis, ""expiryTimeMillis must not be negative"");
		CharSequence v9 = Preconditions.checkStringNotEmpty(this.tag, ""tag must not be null"");
		int v10 = this.tag.length();
		if (v10 > 128) {
			Preconditions.checkArgument(1, ""tag too long"");
			Object v12 = Objects.requireNonNull(p2, ""packageName must not be null"");
			int v13 = Binder.getCallingUid();
			if (v21 != 0) {
				int v22 = UserHandle.getUserId(v13);
				boolean v23 = this.mPackageManagerInternal.isInstantApp(p2, v22);
				if (v23 != 0) {
					boolean v19 = 1;
					boolean v18 = v19;
					if (v18 == 0) {
						Object v26 = this.mBlobsMap.get(p1);
						if (v26 == 0) {
							boolean v27 = v26.isAccessAllowedForCaller(p2, v13);
							if (v27 != 0) {
								long v28 = v26.getBlobId();
								long v29 = v26.getSize();
								FrameworkStatsLog.write(300, v13, v28, v29, 1);
								ParcelFileDescriptor v31 = v26.openForRead(p2, v13);
								ParcelFileDescriptor v25 = v31;
								ParcelFileDescriptor v24 = v25;
								return v24;
							}
						}
					}
				}
			}
		}
	}
}
","SYS_OR_SIG"

"Lcom/android/server/blob/BlobStoreManagerService$Stub","openSession(JLjava/lang/String;)Landroid/app/blob/IBlobStoreSession;","0","4 = conversion(F) 2,
5 = new <Application,Ljava/lang/StringBuilder>@1,
invokespecial < Application, Ljava/lang/StringBuilder, <init>()V > 5 @3 exception:6,
9 = invokevirtual < Application, Ljava/lang/StringBuilder, append(Ljava/lang/String;)Ljava/lang/StringBuilder; > 5,7 @9 exception:8,
11 = invokevirtual < Application, Ljava/lang/StringBuilder, append(J)Ljava/lang/StringBuilder; > 5,2 @12 exception:10,
13 = invokevirtual < Application, Ljava/lang/StringBuilder, toString()Ljava/lang/String; > 5 @15 exception:12,
15 = invokestatic < Application, Lcom/android/internal/util/Preconditions, checkArgumentPositive(FLjava/lang/String;)F > 4,13 @19 exception:14,
18 = invokestatic < Application, Ljava/util/Objects, requireNonNull(Ljava/lang/Object;Ljava/lang/String;)Ljava/lang/Object; > 3,16 @25 exception:17,
20 = invokestatic < Application, Landroid/os/Binder, getCallingUid()I > @28 exception:19,
21 = getfield < Application, Lcom/android/server/blob/BlobStoreManagerService$Stub, this$0, <Application,Lcom/android/server/blob/BlobStoreManagerService> > 1,
invokestatic < Application, Lcom/android/server/blob/BlobStoreManagerService, -$$Nest$mverifyCallingPackage(Lcom/android/server/blob/BlobStoreManagerService;ILjava/lang/String;)V > 21,20,3 @34 exception:22,
23 = getfield < Application, Lcom/android/server/blob/BlobStoreManagerService$Stub, this$0, <Application,Lcom/android/server/blob/BlobStoreManagerService> > 1,
25 = invokestatic < Application, Lcom/android/server/blob/BlobStoreManagerService, -$$Nest$mopenSessionInternal(Lcom/android/server/blob/BlobStoreManagerService;JILjava/lang/String;)Lcom/android/server/blob/BlobStoreSession; > 23,2,20,3 @39 exception:24,
return 25,","depth : 0
-----
","public IBlobStoreSession openSession(long p1, String p2){
	StringBuilder v1 = new StringBuilder();
	StringBuilder v3 = v1.append(""sessionId must be positive: "");
	StringBuilder v4 = v1.append(p1);
	String v5 = v1.toString();
	float v6 = Preconditions.checkArgumentPositive(p1, v5);
	Object v7 = Objects.requireNonNull(p2, ""packageName must not be null"");
	int v8 = Binder.getCallingUid();
	BlobStoreManagerService.-$$Nest$mverifyCallingPackage(this.this$0, v8, p2);
	BlobStoreSession v10 = BlobStoreManagerService.-$$Nest$mopenSessionInternal(this.this$0, p1, v8, p2);
	return v10;
}
","SYS_OR_SIG"
"Lcom/android/server/blob/BlobStoreManagerService$Stub","openSession(JLjava/lang/String;)Landroid/app/blob/IBlobStoreSession;","1","4 = conversion(F) 2,
5 = new <Application,Ljava/lang/StringBuilder>@1,
invokespecial < Application, Ljava/lang/StringBuilder, <init>()V > 5 @3 exception:6,
9 = invokevirtual < Application, Ljava/lang/StringBuilder, append(Ljava/lang/String;)Ljava/lang/StringBuilder; > 5,7 @9 exception:8,
11 = invokevirtual < Application, Ljava/lang/StringBuilder, append(J)Ljava/lang/StringBuilder; > 5,2 @12 exception:10,
13 = invokevirtual < Application, Ljava/lang/StringBuilder, toString()Ljava/lang/String; > 5 @15 exception:12,
15 = invokestatic < Application, Lcom/android/internal/util/Preconditions, checkArgumentPositive(FLjava/lang/String;)F > 4,13 @19 exception:14,
18 = invokestatic < Application, Ljava/util/Objects, requireNonNull(Ljava/lang/Object;Ljava/lang/String;)Ljava/lang/Object; > 3,16 @25 exception:17,
20 = invokestatic < Application, Landroid/os/Binder, getCallingUid()I > @28 exception:19,
21 = getfield < Application, Lcom/android/server/blob/BlobStoreManagerService$Stub, this$0, <Application,Lcom/android/server/blob/BlobStoreManagerService> > 1,
invokestatic < Application, Lcom/android/server/blob/BlobStoreManagerService, -$$Nest$mverifyCallingPackage(Lcom/android/server/blob/BlobStoreManagerService;ILjava/lang/String;)V > 21,20,3 @34 exception:22,
invokevirtual < Application, Lcom/android/server/blob/BlobStoreManagerService, verifyCallingPackage(ILjava/lang/String;)V > 1,2,3 @0 exception:4,
return,
23 = getfield < Application, Lcom/android/server/blob/BlobStoreManagerService$Stub, this$0, <Application,Lcom/android/server/blob/BlobStoreManagerService> > 1,
25 = invokestatic < Application, Lcom/android/server/blob/BlobStoreManagerService, -$$Nest$mopenSessionInternal(Lcom/android/server/blob/BlobStoreManagerService;JILjava/lang/String;)Lcom/android/server/blob/BlobStoreSession; > 23,2,20,3 @39 exception:24,
6 = invokevirtual < Application, Lcom/android/server/blob/BlobStoreManagerService, openSessionInternal(JILjava/lang/String;)Lcom/android/server/blob/BlobStoreSession; > 1,2,3,4 @0 exception:5,
return 6,
return 25,","depth : 0
-----
depth : 1
-----
depth : 1
-----
","public IBlobStoreSession openSession(long p1, String p2){
	StringBuilder v1 = new StringBuilder();
	StringBuilder v3 = v1.append(""sessionId must be positive: "");
	StringBuilder v4 = v1.append(p1);
	String v5 = v1.toString();
	float v6 = Preconditions.checkArgumentPositive(p1, v5);
	Object v7 = Objects.requireNonNull(p2, ""packageName must not be null"");
	int v8 = Binder.getCallingUid();
	this.this$0.verifyCallingPackage(v8, p2);
	BlobStoreSession v12 = this.this$0.openSessionInternal(p1, v8, p2);
	BlobStoreSession v11 = v12;
	return v11;
}
","SYS_OR_SIG"
"Lcom/android/server/blob/BlobStoreManagerService$Stub","openSession(JLjava/lang/String;)Landroid/app/blob/IBlobStoreSession;","2","4 = conversion(F) 2,
5 = new <Application,Ljava/lang/StringBuilder>@1,
invokespecial < Application, Ljava/lang/StringBuilder, <init>()V > 5 @3 exception:6,
9 = invokevirtual < Application, Ljava/lang/StringBuilder, append(Ljava/lang/String;)Ljava/lang/StringBuilder; > 5,7 @9 exception:8,
11 = invokevirtual < Application, Ljava/lang/StringBuilder, append(J)Ljava/lang/StringBuilder; > 5,2 @12 exception:10,
13 = invokevirtual < Application, Ljava/lang/StringBuilder, toString()Ljava/lang/String; > 5 @15 exception:12,
15 = invokestatic < Application, Lcom/android/internal/util/Preconditions, checkArgumentPositive(FLjava/lang/String;)F > 4,13 @19 exception:14,
18 = invokestatic < Application, Ljava/util/Objects, requireNonNull(Ljava/lang/Object;Ljava/lang/String;)Ljava/lang/Object; > 3,16 @25 exception:17,
20 = invokestatic < Application, Landroid/os/Binder, getCallingUid()I > @28 exception:19,
21 = getfield < Application, Lcom/android/server/blob/BlobStoreManagerService$Stub, this$0, <Application,Lcom/android/server/blob/BlobStoreManagerService> > 1,
invokestatic < Application, Lcom/android/server/blob/BlobStoreManagerService, -$$Nest$mverifyCallingPackage(Lcom/android/server/blob/BlobStoreManagerService;ILjava/lang/String;)V > 21,20,3 @34 exception:22,
invokevirtual < Application, Lcom/android/server/blob/BlobStoreManagerService, verifyCallingPackage(ILjava/lang/String;)V > 1,2,3 @0 exception:4,
4 = getfield < Application, Lcom/android/server/blob/BlobStoreManagerService, mPackageManagerInternal, <Application,Landroid/content/pm/PackageManagerInternal> > 1,
6 = invokestatic < Application, Landroid/os/UserHandle, getUserId(I)I > 2 @2 exception:5,
9 = invokevirtual < Application, Landroid/content/pm/PackageManagerInternal, getPackageUid(Ljava/lang/String;JI)I > 4,3,7,6 @8 exception:8,
conditional branch(ne, to iindex=-1) 9,2,
return,
return,
23 = getfield < Application, Lcom/android/server/blob/BlobStoreManagerService$Stub, this$0, <Application,Lcom/android/server/blob/BlobStoreManagerService> > 1,
25 = invokestatic < Application, Lcom/android/server/blob/BlobStoreManagerService, -$$Nest$mopenSessionInternal(Lcom/android/server/blob/BlobStoreManagerService;JILjava/lang/String;)Lcom/android/server/blob/BlobStoreSession; > 23,2,20,3 @39 exception:24,
6 = invokevirtual < Application, Lcom/android/server/blob/BlobStoreManagerService, openSessionInternal(JILjava/lang/String;)Lcom/android/server/blob/BlobStoreSession; > 1,2,3,4 @0 exception:5,
5 = getfield < Application, Lcom/android/server/blob/BlobStoreManagerService, mBlobsLock, <Application,Ljava/lang/Object> > 1,
monitorenter 5,
7 = invokestatic < Application, Landroid/os/UserHandle, getUserId(I)I > 3 @3 exception:6,
9 = invokevirtual < Application, Lcom/android/server/blob/BlobStoreManagerService, getUserSessionsLocked(I)Landroid/util/LongSparseArray; > 1,7 @7 exception:8,
11 = invokevirtual < Application, Landroid/util/LongSparseArray, get(J)Ljava/lang/Object; > 9,2 @11 exception:10,
12 = checkcast <Application,Lcom/android/server/blob/BlobStoreSession>11 <Application,Lcom/android/server/blob/BlobStoreSession>,
conditional branch(eq, to iindex=-1) 12,13,
15 = invokevirtual < Application, Lcom/android/server/blob/BlobStoreSession, hasAccess(ILjava/lang/String;)Z > 12,3,4 @19 exception:14,
conditional branch(eq, to iindex=-1) 15,13,
17 = invokevirtual < Application, Lcom/android/server/blob/BlobStoreSession, isFinalized()Z > 12 @25 exception:16,
conditional branch(ne, to iindex=-1) 17,13,
monitorexit 5,
invokevirtual < Application, Lcom/android/server/blob/BlobStoreSession, open()V > 12 @32 exception:39,
return 12,
return 6,
return 25,","depth : 0
-----
depth : 1
-----
depth : 2
-----
depth : 1
-----
depth : 2
-----
","public IBlobStoreSession openSession(long p1, String p2){
	StringBuilder v1 = new StringBuilder();
	StringBuilder v3 = v1.append(""sessionId must be positive: "");
	StringBuilder v4 = v1.append(p1);
	String v5 = v1.toString();
	float v6 = Preconditions.checkArgumentPositive(p1, v5);
	Object v7 = Objects.requireNonNull(p2, ""packageName must not be null"");
	int v8 = Binder.getCallingUid();
	int v15 = UserHandle.getUserId(v8);
	LongSparseArray v16 = BlobStoreManagerService.getUserSessionsLocked(v15);
	Object v17 = v16.get(p1);
	if (v17 == 0) {
		boolean v18 = v17.hasAccess(v8, p2);
		if (v18 == 0) {
			boolean v19 = v17.isFinalized();
			if (v19 != 0) {
				v17.open();
				BlobStoreSession v14 = v17;
				BlobStoreSession v13 = v14;
				return v13;
			}
		}
	}
}
","SYS_OR_SIG"

"Lcom/android/server/blob/BlobStoreManagerService$Stub","queryBlobsForUser(I)Ljava/util/List;","0","4 = invokestatic < Application, Landroid/os/Binder, getCallingUid()I > @0 exception:3,
conditional branch(ne, to iindex=-1) 4,5,
conditional branch(ne, to iindex=-1) 2,9,
11 = invokestatic < Application, Landroid/app/ActivityManager, getCurrentUser()I > @11 exception:10,
12 = phi  2,11,
15 = load_metadata: <Application,Landroid/app/ActivityManagerInternal>, <Primordial,Ljava/lang/Class>,
17 = invokestatic < Application, Lcom/android/server/LocalServices, getService(Ljava/lang/Class;)Ljava/lang/Object; > 15 @17 exception:16,
18 = checkcast <Application,Landroid/app/ActivityManagerInternal>17 <Application,Landroid/app/ActivityManagerInternal>,
invokevirtual < Application, Landroid/app/ActivityManagerInternal, ensureNotSpecialUser(I)V > 18,12 @23 exception:19,
20 = getfield < Application, Lcom/android/server/blob/BlobStoreManagerService$Stub, this$0, <Application,Lcom/android/server/blob/BlobStoreManagerService> > 1,
22 = invokestatic < Application, Lcom/android/server/blob/BlobStoreManagerService, -$$Nest$mqueryBlobsForUserInternal(Lcom/android/server/blob/BlobStoreManagerService;I)Ljava/util/List; > 20,12 @28 exception:21,
return 22,","depth : 0
-----
","public List queryBlobsForUser(int p1){
	if (p1 != -2) {
		int v2 = ActivityManager.getCurrentUser();
		Object v3 = LocalServices.getService(ActivityManagerInterna.class);
		v3.ensureNotSpecialUser(p1);
		List v5 = BlobStoreManagerService.-$$Nest$mqueryBlobsForUserInternal(this.this$0, p1);
		return v5;
	}
}
","SYS_OR_SIG"
"Lcom/android/server/blob/BlobStoreManagerService$Stub","queryBlobsForUser(I)Ljava/util/List;","1","4 = invokestatic < Application, Landroid/os/Binder, getCallingUid()I > @0 exception:3,
conditional branch(ne, to iindex=-1) 4,5,
conditional branch(ne, to iindex=-1) 2,9,
11 = invokestatic < Application, Landroid/app/ActivityManager, getCurrentUser()I > @11 exception:10,
12 = phi  2,11,
15 = load_metadata: <Application,Landroid/app/ActivityManagerInternal>, <Primordial,Ljava/lang/Class>,
17 = invokestatic < Application, Lcom/android/server/LocalServices, getService(Ljava/lang/Class;)Ljava/lang/Object; > 15 @17 exception:16,
2 = getstatic < Application, Lcom/android/server/LocalServices, sLocalServiceObjects, <Application,Landroid/util/ArrayMap> >,
monitorenter 2,
4 = invokevirtual < Application, Landroid/util/ArrayMap, get(Ljava/lang/Object;)Ljava/lang/Object; > 2,1 @3 exception:3,
monitorexit 2,
return 4,
18 = checkcast <Application,Landroid/app/ActivityManagerInternal>17 <Application,Landroid/app/ActivityManagerInternal>,
invokevirtual < Application, Landroid/app/ActivityManagerInternal, ensureNotSpecialUser(I)V > 18,12 @23 exception:19,
20 = getfield < Application, Lcom/android/server/blob/BlobStoreManagerService$Stub, this$0, <Application,Lcom/android/server/blob/BlobStoreManagerService> > 1,
22 = invokestatic < Application, Lcom/android/server/blob/BlobStoreManagerService, -$$Nest$mqueryBlobsForUserInternal(Lcom/android/server/blob/BlobStoreManagerService;I)Ljava/util/List; > 20,12 @28 exception:21,
4 = invokevirtual < Application, Lcom/android/server/blob/BlobStoreManagerService, queryBlobsForUserInternal(I)Ljava/util/List; > 1,2 @0 exception:3,
return 4,
return 22,","depth : 0
-----
depth : 1
-----
depth : 1
-----
","public List queryBlobsForUser(int p1){
	if (p1 != -2) {
		int v2 = ActivityManager.getCurrentUser();
		Object v4 = this.sLocalServiceObjects.get(ActivityManagerInterna.class);
		Object v3 = v4;
		v3.ensureNotSpecialUser(p1);
		List v7 = this.this$0.queryBlobsForUserInternal(p1);
		List v6 = v7;
		return v6;
	}
}
","SYS_OR_SIG"
"Lcom/android/server/blob/BlobStoreManagerService$Stub","queryBlobsForUser(I)Ljava/util/List;","2","4 = invokestatic < Application, Landroid/os/Binder, getCallingUid()I > @0 exception:3,
conditional branch(ne, to iindex=-1) 4,5,
conditional branch(ne, to iindex=-1) 2,9,
11 = invokestatic < Application, Landroid/app/ActivityManager, getCurrentUser()I > @11 exception:10,
12 = phi  2,11,
15 = load_metadata: <Application,Landroid/app/ActivityManagerInternal>, <Primordial,Ljava/lang/Class>,
17 = invokestatic < Application, Lcom/android/server/LocalServices, getService(Ljava/lang/Class;)Ljava/lang/Object; > 15 @17 exception:16,
2 = getstatic < Application, Lcom/android/server/LocalServices, sLocalServiceObjects, <Application,Landroid/util/ArrayMap> >,
monitorenter 2,
4 = invokevirtual < Application, Landroid/util/ArrayMap, get(Ljava/lang/Object;)Ljava/lang/Object; > 2,1 @3 exception:3,
monitorexit 2,
return 4,
18 = checkcast <Application,Landroid/app/ActivityManagerInternal>17 <Application,Landroid/app/ActivityManagerInternal>,
invokevirtual < Application, Landroid/app/ActivityManagerInternal, ensureNotSpecialUser(I)V > 18,12 @23 exception:19,
20 = getfield < Application, Lcom/android/server/blob/BlobStoreManagerService$Stub, this$0, <Application,Lcom/android/server/blob/BlobStoreManagerService> > 1,
22 = invokestatic < Application, Lcom/android/server/blob/BlobStoreManagerService, -$$Nest$mqueryBlobsForUserInternal(Lcom/android/server/blob/BlobStoreManagerService;I)Ljava/util/List; > 20,12 @28 exception:21,
4 = invokevirtual < Application, Lcom/android/server/blob/BlobStoreManagerService, queryBlobsForUserInternal(I)Ljava/util/List; > 1,2 @0 exception:3,
3 = new <Application,Ljava/util/ArrayList>@0,
invokespecial < Application, Ljava/util/ArrayList, <init>()V > 3 @2 exception:4,
5 = getfield < Application, Lcom/android/server/blob/BlobStoreManagerService, mBlobsLock, <Application,Ljava/lang/Object> > 1,
monitorenter 5,
6 = new <Application,Landroid/util/ArrayMap>@8,
invokespecial < Application, Landroid/util/ArrayMap, <init>()V > 6 @10 exception:7,
8 = new <Application,Lcom/android/server/blob/BlobStoreManagerService$$ExternalSyntheticLambda9>@13,
invokespecial < Application, Lcom/android/server/blob/BlobStoreManagerService$$ExternalSyntheticLambda9, <init>(Lcom/android/server/blob/BlobStoreManagerService;Landroid/util/ArrayMap;I)V > 8,1,6,2 @15 exception:9,
10 = new <Application,Lcom/android/server/blob/BlobStoreManagerService$$ExternalSyntheticLambda10>@18,
invokespecial < Application, Lcom/android/server/blob/BlobStoreManagerService$$ExternalSyntheticLambda10, <init>(ILjava/util/function/Function;Ljava/util/ArrayList;)V > 10,2,8,3 @20 exception:11,
invokevirtual < Application, Lcom/android/server/blob/BlobStoreManagerService, forEachBlobLocked(Ljava/util/function/BiConsumer;)V > 1,10 @23 exception:12,
monitorexit 5,
return 3,
return 4,
return 22,","depth : 0
-----
depth : 1
-----
depth : 1
-----
depth : 2
-----
","public List queryBlobsForUser(int p1){
	if (p1 != -2) {
		int v2 = ActivityManager.getCurrentUser();
		Object v4 = this.sLocalServiceObjects.get(ActivityManagerInterna.class);
		Object v3 = v4;
		v3.ensureNotSpecialUser(p1);
		ArrayList v8 = new ArrayList();
		ArrayMap v10 = new ArrayMap();
		BlobStoreManagerService$$ExternalSyntheticLambda9 v12 = new BlobStoreManagerService$$ExternalSyntheticLambda9(BlobStoreManagerService,v10,p1);
		BlobStoreManagerService$$ExternalSyntheticLambda10 v14 = new BlobStoreManagerService$$ExternalSyntheticLambda10(p1,v12,v8);
		BlobStoreManagerService.forEachBlobLocked(v14);
		List v7 = v8;
		List v6 = v7;
		return v6;
	}
}
","SYS_OR_SIG"

"Lcom/android/server/blob/BlobStoreManagerService$Stub","abandonSession(JLjava/lang/String;)V","0","4 = conversion(F) 2,
5 = new <Application,Ljava/lang/StringBuilder>@1,
invokespecial < Application, Ljava/lang/StringBuilder, <init>()V > 5 @3 exception:6,
9 = invokevirtual < Application, Ljava/lang/StringBuilder, append(Ljava/lang/String;)Ljava/lang/StringBuilder; > 5,7 @9 exception:8,
11 = invokevirtual < Application, Ljava/lang/StringBuilder, append(J)Ljava/lang/StringBuilder; > 5,2 @12 exception:10,
13 = invokevirtual < Application, Ljava/lang/StringBuilder, toString()Ljava/lang/String; > 5 @15 exception:12,
15 = invokestatic < Application, Lcom/android/internal/util/Preconditions, checkArgumentPositive(FLjava/lang/String;)F > 4,13 @19 exception:14,
18 = invokestatic < Application, Ljava/util/Objects, requireNonNull(Ljava/lang/Object;Ljava/lang/String;)Ljava/lang/Object; > 3,16 @25 exception:17,
20 = invokestatic < Application, Landroid/os/Binder, getCallingUid()I > @28 exception:19,
21 = getfield < Application, Lcom/android/server/blob/BlobStoreManagerService$Stub, this$0, <Application,Lcom/android/server/blob/BlobStoreManagerService> > 1,
invokestatic < Application, Lcom/android/server/blob/BlobStoreManagerService, -$$Nest$mverifyCallingPackage(Lcom/android/server/blob/BlobStoreManagerService;ILjava/lang/String;)V > 21,20,3 @34 exception:22,
23 = getfield < Application, Lcom/android/server/blob/BlobStoreManagerService$Stub, this$0, <Application,Lcom/android/server/blob/BlobStoreManagerService> > 1,
invokestatic < Application, Lcom/android/server/blob/BlobStoreManagerService, -$$Nest$mabandonSessionInternal(Lcom/android/server/blob/BlobStoreManagerService;JILjava/lang/String;)V > 23,2,20,3 @39 exception:24,
return,","depth : 0
-----
","public void abandonSession(long p1, String p2){
	StringBuilder v1 = new StringBuilder();
	StringBuilder v3 = v1.append(""sessionId must be positive: "");
	StringBuilder v4 = v1.append(p1);
	String v5 = v1.toString();
	float v6 = Preconditions.checkArgumentPositive(p1, v5);
	Object v7 = Objects.requireNonNull(p2, ""packageName must not be null"");
	int v8 = Binder.getCallingUid();
	BlobStoreManagerService.-$$Nest$mverifyCallingPackage(this.this$0, v8, p2);
	BlobStoreManagerService.-$$Nest$mabandonSessionInternal(this.this$0, p1, v8, p2);
	return;
}
","SYS_OR_SIG"
"Lcom/android/server/blob/BlobStoreManagerService$Stub","abandonSession(JLjava/lang/String;)V","1","4 = conversion(F) 2,
5 = new <Application,Ljava/lang/StringBuilder>@1,
invokespecial < Application, Ljava/lang/StringBuilder, <init>()V > 5 @3 exception:6,
9 = invokevirtual < Application, Ljava/lang/StringBuilder, append(Ljava/lang/String;)Ljava/lang/StringBuilder; > 5,7 @9 exception:8,
11 = invokevirtual < Application, Ljava/lang/StringBuilder, append(J)Ljava/lang/StringBuilder; > 5,2 @12 exception:10,
13 = invokevirtual < Application, Ljava/lang/StringBuilder, toString()Ljava/lang/String; > 5 @15 exception:12,
15 = invokestatic < Application, Lcom/android/internal/util/Preconditions, checkArgumentPositive(FLjava/lang/String;)F > 4,13 @19 exception:14,
18 = invokestatic < Application, Ljava/util/Objects, requireNonNull(Ljava/lang/Object;Ljava/lang/String;)Ljava/lang/Object; > 3,16 @25 exception:17,
20 = invokestatic < Application, Landroid/os/Binder, getCallingUid()I > @28 exception:19,
21 = getfield < Application, Lcom/android/server/blob/BlobStoreManagerService$Stub, this$0, <Application,Lcom/android/server/blob/BlobStoreManagerService> > 1,
invokestatic < Application, Lcom/android/server/blob/BlobStoreManagerService, -$$Nest$mverifyCallingPackage(Lcom/android/server/blob/BlobStoreManagerService;ILjava/lang/String;)V > 21,20,3 @34 exception:22,
invokevirtual < Application, Lcom/android/server/blob/BlobStoreManagerService, verifyCallingPackage(ILjava/lang/String;)V > 1,2,3 @0 exception:4,
return,
23 = getfield < Application, Lcom/android/server/blob/BlobStoreManagerService$Stub, this$0, <Application,Lcom/android/server/blob/BlobStoreManagerService> > 1,
invokestatic < Application, Lcom/android/server/blob/BlobStoreManagerService, -$$Nest$mabandonSessionInternal(Lcom/android/server/blob/BlobStoreManagerService;JILjava/lang/String;)V > 23,2,20,3 @39 exception:24,
invokevirtual < Application, Lcom/android/server/blob/BlobStoreManagerService, abandonSessionInternal(JILjava/lang/String;)V > 1,2,3,4 @0 exception:5,
return,
return,","depth : 0
-----
depth : 1
-----
depth : 1
-----
","public void abandonSession(long p1, String p2){
	StringBuilder v1 = new StringBuilder();
	StringBuilder v3 = v1.append(""sessionId must be positive: "");
	StringBuilder v4 = v1.append(p1);
	String v5 = v1.toString();
	float v6 = Preconditions.checkArgumentPositive(p1, v5);
	Object v7 = Objects.requireNonNull(p2, ""packageName must not be null"");
	int v8 = Binder.getCallingUid();
	this.this$0.verifyCallingPackage(v8, p2);
	this.this$0.abandonSessionInternal(p1, v8, p2);
	return;
}
","SYS_OR_SIG"
"Lcom/android/server/blob/BlobStoreManagerService$Stub","abandonSession(JLjava/lang/String;)V","2","4 = conversion(F) 2,
5 = new <Application,Ljava/lang/StringBuilder>@1,
invokespecial < Application, Ljava/lang/StringBuilder, <init>()V > 5 @3 exception:6,
9 = invokevirtual < Application, Ljava/lang/StringBuilder, append(Ljava/lang/String;)Ljava/lang/StringBuilder; > 5,7 @9 exception:8,
11 = invokevirtual < Application, Ljava/lang/StringBuilder, append(J)Ljava/lang/StringBuilder; > 5,2 @12 exception:10,
13 = invokevirtual < Application, Ljava/lang/StringBuilder, toString()Ljava/lang/String; > 5 @15 exception:12,
15 = invokestatic < Application, Lcom/android/internal/util/Preconditions, checkArgumentPositive(FLjava/lang/String;)F > 4,13 @19 exception:14,
18 = invokestatic < Application, Ljava/util/Objects, requireNonNull(Ljava/lang/Object;Ljava/lang/String;)Ljava/lang/Object; > 3,16 @25 exception:17,
20 = invokestatic < Application, Landroid/os/Binder, getCallingUid()I > @28 exception:19,
21 = getfield < Application, Lcom/android/server/blob/BlobStoreManagerService$Stub, this$0, <Application,Lcom/android/server/blob/BlobStoreManagerService> > 1,
invokestatic < Application, Lcom/android/server/blob/BlobStoreManagerService, -$$Nest$mverifyCallingPackage(Lcom/android/server/blob/BlobStoreManagerService;ILjava/lang/String;)V > 21,20,3 @34 exception:22,
invokevirtual < Application, Lcom/android/server/blob/BlobStoreManagerService, verifyCallingPackage(ILjava/lang/String;)V > 1,2,3 @0 exception:4,
4 = getfield < Application, Lcom/android/server/blob/BlobStoreManagerService, mPackageManagerInternal, <Application,Landroid/content/pm/PackageManagerInternal> > 1,
6 = invokestatic < Application, Landroid/os/UserHandle, getUserId(I)I > 2 @2 exception:5,
9 = invokevirtual < Application, Landroid/content/pm/PackageManagerInternal, getPackageUid(Ljava/lang/String;JI)I > 4,3,7,6 @8 exception:8,
conditional branch(ne, to iindex=-1) 9,2,
return,
return,
23 = getfield < Application, Lcom/android/server/blob/BlobStoreManagerService$Stub, this$0, <Application,Lcom/android/server/blob/BlobStoreManagerService> > 1,
invokestatic < Application, Lcom/android/server/blob/BlobStoreManagerService, -$$Nest$mabandonSessionInternal(Lcom/android/server/blob/BlobStoreManagerService;JILjava/lang/String;)V > 23,2,20,3 @39 exception:24,
invokevirtual < Application, Lcom/android/server/blob/BlobStoreManagerService, abandonSessionInternal(JILjava/lang/String;)V > 1,2,3,4 @0 exception:5,
5 = getfield < Application, Lcom/android/server/blob/BlobStoreManagerService, mBlobsLock, <Application,Ljava/lang/Object> > 1,
monitorenter 5,
7 = invokevirtual < Application, Lcom/android/server/blob/BlobStoreManagerService, openSessionInternal(JILjava/lang/String;)Lcom/android/server/blob/BlobStoreSession; > 1,2,3,4 @3 exception:6,
invokevirtual < Application, Lcom/android/server/blob/BlobStoreSession, open()V > 7 @7 exception:8,
invokevirtual < Application, Lcom/android/server/blob/BlobStoreSession, abandon()V > 7 @10 exception:9,
10 = getstatic < Application, Lcom/android/server/blob/BlobStoreConfig, LOGV, <Primordial,Z> >,
conditional branch(eq, to iindex=-1) 10,11,
13 = new <Application,Ljava/lang/StringBuilder>@19,
invokespecial < Application, Ljava/lang/StringBuilder, <init>()V > 13 @21 exception:14,
17 = invokevirtual < Application, Ljava/lang/StringBuilder, append(Ljava/lang/String;)Ljava/lang/StringBuilder; > 13,15 @26 exception:16,
19 = invokevirtual < Application, Ljava/lang/StringBuilder, append(J)Ljava/lang/StringBuilder; > 13,2 @29 exception:18,
22 = invokevirtual < Application, Ljava/lang/StringBuilder, append(Ljava/lang/String;)Ljava/lang/StringBuilder; > 13,20 @34 exception:21,
24 = invokevirtual < Application, Ljava/lang/StringBuilder, append(I)Ljava/lang/StringBuilder; > 13,3 @37 exception:23,
27 = invokevirtual < Application, Ljava/lang/StringBuilder, append(Ljava/lang/String;)Ljava/lang/StringBuilder; > 13,25 @42 exception:26,
29 = invokevirtual < Application, Ljava/lang/StringBuilder, append(Ljava/lang/String;)Ljava/lang/StringBuilder; > 13,4 @45 exception:28,
31 = invokevirtual < Application, Ljava/lang/StringBuilder, toString()Ljava/lang/String; > 13 @48 exception:30,
33 = invokestatic < Application, Landroid/util/Slog, v(Ljava/lang/String;Ljava/lang/String;)I > 12,31 @52 exception:32,
invokevirtual < Application, Lcom/android/server/blob/BlobStoreManagerService, writeBlobSessionsAsync()V > 1 @55 exception:38,
monitorexit 5,
return,
return,
return,","depth : 0
-----
depth : 1
-----
depth : 2
-----
depth : 1
-----
depth : 2
-----
","public void abandonSession(long p1, String p2){
	StringBuilder v1 = new StringBuilder();
	StringBuilder v3 = v1.append(""sessionId must be positive: "");
	StringBuilder v4 = v1.append(p1);
	String v5 = v1.toString();
	float v6 = Preconditions.checkArgumentPositive(p1, v5);
	Object v7 = Objects.requireNonNull(p2, ""packageName must not be null"");
	int v8 = Binder.getCallingUid();
	BlobStoreSession v15 = BlobStoreManagerService.openSessionInternal(p1, v8, p2);
	v15.open();
	v15.abandon();
	if (BlobStoreConfig.LOGV == 0) {
		BlobStoreManagerService.writeBlobSessionsAsync();
		return;
	}
}
","SYS_OR_SIG"

"Lcom/android/server/blob/BlobStoreManagerService$Stub","releaseLease(Landroid/app/blob/BlobHandle;Ljava/lang/String;)V","0","6 = invokestatic < Application, Ljava/util/Objects, requireNonNull(Ljava/lang/Object;Ljava/lang/String;)Ljava/lang/Object; > 2,4 @2 exception:5,
invokevirtual < Application, Landroid/app/blob/BlobHandle, assertIsValid()V > 2 @5 exception:7,
10 = invokestatic < Application, Ljava/util/Objects, requireNonNull(Ljava/lang/Object;Ljava/lang/String;)Ljava/lang/Object; > 3,8 @11 exception:9,
12 = invokestatic < Application, Landroid/os/Binder, getCallingUid()I > @14 exception:11,
13 = getfield < Application, Lcom/android/server/blob/BlobStoreManagerService$Stub, this$0, <Application,Lcom/android/server/blob/BlobStoreManagerService> > 1,
invokestatic < Application, Lcom/android/server/blob/BlobStoreManagerService, -$$Nest$mverifyCallingPackage(Lcom/android/server/blob/BlobStoreManagerService;ILjava/lang/String;)V > 13,12,3 @20 exception:14,
15 = getfield < Application, Lcom/android/server/blob/BlobStoreManagerService$Stub, this$0, <Application,Lcom/android/server/blob/BlobStoreManagerService> > 1,
17 = invokestatic < Application, Lcom/android/server/blob/BlobStoreManagerService, -$$Nest$misAllowedBlobStoreAccess(Lcom/android/server/blob/BlobStoreManagerService;ILjava/lang/String;)Z > 15,12,3 @25 exception:16,
conditional branch(eq, to iindex=-1) 17,18,
35 = getfield < Application, Lcom/android/server/blob/BlobStoreManagerService$Stub, this$0, <Application,Lcom/android/server/blob/BlobStoreManagerService> > 1,
invokestatic < Application, Lcom/android/server/blob/BlobStoreManagerService, -$$Nest$mreleaseLeaseInternal(Lcom/android/server/blob/BlobStoreManagerService;Landroid/app/blob/BlobHandle;ILjava/lang/String;)V > 35,2,12,3 @33 exception:36,
return,","depth : 0
-----
","public void releaseLease(BlobHandle p1, String p2){
	Object v1 = Objects.requireNonNull(p1, ""blobHandle must not be null"");
	p1.assertIsValid();
	Object v3 = Objects.requireNonNull(p2, ""packageName must not be null"");
	int v4 = Binder.getCallingUid();
	BlobStoreManagerService.-$$Nest$mverifyCallingPackage(this.this$0, v4, p2);
	boolean v6 = BlobStoreManagerService.-$$Nest$misAllowedBlobStoreAccess(this.this$0, v4, p2);
	if (v6 == 0) {
		BlobStoreManagerService.-$$Nest$mreleaseLeaseInternal(this.this$0, p1, v4, p2);
		return;
	}
}
","SYS_OR_SIG"
"Lcom/android/server/blob/BlobStoreManagerService$Stub","releaseLease(Landroid/app/blob/BlobHandle;Ljava/lang/String;)V","1","6 = invokestatic < Application, Ljava/util/Objects, requireNonNull(Ljava/lang/Object;Ljava/lang/String;)Ljava/lang/Object; > 2,4 @2 exception:5,
invokevirtual < Application, Landroid/app/blob/BlobHandle, assertIsValid()V > 2 @5 exception:7,
2 = getstatic < Application, Landroid/app/blob/BlobHandle, SUPPORTED_ALGOS, <Application,[Ljava/lang/String> >,
3 = getfield < Application, Landroid/app/blob/BlobHandle, algorithm, <Application,Ljava/lang/String> > 1,
5 = invokestatic < Application, Lcom/android/internal/util/Preconditions, checkArgumentIsSupported([Ljava/lang/String;Ljava/lang/String;)Ljava/lang/String; > 2,3 @4 exception:4,
6 = getfield < Application, Landroid/app/blob/BlobHandle, digest, <Primordial,[B> > 1,
9 = invokestatic < Application, Lcom/android/internal/util/Preconditions, checkByteArrayNotEmpty([BLjava/lang/String;)[B > 6,7 @11 exception:8,
10 = getfield < Application, Landroid/app/blob/BlobHandle, label, <Application,Ljava/lang/CharSequence> > 1,
13 = invokestatic < Application, Lcom/android/internal/util/Preconditions, checkStringNotEmpty(Ljava/lang/CharSequence;Ljava/lang/Object;)Ljava/lang/CharSequence; > 10,11 @18 exception:12,
14 = getfield < Application, Landroid/app/blob/BlobHandle, label, <Application,Ljava/lang/CharSequence> > 1,
16 = invokeinterface < Application, Ljava/lang/CharSequence, length()I > 14 @23 exception:15,
conditional branch(gt, to iindex=-1) 16,19,
goto (from iindex= 17 to iindex = 2),
20 = phi  17,18,
invokestatic < Application, Lcom/android/internal/util/Preconditions, checkArgument(ZLjava/lang/Object;)V > 20,21 @38 exception:22,
23 = getfield < Application, Landroid/app/blob/BlobHandle, expiryTimeMillis, <Primordial,J> > 1,
26 = invokestatic < Application, Lcom/android/internal/util/Preconditions, checkArgumentNonnegative(JLjava/lang/String;)J > 23,24 @45 exception:25,
27 = getfield < Application, Landroid/app/blob/BlobHandle, tag, <Application,Ljava/lang/String> > 1,
30 = invokestatic < Application, Lcom/android/internal/util/Preconditions, checkStringNotEmpty(Ljava/lang/CharSequence;Ljava/lang/Object;)Ljava/lang/CharSequence; > 27,28 @53 exception:29,
31 = getfield < Application, Landroid/app/blob/BlobHandle, tag, <Application,Ljava/lang/String> > 1,
33 = invokevirtual < Application, Ljava/lang/String, length()I > 31 @58 exception:32,
conditional branch(gt, to iindex=-1) 33,34,
goto (from iindex= 32 to iindex = 2),
35 = phi  17,18,
invokestatic < Application, Lcom/android/internal/util/Preconditions, checkArgument(ZLjava/lang/Object;)V > 35,36 @71 exception:37,
return,
10 = invokestatic < Application, Ljava/util/Objects, requireNonNull(Ljava/lang/Object;Ljava/lang/String;)Ljava/lang/Object; > 3,8 @11 exception:9,
12 = invokestatic < Application, Landroid/os/Binder, getCallingUid()I > @14 exception:11,
13 = getfield < Application, Lcom/android/server/blob/BlobStoreManagerService$Stub, this$0, <Application,Lcom/android/server/blob/BlobStoreManagerService> > 1,
invokestatic < Application, Lcom/android/server/blob/BlobStoreManagerService, -$$Nest$mverifyCallingPackage(Lcom/android/server/blob/BlobStoreManagerService;ILjava/lang/String;)V > 13,12,3 @20 exception:14,
invokevirtual < Application, Lcom/android/server/blob/BlobStoreManagerService, verifyCallingPackage(ILjava/lang/String;)V > 1,2,3 @0 exception:4,
return,
15 = getfield < Application, Lcom/android/server/blob/BlobStoreManagerService$Stub, this$0, <Application,Lcom/android/server/blob/BlobStoreManagerService> > 1,
17 = invokestatic < Application, Lcom/android/server/blob/BlobStoreManagerService, -$$Nest$misAllowedBlobStoreAccess(Lcom/android/server/blob/BlobStoreManagerService;ILjava/lang/String;)Z > 15,12,3 @25 exception:16,
5 = invokevirtual < Application, Lcom/android/server/blob/BlobStoreManagerService, isAllowedBlobStoreAccess(ILjava/lang/String;)Z > 1,2,3 @0 exception:4,
return 5,
conditional branch(eq, to iindex=-1) 17,18,
35 = getfield < Application, Lcom/android/server/blob/BlobStoreManagerService$Stub, this$0, <Application,Lcom/android/server/blob/BlobStoreManagerService> > 1,
invokestatic < Application, Lcom/android/server/blob/BlobStoreManagerService, -$$Nest$mreleaseLeaseInternal(Lcom/android/server/blob/BlobStoreManagerService;Landroid/app/blob/BlobHandle;ILjava/lang/String;)V > 35,2,12,3 @33 exception:36,
invokevirtual < Application, Lcom/android/server/blob/BlobStoreManagerService, releaseLeaseInternal(Landroid/app/blob/BlobHandle;ILjava/lang/String;)V > 1,2,3,4 @0 exception:5,
return,
return,","depth : 0
-----
depth : 1
-----
depth : 1
-----
depth : 1
-----
depth : 1
-----
","public void releaseLease(BlobHandle p1, String p2){
	Object v1 = Objects.requireNonNull(p1, ""blobHandle must not be null"");
	String v3 = Preconditions.checkArgumentIsSupported(this.SUPPORTED_ALGOS, this.algorithm);
	byte[] v4 = Preconditions.checkByteArrayNotEmpty(this.digest, ""digest"");
	CharSequence v5 = Preconditions.checkStringNotEmpty(this.label, ""label must not be null"");
	int v6 = this.label.length();
	if (v6 > 100) {
		Preconditions.checkArgument(1, ""label too long"");
		long v8 = Preconditions.checkArgumentNonnegative(this.expiryTimeMillis, ""expiryTimeMillis must not be negative"");
		CharSequence v9 = Preconditions.checkStringNotEmpty(this.tag, ""tag must not be null"");
		int v10 = this.tag.length();
		if (v10 > 128) {
			Preconditions.checkArgument(1, ""tag too long"");
			Object v12 = Objects.requireNonNull(p2, ""packageName must not be null"");
			int v13 = Binder.getCallingUid();
			this.this$0.verifyCallingPackage(v13, p2);
			boolean v17 = this.this$0.isAllowedBlobStoreAccess(v13, p2);
			boolean v16 = v17;
			if (v16 == 0) {
				this.this$0.releaseLeaseInternal(p1, v13, p2);
				return;
			}
		}
	}
}
","SYS_OR_SIG"
"Lcom/android/server/blob/BlobStoreManagerService$Stub","releaseLease(Landroid/app/blob/BlobHandle;Ljava/lang/String;)V","2","6 = invokestatic < Application, Ljava/util/Objects, requireNonNull(Ljava/lang/Object;Ljava/lang/String;)Ljava/lang/Object; > 2,4 @2 exception:5,
invokevirtual < Application, Landroid/app/blob/BlobHandle, assertIsValid()V > 2 @5 exception:7,
2 = getstatic < Application, Landroid/app/blob/BlobHandle, SUPPORTED_ALGOS, <Application,[Ljava/lang/String> >,
3 = getfield < Application, Landroid/app/blob/BlobHandle, algorithm, <Application,Ljava/lang/String> > 1,
5 = invokestatic < Application, Lcom/android/internal/util/Preconditions, checkArgumentIsSupported([Ljava/lang/String;Ljava/lang/String;)Ljava/lang/String; > 2,3 @4 exception:4,
6 = getfield < Application, Landroid/app/blob/BlobHandle, digest, <Primordial,[B> > 1,
9 = invokestatic < Application, Lcom/android/internal/util/Preconditions, checkByteArrayNotEmpty([BLjava/lang/String;)[B > 6,7 @11 exception:8,
10 = getfield < Application, Landroid/app/blob/BlobHandle, label, <Application,Ljava/lang/CharSequence> > 1,
13 = invokestatic < Application, Lcom/android/internal/util/Preconditions, checkStringNotEmpty(Ljava/lang/CharSequence;Ljava/lang/Object;)Ljava/lang/CharSequence; > 10,11 @18 exception:12,
14 = getfield < Application, Landroid/app/blob/BlobHandle, label, <Application,Ljava/lang/CharSequence> > 1,
16 = invokeinterface < Application, Ljava/lang/CharSequence, length()I > 14 @23 exception:15,
conditional branch(gt, to iindex=-1) 16,19,
goto (from iindex= 17 to iindex = 2),
20 = phi  17,18,
invokestatic < Application, Lcom/android/internal/util/Preconditions, checkArgument(ZLjava/lang/Object;)V > 20,21 @38 exception:22,
23 = getfield < Application, Landroid/app/blob/BlobHandle, expiryTimeMillis, <Primordial,J> > 1,
26 = invokestatic < Application, Lcom/android/internal/util/Preconditions, checkArgumentNonnegative(JLjava/lang/String;)J > 23,24 @45 exception:25,
27 = getfield < Application, Landroid/app/blob/BlobHandle, tag, <Application,Ljava/lang/String> > 1,
30 = invokestatic < Application, Lcom/android/internal/util/Preconditions, checkStringNotEmpty(Ljava/lang/CharSequence;Ljava/lang/Object;)Ljava/lang/CharSequence; > 27,28 @53 exception:29,
31 = getfield < Application, Landroid/app/blob/BlobHandle, tag, <Application,Ljava/lang/String> > 1,
33 = invokevirtual < Application, Ljava/lang/String, length()I > 31 @58 exception:32,
conditional branch(gt, to iindex=-1) 33,34,
goto (from iindex= 32 to iindex = 2),
35 = phi  17,18,
invokestatic < Application, Lcom/android/internal/util/Preconditions, checkArgument(ZLjava/lang/Object;)V > 35,36 @71 exception:37,
return,
10 = invokestatic < Application, Ljava/util/Objects, requireNonNull(Ljava/lang/Object;Ljava/lang/String;)Ljava/lang/Object; > 3,8 @11 exception:9,
12 = invokestatic < Application, Landroid/os/Binder, getCallingUid()I > @14 exception:11,
13 = getfield < Application, Lcom/android/server/blob/BlobStoreManagerService$Stub, this$0, <Application,Lcom/android/server/blob/BlobStoreManagerService> > 1,
invokestatic < Application, Lcom/android/server/blob/BlobStoreManagerService, -$$Nest$mverifyCallingPackage(Lcom/android/server/blob/BlobStoreManagerService;ILjava/lang/String;)V > 13,12,3 @20 exception:14,
invokevirtual < Application, Lcom/android/server/blob/BlobStoreManagerService, verifyCallingPackage(ILjava/lang/String;)V > 1,2,3 @0 exception:4,
4 = getfield < Application, Lcom/android/server/blob/BlobStoreManagerService, mPackageManagerInternal, <Application,Landroid/content/pm/PackageManagerInternal> > 1,
6 = invokestatic < Application, Landroid/os/UserHandle, getUserId(I)I > 2 @2 exception:5,
9 = invokevirtual < Application, Landroid/content/pm/PackageManagerInternal, getPackageUid(Ljava/lang/String;JI)I > 4,3,7,6 @8 exception:8,
conditional branch(ne, to iindex=-1) 9,2,
return,
return,
15 = getfield < Application, Lcom/android/server/blob/BlobStoreManagerService$Stub, this$0, <Application,Lcom/android/server/blob/BlobStoreManagerService> > 1,
17 = invokestatic < Application, Lcom/android/server/blob/BlobStoreManagerService, -$$Nest$misAllowedBlobStoreAccess(Lcom/android/server/blob/BlobStoreManagerService;ILjava/lang/String;)Z > 15,12,3 @25 exception:16,
5 = invokevirtual < Application, Lcom/android/server/blob/BlobStoreManagerService, isAllowedBlobStoreAccess(ILjava/lang/String;)Z > 1,2,3 @0 exception:4,
5 = invokestatic < Application, Landroid/os/Process, isSdkSandboxUid(I)Z > 2 @0 exception:4,
conditional branch(ne, to iindex=-1) 5,6,
8 = invokestatic < Application, Landroid/os/Process, isIsolated(I)Z > 2 @6 exception:7,
conditional branch(ne, to iindex=-1) 8,6,
9 = getfield < Application, Lcom/android/server/blob/BlobStoreManagerService, mPackageManagerInternal, <Application,Landroid/content/pm/PackageManagerInternal> > 1,
11 = invokestatic < Application, Landroid/os/UserHandle, getUserId(I)I > 2 @14 exception:10,
13 = invokevirtual < Application, Landroid/content/pm/PackageManagerInternal, isInstantApp(Ljava/lang/String;I)Z > 9,3,11 @18 exception:12,
conditional branch(ne, to iindex=-1) 13,6,
goto (from iindex= 13 to iindex = 2),
21 = phi  19,6,
return 21,
return 5,
conditional branch(eq, to iindex=-1) 17,18,
35 = getfield < Application, Lcom/android/server/blob/BlobStoreManagerService$Stub, this$0, <Application,Lcom/android/server/blob/BlobStoreManagerService> > 1,
invokestatic < Application, Lcom/android/server/blob/BlobStoreManagerService, -$$Nest$mreleaseLeaseInternal(Lcom/android/server/blob/BlobStoreManagerService;Landroid/app/blob/BlobHandle;ILjava/lang/String;)V > 35,2,12,3 @33 exception:36,
invokevirtual < Application, Lcom/android/server/blob/BlobStoreManagerService, releaseLeaseInternal(Landroid/app/blob/BlobHandle;ILjava/lang/String;)V > 1,2,3,4 @0 exception:5,
5 = getfield < Application, Lcom/android/server/blob/BlobStoreManagerService, mBlobsLock, <Application,Ljava/lang/Object> > 1,
monitorenter 5,
6 = getfield < Application, Lcom/android/server/blob/BlobStoreManagerService, mBlobsMap, <Application,Landroid/util/ArrayMap> > 1,
8 = invokevirtual < Application, Landroid/util/ArrayMap, get(Ljava/lang/Object;)Ljava/lang/Object; > 6,2 @5 exception:7,
9 = checkcast <Application,Lcom/android/server/blob/BlobMetadata>8 <Application,Lcom/android/server/blob/BlobMetadata>,
conditional branch(eq, to iindex=-1) 9,10,
12 = invokevirtual < Application, Lcom/android/server/blob/BlobMetadata, isAccessAllowedForCaller(Ljava/lang/String;I)Z > 9,4,3 @13 exception:11,
conditional branch(eq, to iindex=-1) 12,10,
invokevirtual < Application, Lcom/android/server/blob/BlobMetadata, removeLeasee(Ljava/lang/String;I)V > 9,4,3 @19 exception:36,
37 = getstatic < Application, Lcom/android/server/blob/BlobStoreConfig, LOGV, <Primordial,Z> >,
conditional branch(eq, to iindex=-1) 37,10,
39 = new <Application,Ljava/lang/StringBuilder>@28,
invokespecial < Application, Ljava/lang/StringBuilder, <init>()V > 39 @30 exception:40,
43 = invokevirtual < Application, Ljava/lang/StringBuilder, append(Ljava/lang/String;)Ljava/lang/StringBuilder; > 39,41 @35 exception:42,
45 = invokevirtual < Application, Ljava/lang/StringBuilder, append(Ljava/lang/Object;)Ljava/lang/StringBuilder; > 39,2 @38 exception:44,
47 = invokevirtual < Application, Ljava/lang/StringBuilder, append(Ljava/lang/String;)Ljava/lang/StringBuilder; > 39,23 @43 exception:46,
49 = invokevirtual < Application, Ljava/lang/StringBuilder, append(I)Ljava/lang/StringBuilder; > 39,3 @46 exception:48,
51 = invokevirtual < Application, Ljava/lang/StringBuilder, append(Ljava/lang/String;)Ljava/lang/StringBuilder; > 39,28 @51 exception:50,
53 = invokevirtual < Application, Ljava/lang/StringBuilder, append(Ljava/lang/String;)Ljava/lang/StringBuilder; > 39,4 @54 exception:52,
55 = invokevirtual < Application, Ljava/lang/StringBuilder, toString()Ljava/lang/String; > 39 @57 exception:54,
57 = invokestatic < Application, Landroid/util/Slog, v(Ljava/lang/String;Ljava/lang/String;)I > 38,55 @61 exception:56,
63 = invokevirtual < Application, Lcom/android/server/blob/BlobMetadata, hasValidLeases()Z > 9 @64 exception:62,
conditional branch(ne, to iindex=-1) 63,10,
64 = getfield < Application, Lcom/android/server/blob/BlobStoreManagerService, mHandler, <Application,Landroid/os/Handler> > 1,
65 = new <Application,Lcom/android/server/blob/BlobStoreManagerService$$ExternalSyntheticLambda7>@72,
invokespecial < Application, Lcom/android/server/blob/BlobStoreManagerService$$ExternalSyntheticLambda7, <init>(Lcom/android/server/blob/BlobStoreManagerService;Landroid/app/blob/BlobHandle;Lcom/android/server/blob/BlobMetadata;)V > 65,1,2,9 @74 exception:66,
68 = invokestatic < Application, Lcom/android/server/blob/BlobStoreConfig, getDeletionOnLastLeaseDelayMs()J > @77 exception:67,
70 = invokevirtual < Application, Landroid/os/Handler, postDelayed(Ljava/lang/Runnable;J)Z > 64,65,68 @81 exception:69,
invokevirtual < Application, Lcom/android/server/blob/BlobStoreManagerService, writeBlobsInfoAsync()V > 1 @84 exception:77,
monitorexit 5,
return,
return,
return,","depth : 0
-----
depth : 1
-----
depth : 1
-----
depth : 2
-----
depth : 1
-----
depth : 2
-----
depth : 1
-----
depth : 2
-----
","public void releaseLease(BlobHandle p1, String p2){
	Object v1 = Objects.requireNonNull(p1, ""blobHandle must not be null"");
	String v3 = Preconditions.checkArgumentIsSupported(this.SUPPORTED_ALGOS, this.algorithm);
	byte[] v4 = Preconditions.checkByteArrayNotEmpty(this.digest, ""digest"");
	CharSequence v5 = Preconditions.checkStringNotEmpty(this.label, ""label must not be null"");
	int v6 = this.label.length();
	if (v6 > 100) {
		Preconditions.checkArgument(1, ""label too long"");
		long v8 = Preconditions.checkArgumentNonnegative(this.expiryTimeMillis, ""expiryTimeMillis must not be negative"");
		CharSequence v9 = Preconditions.checkStringNotEmpty(this.tag, ""tag must not be null"");
		int v10 = this.tag.length();
		if (v10 > 128) {
			Preconditions.checkArgument(1, ""tag too long"");
			Object v12 = Objects.requireNonNull(p2, ""packageName must not be null"");
			int v13 = Binder.getCallingUid();
			if (v21 != 0) {
				int v22 = UserHandle.getUserId(v13);
				boolean v23 = this.mPackageManagerInternal.isInstantApp(p2, v22);
				if (v23 != 0) {
					boolean v19 = 1;
					boolean v18 = v19;
					if (v18 == 0) {
						Object v26 = this.mBlobsMap.get(p1);
						if (v26 == 0) {
							boolean v27 = v26.isAccessAllowedForCaller(p2, v13);
							if (v27 == 0) {
								v26.removeLeasee(p2, v13);
								if (BlobStoreConfig.LOGV == 0) {
									boolean v39 = v26.hasValidLeases();
									if (v39 != 0) {
										BlobStoreManagerService$$ExternalSyntheticLambda7 v40 = new BlobStoreManagerService$$ExternalSyntheticLambda7(BlobStoreManagerService,p1,v26);
										long v42 = BlobStoreConfig.getDeletionOnLastLeaseDelayMs();
										boolean v43 = this.mHandler.postDelayed(v40, v42);
										BlobStoreManagerService.writeBlobsInfoAsync();
										return;
									}
								}
							}
						}
					}
				}
			}
		}
	}
}
","SYS_OR_SIG"

"Lcom/android/server/blob/BlobStoreManagerService$Stub","getLeasedBlobs(Ljava/lang/String;)Ljava/util/List;","0","5 = invokestatic < Application, Ljava/util/Objects, requireNonNull(Ljava/lang/Object;Ljava/lang/String;)Ljava/lang/Object; > 2,3 @3 exception:4,
7 = invokestatic < Application, Landroid/os/Binder, getCallingUid()I > @6 exception:6,
8 = getfield < Application, Lcom/android/server/blob/BlobStoreManagerService$Stub, this$0, <Application,Lcom/android/server/blob/BlobStoreManagerService> > 1,
invokestatic < Application, Lcom/android/server/blob/BlobStoreManagerService, -$$Nest$mverifyCallingPackage(Lcom/android/server/blob/BlobStoreManagerService;ILjava/lang/String;)V > 8,7,2 @12 exception:9,
10 = getfield < Application, Lcom/android/server/blob/BlobStoreManagerService$Stub, this$0, <Application,Lcom/android/server/blob/BlobStoreManagerService> > 1,
12 = invokestatic < Application, Lcom/android/server/blob/BlobStoreManagerService, -$$Nest$mgetLeasedBlobsInternal(Lcom/android/server/blob/BlobStoreManagerService;ILjava/lang/String;)Ljava/util/List; > 10,7,2 @17 exception:11,
return 12,","depth : 0
-----
","public List getLeasedBlobs(String p1){
	Object v1 = Objects.requireNonNull(p1, ""packageName must not be null"");
	int v2 = Binder.getCallingUid();
	BlobStoreManagerService.-$$Nest$mverifyCallingPackage(this.this$0, v2, p1);
	List v4 = BlobStoreManagerService.-$$Nest$mgetLeasedBlobsInternal(this.this$0, v2, p1);
	return v4;
}
","SYS_OR_SIG"
"Lcom/android/server/blob/BlobStoreManagerService$Stub","getLeasedBlobs(Ljava/lang/String;)Ljava/util/List;","1","5 = invokestatic < Application, Ljava/util/Objects, requireNonNull(Ljava/lang/Object;Ljava/lang/String;)Ljava/lang/Object; > 2,3 @3 exception:4,
7 = invokestatic < Application, Landroid/os/Binder, getCallingUid()I > @6 exception:6,
8 = getfield < Application, Lcom/android/server/blob/BlobStoreManagerService$Stub, this$0, <Application,Lcom/android/server/blob/BlobStoreManagerService> > 1,
invokestatic < Application, Lcom/android/server/blob/BlobStoreManagerService, -$$Nest$mverifyCallingPackage(Lcom/android/server/blob/BlobStoreManagerService;ILjava/lang/String;)V > 8,7,2 @12 exception:9,
invokevirtual < Application, Lcom/android/server/blob/BlobStoreManagerService, verifyCallingPackage(ILjava/lang/String;)V > 1,2,3 @0 exception:4,
return,
10 = getfield < Application, Lcom/android/server/blob/BlobStoreManagerService$Stub, this$0, <Application,Lcom/android/server/blob/BlobStoreManagerService> > 1,
12 = invokestatic < Application, Lcom/android/server/blob/BlobStoreManagerService, -$$Nest$mgetLeasedBlobsInternal(Lcom/android/server/blob/BlobStoreManagerService;ILjava/lang/String;)Ljava/util/List; > 10,7,2 @17 exception:11,
5 = invokevirtual < Application, Lcom/android/server/blob/BlobStoreManagerService, getLeasedBlobsInternal(ILjava/lang/String;)Ljava/util/List; > 1,2,3 @0 exception:4,
return 5,
return 12,","depth : 0
-----
depth : 1
-----
depth : 1
-----
","public List getLeasedBlobs(String p1){
	Object v1 = Objects.requireNonNull(p1, ""packageName must not be null"");
	int v2 = Binder.getCallingUid();
	this.this$0.verifyCallingPackage(v2, p1);
	List v6 = this.this$0.getLeasedBlobsInternal(v2, p1);
	List v5 = v6;
	return v5;
}
","SYS_OR_SIG"
"Lcom/android/server/blob/BlobStoreManagerService$Stub","getLeasedBlobs(Ljava/lang/String;)Ljava/util/List;","2","5 = invokestatic < Application, Ljava/util/Objects, requireNonNull(Ljava/lang/Object;Ljava/lang/String;)Ljava/lang/Object; > 2,3 @3 exception:4,
7 = invokestatic < Application, Landroid/os/Binder, getCallingUid()I > @6 exception:6,
8 = getfield < Application, Lcom/android/server/blob/BlobStoreManagerService$Stub, this$0, <Application,Lcom/android/server/blob/BlobStoreManagerService> > 1,
invokestatic < Application, Lcom/android/server/blob/BlobStoreManagerService, -$$Nest$mverifyCallingPackage(Lcom/android/server/blob/BlobStoreManagerService;ILjava/lang/String;)V > 8,7,2 @12 exception:9,
invokevirtual < Application, Lcom/android/server/blob/BlobStoreManagerService, verifyCallingPackage(ILjava/lang/String;)V > 1,2,3 @0 exception:4,
4 = getfield < Application, Lcom/android/server/blob/BlobStoreManagerService, mPackageManagerInternal, <Application,Landroid/content/pm/PackageManagerInternal> > 1,
6 = invokestatic < Application, Landroid/os/UserHandle, getUserId(I)I > 2 @2 exception:5,
9 = invokevirtual < Application, Landroid/content/pm/PackageManagerInternal, getPackageUid(Ljava/lang/String;JI)I > 4,3,7,6 @8 exception:8,
conditional branch(ne, to iindex=-1) 9,2,
return,
return,
10 = getfield < Application, Lcom/android/server/blob/BlobStoreManagerService$Stub, this$0, <Application,Lcom/android/server/blob/BlobStoreManagerService> > 1,
12 = invokestatic < Application, Lcom/android/server/blob/BlobStoreManagerService, -$$Nest$mgetLeasedBlobsInternal(Lcom/android/server/blob/BlobStoreManagerService;ILjava/lang/String;)Ljava/util/List; > 10,7,2 @17 exception:11,
5 = invokevirtual < Application, Lcom/android/server/blob/BlobStoreManagerService, getLeasedBlobsInternal(ILjava/lang/String;)Ljava/util/List; > 1,2,3 @0 exception:4,
4 = new <Application,Ljava/util/ArrayList>@0,
invokespecial < Application, Ljava/util/ArrayList, <init>()V > 4 @2 exception:5,
6 = getfield < Application, Lcom/android/server/blob/BlobStoreManagerService, mBlobsLock, <Application,Ljava/lang/Object> > 1,
monitorenter 6,
7 = new <Application,Lcom/android/server/blob/BlobStoreManagerService$$ExternalSyntheticLambda13>@8,
invokespecial < Application, Lcom/android/server/blob/BlobStoreManagerService$$ExternalSyntheticLambda13, <init>(Ljava/lang/String;ILjava/util/ArrayList;)V > 7,3,2,4 @10 exception:8,
invokevirtual < Application, Lcom/android/server/blob/BlobStoreManagerService, forEachBlobLocked(Ljava/util/function/Consumer;)V > 1,7 @13 exception:9,
monitorexit 6,
return 4,
return 5,
return 12,","depth : 0
-----
depth : 1
-----
depth : 2
-----
depth : 1
-----
depth : 2
-----
","public List getLeasedBlobs(String p1){
	Object v1 = Objects.requireNonNull(p1, ""packageName must not be null"");
	int v2 = Binder.getCallingUid();
	ArrayList v9 = new ArrayList();
	BlobStoreManagerService$$ExternalSyntheticLambda13 v11 = new BlobStoreManagerService$$ExternalSyntheticLambda13(p1,v2,v9);
	BlobStoreManagerService.forEachBlobLocked(v11);
	List v8 = v9;
	List v7 = v8;
	return v7;
}
","SYS_OR_SIG"

"Lcom/android/server/blob/BlobStoreManagerService$Stub","createSession(Landroid/app/blob/BlobHandle;Ljava/lang/String;)J","0","6 = invokestatic < Application, Ljava/util/Objects, requireNonNull(Ljava/lang/Object;Ljava/lang/String;)Ljava/lang/Object; > 2,4 @2 exception:5,
invokevirtual < Application, Landroid/app/blob/BlobHandle, assertIsValid()V > 2 @5 exception:7,
10 = invokestatic < Application, Ljava/util/Objects, requireNonNull(Ljava/lang/Object;Ljava/lang/String;)Ljava/lang/Object; > 3,8 @11 exception:9,
12 = invokestatic < Application, Landroid/os/Binder, getCallingUid()I > @14 exception:11,
13 = getfield < Application, Lcom/android/server/blob/BlobStoreManagerService$Stub, this$0, <Application,Lcom/android/server/blob/BlobStoreManagerService> > 1,
invokestatic < Application, Lcom/android/server/blob/BlobStoreManagerService, -$$Nest$mverifyCallingPackage(Lcom/android/server/blob/BlobStoreManagerService;ILjava/lang/String;)V > 13,12,3 @20 exception:14,
15 = getfield < Application, Lcom/android/server/blob/BlobStoreManagerService$Stub, this$0, <Application,Lcom/android/server/blob/BlobStoreManagerService> > 1,
17 = invokestatic < Application, Lcom/android/server/blob/BlobStoreManagerService, -$$Nest$misAllowedBlobStoreAccess(Lcom/android/server/blob/BlobStoreManagerService;ILjava/lang/String;)Z > 15,12,3 @25 exception:16,
conditional branch(eq, to iindex=-1) 17,18,
35 = getfield < Application, Lcom/android/server/blob/BlobStoreManagerService$Stub, this$0, <Application,Lcom/android/server/blob/BlobStoreManagerService> > 1,
37 = invokestatic < Application, Lcom/android/server/blob/BlobStoreManagerService, -$$Nest$mcreateSessionInternal(Lcom/android/server/blob/BlobStoreManagerService;Landroid/app/blob/BlobHandle;ILjava/lang/String;)J > 35,2,12,3 @33 exception:36,
return 37,","depth : 0
-----
","public long createSession(BlobHandle p1, String p2){
	Object v1 = Objects.requireNonNull(p1, ""blobHandle must not be null"");
	p1.assertIsValid();
	Object v3 = Objects.requireNonNull(p2, ""packageName must not be null"");
	int v4 = Binder.getCallingUid();
	BlobStoreManagerService.-$$Nest$mverifyCallingPackage(this.this$0, v4, p2);
	boolean v6 = BlobStoreManagerService.-$$Nest$misAllowedBlobStoreAccess(this.this$0, v4, p2);
	if (v6 == 0) {
		long v7 = BlobStoreManagerService.-$$Nest$mcreateSessionInternal(this.this$0, p1, v4, p2);
		return v7;
	}
}
","SYS_OR_SIG"
"Lcom/android/server/blob/BlobStoreManagerService$Stub","createSession(Landroid/app/blob/BlobHandle;Ljava/lang/String;)J","1","6 = invokestatic < Application, Ljava/util/Objects, requireNonNull(Ljava/lang/Object;Ljava/lang/String;)Ljava/lang/Object; > 2,4 @2 exception:5,
invokevirtual < Application, Landroid/app/blob/BlobHandle, assertIsValid()V > 2 @5 exception:7,
2 = getstatic < Application, Landroid/app/blob/BlobHandle, SUPPORTED_ALGOS, <Application,[Ljava/lang/String> >,
3 = getfield < Application, Landroid/app/blob/BlobHandle, algorithm, <Application,Ljava/lang/String> > 1,
5 = invokestatic < Application, Lcom/android/internal/util/Preconditions, checkArgumentIsSupported([Ljava/lang/String;Ljava/lang/String;)Ljava/lang/String; > 2,3 @4 exception:4,
6 = getfield < Application, Landroid/app/blob/BlobHandle, digest, <Primordial,[B> > 1,
9 = invokestatic < Application, Lcom/android/internal/util/Preconditions, checkByteArrayNotEmpty([BLjava/lang/String;)[B > 6,7 @11 exception:8,
10 = getfield < Application, Landroid/app/blob/BlobHandle, label, <Application,Ljava/lang/CharSequence> > 1,
13 = invokestatic < Application, Lcom/android/internal/util/Preconditions, checkStringNotEmpty(Ljava/lang/CharSequence;Ljava/lang/Object;)Ljava/lang/CharSequence; > 10,11 @18 exception:12,
14 = getfield < Application, Landroid/app/blob/BlobHandle, label, <Application,Ljava/lang/CharSequence> > 1,
16 = invokeinterface < Application, Ljava/lang/CharSequence, length()I > 14 @23 exception:15,
conditional branch(gt, to iindex=-1) 16,19,
goto (from iindex= 17 to iindex = 2),
20 = phi  17,18,
invokestatic < Application, Lcom/android/internal/util/Preconditions, checkArgument(ZLjava/lang/Object;)V > 20,21 @38 exception:22,
23 = getfield < Application, Landroid/app/blob/BlobHandle, expiryTimeMillis, <Primordial,J> > 1,
26 = invokestatic < Application, Lcom/android/internal/util/Preconditions, checkArgumentNonnegative(JLjava/lang/String;)J > 23,24 @45 exception:25,
27 = getfield < Application, Landroid/app/blob/BlobHandle, tag, <Application,Ljava/lang/String> > 1,
30 = invokestatic < Application, Lcom/android/internal/util/Preconditions, checkStringNotEmpty(Ljava/lang/CharSequence;Ljava/lang/Object;)Ljava/lang/CharSequence; > 27,28 @53 exception:29,
31 = getfield < Application, Landroid/app/blob/BlobHandle, tag, <Application,Ljava/lang/String> > 1,
33 = invokevirtual < Application, Ljava/lang/String, length()I > 31 @58 exception:32,
conditional branch(gt, to iindex=-1) 33,34,
goto (from iindex= 32 to iindex = 2),
35 = phi  17,18,
invokestatic < Application, Lcom/android/internal/util/Preconditions, checkArgument(ZLjava/lang/Object;)V > 35,36 @71 exception:37,
return,
10 = invokestatic < Application, Ljava/util/Objects, requireNonNull(Ljava/lang/Object;Ljava/lang/String;)Ljava/lang/Object; > 3,8 @11 exception:9,
12 = invokestatic < Application, Landroid/os/Binder, getCallingUid()I > @14 exception:11,
13 = getfield < Application, Lcom/android/server/blob/BlobStoreManagerService$Stub, this$0, <Application,Lcom/android/server/blob/BlobStoreManagerService> > 1,
invokestatic < Application, Lcom/android/server/blob/BlobStoreManagerService, -$$Nest$mverifyCallingPackage(Lcom/android/server/blob/BlobStoreManagerService;ILjava/lang/String;)V > 13,12,3 @20 exception:14,
invokevirtual < Application, Lcom/android/server/blob/BlobStoreManagerService, verifyCallingPackage(ILjava/lang/String;)V > 1,2,3 @0 exception:4,
return,
15 = getfield < Application, Lcom/android/server/blob/BlobStoreManagerService$Stub, this$0, <Application,Lcom/android/server/blob/BlobStoreManagerService> > 1,
17 = invokestatic < Application, Lcom/android/server/blob/BlobStoreManagerService, -$$Nest$misAllowedBlobStoreAccess(Lcom/android/server/blob/BlobStoreManagerService;ILjava/lang/String;)Z > 15,12,3 @25 exception:16,
5 = invokevirtual < Application, Lcom/android/server/blob/BlobStoreManagerService, isAllowedBlobStoreAccess(ILjava/lang/String;)Z > 1,2,3 @0 exception:4,
return 5,
conditional branch(eq, to iindex=-1) 17,18,
35 = getfield < Application, Lcom/android/server/blob/BlobStoreManagerService$Stub, this$0, <Application,Lcom/android/server/blob/BlobStoreManagerService> > 1,
37 = invokestatic < Application, Lcom/android/server/blob/BlobStoreManagerService, -$$Nest$mcreateSessionInternal(Lcom/android/server/blob/BlobStoreManagerService;Landroid/app/blob/BlobHandle;ILjava/lang/String;)J > 35,2,12,3 @33 exception:36,
6 = invokevirtual < Application, Lcom/android/server/blob/BlobStoreManagerService, createSessionInternal(Landroid/app/blob/BlobHandle;ILjava/lang/String;)J > 1,2,3,4 @0 exception:5,
return 6,
return 37,","depth : 0
-----
depth : 1
-----
depth : 1
-----
depth : 1
-----
depth : 1
-----
","public long createSession(BlobHandle p1, String p2){
	Object v1 = Objects.requireNonNull(p1, ""blobHandle must not be null"");
	String v3 = Preconditions.checkArgumentIsSupported(this.SUPPORTED_ALGOS, this.algorithm);
	byte[] v4 = Preconditions.checkByteArrayNotEmpty(this.digest, ""digest"");
	CharSequence v5 = Preconditions.checkStringNotEmpty(this.label, ""label must not be null"");
	int v6 = this.label.length();
	if (v6 > 100) {
		Preconditions.checkArgument(1, ""label too long"");
		long v8 = Preconditions.checkArgumentNonnegative(this.expiryTimeMillis, ""expiryTimeMillis must not be negative"");
		CharSequence v9 = Preconditions.checkStringNotEmpty(this.tag, ""tag must not be null"");
		int v10 = this.tag.length();
		if (v10 > 128) {
			Preconditions.checkArgument(1, ""tag too long"");
			Object v12 = Objects.requireNonNull(p2, ""packageName must not be null"");
			int v13 = Binder.getCallingUid();
			this.this$0.verifyCallingPackage(v13, p2);
			boolean v17 = this.this$0.isAllowedBlobStoreAccess(v13, p2);
			boolean v16 = v17;
			if (v16 == 0) {
				long v19 = this.this$0.createSessionInternal(p1, v13, p2);
				long v18 = v19;
				return v18;
			}
		}
	}
}
","SYS_OR_SIG"
"Lcom/android/server/blob/BlobStoreManagerService$Stub","createSession(Landroid/app/blob/BlobHandle;Ljava/lang/String;)J","2","6 = invokestatic < Application, Ljava/util/Objects, requireNonNull(Ljava/lang/Object;Ljava/lang/String;)Ljava/lang/Object; > 2,4 @2 exception:5,
invokevirtual < Application, Landroid/app/blob/BlobHandle, assertIsValid()V > 2 @5 exception:7,
2 = getstatic < Application, Landroid/app/blob/BlobHandle, SUPPORTED_ALGOS, <Application,[Ljava/lang/String> >,
3 = getfield < Application, Landroid/app/blob/BlobHandle, algorithm, <Application,Ljava/lang/String> > 1,
5 = invokestatic < Application, Lcom/android/internal/util/Preconditions, checkArgumentIsSupported([Ljava/lang/String;Ljava/lang/String;)Ljava/lang/String; > 2,3 @4 exception:4,
6 = getfield < Application, Landroid/app/blob/BlobHandle, digest, <Primordial,[B> > 1,
9 = invokestatic < Application, Lcom/android/internal/util/Preconditions, checkByteArrayNotEmpty([BLjava/lang/String;)[B > 6,7 @11 exception:8,
10 = getfield < Application, Landroid/app/blob/BlobHandle, label, <Application,Ljava/lang/CharSequence> > 1,
13 = invokestatic < Application, Lcom/android/internal/util/Preconditions, checkStringNotEmpty(Ljava/lang/CharSequence;Ljava/lang/Object;)Ljava/lang/CharSequence; > 10,11 @18 exception:12,
14 = getfield < Application, Landroid/app/blob/BlobHandle, label, <Application,Ljava/lang/CharSequence> > 1,
16 = invokeinterface < Application, Ljava/lang/CharSequence, length()I > 14 @23 exception:15,
conditional branch(gt, to iindex=-1) 16,19,
goto (from iindex= 17 to iindex = 2),
20 = phi  17,18,
invokestatic < Application, Lcom/android/internal/util/Preconditions, checkArgument(ZLjava/lang/Object;)V > 20,21 @38 exception:22,
23 = getfield < Application, Landroid/app/blob/BlobHandle, expiryTimeMillis, <Primordial,J> > 1,
26 = invokestatic < Application, Lcom/android/internal/util/Preconditions, checkArgumentNonnegative(JLjava/lang/String;)J > 23,24 @45 exception:25,
27 = getfield < Application, Landroid/app/blob/BlobHandle, tag, <Application,Ljava/lang/String> > 1,
30 = invokestatic < Application, Lcom/android/internal/util/Preconditions, checkStringNotEmpty(Ljava/lang/CharSequence;Ljava/lang/Object;)Ljava/lang/CharSequence; > 27,28 @53 exception:29,
31 = getfield < Application, Landroid/app/blob/BlobHandle, tag, <Application,Ljava/lang/String> > 1,
33 = invokevirtual < Application, Ljava/lang/String, length()I > 31 @58 exception:32,
conditional branch(gt, to iindex=-1) 33,34,
goto (from iindex= 32 to iindex = 2),
35 = phi  17,18,
invokestatic < Application, Lcom/android/internal/util/Preconditions, checkArgument(ZLjava/lang/Object;)V > 35,36 @71 exception:37,
return,
10 = invokestatic < Application, Ljava/util/Objects, requireNonNull(Ljava/lang/Object;Ljava/lang/String;)Ljava/lang/Object; > 3,8 @11 exception:9,
12 = invokestatic < Application, Landroid/os/Binder, getCallingUid()I > @14 exception:11,
13 = getfield < Application, Lcom/android/server/blob/BlobStoreManagerService$Stub, this$0, <Application,Lcom/android/server/blob/BlobStoreManagerService> > 1,
invokestatic < Application, Lcom/android/server/blob/BlobStoreManagerService, -$$Nest$mverifyCallingPackage(Lcom/android/server/blob/BlobStoreManagerService;ILjava/lang/String;)V > 13,12,3 @20 exception:14,
invokevirtual < Application, Lcom/android/server/blob/BlobStoreManagerService, verifyCallingPackage(ILjava/lang/String;)V > 1,2,3 @0 exception:4,
4 = getfield < Application, Lcom/android/server/blob/BlobStoreManagerService, mPackageManagerInternal, <Application,Landroid/content/pm/PackageManagerInternal> > 1,
6 = invokestatic < Application, Landroid/os/UserHandle, getUserId(I)I > 2 @2 exception:5,
9 = invokevirtual < Application, Landroid/content/pm/PackageManagerInternal, getPackageUid(Ljava/lang/String;JI)I > 4,3,7,6 @8 exception:8,
conditional branch(ne, to iindex=-1) 9,2,
return,
return,
15 = getfield < Application, Lcom/android/server/blob/BlobStoreManagerService$Stub, this$0, <Application,Lcom/android/server/blob/BlobStoreManagerService> > 1,
17 = invokestatic < Application, Lcom/android/server/blob/BlobStoreManagerService, -$$Nest$misAllowedBlobStoreAccess(Lcom/android/server/blob/BlobStoreManagerService;ILjava/lang/String;)Z > 15,12,3 @25 exception:16,
5 = invokevirtual < Application, Lcom/android/server/blob/BlobStoreManagerService, isAllowedBlobStoreAccess(ILjava/lang/String;)Z > 1,2,3 @0 exception:4,
5 = invokestatic < Application, Landroid/os/Process, isSdkSandboxUid(I)Z > 2 @0 exception:4,
conditional branch(ne, to iindex=-1) 5,6,
8 = invokestatic < Application, Landroid/os/Process, isIsolated(I)Z > 2 @6 exception:7,
conditional branch(ne, to iindex=-1) 8,6,
9 = getfield < Application, Lcom/android/server/blob/BlobStoreManagerService, mPackageManagerInternal, <Application,Landroid/content/pm/PackageManagerInternal> > 1,
11 = invokestatic < Application, Landroid/os/UserHandle, getUserId(I)I > 2 @14 exception:10,
13 = invokevirtual < Application, Landroid/content/pm/PackageManagerInternal, isInstantApp(Ljava/lang/String;I)Z > 9,3,11 @18 exception:12,
conditional branch(ne, to iindex=-1) 13,6,
goto (from iindex= 13 to iindex = 2),
21 = phi  19,6,
return 21,
return 5,
conditional branch(eq, to iindex=-1) 17,18,
35 = getfield < Application, Lcom/android/server/blob/BlobStoreManagerService$Stub, this$0, <Application,Lcom/android/server/blob/BlobStoreManagerService> > 1,
37 = invokestatic < Application, Lcom/android/server/blob/BlobStoreManagerService, -$$Nest$mcreateSessionInternal(Lcom/android/server/blob/BlobStoreManagerService;Landroid/app/blob/BlobHandle;ILjava/lang/String;)J > 35,2,12,3 @33 exception:36,
6 = invokevirtual < Application, Lcom/android/server/blob/BlobStoreManagerService, createSessionInternal(Landroid/app/blob/BlobHandle;ILjava/lang/String;)J > 1,2,3,4 @0 exception:5,
5 = getfield < Application, Lcom/android/server/blob/BlobStoreManagerService, mBlobsLock, <Application,Ljava/lang/Object> > 1,
monitorenter 5,
7 = invokevirtual < Application, Lcom/android/server/blob/BlobStoreManagerService, getSessionsCountLocked(ILjava/lang/String;)I > 1,3,4 @3 exception:6,
9 = invokestatic < Application, Lcom/android/server/blob/BlobStoreConfig, getMaxActiveSessions()I > @7 exception:8,
conditional branch(ge, to iindex=-1) 7,9,
22 = invokevirtual < Application, Lcom/android/server/blob/BlobStoreManagerService, generateNextSessionIdLocked()J > 1 @13 exception:21,
23 = new <Application,Lcom/android/server/blob/BlobStoreSession>@17,
24 = getfield < Application, Lcom/android/server/blob/BlobStoreManagerService, mContext, <Application,Landroid/content/Context> > 1,
25 = getfield < Application, Lcom/android/server/blob/BlobStoreManagerService, mSessionStateChangeListener, <Application,Lcom/android/server/blob/BlobStoreManagerService$SessionStateChangeListener> > 1,
invokespecial < Application, Lcom/android/server/blob/BlobStoreSession, <init>(Landroid/content/Context;JLandroid/app/blob/BlobHandle;ILjava/lang/String;Lcom/android/server/blob/BlobStoreManagerService$SessionStateChangeListener;)V > 23,24,22,2,3,4,25 @28 exception:26,
28 = invokestatic < Application, Landroid/os/UserHandle, getUserId(I)I > 3 @31 exception:27,
invokevirtual < Application, Lcom/android/server/blob/BlobStoreManagerService, addSessionForUserLocked(Lcom/android/server/blob/BlobStoreSession;I)V > 1,23,28 @35 exception:29,
30 = getstatic < Application, Lcom/android/server/blob/BlobStoreConfig, LOGV, <Primordial,Z> >,
conditional branch(eq, to iindex=-1) 30,31,
33 = new <Application,Ljava/lang/StringBuilder>@44,
invokespecial < Application, Ljava/lang/StringBuilder, <init>()V > 33 @46 exception:34,
37 = invokevirtual < Application, Ljava/lang/StringBuilder, append(Ljava/lang/String;)Ljava/lang/StringBuilder; > 33,35 @51 exception:36,
39 = invokevirtual < Application, Ljava/lang/StringBuilder, append(Ljava/lang/Object;)Ljava/lang/StringBuilder; > 33,2 @54 exception:38,
42 = invokevirtual < Application, Ljava/lang/StringBuilder, append(Ljava/lang/String;)Ljava/lang/StringBuilder; > 33,40 @59 exception:41,
44 = invokevirtual < Application, Ljava/lang/StringBuilder, append(I)Ljava/lang/StringBuilder; > 33,3 @62 exception:43,
47 = invokevirtual < Application, Ljava/lang/StringBuilder, append(Ljava/lang/String;)Ljava/lang/StringBuilder; > 33,45 @67 exception:46,
49 = invokevirtual < Application, Ljava/lang/StringBuilder, append(Ljava/lang/String;)Ljava/lang/StringBuilder; > 33,4 @70 exception:48,
51 = invokevirtual < Application, Ljava/lang/StringBuilder, toString()Ljava/lang/String; > 33 @73 exception:50,
53 = invokestatic < Application, Landroid/util/Slog, v(Ljava/lang/String;Ljava/lang/String;)I > 32,51 @77 exception:52,
invokevirtual < Application, Lcom/android/server/blob/BlobStoreManagerService, writeBlobSessionsAsync()V > 1 @80 exception:60,
monitorexit 5,
return 22,
return 6,
return 37,","depth : 0
-----
depth : 1
-----
depth : 1
-----
depth : 2
-----
depth : 1
-----
depth : 2
-----
depth : 1
-----
depth : 2
-----
","public long createSession(BlobHandle p1, String p2){
	Object v1 = Objects.requireNonNull(p1, ""blobHandle must not be null"");
	String v3 = Preconditions.checkArgumentIsSupported(this.SUPPORTED_ALGOS, this.algorithm);
	byte[] v4 = Preconditions.checkByteArrayNotEmpty(this.digest, ""digest"");
	CharSequence v5 = Preconditions.checkStringNotEmpty(this.label, ""label must not be null"");
	int v6 = this.label.length();
	if (v6 > 100) {
		Preconditions.checkArgument(1, ""label too long"");
		long v8 = Preconditions.checkArgumentNonnegative(this.expiryTimeMillis, ""expiryTimeMillis must not be negative"");
		CharSequence v9 = Preconditions.checkStringNotEmpty(this.tag, ""tag must not be null"");
		int v10 = this.tag.length();
		if (v10 > 128) {
			Preconditions.checkArgument(1, ""tag too long"");
			Object v12 = Objects.requireNonNull(p2, ""packageName must not be null"");
			int v13 = Binder.getCallingUid();
			if (v21 != 0) {
				int v22 = UserHandle.getUserId(v13);
				boolean v23 = this.mPackageManagerInternal.isInstantApp(p2, v22);
				if (v23 != 0) {
					boolean v19 = 1;
					boolean v18 = v19;
					if (v18 == 0) {
						int v26 = BlobStoreManagerService.getSessionsCountLocked(v13, p2);
						int v27 = BlobStoreConfig.getMaxActiveSessions();
						if (v26 >= v27) {
							long v28 = BlobStoreManagerService.generateNextSessionIdLocked();
							BlobStoreSession v29 = new BlobStoreSession(this.mContext,v28,p1,v13,p2,this.mSessionStateChangeListener);
							int v31 = UserHandle.getUserId(v13);
							BlobStoreManagerService.addSessionForUserLocked(v29, v31);
							if (BlobStoreConfig.LOGV == 0) {
								BlobStoreManagerService.writeBlobSessionsAsync();
								long v25 = v28;
								long v24 = v25;
								return v24;
							}
						}
					}
				}
			}
		}
	}
}
","SYS_OR_SIG"

"Lcom/android/server/blob/BlobStoreManagerService$Stub","acquireLease(Landroid/app/blob/BlobHandle;ILjava/lang/CharSequence;JLjava/lang/String;)V","0","9 = invokestatic < Application, Ljava/util/Objects, requireNonNull(Ljava/lang/Object;Ljava/lang/String;)Ljava/lang/Object; > 2,7 @2 exception:8,
invokevirtual < Application, Landroid/app/blob/BlobHandle, assertIsValid()V > 2 @5 exception:10,
12 = invokestatic < Application, Landroid/content/res/ResourceId, isValid(I)Z > 3 @8 exception:11,
conditional branch(ne, to iindex=-1) 12,13,
conditional branch(eq, to iindex=-1) 4,13,
goto (from iindex= 7 to iindex = 3),
15 = phi  13,14,
16 = new <Application,Ljava/lang/StringBuilder>@20,
invokespecial < Application, Ljava/lang/StringBuilder, <init>()V > 16 @22 exception:17,
20 = invokevirtual < Application, Ljava/lang/StringBuilder, append(Ljava/lang/String;)Ljava/lang/StringBuilder; > 16,18 @27 exception:19,
22 = invokevirtual < Application, Ljava/lang/StringBuilder, append(I)Ljava/lang/StringBuilder; > 16,3 @30 exception:21,
25 = invokevirtual < Application, Ljava/lang/StringBuilder, append(Ljava/lang/String;)Ljava/lang/StringBuilder; > 16,23 @35 exception:24,
27 = invokevirtual < Application, Ljava/lang/StringBuilder, append(Ljava/lang/Object;)Ljava/lang/StringBuilder; > 16,4 @38 exception:26,
29 = invokevirtual < Application, Ljava/lang/StringBuilder, toString()Ljava/lang/String; > 16 @41 exception:28,
invokestatic < Application, Lcom/android/internal/util/Preconditions, checkArgument(ZLjava/lang/Object;)V > 15,29 @45 exception:30,
33 = invokestatic < Application, Lcom/android/internal/util/Preconditions, checkArgumentNonnegative(JLjava/lang/String;)J > 5,31 @50 exception:32,
36 = invokestatic < Application, Ljava/util/Objects, requireNonNull(Ljava/lang/Object;Ljava/lang/String;)Ljava/lang/Object; > 6,34 @56 exception:35,
38 = invokestatic < Application, Lcom/android/server/blob/BlobStoreConfig, getTruncatedLeaseDescription(Ljava/lang/CharSequence;)Ljava/lang/CharSequence; > 4 @59 exception:37,
40 = invokestatic < Application, Landroid/os/Binder, getCallingUid()I > @63 exception:39,
41 = getfield < Application, Lcom/android/server/blob/BlobStoreManagerService$Stub, this$0, <Application,Lcom/android/server/blob/BlobStoreManagerService> > 1,
invokestatic < Application, Lcom/android/server/blob/BlobStoreManagerService, -$$Nest$mverifyCallingPackage(Lcom/android/server/blob/BlobStoreManagerService;ILjava/lang/String;)V > 41,40,6 @69 exception:42,
43 = getfield < Application, Lcom/android/server/blob/BlobStoreManagerService$Stub, this$0, <Application,Lcom/android/server/blob/BlobStoreManagerService> > 1,
45 = invokestatic < Application, Lcom/android/server/blob/BlobStoreManagerService, -$$Nest$misAllowedBlobStoreAccess(Lcom/android/server/blob/BlobStoreManagerService;ILjava/lang/String;)Z > 43,40,6 @74 exception:44,
conditional branch(eq, to iindex=-1) 45,13,
62 = getfield < Application, Lcom/android/server/blob/BlobStoreManagerService$Stub, this$0, <Application,Lcom/android/server/blob/BlobStoreManagerService> > 1,
invokestatic < Application, Lcom/android/server/blob/BlobStoreManagerService, -$$Nest$macquireLeaseInternal(Lcom/android/server/blob/BlobStoreManagerService;Landroid/app/blob/BlobHandle;ILjava/lang/CharSequence;JILjava/lang/String;)V > 62,2,3,38,5,40,6 @86 exception:63,
return,","depth : 0
-----
","public void acquireLease(BlobHandle p1, int p2, CharSequence p3, long p4, String p5){
	Object v1 = Objects.requireNonNull(p1, ""blobHandle must not be null"");
	p1.assertIsValid();
	boolean v3 = ResourceId.isValid(p2);
	if (v3 != 0) {
		if (p3 == 0) {
			StringBuilder v4 = new StringBuilder();
			StringBuilder v6 = v4.append(""Description must be valid; descriptionId="");
			StringBuilder v7 = v4.append(p2);
			StringBuilder v8 = v4.append("", description="");
			StringBuilder v9 = v4.append(p3);
			String v10 = v4.toString();
			Preconditions.checkArgument(0, v10);
			long v12 = Preconditions.checkArgumentNonnegative(p4, ""leaseExpiryTimeMillis must not be negative"");
			Object v13 = Objects.requireNonNull(p5, ""packageName must not be null"");
			CharSequence v14 = BlobStoreConfig.getTruncatedLeaseDescription(p3);
			int v15 = Binder.getCallingUid();
			BlobStoreManagerService.-$$Nest$mverifyCallingPackage(this.this$0, v15, p5);
			boolean v17 = BlobStoreManagerService.-$$Nest$misAllowedBlobStoreAccess(this.this$0, v15, p5);
			if (v17 == 0) {
				BlobStoreManagerService.-$$Nest$macquireLeaseInternal(this.this$0, p1, p2, v14, p4, v15, p5);
				return;
			}
		}
	}
}
","SYS_OR_SIG"
"Lcom/android/server/blob/BlobStoreManagerService$Stub","acquireLease(Landroid/app/blob/BlobHandle;ILjava/lang/CharSequence;JLjava/lang/String;)V","1","9 = invokestatic < Application, Ljava/util/Objects, requireNonNull(Ljava/lang/Object;Ljava/lang/String;)Ljava/lang/Object; > 2,7 @2 exception:8,
invokevirtual < Application, Landroid/app/blob/BlobHandle, assertIsValid()V > 2 @5 exception:10,
2 = getstatic < Application, Landroid/app/blob/BlobHandle, SUPPORTED_ALGOS, <Application,[Ljava/lang/String> >,
3 = getfield < Application, Landroid/app/blob/BlobHandle, algorithm, <Application,Ljava/lang/String> > 1,
5 = invokestatic < Application, Lcom/android/internal/util/Preconditions, checkArgumentIsSupported([Ljava/lang/String;Ljava/lang/String;)Ljava/lang/String; > 2,3 @4 exception:4,
6 = getfield < Application, Landroid/app/blob/BlobHandle, digest, <Primordial,[B> > 1,
9 = invokestatic < Application, Lcom/android/internal/util/Preconditions, checkByteArrayNotEmpty([BLjava/lang/String;)[B > 6,7 @11 exception:8,
10 = getfield < Application, Landroid/app/blob/BlobHandle, label, <Application,Ljava/lang/CharSequence> > 1,
13 = invokestatic < Application, Lcom/android/internal/util/Preconditions, checkStringNotEmpty(Ljava/lang/CharSequence;Ljava/lang/Object;)Ljava/lang/CharSequence; > 10,11 @18 exception:12,
14 = getfield < Application, Landroid/app/blob/BlobHandle, label, <Application,Ljava/lang/CharSequence> > 1,
16 = invokeinterface < Application, Ljava/lang/CharSequence, length()I > 14 @23 exception:15,
conditional branch(gt, to iindex=-1) 16,19,
goto (from iindex= 17 to iindex = 2),
20 = phi  17,18,
invokestatic < Application, Lcom/android/internal/util/Preconditions, checkArgument(ZLjava/lang/Object;)V > 20,21 @38 exception:22,
23 = getfield < Application, Landroid/app/blob/BlobHandle, expiryTimeMillis, <Primordial,J> > 1,
26 = invokestatic < Application, Lcom/android/internal/util/Preconditions, checkArgumentNonnegative(JLjava/lang/String;)J > 23,24 @45 exception:25,
27 = getfield < Application, Landroid/app/blob/BlobHandle, tag, <Application,Ljava/lang/String> > 1,
30 = invokestatic < Application, Lcom/android/internal/util/Preconditions, checkStringNotEmpty(Ljava/lang/CharSequence;Ljava/lang/Object;)Ljava/lang/CharSequence; > 27,28 @53 exception:29,
31 = getfield < Application, Landroid/app/blob/BlobHandle, tag, <Application,Ljava/lang/String> > 1,
33 = invokevirtual < Application, Ljava/lang/String, length()I > 31 @58 exception:32,
conditional branch(gt, to iindex=-1) 33,34,
goto (from iindex= 32 to iindex = 2),
35 = phi  17,18,
invokestatic < Application, Lcom/android/internal/util/Preconditions, checkArgument(ZLjava/lang/Object;)V > 35,36 @71 exception:37,
return,
12 = invokestatic < Application, Landroid/content/res/ResourceId, isValid(I)Z > 3 @8 exception:11,
conditional branch(ne, to iindex=-1) 12,13,
conditional branch(eq, to iindex=-1) 4,13,
goto (from iindex= 7 to iindex = 3),
15 = phi  13,14,
16 = new <Application,Ljava/lang/StringBuilder>@20,
invokespecial < Application, Ljava/lang/StringBuilder, <init>()V > 16 @22 exception:17,
20 = invokevirtual < Application, Ljava/lang/StringBuilder, append(Ljava/lang/String;)Ljava/lang/StringBuilder; > 16,18 @27 exception:19,
22 = invokevirtual < Application, Ljava/lang/StringBuilder, append(I)Ljava/lang/StringBuilder; > 16,3 @30 exception:21,
25 = invokevirtual < Application, Ljava/lang/StringBuilder, append(Ljava/lang/String;)Ljava/lang/StringBuilder; > 16,23 @35 exception:24,
27 = invokevirtual < Application, Ljava/lang/StringBuilder, append(Ljava/lang/Object;)Ljava/lang/StringBuilder; > 16,4 @38 exception:26,
29 = invokevirtual < Application, Ljava/lang/StringBuilder, toString()Ljava/lang/String; > 16 @41 exception:28,
invokestatic < Application, Lcom/android/internal/util/Preconditions, checkArgument(ZLjava/lang/Object;)V > 15,29 @45 exception:30,
33 = invokestatic < Application, Lcom/android/internal/util/Preconditions, checkArgumentNonnegative(JLjava/lang/String;)J > 5,31 @50 exception:32,
36 = invokestatic < Application, Ljava/util/Objects, requireNonNull(Ljava/lang/Object;Ljava/lang/String;)Ljava/lang/Object; > 6,34 @56 exception:35,
38 = invokestatic < Application, Lcom/android/server/blob/BlobStoreConfig, getTruncatedLeaseDescription(Ljava/lang/CharSequence;)Ljava/lang/CharSequence; > 4 @59 exception:37,
3 = invokestatic < Application, Landroid/text/TextUtils, isEmpty(Ljava/lang/CharSequence;)Z > 1 @0 exception:2,
conditional branch(eq, to iindex=-1) 3,4,
5 = getstatic < Application, Lcom/android/server/blob/BlobStoreConfig$DeviceConfigProperties, LEASE_DESC_CHAR_LIMIT, <Primordial,I> >,
7 = invokestatic < Application, Landroid/text/TextUtils, trimToLengthWithEllipsis(Ljava/lang/CharSequence;I)Ljava/lang/CharSequence; > 1,5 @9 exception:6,
return 7,
40 = invokestatic < Application, Landroid/os/Binder, getCallingUid()I > @63 exception:39,
41 = getfield < Application, Lcom/android/server/blob/BlobStoreManagerService$Stub, this$0, <Application,Lcom/android/server/blob/BlobStoreManagerService> > 1,
invokestatic < Application, Lcom/android/server/blob/BlobStoreManagerService, -$$Nest$mverifyCallingPackage(Lcom/android/server/blob/BlobStoreManagerService;ILjava/lang/String;)V > 41,40,6 @69 exception:42,
invokevirtual < Application, Lcom/android/server/blob/BlobStoreManagerService, verifyCallingPackage(ILjava/lang/String;)V > 1,2,3 @0 exception:4,
return,
43 = getfield < Application, Lcom/android/server/blob/BlobStoreManagerService$Stub, this$0, <Application,Lcom/android/server/blob/BlobStoreManagerService> > 1,
45 = invokestatic < Application, Lcom/android/server/blob/BlobStoreManagerService, -$$Nest$misAllowedBlobStoreAccess(Lcom/android/server/blob/BlobStoreManagerService;ILjava/lang/String;)Z > 43,40,6 @74 exception:44,
5 = invokevirtual < Application, Lcom/android/server/blob/BlobStoreManagerService, isAllowedBlobStoreAccess(ILjava/lang/String;)Z > 1,2,3 @0 exception:4,
return 5,
conditional branch(eq, to iindex=-1) 45,13,
62 = getfield < Application, Lcom/android/server/blob/BlobStoreManagerService$Stub, this$0, <Application,Lcom/android/server/blob/BlobStoreManagerService> > 1,
invokestatic < Application, Lcom/android/server/blob/BlobStoreManagerService, -$$Nest$macquireLeaseInternal(Lcom/android/server/blob/BlobStoreManagerService;Landroid/app/blob/BlobHandle;ILjava/lang/CharSequence;JILjava/lang/String;)V > 62,2,3,38,5,40,6 @86 exception:63,
invokevirtual < Application, Lcom/android/server/blob/BlobStoreManagerService, acquireLeaseInternal(Landroid/app/blob/BlobHandle;ILjava/lang/CharSequence;JILjava/lang/String;)V > 1,2,3,4,5,6,7 @0 exception:8,
return,
return,","depth : 0
-----
depth : 1
-----
depth : 1
-----
depth : 1
-----
depth : 1
-----
depth : 1
-----
","public void acquireLease(BlobHandle p1, int p2, CharSequence p3, long p4, String p5){
	Object v1 = Objects.requireNonNull(p1, ""blobHandle must not be null"");
	String v3 = Preconditions.checkArgumentIsSupported(this.SUPPORTED_ALGOS, this.algorithm);
	byte[] v4 = Preconditions.checkByteArrayNotEmpty(this.digest, ""digest"");
	CharSequence v5 = Preconditions.checkStringNotEmpty(this.label, ""label must not be null"");
	int v6 = this.label.length();
	if (v6 > 100) {
		Preconditions.checkArgument(1, ""label too long"");
		long v8 = Preconditions.checkArgumentNonnegative(this.expiryTimeMillis, ""expiryTimeMillis must not be negative"");
		CharSequence v9 = Preconditions.checkStringNotEmpty(this.tag, ""tag must not be null"");
		int v10 = this.tag.length();
		if (v10 > 128) {
			Preconditions.checkArgument(1, ""tag too long"");
			boolean v12 = ResourceId.isValid(p2);
			if (v12 != 0) {
				if (p3 == 0) {
					StringBuilder v13 = new StringBuilder();
					StringBuilder v15 = v13.append(""Description must be valid; descriptionId="");
					StringBuilder v16 = v13.append(p2);
					StringBuilder v17 = v13.append("", description="");
					StringBuilder v18 = v13.append(p3);
					String v19 = v13.toString();
					Preconditions.checkArgument(0, v19);
					long v21 = Preconditions.checkArgumentNonnegative(p4, ""leaseExpiryTimeMillis must not be negative"");
					Object v22 = Objects.requireNonNull(p5, ""packageName must not be null"");
					boolean v24 = TextUtils.isEmpty(p3);
					if (v24 == 0) {
						CharSequence v25 = TextUtils.trimToLengthWithEllipsis(p3, BlobStoreConfig$DeviceConfigProperties.LEASE_DESC_CHAR_LIMIT);
						CharSequence v23 = v25;
						int v26 = Binder.getCallingUid();
						this.this$0.verifyCallingPackage(v26, p5);
						boolean v30 = this.this$0.isAllowedBlobStoreAccess(v26, p5);
						boolean v29 = v30;
						if (v29 == 0) {
							this.this$0.acquireLeaseInternal(p1, p2, v23, p4, v26, p5);
							return;
						}
					}
				}
			}
		}
	}
}
","SYS_OR_SIG"
"Lcom/android/server/blob/BlobStoreManagerService$Stub","acquireLease(Landroid/app/blob/BlobHandle;ILjava/lang/CharSequence;JLjava/lang/String;)V","1","9 = invokestatic < Application, Ljava/util/Objects, requireNonNull(Ljava/lang/Object;Ljava/lang/String;)Ljava/lang/Object; > 2,7 @2 exception:8,
invokevirtual < Application, Landroid/app/blob/BlobHandle, assertIsValid()V > 2 @5 exception:10,
2 = getstatic < Application, Landroid/app/blob/BlobHandle, SUPPORTED_ALGOS, <Application,[Ljava/lang/String> >,
3 = getfield < Application, Landroid/app/blob/BlobHandle, algorithm, <Application,Ljava/lang/String> > 1,
5 = invokestatic < Application, Lcom/android/internal/util/Preconditions, checkArgumentIsSupported([Ljava/lang/String;Ljava/lang/String;)Ljava/lang/String; > 2,3 @4 exception:4,
6 = getfield < Application, Landroid/app/blob/BlobHandle, digest, <Primordial,[B> > 1,
9 = invokestatic < Application, Lcom/android/internal/util/Preconditions, checkByteArrayNotEmpty([BLjava/lang/String;)[B > 6,7 @11 exception:8,
10 = getfield < Application, Landroid/app/blob/BlobHandle, label, <Application,Ljava/lang/CharSequence> > 1,
13 = invokestatic < Application, Lcom/android/internal/util/Preconditions, checkStringNotEmpty(Ljava/lang/CharSequence;Ljava/lang/Object;)Ljava/lang/CharSequence; > 10,11 @18 exception:12,
14 = getfield < Application, Landroid/app/blob/BlobHandle, label, <Application,Ljava/lang/CharSequence> > 1,
16 = invokeinterface < Application, Ljava/lang/CharSequence, length()I > 14 @23 exception:15,
conditional branch(gt, to iindex=-1) 16,19,
goto (from iindex= 17 to iindex = 2),
20 = phi  17,18,
invokestatic < Application, Lcom/android/internal/util/Preconditions, checkArgument(ZLjava/lang/Object;)V > 20,21 @38 exception:22,
23 = getfield < Application, Landroid/app/blob/BlobHandle, expiryTimeMillis, <Primordial,J> > 1,
26 = invokestatic < Application, Lcom/android/internal/util/Preconditions, checkArgumentNonnegative(JLjava/lang/String;)J > 23,24 @45 exception:25,
27 = getfield < Application, Landroid/app/blob/BlobHandle, tag, <Application,Ljava/lang/String> > 1,
30 = invokestatic < Application, Lcom/android/internal/util/Preconditions, checkStringNotEmpty(Ljava/lang/CharSequence;Ljava/lang/Object;)Ljava/lang/CharSequence; > 27,28 @53 exception:29,
31 = getfield < Application, Landroid/app/blob/BlobHandle, tag, <Application,Ljava/lang/String> > 1,
33 = invokevirtual < Application, Ljava/lang/String, length()I > 31 @58 exception:32,
conditional branch(gt, to iindex=-1) 33,34,
goto (from iindex= 32 to iindex = 2),
35 = phi  17,18,
invokestatic < Application, Lcom/android/internal/util/Preconditions, checkArgument(ZLjava/lang/Object;)V > 35,36 @71 exception:37,
return,
12 = invokestatic < Application, Landroid/content/res/ResourceId, isValid(I)Z > 3 @8 exception:11,
conditional branch(ne, to iindex=-1) 12,13,
conditional branch(eq, to iindex=-1) 4,13,
goto (from iindex= 9 to iindex = 2),
15 = phi  13,14,
16 = new <Application,Ljava/lang/StringBuilder>@20,
invokespecial < Application, Ljava/lang/StringBuilder, <init>()V > 16 @22 exception:17,
20 = invokevirtual < Application, Ljava/lang/StringBuilder, append(Ljava/lang/String;)Ljava/lang/StringBuilder; > 16,18 @27 exception:19,
22 = invokevirtual < Application, Ljava/lang/StringBuilder, append(I)Ljava/lang/StringBuilder; > 16,3 @30 exception:21,
25 = invokevirtual < Application, Ljava/lang/StringBuilder, append(Ljava/lang/String;)Ljava/lang/StringBuilder; > 16,23 @35 exception:24,
27 = invokevirtual < Application, Ljava/lang/StringBuilder, append(Ljava/lang/Object;)Ljava/lang/StringBuilder; > 16,4 @38 exception:26,
29 = invokevirtual < Application, Ljava/lang/StringBuilder, toString()Ljava/lang/String; > 16 @41 exception:28,
invokestatic < Application, Lcom/android/internal/util/Preconditions, checkArgument(ZLjava/lang/Object;)V > 15,29 @45 exception:30,
33 = invokestatic < Application, Lcom/android/internal/util/Preconditions, checkArgumentNonnegative(JLjava/lang/String;)J > 5,31 @50 exception:32,
36 = invokestatic < Application, Ljava/util/Objects, requireNonNull(Ljava/lang/Object;Ljava/lang/String;)Ljava/lang/Object; > 6,34 @56 exception:35,
38 = invokestatic < Application, Lcom/android/server/blob/BlobStoreConfig, getTruncatedLeaseDescription(Ljava/lang/CharSequence;)Ljava/lang/CharSequence; > 4 @59 exception:37,
3 = invokestatic < Application, Landroid/text/TextUtils, isEmpty(Ljava/lang/CharSequence;)Z > 1 @0 exception:2,
conditional branch(eq, to iindex=-1) 3,4,
5 = getstatic < Application, Lcom/android/server/blob/BlobStoreConfig$DeviceConfigProperties, LEASE_DESC_CHAR_LIMIT, <Primordial,I> >,
7 = invokestatic < Application, Landroid/text/TextUtils, trimToLengthWithEllipsis(Ljava/lang/CharSequence;I)Ljava/lang/CharSequence; > 1,5 @9 exception:6,
return 7,
40 = invokestatic < Application, Landroid/os/Binder, getCallingUid()I > @63 exception:39,
41 = getfield < Application, Lcom/android/server/blob/BlobStoreManagerService$Stub, this$0, <Application,Lcom/android/server/blob/BlobStoreManagerService> > 1,
invokestatic < Application, Lcom/android/server/blob/BlobStoreManagerService, -$$Nest$mverifyCallingPackage(Lcom/android/server/blob/BlobStoreManagerService;ILjava/lang/String;)V > 41,40,6 @69 exception:42,
invokevirtual < Application, Lcom/android/server/blob/BlobStoreManagerService, verifyCallingPackage(ILjava/lang/String;)V > 1,2,3 @0 exception:4,
return,
43 = getfield < Application, Lcom/android/server/blob/BlobStoreManagerService$Stub, this$0, <Application,Lcom/android/server/blob/BlobStoreManagerService> > 1,
45 = invokestatic < Application, Lcom/android/server/blob/BlobStoreManagerService, -$$Nest$misAllowedBlobStoreAccess(Lcom/android/server/blob/BlobStoreManagerService;ILjava/lang/String;)Z > 43,40,6 @74 exception:44,
5 = invokevirtual < Application, Lcom/android/server/blob/BlobStoreManagerService, isAllowedBlobStoreAccess(ILjava/lang/String;)Z > 1,2,3 @0 exception:4,
return 5,
conditional branch(eq, to iindex=-1) 45,13,
62 = getfield < Application, Lcom/android/server/blob/BlobStoreManagerService$Stub, this$0, <Application,Lcom/android/server/blob/BlobStoreManagerService> > 1,
invokestatic < Application, Lcom/android/server/blob/BlobStoreManagerService, -$$Nest$macquireLeaseInternal(Lcom/android/server/blob/BlobStoreManagerService;Landroid/app/blob/BlobHandle;ILjava/lang/CharSequence;JILjava/lang/String;)V > 62,2,3,38,5,40,6 @86 exception:63,
invokevirtual < Application, Lcom/android/server/blob/BlobStoreManagerService, acquireLeaseInternal(Landroid/app/blob/BlobHandle;ILjava/lang/CharSequence;JILjava/lang/String;)V > 1,2,3,4,5,6,7 @0 exception:8,
return,
return,","depth : 0
-----
depth : 1
-----
depth : 1
-----
depth : 1
-----
depth : 1
-----
depth : 1
-----
","public void acquireLease(BlobHandle p1, int p2, CharSequence p3, long p4, String p5){
	Object v1 = Objects.requireNonNull(p1, ""blobHandle must not be null"");
	String v3 = Preconditions.checkArgumentIsSupported(this.SUPPORTED_ALGOS, this.algorithm);
	byte[] v4 = Preconditions.checkByteArrayNotEmpty(this.digest, ""digest"");
	CharSequence v5 = Preconditions.checkStringNotEmpty(this.label, ""label must not be null"");
	int v6 = this.label.length();
	if (v6 > 100) {
		Preconditions.checkArgument(1, ""label too long"");
		long v8 = Preconditions.checkArgumentNonnegative(this.expiryTimeMillis, ""expiryTimeMillis must not be negative"");
		CharSequence v9 = Preconditions.checkStringNotEmpty(this.tag, ""tag must not be null"");
		int v10 = this.tag.length();
		if (v10 > 128) {
			Preconditions.checkArgument(1, ""tag too long"");
			boolean v12 = ResourceId.isValid(p2);
			if (v12 != 0) {
				if (p3 == 0) {
					StringBuilder v13 = new StringBuilder();
					StringBuilder v15 = v13.append(""Description must be valid; descriptionId="");
					StringBuilder v16 = v13.append(p2);
					StringBuilder v17 = v13.append("", description="");
					StringBuilder v18 = v13.append(p3);
					String v19 = v13.toString();
					Preconditions.checkArgument(0, v19);
					long v21 = Preconditions.checkArgumentNonnegative(p4, ""leaseExpiryTimeMillis must not be negative"");
					Object v22 = Objects.requireNonNull(p5, ""packageName must not be null"");
					boolean v24 = TextUtils.isEmpty(p3);
					if (v24 == 0) {
						CharSequence v25 = TextUtils.trimToLengthWithEllipsis(p3, BlobStoreConfig$DeviceConfigProperties.LEASE_DESC_CHAR_LIMIT);
						CharSequence v23 = v25;
						int v26 = Binder.getCallingUid();
						this.this$0.verifyCallingPackage(v26, p5);
						boolean v30 = this.this$0.isAllowedBlobStoreAccess(v26, p5);
						boolean v29 = v30;
						if (v29 == 0) {
							this.this$0.acquireLeaseInternal(p1, p2, v23, p4, v26, p5);
							return;
						}
					}
				}
			}
		}
	}
}
","SYS_OR_SIG"
"Lcom/android/server/blob/BlobStoreManagerService$Stub","acquireLease(Landroid/app/blob/BlobHandle;ILjava/lang/CharSequence;JLjava/lang/String;)V","2","9 = invokestatic < Application, Ljava/util/Objects, requireNonNull(Ljava/lang/Object;Ljava/lang/String;)Ljava/lang/Object; > 2,7 @2 exception:8,
invokevirtual < Application, Landroid/app/blob/BlobHandle, assertIsValid()V > 2 @5 exception:10,
2 = getstatic < Application, Landroid/app/blob/BlobHandle, SUPPORTED_ALGOS, <Application,[Ljava/lang/String> >,
3 = getfield < Application, Landroid/app/blob/BlobHandle, algorithm, <Application,Ljava/lang/String> > 1,
5 = invokestatic < Application, Lcom/android/internal/util/Preconditions, checkArgumentIsSupported([Ljava/lang/String;Ljava/lang/String;)Ljava/lang/String; > 2,3 @4 exception:4,
6 = getfield < Application, Landroid/app/blob/BlobHandle, digest, <Primordial,[B> > 1,
9 = invokestatic < Application, Lcom/android/internal/util/Preconditions, checkByteArrayNotEmpty([BLjava/lang/String;)[B > 6,7 @11 exception:8,
10 = getfield < Application, Landroid/app/blob/BlobHandle, label, <Application,Ljava/lang/CharSequence> > 1,
13 = invokestatic < Application, Lcom/android/internal/util/Preconditions, checkStringNotEmpty(Ljava/lang/CharSequence;Ljava/lang/Object;)Ljava/lang/CharSequence; > 10,11 @18 exception:12,
14 = getfield < Application, Landroid/app/blob/BlobHandle, label, <Application,Ljava/lang/CharSequence> > 1,
16 = invokeinterface < Application, Ljava/lang/CharSequence, length()I > 14 @23 exception:15,
conditional branch(gt, to iindex=-1) 16,19,
goto (from iindex= 17 to iindex = 2),
20 = phi  17,18,
invokestatic < Application, Lcom/android/internal/util/Preconditions, checkArgument(ZLjava/lang/Object;)V > 20,21 @38 exception:22,
23 = getfield < Application, Landroid/app/blob/BlobHandle, expiryTimeMillis, <Primordial,J> > 1,
26 = invokestatic < Application, Lcom/android/internal/util/Preconditions, checkArgumentNonnegative(JLjava/lang/String;)J > 23,24 @45 exception:25,
27 = getfield < Application, Landroid/app/blob/BlobHandle, tag, <Application,Ljava/lang/String> > 1,
30 = invokestatic < Application, Lcom/android/internal/util/Preconditions, checkStringNotEmpty(Ljava/lang/CharSequence;Ljava/lang/Object;)Ljava/lang/CharSequence; > 27,28 @53 exception:29,
31 = getfield < Application, Landroid/app/blob/BlobHandle, tag, <Application,Ljava/lang/String> > 1,
33 = invokevirtual < Application, Ljava/lang/String, length()I > 31 @58 exception:32,
conditional branch(gt, to iindex=-1) 33,34,
goto (from iindex= 32 to iindex = 2),
35 = phi  17,18,
invokestatic < Application, Lcom/android/internal/util/Preconditions, checkArgument(ZLjava/lang/Object;)V > 35,36 @71 exception:37,
return,
12 = invokestatic < Application, Landroid/content/res/ResourceId, isValid(I)Z > 3 @8 exception:11,
conditional branch(ne, to iindex=-1) 12,13,
conditional branch(eq, to iindex=-1) 4,13,
goto (from iindex= 7 to iindex = 3),
15 = phi  13,14,
16 = new <Application,Ljava/lang/StringBuilder>@20,
invokespecial < Application, Ljava/lang/StringBuilder, <init>()V > 16 @22 exception:17,
20 = invokevirtual < Application, Ljava/lang/StringBuilder, append(Ljava/lang/String;)Ljava/lang/StringBuilder; > 16,18 @27 exception:19,
22 = invokevirtual < Application, Ljava/lang/StringBuilder, append(I)Ljava/lang/StringBuilder; > 16,3 @30 exception:21,
25 = invokevirtual < Application, Ljava/lang/StringBuilder, append(Ljava/lang/String;)Ljava/lang/StringBuilder; > 16,23 @35 exception:24,
27 = invokevirtual < Application, Ljava/lang/StringBuilder, append(Ljava/lang/Object;)Ljava/lang/StringBuilder; > 16,4 @38 exception:26,
29 = invokevirtual < Application, Ljava/lang/StringBuilder, toString()Ljava/lang/String; > 16 @41 exception:28,
invokestatic < Application, Lcom/android/internal/util/Preconditions, checkArgument(ZLjava/lang/Object;)V > 15,29 @45 exception:30,
33 = invokestatic < Application, Lcom/android/internal/util/Preconditions, checkArgumentNonnegative(JLjava/lang/String;)J > 5,31 @50 exception:32,
36 = invokestatic < Application, Ljava/util/Objects, requireNonNull(Ljava/lang/Object;Ljava/lang/String;)Ljava/lang/Object; > 6,34 @56 exception:35,
38 = invokestatic < Application, Lcom/android/server/blob/BlobStoreConfig, getTruncatedLeaseDescription(Ljava/lang/CharSequence;)Ljava/lang/CharSequence; > 4 @59 exception:37,
3 = invokestatic < Application, Landroid/text/TextUtils, isEmpty(Ljava/lang/CharSequence;)Z > 1 @0 exception:2,
conditional branch(eq, to iindex=-1) 3,4,
5 = getstatic < Application, Lcom/android/server/blob/BlobStoreConfig$DeviceConfigProperties, LEASE_DESC_CHAR_LIMIT, <Primordial,I> >,
7 = invokestatic < Application, Landroid/text/TextUtils, trimToLengthWithEllipsis(Ljava/lang/CharSequence;I)Ljava/lang/CharSequence; > 1,5 @9 exception:6,
return 7,
40 = invokestatic < Application, Landroid/os/Binder, getCallingUid()I > @63 exception:39,
41 = getfield < Application, Lcom/android/server/blob/BlobStoreManagerService$Stub, this$0, <Application,Lcom/android/server/blob/BlobStoreManagerService> > 1,
invokestatic < Application, Lcom/android/server/blob/BlobStoreManagerService, -$$Nest$mverifyCallingPackage(Lcom/android/server/blob/BlobStoreManagerService;ILjava/lang/String;)V > 41,40,6 @69 exception:42,
invokevirtual < Application, Lcom/android/server/blob/BlobStoreManagerService, verifyCallingPackage(ILjava/lang/String;)V > 1,2,3 @0 exception:4,
4 = getfield < Application, Lcom/android/server/blob/BlobStoreManagerService, mPackageManagerInternal, <Application,Landroid/content/pm/PackageManagerInternal> > 1,
6 = invokestatic < Application, Landroid/os/UserHandle, getUserId(I)I > 2 @2 exception:5,
9 = invokevirtual < Application, Landroid/content/pm/PackageManagerInternal, getPackageUid(Ljava/lang/String;JI)I > 4,3,7,6 @8 exception:8,
conditional branch(ne, to iindex=-1) 9,2,
return,
return,
43 = getfield < Application, Lcom/android/server/blob/BlobStoreManagerService$Stub, this$0, <Application,Lcom/android/server/blob/BlobStoreManagerService> > 1,
45 = invokestatic < Application, Lcom/android/server/blob/BlobStoreManagerService, -$$Nest$misAllowedBlobStoreAccess(Lcom/android/server/blob/BlobStoreManagerService;ILjava/lang/String;)Z > 43,40,6 @74 exception:44,
5 = invokevirtual < Application, Lcom/android/server/blob/BlobStoreManagerService, isAllowedBlobStoreAccess(ILjava/lang/String;)Z > 1,2,3 @0 exception:4,
5 = invokestatic < Application, Landroid/os/Process, isSdkSandboxUid(I)Z > 2 @0 exception:4,
conditional branch(ne, to iindex=-1) 5,6,
8 = invokestatic < Application, Landroid/os/Process, isIsolated(I)Z > 2 @6 exception:7,
conditional branch(ne, to iindex=-1) 8,6,
9 = getfield < Application, Lcom/android/server/blob/BlobStoreManagerService, mPackageManagerInternal, <Application,Landroid/content/pm/PackageManagerInternal> > 1,
11 = invokestatic < Application, Landroid/os/UserHandle, getUserId(I)I > 2 @14 exception:10,
13 = invokevirtual < Application, Landroid/content/pm/PackageManagerInternal, isInstantApp(Ljava/lang/String;I)Z > 9,3,11 @18 exception:12,
conditional branch(ne, to iindex=-1) 13,6,
goto (from iindex= 13 to iindex = 2),
21 = phi  19,6,
return 21,
return 5,
conditional branch(eq, to iindex=-1) 45,13,
62 = getfield < Application, Lcom/android/server/blob/BlobStoreManagerService$Stub, this$0, <Application,Lcom/android/server/blob/BlobStoreManagerService> > 1,
invokestatic < Application, Lcom/android/server/blob/BlobStoreManagerService, -$$Nest$macquireLeaseInternal(Lcom/android/server/blob/BlobStoreManagerService;Landroid/app/blob/BlobHandle;ILjava/lang/CharSequence;JILjava/lang/String;)V > 62,2,3,38,5,40,6 @86 exception:63,
invokevirtual < Application, Lcom/android/server/blob/BlobStoreManagerService, acquireLeaseInternal(Landroid/app/blob/BlobHandle;ILjava/lang/CharSequence;JILjava/lang/String;)V > 1,2,3,4,5,6,7 @0 exception:8,
8 = getfield < Application, Lcom/android/server/blob/BlobStoreManagerService, mBlobsLock, <Application,Ljava/lang/Object> > 1,
monitorenter 8,
10 = invokevirtual < Application, Lcom/android/server/blob/BlobStoreManagerService, getLeasedBlobsCountLocked(ILjava/lang/String;)I > 1,6,7 @9 exception:9,
12 = invokestatic < Application, Lcom/android/server/blob/BlobStoreConfig, getMaxLeasedBlobs()I > @13 exception:11,
conditional branch(ge, to iindex=-1) 10,12,
28 = binaryop(lt) 5 , 14,
conditional branch(eq, to iindex=-1) 28,29,
30 = getfield < Application, Landroid/app/blob/BlobHandle, expiryTimeMillis, <Primordial,J> > 2,
31 = binaryop(lt) 30 , 14,
conditional branch(eq, to iindex=-1) 31,29,
32 = binaryop(lt) 5 , 30,
conditional branch(gt, to iindex=-1) 32,29,
goto (from iindex= 19 to iindex = 21),
40 = getfield < Application, Lcom/android/server/blob/BlobStoreManagerService, mBlobsMap, <Application,Landroid/util/ArrayMap> > 1,
42 = invokevirtual < Application, Landroid/util/ArrayMap, get(Ljava/lang/Object;)Ljava/lang/Object; > 40,2 @58 exception:41,
43 = checkcast <Application,Lcom/android/server/blob/BlobMetadata>42 <Application,Lcom/android/server/blob/BlobMetadata>,
conditional branch(eq, to iindex=-1) 43,29,
45 = invokevirtual < Application, Lcom/android/server/blob/BlobMetadata, isAccessAllowedForCaller(Ljava/lang/String;I)Z > 43,7,6 @67 exception:44,
conditional branch(ne, to iindex=-1) 45,29,
47 = invokevirtual < Application, Lcom/android/server/blob/BlobMetadata, getSize()J > 43 @74 exception:46,
49 = invokevirtual < Application, Lcom/android/server/blob/BlobStoreManagerService, getRemainingLeaseQuotaBytesInternal(ILjava/lang/String;)J > 1,6,7 @78 exception:48,
50 = binaryop(lt) 47 , 49,
conditional branch(gt, to iindex=-1) 50,29,
61 = invokevirtual < Application, Lcom/android/server/blob/BlobMetadata, getBlobId()J > 43 @88 exception:60,
63 = invokevirtual < Application, Lcom/android/server/blob/BlobMetadata, getSize()J > 43 @92 exception:62,
invokestatic < Application, Lcom/android/internal/util/FrameworkStatsLog, write(IIJJI)V > 13,6,61,63,64 @99 exception:65,
invokevirtual < Application, Lcom/android/server/blob/BlobMetadata, addOrReplaceLeasee(Ljava/lang/String;IILjava/lang/CharSequence;J)V > 43,7,6,3,4,5 @112 exception:66,
67 = getstatic < Application, Lcom/android/server/blob/BlobStoreConfig, LOGV, <Primordial,Z> >,
conditional branch(eq, to iindex=-1) 67,29,
69 = new <Application,Ljava/lang/StringBuilder>@121,
invokespecial < Application, Ljava/lang/StringBuilder, <init>()V > 69 @123 exception:70,
73 = invokevirtual < Application, Ljava/lang/StringBuilder, append(Ljava/lang/String;)Ljava/lang/StringBuilder; > 69,71 @128 exception:72,
75 = invokevirtual < Application, Ljava/lang/StringBuilder, append(Ljava/lang/Object;)Ljava/lang/StringBuilder; > 69,2 @131 exception:74,
78 = invokevirtual < Application, Ljava/lang/StringBuilder, append(Ljava/lang/String;)Ljava/lang/StringBuilder; > 69,76 @136 exception:77,
80 = invokevirtual < Application, Ljava/lang/StringBuilder, append(I)Ljava/lang/StringBuilder; > 69,6 @139 exception:79,
83 = invokevirtual < Application, Ljava/lang/StringBuilder, append(Ljava/lang/String;)Ljava/lang/StringBuilder; > 69,81 @144 exception:82,
85 = invokevirtual < Application, Ljava/lang/StringBuilder, append(Ljava/lang/String;)Ljava/lang/StringBuilder; > 69,7 @147 exception:84,
87 = invokevirtual < Application, Ljava/lang/StringBuilder, toString()Ljava/lang/String; > 69 @150 exception:86,
89 = invokestatic < Application, Landroid/util/Slog, v(Ljava/lang/String;Ljava/lang/String;)I > 68,87 @154 exception:88,
invokevirtual < Application, Lcom/android/server/blob/BlobStoreManagerService, writeBlobsInfoAsync()V > 1 @157 exception:96,
monitorexit 8,
return,
return,
return,","depth : 0
-----
depth : 1
-----
depth : 1
-----
depth : 1
-----
depth : 2
-----
depth : 1
-----
depth : 2
-----
depth : 1
-----
depth : 2
-----
","public void acquireLease(BlobHandle p1, int p2, CharSequence p3, long p4, String p5){
	Object v1 = Objects.requireNonNull(p1, ""blobHandle must not be null"");
	String v3 = Preconditions.checkArgumentIsSupported(this.SUPPORTED_ALGOS, this.algorithm);
	byte[] v4 = Preconditions.checkByteArrayNotEmpty(this.digest, ""digest"");
	CharSequence v5 = Preconditions.checkStringNotEmpty(this.label, ""label must not be null"");
	int v6 = this.label.length();
	if (v6 > 100) {
		Preconditions.checkArgument(1, ""label too long"");
		long v8 = Preconditions.checkArgumentNonnegative(this.expiryTimeMillis, ""expiryTimeMillis must not be negative"");
		CharSequence v9 = Preconditions.checkStringNotEmpty(this.tag, ""tag must not be null"");
		int v10 = this.tag.length();
		if (v10 > 128) {
			Preconditions.checkArgument(1, ""tag too long"");
			boolean v12 = ResourceId.isValid(p2);
			if (v12 != 0) {
				if (p3 == 0) {
					StringBuilder v13 = new StringBuilder();
					StringBuilder v15 = v13.append(""Description must be valid; descriptionId="");
					StringBuilder v16 = v13.append(p2);
					StringBuilder v17 = v13.append("", description="");
					StringBuilder v18 = v13.append(p3);
					String v19 = v13.toString();
					Preconditions.checkArgument(0, v19);
					long v21 = Preconditions.checkArgumentNonnegative(p4, ""leaseExpiryTimeMillis must not be negative"");
					Object v22 = Objects.requireNonNull(p5, ""packageName must not be null"");
					boolean v24 = TextUtils.isEmpty(p3);
					if (v24 == 0) {
						CharSequence v25 = TextUtils.trimToLengthWithEllipsis(p3, BlobStoreConfig$DeviceConfigProperties.LEASE_DESC_CHAR_LIMIT);
						CharSequence v23 = v25;
						int v26 = Binder.getCallingUid();
						if (v34 != 0) {
							int v35 = UserHandle.getUserId(v26);
							boolean v36 = this.mPackageManagerInternal.isInstantApp(p5, v35);
							if (v36 != 0) {
								boolean v32 = 1;
								boolean v31 = v32;
								if (v31 == 0) {
									int v39 = BlobStoreManagerService.getLeasedBlobsCountLocked(v26, p5);
									int v40 = BlobStoreConfig.getMaxLeasedBlobs();
									if (v39 >= v40) {
										if ((p4 < 0) == 0) {
											if ((BlobHandle.expiryTimeMillis < 0) == 0) {
												if ((p4 < BlobHandle.expiryTimeMillis) > 0) {
													Object v41 = this.mBlobsMap.get(p1);
													if (v41 == 0) {
														boolean v42 = v41.isAccessAllowedForCaller(p5, v26);
														if (v42 != 0) {
															long v43 = v41.getSize();
															long v44 = BlobStoreManagerService.getRemainingLeaseQuotaBytesInternal(v26, p5);
															if ((v43 < v44) > 0) {
																long v45 = v41.getBlobId();
																long v46 = v41.getSize();
																FrameworkStatsLog.write(299, v26, v45, v46, 1);
																v41.addOrReplaceLeasee(p5, v26, p2, v23, p4);
																if (BlobStoreConfig.LOGV == 0) {
																	BlobStoreManagerService.writeBlobsInfoAsync();
																	return;
																}
															}
														}
													}
												}
											}
										}
									}
								}
							}
						}
					}
				}
			}
		}
	}
}
","SYS_OR_SIG"
"Lcom/android/server/blob/BlobStoreManagerService$Stub","acquireLease(Landroid/app/blob/BlobHandle;ILjava/lang/CharSequence;JLjava/lang/String;)V","2","9 = invokestatic < Application, Ljava/util/Objects, requireNonNull(Ljava/lang/Object;Ljava/lang/String;)Ljava/lang/Object; > 2,7 @2 exception:8,
invokevirtual < Application, Landroid/app/blob/BlobHandle, assertIsValid()V > 2 @5 exception:10,
2 = getstatic < Application, Landroid/app/blob/BlobHandle, SUPPORTED_ALGOS, <Application,[Ljava/lang/String> >,
3 = getfield < Application, Landroid/app/blob/BlobHandle, algorithm, <Application,Ljava/lang/String> > 1,
5 = invokestatic < Application, Lcom/android/internal/util/Preconditions, checkArgumentIsSupported([Ljava/lang/String;Ljava/lang/String;)Ljava/lang/String; > 2,3 @4 exception:4,
6 = getfield < Application, Landroid/app/blob/BlobHandle, digest, <Primordial,[B> > 1,
9 = invokestatic < Application, Lcom/android/internal/util/Preconditions, checkByteArrayNotEmpty([BLjava/lang/String;)[B > 6,7 @11 exception:8,
10 = getfield < Application, Landroid/app/blob/BlobHandle, label, <Application,Ljava/lang/CharSequence> > 1,
13 = invokestatic < Application, Lcom/android/internal/util/Preconditions, checkStringNotEmpty(Ljava/lang/CharSequence;Ljava/lang/Object;)Ljava/lang/CharSequence; > 10,11 @18 exception:12,
14 = getfield < Application, Landroid/app/blob/BlobHandle, label, <Application,Ljava/lang/CharSequence> > 1,
16 = invokeinterface < Application, Ljava/lang/CharSequence, length()I > 14 @23 exception:15,
conditional branch(gt, to iindex=-1) 16,19,
goto (from iindex= 17 to iindex = 2),
20 = phi  17,18,
invokestatic < Application, Lcom/android/internal/util/Preconditions, checkArgument(ZLjava/lang/Object;)V > 20,21 @38 exception:22,
23 = getfield < Application, Landroid/app/blob/BlobHandle, expiryTimeMillis, <Primordial,J> > 1,
26 = invokestatic < Application, Lcom/android/internal/util/Preconditions, checkArgumentNonnegative(JLjava/lang/String;)J > 23,24 @45 exception:25,
27 = getfield < Application, Landroid/app/blob/BlobHandle, tag, <Application,Ljava/lang/String> > 1,
30 = invokestatic < Application, Lcom/android/internal/util/Preconditions, checkStringNotEmpty(Ljava/lang/CharSequence;Ljava/lang/Object;)Ljava/lang/CharSequence; > 27,28 @53 exception:29,
31 = getfield < Application, Landroid/app/blob/BlobHandle, tag, <Application,Ljava/lang/String> > 1,
33 = invokevirtual < Application, Ljava/lang/String, length()I > 31 @58 exception:32,
conditional branch(gt, to iindex=-1) 33,34,
goto (from iindex= 32 to iindex = 2),
35 = phi  17,18,
invokestatic < Application, Lcom/android/internal/util/Preconditions, checkArgument(ZLjava/lang/Object;)V > 35,36 @71 exception:37,
return,
12 = invokestatic < Application, Landroid/content/res/ResourceId, isValid(I)Z > 3 @8 exception:11,
conditional branch(ne, to iindex=-1) 12,13,
conditional branch(eq, to iindex=-1) 4,13,
goto (from iindex= 9 to iindex = 2),
15 = phi  13,14,
16 = new <Application,Ljava/lang/StringBuilder>@20,
invokespecial < Application, Ljava/lang/StringBuilder, <init>()V > 16 @22 exception:17,
20 = invokevirtual < Application, Ljava/lang/StringBuilder, append(Ljava/lang/String;)Ljava/lang/StringBuilder; > 16,18 @27 exception:19,
22 = invokevirtual < Application, Ljava/lang/StringBuilder, append(I)Ljava/lang/StringBuilder; > 16,3 @30 exception:21,
25 = invokevirtual < Application, Ljava/lang/StringBuilder, append(Ljava/lang/String;)Ljava/lang/StringBuilder; > 16,23 @35 exception:24,
27 = invokevirtual < Application, Ljava/lang/StringBuilder, append(Ljava/lang/Object;)Ljava/lang/StringBuilder; > 16,4 @38 exception:26,
29 = invokevirtual < Application, Ljava/lang/StringBuilder, toString()Ljava/lang/String; > 16 @41 exception:28,
invokestatic < Application, Lcom/android/internal/util/Preconditions, checkArgument(ZLjava/lang/Object;)V > 15,29 @45 exception:30,
33 = invokestatic < Application, Lcom/android/internal/util/Preconditions, checkArgumentNonnegative(JLjava/lang/String;)J > 5,31 @50 exception:32,
36 = invokestatic < Application, Ljava/util/Objects, requireNonNull(Ljava/lang/Object;Ljava/lang/String;)Ljava/lang/Object; > 6,34 @56 exception:35,
38 = invokestatic < Application, Lcom/android/server/blob/BlobStoreConfig, getTruncatedLeaseDescription(Ljava/lang/CharSequence;)Ljava/lang/CharSequence; > 4 @59 exception:37,
3 = invokestatic < Application, Landroid/text/TextUtils, isEmpty(Ljava/lang/CharSequence;)Z > 1 @0 exception:2,
conditional branch(eq, to iindex=-1) 3,4,
5 = getstatic < Application, Lcom/android/server/blob/BlobStoreConfig$DeviceConfigProperties, LEASE_DESC_CHAR_LIMIT, <Primordial,I> >,
7 = invokestatic < Application, Landroid/text/TextUtils, trimToLengthWithEllipsis(Ljava/lang/CharSequence;I)Ljava/lang/CharSequence; > 1,5 @9 exception:6,
return 7,
40 = invokestatic < Application, Landroid/os/Binder, getCallingUid()I > @63 exception:39,
41 = getfield < Application, Lcom/android/server/blob/BlobStoreManagerService$Stub, this$0, <Application,Lcom/android/server/blob/BlobStoreManagerService> > 1,
invokestatic < Application, Lcom/android/server/blob/BlobStoreManagerService, -$$Nest$mverifyCallingPackage(Lcom/android/server/blob/BlobStoreManagerService;ILjava/lang/String;)V > 41,40,6 @69 exception:42,
invokevirtual < Application, Lcom/android/server/blob/BlobStoreManagerService, verifyCallingPackage(ILjava/lang/String;)V > 1,2,3 @0 exception:4,
4 = getfield < Application, Lcom/android/server/blob/BlobStoreManagerService, mPackageManagerInternal, <Application,Landroid/content/pm/PackageManagerInternal> > 1,
6 = invokestatic < Application, Landroid/os/UserHandle, getUserId(I)I > 2 @2 exception:5,
9 = invokevirtual < Application, Landroid/content/pm/PackageManagerInternal, getPackageUid(Ljava/lang/String;JI)I > 4,3,7,6 @8 exception:8,
conditional branch(ne, to iindex=-1) 9,2,
return,
return,
43 = getfield < Application, Lcom/android/server/blob/BlobStoreManagerService$Stub, this$0, <Application,Lcom/android/server/blob/BlobStoreManagerService> > 1,
45 = invokestatic < Application, Lcom/android/server/blob/BlobStoreManagerService, -$$Nest$misAllowedBlobStoreAccess(Lcom/android/server/blob/BlobStoreManagerService;ILjava/lang/String;)Z > 43,40,6 @74 exception:44,
5 = invokevirtual < Application, Lcom/android/server/blob/BlobStoreManagerService, isAllowedBlobStoreAccess(ILjava/lang/String;)Z > 1,2,3 @0 exception:4,
5 = invokestatic < Application, Landroid/os/Process, isSdkSandboxUid(I)Z > 2 @0 exception:4,
conditional branch(ne, to iindex=-1) 5,6,
8 = invokestatic < Application, Landroid/os/Process, isIsolated(I)Z > 2 @6 exception:7,
conditional branch(ne, to iindex=-1) 8,6,
9 = getfield < Application, Lcom/android/server/blob/BlobStoreManagerService, mPackageManagerInternal, <Application,Landroid/content/pm/PackageManagerInternal> > 1,
11 = invokestatic < Application, Landroid/os/UserHandle, getUserId(I)I > 2 @14 exception:10,
13 = invokevirtual < Application, Landroid/content/pm/PackageManagerInternal, isInstantApp(Ljava/lang/String;I)Z > 9,3,11 @18 exception:12,
conditional branch(ne, to iindex=-1) 13,6,
goto (from iindex= 13 to iindex = 2),
21 = phi  19,6,
return 21,
return 5,
conditional branch(eq, to iindex=-1) 45,13,
62 = getfield < Application, Lcom/android/server/blob/BlobStoreManagerService$Stub, this$0, <Application,Lcom/android/server/blob/BlobStoreManagerService> > 1,
invokestatic < Application, Lcom/android/server/blob/BlobStoreManagerService, -$$Nest$macquireLeaseInternal(Lcom/android/server/blob/BlobStoreManagerService;Landroid/app/blob/BlobHandle;ILjava/lang/CharSequence;JILjava/lang/String;)V > 62,2,3,38,5,40,6 @86 exception:63,
invokevirtual < Application, Lcom/android/server/blob/BlobStoreManagerService, acquireLeaseInternal(Landroid/app/blob/BlobHandle;ILjava/lang/CharSequence;JILjava/lang/String;)V > 1,2,3,4,5,6,7 @0 exception:8,
8 = getfield < Application, Lcom/android/server/blob/BlobStoreManagerService, mBlobsLock, <Application,Ljava/lang/Object> > 1,
monitorenter 8,
10 = invokevirtual < Application, Lcom/android/server/blob/BlobStoreManagerService, getLeasedBlobsCountLocked(ILjava/lang/String;)I > 1,6,7 @9 exception:9,
12 = invokestatic < Application, Lcom/android/server/blob/BlobStoreConfig, getMaxLeasedBlobs()I > @13 exception:11,
conditional branch(ge, to iindex=-1) 10,12,
28 = binaryop(lt) 5 , 14,
conditional branch(eq, to iindex=-1) 28,29,
30 = getfield < Application, Landroid/app/blob/BlobHandle, expiryTimeMillis, <Primordial,J> > 2,
31 = binaryop(lt) 30 , 14,
conditional branch(eq, to iindex=-1) 31,29,
32 = binaryop(lt) 5 , 30,
conditional branch(gt, to iindex=-1) 32,29,
goto (from iindex= 19 to iindex = 21),
40 = getfield < Application, Lcom/android/server/blob/BlobStoreManagerService, mBlobsMap, <Application,Landroid/util/ArrayMap> > 1,
42 = invokevirtual < Application, Landroid/util/ArrayMap, get(Ljava/lang/Object;)Ljava/lang/Object; > 40,2 @58 exception:41,
43 = checkcast <Application,Lcom/android/server/blob/BlobMetadata>42 <Application,Lcom/android/server/blob/BlobMetadata>,
conditional branch(eq, to iindex=-1) 43,29,
45 = invokevirtual < Application, Lcom/android/server/blob/BlobMetadata, isAccessAllowedForCaller(Ljava/lang/String;I)Z > 43,7,6 @67 exception:44,
conditional branch(ne, to iindex=-1) 45,29,
47 = invokevirtual < Application, Lcom/android/server/blob/BlobMetadata, getSize()J > 43 @74 exception:46,
49 = invokevirtual < Application, Lcom/android/server/blob/BlobStoreManagerService, getRemainingLeaseQuotaBytesInternal(ILjava/lang/String;)J > 1,6,7 @78 exception:48,
50 = binaryop(lt) 47 , 49,
conditional branch(gt, to iindex=-1) 50,29,
61 = invokevirtual < Application, Lcom/android/server/blob/BlobMetadata, getBlobId()J > 43 @88 exception:60,
63 = invokevirtual < Application, Lcom/android/server/blob/BlobMetadata, getSize()J > 43 @92 exception:62,
invokestatic < Application, Lcom/android/internal/util/FrameworkStatsLog, write(IIJJI)V > 13,6,61,63,64 @99 exception:65,
invokevirtual < Application, Lcom/android/server/blob/BlobMetadata, addOrReplaceLeasee(Ljava/lang/String;IILjava/lang/CharSequence;J)V > 43,7,6,3,4,5 @112 exception:66,
67 = getstatic < Application, Lcom/android/server/blob/BlobStoreConfig, LOGV, <Primordial,Z> >,
conditional branch(eq, to iindex=-1) 67,29,
69 = new <Application,Ljava/lang/StringBuilder>@121,
invokespecial < Application, Ljava/lang/StringBuilder, <init>()V > 69 @123 exception:70,
73 = invokevirtual < Application, Ljava/lang/StringBuilder, append(Ljava/lang/String;)Ljava/lang/StringBuilder; > 69,71 @128 exception:72,
75 = invokevirtual < Application, Ljava/lang/StringBuilder, append(Ljava/lang/Object;)Ljava/lang/StringBuilder; > 69,2 @131 exception:74,
78 = invokevirtual < Application, Ljava/lang/StringBuilder, append(Ljava/lang/String;)Ljava/lang/StringBuilder; > 69,76 @136 exception:77,
80 = invokevirtual < Application, Ljava/lang/StringBuilder, append(I)Ljava/lang/StringBuilder; > 69,6 @139 exception:79,
83 = invokevirtual < Application, Ljava/lang/StringBuilder, append(Ljava/lang/String;)Ljava/lang/StringBuilder; > 69,81 @144 exception:82,
85 = invokevirtual < Application, Ljava/lang/StringBuilder, append(Ljava/lang/String;)Ljava/lang/StringBuilder; > 69,7 @147 exception:84,
87 = invokevirtual < Application, Ljava/lang/StringBuilder, toString()Ljava/lang/String; > 69 @150 exception:86,
89 = invokestatic < Application, Landroid/util/Slog, v(Ljava/lang/String;Ljava/lang/String;)I > 68,87 @154 exception:88,
invokevirtual < Application, Lcom/android/server/blob/BlobStoreManagerService, writeBlobsInfoAsync()V > 1 @157 exception:96,
monitorexit 8,
return,
return,
return,","depth : 0
-----
depth : 1
-----
depth : 1
-----
depth : 1
-----
depth : 2
-----
depth : 1
-----
depth : 2
-----
depth : 1
-----
depth : 2
-----
","public void acquireLease(BlobHandle p1, int p2, CharSequence p3, long p4, String p5){
	Object v1 = Objects.requireNonNull(p1, ""blobHandle must not be null"");
	String v3 = Preconditions.checkArgumentIsSupported(this.SUPPORTED_ALGOS, this.algorithm);
	byte[] v4 = Preconditions.checkByteArrayNotEmpty(this.digest, ""digest"");
	CharSequence v5 = Preconditions.checkStringNotEmpty(this.label, ""label must not be null"");
	int v6 = this.label.length();
	if (v6 > 100) {
		Preconditions.checkArgument(1, ""label too long"");
		long v8 = Preconditions.checkArgumentNonnegative(this.expiryTimeMillis, ""expiryTimeMillis must not be negative"");
		CharSequence v9 = Preconditions.checkStringNotEmpty(this.tag, ""tag must not be null"");
		int v10 = this.tag.length();
		if (v10 > 128) {
			Preconditions.checkArgument(1, ""tag too long"");
			boolean v12 = ResourceId.isValid(p2);
			if (v12 != 0) {
				if (p3 == 0) {
					StringBuilder v13 = new StringBuilder();
					StringBuilder v15 = v13.append(""Description must be valid; descriptionId="");
					StringBuilder v16 = v13.append(p2);
					StringBuilder v17 = v13.append("", description="");
					StringBuilder v18 = v13.append(p3);
					String v19 = v13.toString();
					Preconditions.checkArgument(0, v19);
					long v21 = Preconditions.checkArgumentNonnegative(p4, ""leaseExpiryTimeMillis must not be negative"");
					Object v22 = Objects.requireNonNull(p5, ""packageName must not be null"");
					boolean v24 = TextUtils.isEmpty(p3);
					if (v24 == 0) {
						CharSequence v25 = TextUtils.trimToLengthWithEllipsis(p3, BlobStoreConfig$DeviceConfigProperties.LEASE_DESC_CHAR_LIMIT);
						CharSequence v23 = v25;
						int v26 = Binder.getCallingUid();
						if (v34 != 0) {
							int v35 = UserHandle.getUserId(v26);
							boolean v36 = this.mPackageManagerInternal.isInstantApp(p5, v35);
							if (v36 != 0) {
								boolean v32 = 1;
								boolean v31 = v32;
								if (v31 == 0) {
									int v39 = BlobStoreManagerService.getLeasedBlobsCountLocked(v26, p5);
									int v40 = BlobStoreConfig.getMaxLeasedBlobs();
									if (v39 >= v40) {
										if ((p4 < 0) == 0) {
											if ((BlobHandle.expiryTimeMillis < 0) == 0) {
												if ((p4 < BlobHandle.expiryTimeMillis) > 0) {
													Object v41 = this.mBlobsMap.get(p1);
													if (v41 == 0) {
														boolean v42 = v41.isAccessAllowedForCaller(p5, v26);
														if (v42 != 0) {
															long v43 = v41.getSize();
															long v44 = BlobStoreManagerService.getRemainingLeaseQuotaBytesInternal(v26, p5);
															if ((v43 < v44) > 0) {
																long v45 = v41.getBlobId();
																long v46 = v41.getSize();
																FrameworkStatsLog.write(299, v26, v45, v46, 1);
																v41.addOrReplaceLeasee(p5, v26, p2, v23, p4);
																if (BlobStoreConfig.LOGV == 0) {
																	BlobStoreManagerService.writeBlobsInfoAsync();
																	return;
																}
															}
														}
													}
												}
											}
										}
									}
								}
							}
						}
					}
				}
			}
		}
	}
}
","SYS_OR_SIG"
"Lcom/android/server/blob/BlobStoreManagerService$Stub","acquireLease(Landroid/app/blob/BlobHandle;ILjava/lang/CharSequence;JLjava/lang/String;)V","2","9 = invokestatic < Application, Ljava/util/Objects, requireNonNull(Ljava/lang/Object;Ljava/lang/String;)Ljava/lang/Object; > 2,7 @2 exception:8,
invokevirtual < Application, Landroid/app/blob/BlobHandle, assertIsValid()V > 2 @5 exception:10,
2 = getstatic < Application, Landroid/app/blob/BlobHandle, SUPPORTED_ALGOS, <Application,[Ljava/lang/String> >,
3 = getfield < Application, Landroid/app/blob/BlobHandle, algorithm, <Application,Ljava/lang/String> > 1,
5 = invokestatic < Application, Lcom/android/internal/util/Preconditions, checkArgumentIsSupported([Ljava/lang/String;Ljava/lang/String;)Ljava/lang/String; > 2,3 @4 exception:4,
6 = getfield < Application, Landroid/app/blob/BlobHandle, digest, <Primordial,[B> > 1,
9 = invokestatic < Application, Lcom/android/internal/util/Preconditions, checkByteArrayNotEmpty([BLjava/lang/String;)[B > 6,7 @11 exception:8,
10 = getfield < Application, Landroid/app/blob/BlobHandle, label, <Application,Ljava/lang/CharSequence> > 1,
13 = invokestatic < Application, Lcom/android/internal/util/Preconditions, checkStringNotEmpty(Ljava/lang/CharSequence;Ljava/lang/Object;)Ljava/lang/CharSequence; > 10,11 @18 exception:12,
14 = getfield < Application, Landroid/app/blob/BlobHandle, label, <Application,Ljava/lang/CharSequence> > 1,
16 = invokeinterface < Application, Ljava/lang/CharSequence, length()I > 14 @23 exception:15,
conditional branch(gt, to iindex=-1) 16,19,
goto (from iindex= 17 to iindex = 2),
20 = phi  17,18,
invokestatic < Application, Lcom/android/internal/util/Preconditions, checkArgument(ZLjava/lang/Object;)V > 20,21 @38 exception:22,
23 = getfield < Application, Landroid/app/blob/BlobHandle, expiryTimeMillis, <Primordial,J> > 1,
26 = invokestatic < Application, Lcom/android/internal/util/Preconditions, checkArgumentNonnegative(JLjava/lang/String;)J > 23,24 @45 exception:25,
27 = getfield < Application, Landroid/app/blob/BlobHandle, tag, <Application,Ljava/lang/String> > 1,
30 = invokestatic < Application, Lcom/android/internal/util/Preconditions, checkStringNotEmpty(Ljava/lang/CharSequence;Ljava/lang/Object;)Ljava/lang/CharSequence; > 27,28 @53 exception:29,
31 = getfield < Application, Landroid/app/blob/BlobHandle, tag, <Application,Ljava/lang/String> > 1,
33 = invokevirtual < Application, Ljava/lang/String, length()I > 31 @58 exception:32,
conditional branch(gt, to iindex=-1) 33,34,
goto (from iindex= 32 to iindex = 2),
35 = phi  17,18,
invokestatic < Application, Lcom/android/internal/util/Preconditions, checkArgument(ZLjava/lang/Object;)V > 35,36 @71 exception:37,
return,
12 = invokestatic < Application, Landroid/content/res/ResourceId, isValid(I)Z > 3 @8 exception:11,
conditional branch(ne, to iindex=-1) 12,13,
conditional branch(eq, to iindex=-1) 4,13,
goto (from iindex= 7 to iindex = 3),
15 = phi  13,14,
16 = new <Application,Ljava/lang/StringBuilder>@20,
invokespecial < Application, Ljava/lang/StringBuilder, <init>()V > 16 @22 exception:17,
20 = invokevirtual < Application, Ljava/lang/StringBuilder, append(Ljava/lang/String;)Ljava/lang/StringBuilder; > 16,18 @27 exception:19,
22 = invokevirtual < Application, Ljava/lang/StringBuilder, append(I)Ljava/lang/StringBuilder; > 16,3 @30 exception:21,
25 = invokevirtual < Application, Ljava/lang/StringBuilder, append(Ljava/lang/String;)Ljava/lang/StringBuilder; > 16,23 @35 exception:24,
27 = invokevirtual < Application, Ljava/lang/StringBuilder, append(Ljava/lang/Object;)Ljava/lang/StringBuilder; > 16,4 @38 exception:26,
29 = invokevirtual < Application, Ljava/lang/StringBuilder, toString()Ljava/lang/String; > 16 @41 exception:28,
invokestatic < Application, Lcom/android/internal/util/Preconditions, checkArgument(ZLjava/lang/Object;)V > 15,29 @45 exception:30,
33 = invokestatic < Application, Lcom/android/internal/util/Preconditions, checkArgumentNonnegative(JLjava/lang/String;)J > 5,31 @50 exception:32,
36 = invokestatic < Application, Ljava/util/Objects, requireNonNull(Ljava/lang/Object;Ljava/lang/String;)Ljava/lang/Object; > 6,34 @56 exception:35,
38 = invokestatic < Application, Lcom/android/server/blob/BlobStoreConfig, getTruncatedLeaseDescription(Ljava/lang/CharSequence;)Ljava/lang/CharSequence; > 4 @59 exception:37,
3 = invokestatic < Application, Landroid/text/TextUtils, isEmpty(Ljava/lang/CharSequence;)Z > 1 @0 exception:2,
conditional branch(eq, to iindex=-1) 3,4,
return 1,
40 = invokestatic < Application, Landroid/os/Binder, getCallingUid()I > @63 exception:39,
41 = getfield < Application, Lcom/android/server/blob/BlobStoreManagerService$Stub, this$0, <Application,Lcom/android/server/blob/BlobStoreManagerService> > 1,
invokestatic < Application, Lcom/android/server/blob/BlobStoreManagerService, -$$Nest$mverifyCallingPackage(Lcom/android/server/blob/BlobStoreManagerService;ILjava/lang/String;)V > 41,40,6 @69 exception:42,
invokevirtual < Application, Lcom/android/server/blob/BlobStoreManagerService, verifyCallingPackage(ILjava/lang/String;)V > 1,2,3 @0 exception:4,
4 = getfield < Application, Lcom/android/server/blob/BlobStoreManagerService, mPackageManagerInternal, <Application,Landroid/content/pm/PackageManagerInternal> > 1,
6 = invokestatic < Application, Landroid/os/UserHandle, getUserId(I)I > 2 @2 exception:5,
9 = invokevirtual < Application, Landroid/content/pm/PackageManagerInternal, getPackageUid(Ljava/lang/String;JI)I > 4,3,7,6 @8 exception:8,
conditional branch(ne, to iindex=-1) 9,2,
return,
return,
43 = getfield < Application, Lcom/android/server/blob/BlobStoreManagerService$Stub, this$0, <Application,Lcom/android/server/blob/BlobStoreManagerService> > 1,
45 = invokestatic < Application, Lcom/android/server/blob/BlobStoreManagerService, -$$Nest$misAllowedBlobStoreAccess(Lcom/android/server/blob/BlobStoreManagerService;ILjava/lang/String;)Z > 43,40,6 @74 exception:44,
5 = invokevirtual < Application, Lcom/android/server/blob/BlobStoreManagerService, isAllowedBlobStoreAccess(ILjava/lang/String;)Z > 1,2,3 @0 exception:4,
5 = invokestatic < Application, Landroid/os/Process, isSdkSandboxUid(I)Z > 2 @0 exception:4,
conditional branch(ne, to iindex=-1) 5,6,
8 = invokestatic < Application, Landroid/os/Process, isIsolated(I)Z > 2 @6 exception:7,
conditional branch(ne, to iindex=-1) 8,6,
9 = getfield < Application, Lcom/android/server/blob/BlobStoreManagerService, mPackageManagerInternal, <Application,Landroid/content/pm/PackageManagerInternal> > 1,
11 = invokestatic < Application, Landroid/os/UserHandle, getUserId(I)I > 2 @14 exception:10,
13 = invokevirtual < Application, Landroid/content/pm/PackageManagerInternal, isInstantApp(Ljava/lang/String;I)Z > 9,3,11 @18 exception:12,
conditional branch(ne, to iindex=-1) 13,6,
goto (from iindex= 13 to iindex = 2),
21 = phi  19,6,
return 21,
return 5,
conditional branch(eq, to iindex=-1) 45,13,
62 = getfield < Application, Lcom/android/server/blob/BlobStoreManagerService$Stub, this$0, <Application,Lcom/android/server/blob/BlobStoreManagerService> > 1,
invokestatic < Application, Lcom/android/server/blob/BlobStoreManagerService, -$$Nest$macquireLeaseInternal(Lcom/android/server/blob/BlobStoreManagerService;Landroid/app/blob/BlobHandle;ILjava/lang/CharSequence;JILjava/lang/String;)V > 62,2,3,38,5,40,6 @86 exception:63,
invokevirtual < Application, Lcom/android/server/blob/BlobStoreManagerService, acquireLeaseInternal(Landroid/app/blob/BlobHandle;ILjava/lang/CharSequence;JILjava/lang/String;)V > 1,2,3,4,5,6,7 @0 exception:8,
8 = getfield < Application, Lcom/android/server/blob/BlobStoreManagerService, mBlobsLock, <Application,Ljava/lang/Object> > 1,
monitorenter 8,
10 = invokevirtual < Application, Lcom/android/server/blob/BlobStoreManagerService, getLeasedBlobsCountLocked(ILjava/lang/String;)I > 1,6,7 @9 exception:9,
12 = invokestatic < Application, Lcom/android/server/blob/BlobStoreConfig, getMaxLeasedBlobs()I > @13 exception:11,
conditional branch(ge, to iindex=-1) 10,12,
28 = binaryop(lt) 5 , 14,
conditional branch(eq, to iindex=-1) 28,29,
30 = getfield < Application, Landroid/app/blob/BlobHandle, expiryTimeMillis, <Primordial,J> > 2,
31 = binaryop(lt) 30 , 14,
conditional branch(eq, to iindex=-1) 31,29,
32 = binaryop(lt) 5 , 30,
conditional branch(gt, to iindex=-1) 32,29,
goto (from iindex= 19 to iindex = 21),
40 = getfield < Application, Lcom/android/server/blob/BlobStoreManagerService, mBlobsMap, <Application,Landroid/util/ArrayMap> > 1,
42 = invokevirtual < Application, Landroid/util/ArrayMap, get(Ljava/lang/Object;)Ljava/lang/Object; > 40,2 @58 exception:41,
43 = checkcast <Application,Lcom/android/server/blob/BlobMetadata>42 <Application,Lcom/android/server/blob/BlobMetadata>,
conditional branch(eq, to iindex=-1) 43,29,
45 = invokevirtual < Application, Lcom/android/server/blob/BlobMetadata, isAccessAllowedForCaller(Ljava/lang/String;I)Z > 43,7,6 @67 exception:44,
conditional branch(ne, to iindex=-1) 45,29,
47 = invokevirtual < Application, Lcom/android/server/blob/BlobMetadata, getSize()J > 43 @74 exception:46,
49 = invokevirtual < Application, Lcom/android/server/blob/BlobStoreManagerService, getRemainingLeaseQuotaBytesInternal(ILjava/lang/String;)J > 1,6,7 @78 exception:48,
50 = binaryop(lt) 47 , 49,
conditional branch(gt, to iindex=-1) 50,29,
61 = invokevirtual < Application, Lcom/android/server/blob/BlobMetadata, getBlobId()J > 43 @88 exception:60,
63 = invokevirtual < Application, Lcom/android/server/blob/BlobMetadata, getSize()J > 43 @92 exception:62,
invokestatic < Application, Lcom/android/internal/util/FrameworkStatsLog, write(IIJJI)V > 13,6,61,63,64 @99 exception:65,
invokevirtual < Application, Lcom/android/server/blob/BlobMetadata, addOrReplaceLeasee(Ljava/lang/String;IILjava/lang/CharSequence;J)V > 43,7,6,3,4,5 @112 exception:66,
67 = getstatic < Application, Lcom/android/server/blob/BlobStoreConfig, LOGV, <Primordial,Z> >,
conditional branch(eq, to iindex=-1) 67,29,
69 = new <Application,Ljava/lang/StringBuilder>@121,
invokespecial < Application, Ljava/lang/StringBuilder, <init>()V > 69 @123 exception:70,
73 = invokevirtual < Application, Ljava/lang/StringBuilder, append(Ljava/lang/String;)Ljava/lang/StringBuilder; > 69,71 @128 exception:72,
75 = invokevirtual < Application, Ljava/lang/StringBuilder, append(Ljava/lang/Object;)Ljava/lang/StringBuilder; > 69,2 @131 exception:74,
78 = invokevirtual < Application, Ljava/lang/StringBuilder, append(Ljava/lang/String;)Ljava/lang/StringBuilder; > 69,76 @136 exception:77,
80 = invokevirtual < Application, Ljava/lang/StringBuilder, append(I)Ljava/lang/StringBuilder; > 69,6 @139 exception:79,
83 = invokevirtual < Application, Ljava/lang/StringBuilder, append(Ljava/lang/String;)Ljava/lang/StringBuilder; > 69,81 @144 exception:82,
85 = invokevirtual < Application, Ljava/lang/StringBuilder, append(Ljava/lang/String;)Ljava/lang/StringBuilder; > 69,7 @147 exception:84,
87 = invokevirtual < Application, Ljava/lang/StringBuilder, toString()Ljava/lang/String; > 69 @150 exception:86,
89 = invokestatic < Application, Landroid/util/Slog, v(Ljava/lang/String;Ljava/lang/String;)I > 68,87 @154 exception:88,
invokevirtual < Application, Lcom/android/server/blob/BlobStoreManagerService, writeBlobsInfoAsync()V > 1 @157 exception:96,
monitorexit 8,
return,
return,
return,","depth : 0
-----
depth : 1
-----
depth : 1
-----
depth : 1
-----
depth : 2
-----
depth : 1
-----
depth : 2
-----
depth : 1
-----
depth : 2
-----
","public void acquireLease(BlobHandle p1, int p2, CharSequence p3, long p4, String p5){
	Object v1 = Objects.requireNonNull(p1, ""blobHandle must not be null"");
	String v3 = Preconditions.checkArgumentIsSupported(this.SUPPORTED_ALGOS, this.algorithm);
	byte[] v4 = Preconditions.checkByteArrayNotEmpty(this.digest, ""digest"");
	CharSequence v5 = Preconditions.checkStringNotEmpty(this.label, ""label must not be null"");
	int v6 = this.label.length();
	if (v6 > 100) {
		Preconditions.checkArgument(1, ""label too long"");
		long v8 = Preconditions.checkArgumentNonnegative(this.expiryTimeMillis, ""expiryTimeMillis must not be negative"");
		CharSequence v9 = Preconditions.checkStringNotEmpty(this.tag, ""tag must not be null"");
		int v10 = this.tag.length();
		if (v10 > 128) {
			Preconditions.checkArgument(1, ""tag too long"");
			boolean v12 = ResourceId.isValid(p2);
			if (v12 != 0) {
				if (p3 == 0) {
					StringBuilder v13 = new StringBuilder();
					StringBuilder v15 = v13.append(""Description must be valid; descriptionId="");
					StringBuilder v16 = v13.append(p2);
					StringBuilder v17 = v13.append("", description="");
					StringBuilder v18 = v13.append(p3);
					String v19 = v13.toString();
					Preconditions.checkArgument(0, v19);
					long v21 = Preconditions.checkArgumentNonnegative(p4, ""leaseExpiryTimeMillis must not be negative"");
					Object v22 = Objects.requireNonNull(p5, ""packageName must not be null"");
					boolean v24 = TextUtils.isEmpty(p3);
					if (v24 == 0) {
						CharSequence v23 = p3;
						int v25 = Binder.getCallingUid();
						if (v33 != 0) {
							int v34 = UserHandle.getUserId(v25);
							boolean v35 = this.mPackageManagerInternal.isInstantApp(p5, v34);
							if (v35 != 0) {
								boolean v31 = 1;
								boolean v30 = v31;
								if (v30 == 0) {
									int v38 = BlobStoreManagerService.getLeasedBlobsCountLocked(v25, p5);
									int v39 = BlobStoreConfig.getMaxLeasedBlobs();
									if (v38 >= v39) {
										if ((p4 < 0) == 0) {
											if ((BlobHandle.expiryTimeMillis < 0) == 0) {
												if ((p4 < BlobHandle.expiryTimeMillis) > 0) {
													Object v40 = this.mBlobsMap.get(p1);
													if (v40 == 0) {
														boolean v41 = v40.isAccessAllowedForCaller(p5, v25);
														if (v41 != 0) {
															long v42 = v40.getSize();
															long v43 = BlobStoreManagerService.getRemainingLeaseQuotaBytesInternal(v25, p5);
															if ((v42 < v43) > 0) {
																long v44 = v40.getBlobId();
																long v45 = v40.getSize();
																FrameworkStatsLog.write(299, v25, v44, v45, 1);
																v40.addOrReplaceLeasee(p5, v25, p2, v23, p4);
																if (BlobStoreConfig.LOGV == 0) {
																	BlobStoreManagerService.writeBlobsInfoAsync();
																	return;
																}
															}
														}
													}
												}
											}
										}
									}
								}
							}
						}
					}
				}
			}
		}
	}
}
","SYS_OR_SIG"

"Lcom/android/server/blob/BlobStoreManagerService$Stub","getRemainingLeaseQuotaBytes(Ljava/lang/String;)J","0","4 = invokestatic < Application, Landroid/os/Binder, getCallingUid()I > @0 exception:3,
5 = getfield < Application, Lcom/android/server/blob/BlobStoreManagerService$Stub, this$0, <Application,Lcom/android/server/blob/BlobStoreManagerService> > 1,
invokestatic < Application, Lcom/android/server/blob/BlobStoreManagerService, -$$Nest$mverifyCallingPackage(Lcom/android/server/blob/BlobStoreManagerService;ILjava/lang/String;)V > 5,4,2 @6 exception:6,
7 = getfield < Application, Lcom/android/server/blob/BlobStoreManagerService$Stub, this$0, <Application,Lcom/android/server/blob/BlobStoreManagerService> > 1,
9 = invokestatic < Application, Lcom/android/server/blob/BlobStoreManagerService, -$$Nest$mgetRemainingLeaseQuotaBytesInternal(Lcom/android/server/blob/BlobStoreManagerService;ILjava/lang/String;)J > 7,4,2 @11 exception:8,
return 9,","depth : 0
-----
","public long getRemainingLeaseQuotaBytes(String p1){
	int v1 = Binder.getCallingUid();
	BlobStoreManagerService.-$$Nest$mverifyCallingPackage(this.this$0, v1, p1);
	long v3 = BlobStoreManagerService.-$$Nest$mgetRemainingLeaseQuotaBytesInternal(this.this$0, v1, p1);
	return v3;
}
","SYS_OR_SIG"
"Lcom/android/server/blob/BlobStoreManagerService$Stub","getRemainingLeaseQuotaBytes(Ljava/lang/String;)J","1","4 = invokestatic < Application, Landroid/os/Binder, getCallingUid()I > @0 exception:3,
5 = getfield < Application, Lcom/android/server/blob/BlobStoreManagerService$Stub, this$0, <Application,Lcom/android/server/blob/BlobStoreManagerService> > 1,
invokestatic < Application, Lcom/android/server/blob/BlobStoreManagerService, -$$Nest$mverifyCallingPackage(Lcom/android/server/blob/BlobStoreManagerService;ILjava/lang/String;)V > 5,4,2 @6 exception:6,
invokevirtual < Application, Lcom/android/server/blob/BlobStoreManagerService, verifyCallingPackage(ILjava/lang/String;)V > 1,2,3 @0 exception:4,
return,
7 = getfield < Application, Lcom/android/server/blob/BlobStoreManagerService$Stub, this$0, <Application,Lcom/android/server/blob/BlobStoreManagerService> > 1,
9 = invokestatic < Application, Lcom/android/server/blob/BlobStoreManagerService, -$$Nest$mgetRemainingLeaseQuotaBytesInternal(Lcom/android/server/blob/BlobStoreManagerService;ILjava/lang/String;)J > 7,4,2 @11 exception:8,
5 = invokevirtual < Application, Lcom/android/server/blob/BlobStoreManagerService, getRemainingLeaseQuotaBytesInternal(ILjava/lang/String;)J > 1,2,3 @0 exception:4,
return 5,
return 9,","depth : 0
-----
depth : 1
-----
depth : 1
-----
","public long getRemainingLeaseQuotaBytes(String p1){
	int v1 = Binder.getCallingUid();
	this.this$0.verifyCallingPackage(v1, p1);
	long v5 = this.this$0.getRemainingLeaseQuotaBytesInternal(v1, p1);
	long v4 = v5;
	return v4;
}
","SYS_OR_SIG"
"Lcom/android/server/blob/BlobStoreManagerService$Stub","getRemainingLeaseQuotaBytes(Ljava/lang/String;)J","2","4 = invokestatic < Application, Landroid/os/Binder, getCallingUid()I > @0 exception:3,
5 = getfield < Application, Lcom/android/server/blob/BlobStoreManagerService$Stub, this$0, <Application,Lcom/android/server/blob/BlobStoreManagerService> > 1,
invokestatic < Application, Lcom/android/server/blob/BlobStoreManagerService, -$$Nest$mverifyCallingPackage(Lcom/android/server/blob/BlobStoreManagerService;ILjava/lang/String;)V > 5,4,2 @6 exception:6,
invokevirtual < Application, Lcom/android/server/blob/BlobStoreManagerService, verifyCallingPackage(ILjava/lang/String;)V > 1,2,3 @0 exception:4,
4 = getfield < Application, Lcom/android/server/blob/BlobStoreManagerService, mPackageManagerInternal, <Application,Landroid/content/pm/PackageManagerInternal> > 1,
6 = invokestatic < Application, Landroid/os/UserHandle, getUserId(I)I > 2 @2 exception:5,
9 = invokevirtual < Application, Landroid/content/pm/PackageManagerInternal, getPackageUid(Ljava/lang/String;JI)I > 4,3,7,6 @8 exception:8,
conditional branch(ne, to iindex=-1) 9,2,
return,
return,
7 = getfield < Application, Lcom/android/server/blob/BlobStoreManagerService$Stub, this$0, <Application,Lcom/android/server/blob/BlobStoreManagerService> > 1,
9 = invokestatic < Application, Lcom/android/server/blob/BlobStoreManagerService, -$$Nest$mgetRemainingLeaseQuotaBytesInternal(Lcom/android/server/blob/BlobStoreManagerService;ILjava/lang/String;)J > 7,4,2 @11 exception:8,
5 = invokevirtual < Application, Lcom/android/server/blob/BlobStoreManagerService, getRemainingLeaseQuotaBytesInternal(ILjava/lang/String;)J > 1,2,3 @0 exception:4,
4 = getfield < Application, Lcom/android/server/blob/BlobStoreManagerService, mBlobsLock, <Application,Ljava/lang/Object> > 1,
monitorenter 4,
6 = invokestatic < Application, Lcom/android/server/blob/BlobStoreConfig, getAppDataBytesLimit()J > @3 exception:5,
8 = invokevirtual < Application, Lcom/android/server/blob/BlobStoreManagerService, getTotalUsageBytesLocked(ILjava/lang/String;)J > 1,2,3 @7 exception:7,
9 = binaryop(sub) 6 , 8,
11 = binaryop(lt) 9 , 10,
conditional branch(le, to iindex=-1) 11,12,
goto (from iindex= 10 to iindex = 2),
13 = phi  9,10,
monitorexit 4,
return 13,
return 5,
return 9,","depth : 0
-----
depth : 1
-----
depth : 2
-----
depth : 1
-----
depth : 2
-----
","public long getRemainingLeaseQuotaBytes(String p1){
	int v1 = Binder.getCallingUid();
	long v8 = BlobStoreConfig.getAppDataBytesLimit();
	long v9 = BlobStoreManagerService.getTotalUsageBytesLocked(v1, p1);
	if (((v8 - v9) < 0) <= 0) {
		long v7 = (v8 - v9);
		long v6 = v7;
		return v6;
	}
}
","SYS_OR_SIG"

"Lcom/android/server/blob/BlobStoreManagerService$Stub","deleteBlob(J)V","0","4 = invokestatic < Application, Landroid/os/Binder, getCallingUid()I > @0 exception:3,
conditional branch(ne, to iindex=-1) 4,5,
9 = getfield < Application, Lcom/android/server/blob/BlobStoreManagerService$Stub, this$0, <Application,Lcom/android/server/blob/BlobStoreManagerService> > 1,
invokestatic < Application, Lcom/android/server/blob/BlobStoreManagerService, -$$Nest$mdeleteBlobInternal(Lcom/android/server/blob/BlobStoreManagerService;JI)V > 9,2,4 @10 exception:10,
return,","depth : 0
-----
","public void deleteBlob(long p1){
	BlobStoreManagerService.-$$Nest$mdeleteBlobInternal(this.this$0, p1, v1);
	return;
}
","SYS_OR_SIG"
"Lcom/android/server/blob/BlobStoreManagerService$Stub","deleteBlob(J)V","1","4 = invokestatic < Application, Landroid/os/Binder, getCallingUid()I > @0 exception:3,
conditional branch(ne, to iindex=-1) 4,5,
9 = getfield < Application, Lcom/android/server/blob/BlobStoreManagerService$Stub, this$0, <Application,Lcom/android/server/blob/BlobStoreManagerService> > 1,
invokestatic < Application, Lcom/android/server/blob/BlobStoreManagerService, -$$Nest$mdeleteBlobInternal(Lcom/android/server/blob/BlobStoreManagerService;JI)V > 9,2,4 @10 exception:10,
invokevirtual < Application, Lcom/android/server/blob/BlobStoreManagerService, deleteBlobInternal(JI)V > 1,2,3 @0 exception:4,
return,
return,","depth : 0
-----
depth : 1
-----
","public void deleteBlob(long p1){
	this.this$0.deleteBlobInternal(p1, v1);
	return;
}
","SYS_OR_SIG"
"Lcom/android/server/blob/BlobStoreManagerService$Stub","deleteBlob(J)V","2","4 = invokestatic < Application, Landroid/os/Binder, getCallingUid()I > @0 exception:3,
conditional branch(ne, to iindex=-1) 4,5,
9 = getfield < Application, Lcom/android/server/blob/BlobStoreManagerService$Stub, this$0, <Application,Lcom/android/server/blob/BlobStoreManagerService> > 1,
invokestatic < Application, Lcom/android/server/blob/BlobStoreManagerService, -$$Nest$mdeleteBlobInternal(Lcom/android/server/blob/BlobStoreManagerService;JI)V > 9,2,4 @10 exception:10,
invokevirtual < Application, Lcom/android/server/blob/BlobStoreManagerService, deleteBlobInternal(JI)V > 1,2,3 @0 exception:4,
4 = getfield < Application, Lcom/android/server/blob/BlobStoreManagerService, mBlobsLock, <Application,Ljava/lang/Object> > 1,
monitorenter 4,
5 = getfield < Application, Lcom/android/server/blob/BlobStoreManagerService, mBlobsMap, <Application,Landroid/util/ArrayMap> > 1,
7 = invokevirtual < Application, Landroid/util/ArrayMap, entrySet()Ljava/util/Set; > 5 @5 exception:6,
8 = new <Application,Lcom/android/server/blob/BlobStoreManagerService$$ExternalSyntheticLambda8>@9,
invokespecial < Application, Lcom/android/server/blob/BlobStoreManagerService$$ExternalSyntheticLambda8, <init>(Lcom/android/server/blob/BlobStoreManagerService;J)V > 8,1,2 @11 exception:9,
11 = invokeinterface < Application, Ljava/util/Set, removeIf(Ljava/util/function/Predicate;)Z > 7,8 @14 exception:10,
invokevirtual < Application, Lcom/android/server/blob/BlobStoreManagerService, writeBlobsInfoAsync()V > 1 @17 exception:12,
monitorexit 4,
return,
return,
return,","depth : 0
-----
depth : 1
-----
depth : 2
-----
","public void deleteBlob(long p1){
	Set v4 = this.mBlobsMap.entrySet();
	BlobStoreManagerService$$ExternalSyntheticLambda8 v5 = new BlobStoreManagerService$$ExternalSyntheticLambda8(BlobStoreManagerService,p1);
	boolean v7 = v4.removeIf(v5);
	BlobStoreManagerService.writeBlobsInfoAsync();
	return;
}
","SYS_OR_SIG"

"Lcom/android/server/blob/BlobStoreManagerService$Stub","getLeaseInfo(Landroid/app/blob/BlobHandle;Ljava/lang/String;)Landroid/app/blob/LeaseInfo;","0","6 = invokestatic < Application, Ljava/util/Objects, requireNonNull(Ljava/lang/Object;Ljava/lang/String;)Ljava/lang/Object; > 2,4 @2 exception:5,
invokevirtual < Application, Landroid/app/blob/BlobHandle, assertIsValid()V > 2 @5 exception:7,
10 = invokestatic < Application, Ljava/util/Objects, requireNonNull(Ljava/lang/Object;Ljava/lang/String;)Ljava/lang/Object; > 3,8 @11 exception:9,
12 = invokestatic < Application, Landroid/os/Binder, getCallingUid()I > @14 exception:11,
13 = getfield < Application, Lcom/android/server/blob/BlobStoreManagerService$Stub, this$0, <Application,Lcom/android/server/blob/BlobStoreManagerService> > 1,
invokestatic < Application, Lcom/android/server/blob/BlobStoreManagerService, -$$Nest$mverifyCallingPackage(Lcom/android/server/blob/BlobStoreManagerService;ILjava/lang/String;)V > 13,12,3 @20 exception:14,
15 = getfield < Application, Lcom/android/server/blob/BlobStoreManagerService$Stub, this$0, <Application,Lcom/android/server/blob/BlobStoreManagerService> > 1,
17 = invokestatic < Application, Lcom/android/server/blob/BlobStoreManagerService, -$$Nest$misAllowedBlobStoreAccess(Lcom/android/server/blob/BlobStoreManagerService;ILjava/lang/String;)Z > 15,12,3 @25 exception:16,
conditional branch(eq, to iindex=-1) 17,18,
35 = getfield < Application, Lcom/android/server/blob/BlobStoreManagerService$Stub, this$0, <Application,Lcom/android/server/blob/BlobStoreManagerService> > 1,
37 = invokestatic < Application, Lcom/android/server/blob/BlobStoreManagerService, -$$Nest$mgetLeaseInfoInternal(Lcom/android/server/blob/BlobStoreManagerService;Landroid/app/blob/BlobHandle;ILjava/lang/String;)Landroid/app/blob/LeaseInfo; > 35,2,12,3 @33 exception:36,
return 37,","depth : 0
-----
","public LeaseInfo getLeaseInfo(BlobHandle p1, String p2){
	Object v1 = Objects.requireNonNull(p1, ""blobHandle must not be null"");
	p1.assertIsValid();
	Object v3 = Objects.requireNonNull(p2, ""packageName must not be null"");
	int v4 = Binder.getCallingUid();
	BlobStoreManagerService.-$$Nest$mverifyCallingPackage(this.this$0, v4, p2);
	boolean v6 = BlobStoreManagerService.-$$Nest$misAllowedBlobStoreAccess(this.this$0, v4, p2);
	if (v6 == 0) {
		LeaseInfo v7 = BlobStoreManagerService.-$$Nest$mgetLeaseInfoInternal(this.this$0, p1, v4, p2);
		return v7;
	}
}
","SYS_OR_SIG"
"Lcom/android/server/blob/BlobStoreManagerService$Stub","getLeaseInfo(Landroid/app/blob/BlobHandle;Ljava/lang/String;)Landroid/app/blob/LeaseInfo;","1","6 = invokestatic < Application, Ljava/util/Objects, requireNonNull(Ljava/lang/Object;Ljava/lang/String;)Ljava/lang/Object; > 2,4 @2 exception:5,
invokevirtual < Application, Landroid/app/blob/BlobHandle, assertIsValid()V > 2 @5 exception:7,
2 = getstatic < Application, Landroid/app/blob/BlobHandle, SUPPORTED_ALGOS, <Application,[Ljava/lang/String> >,
3 = getfield < Application, Landroid/app/blob/BlobHandle, algorithm, <Application,Ljava/lang/String> > 1,
5 = invokestatic < Application, Lcom/android/internal/util/Preconditions, checkArgumentIsSupported([Ljava/lang/String;Ljava/lang/String;)Ljava/lang/String; > 2,3 @4 exception:4,
6 = getfield < Application, Landroid/app/blob/BlobHandle, digest, <Primordial,[B> > 1,
9 = invokestatic < Application, Lcom/android/internal/util/Preconditions, checkByteArrayNotEmpty([BLjava/lang/String;)[B > 6,7 @11 exception:8,
10 = getfield < Application, Landroid/app/blob/BlobHandle, label, <Application,Ljava/lang/CharSequence> > 1,
13 = invokestatic < Application, Lcom/android/internal/util/Preconditions, checkStringNotEmpty(Ljava/lang/CharSequence;Ljava/lang/Object;)Ljava/lang/CharSequence; > 10,11 @18 exception:12,
14 = getfield < Application, Landroid/app/blob/BlobHandle, label, <Application,Ljava/lang/CharSequence> > 1,
16 = invokeinterface < Application, Ljava/lang/CharSequence, length()I > 14 @23 exception:15,
conditional branch(gt, to iindex=-1) 16,19,
goto (from iindex= 17 to iindex = 2),
20 = phi  17,18,
invokestatic < Application, Lcom/android/internal/util/Preconditions, checkArgument(ZLjava/lang/Object;)V > 20,21 @38 exception:22,
23 = getfield < Application, Landroid/app/blob/BlobHandle, expiryTimeMillis, <Primordial,J> > 1,
26 = invokestatic < Application, Lcom/android/internal/util/Preconditions, checkArgumentNonnegative(JLjava/lang/String;)J > 23,24 @45 exception:25,
27 = getfield < Application, Landroid/app/blob/BlobHandle, tag, <Application,Ljava/lang/String> > 1,
30 = invokestatic < Application, Lcom/android/internal/util/Preconditions, checkStringNotEmpty(Ljava/lang/CharSequence;Ljava/lang/Object;)Ljava/lang/CharSequence; > 27,28 @53 exception:29,
31 = getfield < Application, Landroid/app/blob/BlobHandle, tag, <Application,Ljava/lang/String> > 1,
33 = invokevirtual < Application, Ljava/lang/String, length()I > 31 @58 exception:32,
conditional branch(gt, to iindex=-1) 33,34,
goto (from iindex= 32 to iindex = 2),
35 = phi  17,18,
invokestatic < Application, Lcom/android/internal/util/Preconditions, checkArgument(ZLjava/lang/Object;)V > 35,36 @71 exception:37,
return,
10 = invokestatic < Application, Ljava/util/Objects, requireNonNull(Ljava/lang/Object;Ljava/lang/String;)Ljava/lang/Object; > 3,8 @11 exception:9,
12 = invokestatic < Application, Landroid/os/Binder, getCallingUid()I > @14 exception:11,
13 = getfield < Application, Lcom/android/server/blob/BlobStoreManagerService$Stub, this$0, <Application,Lcom/android/server/blob/BlobStoreManagerService> > 1,
invokestatic < Application, Lcom/android/server/blob/BlobStoreManagerService, -$$Nest$mverifyCallingPackage(Lcom/android/server/blob/BlobStoreManagerService;ILjava/lang/String;)V > 13,12,3 @20 exception:14,
invokevirtual < Application, Lcom/android/server/blob/BlobStoreManagerService, verifyCallingPackage(ILjava/lang/String;)V > 1,2,3 @0 exception:4,
return,
15 = getfield < Application, Lcom/android/server/blob/BlobStoreManagerService$Stub, this$0, <Application,Lcom/android/server/blob/BlobStoreManagerService> > 1,
17 = invokestatic < Application, Lcom/android/server/blob/BlobStoreManagerService, -$$Nest$misAllowedBlobStoreAccess(Lcom/android/server/blob/BlobStoreManagerService;ILjava/lang/String;)Z > 15,12,3 @25 exception:16,
5 = invokevirtual < Application, Lcom/android/server/blob/BlobStoreManagerService, isAllowedBlobStoreAccess(ILjava/lang/String;)Z > 1,2,3 @0 exception:4,
return 5,
conditional branch(eq, to iindex=-1) 17,18,
35 = getfield < Application, Lcom/android/server/blob/BlobStoreManagerService$Stub, this$0, <Application,Lcom/android/server/blob/BlobStoreManagerService> > 1,
37 = invokestatic < Application, Lcom/android/server/blob/BlobStoreManagerService, -$$Nest$mgetLeaseInfoInternal(Lcom/android/server/blob/BlobStoreManagerService;Landroid/app/blob/BlobHandle;ILjava/lang/String;)Landroid/app/blob/LeaseInfo; > 35,2,12,3 @33 exception:36,
6 = invokevirtual < Application, Lcom/android/server/blob/BlobStoreManagerService, getLeaseInfoInternal(Landroid/app/blob/BlobHandle;ILjava/lang/String;)Landroid/app/blob/LeaseInfo; > 1,2,3,4 @0 exception:5,
return 6,
return 37,","depth : 0
-----
depth : 1
-----
depth : 1
-----
depth : 1
-----
depth : 1
-----
","public LeaseInfo getLeaseInfo(BlobHandle p1, String p2){
	Object v1 = Objects.requireNonNull(p1, ""blobHandle must not be null"");
	String v3 = Preconditions.checkArgumentIsSupported(this.SUPPORTED_ALGOS, this.algorithm);
	byte[] v4 = Preconditions.checkByteArrayNotEmpty(this.digest, ""digest"");
	CharSequence v5 = Preconditions.checkStringNotEmpty(this.label, ""label must not be null"");
	int v6 = this.label.length();
	if (v6 > 100) {
		Preconditions.checkArgument(1, ""label too long"");
		long v8 = Preconditions.checkArgumentNonnegative(this.expiryTimeMillis, ""expiryTimeMillis must not be negative"");
		CharSequence v9 = Preconditions.checkStringNotEmpty(this.tag, ""tag must not be null"");
		int v10 = this.tag.length();
		if (v10 > 128) {
			Preconditions.checkArgument(1, ""tag too long"");
			Object v12 = Objects.requireNonNull(p2, ""packageName must not be null"");
			int v13 = Binder.getCallingUid();
			this.this$0.verifyCallingPackage(v13, p2);
			boolean v17 = this.this$0.isAllowedBlobStoreAccess(v13, p2);
			boolean v16 = v17;
			if (v16 == 0) {
				LeaseInfo v19 = this.this$0.getLeaseInfoInternal(p1, v13, p2);
				LeaseInfo v18 = v19;
				return v18;
			}
		}
	}
}
","SYS_OR_SIG"
"Lcom/android/server/blob/BlobStoreManagerService$Stub","getLeaseInfo(Landroid/app/blob/BlobHandle;Ljava/lang/String;)Landroid/app/blob/LeaseInfo;","2","6 = invokestatic < Application, Ljava/util/Objects, requireNonNull(Ljava/lang/Object;Ljava/lang/String;)Ljava/lang/Object; > 2,4 @2 exception:5,
invokevirtual < Application, Landroid/app/blob/BlobHandle, assertIsValid()V > 2 @5 exception:7,
2 = getstatic < Application, Landroid/app/blob/BlobHandle, SUPPORTED_ALGOS, <Application,[Ljava/lang/String> >,
3 = getfield < Application, Landroid/app/blob/BlobHandle, algorithm, <Application,Ljava/lang/String> > 1,
5 = invokestatic < Application, Lcom/android/internal/util/Preconditions, checkArgumentIsSupported([Ljava/lang/String;Ljava/lang/String;)Ljava/lang/String; > 2,3 @4 exception:4,
6 = getfield < Application, Landroid/app/blob/BlobHandle, digest, <Primordial,[B> > 1,
9 = invokestatic < Application, Lcom/android/internal/util/Preconditions, checkByteArrayNotEmpty([BLjava/lang/String;)[B > 6,7 @11 exception:8,
10 = getfield < Application, Landroid/app/blob/BlobHandle, label, <Application,Ljava/lang/CharSequence> > 1,
13 = invokestatic < Application, Lcom/android/internal/util/Preconditions, checkStringNotEmpty(Ljava/lang/CharSequence;Ljava/lang/Object;)Ljava/lang/CharSequence; > 10,11 @18 exception:12,
14 = getfield < Application, Landroid/app/blob/BlobHandle, label, <Application,Ljava/lang/CharSequence> > 1,
16 = invokeinterface < Application, Ljava/lang/CharSequence, length()I > 14 @23 exception:15,
conditional branch(gt, to iindex=-1) 16,19,
goto (from iindex= 17 to iindex = 2),
20 = phi  17,18,
invokestatic < Application, Lcom/android/internal/util/Preconditions, checkArgument(ZLjava/lang/Object;)V > 20,21 @38 exception:22,
23 = getfield < Application, Landroid/app/blob/BlobHandle, expiryTimeMillis, <Primordial,J> > 1,
26 = invokestatic < Application, Lcom/android/internal/util/Preconditions, checkArgumentNonnegative(JLjava/lang/String;)J > 23,24 @45 exception:25,
27 = getfield < Application, Landroid/app/blob/BlobHandle, tag, <Application,Ljava/lang/String> > 1,
30 = invokestatic < Application, Lcom/android/internal/util/Preconditions, checkStringNotEmpty(Ljava/lang/CharSequence;Ljava/lang/Object;)Ljava/lang/CharSequence; > 27,28 @53 exception:29,
31 = getfield < Application, Landroid/app/blob/BlobHandle, tag, <Application,Ljava/lang/String> > 1,
33 = invokevirtual < Application, Ljava/lang/String, length()I > 31 @58 exception:32,
conditional branch(gt, to iindex=-1) 33,34,
goto (from iindex= 32 to iindex = 2),
35 = phi  17,18,
invokestatic < Application, Lcom/android/internal/util/Preconditions, checkArgument(ZLjava/lang/Object;)V > 35,36 @71 exception:37,
return,
10 = invokestatic < Application, Ljava/util/Objects, requireNonNull(Ljava/lang/Object;Ljava/lang/String;)Ljava/lang/Object; > 3,8 @11 exception:9,
12 = invokestatic < Application, Landroid/os/Binder, getCallingUid()I > @14 exception:11,
13 = getfield < Application, Lcom/android/server/blob/BlobStoreManagerService$Stub, this$0, <Application,Lcom/android/server/blob/BlobStoreManagerService> > 1,
invokestatic < Application, Lcom/android/server/blob/BlobStoreManagerService, -$$Nest$mverifyCallingPackage(Lcom/android/server/blob/BlobStoreManagerService;ILjava/lang/String;)V > 13,12,3 @20 exception:14,
invokevirtual < Application, Lcom/android/server/blob/BlobStoreManagerService, verifyCallingPackage(ILjava/lang/String;)V > 1,2,3 @0 exception:4,
4 = getfield < Application, Lcom/android/server/blob/BlobStoreManagerService, mPackageManagerInternal, <Application,Landroid/content/pm/PackageManagerInternal> > 1,
6 = invokestatic < Application, Landroid/os/UserHandle, getUserId(I)I > 2 @2 exception:5,
9 = invokevirtual < Application, Landroid/content/pm/PackageManagerInternal, getPackageUid(Ljava/lang/String;JI)I > 4,3,7,6 @8 exception:8,
conditional branch(ne, to iindex=-1) 9,2,
return,
return,
15 = getfield < Application, Lcom/android/server/blob/BlobStoreManagerService$Stub, this$0, <Application,Lcom/android/server/blob/BlobStoreManagerService> > 1,
17 = invokestatic < Application, Lcom/android/server/blob/BlobStoreManagerService, -$$Nest$misAllowedBlobStoreAccess(Lcom/android/server/blob/BlobStoreManagerService;ILjava/lang/String;)Z > 15,12,3 @25 exception:16,
5 = invokevirtual < Application, Lcom/android/server/blob/BlobStoreManagerService, isAllowedBlobStoreAccess(ILjava/lang/String;)Z > 1,2,3 @0 exception:4,
5 = invokestatic < Application, Landroid/os/Process, isSdkSandboxUid(I)Z > 2 @0 exception:4,
conditional branch(ne, to iindex=-1) 5,6,
8 = invokestatic < Application, Landroid/os/Process, isIsolated(I)Z > 2 @6 exception:7,
conditional branch(ne, to iindex=-1) 8,6,
9 = getfield < Application, Lcom/android/server/blob/BlobStoreManagerService, mPackageManagerInternal, <Application,Landroid/content/pm/PackageManagerInternal> > 1,
11 = invokestatic < Application, Landroid/os/UserHandle, getUserId(I)I > 2 @14 exception:10,
13 = invokevirtual < Application, Landroid/content/pm/PackageManagerInternal, isInstantApp(Ljava/lang/String;I)Z > 9,3,11 @18 exception:12,
conditional branch(ne, to iindex=-1) 13,6,
goto (from iindex= 13 to iindex = 2),
21 = phi  19,6,
return 21,
return 5,
conditional branch(eq, to iindex=-1) 17,18,
35 = getfield < Application, Lcom/android/server/blob/BlobStoreManagerService$Stub, this$0, <Application,Lcom/android/server/blob/BlobStoreManagerService> > 1,
37 = invokestatic < Application, Lcom/android/server/blob/BlobStoreManagerService, -$$Nest$mgetLeaseInfoInternal(Lcom/android/server/blob/BlobStoreManagerService;Landroid/app/blob/BlobHandle;ILjava/lang/String;)Landroid/app/blob/LeaseInfo; > 35,2,12,3 @33 exception:36,
6 = invokevirtual < Application, Lcom/android/server/blob/BlobStoreManagerService, getLeaseInfoInternal(Landroid/app/blob/BlobHandle;ILjava/lang/String;)Landroid/app/blob/LeaseInfo; > 1,2,3,4 @0 exception:5,
5 = getfield < Application, Lcom/android/server/blob/BlobStoreManagerService, mBlobsLock, <Application,Ljava/lang/Object> > 1,
monitorenter 5,
6 = getfield < Application, Lcom/android/server/blob/BlobStoreManagerService, mBlobsMap, <Application,Landroid/util/ArrayMap> > 1,
8 = invokevirtual < Application, Landroid/util/ArrayMap, get(Ljava/lang/Object;)Ljava/lang/Object; > 6,2 @5 exception:7,
9 = checkcast <Application,Lcom/android/server/blob/BlobMetadata>8 <Application,Lcom/android/server/blob/BlobMetadata>,
conditional branch(eq, to iindex=-1) 9,10,
12 = invokevirtual < Application, Lcom/android/server/blob/BlobMetadata, isAccessAllowedForCaller(Ljava/lang/String;I)Z > 9,4,3 @13 exception:11,
conditional branch(eq, to iindex=-1) 12,10,
37 = invokevirtual < Application, Lcom/android/server/blob/BlobMetadata, getLeaseInfo(Ljava/lang/String;I)Landroid/app/blob/LeaseInfo; > 9,4,3 @19 exception:36,
monitorexit 5,
return 37,
return 6,
return 37,","depth : 0
-----
depth : 1
-----
depth : 1
-----
depth : 2
-----
depth : 1
-----
depth : 2
-----
depth : 1
-----
depth : 2
-----
","public LeaseInfo getLeaseInfo(BlobHandle p1, String p2){
	Object v1 = Objects.requireNonNull(p1, ""blobHandle must not be null"");
	String v3 = Preconditions.checkArgumentIsSupported(this.SUPPORTED_ALGOS, this.algorithm);
	byte[] v4 = Preconditions.checkByteArrayNotEmpty(this.digest, ""digest"");
	CharSequence v5 = Preconditions.checkStringNotEmpty(this.label, ""label must not be null"");
	int v6 = this.label.length();
	if (v6 > 100) {
		Preconditions.checkArgument(1, ""label too long"");
		long v8 = Preconditions.checkArgumentNonnegative(this.expiryTimeMillis, ""expiryTimeMillis must not be negative"");
		CharSequence v9 = Preconditions.checkStringNotEmpty(this.tag, ""tag must not be null"");
		int v10 = this.tag.length();
		if (v10 > 128) {
			Preconditions.checkArgument(1, ""tag too long"");
			Object v12 = Objects.requireNonNull(p2, ""packageName must not be null"");
			int v13 = Binder.getCallingUid();
			if (v21 != 0) {
				int v22 = UserHandle.getUserId(v13);
				boolean v23 = this.mPackageManagerInternal.isInstantApp(p2, v22);
				if (v23 != 0) {
					boolean v19 = 1;
					boolean v18 = v19;
					if (v18 == 0) {
						Object v26 = this.mBlobsMap.get(p1);
						if (v26 == 0) {
							boolean v27 = v26.isAccessAllowedForCaller(p2, v13);
							if (v27 == 0) {
								LeaseInfo v28 = v26.getLeaseInfo(p2, v13);
								LeaseInfo v25 = v28;
								LeaseInfo v24 = v25;
								return v24;
							}
						}
					}
				}
			}
		}
	}
}
","SYS_OR_SIG"

