"Class","Method","Depth","Trace Instruction(s) ...","Java Code Representation","Code Merged","Access Control Level"
"Lcom/android/server/oemlock/OemLockService$2","isOemUnlockAllowed()Z","0","2 = getfield < Application, Lcom/android/server/oemlock/OemLockService$2, this$0, <Application,Lcom/android/server/oemlock/OemLockService> > 1,
invokestatic < Application, Lcom/android/server/oemlock/OemLockService, -$$Nest$menforceOemUnlockReadPermission(Lcom/android/server/oemlock/OemLockService;)V > 2 @2 exception:3,
5 = invokestatic < Application, Landroid/os/Binder, clearCallingIdentity()J > @5 exception:4,
6 = getfield < Application, Lcom/android/server/oemlock/OemLockService$2, this$0, <Application,Lcom/android/server/oemlock/OemLockService> > 1,
8 = invokestatic < Application, Lcom/android/server/oemlock/OemLockService, -$$Nest$fgetmOemLock(Lcom/android/server/oemlock/OemLockService;)Lcom/android/server/oemlock/OemLock; > 6 @11 exception:7,
10 = invokevirtual < Application, Lcom/android/server/oemlock/OemLock, isOemUnlockAllowedByCarrier()Z > 8 @15 exception:9,
conditional branch(eq, to iindex=-1) 10,11,
12 = getfield < Application, Lcom/android/server/oemlock/OemLockService$2, this$0, <Application,Lcom/android/server/oemlock/OemLockService> > 1,
14 = invokestatic < Application, Lcom/android/server/oemlock/OemLockService, -$$Nest$fgetmOemLock(Lcom/android/server/oemlock/OemLockService;)Lcom/android/server/oemlock/OemLock; > 12 @23 exception:13,
16 = invokevirtual < Application, Lcom/android/server/oemlock/OemLock, isOemUnlockAllowedByDevice()Z > 14 @27 exception:15,
conditional branch(eq, to iindex=-1) 16,11,
goto (from iindex= 17 to iindex = 2),
21 = phi  20,11,
24 = getfield < Application, Lcom/android/server/oemlock/OemLockService$2, this$0, <Application,Lcom/android/server/oemlock/OemLockService> > 1,
invokestatic < Application, Lcom/android/server/oemlock/OemLockService, -$$Nest$msetPersistentDataBlockOemUnlockAllowedBit(Lcom/android/server/oemlock/OemLockService;Z)V > 24,21 @38 exception:25,
invokestatic < Application, Landroid/os/Binder, restoreCallingIdentity(J)V > 5 @41 exception:32,
return 21,","depth : 0
public boolean isOemUnlockAllowed(){
	OemLockService.-$$Nest$menforceOemUnlockReadPermission(this.this$0);
	long v2 = Binder.clearCallingIdentity();
	OemLock v3 = OemLockService.-$$Nest$fgetmOemLock(this.this$0);
	boolean v4 = v3.isOemUnlockAllowedByCarrier();
	OemLock v5 = OemLockService.-$$Nest$fgetmOemLock(this.this$0);
	boolean v6 = v5.isOemUnlockAllowedByDevice();
	OemLockService.-$$Nest$msetPersistentDataBlockOemUnlockAllowedBit(this.this$0, phiInstruction);
	Binder.restoreCallingIdentity(v2);
	return phiInstruction;
}
-----
","public boolean isOemUnlockAllowed(){
	OemLockService.-$$Nest$menforceOemUnlockReadPermission(this.this$0);
	long v2 = Binder.clearCallingIdentity();
	OemLock v3 = OemLockService.-$$Nest$fgetmOemLock(this.this$0);
	boolean v4 = v3.isOemUnlockAllowedByCarrier();
	OemLock v5 = OemLockService.-$$Nest$fgetmOemLock(this.this$0);
	boolean v6 = v5.isOemUnlockAllowedByDevice();
	OemLockService.-$$Nest$msetPersistentDataBlockOemUnlockAllowedBit(this.this$0, phiInstruction);
	Binder.restoreCallingIdentity(v2);
	return phiInstruction;
}
","SYS_OR_SIG"
"Lcom/android/server/oemlock/OemLockService$2","isOemUnlockAllowed()Z","1","2 = getfield < Application, Lcom/android/server/oemlock/OemLockService$2, this$0, <Application,Lcom/android/server/oemlock/OemLockService> > 1,
invokestatic < Application, Lcom/android/server/oemlock/OemLockService, -$$Nest$menforceOemUnlockReadPermission(Lcom/android/server/oemlock/OemLockService;)V > 2 @2 exception:3,
invokevirtual < Application, Lcom/android/server/oemlock/OemLockService, enforceOemUnlockReadPermission()V > 1 @0 exception:2,
return,
5 = invokestatic < Application, Landroid/os/Binder, clearCallingIdentity()J > @5 exception:4,
6 = getfield < Application, Lcom/android/server/oemlock/OemLockService$2, this$0, <Application,Lcom/android/server/oemlock/OemLockService> > 1,
8 = invokestatic < Application, Lcom/android/server/oemlock/OemLockService, -$$Nest$fgetmOemLock(Lcom/android/server/oemlock/OemLockService;)Lcom/android/server/oemlock/OemLock; > 6 @11 exception:7,
2 = getfield < Application, Lcom/android/server/oemlock/OemLockService, mOemLock, <Application,Lcom/android/server/oemlock/OemLock> > 1,
return 2,
10 = invokevirtual < Application, Lcom/android/server/oemlock/OemLock, isOemUnlockAllowedByCarrier()Z > 8 @15 exception:9,
conditional branch(eq, to iindex=-1) 10,11,
12 = getfield < Application, Lcom/android/server/oemlock/OemLockService$2, this$0, <Application,Lcom/android/server/oemlock/OemLockService> > 1,
14 = invokestatic < Application, Lcom/android/server/oemlock/OemLockService, -$$Nest$fgetmOemLock(Lcom/android/server/oemlock/OemLockService;)Lcom/android/server/oemlock/OemLock; > 12 @23 exception:13,
2 = getfield < Application, Lcom/android/server/oemlock/OemLockService, mOemLock, <Application,Lcom/android/server/oemlock/OemLock> > 1,
return 2,
16 = invokevirtual < Application, Lcom/android/server/oemlock/OemLock, isOemUnlockAllowedByDevice()Z > 14 @27 exception:15,
conditional branch(eq, to iindex=-1) 16,11,
goto (from iindex= 17 to iindex = 2),
21 = phi  20,11,
24 = getfield < Application, Lcom/android/server/oemlock/OemLockService$2, this$0, <Application,Lcom/android/server/oemlock/OemLockService> > 1,
invokestatic < Application, Lcom/android/server/oemlock/OemLockService, -$$Nest$msetPersistentDataBlockOemUnlockAllowedBit(Lcom/android/server/oemlock/OemLockService;Z)V > 24,21 @38 exception:25,
invokevirtual < Application, Lcom/android/server/oemlock/OemLockService, setPersistentDataBlockOemUnlockAllowedBit(Z)V > 1,2 @0 exception:3,
return,
invokestatic < Application, Landroid/os/Binder, restoreCallingIdentity(J)V > 5 @41 exception:32,
return 21,","depth : 0
public boolean isOemUnlockAllowed(){
	OemLockService.-$$Nest$menforceOemUnlockReadPermission(this.this$0);
	long v2 = Binder.clearCallingIdentity();
	OemLock v3 = OemLockService.-$$Nest$fgetmOemLock(this.this$0);
	boolean v4 = v3.isOemUnlockAllowedByCarrier();
	OemLock v5 = OemLockService.-$$Nest$fgetmOemLock(this.this$0);
	boolean v6 = v5.isOemUnlockAllowedByDevice();
	OemLockService.-$$Nest$msetPersistentDataBlockOemUnlockAllowedBit(this.this$0, phiInstruction);
	Binder.restoreCallingIdentity(v2);
	return phiInstruction;
}
-----
depth : 1
public void -$$Nest$menforceOemUnlockReadPermission(OemLockService p1){
	p1.enforceOemUnlockReadPermission();
	return;
}
-----
depth : 1
public OemLock -$$Nest$fgetmOemLock(OemLockService p1){
	return this.mOemLock;
}
-----
depth : 1
public OemLock -$$Nest$fgetmOemLock(OemLockService p1){
	return this.mOemLock;
}
-----
depth : 1
public void -$$Nest$msetPersistentDataBlockOemUnlockAllowedBit(OemLockService p1, boolean p2){
	p1.setPersistentDataBlockOemUnlockAllowedBit(p2);
	return;
}
-----
","public boolean isOemUnlockAllowed(){
	this.this$0.enforceOemUnlockReadPermission();
	long v3 = Binder.clearCallingIdentity();
	OemLock v4 = this.mOemLock;
	boolean v5 = v4.isOemUnlockAllowedByCarrier();
	OemLock v6 = this.mOemLock;
	boolean v7 = v6.isOemUnlockAllowedByDevice();
	this.this$0.setPersistentDataBlockOemUnlockAllowedBit(phiInstruction);
	Binder.restoreCallingIdentity(v3);
	return phiInstruction;
}
","SYS_OR_SIG"
"Lcom/android/server/oemlock/OemLockService$2","isOemUnlockAllowed()Z","1","2 = getfield < Application, Lcom/android/server/oemlock/OemLockService$2, this$0, <Application,Lcom/android/server/oemlock/OemLockService> > 1,
invokestatic < Application, Lcom/android/server/oemlock/OemLockService, -$$Nest$menforceOemUnlockReadPermission(Lcom/android/server/oemlock/OemLockService;)V > 2 @2 exception:3,
invokevirtual < Application, Lcom/android/server/oemlock/OemLockService, enforceOemUnlockReadPermission()V > 1 @0 exception:2,
return,
5 = invokestatic < Application, Landroid/os/Binder, clearCallingIdentity()J > @5 exception:4,
6 = getfield < Application, Lcom/android/server/oemlock/OemLockService$2, this$0, <Application,Lcom/android/server/oemlock/OemLockService> > 1,
8 = invokestatic < Application, Lcom/android/server/oemlock/OemLockService, -$$Nest$fgetmOemLock(Lcom/android/server/oemlock/OemLockService;)Lcom/android/server/oemlock/OemLock; > 6 @11 exception:7,
2 = getfield < Application, Lcom/android/server/oemlock/OemLockService, mOemLock, <Application,Lcom/android/server/oemlock/OemLock> > 1,
return 2,
10 = invokevirtual < Application, Lcom/android/server/oemlock/OemLock, isOemUnlockAllowedByCarrier()Z > 8 @15 exception:9,
conditional branch(eq, to iindex=-1) 10,11,
12 = getfield < Application, Lcom/android/server/oemlock/OemLockService$2, this$0, <Application,Lcom/android/server/oemlock/OemLockService> > 1,
14 = invokestatic < Application, Lcom/android/server/oemlock/OemLockService, -$$Nest$fgetmOemLock(Lcom/android/server/oemlock/OemLockService;)Lcom/android/server/oemlock/OemLock; > 12 @23 exception:13,
2 = getfield < Application, Lcom/android/server/oemlock/OemLockService, mOemLock, <Application,Lcom/android/server/oemlock/OemLock> > 1,
return 2,
16 = invokevirtual < Application, Lcom/android/server/oemlock/OemLock, isOemUnlockAllowedByDevice()Z > 14 @27 exception:15,
conditional branch(eq, to iindex=-1) 16,11,
21 = phi  20,11,
24 = getfield < Application, Lcom/android/server/oemlock/OemLockService$2, this$0, <Application,Lcom/android/server/oemlock/OemLockService> > 1,
invokestatic < Application, Lcom/android/server/oemlock/OemLockService, -$$Nest$msetPersistentDataBlockOemUnlockAllowedBit(Lcom/android/server/oemlock/OemLockService;Z)V > 24,21 @38 exception:25,
invokevirtual < Application, Lcom/android/server/oemlock/OemLockService, setPersistentDataBlockOemUnlockAllowedBit(Z)V > 1,2 @0 exception:3,
return,
invokestatic < Application, Landroid/os/Binder, restoreCallingIdentity(J)V > 5 @41 exception:32,
return 21,","depth : 0
public boolean isOemUnlockAllowed(){
	OemLockService.-$$Nest$menforceOemUnlockReadPermission(this.this$0);
	long v2 = Binder.clearCallingIdentity();
	OemLock v3 = OemLockService.-$$Nest$fgetmOemLock(this.this$0);
	boolean v4 = v3.isOemUnlockAllowedByCarrier();
	OemLock v5 = OemLockService.-$$Nest$fgetmOemLock(this.this$0);
	boolean v6 = v5.isOemUnlockAllowedByDevice();
	OemLockService.-$$Nest$msetPersistentDataBlockOemUnlockAllowedBit(this.this$0, phiInstruction);
	Binder.restoreCallingIdentity(v2);
	return phiInstruction;
}
-----
depth : 1
public void -$$Nest$menforceOemUnlockReadPermission(OemLockService p1){
	p1.enforceOemUnlockReadPermission();
	return;
}
-----
depth : 1
public OemLock -$$Nest$fgetmOemLock(OemLockService p1){
	return this.mOemLock;
}
-----
depth : 1
public OemLock -$$Nest$fgetmOemLock(OemLockService p1){
	return this.mOemLock;
}
-----
depth : 1
public void -$$Nest$msetPersistentDataBlockOemUnlockAllowedBit(OemLockService p1, boolean p2){
	p1.setPersistentDataBlockOemUnlockAllowedBit(p2);
	return;
}
-----
","public boolean isOemUnlockAllowed(){
	this.this$0.enforceOemUnlockReadPermission();
	long v3 = Binder.clearCallingIdentity();
	OemLock v4 = this.mOemLock;
	boolean v5 = v4.isOemUnlockAllowedByCarrier();
	OemLock v6 = this.mOemLock;
	boolean v7 = v6.isOemUnlockAllowedByDevice();
	this.this$0.setPersistentDataBlockOemUnlockAllowedBit(phiInstruction);
	Binder.restoreCallingIdentity(v3);
	return phiInstruction;
}
","SYS_OR_SIG"
"Lcom/android/server/oemlock/OemLockService$2","isOemUnlockAllowed()Z","2","2 = getfield < Application, Lcom/android/server/oemlock/OemLockService$2, this$0, <Application,Lcom/android/server/oemlock/OemLockService> > 1,
invokestatic < Application, Lcom/android/server/oemlock/OemLockService, -$$Nest$menforceOemUnlockReadPermission(Lcom/android/server/oemlock/OemLockService;)V > 2 @2 exception:3,
invokevirtual < Application, Lcom/android/server/oemlock/OemLockService, enforceOemUnlockReadPermission()V > 1 @0 exception:2,
2 = getfield < Application, Lcom/android/server/oemlock/OemLockService, mContext, <Application,Landroid/content/Context> > 1,
5 = invokevirtual < Application, Landroid/content/Context, checkCallingOrSelfPermission(Ljava/lang/String;)I > 2,3 @4 exception:4,
conditional branch(ne, to iindex=-1) 5,6,
7 = getfield < Application, Lcom/android/server/oemlock/OemLockService, mContext, <Application,Landroid/content/Context> > 1,
10 = invokevirtual < Application, Landroid/content/Context, checkCallingOrSelfPermission(Ljava/lang/String;)I > 7,8 @15 exception:9,
conditional branch(eq, to iindex=-1) 10,6,
goto (from iindex= 11 to iindex = 9),
return,
return,
5 = invokestatic < Application, Landroid/os/Binder, clearCallingIdentity()J > @5 exception:4,
6 = getfield < Application, Lcom/android/server/oemlock/OemLockService$2, this$0, <Application,Lcom/android/server/oemlock/OemLockService> > 1,
8 = invokestatic < Application, Lcom/android/server/oemlock/OemLockService, -$$Nest$fgetmOemLock(Lcom/android/server/oemlock/OemLockService;)Lcom/android/server/oemlock/OemLock; > 6 @11 exception:7,
10 = invokevirtual < Application, Lcom/android/server/oemlock/OemLock, isOemUnlockAllowedByCarrier()Z > 8 @15 exception:9,
conditional branch(eq, to iindex=-1) 10,11,
12 = getfield < Application, Lcom/android/server/oemlock/OemLockService$2, this$0, <Application,Lcom/android/server/oemlock/OemLockService> > 1,
14 = invokestatic < Application, Lcom/android/server/oemlock/OemLockService, -$$Nest$fgetmOemLock(Lcom/android/server/oemlock/OemLockService;)Lcom/android/server/oemlock/OemLock; > 12 @23 exception:13,
16 = invokevirtual < Application, Lcom/android/server/oemlock/OemLock, isOemUnlockAllowedByDevice()Z > 14 @27 exception:15,
conditional branch(eq, to iindex=-1) 16,11,
goto (from iindex= 17 to iindex = 2),
21 = phi  20,11,
24 = getfield < Application, Lcom/android/server/oemlock/OemLockService$2, this$0, <Application,Lcom/android/server/oemlock/OemLockService> > 1,
invokestatic < Application, Lcom/android/server/oemlock/OemLockService, -$$Nest$msetPersistentDataBlockOemUnlockAllowedBit(Lcom/android/server/oemlock/OemLockService;Z)V > 24,21 @38 exception:25,
invokevirtual < Application, Lcom/android/server/oemlock/OemLockService, setPersistentDataBlockOemUnlockAllowedBit(Z)V > 1,2 @0 exception:3,
3 = load_metadata: <Application,Lcom/android/server/PersistentDataBlockManagerInternal>, <Primordial,Ljava/lang/Class>,
5 = invokestatic < Application, Lcom/android/server/LocalServices, getService(Ljava/lang/Class;)Ljava/lang/Object; > 3 @2 exception:4,
6 = checkcast <Application,Lcom/android/server/PersistentDataBlockManagerInternal>5 <Application,Lcom/android/server/PersistentDataBlockManagerInternal>,
conditional branch(eq, to iindex=-1) 6,7,
8 = getfield < Application, Lcom/android/server/oemlock/OemLockService, mOemLock, <Application,Lcom/android/server/oemlock/OemLock> > 1,
9 = instanceof 8 <Application,Lcom/android/server/oemlock/PersistentDataBlockLock>,
conditional branch(ne, to iindex=-1) 9,7,
10 = new <Application,Ljava/lang/StringBuilder>@16,
invokespecial < Application, Ljava/lang/StringBuilder, <init>()V > 10 @18 exception:11,
14 = invokevirtual < Application, Ljava/lang/StringBuilder, append(Ljava/lang/String;)Ljava/lang/StringBuilder; > 10,12 @23 exception:13,
16 = invokevirtual < Application, Ljava/lang/StringBuilder, append(Z)Ljava/lang/StringBuilder; > 10,2 @26 exception:15,
18 = invokevirtual < Application, Ljava/lang/StringBuilder, toString()Ljava/lang/String; > 10 @29 exception:17,
21 = invokestatic < Application, Landroid/util/Slog, i(Ljava/lang/String;Ljava/lang/String;)I > 19,18 @35 exception:20,
invokeinterface < Application, Lcom/android/server/PersistentDataBlockManagerInternal, forceOemUnlockEnabled(Z)V > 6,2 @38 exception:22,
return,
return,
invokestatic < Application, Landroid/os/Binder, restoreCallingIdentity(J)V > 5 @41 exception:32,
return 21,","depth : 0
public boolean isOemUnlockAllowed(){
	OemLockService.-$$Nest$menforceOemUnlockReadPermission(this.this$0);
	long v2 = Binder.clearCallingIdentity();
	OemLock v3 = OemLockService.-$$Nest$fgetmOemLock(this.this$0);
	boolean v4 = v3.isOemUnlockAllowedByCarrier();
	OemLock v5 = OemLockService.-$$Nest$fgetmOemLock(this.this$0);
	boolean v6 = v5.isOemUnlockAllowedByDevice();
	OemLockService.-$$Nest$msetPersistentDataBlockOemUnlockAllowedBit(this.this$0, phiInstruction);
	Binder.restoreCallingIdentity(v2);
	return phiInstruction;
}
-----
depth : 1
public void -$$Nest$menforceOemUnlockReadPermission(OemLockService p1){
	p1.enforceOemUnlockReadPermission();
	return;
}
-----
depth : 2
public void enforceOemUnlockReadPermission(){
	return;
}
-----
depth : 1
public void -$$Nest$msetPersistentDataBlockOemUnlockAllowedBit(OemLockService p1, boolean p2){
	p1.setPersistentDataBlockOemUnlockAllowedBit(p2);
	return;
}
-----
depth : 2
public void setPersistentDataBlockOemUnlockAllowedBit(boolean p1){
	Object v1 = LocalServices.getService(PersistentDataBlockManagerInterna.class);
	StringBuilder v1 = new StringBuilder();
	StringBuilder v3 = v1.append(""Update OEM Unlock bit in pst partition to "");
	StringBuilder v4 = v1.append(p1);
	String v5 = v1.toString();
	int v6 = Slog.i(""OemLock"", v5);
	v1.forceOemUnlockEnabled(p1);
	return;
}
-----
","public boolean isOemUnlockAllowed(){
	long v5 = Binder.clearCallingIdentity();
	OemLock v6 = OemLockService.-$$Nest$fgetmOemLock(this.this$0);
	boolean v7 = v6.isOemUnlockAllowedByCarrier();
	OemLock v8 = OemLockService.-$$Nest$fgetmOemLock(this.this$0);
	boolean v9 = v8.isOemUnlockAllowedByDevice();
	Object v12 = LocalServices.getService(PersistentDataBlockManagerInterna.class);
	v12.forceOemUnlockEnabled(p2);
	Binder.restoreCallingIdentity(v5);
	return phiInstruction;
}
","SYS_OR_SIG"
"Lcom/android/server/oemlock/OemLockService$2","isOemUnlockAllowed()Z","2","2 = getfield < Application, Lcom/android/server/oemlock/OemLockService$2, this$0, <Application,Lcom/android/server/oemlock/OemLockService> > 1,
invokestatic < Application, Lcom/android/server/oemlock/OemLockService, -$$Nest$menforceOemUnlockReadPermission(Lcom/android/server/oemlock/OemLockService;)V > 2 @2 exception:3,
invokevirtual < Application, Lcom/android/server/oemlock/OemLockService, enforceOemUnlockReadPermission()V > 1 @0 exception:2,
2 = getfield < Application, Lcom/android/server/oemlock/OemLockService, mContext, <Application,Landroid/content/Context> > 1,
5 = invokevirtual < Application, Landroid/content/Context, checkCallingOrSelfPermission(Ljava/lang/String;)I > 2,3 @4 exception:4,
conditional branch(ne, to iindex=-1) 5,6,
7 = getfield < Application, Lcom/android/server/oemlock/OemLockService, mContext, <Application,Landroid/content/Context> > 1,
10 = invokevirtual < Application, Landroid/content/Context, checkCallingOrSelfPermission(Ljava/lang/String;)I > 7,8 @15 exception:9,
conditional branch(eq, to iindex=-1) 10,6,
goto (from iindex= 11 to iindex = 9),
return,
return,
5 = invokestatic < Application, Landroid/os/Binder, clearCallingIdentity()J > @5 exception:4,
6 = getfield < Application, Lcom/android/server/oemlock/OemLockService$2, this$0, <Application,Lcom/android/server/oemlock/OemLockService> > 1,
8 = invokestatic < Application, Lcom/android/server/oemlock/OemLockService, -$$Nest$fgetmOemLock(Lcom/android/server/oemlock/OemLockService;)Lcom/android/server/oemlock/OemLock; > 6 @11 exception:7,
10 = invokevirtual < Application, Lcom/android/server/oemlock/OemLock, isOemUnlockAllowedByCarrier()Z > 8 @15 exception:9,
conditional branch(eq, to iindex=-1) 10,11,
12 = getfield < Application, Lcom/android/server/oemlock/OemLockService$2, this$0, <Application,Lcom/android/server/oemlock/OemLockService> > 1,
14 = invokestatic < Application, Lcom/android/server/oemlock/OemLockService, -$$Nest$fgetmOemLock(Lcom/android/server/oemlock/OemLockService;)Lcom/android/server/oemlock/OemLock; > 12 @23 exception:13,
16 = invokevirtual < Application, Lcom/android/server/oemlock/OemLock, isOemUnlockAllowedByDevice()Z > 14 @27 exception:15,
conditional branch(eq, to iindex=-1) 16,11,
21 = phi  20,11,
24 = getfield < Application, Lcom/android/server/oemlock/OemLockService$2, this$0, <Application,Lcom/android/server/oemlock/OemLockService> > 1,
invokestatic < Application, Lcom/android/server/oemlock/OemLockService, -$$Nest$msetPersistentDataBlockOemUnlockAllowedBit(Lcom/android/server/oemlock/OemLockService;Z)V > 24,21 @38 exception:25,
invokevirtual < Application, Lcom/android/server/oemlock/OemLockService, setPersistentDataBlockOemUnlockAllowedBit(Z)V > 1,2 @0 exception:3,
3 = load_metadata: <Application,Lcom/android/server/PersistentDataBlockManagerInternal>, <Primordial,Ljava/lang/Class>,
5 = invokestatic < Application, Lcom/android/server/LocalServices, getService(Ljava/lang/Class;)Ljava/lang/Object; > 3 @2 exception:4,
6 = checkcast <Application,Lcom/android/server/PersistentDataBlockManagerInternal>5 <Application,Lcom/android/server/PersistentDataBlockManagerInternal>,
conditional branch(eq, to iindex=-1) 6,7,
8 = getfield < Application, Lcom/android/server/oemlock/OemLockService, mOemLock, <Application,Lcom/android/server/oemlock/OemLock> > 1,
9 = instanceof 8 <Application,Lcom/android/server/oemlock/PersistentDataBlockLock>,
conditional branch(ne, to iindex=-1) 9,7,
10 = new <Application,Ljava/lang/StringBuilder>@16,
invokespecial < Application, Ljava/lang/StringBuilder, <init>()V > 10 @18 exception:11,
14 = invokevirtual < Application, Ljava/lang/StringBuilder, append(Ljava/lang/String;)Ljava/lang/StringBuilder; > 10,12 @23 exception:13,
16 = invokevirtual < Application, Ljava/lang/StringBuilder, append(Z)Ljava/lang/StringBuilder; > 10,2 @26 exception:15,
18 = invokevirtual < Application, Ljava/lang/StringBuilder, toString()Ljava/lang/String; > 10 @29 exception:17,
21 = invokestatic < Application, Landroid/util/Slog, i(Ljava/lang/String;Ljava/lang/String;)I > 19,18 @35 exception:20,
invokeinterface < Application, Lcom/android/server/PersistentDataBlockManagerInternal, forceOemUnlockEnabled(Z)V > 6,2 @38 exception:22,
return,
return,
invokestatic < Application, Landroid/os/Binder, restoreCallingIdentity(J)V > 5 @41 exception:32,
return 21,","depth : 0
public boolean isOemUnlockAllowed(){
	OemLockService.-$$Nest$menforceOemUnlockReadPermission(this.this$0);
	long v2 = Binder.clearCallingIdentity();
	OemLock v3 = OemLockService.-$$Nest$fgetmOemLock(this.this$0);
	boolean v4 = v3.isOemUnlockAllowedByCarrier();
	OemLock v5 = OemLockService.-$$Nest$fgetmOemLock(this.this$0);
	boolean v6 = v5.isOemUnlockAllowedByDevice();
	OemLockService.-$$Nest$msetPersistentDataBlockOemUnlockAllowedBit(this.this$0, phiInstruction);
	Binder.restoreCallingIdentity(v2);
	return phiInstruction;
}
-----
depth : 1
public void -$$Nest$menforceOemUnlockReadPermission(OemLockService p1){
	p1.enforceOemUnlockReadPermission();
	return;
}
-----
depth : 2
public void enforceOemUnlockReadPermission(){
	return;
}
-----
depth : 1
public void -$$Nest$msetPersistentDataBlockOemUnlockAllowedBit(OemLockService p1, boolean p2){
	p1.setPersistentDataBlockOemUnlockAllowedBit(p2);
	return;
}
-----
depth : 2
public void setPersistentDataBlockOemUnlockAllowedBit(boolean p1){
	Object v1 = LocalServices.getService(PersistentDataBlockManagerInterna.class);
	StringBuilder v1 = new StringBuilder();
	StringBuilder v3 = v1.append(""Update OEM Unlock bit in pst partition to "");
	StringBuilder v4 = v1.append(p1);
	String v5 = v1.toString();
	int v6 = Slog.i(""OemLock"", v5);
	v1.forceOemUnlockEnabled(p1);
	return;
}
-----
","public boolean isOemUnlockAllowed(){
	long v5 = Binder.clearCallingIdentity();
	OemLock v6 = OemLockService.-$$Nest$fgetmOemLock(this.this$0);
	boolean v7 = v6.isOemUnlockAllowedByCarrier();
	OemLock v8 = OemLockService.-$$Nest$fgetmOemLock(this.this$0);
	boolean v9 = v8.isOemUnlockAllowedByDevice();
	Object v12 = LocalServices.getService(PersistentDataBlockManagerInterna.class);
	v12.forceOemUnlockEnabled(p2);
	Binder.restoreCallingIdentity(v5);
	return phiInstruction;
}
","SYS_OR_SIG"
"Lcom/android/server/oemlock/OemLockService$2","isOemUnlockAllowed()Z","2","2 = getfield < Application, Lcom/android/server/oemlock/OemLockService$2, this$0, <Application,Lcom/android/server/oemlock/OemLockService> > 1,
invokestatic < Application, Lcom/android/server/oemlock/OemLockService, -$$Nest$menforceOemUnlockReadPermission(Lcom/android/server/oemlock/OemLockService;)V > 2 @2 exception:3,
invokevirtual < Application, Lcom/android/server/oemlock/OemLockService, enforceOemUnlockReadPermission()V > 1 @0 exception:2,
2 = getfield < Application, Lcom/android/server/oemlock/OemLockService, mContext, <Application,Landroid/content/Context> > 1,
5 = invokevirtual < Application, Landroid/content/Context, checkCallingOrSelfPermission(Ljava/lang/String;)I > 2,3 @4 exception:4,
conditional branch(ne, to iindex=-1) 5,6,
return,
return,
5 = invokestatic < Application, Landroid/os/Binder, clearCallingIdentity()J > @5 exception:4,
6 = getfield < Application, Lcom/android/server/oemlock/OemLockService$2, this$0, <Application,Lcom/android/server/oemlock/OemLockService> > 1,
8 = invokestatic < Application, Lcom/android/server/oemlock/OemLockService, -$$Nest$fgetmOemLock(Lcom/android/server/oemlock/OemLockService;)Lcom/android/server/oemlock/OemLock; > 6 @11 exception:7,
10 = invokevirtual < Application, Lcom/android/server/oemlock/OemLock, isOemUnlockAllowedByCarrier()Z > 8 @15 exception:9,
conditional branch(eq, to iindex=-1) 10,11,
12 = getfield < Application, Lcom/android/server/oemlock/OemLockService$2, this$0, <Application,Lcom/android/server/oemlock/OemLockService> > 1,
14 = invokestatic < Application, Lcom/android/server/oemlock/OemLockService, -$$Nest$fgetmOemLock(Lcom/android/server/oemlock/OemLockService;)Lcom/android/server/oemlock/OemLock; > 12 @23 exception:13,
16 = invokevirtual < Application, Lcom/android/server/oemlock/OemLock, isOemUnlockAllowedByDevice()Z > 14 @27 exception:15,
conditional branch(eq, to iindex=-1) 16,11,
goto (from iindex= 17 to iindex = 2),
21 = phi  20,11,
24 = getfield < Application, Lcom/android/server/oemlock/OemLockService$2, this$0, <Application,Lcom/android/server/oemlock/OemLockService> > 1,
invokestatic < Application, Lcom/android/server/oemlock/OemLockService, -$$Nest$msetPersistentDataBlockOemUnlockAllowedBit(Lcom/android/server/oemlock/OemLockService;Z)V > 24,21 @38 exception:25,
invokevirtual < Application, Lcom/android/server/oemlock/OemLockService, setPersistentDataBlockOemUnlockAllowedBit(Z)V > 1,2 @0 exception:3,
3 = load_metadata: <Application,Lcom/android/server/PersistentDataBlockManagerInternal>, <Primordial,Ljava/lang/Class>,
5 = invokestatic < Application, Lcom/android/server/LocalServices, getService(Ljava/lang/Class;)Ljava/lang/Object; > 3 @2 exception:4,
6 = checkcast <Application,Lcom/android/server/PersistentDataBlockManagerInternal>5 <Application,Lcom/android/server/PersistentDataBlockManagerInternal>,
conditional branch(eq, to iindex=-1) 6,7,
8 = getfield < Application, Lcom/android/server/oemlock/OemLockService, mOemLock, <Application,Lcom/android/server/oemlock/OemLock> > 1,
9 = instanceof 8 <Application,Lcom/android/server/oemlock/PersistentDataBlockLock>,
conditional branch(ne, to iindex=-1) 9,7,
10 = new <Application,Ljava/lang/StringBuilder>@16,
invokespecial < Application, Ljava/lang/StringBuilder, <init>()V > 10 @18 exception:11,
14 = invokevirtual < Application, Ljava/lang/StringBuilder, append(Ljava/lang/String;)Ljava/lang/StringBuilder; > 10,12 @23 exception:13,
16 = invokevirtual < Application, Ljava/lang/StringBuilder, append(Z)Ljava/lang/StringBuilder; > 10,2 @26 exception:15,
18 = invokevirtual < Application, Ljava/lang/StringBuilder, toString()Ljava/lang/String; > 10 @29 exception:17,
21 = invokestatic < Application, Landroid/util/Slog, i(Ljava/lang/String;Ljava/lang/String;)I > 19,18 @35 exception:20,
invokeinterface < Application, Lcom/android/server/PersistentDataBlockManagerInternal, forceOemUnlockEnabled(Z)V > 6,2 @38 exception:22,
return,
return,
invokestatic < Application, Landroid/os/Binder, restoreCallingIdentity(J)V > 5 @41 exception:32,
return 21,","depth : 0
public boolean isOemUnlockAllowed(){
	OemLockService.-$$Nest$menforceOemUnlockReadPermission(this.this$0);
	long v2 = Binder.clearCallingIdentity();
	OemLock v3 = OemLockService.-$$Nest$fgetmOemLock(this.this$0);
	boolean v4 = v3.isOemUnlockAllowedByCarrier();
	OemLock v5 = OemLockService.-$$Nest$fgetmOemLock(this.this$0);
	boolean v6 = v5.isOemUnlockAllowedByDevice();
	OemLockService.-$$Nest$msetPersistentDataBlockOemUnlockAllowedBit(this.this$0, phiInstruction);
	Binder.restoreCallingIdentity(v2);
	return phiInstruction;
}
-----
depth : 1
public void -$$Nest$menforceOemUnlockReadPermission(OemLockService p1){
	p1.enforceOemUnlockReadPermission();
	return;
}
-----
depth : 2
public void enforceOemUnlockReadPermission(){
	return;
}
-----
depth : 1
public void -$$Nest$msetPersistentDataBlockOemUnlockAllowedBit(OemLockService p1, boolean p2){
	p1.setPersistentDataBlockOemUnlockAllowedBit(p2);
	return;
}
-----
depth : 2
public void setPersistentDataBlockOemUnlockAllowedBit(boolean p1){
	Object v1 = LocalServices.getService(PersistentDataBlockManagerInterna.class);
	StringBuilder v1 = new StringBuilder();
	StringBuilder v3 = v1.append(""Update OEM Unlock bit in pst partition to "");
	StringBuilder v4 = v1.append(p1);
	String v5 = v1.toString();
	int v6 = Slog.i(""OemLock"", v5);
	v1.forceOemUnlockEnabled(p1);
	return;
}
-----
","public boolean isOemUnlockAllowed(){
	long v4 = Binder.clearCallingIdentity();
	OemLock v5 = OemLockService.-$$Nest$fgetmOemLock(this.this$0);
	boolean v6 = v5.isOemUnlockAllowedByCarrier();
	OemLock v7 = OemLockService.-$$Nest$fgetmOemLock(this.this$0);
	boolean v8 = v7.isOemUnlockAllowedByDevice();
	Object v11 = LocalServices.getService(PersistentDataBlockManagerInterna.class);
	v11.forceOemUnlockEnabled(p2);
	Binder.restoreCallingIdentity(v4);
	return phiInstruction;
}
","SYS_OR_SIG"

"Lcom/android/server/oemlock/OemLockService$2","isOemUnlockAllowedByCarrier()Z","0","2 = getfield < Application, Lcom/android/server/oemlock/OemLockService$2, this$0, <Application,Lcom/android/server/oemlock/OemLockService> > 1,
invokestatic < Application, Lcom/android/server/oemlock/OemLockService, -$$Nest$menforceManageCarrierOemUnlockPermission(Lcom/android/server/oemlock/OemLockService;)V > 2 @2 exception:3,
5 = invokestatic < Application, Landroid/os/Binder, clearCallingIdentity()J > @5 exception:4,
6 = getfield < Application, Lcom/android/server/oemlock/OemLockService$2, this$0, <Application,Lcom/android/server/oemlock/OemLockService> > 1,
8 = invokestatic < Application, Lcom/android/server/oemlock/OemLockService, -$$Nest$fgetmOemLock(Lcom/android/server/oemlock/OemLockService;)Lcom/android/server/oemlock/OemLock; > 6 @11 exception:7,
10 = invokevirtual < Application, Lcom/android/server/oemlock/OemLock, isOemUnlockAllowedByCarrier()Z > 8 @15 exception:9,
invokestatic < Application, Landroid/os/Binder, restoreCallingIdentity(J)V > 5 @19 exception:16,
return 10,","depth : 0
public boolean isOemUnlockAllowedByCarrier(){
	OemLockService.-$$Nest$menforceManageCarrierOemUnlockPermission(this.this$0);
	long v2 = Binder.clearCallingIdentity();
	OemLock v3 = OemLockService.-$$Nest$fgetmOemLock(this.this$0);
	boolean v4 = v3.isOemUnlockAllowedByCarrier();
	Binder.restoreCallingIdentity(v2);
	return v4;
}
-----
","public boolean isOemUnlockAllowedByCarrier(){
	OemLockService.-$$Nest$menforceManageCarrierOemUnlockPermission(this.this$0);
	long v2 = Binder.clearCallingIdentity();
	OemLock v3 = OemLockService.-$$Nest$fgetmOemLock(this.this$0);
	boolean v4 = v3.isOemUnlockAllowedByCarrier();
	Binder.restoreCallingIdentity(v2);
	return v4;
}
","SYS_OR_SIG"
"Lcom/android/server/oemlock/OemLockService$2","isOemUnlockAllowedByCarrier()Z","1","2 = getfield < Application, Lcom/android/server/oemlock/OemLockService$2, this$0, <Application,Lcom/android/server/oemlock/OemLockService> > 1,
invokestatic < Application, Lcom/android/server/oemlock/OemLockService, -$$Nest$menforceManageCarrierOemUnlockPermission(Lcom/android/server/oemlock/OemLockService;)V > 2 @2 exception:3,
invokevirtual < Application, Lcom/android/server/oemlock/OemLockService, enforceManageCarrierOemUnlockPermission()V > 1 @0 exception:2,
return,
5 = invokestatic < Application, Landroid/os/Binder, clearCallingIdentity()J > @5 exception:4,
6 = getfield < Application, Lcom/android/server/oemlock/OemLockService$2, this$0, <Application,Lcom/android/server/oemlock/OemLockService> > 1,
8 = invokestatic < Application, Lcom/android/server/oemlock/OemLockService, -$$Nest$fgetmOemLock(Lcom/android/server/oemlock/OemLockService;)Lcom/android/server/oemlock/OemLock; > 6 @11 exception:7,
2 = getfield < Application, Lcom/android/server/oemlock/OemLockService, mOemLock, <Application,Lcom/android/server/oemlock/OemLock> > 1,
return 2,
10 = invokevirtual < Application, Lcom/android/server/oemlock/OemLock, isOemUnlockAllowedByCarrier()Z > 8 @15 exception:9,
invokestatic < Application, Landroid/os/Binder, restoreCallingIdentity(J)V > 5 @19 exception:16,
return 10,","depth : 0
public boolean isOemUnlockAllowedByCarrier(){
	OemLockService.-$$Nest$menforceManageCarrierOemUnlockPermission(this.this$0);
	long v2 = Binder.clearCallingIdentity();
	OemLock v3 = OemLockService.-$$Nest$fgetmOemLock(this.this$0);
	boolean v4 = v3.isOemUnlockAllowedByCarrier();
	Binder.restoreCallingIdentity(v2);
	return v4;
}
-----
depth : 1
public void -$$Nest$menforceManageCarrierOemUnlockPermission(OemLockService p1){
	p1.enforceManageCarrierOemUnlockPermission();
	return;
}
-----
depth : 1
public OemLock -$$Nest$fgetmOemLock(OemLockService p1){
	return this.mOemLock;
}
-----
","public boolean isOemUnlockAllowedByCarrier(){
	this.this$0.enforceManageCarrierOemUnlockPermission();
	long v3 = Binder.clearCallingIdentity();
	OemLock v4 = this.mOemLock;
	boolean v5 = v4.isOemUnlockAllowedByCarrier();
	Binder.restoreCallingIdentity(v3);
	return v5;
}
","SYS_OR_SIG"
"Lcom/android/server/oemlock/OemLockService$2","isOemUnlockAllowedByCarrier()Z","2","2 = getfield < Application, Lcom/android/server/oemlock/OemLockService$2, this$0, <Application,Lcom/android/server/oemlock/OemLockService> > 1,
invokestatic < Application, Lcom/android/server/oemlock/OemLockService, -$$Nest$menforceManageCarrierOemUnlockPermission(Lcom/android/server/oemlock/OemLockService;)V > 2 @2 exception:3,
invokevirtual < Application, Lcom/android/server/oemlock/OemLockService, enforceManageCarrierOemUnlockPermission()V > 1 @0 exception:2,
2 = getfield < Application, Lcom/android/server/oemlock/OemLockService, mContext, <Application,Landroid/content/Context> > 1,
invokevirtual < Application, Landroid/content/Context, enforceCallingOrSelfPermission(Ljava/lang/String;Ljava/lang/String;)V > 2,3,4 @6 exception:5,
return,
return,
5 = invokestatic < Application, Landroid/os/Binder, clearCallingIdentity()J > @5 exception:4,
6 = getfield < Application, Lcom/android/server/oemlock/OemLockService$2, this$0, <Application,Lcom/android/server/oemlock/OemLockService> > 1,
8 = invokestatic < Application, Lcom/android/server/oemlock/OemLockService, -$$Nest$fgetmOemLock(Lcom/android/server/oemlock/OemLockService;)Lcom/android/server/oemlock/OemLock; > 6 @11 exception:7,
10 = invokevirtual < Application, Lcom/android/server/oemlock/OemLock, isOemUnlockAllowedByCarrier()Z > 8 @15 exception:9,
invokestatic < Application, Landroid/os/Binder, restoreCallingIdentity(J)V > 5 @19 exception:16,
return 10,","depth : 0
public boolean isOemUnlockAllowedByCarrier(){
	OemLockService.-$$Nest$menforceManageCarrierOemUnlockPermission(this.this$0);
	long v2 = Binder.clearCallingIdentity();
	OemLock v3 = OemLockService.-$$Nest$fgetmOemLock(this.this$0);
	boolean v4 = v3.isOemUnlockAllowedByCarrier();
	Binder.restoreCallingIdentity(v2);
	return v4;
}
-----
depth : 1
public void -$$Nest$menforceManageCarrierOemUnlockPermission(OemLockService p1){
	p1.enforceManageCarrierOemUnlockPermission();
	return;
}
-----
depth : 2
public void enforceManageCarrierOemUnlockPermission(){
	return;
}
-----
","public boolean isOemUnlockAllowedByCarrier(){
	long v4 = Binder.clearCallingIdentity();
	OemLock v5 = OemLockService.-$$Nest$fgetmOemLock(this.this$0);
	boolean v6 = v5.isOemUnlockAllowedByCarrier();
	Binder.restoreCallingIdentity(v4);
	return v6;
}
","SYS_OR_SIG"

"Lcom/android/server/oemlock/OemLockService$2","isDeviceOemUnlocked()Z","0","2 = getfield < Application, Lcom/android/server/oemlock/OemLockService$2, this$0, <Application,Lcom/android/server/oemlock/OemLockService> > 1,
invokestatic < Application, Lcom/android/server/oemlock/OemLockService, -$$Nest$menforceOemUnlockReadPermission(Lcom/android/server/oemlock/OemLockService;)V > 2 @2 exception:3,
6 = invokestatic < Application, Landroid/os/SystemProperties, get(Ljava/lang/String;)Ljava/lang/String; > 4 @8 exception:5,
8 = invokevirtual < Application, Ljava/lang/String, hashCode()I > 6 @12 exception:7,
11 = invokevirtual < Application, Ljava/lang/String, equals(Ljava/lang/Object;)Z > 6,9 @17 exception:10,
conditional branch(ne, to iindex=-1) 11,12,
return 12,","depth : 0
public boolean isDeviceOemUnlocked(){
	OemLockService.-$$Nest$menforceOemUnlockReadPermission(this.this$0);
	String v2 = SystemProperties.get(""ro.boot.flash.locked"");
	int v3 = v2.hashCode();
	boolean v4 = v2.equals(""0"");
	return 0;
}
-----
","public boolean isDeviceOemUnlocked(){
	OemLockService.-$$Nest$menforceOemUnlockReadPermission(this.this$0);
	String v2 = SystemProperties.get(""ro.boot.flash.locked"");
	int v3 = v2.hashCode();
	boolean v4 = v2.equals(""0"");
	return 0;
}
","SYS_OR_SIG"
"Lcom/android/server/oemlock/OemLockService$2","isDeviceOemUnlocked()Z","1","2 = getfield < Application, Lcom/android/server/oemlock/OemLockService$2, this$0, <Application,Lcom/android/server/oemlock/OemLockService> > 1,
invokestatic < Application, Lcom/android/server/oemlock/OemLockService, -$$Nest$menforceOemUnlockReadPermission(Lcom/android/server/oemlock/OemLockService;)V > 2 @2 exception:3,
invokevirtual < Application, Lcom/android/server/oemlock/OemLockService, enforceOemUnlockReadPermission()V > 1 @0 exception:2,
return,
6 = invokestatic < Application, Landroid/os/SystemProperties, get(Ljava/lang/String;)Ljava/lang/String; > 4 @8 exception:5,
8 = invokevirtual < Application, Ljava/lang/String, hashCode()I > 6 @12 exception:7,
11 = invokevirtual < Application, Ljava/lang/String, equals(Ljava/lang/Object;)Z > 6,9 @17 exception:10,
conditional branch(ne, to iindex=-1) 11,12,
return 12,","depth : 0
public boolean isDeviceOemUnlocked(){
	OemLockService.-$$Nest$menforceOemUnlockReadPermission(this.this$0);
	String v2 = SystemProperties.get(""ro.boot.flash.locked"");
	int v3 = v2.hashCode();
	boolean v4 = v2.equals(""0"");
	return 0;
}
-----
depth : 1
public void -$$Nest$menforceOemUnlockReadPermission(OemLockService p1){
	p1.enforceOemUnlockReadPermission();
	return;
}
-----
","public boolean isDeviceOemUnlocked(){
	this.this$0.enforceOemUnlockReadPermission();
	String v3 = SystemProperties.get(""ro.boot.flash.locked"");
	int v4 = v3.hashCode();
	boolean v5 = v3.equals(""0"");
	return 0;
}
","SYS_OR_SIG"
"Lcom/android/server/oemlock/OemLockService$2","isDeviceOemUnlocked()Z","1","2 = getfield < Application, Lcom/android/server/oemlock/OemLockService$2, this$0, <Application,Lcom/android/server/oemlock/OemLockService> > 1,
invokestatic < Application, Lcom/android/server/oemlock/OemLockService, -$$Nest$menforceOemUnlockReadPermission(Lcom/android/server/oemlock/OemLockService;)V > 2 @2 exception:3,
invokevirtual < Application, Lcom/android/server/oemlock/OemLockService, enforceOemUnlockReadPermission()V > 1 @0 exception:2,
return,
6 = invokestatic < Application, Landroid/os/SystemProperties, get(Ljava/lang/String;)Ljava/lang/String; > 4 @8 exception:5,
8 = invokevirtual < Application, Ljava/lang/String, hashCode()I > 6 @12 exception:7,
11 = invokevirtual < Application, Ljava/lang/String, equals(Ljava/lang/Object;)Z > 6,9 @17 exception:10,
conditional branch(ne, to iindex=-1) 11,12,
return 13,","depth : 0
public boolean isDeviceOemUnlocked(){
	OemLockService.-$$Nest$menforceOemUnlockReadPermission(this.this$0);
	String v2 = SystemProperties.get(""ro.boot.flash.locked"");
	int v3 = v2.hashCode();
	boolean v4 = v2.equals(""0"");
	return 1;
}
-----
depth : 1
public void -$$Nest$menforceOemUnlockReadPermission(OemLockService p1){
	p1.enforceOemUnlockReadPermission();
	return;
}
-----
","public boolean isDeviceOemUnlocked(){
	this.this$0.enforceOemUnlockReadPermission();
	String v3 = SystemProperties.get(""ro.boot.flash.locked"");
	int v4 = v3.hashCode();
	boolean v5 = v3.equals(""0"");
	return 1;
}
","SYS_OR_SIG"
"Lcom/android/server/oemlock/OemLockService$2","isDeviceOemUnlocked()Z","2","2 = getfield < Application, Lcom/android/server/oemlock/OemLockService$2, this$0, <Application,Lcom/android/server/oemlock/OemLockService> > 1,
invokestatic < Application, Lcom/android/server/oemlock/OemLockService, -$$Nest$menforceOemUnlockReadPermission(Lcom/android/server/oemlock/OemLockService;)V > 2 @2 exception:3,
invokevirtual < Application, Lcom/android/server/oemlock/OemLockService, enforceOemUnlockReadPermission()V > 1 @0 exception:2,
2 = getfield < Application, Lcom/android/server/oemlock/OemLockService, mContext, <Application,Landroid/content/Context> > 1,
5 = invokevirtual < Application, Landroid/content/Context, checkCallingOrSelfPermission(Ljava/lang/String;)I > 2,3 @4 exception:4,
conditional branch(ne, to iindex=-1) 5,6,
7 = getfield < Application, Lcom/android/server/oemlock/OemLockService, mContext, <Application,Landroid/content/Context> > 1,
10 = invokevirtual < Application, Landroid/content/Context, checkCallingOrSelfPermission(Ljava/lang/String;)I > 7,8 @15 exception:9,
conditional branch(eq, to iindex=-1) 10,6,
goto (from iindex= 11 to iindex = 9),
return,
return,
6 = invokestatic < Application, Landroid/os/SystemProperties, get(Ljava/lang/String;)Ljava/lang/String; > 4 @8 exception:5,
8 = invokevirtual < Application, Ljava/lang/String, hashCode()I > 6 @12 exception:7,
11 = invokevirtual < Application, Ljava/lang/String, equals(Ljava/lang/Object;)Z > 6,9 @17 exception:10,
conditional branch(ne, to iindex=-1) 11,12,
return 12,","depth : 0
public boolean isDeviceOemUnlocked(){
	OemLockService.-$$Nest$menforceOemUnlockReadPermission(this.this$0);
	String v2 = SystemProperties.get(""ro.boot.flash.locked"");
	int v3 = v2.hashCode();
	boolean v4 = v2.equals(""0"");
	return 0;
}
-----
depth : 1
public void -$$Nest$menforceOemUnlockReadPermission(OemLockService p1){
	p1.enforceOemUnlockReadPermission();
	return;
}
-----
depth : 2
public void enforceOemUnlockReadPermission(){
	return;
}
-----
","public boolean isDeviceOemUnlocked(){
	String v5 = SystemProperties.get(""ro.boot.flash.locked"");
	int v6 = v5.hashCode();
	boolean v7 = v5.equals(""0"");
	return 0;
}
","SYS_OR_SIG"
"Lcom/android/server/oemlock/OemLockService$2","isDeviceOemUnlocked()Z","2","2 = getfield < Application, Lcom/android/server/oemlock/OemLockService$2, this$0, <Application,Lcom/android/server/oemlock/OemLockService> > 1,
invokestatic < Application, Lcom/android/server/oemlock/OemLockService, -$$Nest$menforceOemUnlockReadPermission(Lcom/android/server/oemlock/OemLockService;)V > 2 @2 exception:3,
invokevirtual < Application, Lcom/android/server/oemlock/OemLockService, enforceOemUnlockReadPermission()V > 1 @0 exception:2,
2 = getfield < Application, Lcom/android/server/oemlock/OemLockService, mContext, <Application,Landroid/content/Context> > 1,
5 = invokevirtual < Application, Landroid/content/Context, checkCallingOrSelfPermission(Ljava/lang/String;)I > 2,3 @4 exception:4,
conditional branch(ne, to iindex=-1) 5,6,
7 = getfield < Application, Lcom/android/server/oemlock/OemLockService, mContext, <Application,Landroid/content/Context> > 1,
10 = invokevirtual < Application, Landroid/content/Context, checkCallingOrSelfPermission(Ljava/lang/String;)I > 7,8 @15 exception:9,
conditional branch(eq, to iindex=-1) 10,6,
goto (from iindex= 11 to iindex = 9),
return,
return,
6 = invokestatic < Application, Landroid/os/SystemProperties, get(Ljava/lang/String;)Ljava/lang/String; > 4 @8 exception:5,
8 = invokevirtual < Application, Ljava/lang/String, hashCode()I > 6 @12 exception:7,
11 = invokevirtual < Application, Ljava/lang/String, equals(Ljava/lang/Object;)Z > 6,9 @17 exception:10,
conditional branch(ne, to iindex=-1) 11,12,
return 13,","depth : 0
public boolean isDeviceOemUnlocked(){
	OemLockService.-$$Nest$menforceOemUnlockReadPermission(this.this$0);
	String v2 = SystemProperties.get(""ro.boot.flash.locked"");
	int v3 = v2.hashCode();
	boolean v4 = v2.equals(""0"");
	return 1;
}
-----
depth : 1
public void -$$Nest$menforceOemUnlockReadPermission(OemLockService p1){
	p1.enforceOemUnlockReadPermission();
	return;
}
-----
depth : 2
public void enforceOemUnlockReadPermission(){
	return;
}
-----
","public boolean isDeviceOemUnlocked(){
	String v5 = SystemProperties.get(""ro.boot.flash.locked"");
	int v6 = v5.hashCode();
	boolean v7 = v5.equals(""0"");
	return 1;
}
","SYS_OR_SIG"
"Lcom/android/server/oemlock/OemLockService$2","isDeviceOemUnlocked()Z","2","2 = getfield < Application, Lcom/android/server/oemlock/OemLockService$2, this$0, <Application,Lcom/android/server/oemlock/OemLockService> > 1,
invokestatic < Application, Lcom/android/server/oemlock/OemLockService, -$$Nest$menforceOemUnlockReadPermission(Lcom/android/server/oemlock/OemLockService;)V > 2 @2 exception:3,
invokevirtual < Application, Lcom/android/server/oemlock/OemLockService, enforceOemUnlockReadPermission()V > 1 @0 exception:2,
2 = getfield < Application, Lcom/android/server/oemlock/OemLockService, mContext, <Application,Landroid/content/Context> > 1,
5 = invokevirtual < Application, Landroid/content/Context, checkCallingOrSelfPermission(Ljava/lang/String;)I > 2,3 @4 exception:4,
conditional branch(ne, to iindex=-1) 5,6,
return,
return,
6 = invokestatic < Application, Landroid/os/SystemProperties, get(Ljava/lang/String;)Ljava/lang/String; > 4 @8 exception:5,
8 = invokevirtual < Application, Ljava/lang/String, hashCode()I > 6 @12 exception:7,
11 = invokevirtual < Application, Ljava/lang/String, equals(Ljava/lang/Object;)Z > 6,9 @17 exception:10,
conditional branch(ne, to iindex=-1) 11,12,
return 12,","depth : 0
public boolean isDeviceOemUnlocked(){
	OemLockService.-$$Nest$menforceOemUnlockReadPermission(this.this$0);
	String v2 = SystemProperties.get(""ro.boot.flash.locked"");
	int v3 = v2.hashCode();
	boolean v4 = v2.equals(""0"");
	return 0;
}
-----
depth : 1
public void -$$Nest$menforceOemUnlockReadPermission(OemLockService p1){
	p1.enforceOemUnlockReadPermission();
	return;
}
-----
depth : 2
public void enforceOemUnlockReadPermission(){
	return;
}
-----
","public boolean isDeviceOemUnlocked(){
	String v4 = SystemProperties.get(""ro.boot.flash.locked"");
	int v5 = v4.hashCode();
	boolean v6 = v4.equals(""0"");
	return 0;
}
","SYS_OR_SIG"

"Lcom/android/server/oemlock/OemLockService$2","setOemUnlockAllowedByCarrier(Z[B)V","0","4 = getfield < Application, Lcom/android/server/oemlock/OemLockService$2, this$0, <Application,Lcom/android/server/oemlock/OemLockService> > 1,
invokestatic < Application, Lcom/android/server/oemlock/OemLockService, -$$Nest$menforceManageCarrierOemUnlockPermission(Lcom/android/server/oemlock/OemLockService;)V > 4 @2 exception:5,
6 = getfield < Application, Lcom/android/server/oemlock/OemLockService$2, this$0, <Application,Lcom/android/server/oemlock/OemLockService> > 1,
invokestatic < Application, Lcom/android/server/oemlock/OemLockService, -$$Nest$menforceUserIsAdmin(Lcom/android/server/oemlock/OemLockService;)V > 6 @7 exception:7,
9 = invokestatic < Application, Landroid/os/Binder, clearCallingIdentity()J > @10 exception:8,
10 = getfield < Application, Lcom/android/server/oemlock/OemLockService$2, this$0, <Application,Lcom/android/server/oemlock/OemLockService> > 1,
12 = invokestatic < Application, Lcom/android/server/oemlock/OemLockService, -$$Nest$fgetmOemLock(Lcom/android/server/oemlock/OemLockService;)Lcom/android/server/oemlock/OemLock; > 10 @16 exception:11,
invokevirtual < Application, Lcom/android/server/oemlock/OemLock, setOemUnlockAllowedByCarrier(Z[B)V > 12,2,3 @20 exception:13,
invokestatic < Application, Landroid/os/Binder, restoreCallingIdentity(J)V > 9 @23 exception:19,
return,","depth : 0
public void setOemUnlockAllowedByCarrier(boolean p1, byte[] p2){
	OemLockService.-$$Nest$menforceManageCarrierOemUnlockPermission(this.this$0);
	OemLockService.-$$Nest$menforceUserIsAdmin(this.this$0);
	long v3 = Binder.clearCallingIdentity();
	OemLock v4 = OemLockService.-$$Nest$fgetmOemLock(this.this$0);
	v4.setOemUnlockAllowedByCarrier(p1, p2);
	Binder.restoreCallingIdentity(v3);
	return;
}
-----
","public void setOemUnlockAllowedByCarrier(boolean p1, byte[] p2){
	OemLockService.-$$Nest$menforceManageCarrierOemUnlockPermission(this.this$0);
	OemLockService.-$$Nest$menforceUserIsAdmin(this.this$0);
	long v3 = Binder.clearCallingIdentity();
	OemLock v4 = OemLockService.-$$Nest$fgetmOemLock(this.this$0);
	v4.setOemUnlockAllowedByCarrier(p1, p2);
	Binder.restoreCallingIdentity(v3);
	return;
}
","SYS_OR_SIG"
"Lcom/android/server/oemlock/OemLockService$2","setOemUnlockAllowedByCarrier(Z[B)V","1","4 = getfield < Application, Lcom/android/server/oemlock/OemLockService$2, this$0, <Application,Lcom/android/server/oemlock/OemLockService> > 1,
invokestatic < Application, Lcom/android/server/oemlock/OemLockService, -$$Nest$menforceManageCarrierOemUnlockPermission(Lcom/android/server/oemlock/OemLockService;)V > 4 @2 exception:5,
invokevirtual < Application, Lcom/android/server/oemlock/OemLockService, enforceManageCarrierOemUnlockPermission()V > 1 @0 exception:2,
return,
6 = getfield < Application, Lcom/android/server/oemlock/OemLockService$2, this$0, <Application,Lcom/android/server/oemlock/OemLockService> > 1,
invokestatic < Application, Lcom/android/server/oemlock/OemLockService, -$$Nest$menforceUserIsAdmin(Lcom/android/server/oemlock/OemLockService;)V > 6 @7 exception:7,
invokevirtual < Application, Lcom/android/server/oemlock/OemLockService, enforceUserIsAdmin()V > 1 @0 exception:2,
return,
9 = invokestatic < Application, Landroid/os/Binder, clearCallingIdentity()J > @10 exception:8,
10 = getfield < Application, Lcom/android/server/oemlock/OemLockService$2, this$0, <Application,Lcom/android/server/oemlock/OemLockService> > 1,
12 = invokestatic < Application, Lcom/android/server/oemlock/OemLockService, -$$Nest$fgetmOemLock(Lcom/android/server/oemlock/OemLockService;)Lcom/android/server/oemlock/OemLock; > 10 @16 exception:11,
2 = getfield < Application, Lcom/android/server/oemlock/OemLockService, mOemLock, <Application,Lcom/android/server/oemlock/OemLock> > 1,
return 2,
invokevirtual < Application, Lcom/android/server/oemlock/OemLock, setOemUnlockAllowedByCarrier(Z[B)V > 12,2,3 @20 exception:13,
invokestatic < Application, Landroid/os/Binder, restoreCallingIdentity(J)V > 9 @23 exception:19,
return,","depth : 0
public void setOemUnlockAllowedByCarrier(boolean p1, byte[] p2){
	OemLockService.-$$Nest$menforceManageCarrierOemUnlockPermission(this.this$0);
	OemLockService.-$$Nest$menforceUserIsAdmin(this.this$0);
	long v3 = Binder.clearCallingIdentity();
	OemLock v4 = OemLockService.-$$Nest$fgetmOemLock(this.this$0);
	v4.setOemUnlockAllowedByCarrier(p1, p2);
	Binder.restoreCallingIdentity(v3);
	return;
}
-----
depth : 1
public void -$$Nest$menforceManageCarrierOemUnlockPermission(OemLockService p1){
	p1.enforceManageCarrierOemUnlockPermission();
	return;
}
-----
depth : 1
public void -$$Nest$menforceUserIsAdmin(OemLockService p1){
	p1.enforceUserIsAdmin();
	return;
}
-----
depth : 1
public OemLock -$$Nest$fgetmOemLock(OemLockService p1){
	return this.mOemLock;
}
-----
","public void setOemUnlockAllowedByCarrier(boolean p1, byte[] p2){
	this.this$0.enforceManageCarrierOemUnlockPermission();
	this.this$0.enforceUserIsAdmin();
	long v5 = Binder.clearCallingIdentity();
	OemLock v6 = this.mOemLock;
	v6.setOemUnlockAllowedByCarrier(p1, p2);
	Binder.restoreCallingIdentity(v5);
	return;
}
","SYS_OR_SIG"
"Lcom/android/server/oemlock/OemLockService$2","setOemUnlockAllowedByCarrier(Z[B)V","2","4 = getfield < Application, Lcom/android/server/oemlock/OemLockService$2, this$0, <Application,Lcom/android/server/oemlock/OemLockService> > 1,
invokestatic < Application, Lcom/android/server/oemlock/OemLockService, -$$Nest$menforceManageCarrierOemUnlockPermission(Lcom/android/server/oemlock/OemLockService;)V > 4 @2 exception:5,
invokevirtual < Application, Lcom/android/server/oemlock/OemLockService, enforceManageCarrierOemUnlockPermission()V > 1 @0 exception:2,
2 = getfield < Application, Lcom/android/server/oemlock/OemLockService, mContext, <Application,Landroid/content/Context> > 1,
invokevirtual < Application, Landroid/content/Context, enforceCallingOrSelfPermission(Ljava/lang/String;Ljava/lang/String;)V > 2,3,4 @6 exception:5,
return,
return,
6 = getfield < Application, Lcom/android/server/oemlock/OemLockService$2, this$0, <Application,Lcom/android/server/oemlock/OemLockService> > 1,
invokestatic < Application, Lcom/android/server/oemlock/OemLockService, -$$Nest$menforceUserIsAdmin(Lcom/android/server/oemlock/OemLockService;)V > 6 @7 exception:7,
invokevirtual < Application, Lcom/android/server/oemlock/OemLockService, enforceUserIsAdmin()V > 1 @0 exception:2,
3 = invokestatic < Application, Landroid/os/UserHandle, getCallingUserId()I > @0 exception:2,
5 = invokestatic < Application, Landroid/os/Binder, clearCallingIdentity()J > @4 exception:4,
6 = getfield < Application, Lcom/android/server/oemlock/OemLockService, mContext, <Application,Landroid/content/Context> > 1,
8 = invokestatic < Application, Landroid/os/UserManager, get(Landroid/content/Context;)Landroid/os/UserManager; > 6 @10 exception:7,
10 = invokevirtual < Application, Landroid/os/UserManager, isUserAdmin(I)Z > 8,3 @14 exception:9,
conditional branch(eq, to iindex=-1) 10,11,
invokestatic < Application, Landroid/os/Binder, restoreCallingIdentity(J)V > 5 @20 exception:21,
return,
return,
9 = invokestatic < Application, Landroid/os/Binder, clearCallingIdentity()J > @10 exception:8,
10 = getfield < Application, Lcom/android/server/oemlock/OemLockService$2, this$0, <Application,Lcom/android/server/oemlock/OemLockService> > 1,
12 = invokestatic < Application, Lcom/android/server/oemlock/OemLockService, -$$Nest$fgetmOemLock(Lcom/android/server/oemlock/OemLockService;)Lcom/android/server/oemlock/OemLock; > 10 @16 exception:11,
invokevirtual < Application, Lcom/android/server/oemlock/OemLock, setOemUnlockAllowedByCarrier(Z[B)V > 12,2,3 @20 exception:13,
invokestatic < Application, Landroid/os/Binder, restoreCallingIdentity(J)V > 9 @23 exception:19,
return,","depth : 0
public void setOemUnlockAllowedByCarrier(boolean p1, byte[] p2){
	OemLockService.-$$Nest$menforceManageCarrierOemUnlockPermission(this.this$0);
	OemLockService.-$$Nest$menforceUserIsAdmin(this.this$0);
	long v3 = Binder.clearCallingIdentity();
	OemLock v4 = OemLockService.-$$Nest$fgetmOemLock(this.this$0);
	v4.setOemUnlockAllowedByCarrier(p1, p2);
	Binder.restoreCallingIdentity(v3);
	return;
}
-----
depth : 1
public void -$$Nest$menforceManageCarrierOemUnlockPermission(OemLockService p1){
	p1.enforceManageCarrierOemUnlockPermission();
	return;
}
-----
depth : 2
public void enforceManageCarrierOemUnlockPermission(){
	return;
}
-----
depth : 1
public void -$$Nest$menforceUserIsAdmin(OemLockService p1){
	p1.enforceUserIsAdmin();
	return;
}
-----
depth : 2
public void enforceUserIsAdmin(){
	int v1 = UserHandle.getCallingUserId();
	long v2 = Binder.clearCallingIdentity();
	UserManager v3 = UserManager.get(this.mContext);
	boolean v4 = v3.isUserAdmin(v1);
	Binder.restoreCallingIdentity(v2);
	return;
}
-----
","public void setOemUnlockAllowedByCarrier(boolean p1, byte[] p2){
	int v6 = UserHandle.getCallingUserId();
	long v7 = Binder.clearCallingIdentity();
	UserManager v8 = UserManager.get(this.mContext);
	boolean v9 = v8.isUserAdmin(v6);
	Binder.restoreCallingIdentity(v7);
	long v11 = Binder.clearCallingIdentity();
	OemLock v12 = OemLockService.-$$Nest$fgetmOemLock(this.this$0);
	v12.setOemUnlockAllowedByCarrier(p1, p2);
	Binder.restoreCallingIdentity(v11);
	return;
}
","SYS_OR_SIG"

"Lcom/android/server/oemlock/OemLockService$2","isOemUnlockAllowedByUser()Z","0","2 = getfield < Application, Lcom/android/server/oemlock/OemLockService$2, this$0, <Application,Lcom/android/server/oemlock/OemLockService> > 1,
invokestatic < Application, Lcom/android/server/oemlock/OemLockService, -$$Nest$menforceManageUserOemUnlockPermission(Lcom/android/server/oemlock/OemLockService;)V > 2 @2 exception:3,
5 = invokestatic < Application, Landroid/os/Binder, clearCallingIdentity()J > @5 exception:4,
6 = getfield < Application, Lcom/android/server/oemlock/OemLockService$2, this$0, <Application,Lcom/android/server/oemlock/OemLockService> > 1,
8 = invokestatic < Application, Lcom/android/server/oemlock/OemLockService, -$$Nest$fgetmOemLock(Lcom/android/server/oemlock/OemLockService;)Lcom/android/server/oemlock/OemLock; > 6 @11 exception:7,
10 = invokevirtual < Application, Lcom/android/server/oemlock/OemLock, isOemUnlockAllowedByDevice()Z > 8 @15 exception:9,
invokestatic < Application, Landroid/os/Binder, restoreCallingIdentity(J)V > 5 @19 exception:16,
return 10,","depth : 0
public boolean isOemUnlockAllowedByUser(){
	OemLockService.-$$Nest$menforceManageUserOemUnlockPermission(this.this$0);
	long v2 = Binder.clearCallingIdentity();
	OemLock v3 = OemLockService.-$$Nest$fgetmOemLock(this.this$0);
	boolean v4 = v3.isOemUnlockAllowedByDevice();
	Binder.restoreCallingIdentity(v2);
	return v4;
}
-----
","public boolean isOemUnlockAllowedByUser(){
	OemLockService.-$$Nest$menforceManageUserOemUnlockPermission(this.this$0);
	long v2 = Binder.clearCallingIdentity();
	OemLock v3 = OemLockService.-$$Nest$fgetmOemLock(this.this$0);
	boolean v4 = v3.isOemUnlockAllowedByDevice();
	Binder.restoreCallingIdentity(v2);
	return v4;
}
","SYS_OR_SIG"
"Lcom/android/server/oemlock/OemLockService$2","isOemUnlockAllowedByUser()Z","1","2 = getfield < Application, Lcom/android/server/oemlock/OemLockService$2, this$0, <Application,Lcom/android/server/oemlock/OemLockService> > 1,
invokestatic < Application, Lcom/android/server/oemlock/OemLockService, -$$Nest$menforceManageUserOemUnlockPermission(Lcom/android/server/oemlock/OemLockService;)V > 2 @2 exception:3,
invokevirtual < Application, Lcom/android/server/oemlock/OemLockService, enforceManageUserOemUnlockPermission()V > 1 @0 exception:2,
return,
5 = invokestatic < Application, Landroid/os/Binder, clearCallingIdentity()J > @5 exception:4,
6 = getfield < Application, Lcom/android/server/oemlock/OemLockService$2, this$0, <Application,Lcom/android/server/oemlock/OemLockService> > 1,
8 = invokestatic < Application, Lcom/android/server/oemlock/OemLockService, -$$Nest$fgetmOemLock(Lcom/android/server/oemlock/OemLockService;)Lcom/android/server/oemlock/OemLock; > 6 @11 exception:7,
2 = getfield < Application, Lcom/android/server/oemlock/OemLockService, mOemLock, <Application,Lcom/android/server/oemlock/OemLock> > 1,
return 2,
10 = invokevirtual < Application, Lcom/android/server/oemlock/OemLock, isOemUnlockAllowedByDevice()Z > 8 @15 exception:9,
invokestatic < Application, Landroid/os/Binder, restoreCallingIdentity(J)V > 5 @19 exception:16,
return 10,","depth : 0
public boolean isOemUnlockAllowedByUser(){
	OemLockService.-$$Nest$menforceManageUserOemUnlockPermission(this.this$0);
	long v2 = Binder.clearCallingIdentity();
	OemLock v3 = OemLockService.-$$Nest$fgetmOemLock(this.this$0);
	boolean v4 = v3.isOemUnlockAllowedByDevice();
	Binder.restoreCallingIdentity(v2);
	return v4;
}
-----
depth : 1
public void -$$Nest$menforceManageUserOemUnlockPermission(OemLockService p1){
	p1.enforceManageUserOemUnlockPermission();
	return;
}
-----
depth : 1
public OemLock -$$Nest$fgetmOemLock(OemLockService p1){
	return this.mOemLock;
}
-----
","public boolean isOemUnlockAllowedByUser(){
	this.this$0.enforceManageUserOemUnlockPermission();
	long v3 = Binder.clearCallingIdentity();
	OemLock v4 = this.mOemLock;
	boolean v5 = v4.isOemUnlockAllowedByDevice();
	Binder.restoreCallingIdentity(v3);
	return v5;
}
","SYS_OR_SIG"
"Lcom/android/server/oemlock/OemLockService$2","isOemUnlockAllowedByUser()Z","2","2 = getfield < Application, Lcom/android/server/oemlock/OemLockService$2, this$0, <Application,Lcom/android/server/oemlock/OemLockService> > 1,
invokestatic < Application, Lcom/android/server/oemlock/OemLockService, -$$Nest$menforceManageUserOemUnlockPermission(Lcom/android/server/oemlock/OemLockService;)V > 2 @2 exception:3,
invokevirtual < Application, Lcom/android/server/oemlock/OemLockService, enforceManageUserOemUnlockPermission()V > 1 @0 exception:2,
2 = getfield < Application, Lcom/android/server/oemlock/OemLockService, mContext, <Application,Landroid/content/Context> > 1,
invokevirtual < Application, Landroid/content/Context, enforceCallingOrSelfPermission(Ljava/lang/String;Ljava/lang/String;)V > 2,3,4 @6 exception:5,
return,
return,
5 = invokestatic < Application, Landroid/os/Binder, clearCallingIdentity()J > @5 exception:4,
6 = getfield < Application, Lcom/android/server/oemlock/OemLockService$2, this$0, <Application,Lcom/android/server/oemlock/OemLockService> > 1,
8 = invokestatic < Application, Lcom/android/server/oemlock/OemLockService, -$$Nest$fgetmOemLock(Lcom/android/server/oemlock/OemLockService;)Lcom/android/server/oemlock/OemLock; > 6 @11 exception:7,
10 = invokevirtual < Application, Lcom/android/server/oemlock/OemLock, isOemUnlockAllowedByDevice()Z > 8 @15 exception:9,
invokestatic < Application, Landroid/os/Binder, restoreCallingIdentity(J)V > 5 @19 exception:16,
return 10,","depth : 0
public boolean isOemUnlockAllowedByUser(){
	OemLockService.-$$Nest$menforceManageUserOemUnlockPermission(this.this$0);
	long v2 = Binder.clearCallingIdentity();
	OemLock v3 = OemLockService.-$$Nest$fgetmOemLock(this.this$0);
	boolean v4 = v3.isOemUnlockAllowedByDevice();
	Binder.restoreCallingIdentity(v2);
	return v4;
}
-----
depth : 1
public void -$$Nest$menforceManageUserOemUnlockPermission(OemLockService p1){
	p1.enforceManageUserOemUnlockPermission();
	return;
}
-----
depth : 2
public void enforceManageUserOemUnlockPermission(){
	return;
}
-----
","public boolean isOemUnlockAllowedByUser(){
	long v4 = Binder.clearCallingIdentity();
	OemLock v5 = OemLockService.-$$Nest$fgetmOemLock(this.this$0);
	boolean v6 = v5.isOemUnlockAllowedByDevice();
	Binder.restoreCallingIdentity(v4);
	return v6;
}
","SYS_OR_SIG"

"Lcom/android/server/oemlock/OemLockService$2","setOemUnlockAllowedByUser(Z)V","0","4 = invokestatic < Application, Landroid/app/ActivityManager, isUserAMonkey()Z > @0 exception:3,
conditional branch(eq, to iindex=-1) 4,5,
6 = getfield < Application, Lcom/android/server/oemlock/OemLockService$2, this$0, <Application,Lcom/android/server/oemlock/OemLockService> > 1,
invokestatic < Application, Lcom/android/server/oemlock/OemLockService, -$$Nest$menforceManageUserOemUnlockPermission(Lcom/android/server/oemlock/OemLockService;)V > 6 @9 exception:7,
8 = getfield < Application, Lcom/android/server/oemlock/OemLockService$2, this$0, <Application,Lcom/android/server/oemlock/OemLockService> > 1,
invokestatic < Application, Lcom/android/server/oemlock/OemLockService, -$$Nest$menforceUserIsAdmin(Lcom/android/server/oemlock/OemLockService;)V > 8 @14 exception:9,
11 = invokestatic < Application, Landroid/os/Binder, clearCallingIdentity()J > @17 exception:10,
12 = getfield < Application, Lcom/android/server/oemlock/OemLockService$2, this$0, <Application,Lcom/android/server/oemlock/OemLockService> > 1,
14 = invokestatic < Application, Lcom/android/server/oemlock/OemLockService, -$$Nest$misOemUnlockAllowedByAdmin(Lcom/android/server/oemlock/OemLockService;)Z > 12 @23 exception:13,
conditional branch(eq, to iindex=-1) 14,5,
18 = getfield < Application, Lcom/android/server/oemlock/OemLockService$2, this$0, <Application,Lcom/android/server/oemlock/OemLockService> > 1,
20 = invokestatic < Application, Lcom/android/server/oemlock/OemLockService, -$$Nest$fgetmOemLock(Lcom/android/server/oemlock/OemLockService;)Lcom/android/server/oemlock/OemLock; > 18 @31 exception:19,
22 = invokevirtual < Application, Lcom/android/server/oemlock/OemLock, isOemUnlockAllowedByCarrier()Z > 20 @35 exception:21,
conditional branch(eq, to iindex=-1) 22,5,
26 = getfield < Application, Lcom/android/server/oemlock/OemLockService$2, this$0, <Application,Lcom/android/server/oemlock/OemLockService> > 1,
28 = invokestatic < Application, Lcom/android/server/oemlock/OemLockService, -$$Nest$fgetmOemLock(Lcom/android/server/oemlock/OemLockService;)Lcom/android/server/oemlock/OemLock; > 26 @43 exception:27,
invokevirtual < Application, Lcom/android/server/oemlock/OemLock, setOemUnlockAllowedByDevice(Z)V > 28,2 @47 exception:29,
30 = getfield < Application, Lcom/android/server/oemlock/OemLockService$2, this$0, <Application,Lcom/android/server/oemlock/OemLockService> > 1,
invokestatic < Application, Lcom/android/server/oemlock/OemLockService, -$$Nest$msetPersistentDataBlockOemUnlockAllowedBit(Lcom/android/server/oemlock/OemLockService;Z)V > 30,2 @52 exception:31,
invokestatic < Application, Landroid/os/Binder, restoreCallingIdentity(J)V > 11 @55 exception:39,
return,","depth : 0
public void setOemUnlockAllowedByUser(boolean p1){
	boolean v1 = ActivityManager.isUserAMonkey();
	OemLockService.-$$Nest$menforceManageUserOemUnlockPermission(this.this$0);
	OemLockService.-$$Nest$menforceUserIsAdmin(this.this$0);
	long v4 = Binder.clearCallingIdentity();
	boolean v5 = OemLockService.-$$Nest$misOemUnlockAllowedByAdmin(this.this$0);
	OemLock v6 = OemLockService.-$$Nest$fgetmOemLock(this.this$0);
	boolean v7 = v6.isOemUnlockAllowedByCarrier();
	OemLock v8 = OemLockService.-$$Nest$fgetmOemLock(this.this$0);
	v8.setOemUnlockAllowedByDevice(p1);
	OemLockService.-$$Nest$msetPersistentDataBlockOemUnlockAllowedBit(this.this$0, p1);
	Binder.restoreCallingIdentity(v4);
	return;
}
-----
","public void setOemUnlockAllowedByUser(boolean p1){
	boolean v1 = ActivityManager.isUserAMonkey();
	OemLockService.-$$Nest$menforceManageUserOemUnlockPermission(this.this$0);
	OemLockService.-$$Nest$menforceUserIsAdmin(this.this$0);
	long v4 = Binder.clearCallingIdentity();
	boolean v5 = OemLockService.-$$Nest$misOemUnlockAllowedByAdmin(this.this$0);
	OemLock v6 = OemLockService.-$$Nest$fgetmOemLock(this.this$0);
	boolean v7 = v6.isOemUnlockAllowedByCarrier();
	OemLock v8 = OemLockService.-$$Nest$fgetmOemLock(this.this$0);
	v8.setOemUnlockAllowedByDevice(p1);
	OemLockService.-$$Nest$msetPersistentDataBlockOemUnlockAllowedBit(this.this$0, p1);
	Binder.restoreCallingIdentity(v4);
	return;
}
","SYS_OR_SIG"
"Lcom/android/server/oemlock/OemLockService$2","setOemUnlockAllowedByUser(Z)V","1","4 = invokestatic < Application, Landroid/app/ActivityManager, isUserAMonkey()Z > @0 exception:3,
conditional branch(eq, to iindex=-1) 4,5,
6 = getfield < Application, Lcom/android/server/oemlock/OemLockService$2, this$0, <Application,Lcom/android/server/oemlock/OemLockService> > 1,
invokestatic < Application, Lcom/android/server/oemlock/OemLockService, -$$Nest$menforceManageUserOemUnlockPermission(Lcom/android/server/oemlock/OemLockService;)V > 6 @9 exception:7,
invokevirtual < Application, Lcom/android/server/oemlock/OemLockService, enforceManageUserOemUnlockPermission()V > 1 @0 exception:2,
return,
8 = getfield < Application, Lcom/android/server/oemlock/OemLockService$2, this$0, <Application,Lcom/android/server/oemlock/OemLockService> > 1,
invokestatic < Application, Lcom/android/server/oemlock/OemLockService, -$$Nest$menforceUserIsAdmin(Lcom/android/server/oemlock/OemLockService;)V > 8 @14 exception:9,
invokevirtual < Application, Lcom/android/server/oemlock/OemLockService, enforceUserIsAdmin()V > 1 @0 exception:2,
return,
11 = invokestatic < Application, Landroid/os/Binder, clearCallingIdentity()J > @17 exception:10,
12 = getfield < Application, Lcom/android/server/oemlock/OemLockService$2, this$0, <Application,Lcom/android/server/oemlock/OemLockService> > 1,
14 = invokestatic < Application, Lcom/android/server/oemlock/OemLockService, -$$Nest$misOemUnlockAllowedByAdmin(Lcom/android/server/oemlock/OemLockService;)Z > 12 @23 exception:13,
3 = invokevirtual < Application, Lcom/android/server/oemlock/OemLockService, isOemUnlockAllowedByAdmin()Z > 1 @0 exception:2,
return 3,
conditional branch(eq, to iindex=-1) 14,5,
18 = getfield < Application, Lcom/android/server/oemlock/OemLockService$2, this$0, <Application,Lcom/android/server/oemlock/OemLockService> > 1,
20 = invokestatic < Application, Lcom/android/server/oemlock/OemLockService, -$$Nest$fgetmOemLock(Lcom/android/server/oemlock/OemLockService;)Lcom/android/server/oemlock/OemLock; > 18 @31 exception:19,
2 = getfield < Application, Lcom/android/server/oemlock/OemLockService, mOemLock, <Application,Lcom/android/server/oemlock/OemLock> > 1,
return 2,
22 = invokevirtual < Application, Lcom/android/server/oemlock/OemLock, isOemUnlockAllowedByCarrier()Z > 20 @35 exception:21,
conditional branch(eq, to iindex=-1) 22,5,
26 = getfield < Application, Lcom/android/server/oemlock/OemLockService$2, this$0, <Application,Lcom/android/server/oemlock/OemLockService> > 1,
28 = invokestatic < Application, Lcom/android/server/oemlock/OemLockService, -$$Nest$fgetmOemLock(Lcom/android/server/oemlock/OemLockService;)Lcom/android/server/oemlock/OemLock; > 26 @43 exception:27,
2 = getfield < Application, Lcom/android/server/oemlock/OemLockService, mOemLock, <Application,Lcom/android/server/oemlock/OemLock> > 1,
return 2,
invokevirtual < Application, Lcom/android/server/oemlock/OemLock, setOemUnlockAllowedByDevice(Z)V > 28,2 @47 exception:29,
30 = getfield < Application, Lcom/android/server/oemlock/OemLockService$2, this$0, <Application,Lcom/android/server/oemlock/OemLockService> > 1,
invokestatic < Application, Lcom/android/server/oemlock/OemLockService, -$$Nest$msetPersistentDataBlockOemUnlockAllowedBit(Lcom/android/server/oemlock/OemLockService;Z)V > 30,2 @52 exception:31,
invokevirtual < Application, Lcom/android/server/oemlock/OemLockService, setPersistentDataBlockOemUnlockAllowedBit(Z)V > 1,2 @0 exception:3,
return,
invokestatic < Application, Landroid/os/Binder, restoreCallingIdentity(J)V > 11 @55 exception:39,
return,","depth : 0
public void setOemUnlockAllowedByUser(boolean p1){
	boolean v1 = ActivityManager.isUserAMonkey();
	OemLockService.-$$Nest$menforceManageUserOemUnlockPermission(this.this$0);
	OemLockService.-$$Nest$menforceUserIsAdmin(this.this$0);
	long v4 = Binder.clearCallingIdentity();
	boolean v5 = OemLockService.-$$Nest$misOemUnlockAllowedByAdmin(this.this$0);
	OemLock v6 = OemLockService.-$$Nest$fgetmOemLock(this.this$0);
	boolean v7 = v6.isOemUnlockAllowedByCarrier();
	OemLock v8 = OemLockService.-$$Nest$fgetmOemLock(this.this$0);
	v8.setOemUnlockAllowedByDevice(p1);
	OemLockService.-$$Nest$msetPersistentDataBlockOemUnlockAllowedBit(this.this$0, p1);
	Binder.restoreCallingIdentity(v4);
	return;
}
-----
depth : 1
public void -$$Nest$menforceManageUserOemUnlockPermission(OemLockService p1){
	p1.enforceManageUserOemUnlockPermission();
	return;
}
-----
depth : 1
public void -$$Nest$menforceUserIsAdmin(OemLockService p1){
	p1.enforceUserIsAdmin();
	return;
}
-----
depth : 1
public boolean -$$Nest$misOemUnlockAllowedByAdmin(OemLockService p1){
	boolean v1 = p1.isOemUnlockAllowedByAdmin();
	return v1;
}
-----
depth : 1
public OemLock -$$Nest$fgetmOemLock(OemLockService p1){
	return this.mOemLock;
}
-----
depth : 1
public OemLock -$$Nest$fgetmOemLock(OemLockService p1){
	return this.mOemLock;
}
-----
depth : 1
public void -$$Nest$msetPersistentDataBlockOemUnlockAllowedBit(OemLockService p1, boolean p2){
	p1.setPersistentDataBlockOemUnlockAllowedBit(p2);
	return;
}
-----
","public void setOemUnlockAllowedByUser(boolean p1){
	boolean v1 = ActivityManager.isUserAMonkey();
	this.this$0.enforceManageUserOemUnlockPermission();
	this.this$0.enforceUserIsAdmin();
	long v6 = Binder.clearCallingIdentity();
	boolean v8 = this.this$0.isOemUnlockAllowedByAdmin();
	boolean v7 = v8;
	OemLock v9 = this.mOemLock;
	boolean v10 = v9.isOemUnlockAllowedByCarrier();
	OemLock v11 = this.mOemLock;
	v11.setOemUnlockAllowedByDevice(p1);
	this.this$0.setPersistentDataBlockOemUnlockAllowedBit(p1);
	Binder.restoreCallingIdentity(v6);
	return;
}
","SYS_OR_SIG"
"Lcom/android/server/oemlock/OemLockService$2","setOemUnlockAllowedByUser(Z)V","2","4 = invokestatic < Application, Landroid/app/ActivityManager, isUserAMonkey()Z > @0 exception:3,
conditional branch(eq, to iindex=-1) 4,5,
6 = getfield < Application, Lcom/android/server/oemlock/OemLockService$2, this$0, <Application,Lcom/android/server/oemlock/OemLockService> > 1,
invokestatic < Application, Lcom/android/server/oemlock/OemLockService, -$$Nest$menforceManageUserOemUnlockPermission(Lcom/android/server/oemlock/OemLockService;)V > 6 @9 exception:7,
invokevirtual < Application, Lcom/android/server/oemlock/OemLockService, enforceManageUserOemUnlockPermission()V > 1 @0 exception:2,
2 = getfield < Application, Lcom/android/server/oemlock/OemLockService, mContext, <Application,Landroid/content/Context> > 1,
invokevirtual < Application, Landroid/content/Context, enforceCallingOrSelfPermission(Ljava/lang/String;Ljava/lang/String;)V > 2,3,4 @6 exception:5,
return,
return,
8 = getfield < Application, Lcom/android/server/oemlock/OemLockService$2, this$0, <Application,Lcom/android/server/oemlock/OemLockService> > 1,
invokestatic < Application, Lcom/android/server/oemlock/OemLockService, -$$Nest$menforceUserIsAdmin(Lcom/android/server/oemlock/OemLockService;)V > 8 @14 exception:9,
invokevirtual < Application, Lcom/android/server/oemlock/OemLockService, enforceUserIsAdmin()V > 1 @0 exception:2,
3 = invokestatic < Application, Landroid/os/UserHandle, getCallingUserId()I > @0 exception:2,
5 = invokestatic < Application, Landroid/os/Binder, clearCallingIdentity()J > @4 exception:4,
6 = getfield < Application, Lcom/android/server/oemlock/OemLockService, mContext, <Application,Landroid/content/Context> > 1,
8 = invokestatic < Application, Landroid/os/UserManager, get(Landroid/content/Context;)Landroid/os/UserManager; > 6 @10 exception:7,
10 = invokevirtual < Application, Landroid/os/UserManager, isUserAdmin(I)Z > 8,3 @14 exception:9,
conditional branch(eq, to iindex=-1) 10,11,
invokestatic < Application, Landroid/os/Binder, restoreCallingIdentity(J)V > 5 @20 exception:21,
return,
return,
11 = invokestatic < Application, Landroid/os/Binder, clearCallingIdentity()J > @17 exception:10,
12 = getfield < Application, Lcom/android/server/oemlock/OemLockService$2, this$0, <Application,Lcom/android/server/oemlock/OemLockService> > 1,
14 = invokestatic < Application, Lcom/android/server/oemlock/OemLockService, -$$Nest$misOemUnlockAllowedByAdmin(Lcom/android/server/oemlock/OemLockService;)Z > 12 @23 exception:13,
3 = invokevirtual < Application, Lcom/android/server/oemlock/OemLockService, isOemUnlockAllowedByAdmin()Z > 1 @0 exception:2,
2 = getfield < Application, Lcom/android/server/oemlock/OemLockService, mContext, <Application,Landroid/content/Context> > 1,
4 = invokestatic < Application, Landroid/os/UserManager, get(Landroid/content/Context;)Landroid/os/UserManager; > 2 @2 exception:3,
5 = getstatic < Application, Landroid/os/UserHandle, SYSTEM, <Application,Landroid/os/UserHandle> >,
8 = invokevirtual < Application, Landroid/os/UserManager, hasUserRestriction(Ljava/lang/String;Landroid/os/UserHandle;)Z > 4,6,5 @11 exception:7,
10 = binaryop(xor) 8 , 9,
return 10,
return 3,
conditional branch(eq, to iindex=-1) 14,5,
18 = getfield < Application, Lcom/android/server/oemlock/OemLockService$2, this$0, <Application,Lcom/android/server/oemlock/OemLockService> > 1,
20 = invokestatic < Application, Lcom/android/server/oemlock/OemLockService, -$$Nest$fgetmOemLock(Lcom/android/server/oemlock/OemLockService;)Lcom/android/server/oemlock/OemLock; > 18 @31 exception:19,
22 = invokevirtual < Application, Lcom/android/server/oemlock/OemLock, isOemUnlockAllowedByCarrier()Z > 20 @35 exception:21,
conditional branch(eq, to iindex=-1) 22,5,
26 = getfield < Application, Lcom/android/server/oemlock/OemLockService$2, this$0, <Application,Lcom/android/server/oemlock/OemLockService> > 1,
28 = invokestatic < Application, Lcom/android/server/oemlock/OemLockService, -$$Nest$fgetmOemLock(Lcom/android/server/oemlock/OemLockService;)Lcom/android/server/oemlock/OemLock; > 26 @43 exception:27,
invokevirtual < Application, Lcom/android/server/oemlock/OemLock, setOemUnlockAllowedByDevice(Z)V > 28,2 @47 exception:29,
30 = getfield < Application, Lcom/android/server/oemlock/OemLockService$2, this$0, <Application,Lcom/android/server/oemlock/OemLockService> > 1,
invokestatic < Application, Lcom/android/server/oemlock/OemLockService, -$$Nest$msetPersistentDataBlockOemUnlockAllowedBit(Lcom/android/server/oemlock/OemLockService;Z)V > 30,2 @52 exception:31,
invokevirtual < Application, Lcom/android/server/oemlock/OemLockService, setPersistentDataBlockOemUnlockAllowedBit(Z)V > 1,2 @0 exception:3,
3 = load_metadata: <Application,Lcom/android/server/PersistentDataBlockManagerInternal>, <Primordial,Ljava/lang/Class>,
5 = invokestatic < Application, Lcom/android/server/LocalServices, getService(Ljava/lang/Class;)Ljava/lang/Object; > 3 @2 exception:4,
6 = checkcast <Application,Lcom/android/server/PersistentDataBlockManagerInternal>5 <Application,Lcom/android/server/PersistentDataBlockManagerInternal>,
conditional branch(eq, to iindex=-1) 6,7,
8 = getfield < Application, Lcom/android/server/oemlock/OemLockService, mOemLock, <Application,Lcom/android/server/oemlock/OemLock> > 1,
9 = instanceof 8 <Application,Lcom/android/server/oemlock/PersistentDataBlockLock>,
conditional branch(ne, to iindex=-1) 9,7,
10 = new <Application,Ljava/lang/StringBuilder>@16,
invokespecial < Application, Ljava/lang/StringBuilder, <init>()V > 10 @18 exception:11,
14 = invokevirtual < Application, Ljava/lang/StringBuilder, append(Ljava/lang/String;)Ljava/lang/StringBuilder; > 10,12 @23 exception:13,
16 = invokevirtual < Application, Ljava/lang/StringBuilder, append(Z)Ljava/lang/StringBuilder; > 10,2 @26 exception:15,
18 = invokevirtual < Application, Ljava/lang/StringBuilder, toString()Ljava/lang/String; > 10 @29 exception:17,
21 = invokestatic < Application, Landroid/util/Slog, i(Ljava/lang/String;Ljava/lang/String;)I > 19,18 @35 exception:20,
invokeinterface < Application, Lcom/android/server/PersistentDataBlockManagerInternal, forceOemUnlockEnabled(Z)V > 6,2 @38 exception:22,
return,
return,
invokestatic < Application, Landroid/os/Binder, restoreCallingIdentity(J)V > 11 @55 exception:39,
return,","depth : 0
public void setOemUnlockAllowedByUser(boolean p1){
	boolean v1 = ActivityManager.isUserAMonkey();
	OemLockService.-$$Nest$menforceManageUserOemUnlockPermission(this.this$0);
	OemLockService.-$$Nest$menforceUserIsAdmin(this.this$0);
	long v4 = Binder.clearCallingIdentity();
	boolean v5 = OemLockService.-$$Nest$misOemUnlockAllowedByAdmin(this.this$0);
	OemLock v6 = OemLockService.-$$Nest$fgetmOemLock(this.this$0);
	boolean v7 = v6.isOemUnlockAllowedByCarrier();
	OemLock v8 = OemLockService.-$$Nest$fgetmOemLock(this.this$0);
	v8.setOemUnlockAllowedByDevice(p1);
	OemLockService.-$$Nest$msetPersistentDataBlockOemUnlockAllowedBit(this.this$0, p1);
	Binder.restoreCallingIdentity(v4);
	return;
}
-----
depth : 1
public void -$$Nest$menforceManageUserOemUnlockPermission(OemLockService p1){
	p1.enforceManageUserOemUnlockPermission();
	return;
}
-----
depth : 2
public void enforceManageUserOemUnlockPermission(){
	return;
}
-----
depth : 1
public void -$$Nest$menforceUserIsAdmin(OemLockService p1){
	p1.enforceUserIsAdmin();
	return;
}
-----
depth : 2
public void enforceUserIsAdmin(){
	int v1 = UserHandle.getCallingUserId();
	long v2 = Binder.clearCallingIdentity();
	UserManager v3 = UserManager.get(this.mContext);
	boolean v4 = v3.isUserAdmin(v1);
	Binder.restoreCallingIdentity(v2);
	return;
}
-----
depth : 1
public boolean -$$Nest$misOemUnlockAllowedByAdmin(OemLockService p1){
	boolean v1 = p1.isOemUnlockAllowedByAdmin();
	return v1;
}
-----
depth : 2
public boolean isOemUnlockAllowedByAdmin(){
	UserManager v1 = UserManager.get(this.mContext);
	boolean v2 = v1.hasUserRestriction(""no_factory_reset"", UserHandle.SYSTEM);
	return (v2 ^ 1);
}
-----
depth : 1
public void -$$Nest$msetPersistentDataBlockOemUnlockAllowedBit(OemLockService p1, boolean p2){
	p1.setPersistentDataBlockOemUnlockAllowedBit(p2);
	return;
}
-----
depth : 2
public void setPersistentDataBlockOemUnlockAllowedBit(boolean p1){
	Object v1 = LocalServices.getService(PersistentDataBlockManagerInterna.class);
	StringBuilder v1 = new StringBuilder();
	StringBuilder v3 = v1.append(""Update OEM Unlock bit in pst partition to "");
	StringBuilder v4 = v1.append(p1);
	String v5 = v1.toString();
	int v6 = Slog.i(""OemLock"", v5);
	v1.forceOemUnlockEnabled(p1);
	return;
}
-----
","public void setOemUnlockAllowedByUser(boolean p1){
	boolean v1 = ActivityManager.isUserAMonkey();
	int v7 = UserHandle.getCallingUserId();
	long v8 = Binder.clearCallingIdentity();
	UserManager v9 = UserManager.get(this.mContext);
	boolean v10 = v9.isUserAdmin(v7);
	Binder.restoreCallingIdentity(v8);
	long v12 = Binder.clearCallingIdentity();
	UserManager v15 = UserManager.get(this.mContext);
	boolean v16 = v15.hasUserRestriction(""no_factory_reset"", UserHandle.SYSTEM);
	boolean v14 = (v16 ^ 1);
	boolean v13 = v14;
	OemLock v17 = OemLockService.-$$Nest$fgetmOemLock(this.this$0);
	boolean v18 = v17.isOemUnlockAllowedByCarrier();
	OemLock v19 = OemLockService.-$$Nest$fgetmOemLock(this.this$0);
	v19.setOemUnlockAllowedByDevice(p1);
	Object v23 = LocalServices.getService(PersistentDataBlockManagerInterna.class);
	v23.forceOemUnlockEnabled(p2);
	Binder.restoreCallingIdentity(v12);
	return;
}
","SYS_OR_SIG"
"Lcom/android/server/oemlock/OemLockService$2","setOemUnlockAllowedByUser(Z)V","2","4 = invokestatic < Application, Landroid/app/ActivityManager, isUserAMonkey()Z > @0 exception:3,
conditional branch(eq, to iindex=-1) 4,5,
6 = getfield < Application, Lcom/android/server/oemlock/OemLockService$2, this$0, <Application,Lcom/android/server/oemlock/OemLockService> > 1,
invokestatic < Application, Lcom/android/server/oemlock/OemLockService, -$$Nest$menforceManageUserOemUnlockPermission(Lcom/android/server/oemlock/OemLockService;)V > 6 @9 exception:7,
invokevirtual < Application, Lcom/android/server/oemlock/OemLockService, enforceManageUserOemUnlockPermission()V > 1 @0 exception:2,
2 = getfield < Application, Lcom/android/server/oemlock/OemLockService, mContext, <Application,Landroid/content/Context> > 1,
invokevirtual < Application, Landroid/content/Context, enforceCallingOrSelfPermission(Ljava/lang/String;Ljava/lang/String;)V > 2,3,4 @6 exception:5,
return,
return,
8 = getfield < Application, Lcom/android/server/oemlock/OemLockService$2, this$0, <Application,Lcom/android/server/oemlock/OemLockService> > 1,
invokestatic < Application, Lcom/android/server/oemlock/OemLockService, -$$Nest$menforceUserIsAdmin(Lcom/android/server/oemlock/OemLockService;)V > 8 @14 exception:9,
invokevirtual < Application, Lcom/android/server/oemlock/OemLockService, enforceUserIsAdmin()V > 1 @0 exception:2,
3 = invokestatic < Application, Landroid/os/UserHandle, getCallingUserId()I > @0 exception:2,
5 = invokestatic < Application, Landroid/os/Binder, clearCallingIdentity()J > @4 exception:4,
6 = getfield < Application, Lcom/android/server/oemlock/OemLockService, mContext, <Application,Landroid/content/Context> > 1,
8 = invokestatic < Application, Landroid/os/UserManager, get(Landroid/content/Context;)Landroid/os/UserManager; > 6 @10 exception:7,
10 = invokevirtual < Application, Landroid/os/UserManager, isUserAdmin(I)Z > 8,3 @14 exception:9,
conditional branch(eq, to iindex=-1) 10,11,
invokestatic < Application, Landroid/os/Binder, restoreCallingIdentity(J)V > 5 @20 exception:21,
return,
return,
11 = invokestatic < Application, Landroid/os/Binder, clearCallingIdentity()J > @17 exception:10,
12 = getfield < Application, Lcom/android/server/oemlock/OemLockService$2, this$0, <Application,Lcom/android/server/oemlock/OemLockService> > 1,
14 = invokestatic < Application, Lcom/android/server/oemlock/OemLockService, -$$Nest$misOemUnlockAllowedByAdmin(Lcom/android/server/oemlock/OemLockService;)Z > 12 @23 exception:13,
3 = invokevirtual < Application, Lcom/android/server/oemlock/OemLockService, isOemUnlockAllowedByAdmin()Z > 1 @0 exception:2,
2 = getfield < Application, Lcom/android/server/oemlock/OemLockService, mContext, <Application,Landroid/content/Context> > 1,
4 = invokestatic < Application, Landroid/os/UserManager, get(Landroid/content/Context;)Landroid/os/UserManager; > 2 @2 exception:3,
5 = getstatic < Application, Landroid/os/UserHandle, SYSTEM, <Application,Landroid/os/UserHandle> >,
8 = invokevirtual < Application, Landroid/os/UserManager, hasUserRestriction(Ljava/lang/String;Landroid/os/UserHandle;)Z > 4,6,5 @11 exception:7,
10 = binaryop(xor) 8 , 9,
return 10,
return 3,
conditional branch(eq, to iindex=-1) 14,5,
18 = getfield < Application, Lcom/android/server/oemlock/OemLockService$2, this$0, <Application,Lcom/android/server/oemlock/OemLockService> > 1,
20 = invokestatic < Application, Lcom/android/server/oemlock/OemLockService, -$$Nest$fgetmOemLock(Lcom/android/server/oemlock/OemLockService;)Lcom/android/server/oemlock/OemLock; > 18 @31 exception:19,
22 = invokevirtual < Application, Lcom/android/server/oemlock/OemLock, isOemUnlockAllowedByCarrier()Z > 20 @35 exception:21,
conditional branch(eq, to iindex=-1) 22,5,
26 = getfield < Application, Lcom/android/server/oemlock/OemLockService$2, this$0, <Application,Lcom/android/server/oemlock/OemLockService> > 1,
28 = invokestatic < Application, Lcom/android/server/oemlock/OemLockService, -$$Nest$fgetmOemLock(Lcom/android/server/oemlock/OemLockService;)Lcom/android/server/oemlock/OemLock; > 26 @43 exception:27,
invokevirtual < Application, Lcom/android/server/oemlock/OemLock, setOemUnlockAllowedByDevice(Z)V > 28,2 @47 exception:29,
30 = getfield < Application, Lcom/android/server/oemlock/OemLockService$2, this$0, <Application,Lcom/android/server/oemlock/OemLockService> > 1,
invokestatic < Application, Lcom/android/server/oemlock/OemLockService, -$$Nest$msetPersistentDataBlockOemUnlockAllowedBit(Lcom/android/server/oemlock/OemLockService;Z)V > 30,2 @52 exception:31,
invokevirtual < Application, Lcom/android/server/oemlock/OemLockService, setPersistentDataBlockOemUnlockAllowedBit(Z)V > 1,2 @0 exception:3,
3 = load_metadata: <Application,Lcom/android/server/PersistentDataBlockManagerInternal>, <Primordial,Ljava/lang/Class>,
5 = invokestatic < Application, Lcom/android/server/LocalServices, getService(Ljava/lang/Class;)Ljava/lang/Object; > 3 @2 exception:4,
6 = checkcast <Application,Lcom/android/server/PersistentDataBlockManagerInternal>5 <Application,Lcom/android/server/PersistentDataBlockManagerInternal>,
conditional branch(eq, to iindex=-1) 6,7,
8 = getfield < Application, Lcom/android/server/oemlock/OemLockService, mOemLock, <Application,Lcom/android/server/oemlock/OemLock> > 1,
9 = instanceof 8 <Application,Lcom/android/server/oemlock/PersistentDataBlockLock>,
conditional branch(ne, to iindex=-1) 9,7,
return,
return,
invokestatic < Application, Landroid/os/Binder, restoreCallingIdentity(J)V > 11 @55 exception:39,
return,","depth : 0
public void setOemUnlockAllowedByUser(boolean p1){
	boolean v1 = ActivityManager.isUserAMonkey();
	OemLockService.-$$Nest$menforceManageUserOemUnlockPermission(this.this$0);
	OemLockService.-$$Nest$menforceUserIsAdmin(this.this$0);
	long v4 = Binder.clearCallingIdentity();
	boolean v5 = OemLockService.-$$Nest$misOemUnlockAllowedByAdmin(this.this$0);
	OemLock v6 = OemLockService.-$$Nest$fgetmOemLock(this.this$0);
	boolean v7 = v6.isOemUnlockAllowedByCarrier();
	OemLock v8 = OemLockService.-$$Nest$fgetmOemLock(this.this$0);
	v8.setOemUnlockAllowedByDevice(p1);
	OemLockService.-$$Nest$msetPersistentDataBlockOemUnlockAllowedBit(this.this$0, p1);
	Binder.restoreCallingIdentity(v4);
	return;
}
-----
depth : 1
public void -$$Nest$menforceManageUserOemUnlockPermission(OemLockService p1){
	p1.enforceManageUserOemUnlockPermission();
	return;
}
-----
depth : 2
public void enforceManageUserOemUnlockPermission(){
	return;
}
-----
depth : 1
public void -$$Nest$menforceUserIsAdmin(OemLockService p1){
	p1.enforceUserIsAdmin();
	return;
}
-----
depth : 2
public void enforceUserIsAdmin(){
	int v1 = UserHandle.getCallingUserId();
	long v2 = Binder.clearCallingIdentity();
	UserManager v3 = UserManager.get(this.mContext);
	boolean v4 = v3.isUserAdmin(v1);
	Binder.restoreCallingIdentity(v2);
	return;
}
-----
depth : 1
public boolean -$$Nest$misOemUnlockAllowedByAdmin(OemLockService p1){
	boolean v1 = p1.isOemUnlockAllowedByAdmin();
	return v1;
}
-----
depth : 2
public boolean isOemUnlockAllowedByAdmin(){
	UserManager v1 = UserManager.get(this.mContext);
	boolean v2 = v1.hasUserRestriction(""no_factory_reset"", UserHandle.SYSTEM);
	return (v2 ^ 1);
}
-----
depth : 1
public void -$$Nest$msetPersistentDataBlockOemUnlockAllowedBit(OemLockService p1, boolean p2){
	p1.setPersistentDataBlockOemUnlockAllowedBit(p2);
	return;
}
-----
depth : 2
public void setPersistentDataBlockOemUnlockAllowedBit(boolean p1){
	Object v1 = LocalServices.getService(PersistentDataBlockManagerInterna.class);
	return;
}
-----
","public void setOemUnlockAllowedByUser(boolean p1){
	boolean v1 = ActivityManager.isUserAMonkey();
	int v7 = UserHandle.getCallingUserId();
	long v8 = Binder.clearCallingIdentity();
	UserManager v9 = UserManager.get(this.mContext);
	boolean v10 = v9.isUserAdmin(v7);
	Binder.restoreCallingIdentity(v8);
	long v12 = Binder.clearCallingIdentity();
	UserManager v15 = UserManager.get(this.mContext);
	boolean v16 = v15.hasUserRestriction(""no_factory_reset"", UserHandle.SYSTEM);
	boolean v14 = (v16 ^ 1);
	boolean v13 = v14;
	OemLock v17 = OemLockService.-$$Nest$fgetmOemLock(this.this$0);
	boolean v18 = v17.isOemUnlockAllowedByCarrier();
	OemLock v19 = OemLockService.-$$Nest$fgetmOemLock(this.this$0);
	v19.setOemUnlockAllowedByDevice(p1);
	Object v23 = LocalServices.getService(PersistentDataBlockManagerInterna.class);
	Binder.restoreCallingIdentity(v12);
	return;
}
","SYS_OR_SIG"
"Lcom/android/server/oemlock/OemLockService$2","setOemUnlockAllowedByUser(Z)V","2","4 = invokestatic < Application, Landroid/app/ActivityManager, isUserAMonkey()Z > @0 exception:3,
conditional branch(eq, to iindex=-1) 4,5,
6 = getfield < Application, Lcom/android/server/oemlock/OemLockService$2, this$0, <Application,Lcom/android/server/oemlock/OemLockService> > 1,
invokestatic < Application, Lcom/android/server/oemlock/OemLockService, -$$Nest$menforceManageUserOemUnlockPermission(Lcom/android/server/oemlock/OemLockService;)V > 6 @9 exception:7,
invokevirtual < Application, Lcom/android/server/oemlock/OemLockService, enforceManageUserOemUnlockPermission()V > 1 @0 exception:2,
2 = getfield < Application, Lcom/android/server/oemlock/OemLockService, mContext, <Application,Landroid/content/Context> > 1,
invokevirtual < Application, Landroid/content/Context, enforceCallingOrSelfPermission(Ljava/lang/String;Ljava/lang/String;)V > 2,3,4 @6 exception:5,
return,
return,
8 = getfield < Application, Lcom/android/server/oemlock/OemLockService$2, this$0, <Application,Lcom/android/server/oemlock/OemLockService> > 1,
invokestatic < Application, Lcom/android/server/oemlock/OemLockService, -$$Nest$menforceUserIsAdmin(Lcom/android/server/oemlock/OemLockService;)V > 8 @14 exception:9,
invokevirtual < Application, Lcom/android/server/oemlock/OemLockService, enforceUserIsAdmin()V > 1 @0 exception:2,
3 = invokestatic < Application, Landroid/os/UserHandle, getCallingUserId()I > @0 exception:2,
5 = invokestatic < Application, Landroid/os/Binder, clearCallingIdentity()J > @4 exception:4,
6 = getfield < Application, Lcom/android/server/oemlock/OemLockService, mContext, <Application,Landroid/content/Context> > 1,
8 = invokestatic < Application, Landroid/os/UserManager, get(Landroid/content/Context;)Landroid/os/UserManager; > 6 @10 exception:7,
10 = invokevirtual < Application, Landroid/os/UserManager, isUserAdmin(I)Z > 8,3 @14 exception:9,
conditional branch(eq, to iindex=-1) 10,11,
invokestatic < Application, Landroid/os/Binder, restoreCallingIdentity(J)V > 5 @20 exception:21,
return,
return,
11 = invokestatic < Application, Landroid/os/Binder, clearCallingIdentity()J > @17 exception:10,
12 = getfield < Application, Lcom/android/server/oemlock/OemLockService$2, this$0, <Application,Lcom/android/server/oemlock/OemLockService> > 1,
14 = invokestatic < Application, Lcom/android/server/oemlock/OemLockService, -$$Nest$misOemUnlockAllowedByAdmin(Lcom/android/server/oemlock/OemLockService;)Z > 12 @23 exception:13,
3 = invokevirtual < Application, Lcom/android/server/oemlock/OemLockService, isOemUnlockAllowedByAdmin()Z > 1 @0 exception:2,
2 = getfield < Application, Lcom/android/server/oemlock/OemLockService, mContext, <Application,Landroid/content/Context> > 1,
4 = invokestatic < Application, Landroid/os/UserManager, get(Landroid/content/Context;)Landroid/os/UserManager; > 2 @2 exception:3,
5 = getstatic < Application, Landroid/os/UserHandle, SYSTEM, <Application,Landroid/os/UserHandle> >,
8 = invokevirtual < Application, Landroid/os/UserManager, hasUserRestriction(Ljava/lang/String;Landroid/os/UserHandle;)Z > 4,6,5 @11 exception:7,
10 = binaryop(xor) 8 , 9,
return 10,
return 3,
conditional branch(eq, to iindex=-1) 14,5,
18 = getfield < Application, Lcom/android/server/oemlock/OemLockService$2, this$0, <Application,Lcom/android/server/oemlock/OemLockService> > 1,
20 = invokestatic < Application, Lcom/android/server/oemlock/OemLockService, -$$Nest$fgetmOemLock(Lcom/android/server/oemlock/OemLockService;)Lcom/android/server/oemlock/OemLock; > 18 @31 exception:19,
22 = invokevirtual < Application, Lcom/android/server/oemlock/OemLock, isOemUnlockAllowedByCarrier()Z > 20 @35 exception:21,
conditional branch(eq, to iindex=-1) 22,5,
26 = getfield < Application, Lcom/android/server/oemlock/OemLockService$2, this$0, <Application,Lcom/android/server/oemlock/OemLockService> > 1,
28 = invokestatic < Application, Lcom/android/server/oemlock/OemLockService, -$$Nest$fgetmOemLock(Lcom/android/server/oemlock/OemLockService;)Lcom/android/server/oemlock/OemLock; > 26 @43 exception:27,
invokevirtual < Application, Lcom/android/server/oemlock/OemLock, setOemUnlockAllowedByDevice(Z)V > 28,2 @47 exception:29,
30 = getfield < Application, Lcom/android/server/oemlock/OemLockService$2, this$0, <Application,Lcom/android/server/oemlock/OemLockService> > 1,
invokestatic < Application, Lcom/android/server/oemlock/OemLockService, -$$Nest$msetPersistentDataBlockOemUnlockAllowedBit(Lcom/android/server/oemlock/OemLockService;Z)V > 30,2 @52 exception:31,
invokevirtual < Application, Lcom/android/server/oemlock/OemLockService, setPersistentDataBlockOemUnlockAllowedBit(Z)V > 1,2 @0 exception:3,
3 = load_metadata: <Application,Lcom/android/server/PersistentDataBlockManagerInternal>, <Primordial,Ljava/lang/Class>,
5 = invokestatic < Application, Lcom/android/server/LocalServices, getService(Ljava/lang/Class;)Ljava/lang/Object; > 3 @2 exception:4,
6 = checkcast <Application,Lcom/android/server/PersistentDataBlockManagerInternal>5 <Application,Lcom/android/server/PersistentDataBlockManagerInternal>,
conditional branch(eq, to iindex=-1) 6,7,
return,
return,
invokestatic < Application, Landroid/os/Binder, restoreCallingIdentity(J)V > 11 @55 exception:39,
return,","depth : 0
public void setOemUnlockAllowedByUser(boolean p1){
	boolean v1 = ActivityManager.isUserAMonkey();
	OemLockService.-$$Nest$menforceManageUserOemUnlockPermission(this.this$0);
	OemLockService.-$$Nest$menforceUserIsAdmin(this.this$0);
	long v4 = Binder.clearCallingIdentity();
	boolean v5 = OemLockService.-$$Nest$misOemUnlockAllowedByAdmin(this.this$0);
	OemLock v6 = OemLockService.-$$Nest$fgetmOemLock(this.this$0);
	boolean v7 = v6.isOemUnlockAllowedByCarrier();
	OemLock v8 = OemLockService.-$$Nest$fgetmOemLock(this.this$0);
	v8.setOemUnlockAllowedByDevice(p1);
	OemLockService.-$$Nest$msetPersistentDataBlockOemUnlockAllowedBit(this.this$0, p1);
	Binder.restoreCallingIdentity(v4);
	return;
}
-----
depth : 1
public void -$$Nest$menforceManageUserOemUnlockPermission(OemLockService p1){
	p1.enforceManageUserOemUnlockPermission();
	return;
}
-----
depth : 2
public void enforceManageUserOemUnlockPermission(){
	return;
}
-----
depth : 1
public void -$$Nest$menforceUserIsAdmin(OemLockService p1){
	p1.enforceUserIsAdmin();
	return;
}
-----
depth : 2
public void enforceUserIsAdmin(){
	int v1 = UserHandle.getCallingUserId();
	long v2 = Binder.clearCallingIdentity();
	UserManager v3 = UserManager.get(this.mContext);
	boolean v4 = v3.isUserAdmin(v1);
	Binder.restoreCallingIdentity(v2);
	return;
}
-----
depth : 1
public boolean -$$Nest$misOemUnlockAllowedByAdmin(OemLockService p1){
	boolean v1 = p1.isOemUnlockAllowedByAdmin();
	return v1;
}
-----
depth : 2
public boolean isOemUnlockAllowedByAdmin(){
	UserManager v1 = UserManager.get(this.mContext);
	boolean v2 = v1.hasUserRestriction(""no_factory_reset"", UserHandle.SYSTEM);
	return (v2 ^ 1);
}
-----
depth : 1
public void -$$Nest$msetPersistentDataBlockOemUnlockAllowedBit(OemLockService p1, boolean p2){
	p1.setPersistentDataBlockOemUnlockAllowedBit(p2);
	return;
}
-----
depth : 2
public void setPersistentDataBlockOemUnlockAllowedBit(boolean p1){
	Object v1 = LocalServices.getService(PersistentDataBlockManagerInterna.class);
	return;
}
-----
","public void setOemUnlockAllowedByUser(boolean p1){
	boolean v1 = ActivityManager.isUserAMonkey();
	int v7 = UserHandle.getCallingUserId();
	long v8 = Binder.clearCallingIdentity();
	UserManager v9 = UserManager.get(this.mContext);
	boolean v10 = v9.isUserAdmin(v7);
	Binder.restoreCallingIdentity(v8);
	long v12 = Binder.clearCallingIdentity();
	UserManager v15 = UserManager.get(this.mContext);
	boolean v16 = v15.hasUserRestriction(""no_factory_reset"", UserHandle.SYSTEM);
	boolean v14 = (v16 ^ 1);
	boolean v13 = v14;
	OemLock v17 = OemLockService.-$$Nest$fgetmOemLock(this.this$0);
	boolean v18 = v17.isOemUnlockAllowedByCarrier();
	OemLock v19 = OemLockService.-$$Nest$fgetmOemLock(this.this$0);
	v19.setOemUnlockAllowedByDevice(p1);
	Object v23 = LocalServices.getService(PersistentDataBlockManagerInterna.class);
	Binder.restoreCallingIdentity(v12);
	return;
}
","SYS_OR_SIG"

"Lcom/android/server/oemlock/OemLockService$2","getLockName()Ljava/lang/String;","0","2 = getfield < Application, Lcom/android/server/oemlock/OemLockService$2, this$0, <Application,Lcom/android/server/oemlock/OemLockService> > 1,
invokestatic < Application, Lcom/android/server/oemlock/OemLockService, -$$Nest$menforceManageCarrierOemUnlockPermission(Lcom/android/server/oemlock/OemLockService;)V > 2 @2 exception:3,
5 = invokestatic < Application, Landroid/os/Binder, clearCallingIdentity()J > @5 exception:4,
6 = getfield < Application, Lcom/android/server/oemlock/OemLockService$2, this$0, <Application,Lcom/android/server/oemlock/OemLockService> > 1,
8 = invokestatic < Application, Lcom/android/server/oemlock/OemLockService, -$$Nest$fgetmOemLock(Lcom/android/server/oemlock/OemLockService;)Lcom/android/server/oemlock/OemLock; > 6 @11 exception:7,
10 = invokevirtual < Application, Lcom/android/server/oemlock/OemLock, getLockName()Ljava/lang/String; > 8 @15 exception:9,
invokestatic < Application, Landroid/os/Binder, restoreCallingIdentity(J)V > 5 @19 exception:16,
return 10,","depth : 0
public String getLockName(){
	OemLockService.-$$Nest$menforceManageCarrierOemUnlockPermission(this.this$0);
	long v2 = Binder.clearCallingIdentity();
	OemLock v3 = OemLockService.-$$Nest$fgetmOemLock(this.this$0);
	String v4 = v3.getLockName();
	Binder.restoreCallingIdentity(v2);
	return v4;
}
-----
","public String getLockName(){
	OemLockService.-$$Nest$menforceManageCarrierOemUnlockPermission(this.this$0);
	long v2 = Binder.clearCallingIdentity();
	OemLock v3 = OemLockService.-$$Nest$fgetmOemLock(this.this$0);
	String v4 = v3.getLockName();
	Binder.restoreCallingIdentity(v2);
	return v4;
}
","SYS_OR_SIG"
"Lcom/android/server/oemlock/OemLockService$2","getLockName()Ljava/lang/String;","1","2 = getfield < Application, Lcom/android/server/oemlock/OemLockService$2, this$0, <Application,Lcom/android/server/oemlock/OemLockService> > 1,
invokestatic < Application, Lcom/android/server/oemlock/OemLockService, -$$Nest$menforceManageCarrierOemUnlockPermission(Lcom/android/server/oemlock/OemLockService;)V > 2 @2 exception:3,
invokevirtual < Application, Lcom/android/server/oemlock/OemLockService, enforceManageCarrierOemUnlockPermission()V > 1 @0 exception:2,
return,
5 = invokestatic < Application, Landroid/os/Binder, clearCallingIdentity()J > @5 exception:4,
6 = getfield < Application, Lcom/android/server/oemlock/OemLockService$2, this$0, <Application,Lcom/android/server/oemlock/OemLockService> > 1,
8 = invokestatic < Application, Lcom/android/server/oemlock/OemLockService, -$$Nest$fgetmOemLock(Lcom/android/server/oemlock/OemLockService;)Lcom/android/server/oemlock/OemLock; > 6 @11 exception:7,
2 = getfield < Application, Lcom/android/server/oemlock/OemLockService, mOemLock, <Application,Lcom/android/server/oemlock/OemLock> > 1,
return 2,
10 = invokevirtual < Application, Lcom/android/server/oemlock/OemLock, getLockName()Ljava/lang/String; > 8 @15 exception:9,
invokestatic < Application, Landroid/os/Binder, restoreCallingIdentity(J)V > 5 @19 exception:16,
return 10,","depth : 0
public String getLockName(){
	OemLockService.-$$Nest$menforceManageCarrierOemUnlockPermission(this.this$0);
	long v2 = Binder.clearCallingIdentity();
	OemLock v3 = OemLockService.-$$Nest$fgetmOemLock(this.this$0);
	String v4 = v3.getLockName();
	Binder.restoreCallingIdentity(v2);
	return v4;
}
-----
depth : 1
public void -$$Nest$menforceManageCarrierOemUnlockPermission(OemLockService p1){
	p1.enforceManageCarrierOemUnlockPermission();
	return;
}
-----
depth : 1
public OemLock -$$Nest$fgetmOemLock(OemLockService p1){
	return this.mOemLock;
}
-----
","public String getLockName(){
	this.this$0.enforceManageCarrierOemUnlockPermission();
	long v3 = Binder.clearCallingIdentity();
	OemLock v4 = this.mOemLock;
	String v5 = v4.getLockName();
	Binder.restoreCallingIdentity(v3);
	return v5;
}
","SYS_OR_SIG"
"Lcom/android/server/oemlock/OemLockService$2","getLockName()Ljava/lang/String;","2","2 = getfield < Application, Lcom/android/server/oemlock/OemLockService$2, this$0, <Application,Lcom/android/server/oemlock/OemLockService> > 1,
invokestatic < Application, Lcom/android/server/oemlock/OemLockService, -$$Nest$menforceManageCarrierOemUnlockPermission(Lcom/android/server/oemlock/OemLockService;)V > 2 @2 exception:3,
invokevirtual < Application, Lcom/android/server/oemlock/OemLockService, enforceManageCarrierOemUnlockPermission()V > 1 @0 exception:2,
2 = getfield < Application, Lcom/android/server/oemlock/OemLockService, mContext, <Application,Landroid/content/Context> > 1,
invokevirtual < Application, Landroid/content/Context, enforceCallingOrSelfPermission(Ljava/lang/String;Ljava/lang/String;)V > 2,3,4 @6 exception:5,
return,
return,
5 = invokestatic < Application, Landroid/os/Binder, clearCallingIdentity()J > @5 exception:4,
6 = getfield < Application, Lcom/android/server/oemlock/OemLockService$2, this$0, <Application,Lcom/android/server/oemlock/OemLockService> > 1,
8 = invokestatic < Application, Lcom/android/server/oemlock/OemLockService, -$$Nest$fgetmOemLock(Lcom/android/server/oemlock/OemLockService;)Lcom/android/server/oemlock/OemLock; > 6 @11 exception:7,
10 = invokevirtual < Application, Lcom/android/server/oemlock/OemLock, getLockName()Ljava/lang/String; > 8 @15 exception:9,
invokestatic < Application, Landroid/os/Binder, restoreCallingIdentity(J)V > 5 @19 exception:16,
return 10,","depth : 0
public String getLockName(){
	OemLockService.-$$Nest$menforceManageCarrierOemUnlockPermission(this.this$0);
	long v2 = Binder.clearCallingIdentity();
	OemLock v3 = OemLockService.-$$Nest$fgetmOemLock(this.this$0);
	String v4 = v3.getLockName();
	Binder.restoreCallingIdentity(v2);
	return v4;
}
-----
depth : 1
public void -$$Nest$menforceManageCarrierOemUnlockPermission(OemLockService p1){
	p1.enforceManageCarrierOemUnlockPermission();
	return;
}
-----
depth : 2
public void enforceManageCarrierOemUnlockPermission(){
	return;
}
-----
","public String getLockName(){
	long v4 = Binder.clearCallingIdentity();
	OemLock v5 = OemLockService.-$$Nest$fgetmOemLock(this.this$0);
	String v6 = v5.getLockName();
	Binder.restoreCallingIdentity(v4);
	return v6;
}
","SYS_OR_SIG"

