"Class","Method","Depth","Trace Instruction(s) ...","Java Code Representation","Code Merged","Access Control Level"
"Lcom/android/server/os/BugreportManagerServiceImpl","cancelBugreport(ILjava/lang/String;)V","0","5 = invokestatic < Application, Landroid/os/Binder, getCallingUid()I > @0 exception:4,
invokevirtual < Application, Lcom/android/server/os/BugreportManagerServiceImpl, enforcePermission(Ljava/lang/String;IZ)V > 1,3,5,6 @5 exception:7,
8 = getfield < Application, Lcom/android/server/os/BugreportManagerServiceImpl, mLock, <Application,Ljava/lang/Object> > 1,
monitorenter 8,
10 = invokevirtual < Application, Lcom/android/server/os/BugreportManagerServiceImpl, getDumpstateBinderServiceLocked()Landroid/os/IDumpstate; > 1 @11 exception:9,
conditional branch(ne, to iindex=-1) 10,11,
invokeinterface < Application, Landroid/os/IDumpstate, cancelBugreport(ILjava/lang/String;)V > 10,5,3 @26 exception:12,
13 = getCaughtException ,
17 = invokestatic < Application, Landroid/util/Slog, e(Ljava/lang/String;Ljava/lang/String;Ljava/lang/Throwable;)I > 14,15,13 @35 exception:16,
invokestatic < Application, Landroid/os/SystemProperties, set(Ljava/lang/String;Ljava/lang/String;)V > 23,24 @42 exception:25,
monitorexit 8,
return,","depth : 0
public void cancelBugreport(int p1, String p2){
	IDumpstate v3 = p0.getDumpstateBinderServiceLocked();
	v3.cancelBugreport(v1, p2);
	int v5 = Slog.e(""BugreportManagerService"", ""RemoteException in cancelBugreport"", caughtException);
	SystemProperties.set(""ctl.stop"", ""bugreportd"");
	return;
}
-----
","public void cancelBugreport(int p1, String p2){
	IDumpstate v3 = p0.getDumpstateBinderServiceLocked();
	v3.cancelBugreport(v1, p2);
	SystemProperties.set(""ctl.stop"", ""bugreportd"");
	return;
}
","NORMAL"
"Lcom/android/server/os/BugreportManagerServiceImpl","cancelBugreport(ILjava/lang/String;)V","1","5 = invokestatic < Application, Landroid/os/Binder, getCallingUid()I > @0 exception:4,
invokevirtual < Application, Lcom/android/server/os/BugreportManagerServiceImpl, enforcePermission(Ljava/lang/String;IZ)V > 1,3,5,6 @5 exception:7,
8 = getfield < Application, Lcom/android/server/os/BugreportManagerServiceImpl, mLock, <Application,Ljava/lang/Object> > 1,
monitorenter 8,
10 = invokevirtual < Application, Lcom/android/server/os/BugreportManagerServiceImpl, getDumpstateBinderServiceLocked()Landroid/os/IDumpstate; > 1 @11 exception:9,
4 = invokestatic < Application, Landroid/os/ServiceManager, getService(Ljava/lang/String;)Landroid/os/IBinder; > 2 @2 exception:3,
6 = invokestatic < Application, Landroid/os/IDumpstate$Stub, asInterface(Landroid/os/IBinder;)Landroid/os/IDumpstate; > 4 @6 exception:5,
return 6,
conditional branch(ne, to iindex=-1) 10,11,
invokeinterface < Application, Landroid/os/IDumpstate, cancelBugreport(ILjava/lang/String;)V > 10,5,3 @26 exception:12,
13 = getCaughtException ,
17 = invokestatic < Application, Landroid/util/Slog, e(Ljava/lang/String;Ljava/lang/String;Ljava/lang/Throwable;)I > 14,15,13 @35 exception:16,
invokestatic < Application, Landroid/os/SystemProperties, set(Ljava/lang/String;Ljava/lang/String;)V > 23,24 @42 exception:25,
monitorexit 8,
return,","depth : 0
public void cancelBugreport(int p1, String p2){
	IDumpstate v3 = p0.getDumpstateBinderServiceLocked();
	v3.cancelBugreport(v1, p2);
	int v5 = Slog.e(""BugreportManagerService"", ""RemoteException in cancelBugreport"", caughtException);
	SystemProperties.set(""ctl.stop"", ""bugreportd"");
	return;
}
-----
depth : 1
public IDumpstate getDumpstateBinderServiceLocked(){
	IBinder v1 = ServiceManager.getService(""dumpstate"");
	IDumpstate v2 = IDumpstate$Stub.asInterface(v1);
	return v2;
}
-----
","public void cancelBugreport(int p1, String p2){
	IBinder v4 = ServiceManager.getService(""dumpstate"");
	IDumpstate v5 = IDumpstate$Stub.asInterface(v4);
	IDumpstate v3 = v5;
	v3.cancelBugreport(v1, p2);
	SystemProperties.set(""ctl.stop"", ""bugreportd"");
	return;
}
","NORMAL"
"Lcom/android/server/os/BugreportManagerServiceImpl","cancelBugreport(ILjava/lang/String;)V","1","5 = invokestatic < Application, Landroid/os/Binder, getCallingUid()I > @0 exception:4,
invokevirtual < Application, Lcom/android/server/os/BugreportManagerServiceImpl, enforcePermission(Ljava/lang/String;IZ)V > 1,3,5,6 @5 exception:7,
8 = getfield < Application, Lcom/android/server/os/BugreportManagerServiceImpl, mLock, <Application,Ljava/lang/Object> > 1,
monitorenter 8,
10 = invokevirtual < Application, Lcom/android/server/os/BugreportManagerServiceImpl, getDumpstateBinderServiceLocked()Landroid/os/IDumpstate; > 1 @11 exception:9,
4 = invokestatic < Application, Landroid/os/ServiceManager, getService(Ljava/lang/String;)Landroid/os/IBinder; > 2 @2 exception:3,
6 = invokestatic < Application, Landroid/os/IDumpstate$Stub, asInterface(Landroid/os/IBinder;)Landroid/os/IDumpstate; > 4 @6 exception:5,
return 6,
conditional branch(ne, to iindex=-1) 10,11,
invokeinterface < Application, Landroid/os/IDumpstate, cancelBugreport(ILjava/lang/String;)V > 10,5,3 @26 exception:12,
goto (from iindex= 15 to iindex = 9),
invokestatic < Application, Landroid/os/SystemProperties, set(Ljava/lang/String;Ljava/lang/String;)V > 23,24 @42 exception:25,
monitorexit 8,
return,","depth : 0
public void cancelBugreport(int p1, String p2){
	IDumpstate v3 = p0.getDumpstateBinderServiceLocked();
	v3.cancelBugreport(v1, p2);
	SystemProperties.set(""ctl.stop"", ""bugreportd"");
	return;
}
-----
depth : 1
public IDumpstate getDumpstateBinderServiceLocked(){
	IBinder v1 = ServiceManager.getService(""dumpstate"");
	IDumpstate v2 = IDumpstate$Stub.asInterface(v1);
	return v2;
}
-----
","public void cancelBugreport(int p1, String p2){
	IBinder v4 = ServiceManager.getService(""dumpstate"");
	IDumpstate v5 = IDumpstate$Stub.asInterface(v4);
	IDumpstate v3 = v5;
	v3.cancelBugreport(v1, p2);
	SystemProperties.set(""ctl.stop"", ""bugreportd"");
	return;
}
","NORMAL"
"Lcom/android/server/os/BugreportManagerServiceImpl","cancelBugreport(ILjava/lang/String;)V","2","5 = invokestatic < Application, Landroid/os/Binder, getCallingUid()I > @0 exception:4,
invokevirtual < Application, Lcom/android/server/os/BugreportManagerServiceImpl, enforcePermission(Ljava/lang/String;IZ)V > 1,3,5,6 @5 exception:7,
8 = getfield < Application, Lcom/android/server/os/BugreportManagerServiceImpl, mLock, <Application,Ljava/lang/Object> > 1,
monitorenter 8,
10 = invokevirtual < Application, Lcom/android/server/os/BugreportManagerServiceImpl, getDumpstateBinderServiceLocked()Landroid/os/IDumpstate; > 1 @11 exception:9,
4 = invokestatic < Application, Landroid/os/ServiceManager, getService(Ljava/lang/String;)Landroid/os/IBinder; > 2 @2 exception:3,
6 = invokestatic < Application, Landroid/os/IDumpstate$Stub, asInterface(Landroid/os/IBinder;)Landroid/os/IDumpstate; > 4 @6 exception:5,
conditional branch(ne, to iindex=-1) 1,2,
5 = invokeinterface < Application, Landroid/os/IBinder, queryLocalInterface(Ljava/lang/String;)Landroid/os/IInterface; > 1,3 @6 exception:4,
conditional branch(eq, to iindex=-1) 5,2,
6 = instanceof 5 <Application,Landroid/os/IDumpstate>,
conditional branch(eq, to iindex=-1) 6,2,
7 = new <Application,Landroid/os/IDumpstate$Stub$Proxy>@20,
invokespecial < Application, Landroid/os/IDumpstate$Stub$Proxy, <init>(Landroid/os/IBinder;)V > 7,1 @22 exception:8,
return 7,
return 6,
conditional branch(ne, to iindex=-1) 10,11,
invokeinterface < Application, Landroid/os/IDumpstate, cancelBugreport(ILjava/lang/String;)V > 10,5,3 @26 exception:12,
13 = getCaughtException ,
17 = invokestatic < Application, Landroid/util/Slog, e(Ljava/lang/String;Ljava/lang/String;Ljava/lang/Throwable;)I > 14,15,13 @35 exception:16,
invokestatic < Application, Landroid/os/SystemProperties, set(Ljava/lang/String;Ljava/lang/String;)V > 23,24 @42 exception:25,
monitorexit 8,
return,","depth : 0
public void cancelBugreport(int p1, String p2){
	IDumpstate v3 = p0.getDumpstateBinderServiceLocked();
	v3.cancelBugreport(v1, p2);
	int v5 = Slog.e(""BugreportManagerService"", ""RemoteException in cancelBugreport"", caughtException);
	SystemProperties.set(""ctl.stop"", ""bugreportd"");
	return;
}
-----
depth : 1
public IDumpstate getDumpstateBinderServiceLocked(){
	IBinder v1 = ServiceManager.getService(""dumpstate"");
	IDumpstate v2 = IDumpstate$Stub.asInterface(v1);
	return v2;
}
-----
depth : 2
public IDumpstate asInterface(IBinder p1){
	IInterface v1 = p1.queryLocalInterface(""android.os.IDumpstate"");
	IDumpstate$Stub$Proxy v1 = new IDumpstate$Stub$Proxy(p1);
	return v1;
}
-----
","public void cancelBugreport(int p1, String p2){
	IBinder v4 = ServiceManager.getService(""dumpstate"");
	IInterface v6 = v4.queryLocalInterface(""android.os.IDumpstate"");
	IDumpstate$Stub$Proxy v7 = new IDumpstate$Stub$Proxy(v4);
	IDumpstate v5 = v7;
	IDumpstate v3 = v5;
	v3.cancelBugreport(v1, p2);
	SystemProperties.set(""ctl.stop"", ""bugreportd"");
	return;
}
","NORMAL"
"Lcom/android/server/os/BugreportManagerServiceImpl","cancelBugreport(ILjava/lang/String;)V","2","5 = invokestatic < Application, Landroid/os/Binder, getCallingUid()I > @0 exception:4,
invokevirtual < Application, Lcom/android/server/os/BugreportManagerServiceImpl, enforcePermission(Ljava/lang/String;IZ)V > 1,3,5,6 @5 exception:7,
8 = getfield < Application, Lcom/android/server/os/BugreportManagerServiceImpl, mLock, <Application,Ljava/lang/Object> > 1,
monitorenter 8,
10 = invokevirtual < Application, Lcom/android/server/os/BugreportManagerServiceImpl, getDumpstateBinderServiceLocked()Landroid/os/IDumpstate; > 1 @11 exception:9,
4 = invokestatic < Application, Landroid/os/ServiceManager, getService(Ljava/lang/String;)Landroid/os/IBinder; > 2 @2 exception:3,
6 = invokestatic < Application, Landroid/os/IDumpstate$Stub, asInterface(Landroid/os/IBinder;)Landroid/os/IDumpstate; > 4 @6 exception:5,
conditional branch(ne, to iindex=-1) 1,2,
5 = invokeinterface < Application, Landroid/os/IBinder, queryLocalInterface(Ljava/lang/String;)Landroid/os/IInterface; > 1,3 @6 exception:4,
conditional branch(eq, to iindex=-1) 5,2,
6 = instanceof 5 <Application,Landroid/os/IDumpstate>,
conditional branch(eq, to iindex=-1) 6,2,
9 = checkcast <Application,Landroid/os/IDumpstate>5 <Application,Landroid/os/IDumpstate>,
return 9,
return 6,
conditional branch(ne, to iindex=-1) 10,11,
invokeinterface < Application, Landroid/os/IDumpstate, cancelBugreport(ILjava/lang/String;)V > 10,5,3 @26 exception:12,
13 = getCaughtException ,
17 = invokestatic < Application, Landroid/util/Slog, e(Ljava/lang/String;Ljava/lang/String;Ljava/lang/Throwable;)I > 14,15,13 @35 exception:16,
invokestatic < Application, Landroid/os/SystemProperties, set(Ljava/lang/String;Ljava/lang/String;)V > 23,24 @42 exception:25,
monitorexit 8,
return,","depth : 0
public void cancelBugreport(int p1, String p2){
	IDumpstate v3 = p0.getDumpstateBinderServiceLocked();
	v3.cancelBugreport(v1, p2);
	int v5 = Slog.e(""BugreportManagerService"", ""RemoteException in cancelBugreport"", caughtException);
	SystemProperties.set(""ctl.stop"", ""bugreportd"");
	return;
}
-----
depth : 1
public IDumpstate getDumpstateBinderServiceLocked(){
	IBinder v1 = ServiceManager.getService(""dumpstate"");
	IDumpstate v2 = IDumpstate$Stub.asInterface(v1);
	return v2;
}
-----
depth : 2
public IDumpstate asInterface(IBinder p1){
	IInterface v1 = p1.queryLocalInterface(""android.os.IDumpstate"");
	return v1;
}
-----
","public void cancelBugreport(int p1, String p2){
	IBinder v4 = ServiceManager.getService(""dumpstate"");
	IInterface v6 = v4.queryLocalInterface(""android.os.IDumpstate"");
	IDumpstate v5 = v6;
	IDumpstate v3 = v5;
	v3.cancelBugreport(v1, p2);
	SystemProperties.set(""ctl.stop"", ""bugreportd"");
	return;
}
","NORMAL"
"Lcom/android/server/os/BugreportManagerServiceImpl","cancelBugreport(ILjava/lang/String;)V","2","5 = invokestatic < Application, Landroid/os/Binder, getCallingUid()I > @0 exception:4,
invokevirtual < Application, Lcom/android/server/os/BugreportManagerServiceImpl, enforcePermission(Ljava/lang/String;IZ)V > 1,3,5,6 @5 exception:7,
8 = getfield < Application, Lcom/android/server/os/BugreportManagerServiceImpl, mLock, <Application,Ljava/lang/Object> > 1,
monitorenter 8,
10 = invokevirtual < Application, Lcom/android/server/os/BugreportManagerServiceImpl, getDumpstateBinderServiceLocked()Landroid/os/IDumpstate; > 1 @11 exception:9,
4 = invokestatic < Application, Landroid/os/ServiceManager, getService(Ljava/lang/String;)Landroid/os/IBinder; > 2 @2 exception:3,
6 = invokestatic < Application, Landroid/os/IDumpstate$Stub, asInterface(Landroid/os/IBinder;)Landroid/os/IDumpstate; > 4 @6 exception:5,
conditional branch(ne, to iindex=-1) 1,2,
5 = invokeinterface < Application, Landroid/os/IBinder, queryLocalInterface(Ljava/lang/String;)Landroid/os/IInterface; > 1,3 @6 exception:4,
conditional branch(eq, to iindex=-1) 5,2,
6 = instanceof 5 <Application,Landroid/os/IDumpstate>,
conditional branch(eq, to iindex=-1) 6,2,
7 = new <Application,Landroid/os/IDumpstate$Stub$Proxy>@20,
invokespecial < Application, Landroid/os/IDumpstate$Stub$Proxy, <init>(Landroid/os/IBinder;)V > 7,1 @22 exception:8,
return 7,
return 6,
conditional branch(ne, to iindex=-1) 10,11,
invokeinterface < Application, Landroid/os/IDumpstate, cancelBugreport(ILjava/lang/String;)V > 10,5,3 @26 exception:12,
goto (from iindex= 15 to iindex = 9),
invokestatic < Application, Landroid/os/SystemProperties, set(Ljava/lang/String;Ljava/lang/String;)V > 23,24 @42 exception:25,
monitorexit 8,
return,","depth : 0
public void cancelBugreport(int p1, String p2){
	IDumpstate v3 = p0.getDumpstateBinderServiceLocked();
	v3.cancelBugreport(v1, p2);
	SystemProperties.set(""ctl.stop"", ""bugreportd"");
	return;
}
-----
depth : 1
public IDumpstate getDumpstateBinderServiceLocked(){
	IBinder v1 = ServiceManager.getService(""dumpstate"");
	IDumpstate v2 = IDumpstate$Stub.asInterface(v1);
	return v2;
}
-----
depth : 2
public IDumpstate asInterface(IBinder p1){
	IInterface v1 = p1.queryLocalInterface(""android.os.IDumpstate"");
	IDumpstate$Stub$Proxy v1 = new IDumpstate$Stub$Proxy(p1);
	return v1;
}
-----
","public void cancelBugreport(int p1, String p2){
	IBinder v4 = ServiceManager.getService(""dumpstate"");
	IInterface v6 = v4.queryLocalInterface(""android.os.IDumpstate"");
	IDumpstate$Stub$Proxy v7 = new IDumpstate$Stub$Proxy(v4);
	IDumpstate v5 = v7;
	IDumpstate v3 = v5;
	v3.cancelBugreport(v1, p2);
	SystemProperties.set(""ctl.stop"", ""bugreportd"");
	return;
}
","NORMAL"

