"Class","Method","Depth","Trace Instruction(s) ...","Java Code Representation","Code Merged","Access Control Level"
"Lcom/android/server/BootReceiver","onReceive(Landroid/content/Context;Landroid/content/Intent;)V","0","4 = new <Application,Lcom/android/server/BootReceiver$1>@0,
invokespecial < Application, Lcom/android/server/BootReceiver$1, <init>(Lcom/android/server/BootReceiver;Landroid/content/Context;)V > 4,1,2 @2 exception:5,
invokevirtual < Application, Ljava/lang/Thread, start()V > 4 @5 exception:6,
8 = getstatic < Application, Landroid/system/OsConstants, O_RDONLY, <Primordial,I> >,
11 = invokestatic < Application, Landroid/system/Os, open(Ljava/lang/String;II)Ljava/io/FileDescriptor; > 7,8,9 @14 exception:10,
14 = getCaughtException ,
18 = invokestatic < Application, Landroid/util/Slog, wtf(Ljava/lang/String;Ljava/lang/String;Ljava/lang/Throwable;)I > 15,16,14 @45 exception:17,
return,","depth : 0
-----
","public void onReceive(Context p1, Intent p2){
	BootReceiver$1 v1 = new BootReceiver$1(p0,p1);
	v1.start();
	FileDescriptor v4 = Os.open(""/sys/kernel/tracing/instances/bootreceiver/trace_pipe"", OsConstants.O_RDONLY, 384);
	return;
}
","NONE"
"Lcom/android/server/BootReceiver","onReceive(Landroid/content/Context;Landroid/content/Intent;)V","0","4 = new <Application,Lcom/android/server/BootReceiver$1>@0,
invokespecial < Application, Lcom/android/server/BootReceiver$1, <init>(Lcom/android/server/BootReceiver;Landroid/content/Context;)V > 4,1,2 @2 exception:5,
invokevirtual < Application, Ljava/lang/Thread, start()V > 4 @5 exception:6,
8 = getstatic < Application, Landroid/system/OsConstants, O_RDONLY, <Primordial,I> >,
11 = invokestatic < Application, Landroid/system/Os, open(Ljava/lang/String;II)Ljava/io/FileDescriptor; > 7,8,9 @14 exception:10,
19 = new <Application,Lcom/android/server/BootReceiver$2>@18,
invokespecial < Application, Lcom/android/server/BootReceiver$2, <init>(Lcom/android/server/BootReceiver;)V > 19,1 @20 exception:20,
22 = invokestatic < Application, Lcom/android/server/IoThread, get()Lcom/android/server/IoThread; > @23 exception:21,
24 = invokevirtual < Application, Landroid/os/HandlerThread, getLooper()Landroid/os/Looper; > 22 @27 exception:23,
26 = invokevirtual < Application, Landroid/os/Looper, getQueue()Landroid/os/MessageQueue; > 24 @31 exception:25,
invokevirtual < Application, Landroid/os/MessageQueue, addOnFileDescriptorEventListener(Ljava/io/FileDescriptor;ILandroid/os/MessageQueue$OnFileDescriptorEventListener;)V > 26,11,27,19 @36 exception:28,
return,","depth : 0
-----
","public void onReceive(Context p1, Intent p2){
	BootReceiver$1 v1 = new BootReceiver$1(p0,p1);
	v1.start();
	FileDescriptor v4 = Os.open(""/sys/kernel/tracing/instances/bootreceiver/trace_pipe"", OsConstants.O_RDONLY, 384);
	BootReceiver$2 v5 = new BootReceiver$2(p0);
	IoThread v7 = IoThread.get();
	Looper v8 = v7.getLooper();
	MessageQueue v9 = v8.getQueue();
	v9.addOnFileDescriptorEventListener(v4, 1, v5);
	return;
}
","NONE"
"Lcom/android/server/BootReceiver","onReceive(Landroid/content/Context;Landroid/content/Intent;)V","1","4 = new <Application,Lcom/android/server/BootReceiver$1>@0,
invokespecial < Application, Lcom/android/server/BootReceiver$1, <init>(Lcom/android/server/BootReceiver;Landroid/content/Context;)V > 4,1,2 @2 exception:5,
invokevirtual < Application, Ljava/lang/Thread, start()V > 4 @5 exception:6,
8 = getstatic < Application, Landroid/system/OsConstants, O_RDONLY, <Primordial,I> >,
11 = invokestatic < Application, Landroid/system/Os, open(Ljava/lang/String;II)Ljava/io/FileDescriptor; > 7,8,9 @14 exception:10,
19 = new <Application,Lcom/android/server/BootReceiver$2>@18,
invokespecial < Application, Lcom/android/server/BootReceiver$2, <init>(Lcom/android/server/BootReceiver;)V > 19,1 @20 exception:20,
22 = invokestatic < Application, Lcom/android/server/IoThread, get()Lcom/android/server/IoThread; > @23 exception:21,
1 = load_metadata: <Application,Lcom/android/server/IoThread>, <Primordial,Ljava/lang/Class>,
monitorenter 1,
invokestatic < Application, Lcom/android/server/IoThread, ensureThreadLocked()V > @3 exception:2,
3 = getstatic < Application, Lcom/android/server/IoThread, sInstance, <Application,Lcom/android/server/IoThread> >,
monitorexit 1,
return 3,
24 = invokevirtual < Application, Landroid/os/HandlerThread, getLooper()Landroid/os/Looper; > 22 @27 exception:23,
26 = invokevirtual < Application, Landroid/os/Looper, getQueue()Landroid/os/MessageQueue; > 24 @31 exception:25,
invokevirtual < Application, Landroid/os/MessageQueue, addOnFileDescriptorEventListener(Ljava/io/FileDescriptor;ILandroid/os/MessageQueue$OnFileDescriptorEventListener;)V > 26,11,27,19 @36 exception:28,
return,","depth : 0
-----
depth : 1
-----
","public void onReceive(Context p1, Intent p2){
	BootReceiver$1 v1 = new BootReceiver$1(p0,p1);
	v1.start();
	FileDescriptor v4 = Os.open(""/sys/kernel/tracing/instances/bootreceiver/trace_pipe"", OsConstants.O_RDONLY, 384);
	BootReceiver$2 v5 = new BootReceiver$2(p0);
	IoThread.ensureThreadLocked();
	IoThread v7 = this.sInstance;
	Looper v9 = v7.getLooper();
	MessageQueue v10 = v9.getQueue();
	v10.addOnFileDescriptorEventListener(v4, 1, v5);
	return;
}
","NONE"
"Lcom/android/server/BootReceiver","onReceive(Landroid/content/Context;Landroid/content/Intent;)V","2","4 = new <Application,Lcom/android/server/BootReceiver$1>@0,
invokespecial < Application, Lcom/android/server/BootReceiver$1, <init>(Lcom/android/server/BootReceiver;Landroid/content/Context;)V > 4,1,2 @2 exception:5,
invokevirtual < Application, Ljava/lang/Thread, start()V > 4 @5 exception:6,
8 = getstatic < Application, Landroid/system/OsConstants, O_RDONLY, <Primordial,I> >,
11 = invokestatic < Application, Landroid/system/Os, open(Ljava/lang/String;II)Ljava/io/FileDescriptor; > 7,8,9 @14 exception:10,
19 = new <Application,Lcom/android/server/BootReceiver$2>@18,
invokespecial < Application, Lcom/android/server/BootReceiver$2, <init>(Lcom/android/server/BootReceiver;)V > 19,1 @20 exception:20,
22 = invokestatic < Application, Lcom/android/server/IoThread, get()Lcom/android/server/IoThread; > @23 exception:21,
1 = load_metadata: <Application,Lcom/android/server/IoThread>, <Primordial,Ljava/lang/Class>,
monitorenter 1,
invokestatic < Application, Lcom/android/server/IoThread, ensureThreadLocked()V > @3 exception:2,
1 = getstatic < Application, Lcom/android/server/IoThread, sInstance, <Application,Lcom/android/server/IoThread> >,
conditional branch(ne, to iindex=-1) 1,2,
3 = new <Application,Lcom/android/server/IoThread>@4,
invokespecial < Application, Lcom/android/server/IoThread, <init>()V > 3 @6 exception:4,
putstatic < Application, Lcom/android/server/IoThread, sInstance, <Application,Lcom/android/server/IoThread> > = 3,
invokevirtual < Application, Landroid/os/HandlerThread, start()V > 3 @11 exception:5,
6 = getstatic < Application, Lcom/android/server/IoThread, sInstance, <Application,Lcom/android/server/IoThread> >,
8 = invokevirtual < Application, Landroid/os/HandlerThread, getLooper()Landroid/os/Looper; > 6 @16 exception:7,
invokevirtual < Application, Landroid/os/Looper, setTraceTag(J)V > 8,9 @23 exception:10,
11 = new <Application,Landroid/os/Handler>@26,
12 = getstatic < Application, Lcom/android/server/IoThread, sInstance, <Application,Lcom/android/server/IoThread> >,
14 = invokevirtual < Application, Landroid/os/HandlerThread, getLooper()Landroid/os/Looper; > 12 @30 exception:13,
invokespecial < Application, Landroid/os/Handler, <init>(Landroid/os/Looper;)V > 11,14 @34 exception:15,
putstatic < Application, Lcom/android/server/IoThread, sHandler, <Application,Landroid/os/Handler> > = 11,
16 = new <Application,Landroid/os/HandlerExecutor>@39,
17 = getstatic < Application, Lcom/android/server/IoThread, sHandler, <Application,Landroid/os/Handler> >,
invokespecial < Application, Landroid/os/HandlerExecutor, <init>(Landroid/os/Handler;)V > 16,17 @43 exception:18,
putstatic < Application, Lcom/android/server/IoThread, sHandlerExecutor, <Application,Landroid/os/HandlerExecutor> > = 16,
return,
3 = getstatic < Application, Lcom/android/server/IoThread, sInstance, <Application,Lcom/android/server/IoThread> >,
monitorexit 1,
return 3,
24 = invokevirtual < Application, Landroid/os/HandlerThread, getLooper()Landroid/os/Looper; > 22 @27 exception:23,
26 = invokevirtual < Application, Landroid/os/Looper, getQueue()Landroid/os/MessageQueue; > 24 @31 exception:25,
invokevirtual < Application, Landroid/os/MessageQueue, addOnFileDescriptorEventListener(Ljava/io/FileDescriptor;ILandroid/os/MessageQueue$OnFileDescriptorEventListener;)V > 26,11,27,19 @36 exception:28,
return,","depth : 0
-----
depth : 1
-----
depth : 2
-----
","public void onReceive(Context p1, Intent p2){
	BootReceiver$1 v1 = new BootReceiver$1(p0,p1);
	v1.start();
	FileDescriptor v4 = Os.open(""/sys/kernel/tracing/instances/bootreceiver/trace_pipe"", OsConstants.O_RDONLY, 384);
	BootReceiver$2 v5 = new BootReceiver$2(p0);
	if (this.sInstance != 0) {
		IoThread v9 = new IoThread();
		this.sInstance = v9;
		v9.start();
		Looper v12 = this.sInstance.getLooper();
		v12.setTraceTag(524288);
		Handler v14 = new Handler(v15);
		Looper v15 = this.sInstance.getLooper();
		this.sHandler = v14;
		HandlerExecutor v17 = new HandlerExecutor(this.sHandler);
		this.sHandlerExecutor = v17;
		IoThread v7 = this.sInstance;
		Looper v19 = v7.getLooper();
		MessageQueue v20 = v19.getQueue();
		v20.addOnFileDescriptorEventListener(v4, 1, v5);
		return;
	}
}
","NONE"

