"Class","Method","Depth","Trace Instruction(s) ...","Java Code Representation","Code Merged","Access Control Level"
"Lcom/android/server/ambientcontext/AmbientContextManagerService$AmbientContextManagerInternal","startConsentActivity([ILjava/lang/String;)V","0","5 = invokestatic < Application, Ljava/util/Objects, requireNonNull(Ljava/lang/Object;)Ljava/lang/Object; > 2 @0 exception:4,
7 = invokestatic < Application, Ljava/util/Objects, requireNonNull(Ljava/lang/Object;)Ljava/lang/Object; > 3 @3 exception:6,
8 = getfield < Application, Lcom/android/server/ambientcontext/AmbientContextManagerService$AmbientContextManagerInternal, this$0, <Application,Lcom/android/server/ambientcontext/AmbientContextManagerService> > 1,
invokestatic < Application, Lcom/android/server/ambientcontext/AmbientContextManagerService, access$400(Lcom/android/server/ambientcontext/AmbientContextManagerService;Ljava/lang/String;)V > 8,3 @8 exception:9,
10 = getfield < Application, Lcom/android/server/ambientcontext/AmbientContextManagerService$AmbientContextManagerInternal, this$0, <Application,Lcom/android/server/ambientcontext/AmbientContextManagerService> > 1,
12 = invokestatic < Application, Lcom/android/server/ambientcontext/AmbientContextManagerService, -$$Nest$fgetmContext(Lcom/android/server/ambientcontext/AmbientContextManagerService;)Landroid/content/Context; > 10 @13 exception:11,
14 = invokestatic < Application, Lcom/android/server/ambientcontext/AmbientContextManagerService, -$$Nest$sfgetTAG()Ljava/lang/String; > @17 exception:13,
invokevirtual < Application, Landroid/content/Context, enforceCallingOrSelfPermission(Ljava/lang/String;Ljava/lang/String;)V > 12,15,14 @23 exception:16,
17 = getfield < Application, Lcom/android/server/ambientcontext/AmbientContextManagerService$AmbientContextManagerInternal, mService, <Application,Lcom/android/server/ambientcontext/AmbientContextManagerPerUserService> > 1,
invokevirtual < Application, Lcom/android/server/ambientcontext/AmbientContextManagerPerUserService, onStartConsentActivity([ILjava/lang/String;)V > 17,2,3 @28 exception:18,
return,","depth : 0
-----
","public void startConsentActivity([I p1, String p2){
	this.mService.onStartConsentActivity(p1, p2);
	return;
}
","NORMAL"

"Lcom/android/server/ambientcontext/AmbientContextManagerService$AmbientContextManagerInternal","registerObserverWithCallback(Landroid/app/ambientcontext/AmbientContextEventRequest;Ljava/lang/String;Landroid/app/ambientcontext/IAmbientContextObserver;)V","0","6 = invokestatic < Application, Lcom/android/server/ambientcontext/AmbientContextManagerService, -$$Nest$sfgetTAG()Ljava/lang/String; > @0 exception:5,
9 = invokestatic < Application, Landroid/util/Slog, i(Ljava/lang/String;Ljava/lang/String;)I > 6,7 @6 exception:8,
11 = invokestatic < Application, Ljava/util/Objects, requireNonNull(Ljava/lang/Object;)Ljava/lang/Object; > 2 @9 exception:10,
13 = invokestatic < Application, Ljava/util/Objects, requireNonNull(Ljava/lang/Object;)Ljava/lang/Object; > 3 @12 exception:12,
15 = invokestatic < Application, Ljava/util/Objects, requireNonNull(Ljava/lang/Object;)Ljava/lang/Object; > 4 @15 exception:14,
16 = getfield < Application, Lcom/android/server/ambientcontext/AmbientContextManagerService$AmbientContextManagerInternal, this$0, <Application,Lcom/android/server/ambientcontext/AmbientContextManagerService> > 1,
18 = invokestatic < Application, Lcom/android/server/ambientcontext/AmbientContextManagerService, -$$Nest$fgetmContext(Lcom/android/server/ambientcontext/AmbientContextManagerService;)Landroid/content/Context; > 16 @20 exception:17,
20 = invokestatic < Application, Lcom/android/server/ambientcontext/AmbientContextManagerService, -$$Nest$sfgetTAG()Ljava/lang/String; > @24 exception:19,
invokevirtual < Application, Landroid/content/Context, enforceCallingOrSelfPermission(Ljava/lang/String;Ljava/lang/String;)V > 18,21,20 @30 exception:22,
23 = getfield < Application, Lcom/android/server/ambientcontext/AmbientContextManagerService$AmbientContextManagerInternal, this$0, <Application,Lcom/android/server/ambientcontext/AmbientContextManagerService> > 1,
invokestatic < Application, Lcom/android/server/ambientcontext/AmbientContextManagerService, access$100(Lcom/android/server/ambientcontext/AmbientContextManagerService;Ljava/lang/String;)V > 23,3 @35 exception:24,
25 = getfield < Application, Lcom/android/server/ambientcontext/AmbientContextManagerService$AmbientContextManagerInternal, this$0, <Application,Lcom/android/server/ambientcontext/AmbientContextManagerService> > 1,
26 = getfield < Application, Lcom/android/server/ambientcontext/AmbientContextManagerService, mIsServiceEnabled, <Primordial,Z> > 25,
conditional branch(ne, to iindex=-1) 26,27,
28 = getfield < Application, Lcom/android/server/ambientcontext/AmbientContextManagerService$AmbientContextManagerInternal, mService, <Application,Lcom/android/server/ambientcontext/AmbientContextManagerPerUserService> > 1,
invokevirtual < Application, Lcom/android/server/ambientcontext/AmbientContextManagerPerUserService, onRegisterObserver(Landroid/app/ambientcontext/AmbientContextEventRequest;Ljava/lang/String;Landroid/app/ambientcontext/IAmbientContextObserver;)V > 28,2,3,4 @60 exception:29,
return,","depth : 0
-----
","public void registerObserverWithCallback(AmbientContextEventRequest p1, String p2, IAmbientContextObserver p3){
	AmbientContextManagerService.access$100(this.this$0, p2);
	if (AmbientContextManagerService.mIsServiceEnabled != 0) {
		this.mService.onRegisterObserver(p1, p2, p3);
		return;
	}
}
","NORMAL"
"Lcom/android/server/ambientcontext/AmbientContextManagerService$AmbientContextManagerInternal","registerObserverWithCallback(Landroid/app/ambientcontext/AmbientContextEventRequest;Ljava/lang/String;Landroid/app/ambientcontext/IAmbientContextObserver;)V","1","6 = invokestatic < Application, Lcom/android/server/ambientcontext/AmbientContextManagerService, -$$Nest$sfgetTAG()Ljava/lang/String; > @0 exception:5,
9 = invokestatic < Application, Landroid/util/Slog, i(Ljava/lang/String;Ljava/lang/String;)I > 6,7 @6 exception:8,
11 = invokestatic < Application, Ljava/util/Objects, requireNonNull(Ljava/lang/Object;)Ljava/lang/Object; > 2 @9 exception:10,
13 = invokestatic < Application, Ljava/util/Objects, requireNonNull(Ljava/lang/Object;)Ljava/lang/Object; > 3 @12 exception:12,
15 = invokestatic < Application, Ljava/util/Objects, requireNonNull(Ljava/lang/Object;)Ljava/lang/Object; > 4 @15 exception:14,
16 = getfield < Application, Lcom/android/server/ambientcontext/AmbientContextManagerService$AmbientContextManagerInternal, this$0, <Application,Lcom/android/server/ambientcontext/AmbientContextManagerService> > 1,
18 = invokestatic < Application, Lcom/android/server/ambientcontext/AmbientContextManagerService, -$$Nest$fgetmContext(Lcom/android/server/ambientcontext/AmbientContextManagerService;)Landroid/content/Context; > 16 @20 exception:17,
20 = invokestatic < Application, Lcom/android/server/ambientcontext/AmbientContextManagerService, -$$Nest$sfgetTAG()Ljava/lang/String; > @24 exception:19,
invokevirtual < Application, Landroid/content/Context, enforceCallingOrSelfPermission(Ljava/lang/String;Ljava/lang/String;)V > 18,21,20 @30 exception:22,
23 = getfield < Application, Lcom/android/server/ambientcontext/AmbientContextManagerService$AmbientContextManagerInternal, this$0, <Application,Lcom/android/server/ambientcontext/AmbientContextManagerService> > 1,
invokestatic < Application, Lcom/android/server/ambientcontext/AmbientContextManagerService, access$100(Lcom/android/server/ambientcontext/AmbientContextManagerService;Ljava/lang/String;)V > 23,3 @35 exception:24,
invokevirtual < Application, Lcom/android/server/infra/AbstractMasterSystemService, assertCalledByPackageOwner(Ljava/lang/String;)V > 1,2 @0 exception:3,
return,
25 = getfield < Application, Lcom/android/server/ambientcontext/AmbientContextManagerService$AmbientContextManagerInternal, this$0, <Application,Lcom/android/server/ambientcontext/AmbientContextManagerService> > 1,
26 = getfield < Application, Lcom/android/server/ambientcontext/AmbientContextManagerService, mIsServiceEnabled, <Primordial,Z> > 25,
conditional branch(ne, to iindex=-1) 26,27,
28 = getfield < Application, Lcom/android/server/ambientcontext/AmbientContextManagerService$AmbientContextManagerInternal, mService, <Application,Lcom/android/server/ambientcontext/AmbientContextManagerPerUserService> > 1,
invokevirtual < Application, Lcom/android/server/ambientcontext/AmbientContextManagerPerUserService, onRegisterObserver(Landroid/app/ambientcontext/AmbientContextEventRequest;Ljava/lang/String;Landroid/app/ambientcontext/IAmbientContextObserver;)V > 28,2,3,4 @60 exception:29,
5 = getfield < Application, Lcom/android/server/infra/AbstractPerUserSystemService, mLock, <Application,Ljava/lang/Object> > 1,
monitorenter 5,
7 = invokevirtual < Application, Lcom/android/server/ambientcontext/AmbientContextManagerPerUserService, setUpServiceIfNeeded()Z > 1 @3 exception:6,
conditional branch(ne, to iindex=-1) 7,8,
invokevirtual < Application, Lcom/android/server/ambientcontext/AmbientContextManagerPerUserService, startDetection(Landroid/app/ambientcontext/AmbientContextEventRequest;Ljava/lang/String;Landroid/app/ambientcontext/IAmbientContextObserver;)V > 1,2,3,4 @22 exception:9,
10 = getfield < Application, Lcom/android/server/infra/AbstractPerUserSystemService, mMaster, <Application,Lcom/android/server/infra/AbstractMasterSystemService> > 1,
11 = checkcast <Application,Lcom/android/server/ambientcontext/AmbientContextManagerService>10 <Application,Lcom/android/server/ambientcontext/AmbientContextManagerService>,
12 = getfield < Application, Lcom/android/server/infra/AbstractPerUserSystemService, mUserId, <Primordial,I> > 1,
invokevirtual < Application, Lcom/android/server/ambientcontext/AmbientContextManagerService, newClientAdded(ILandroid/app/ambientcontext/AmbientContextEventRequest;Ljava/lang/String;Landroid/app/ambientcontext/IAmbientContextObserver;)V > 11,12,2,3,4 @31 exception:13,
monitorexit 5,
return,
return,","depth : 0
-----
depth : 1
-----
depth : 1
-----
","public void registerObserverWithCallback(AmbientContextEventRequest p1, String p2, IAmbientContextObserver p3){
	this.this$0.assertCalledByPackageOwner(p2);
	if (AmbientContextManagerService.mIsServiceEnabled != 0) {
		boolean v12 = AmbientContextManagerPerUserService.setUpServiceIfNeeded();
		if (v12 != 0) {
			AmbientContextManagerPerUserService.startDetection(p1, p2, p3);
			AbstractPerUserSystemService.mMaster.newClientAdded(AbstractPerUserSystemService.mUserId, p1, p2, p3);
			return;
		}
	}
}
","NORMAL"
"Lcom/android/server/ambientcontext/AmbientContextManagerService$AmbientContextManagerInternal","registerObserverWithCallback(Landroid/app/ambientcontext/AmbientContextEventRequest;Ljava/lang/String;Landroid/app/ambientcontext/IAmbientContextObserver;)V","2","6 = invokestatic < Application, Lcom/android/server/ambientcontext/AmbientContextManagerService, -$$Nest$sfgetTAG()Ljava/lang/String; > @0 exception:5,
9 = invokestatic < Application, Landroid/util/Slog, i(Ljava/lang/String;Ljava/lang/String;)I > 6,7 @6 exception:8,
11 = invokestatic < Application, Ljava/util/Objects, requireNonNull(Ljava/lang/Object;)Ljava/lang/Object; > 2 @9 exception:10,
13 = invokestatic < Application, Ljava/util/Objects, requireNonNull(Ljava/lang/Object;)Ljava/lang/Object; > 3 @12 exception:12,
15 = invokestatic < Application, Ljava/util/Objects, requireNonNull(Ljava/lang/Object;)Ljava/lang/Object; > 4 @15 exception:14,
16 = getfield < Application, Lcom/android/server/ambientcontext/AmbientContextManagerService$AmbientContextManagerInternal, this$0, <Application,Lcom/android/server/ambientcontext/AmbientContextManagerService> > 1,
18 = invokestatic < Application, Lcom/android/server/ambientcontext/AmbientContextManagerService, -$$Nest$fgetmContext(Lcom/android/server/ambientcontext/AmbientContextManagerService;)Landroid/content/Context; > 16 @20 exception:17,
20 = invokestatic < Application, Lcom/android/server/ambientcontext/AmbientContextManagerService, -$$Nest$sfgetTAG()Ljava/lang/String; > @24 exception:19,
invokevirtual < Application, Landroid/content/Context, enforceCallingOrSelfPermission(Ljava/lang/String;Ljava/lang/String;)V > 18,21,20 @30 exception:22,
23 = getfield < Application, Lcom/android/server/ambientcontext/AmbientContextManagerService$AmbientContextManagerInternal, this$0, <Application,Lcom/android/server/ambientcontext/AmbientContextManagerService> > 1,
invokestatic < Application, Lcom/android/server/ambientcontext/AmbientContextManagerService, access$100(Lcom/android/server/ambientcontext/AmbientContextManagerService;Ljava/lang/String;)V > 23,3 @35 exception:24,
invokevirtual < Application, Lcom/android/server/infra/AbstractMasterSystemService, assertCalledByPackageOwner(Ljava/lang/String;)V > 1,2 @0 exception:3,
return,
25 = getfield < Application, Lcom/android/server/ambientcontext/AmbientContextManagerService$AmbientContextManagerInternal, this$0, <Application,Lcom/android/server/ambientcontext/AmbientContextManagerService> > 1,
26 = getfield < Application, Lcom/android/server/ambientcontext/AmbientContextManagerService, mIsServiceEnabled, <Primordial,Z> > 25,
conditional branch(ne, to iindex=-1) 26,27,
28 = getfield < Application, Lcom/android/server/ambientcontext/AmbientContextManagerService$AmbientContextManagerInternal, mService, <Application,Lcom/android/server/ambientcontext/AmbientContextManagerPerUserService> > 1,
invokevirtual < Application, Lcom/android/server/ambientcontext/AmbientContextManagerPerUserService, onRegisterObserver(Landroid/app/ambientcontext/AmbientContextEventRequest;Ljava/lang/String;Landroid/app/ambientcontext/IAmbientContextObserver;)V > 28,2,3,4 @60 exception:29,
5 = getfield < Application, Lcom/android/server/infra/AbstractPerUserSystemService, mLock, <Application,Ljava/lang/Object> > 1,
monitorenter 5,
7 = invokevirtual < Application, Lcom/android/server/ambientcontext/AmbientContextManagerPerUserService, setUpServiceIfNeeded()Z > 1 @3 exception:6,
2 = getfield < Application, Lcom/android/server/ambientcontext/AmbientContextManagerPerUserService, mComponentName, <Application,Landroid/content/ComponentName> > 1,
conditional branch(ne, to iindex=-1) 2,3,
5 = invokevirtual < Application, Lcom/android/server/infra/AbstractPerUserSystemService, updateServiceInfoLocked()Landroid/content/ComponentName; > 1 @4 exception:4,
putfield 1.< Application, Lcom/android/server/ambientcontext/AmbientContextManagerPerUserService, mComponentName, <Application,Landroid/content/ComponentName> > = 5,
7 = getfield < Application, Lcom/android/server/ambientcontext/AmbientContextManagerPerUserService, mComponentName, <Application,Landroid/content/ComponentName> > 1,
conditional branch(ne, to iindex=-1) 7,3,
9 = invokestatic < Application, Landroid/app/AppGlobals, getPackageManager()Landroid/content/pm/IPackageManager; > @16 exception:8,
10 = getfield < Application, Lcom/android/server/ambientcontext/AmbientContextManagerPerUserService, mComponentName, <Application,Landroid/content/ComponentName> > 1,
12 = getfield < Application, Lcom/android/server/infra/AbstractPerUserSystemService, mUserId, <Primordial,I> > 1,
14 = invokeinterface < Application, Landroid/content/pm/IPackageManager, getServiceInfo(Landroid/content/ComponentName;JI)Landroid/content/pm/ServiceInfo; > 9,10,11,12 @26 exception:13,
conditional branch(eq, to iindex=-1) 14,3,
20 = phi  3,19,
return 20,
conditional branch(ne, to iindex=-1) 7,8,
invokevirtual < Application, Lcom/android/server/ambientcontext/AmbientContextManagerPerUserService, startDetection(Landroid/app/ambientcontext/AmbientContextEventRequest;Ljava/lang/String;Landroid/app/ambientcontext/IAmbientContextObserver;)V > 1,2,3,4 @22 exception:9,
5 = getstatic < Application, Lcom/android/server/ambientcontext/AmbientContextManagerPerUserService, TAG, <Application,Ljava/lang/String> >,
6 = new <Application,Ljava/lang/StringBuilder>@2,
invokespecial < Application, Ljava/lang/StringBuilder, <init>()V > 6 @4 exception:7,
10 = invokevirtual < Application, Ljava/lang/StringBuilder, append(Ljava/lang/String;)Ljava/lang/StringBuilder; > 6,8 @9 exception:9,
12 = invokevirtual < Application, Landroid/app/ambientcontext/AmbientContextEventRequest, getEventTypes()Ljava/util/Set; > 2 @12 exception:11,
14 = invokevirtual < Application, Ljava/lang/StringBuilder, append(Ljava/lang/Object;)Ljava/lang/StringBuilder; > 6,12 @16 exception:13,
16 = invokevirtual < Application, Ljava/lang/StringBuilder, toString()Ljava/lang/String; > 6 @19 exception:15,
18 = invokestatic < Application, Landroid/util/Slog, d(Ljava/lang/String;Ljava/lang/String;)I > 5,16 @23 exception:17,
19 = getfield < Application, Lcom/android/server/infra/AbstractPerUserSystemService, mLock, <Application,Ljava/lang/Object> > 1,
monitorenter 19,
21 = invokevirtual < Application, Lcom/android/server/ambientcontext/AmbientContextManagerPerUserService, setUpServiceIfNeeded()Z > 1 @29 exception:20,
conditional branch(eq, to iindex=-1) 21,22,
invokevirtual < Application, Lcom/android/server/ambientcontext/AmbientContextManagerPerUserService, ensureRemoteServiceInitiated()V > 1 @35 exception:28,
29 = getfield < Application, Lcom/android/server/ambientcontext/AmbientContextManagerPerUserService, mRemoteService, <Application,Lcom/android/server/ambientcontext/RemoteAmbientContextDetectionService> > 1,
31 = invokevirtual < Application, Lcom/android/server/ambientcontext/AmbientContextManagerPerUserService, createDetectionResultRemoteCallback()Landroid/os/RemoteCallback; > 1 @40 exception:30,
32 = new <Application,Lcom/android/server/ambientcontext/AmbientContextManagerPerUserService$$ExternalSyntheticLambda1>@44,
invokespecial < Application, Lcom/android/server/ambientcontext/AmbientContextManagerPerUserService$$ExternalSyntheticLambda1, <init>(Landroid/app/ambientcontext/IAmbientContextObserver;)V > 32,4 @46 exception:33,
35 = invokevirtual < Application, Lcom/android/server/ambientcontext/AmbientContextManagerPerUserService, getServerStatusCallback(Ljava/util/function/Consumer;)Landroid/os/RemoteCallback; > 1,32 @49 exception:34,
invokevirtual < Application, Lcom/android/server/ambientcontext/RemoteAmbientContextDetectionService, startDetection(Landroid/app/ambientcontext/AmbientContextEventRequest;Ljava/lang/String;Landroid/os/RemoteCallback;Landroid/os/RemoteCallback;)V > 29,2,3,31,35 @53 exception:36,
goto (from iindex= 25 to iindex = 10),
monitorexit 19,
return,
10 = getfield < Application, Lcom/android/server/infra/AbstractPerUserSystemService, mMaster, <Application,Lcom/android/server/infra/AbstractMasterSystemService> > 1,
11 = checkcast <Application,Lcom/android/server/ambientcontext/AmbientContextManagerService>10 <Application,Lcom/android/server/ambientcontext/AmbientContextManagerService>,
12 = getfield < Application, Lcom/android/server/infra/AbstractPerUserSystemService, mUserId, <Primordial,I> > 1,
invokevirtual < Application, Lcom/android/server/ambientcontext/AmbientContextManagerService, newClientAdded(ILandroid/app/ambientcontext/AmbientContextEventRequest;Ljava/lang/String;Landroid/app/ambientcontext/IAmbientContextObserver;)V > 11,12,2,3,4 @31 exception:13,
6 = getstatic < Application, Lcom/android/server/ambientcontext/AmbientContextManagerService, TAG, <Application,Ljava/lang/String> >,
7 = new <Application,Ljava/lang/StringBuilder>@2,
invokespecial < Application, Ljava/lang/StringBuilder, <init>()V > 7 @4 exception:8,
11 = invokevirtual < Application, Ljava/lang/StringBuilder, append(Ljava/lang/String;)Ljava/lang/StringBuilder; > 7,9 @9 exception:10,
13 = invokevirtual < Application, Ljava/lang/StringBuilder, append(Ljava/lang/String;)Ljava/lang/StringBuilder; > 7,4 @12 exception:12,
15 = invokevirtual < Application, Ljava/lang/StringBuilder, toString()Ljava/lang/String; > 7 @15 exception:14,
17 = invokestatic < Application, Landroid/util/Slog, d(Ljava/lang/String;Ljava/lang/String;)I > 6,15 @19 exception:16,
18 = getfield < Application, Lcom/android/server/ambientcontext/AmbientContextManagerService, mExistingClientRequests, <Application,Ljava/util/Set> > 1,
20 = invokevirtual < Application, Lcom/android/server/ambientcontext/AmbientContextManagerService, findExistingRequests(ILjava/lang/String;)Ljava/util/Set; > 1,2,4 @24 exception:19,
22 = invokeinterface < Application, Ljava/util/Set, removeAll(Ljava/util/Collection;)Z > 18,20 @28 exception:21,
23 = getfield < Application, Lcom/android/server/ambientcontext/AmbientContextManagerService, mExistingClientRequests, <Application,Ljava/util/Set> > 1,
24 = new <Application,Lcom/android/server/ambientcontext/AmbientContextManagerService$ClientRequest>@33,
invokespecial < Application, Lcom/android/server/ambientcontext/AmbientContextManagerService$ClientRequest, <init>(ILandroid/app/ambientcontext/AmbientContextEventRequest;Ljava/lang/String;Landroid/app/ambientcontext/IAmbientContextObserver;)V > 24,2,3,4,5 @35 exception:25,
27 = invokeinterface < Application, Ljava/util/Set, add(Ljava/lang/Object;)Z > 23,24 @38 exception:26,
return,
monitorexit 5,
return,
return,","depth : 0
-----
depth : 1
-----
depth : 1
-----
depth : 2
-----
depth : 2
-----
depth : 2
-----
","public void registerObserverWithCallback(AmbientContextEventRequest p1, String p2, IAmbientContextObserver p3){
	this.this$0.assertCalledByPackageOwner(p2);
	if (AmbientContextManagerService.mIsServiceEnabled != 0) {
		if (this.mComponentName != 0) {
			ComponentName v13 = AmbientContextManagerPerUserService.updateServiceInfoLocked();
			this.mComponentName = v13;
			if (this.mComponentName != 0) {
				IPackageManager v14 = AppGlobals.getPackageManager();
				ServiceInfo v15 = v14.getServiceInfo(this.mComponentName, 0, AbstractPerUserSystemService.mUserId);
				if (v15 == 0) {
					boolean v12 = 0;
					if (v12 != 0) {
						Set v20 = p1.getEventTypes();
						boolean v24 = AmbientContextManagerPerUserService.setUpServiceIfNeeded();
						if (v24 == 0) {
							AmbientContextManagerPerUserService.ensureRemoteServiceInitiated();
							RemoteCallback v26 = AmbientContextManagerPerUserService.createDetectionResultRemoteCallback();
							AmbientContextManagerPerUserService$$ExternalSyntheticLambda1 v27 = new AmbientContextManagerPerUserService$$ExternalSyntheticLambda1(p3);
							RemoteCallback v29 = AmbientContextManagerPerUserService.getServerStatusCallback(v27);
							this.mRemoteService.startDetection(p1, p2, v26, v29);
							Set v38 = AmbientContextManagerService.findExistingRequests(AbstractPerUserSystemService.mUserId, p2);
							boolean v39 = this.mExistingClientRequests.removeAll(v38);
							AmbientContextManagerService$ClientRequest v40 = new AmbientContextManagerService$ClientRequest(AbstractPerUserSystemService.mUserId,p1,p2,p3);
							boolean v42 = this.mExistingClientRequests.add(v40);
							return;
						}
					}
				}
			}
		}
	}
}
","NORMAL"

"Lcom/android/server/ambientcontext/AmbientContextManagerService$AmbientContextManagerInternal","unregisterObserver(Ljava/lang/String;)V","0","3 = getfield < Application, Lcom/android/server/ambientcontext/AmbientContextManagerService$AmbientContextManagerInternal, this$0, <Application,Lcom/android/server/ambientcontext/AmbientContextManagerService> > 1,
5 = invokestatic < Application, Lcom/android/server/ambientcontext/AmbientContextManagerService, -$$Nest$fgetmContext(Lcom/android/server/ambientcontext/AmbientContextManagerService;)Landroid/content/Context; > 3 @2 exception:4,
7 = invokestatic < Application, Lcom/android/server/ambientcontext/AmbientContextManagerService, -$$Nest$sfgetTAG()Ljava/lang/String; > @6 exception:6,
invokevirtual < Application, Landroid/content/Context, enforceCallingOrSelfPermission(Ljava/lang/String;Ljava/lang/String;)V > 5,8,7 @12 exception:9,
10 = getfield < Application, Lcom/android/server/ambientcontext/AmbientContextManagerService$AmbientContextManagerInternal, this$0, <Application,Lcom/android/server/ambientcontext/AmbientContextManagerService> > 1,
invokestatic < Application, Lcom/android/server/ambientcontext/AmbientContextManagerService, access$200(Lcom/android/server/ambientcontext/AmbientContextManagerService;Ljava/lang/String;)V > 10,2 @17 exception:11,
12 = getfield < Application, Lcom/android/server/ambientcontext/AmbientContextManagerService$AmbientContextManagerInternal, mService, <Application,Lcom/android/server/ambientcontext/AmbientContextManagerPerUserService> > 1,
invokevirtual < Application, Lcom/android/server/ambientcontext/AmbientContextManagerPerUserService, onUnregisterObserver(Ljava/lang/String;)V > 12,2 @22 exception:13,
return,","depth : 0
-----
","public void unregisterObserver(String p1){
	AmbientContextManagerService.access$200(this.this$0, p1);
	this.mService.onUnregisterObserver(p1);
	return;
}
","NORMAL"
"Lcom/android/server/ambientcontext/AmbientContextManagerService$AmbientContextManagerInternal","unregisterObserver(Ljava/lang/String;)V","1","3 = getfield < Application, Lcom/android/server/ambientcontext/AmbientContextManagerService$AmbientContextManagerInternal, this$0, <Application,Lcom/android/server/ambientcontext/AmbientContextManagerService> > 1,
5 = invokestatic < Application, Lcom/android/server/ambientcontext/AmbientContextManagerService, -$$Nest$fgetmContext(Lcom/android/server/ambientcontext/AmbientContextManagerService;)Landroid/content/Context; > 3 @2 exception:4,
7 = invokestatic < Application, Lcom/android/server/ambientcontext/AmbientContextManagerService, -$$Nest$sfgetTAG()Ljava/lang/String; > @6 exception:6,
invokevirtual < Application, Landroid/content/Context, enforceCallingOrSelfPermission(Ljava/lang/String;Ljava/lang/String;)V > 5,8,7 @12 exception:9,
10 = getfield < Application, Lcom/android/server/ambientcontext/AmbientContextManagerService$AmbientContextManagerInternal, this$0, <Application,Lcom/android/server/ambientcontext/AmbientContextManagerService> > 1,
invokestatic < Application, Lcom/android/server/ambientcontext/AmbientContextManagerService, access$200(Lcom/android/server/ambientcontext/AmbientContextManagerService;Ljava/lang/String;)V > 10,2 @17 exception:11,
invokevirtual < Application, Lcom/android/server/infra/AbstractMasterSystemService, assertCalledByPackageOwner(Ljava/lang/String;)V > 1,2 @0 exception:3,
return,
12 = getfield < Application, Lcom/android/server/ambientcontext/AmbientContextManagerService$AmbientContextManagerInternal, mService, <Application,Lcom/android/server/ambientcontext/AmbientContextManagerPerUserService> > 1,
invokevirtual < Application, Lcom/android/server/ambientcontext/AmbientContextManagerPerUserService, onUnregisterObserver(Ljava/lang/String;)V > 12,2 @22 exception:13,
3 = getfield < Application, Lcom/android/server/infra/AbstractPerUserSystemService, mLock, <Application,Ljava/lang/Object> > 1,
monitorenter 3,
invokevirtual < Application, Lcom/android/server/ambientcontext/AmbientContextManagerPerUserService, stopDetection(Ljava/lang/String;)V > 1,2 @3 exception:4,
5 = getfield < Application, Lcom/android/server/infra/AbstractPerUserSystemService, mMaster, <Application,Lcom/android/server/infra/AbstractMasterSystemService> > 1,
6 = checkcast <Application,Lcom/android/server/ambientcontext/AmbientContextManagerService>5 <Application,Lcom/android/server/ambientcontext/AmbientContextManagerService>,
7 = getfield < Application, Lcom/android/server/infra/AbstractPerUserSystemService, mUserId, <Primordial,I> > 1,
invokevirtual < Application, Lcom/android/server/ambientcontext/AmbientContextManagerService, clientRemoved(ILjava/lang/String;)V > 6,7,2 @12 exception:8,
monitorexit 3,
return,
return,","depth : 0
-----
depth : 1
-----
depth : 1
-----
","public void unregisterObserver(String p1){
	this.this$0.assertCalledByPackageOwner(p1);
	AmbientContextManagerPerUserService.stopDetection(p1);
	AbstractPerUserSystemService.mMaster.clientRemoved(AbstractPerUserSystemService.mUserId, p1);
	return;
}
","NORMAL"
"Lcom/android/server/ambientcontext/AmbientContextManagerService$AmbientContextManagerInternal","unregisterObserver(Ljava/lang/String;)V","2","3 = getfield < Application, Lcom/android/server/ambientcontext/AmbientContextManagerService$AmbientContextManagerInternal, this$0, <Application,Lcom/android/server/ambientcontext/AmbientContextManagerService> > 1,
5 = invokestatic < Application, Lcom/android/server/ambientcontext/AmbientContextManagerService, -$$Nest$fgetmContext(Lcom/android/server/ambientcontext/AmbientContextManagerService;)Landroid/content/Context; > 3 @2 exception:4,
7 = invokestatic < Application, Lcom/android/server/ambientcontext/AmbientContextManagerService, -$$Nest$sfgetTAG()Ljava/lang/String; > @6 exception:6,
invokevirtual < Application, Landroid/content/Context, enforceCallingOrSelfPermission(Ljava/lang/String;Ljava/lang/String;)V > 5,8,7 @12 exception:9,
10 = getfield < Application, Lcom/android/server/ambientcontext/AmbientContextManagerService$AmbientContextManagerInternal, this$0, <Application,Lcom/android/server/ambientcontext/AmbientContextManagerService> > 1,
invokestatic < Application, Lcom/android/server/ambientcontext/AmbientContextManagerService, access$200(Lcom/android/server/ambientcontext/AmbientContextManagerService;Ljava/lang/String;)V > 10,2 @17 exception:11,
invokevirtual < Application, Lcom/android/server/infra/AbstractMasterSystemService, assertCalledByPackageOwner(Ljava/lang/String;)V > 1,2 @0 exception:3,
return,
12 = getfield < Application, Lcom/android/server/ambientcontext/AmbientContextManagerService$AmbientContextManagerInternal, mService, <Application,Lcom/android/server/ambientcontext/AmbientContextManagerPerUserService> > 1,
invokevirtual < Application, Lcom/android/server/ambientcontext/AmbientContextManagerPerUserService, onUnregisterObserver(Ljava/lang/String;)V > 12,2 @22 exception:13,
3 = getfield < Application, Lcom/android/server/infra/AbstractPerUserSystemService, mLock, <Application,Ljava/lang/Object> > 1,
monitorenter 3,
invokevirtual < Application, Lcom/android/server/ambientcontext/AmbientContextManagerPerUserService, stopDetection(Ljava/lang/String;)V > 1,2 @3 exception:4,
3 = getstatic < Application, Lcom/android/server/ambientcontext/AmbientContextManagerPerUserService, TAG, <Application,Ljava/lang/String> >,
4 = new <Application,Ljava/lang/StringBuilder>@2,
invokespecial < Application, Ljava/lang/StringBuilder, <init>()V > 4 @4 exception:5,
8 = invokevirtual < Application, Ljava/lang/StringBuilder, append(Ljava/lang/String;)Ljava/lang/StringBuilder; > 4,6 @9 exception:7,
10 = invokevirtual < Application, Ljava/lang/StringBuilder, append(Ljava/lang/String;)Ljava/lang/StringBuilder; > 4,2 @12 exception:9,
12 = invokevirtual < Application, Ljava/lang/StringBuilder, toString()Ljava/lang/String; > 4 @15 exception:11,
14 = invokestatic < Application, Landroid/util/Slog, d(Ljava/lang/String;Ljava/lang/String;)I > 3,12 @19 exception:13,
15 = getfield < Application, Lcom/android/server/infra/AbstractPerUserSystemService, mLock, <Application,Ljava/lang/Object> > 1,
monitorenter 15,
16 = getfield < Application, Lcom/android/server/ambientcontext/AmbientContextManagerPerUserService, mComponentName, <Application,Landroid/content/ComponentName> > 1,
conditional branch(eq, to iindex=-1) 16,17,
invokevirtual < Application, Lcom/android/server/ambientcontext/AmbientContextManagerPerUserService, ensureRemoteServiceInitiated()V > 1 @29 exception:18,
19 = getfield < Application, Lcom/android/server/ambientcontext/AmbientContextManagerPerUserService, mRemoteService, <Application,Lcom/android/server/ambientcontext/RemoteAmbientContextDetectionService> > 1,
invokevirtual < Application, Lcom/android/server/ambientcontext/RemoteAmbientContextDetectionService, stopDetection(Ljava/lang/String;)V > 19,2 @34 exception:20,
monitorexit 15,
return,
5 = getfield < Application, Lcom/android/server/infra/AbstractPerUserSystemService, mMaster, <Application,Lcom/android/server/infra/AbstractMasterSystemService> > 1,
6 = checkcast <Application,Lcom/android/server/ambientcontext/AmbientContextManagerService>5 <Application,Lcom/android/server/ambientcontext/AmbientContextManagerService>,
7 = getfield < Application, Lcom/android/server/infra/AbstractPerUserSystemService, mUserId, <Primordial,I> > 1,
invokevirtual < Application, Lcom/android/server/ambientcontext/AmbientContextManagerService, clientRemoved(ILjava/lang/String;)V > 6,7,2 @12 exception:8,
4 = getstatic < Application, Lcom/android/server/ambientcontext/AmbientContextManagerService, TAG, <Application,Ljava/lang/String> >,
5 = new <Application,Ljava/lang/StringBuilder>@2,
invokespecial < Application, Ljava/lang/StringBuilder, <init>()V > 5 @4 exception:6,
9 = invokevirtual < Application, Ljava/lang/StringBuilder, append(Ljava/lang/String;)Ljava/lang/StringBuilder; > 5,7 @9 exception:8,
11 = invokevirtual < Application, Ljava/lang/StringBuilder, append(Ljava/lang/String;)Ljava/lang/StringBuilder; > 5,3 @12 exception:10,
13 = invokevirtual < Application, Ljava/lang/StringBuilder, toString()Ljava/lang/String; > 5 @15 exception:12,
15 = invokestatic < Application, Landroid/util/Slog, d(Ljava/lang/String;Ljava/lang/String;)I > 4,13 @19 exception:14,
16 = getfield < Application, Lcom/android/server/ambientcontext/AmbientContextManagerService, mExistingClientRequests, <Application,Ljava/util/Set> > 1,
18 = invokevirtual < Application, Lcom/android/server/ambientcontext/AmbientContextManagerService, findExistingRequests(ILjava/lang/String;)Ljava/util/Set; > 1,2,3 @24 exception:17,
20 = invokeinterface < Application, Ljava/util/Set, removeAll(Ljava/util/Collection;)Z > 16,18 @28 exception:19,
return,
monitorexit 3,
return,
return,","depth : 0
-----
depth : 1
-----
depth : 1
-----
depth : 2
-----
depth : 2
-----
","public void unregisterObserver(String p1){
	this.this$0.assertCalledByPackageOwner(p1);
	if (this.mComponentName == 0) {
		AmbientContextManagerPerUserService.ensureRemoteServiceInitiated();
		this.mRemoteService.stopDetection(p1);
		Set v23 = AmbientContextManagerService.findExistingRequests(AbstractPerUserSystemService.mUserId, p1);
		boolean v24 = this.mExistingClientRequests.removeAll(v23);
		return;
	}
}
","NORMAL"

"Lcom/android/server/ambientcontext/AmbientContextManagerService$AmbientContextManagerInternal","registerObserver(Landroid/app/ambientcontext/AmbientContextEventRequest;Landroid/app/PendingIntent;Landroid/os/RemoteCallback;)V","0","6 = invokestatic < Application, Ljava/util/Objects, requireNonNull(Ljava/lang/Object;)Ljava/lang/Object; > 2 @0 exception:5,
8 = invokestatic < Application, Ljava/util/Objects, requireNonNull(Ljava/lang/Object;)Ljava/lang/Object; > 3 @3 exception:7,
10 = invokestatic < Application, Ljava/util/Objects, requireNonNull(Ljava/lang/Object;)Ljava/lang/Object; > 4 @6 exception:9,
11 = new <Application,Lcom/android/server/ambientcontext/AmbientContextManagerService$AmbientContextManagerInternal$1>@9,
invokespecial < Application, Lcom/android/server/ambientcontext/AmbientContextManagerService$AmbientContextManagerInternal$1, <init>(Lcom/android/server/ambientcontext/AmbientContextManagerService$AmbientContextManagerInternal;Landroid/app/PendingIntent;Landroid/os/RemoteCallback;)V > 11,1,3,4 @11 exception:12,
14 = invokevirtual < Application, Landroid/app/PendingIntent, getCreatorPackage()Ljava/lang/String; > 3 @14 exception:13,
invokevirtual < Application, Lcom/android/server/ambientcontext/AmbientContextManagerService$AmbientContextManagerInternal, registerObserverWithCallback(Landroid/app/ambientcontext/AmbientContextEventRequest;Ljava/lang/String;Landroid/app/ambientcontext/IAmbientContextObserver;)V > 1,2,14,11 @18 exception:15,
return,","depth : 0
-----
","public void registerObserver(AmbientContextEventRequest p1, PendingIntent p2, RemoteCallback p3){
	Object v1 = Objects.requireNonNull(p1);
	Object v2 = Objects.requireNonNull(p2);
	Object v3 = Objects.requireNonNull(p3);
	AmbientContextManagerService$AmbientContextManagerInternal$1 v4 = new AmbientContextManagerService$AmbientContextManagerInternal$1(p0,p2,p3);
	String v6 = p2.getCreatorPackage();
	p0.registerObserverWithCallback(p1, v6, v4);
	return;
}
","NORMAL"
"Lcom/android/server/ambientcontext/AmbientContextManagerService$AmbientContextManagerInternal","registerObserver(Landroid/app/ambientcontext/AmbientContextEventRequest;Landroid/app/PendingIntent;Landroid/os/RemoteCallback;)V","1","6 = invokestatic < Application, Ljava/util/Objects, requireNonNull(Ljava/lang/Object;)Ljava/lang/Object; > 2 @0 exception:5,
8 = invokestatic < Application, Ljava/util/Objects, requireNonNull(Ljava/lang/Object;)Ljava/lang/Object; > 3 @3 exception:7,
10 = invokestatic < Application, Ljava/util/Objects, requireNonNull(Ljava/lang/Object;)Ljava/lang/Object; > 4 @6 exception:9,
11 = new <Application,Lcom/android/server/ambientcontext/AmbientContextManagerService$AmbientContextManagerInternal$1>@9,
invokespecial < Application, Lcom/android/server/ambientcontext/AmbientContextManagerService$AmbientContextManagerInternal$1, <init>(Lcom/android/server/ambientcontext/AmbientContextManagerService$AmbientContextManagerInternal;Landroid/app/PendingIntent;Landroid/os/RemoteCallback;)V > 11,1,3,4 @11 exception:12,
14 = invokevirtual < Application, Landroid/app/PendingIntent, getCreatorPackage()Ljava/lang/String; > 3 @14 exception:13,
invokevirtual < Application, Lcom/android/server/ambientcontext/AmbientContextManagerService$AmbientContextManagerInternal, registerObserverWithCallback(Landroid/app/ambientcontext/AmbientContextEventRequest;Ljava/lang/String;Landroid/app/ambientcontext/IAmbientContextObserver;)V > 1,2,14,11 @18 exception:15,
6 = invokestatic < Application, Lcom/android/server/ambientcontext/AmbientContextManagerService, -$$Nest$sfgetTAG()Ljava/lang/String; > @0 exception:5,
9 = invokestatic < Application, Landroid/util/Slog, i(Ljava/lang/String;Ljava/lang/String;)I > 6,7 @6 exception:8,
11 = invokestatic < Application, Ljava/util/Objects, requireNonNull(Ljava/lang/Object;)Ljava/lang/Object; > 2 @9 exception:10,
13 = invokestatic < Application, Ljava/util/Objects, requireNonNull(Ljava/lang/Object;)Ljava/lang/Object; > 3 @12 exception:12,
15 = invokestatic < Application, Ljava/util/Objects, requireNonNull(Ljava/lang/Object;)Ljava/lang/Object; > 4 @15 exception:14,
16 = getfield < Application, Lcom/android/server/ambientcontext/AmbientContextManagerService$AmbientContextManagerInternal, this$0, <Application,Lcom/android/server/ambientcontext/AmbientContextManagerService> > 1,
18 = invokestatic < Application, Lcom/android/server/ambientcontext/AmbientContextManagerService, -$$Nest$fgetmContext(Lcom/android/server/ambientcontext/AmbientContextManagerService;)Landroid/content/Context; > 16 @20 exception:17,
20 = invokestatic < Application, Lcom/android/server/ambientcontext/AmbientContextManagerService, -$$Nest$sfgetTAG()Ljava/lang/String; > @24 exception:19,
invokevirtual < Application, Landroid/content/Context, enforceCallingOrSelfPermission(Ljava/lang/String;Ljava/lang/String;)V > 18,21,20 @30 exception:22,
23 = getfield < Application, Lcom/android/server/ambientcontext/AmbientContextManagerService$AmbientContextManagerInternal, this$0, <Application,Lcom/android/server/ambientcontext/AmbientContextManagerService> > 1,
invokestatic < Application, Lcom/android/server/ambientcontext/AmbientContextManagerService, access$100(Lcom/android/server/ambientcontext/AmbientContextManagerService;Ljava/lang/String;)V > 23,3 @35 exception:24,
25 = getfield < Application, Lcom/android/server/ambientcontext/AmbientContextManagerService$AmbientContextManagerInternal, this$0, <Application,Lcom/android/server/ambientcontext/AmbientContextManagerService> > 1,
26 = getfield < Application, Lcom/android/server/ambientcontext/AmbientContextManagerService, mIsServiceEnabled, <Primordial,Z> > 25,
conditional branch(ne, to iindex=-1) 26,27,
28 = getfield < Application, Lcom/android/server/ambientcontext/AmbientContextManagerService$AmbientContextManagerInternal, mService, <Application,Lcom/android/server/ambientcontext/AmbientContextManagerPerUserService> > 1,
invokevirtual < Application, Lcom/android/server/ambientcontext/AmbientContextManagerPerUserService, onRegisterObserver(Landroid/app/ambientcontext/AmbientContextEventRequest;Ljava/lang/String;Landroid/app/ambientcontext/IAmbientContextObserver;)V > 28,2,3,4 @60 exception:29,
return,
return,","depth : 0
-----
depth : 1
-----
","public void registerObserver(AmbientContextEventRequest p1, PendingIntent p2, RemoteCallback p3){
	Object v1 = Objects.requireNonNull(p1);
	Object v2 = Objects.requireNonNull(p2);
	Object v3 = Objects.requireNonNull(p3);
	AmbientContextManagerService$AmbientContextManagerInternal$1 v4 = new AmbientContextManagerService$AmbientContextManagerInternal$1(p0,p2,p3);
	String v6 = p2.getCreatorPackage();
	AmbientContextManagerService.access$100(this.this$0, v6);
	if (AmbientContextManagerService.mIsServiceEnabled != 0) {
		this.mService.onRegisterObserver(p1, v6, v4);
		return;
	}
}
","NORMAL"
"Lcom/android/server/ambientcontext/AmbientContextManagerService$AmbientContextManagerInternal","registerObserver(Landroid/app/ambientcontext/AmbientContextEventRequest;Landroid/app/PendingIntent;Landroid/os/RemoteCallback;)V","2","6 = invokestatic < Application, Ljava/util/Objects, requireNonNull(Ljava/lang/Object;)Ljava/lang/Object; > 2 @0 exception:5,
8 = invokestatic < Application, Ljava/util/Objects, requireNonNull(Ljava/lang/Object;)Ljava/lang/Object; > 3 @3 exception:7,
10 = invokestatic < Application, Ljava/util/Objects, requireNonNull(Ljava/lang/Object;)Ljava/lang/Object; > 4 @6 exception:9,
11 = new <Application,Lcom/android/server/ambientcontext/AmbientContextManagerService$AmbientContextManagerInternal$1>@9,
invokespecial < Application, Lcom/android/server/ambientcontext/AmbientContextManagerService$AmbientContextManagerInternal$1, <init>(Lcom/android/server/ambientcontext/AmbientContextManagerService$AmbientContextManagerInternal;Landroid/app/PendingIntent;Landroid/os/RemoteCallback;)V > 11,1,3,4 @11 exception:12,
14 = invokevirtual < Application, Landroid/app/PendingIntent, getCreatorPackage()Ljava/lang/String; > 3 @14 exception:13,
invokevirtual < Application, Lcom/android/server/ambientcontext/AmbientContextManagerService$AmbientContextManagerInternal, registerObserverWithCallback(Landroid/app/ambientcontext/AmbientContextEventRequest;Ljava/lang/String;Landroid/app/ambientcontext/IAmbientContextObserver;)V > 1,2,14,11 @18 exception:15,
6 = invokestatic < Application, Lcom/android/server/ambientcontext/AmbientContextManagerService, -$$Nest$sfgetTAG()Ljava/lang/String; > @0 exception:5,
9 = invokestatic < Application, Landroid/util/Slog, i(Ljava/lang/String;Ljava/lang/String;)I > 6,7 @6 exception:8,
11 = invokestatic < Application, Ljava/util/Objects, requireNonNull(Ljava/lang/Object;)Ljava/lang/Object; > 2 @9 exception:10,
13 = invokestatic < Application, Ljava/util/Objects, requireNonNull(Ljava/lang/Object;)Ljava/lang/Object; > 3 @12 exception:12,
15 = invokestatic < Application, Ljava/util/Objects, requireNonNull(Ljava/lang/Object;)Ljava/lang/Object; > 4 @15 exception:14,
16 = getfield < Application, Lcom/android/server/ambientcontext/AmbientContextManagerService$AmbientContextManagerInternal, this$0, <Application,Lcom/android/server/ambientcontext/AmbientContextManagerService> > 1,
18 = invokestatic < Application, Lcom/android/server/ambientcontext/AmbientContextManagerService, -$$Nest$fgetmContext(Lcom/android/server/ambientcontext/AmbientContextManagerService;)Landroid/content/Context; > 16 @20 exception:17,
20 = invokestatic < Application, Lcom/android/server/ambientcontext/AmbientContextManagerService, -$$Nest$sfgetTAG()Ljava/lang/String; > @24 exception:19,
invokevirtual < Application, Landroid/content/Context, enforceCallingOrSelfPermission(Ljava/lang/String;Ljava/lang/String;)V > 18,21,20 @30 exception:22,
23 = getfield < Application, Lcom/android/server/ambientcontext/AmbientContextManagerService$AmbientContextManagerInternal, this$0, <Application,Lcom/android/server/ambientcontext/AmbientContextManagerService> > 1,
invokestatic < Application, Lcom/android/server/ambientcontext/AmbientContextManagerService, access$100(Lcom/android/server/ambientcontext/AmbientContextManagerService;Ljava/lang/String;)V > 23,3 @35 exception:24,
invokevirtual < Application, Lcom/android/server/infra/AbstractMasterSystemService, assertCalledByPackageOwner(Ljava/lang/String;)V > 1,2 @0 exception:3,
return,
25 = getfield < Application, Lcom/android/server/ambientcontext/AmbientContextManagerService$AmbientContextManagerInternal, this$0, <Application,Lcom/android/server/ambientcontext/AmbientContextManagerService> > 1,
26 = getfield < Application, Lcom/android/server/ambientcontext/AmbientContextManagerService, mIsServiceEnabled, <Primordial,Z> > 25,
conditional branch(ne, to iindex=-1) 26,27,
28 = getfield < Application, Lcom/android/server/ambientcontext/AmbientContextManagerService$AmbientContextManagerInternal, mService, <Application,Lcom/android/server/ambientcontext/AmbientContextManagerPerUserService> > 1,
invokevirtual < Application, Lcom/android/server/ambientcontext/AmbientContextManagerPerUserService, onRegisterObserver(Landroid/app/ambientcontext/AmbientContextEventRequest;Ljava/lang/String;Landroid/app/ambientcontext/IAmbientContextObserver;)V > 28,2,3,4 @60 exception:29,
5 = getfield < Application, Lcom/android/server/infra/AbstractPerUserSystemService, mLock, <Application,Ljava/lang/Object> > 1,
monitorenter 5,
7 = invokevirtual < Application, Lcom/android/server/ambientcontext/AmbientContextManagerPerUserService, setUpServiceIfNeeded()Z > 1 @3 exception:6,
conditional branch(ne, to iindex=-1) 7,8,
invokevirtual < Application, Lcom/android/server/ambientcontext/AmbientContextManagerPerUserService, startDetection(Landroid/app/ambientcontext/AmbientContextEventRequest;Ljava/lang/String;Landroid/app/ambientcontext/IAmbientContextObserver;)V > 1,2,3,4 @22 exception:9,
10 = getfield < Application, Lcom/android/server/infra/AbstractPerUserSystemService, mMaster, <Application,Lcom/android/server/infra/AbstractMasterSystemService> > 1,
11 = checkcast <Application,Lcom/android/server/ambientcontext/AmbientContextManagerService>10 <Application,Lcom/android/server/ambientcontext/AmbientContextManagerService>,
12 = getfield < Application, Lcom/android/server/infra/AbstractPerUserSystemService, mUserId, <Primordial,I> > 1,
invokevirtual < Application, Lcom/android/server/ambientcontext/AmbientContextManagerService, newClientAdded(ILandroid/app/ambientcontext/AmbientContextEventRequest;Ljava/lang/String;Landroid/app/ambientcontext/IAmbientContextObserver;)V > 11,12,2,3,4 @31 exception:13,
monitorexit 5,
return,
return,
return,","depth : 0
-----
depth : 1
-----
depth : 2
-----
depth : 2
-----
","public void registerObserver(AmbientContextEventRequest p1, PendingIntent p2, RemoteCallback p3){
	Object v1 = Objects.requireNonNull(p1);
	Object v2 = Objects.requireNonNull(p2);
	Object v3 = Objects.requireNonNull(p3);
	AmbientContextManagerService$AmbientContextManagerInternal$1 v4 = new AmbientContextManagerService$AmbientContextManagerInternal$1(p0,p2,p3);
	String v6 = p2.getCreatorPackage();
	this.this$0.assertCalledByPackageOwner(v6);
	if (AmbientContextManagerService.mIsServiceEnabled != 0) {
		boolean v19 = AmbientContextManagerPerUserService.setUpServiceIfNeeded();
		if (v19 != 0) {
			AmbientContextManagerPerUserService.startDetection(p1, v6, v4);
			AbstractPerUserSystemService.mMaster.newClientAdded(AbstractPerUserSystemService.mUserId, p1, v6, v4);
			return;
		}
	}
}
","NORMAL"

"Lcom/android/server/ambientcontext/AmbientContextManagerService$AmbientContextManagerInternal","queryServiceStatus([ILjava/lang/String;Landroid/os/RemoteCallback;)V","0","6 = invokestatic < Application, Ljava/util/Objects, requireNonNull(Ljava/lang/Object;)Ljava/lang/Object; > 2 @0 exception:5,
8 = invokestatic < Application, Ljava/util/Objects, requireNonNull(Ljava/lang/Object;)Ljava/lang/Object; > 3 @3 exception:7,
10 = invokestatic < Application, Ljava/util/Objects, requireNonNull(Ljava/lang/Object;)Ljava/lang/Object; > 4 @6 exception:9,
11 = getfield < Application, Lcom/android/server/ambientcontext/AmbientContextManagerService$AmbientContextManagerInternal, this$0, <Application,Lcom/android/server/ambientcontext/AmbientContextManagerService> > 1,
13 = invokestatic < Application, Lcom/android/server/ambientcontext/AmbientContextManagerService, -$$Nest$fgetmContext(Lcom/android/server/ambientcontext/AmbientContextManagerService;)Landroid/content/Context; > 11 @11 exception:12,
15 = invokestatic < Application, Lcom/android/server/ambientcontext/AmbientContextManagerService, -$$Nest$sfgetTAG()Ljava/lang/String; > @15 exception:14,
invokevirtual < Application, Landroid/content/Context, enforceCallingOrSelfPermission(Ljava/lang/String;Ljava/lang/String;)V > 13,16,15 @21 exception:17,
18 = getfield < Application, Lcom/android/server/ambientcontext/AmbientContextManagerService$AmbientContextManagerInternal, this$0, <Application,Lcom/android/server/ambientcontext/AmbientContextManagerService> > 1,
invokestatic < Application, Lcom/android/server/ambientcontext/AmbientContextManagerService, access$300(Lcom/android/server/ambientcontext/AmbientContextManagerService;Ljava/lang/String;)V > 18,3 @26 exception:19,
20 = getfield < Application, Lcom/android/server/ambientcontext/AmbientContextManagerService$AmbientContextManagerInternal, this$0, <Application,Lcom/android/server/ambientcontext/AmbientContextManagerService> > 1,
21 = getfield < Application, Lcom/android/server/ambientcontext/AmbientContextManagerService, mIsServiceEnabled, <Primordial,Z> > 20,
conditional branch(ne, to iindex=-1) 21,22,
23 = getfield < Application, Lcom/android/server/ambientcontext/AmbientContextManagerService$AmbientContextManagerInternal, mService, <Application,Lcom/android/server/ambientcontext/AmbientContextManagerPerUserService> > 1,
invokevirtual < Application, Lcom/android/server/ambientcontext/AmbientContextManagerPerUserService, onQueryServiceStatus([ILjava/lang/String;Landroid/os/RemoteCallback;)V > 23,2,3,4 @51 exception:24,
return,","depth : 0
-----
","public void queryServiceStatus([I p1, String p2, RemoteCallback p3){
	AmbientContextManagerService.access$300(this.this$0, p2);
	if (AmbientContextManagerService.mIsServiceEnabled != 0) {
		this.mService.onQueryServiceStatus(p1, p2, p3);
		return;
	}
}
","NORMAL"
"Lcom/android/server/ambientcontext/AmbientContextManagerService$AmbientContextManagerInternal","queryServiceStatus([ILjava/lang/String;Landroid/os/RemoteCallback;)V","1","6 = invokestatic < Application, Ljava/util/Objects, requireNonNull(Ljava/lang/Object;)Ljava/lang/Object; > 2 @0 exception:5,
8 = invokestatic < Application, Ljava/util/Objects, requireNonNull(Ljava/lang/Object;)Ljava/lang/Object; > 3 @3 exception:7,
10 = invokestatic < Application, Ljava/util/Objects, requireNonNull(Ljava/lang/Object;)Ljava/lang/Object; > 4 @6 exception:9,
11 = getfield < Application, Lcom/android/server/ambientcontext/AmbientContextManagerService$AmbientContextManagerInternal, this$0, <Application,Lcom/android/server/ambientcontext/AmbientContextManagerService> > 1,
13 = invokestatic < Application, Lcom/android/server/ambientcontext/AmbientContextManagerService, -$$Nest$fgetmContext(Lcom/android/server/ambientcontext/AmbientContextManagerService;)Landroid/content/Context; > 11 @11 exception:12,
15 = invokestatic < Application, Lcom/android/server/ambientcontext/AmbientContextManagerService, -$$Nest$sfgetTAG()Ljava/lang/String; > @15 exception:14,
invokevirtual < Application, Landroid/content/Context, enforceCallingOrSelfPermission(Ljava/lang/String;Ljava/lang/String;)V > 13,16,15 @21 exception:17,
18 = getfield < Application, Lcom/android/server/ambientcontext/AmbientContextManagerService$AmbientContextManagerInternal, this$0, <Application,Lcom/android/server/ambientcontext/AmbientContextManagerService> > 1,
invokestatic < Application, Lcom/android/server/ambientcontext/AmbientContextManagerService, access$300(Lcom/android/server/ambientcontext/AmbientContextManagerService;Ljava/lang/String;)V > 18,3 @26 exception:19,
invokevirtual < Application, Lcom/android/server/infra/AbstractMasterSystemService, assertCalledByPackageOwner(Ljava/lang/String;)V > 1,2 @0 exception:3,
return,
20 = getfield < Application, Lcom/android/server/ambientcontext/AmbientContextManagerService$AmbientContextManagerInternal, this$0, <Application,Lcom/android/server/ambientcontext/AmbientContextManagerService> > 1,
21 = getfield < Application, Lcom/android/server/ambientcontext/AmbientContextManagerService, mIsServiceEnabled, <Primordial,Z> > 20,
conditional branch(ne, to iindex=-1) 21,22,
23 = getfield < Application, Lcom/android/server/ambientcontext/AmbientContextManagerService$AmbientContextManagerInternal, mService, <Application,Lcom/android/server/ambientcontext/AmbientContextManagerPerUserService> > 1,
invokevirtual < Application, Lcom/android/server/ambientcontext/AmbientContextManagerPerUserService, onQueryServiceStatus([ILjava/lang/String;Landroid/os/RemoteCallback;)V > 23,2,3,4 @51 exception:24,
5 = getstatic < Application, Lcom/android/server/ambientcontext/AmbientContextManagerPerUserService, TAG, <Application,Ljava/lang/String> >,
6 = new <Application,Ljava/lang/StringBuilder>@2,
invokespecial < Application, Ljava/lang/StringBuilder, <init>()V > 6 @4 exception:7,
10 = invokevirtual < Application, Ljava/lang/StringBuilder, append(Ljava/lang/String;)Ljava/lang/StringBuilder; > 6,8 @9 exception:9,
12 = invokestatic < Application, Ljava/util/Arrays, toString([I)Ljava/lang/String; > 2 @12 exception:11,
14 = invokevirtual < Application, Ljava/lang/StringBuilder, append(Ljava/lang/String;)Ljava/lang/StringBuilder; > 6,12 @16 exception:13,
17 = invokevirtual < Application, Ljava/lang/StringBuilder, append(Ljava/lang/String;)Ljava/lang/StringBuilder; > 6,15 @21 exception:16,
19 = invokevirtual < Application, Ljava/lang/StringBuilder, append(Ljava/lang/String;)Ljava/lang/StringBuilder; > 6,3 @24 exception:18,
21 = invokevirtual < Application, Ljava/lang/StringBuilder, toString()Ljava/lang/String; > 6 @27 exception:20,
23 = invokestatic < Application, Landroid/util/Slog, d(Ljava/lang/String;Ljava/lang/String;)I > 5,21 @31 exception:22,
24 = getfield < Application, Lcom/android/server/infra/AbstractPerUserSystemService, mLock, <Application,Ljava/lang/Object> > 1,
monitorenter 24,
26 = invokevirtual < Application, Lcom/android/server/ambientcontext/AmbientContextManagerPerUserService, setUpServiceIfNeeded()Z > 1 @37 exception:25,
conditional branch(ne, to iindex=-1) 26,27,
invokevirtual < Application, Lcom/android/server/ambientcontext/AmbientContextManagerPerUserService, ensureRemoteServiceInitiated()V > 1 @54 exception:28,
29 = getfield < Application, Lcom/android/server/ambientcontext/AmbientContextManagerPerUserService, mRemoteService, <Application,Lcom/android/server/ambientcontext/RemoteAmbientContextDetectionService> > 1,
30 = new <Application,Lcom/android/server/ambientcontext/AmbientContextManagerPerUserService$$ExternalSyntheticLambda0>@59,
invokespecial < Application, Lcom/android/server/ambientcontext/AmbientContextManagerPerUserService$$ExternalSyntheticLambda0, <init>(Landroid/os/RemoteCallback;)V > 30,4 @61 exception:31,
33 = invokevirtual < Application, Lcom/android/server/ambientcontext/AmbientContextManagerPerUserService, getServerStatusCallback(Ljava/util/function/Consumer;)Landroid/os/RemoteCallback; > 1,30 @64 exception:32,
invokevirtual < Application, Lcom/android/server/ambientcontext/RemoteAmbientContextDetectionService, queryServiceStatus([ILjava/lang/String;Landroid/os/RemoteCallback;)V > 29,2,3,33 @68 exception:34,
monitorexit 24,
return,
return,","depth : 0
-----
depth : 1
-----
depth : 1
-----
","public void queryServiceStatus([I p1, String p2, RemoteCallback p3){
	this.this$0.assertCalledByPackageOwner(p2);
	if (AmbientContextManagerService.mIsServiceEnabled != 0) {
		String v13 = Arrays.toString(p1);
		boolean v19 = AmbientContextManagerPerUserService.setUpServiceIfNeeded();
		if (v19 != 0) {
			AmbientContextManagerPerUserService.ensureRemoteServiceInitiated();
			AmbientContextManagerPerUserService$$ExternalSyntheticLambda0 v21 = new AmbientContextManagerPerUserService$$ExternalSyntheticLambda0(p3);
			RemoteCallback v23 = AmbientContextManagerPerUserService.getServerStatusCallback(v21);
			this.mRemoteService.queryServiceStatus(p1, p2, v23);
			return;
		}
	}
}
","NORMAL"
"Lcom/android/server/ambientcontext/AmbientContextManagerService$AmbientContextManagerInternal","queryServiceStatus([ILjava/lang/String;Landroid/os/RemoteCallback;)V","2","6 = invokestatic < Application, Ljava/util/Objects, requireNonNull(Ljava/lang/Object;)Ljava/lang/Object; > 2 @0 exception:5,
8 = invokestatic < Application, Ljava/util/Objects, requireNonNull(Ljava/lang/Object;)Ljava/lang/Object; > 3 @3 exception:7,
10 = invokestatic < Application, Ljava/util/Objects, requireNonNull(Ljava/lang/Object;)Ljava/lang/Object; > 4 @6 exception:9,
11 = getfield < Application, Lcom/android/server/ambientcontext/AmbientContextManagerService$AmbientContextManagerInternal, this$0, <Application,Lcom/android/server/ambientcontext/AmbientContextManagerService> > 1,
13 = invokestatic < Application, Lcom/android/server/ambientcontext/AmbientContextManagerService, -$$Nest$fgetmContext(Lcom/android/server/ambientcontext/AmbientContextManagerService;)Landroid/content/Context; > 11 @11 exception:12,
15 = invokestatic < Application, Lcom/android/server/ambientcontext/AmbientContextManagerService, -$$Nest$sfgetTAG()Ljava/lang/String; > @15 exception:14,
invokevirtual < Application, Landroid/content/Context, enforceCallingOrSelfPermission(Ljava/lang/String;Ljava/lang/String;)V > 13,16,15 @21 exception:17,
18 = getfield < Application, Lcom/android/server/ambientcontext/AmbientContextManagerService$AmbientContextManagerInternal, this$0, <Application,Lcom/android/server/ambientcontext/AmbientContextManagerService> > 1,
invokestatic < Application, Lcom/android/server/ambientcontext/AmbientContextManagerService, access$300(Lcom/android/server/ambientcontext/AmbientContextManagerService;Ljava/lang/String;)V > 18,3 @26 exception:19,
invokevirtual < Application, Lcom/android/server/infra/AbstractMasterSystemService, assertCalledByPackageOwner(Ljava/lang/String;)V > 1,2 @0 exception:3,
return,
20 = getfield < Application, Lcom/android/server/ambientcontext/AmbientContextManagerService$AmbientContextManagerInternal, this$0, <Application,Lcom/android/server/ambientcontext/AmbientContextManagerService> > 1,
21 = getfield < Application, Lcom/android/server/ambientcontext/AmbientContextManagerService, mIsServiceEnabled, <Primordial,Z> > 20,
conditional branch(ne, to iindex=-1) 21,22,
23 = getfield < Application, Lcom/android/server/ambientcontext/AmbientContextManagerService$AmbientContextManagerInternal, mService, <Application,Lcom/android/server/ambientcontext/AmbientContextManagerPerUserService> > 1,
invokevirtual < Application, Lcom/android/server/ambientcontext/AmbientContextManagerPerUserService, onQueryServiceStatus([ILjava/lang/String;Landroid/os/RemoteCallback;)V > 23,2,3,4 @51 exception:24,
5 = getstatic < Application, Lcom/android/server/ambientcontext/AmbientContextManagerPerUserService, TAG, <Application,Ljava/lang/String> >,
6 = new <Application,Ljava/lang/StringBuilder>@2,
invokespecial < Application, Ljava/lang/StringBuilder, <init>()V > 6 @4 exception:7,
10 = invokevirtual < Application, Ljava/lang/StringBuilder, append(Ljava/lang/String;)Ljava/lang/StringBuilder; > 6,8 @9 exception:9,
12 = invokestatic < Application, Ljava/util/Arrays, toString([I)Ljava/lang/String; > 2 @12 exception:11,
14 = invokevirtual < Application, Ljava/lang/StringBuilder, append(Ljava/lang/String;)Ljava/lang/StringBuilder; > 6,12 @16 exception:13,
17 = invokevirtual < Application, Ljava/lang/StringBuilder, append(Ljava/lang/String;)Ljava/lang/StringBuilder; > 6,15 @21 exception:16,
19 = invokevirtual < Application, Ljava/lang/StringBuilder, append(Ljava/lang/String;)Ljava/lang/StringBuilder; > 6,3 @24 exception:18,
21 = invokevirtual < Application, Ljava/lang/StringBuilder, toString()Ljava/lang/String; > 6 @27 exception:20,
23 = invokestatic < Application, Landroid/util/Slog, d(Ljava/lang/String;Ljava/lang/String;)I > 5,21 @31 exception:22,
24 = getfield < Application, Lcom/android/server/infra/AbstractPerUserSystemService, mLock, <Application,Ljava/lang/Object> > 1,
monitorenter 24,
26 = invokevirtual < Application, Lcom/android/server/ambientcontext/AmbientContextManagerPerUserService, setUpServiceIfNeeded()Z > 1 @37 exception:25,
2 = getfield < Application, Lcom/android/server/ambientcontext/AmbientContextManagerPerUserService, mComponentName, <Application,Landroid/content/ComponentName> > 1,
conditional branch(ne, to iindex=-1) 2,3,
5 = invokevirtual < Application, Lcom/android/server/infra/AbstractPerUserSystemService, updateServiceInfoLocked()Landroid/content/ComponentName; > 1 @4 exception:4,
putfield 1.< Application, Lcom/android/server/ambientcontext/AmbientContextManagerPerUserService, mComponentName, <Application,Landroid/content/ComponentName> > = 5,
7 = getfield < Application, Lcom/android/server/ambientcontext/AmbientContextManagerPerUserService, mComponentName, <Application,Landroid/content/ComponentName> > 1,
conditional branch(ne, to iindex=-1) 7,3,
9 = invokestatic < Application, Landroid/app/AppGlobals, getPackageManager()Landroid/content/pm/IPackageManager; > @16 exception:8,
10 = getfield < Application, Lcom/android/server/ambientcontext/AmbientContextManagerPerUserService, mComponentName, <Application,Landroid/content/ComponentName> > 1,
12 = getfield < Application, Lcom/android/server/infra/AbstractPerUserSystemService, mUserId, <Primordial,I> > 1,
14 = invokeinterface < Application, Landroid/content/pm/IPackageManager, getServiceInfo(Landroid/content/ComponentName;JI)Landroid/content/pm/ServiceInfo; > 9,10,11,12 @26 exception:13,
conditional branch(eq, to iindex=-1) 14,3,
20 = phi  3,19,
return 20,
conditional branch(ne, to iindex=-1) 26,27,
invokevirtual < Application, Lcom/android/server/ambientcontext/AmbientContextManagerPerUserService, ensureRemoteServiceInitiated()V > 1 @54 exception:28,
2 = getfield < Application, Lcom/android/server/ambientcontext/AmbientContextManagerPerUserService, mRemoteService, <Application,Lcom/android/server/ambientcontext/RemoteAmbientContextDetectionService> > 1,
conditional branch(ne, to iindex=-1) 2,3,
4 = new <Application,Lcom/android/server/ambientcontext/RemoteAmbientContextDetectionService>@4,
6 = invokevirtual < Application, Lcom/android/server/infra/AbstractPerUserSystemService, getContext()Landroid/content/Context; > 1 @6 exception:5,
7 = getfield < Application, Lcom/android/server/ambientcontext/AmbientContextManagerPerUserService, mComponentName, <Application,Landroid/content/ComponentName> > 1,
9 = invokevirtual < Application, Lcom/android/server/infra/AbstractPerUserSystemService, getUserId()I > 1 @12 exception:8,
invokespecial < Application, Lcom/android/server/ambientcontext/RemoteAmbientContextDetectionService, <init>(Landroid/content/Context;Landroid/content/ComponentName;I)V > 4,6,7,9 @16 exception:10,
putfield 1.< Application, Lcom/android/server/ambientcontext/AmbientContextManagerPerUserService, mRemoteService, <Application,Lcom/android/server/ambientcontext/RemoteAmbientContextDetectionService> > = 4,
return,
29 = getfield < Application, Lcom/android/server/ambientcontext/AmbientContextManagerPerUserService, mRemoteService, <Application,Lcom/android/server/ambientcontext/RemoteAmbientContextDetectionService> > 1,
30 = new <Application,Lcom/android/server/ambientcontext/AmbientContextManagerPerUserService$$ExternalSyntheticLambda0>@59,
invokespecial < Application, Lcom/android/server/ambientcontext/AmbientContextManagerPerUserService$$ExternalSyntheticLambda0, <init>(Landroid/os/RemoteCallback;)V > 30,4 @61 exception:31,
33 = invokevirtual < Application, Lcom/android/server/ambientcontext/AmbientContextManagerPerUserService, getServerStatusCallback(Ljava/util/function/Consumer;)Landroid/os/RemoteCallback; > 1,30 @64 exception:32,
3 = new <Application,Landroid/os/RemoteCallback>@0,
4 = new <Application,Lcom/android/server/ambientcontext/AmbientContextManagerPerUserService$$ExternalSyntheticLambda2>@2,
invokespecial < Application, Lcom/android/server/ambientcontext/AmbientContextManagerPerUserService$$ExternalSyntheticLambda2, <init>(Ljava/util/function/Consumer;)V > 4,2 @4 exception:5,
invokespecial < Application, Landroid/os/RemoteCallback, <init>(Landroid/os/RemoteCallback$OnResultListener;)V > 3,4 @7 exception:6,
return 3,
invokevirtual < Application, Lcom/android/server/ambientcontext/RemoteAmbientContextDetectionService, queryServiceStatus([ILjava/lang/String;Landroid/os/RemoteCallback;)V > 29,2,3,33 @68 exception:34,
5 = getstatic < Application, Lcom/android/server/ambientcontext/RemoteAmbientContextDetectionService, TAG, <Application,Ljava/lang/String> >,
6 = new <Application,Ljava/lang/StringBuilder>@2,
invokespecial < Application, Ljava/lang/StringBuilder, <init>()V > 6 @4 exception:7,
10 = invokevirtual < Application, Ljava/lang/StringBuilder, append(Ljava/lang/String;)Ljava/lang/StringBuilder; > 6,8 @9 exception:9,
12 = invokevirtual < Application, Ljava/lang/StringBuilder, append(Ljava/lang/String;)Ljava/lang/StringBuilder; > 6,3 @12 exception:11,
14 = invokevirtual < Application, Ljava/lang/StringBuilder, toString()Ljava/lang/String; > 6 @15 exception:13,
16 = invokestatic < Application, Landroid/util/Slog, i(Ljava/lang/String;Ljava/lang/String;)I > 5,14 @19 exception:15,
17 = new <Application,Lcom/android/server/ambientcontext/RemoteAmbientContextDetectionService$$ExternalSyntheticLambda3>@22,
invokespecial < Application, Lcom/android/server/ambientcontext/RemoteAmbientContextDetectionService$$ExternalSyntheticLambda3, <init>([ILjava/lang/String;Landroid/os/RemoteCallback;)V > 17,2,3,4 @24 exception:18,
20 = invokevirtual < Application, Lcom/android/internal/infra/ServiceConnector$Impl, post(Lcom/android/internal/infra/ServiceConnector$VoidJob;)Lcom/android/internal/infra/AndroidFuture; > 1,17 @27 exception:19,
return,
monitorexit 24,
return,
return,","depth : 0
-----
depth : 1
-----
depth : 1
-----
depth : 2
-----
depth : 2
-----
depth : 2
-----
depth : 2
-----
","public void queryServiceStatus([I p1, String p2, RemoteCallback p3){
	this.this$0.assertCalledByPackageOwner(p2);
	if (AmbientContextManagerService.mIsServiceEnabled != 0) {
		String v13 = Arrays.toString(p1);
		if (this.mComponentName != 0) {
			ComponentName v20 = AmbientContextManagerPerUserService.updateServiceInfoLocked();
			this.mComponentName = v20;
			if (this.mComponentName != 0) {
				IPackageManager v21 = AppGlobals.getPackageManager();
				ServiceInfo v22 = v21.getServiceInfo(this.mComponentName, 0, AbstractPerUserSystemService.mUserId);
				if (v22 == 0) {
					boolean v19 = 0;
					if (v19 != 0) {
						if (this.mRemoteService != 0) {
							RemoteAmbientContextDetectionService v24 = new RemoteAmbientContextDetectionService(v25,this.mComponentName,v26);
							Context v25 = AmbientContextManagerPerUserService.getContext();
							int v26 = AmbientContextManagerPerUserService.getUserId();
							this.mRemoteService = v24;
							AmbientContextManagerPerUserService$$ExternalSyntheticLambda0 v28 = new AmbientContextManagerPerUserService$$ExternalSyntheticLambda0(p3);
							RemoteCallback v31 = new RemoteCallback(v32);
							AmbientContextManagerPerUserService$$ExternalSyntheticLambda2 v32 = new AmbientContextManagerPerUserService$$ExternalSyntheticLambda2(v28);
							RemoteCallback v30 = v31;
							RemoteAmbientContextDetectionService$$ExternalSyntheticLambda3 v42 = new RemoteAmbientContextDetectionService$$ExternalSyntheticLambda3(p1,p2,v30);
							AndroidFuture v44 = RemoteAmbientContextDetectionService.post(v42);
							return;
						}
					}
				}
			}
		}
	}
}
","NORMAL"

