"Class","Method","Depth","Trace Instruction(s) ...","Java Code Representation","Code Merged","Access Control Level"
"Lcom/android/server/devicestate/DeviceStateManagerService$BinderService","getDeviceStateInfo()Landroid/hardware/devicestate/DeviceStateInfo;","0","2 = getfield < Application, Lcom/android/server/devicestate/DeviceStateManagerService$BinderService, this$0, <Application,Lcom/android/server/devicestate/DeviceStateManagerService> > 1,
4 = invokestatic < Application, Lcom/android/server/devicestate/DeviceStateManagerService, -$$Nest$fgetmLock(Lcom/android/server/devicestate/DeviceStateManagerService;)Ljava/lang/Object; > 2 @2 exception:3,
monitorenter 4,
5 = getfield < Application, Lcom/android/server/devicestate/DeviceStateManagerService$BinderService, this$0, <Application,Lcom/android/server/devicestate/DeviceStateManagerService> > 1,
7 = invokestatic < Application, Lcom/android/server/devicestate/DeviceStateManagerService, -$$Nest$mgetDeviceStateInfoLocked(Lcom/android/server/devicestate/DeviceStateManagerService;)Landroid/hardware/devicestate/DeviceStateInfo; > 5 @9 exception:6,
monitorexit 4,
return 7,","depth : 0
-----
","public DeviceStateInfo getDeviceStateInfo(){
	Object v1 = DeviceStateManagerService.-$$Nest$fgetmLock(this.this$0);
	DeviceStateInfo v2 = DeviceStateManagerService.-$$Nest$mgetDeviceStateInfoLocked(this.this$0);
	return v2;
}
","NONE"
"Lcom/android/server/devicestate/DeviceStateManagerService$BinderService","getDeviceStateInfo()Landroid/hardware/devicestate/DeviceStateInfo;","1","2 = getfield < Application, Lcom/android/server/devicestate/DeviceStateManagerService$BinderService, this$0, <Application,Lcom/android/server/devicestate/DeviceStateManagerService> > 1,
4 = invokestatic < Application, Lcom/android/server/devicestate/DeviceStateManagerService, -$$Nest$fgetmLock(Lcom/android/server/devicestate/DeviceStateManagerService;)Ljava/lang/Object; > 2 @2 exception:3,
2 = getfield < Application, Lcom/android/server/devicestate/DeviceStateManagerService, mLock, <Application,Ljava/lang/Object> > 1,
return 2,
monitorenter 4,
5 = getfield < Application, Lcom/android/server/devicestate/DeviceStateManagerService$BinderService, this$0, <Application,Lcom/android/server/devicestate/DeviceStateManagerService> > 1,
7 = invokestatic < Application, Lcom/android/server/devicestate/DeviceStateManagerService, -$$Nest$mgetDeviceStateInfoLocked(Lcom/android/server/devicestate/DeviceStateManagerService;)Landroid/hardware/devicestate/DeviceStateInfo; > 5 @9 exception:6,
3 = invokevirtual < Application, Lcom/android/server/devicestate/DeviceStateManagerService, getDeviceStateInfoLocked()Landroid/hardware/devicestate/DeviceStateInfo; > 1 @0 exception:2,
return 3,
monitorexit 4,
return 7,","depth : 0
-----
depth : 1
-----
depth : 1
-----
","public DeviceStateInfo getDeviceStateInfo(){
	Object v1 = this.mLock;
	DeviceStateInfo v3 = this.this$0.getDeviceStateInfoLocked();
	DeviceStateInfo v2 = v3;
	return v2;
}
","NONE"
"Lcom/android/server/devicestate/DeviceStateManagerService$BinderService","getDeviceStateInfo()Landroid/hardware/devicestate/DeviceStateInfo;","2","2 = getfield < Application, Lcom/android/server/devicestate/DeviceStateManagerService$BinderService, this$0, <Application,Lcom/android/server/devicestate/DeviceStateManagerService> > 1,
4 = invokestatic < Application, Lcom/android/server/devicestate/DeviceStateManagerService, -$$Nest$fgetmLock(Lcom/android/server/devicestate/DeviceStateManagerService;)Ljava/lang/Object; > 2 @2 exception:3,
2 = getfield < Application, Lcom/android/server/devicestate/DeviceStateManagerService, mLock, <Application,Ljava/lang/Object> > 1,
return 2,
monitorenter 4,
5 = getfield < Application, Lcom/android/server/devicestate/DeviceStateManagerService$BinderService, this$0, <Application,Lcom/android/server/devicestate/DeviceStateManagerService> > 1,
7 = invokestatic < Application, Lcom/android/server/devicestate/DeviceStateManagerService, -$$Nest$mgetDeviceStateInfoLocked(Lcom/android/server/devicestate/DeviceStateManagerService;)Landroid/hardware/devicestate/DeviceStateInfo; > 5 @9 exception:6,
3 = invokevirtual < Application, Lcom/android/server/devicestate/DeviceStateManagerService, getDeviceStateInfoLocked()Landroid/hardware/devicestate/DeviceStateInfo; > 1 @0 exception:2,
2 = getfield < Application, Lcom/android/server/devicestate/DeviceStateManagerService, mBaseState, <Application,Ljava/util/Optional> > 1,
4 = invokevirtual < Application, Ljava/util/Optional, isPresent()Z > 2 @2 exception:3,
conditional branch(eq, to iindex=-1) 4,5,
6 = getfield < Application, Lcom/android/server/devicestate/DeviceStateManagerService, mCommittedState, <Application,Ljava/util/Optional> > 1,
8 = invokevirtual < Application, Ljava/util/Optional, isPresent()Z > 6 @10 exception:7,
conditional branch(eq, to iindex=-1) 8,5,
16 = invokevirtual < Application, Lcom/android/server/devicestate/DeviceStateManagerService, getSupportedStateIdentifiersLocked()[I > 1 @16 exception:15,
17 = getfield < Application, Lcom/android/server/devicestate/DeviceStateManagerService, mBaseState, <Application,Ljava/util/Optional> > 1,
19 = invokevirtual < Application, Ljava/util/Optional, get()Ljava/lang/Object; > 17 @22 exception:18,
20 = checkcast <Application,Lcom/android/server/devicestate/DeviceState>19 <Application,Lcom/android/server/devicestate/DeviceState>,
22 = invokevirtual < Application, Lcom/android/server/devicestate/DeviceState, getIdentifier()I > 20 @28 exception:21,
23 = getfield < Application, Lcom/android/server/devicestate/DeviceStateManagerService, mCommittedState, <Application,Ljava/util/Optional> > 1,
25 = invokevirtual < Application, Ljava/util/Optional, get()Ljava/lang/Object; > 23 @34 exception:24,
26 = checkcast <Application,Lcom/android/server/devicestate/DeviceState>25 <Application,Lcom/android/server/devicestate/DeviceState>,
28 = invokevirtual < Application, Lcom/android/server/devicestate/DeviceState, getIdentifier()I > 26 @40 exception:27,
29 = new <Application,Landroid/hardware/devicestate/DeviceStateInfo>@44,
invokespecial < Application, Landroid/hardware/devicestate/DeviceStateInfo, <init>([III)V > 29,16,22,28 @46 exception:30,
return 29,
return 3,
monitorexit 4,
return 7,","depth : 0
-----
depth : 1
-----
depth : 1
-----
depth : 2
-----
","public DeviceStateInfo getDeviceStateInfo(){
	Object v1 = this.mLock;
	boolean v4 = this.mBaseState.isPresent();
	if (v4 == 0) {
		boolean v5 = this.mCommittedState.isPresent();
		if (v5 == 0) {
			[I v6 = DeviceStateManagerService.getSupportedStateIdentifiersLocked();
			Object v7 = this.mBaseState.get();
			int v8 = v7.getIdentifier();
			Object v9 = this.mCommittedState.get();
			int v10 = v9.getIdentifier();
			DeviceStateInfo v11 = new DeviceStateInfo(v6,v8,v10);
			DeviceStateInfo v3 = v11;
			DeviceStateInfo v2 = v3;
			return v2;
		}
	}
}
","NONE"

"Lcom/android/server/devicestate/DeviceStateManagerService$BinderService","requestBaseStateOverride(Landroid/os/IBinder;II)V","0","6 = invokestatic < Application, Landroid/os/Binder, getCallingPid()I > @0 exception:5,
7 = getfield < Application, Lcom/android/server/devicestate/DeviceStateManagerService$BinderService, this$0, <Application,Lcom/android/server/devicestate/DeviceStateManagerService> > 1,
9 = invokevirtual < Application, Lcom/android/server/SystemService, getContext()Landroid/content/Context; > 7 @6 exception:8,
invokevirtual < Application, Landroid/content/Context, enforceCallingOrSelfPermission(Ljava/lang/String;Ljava/lang/String;)V > 9,10,11 @14 exception:12,
conditional branch(eq, to iindex=-1) 2,13,
18 = invokestatic < Application, Landroid/os/Binder, clearCallingIdentity()J > @19 exception:17,
19 = getfield < Application, Lcom/android/server/devicestate/DeviceStateManagerService$BinderService, this$0, <Application,Lcom/android/server/devicestate/DeviceStateManagerService> > 1,
invokestatic < Application, Lcom/android/server/devicestate/DeviceStateManagerService, -$$Nest$mrequestBaseStateOverrideInternal(Lcom/android/server/devicestate/DeviceStateManagerService;IIILandroid/os/IBinder;)V > 19,3,4,6,2 @25 exception:20,
invokestatic < Application, Landroid/os/Binder, restoreCallingIdentity(J)V > 18 @28 exception:24,
return,","depth : 0
-----
","public void requestBaseStateOverride(IBinder p1, int p2, int p3){
	if (p1 == 0) {
		long v4 = Binder.clearCallingIdentity();
		DeviceStateManagerService.-$$Nest$mrequestBaseStateOverrideInternal(this.this$0, p2, p3, v1, p1);
		Binder.restoreCallingIdentity(v4);
		return;
	}
}
","SYS_OR_SIG"
"Lcom/android/server/devicestate/DeviceStateManagerService$BinderService","requestBaseStateOverride(Landroid/os/IBinder;II)V","1","6 = invokestatic < Application, Landroid/os/Binder, getCallingPid()I > @0 exception:5,
7 = getfield < Application, Lcom/android/server/devicestate/DeviceStateManagerService$BinderService, this$0, <Application,Lcom/android/server/devicestate/DeviceStateManagerService> > 1,
9 = invokevirtual < Application, Lcom/android/server/SystemService, getContext()Landroid/content/Context; > 7 @6 exception:8,
invokevirtual < Application, Landroid/content/Context, enforceCallingOrSelfPermission(Ljava/lang/String;Ljava/lang/String;)V > 9,10,11 @14 exception:12,
conditional branch(eq, to iindex=-1) 2,13,
18 = invokestatic < Application, Landroid/os/Binder, clearCallingIdentity()J > @19 exception:17,
19 = getfield < Application, Lcom/android/server/devicestate/DeviceStateManagerService$BinderService, this$0, <Application,Lcom/android/server/devicestate/DeviceStateManagerService> > 1,
invokestatic < Application, Lcom/android/server/devicestate/DeviceStateManagerService, -$$Nest$mrequestBaseStateOverrideInternal(Lcom/android/server/devicestate/DeviceStateManagerService;IIILandroid/os/IBinder;)V > 19,3,4,6,2 @25 exception:20,
invokevirtual < Application, Lcom/android/server/devicestate/DeviceStateManagerService, requestBaseStateOverrideInternal(IIILandroid/os/IBinder;)V > 1,2,3,4,5 @0 exception:6,
return,
invokestatic < Application, Landroid/os/Binder, restoreCallingIdentity(J)V > 18 @28 exception:24,
return,","depth : 0
-----
depth : 1
-----
","public void requestBaseStateOverride(IBinder p1, int p2, int p3){
	if (p1 == 0) {
		long v4 = Binder.clearCallingIdentity();
		this.this$0.requestBaseStateOverrideInternal(p2, p3, v1, p1);
		Binder.restoreCallingIdentity(v4);
		return;
	}
}
","SYS_OR_SIG"
"Lcom/android/server/devicestate/DeviceStateManagerService$BinderService","requestBaseStateOverride(Landroid/os/IBinder;II)V","2","6 = invokestatic < Application, Landroid/os/Binder, getCallingPid()I > @0 exception:5,
7 = getfield < Application, Lcom/android/server/devicestate/DeviceStateManagerService$BinderService, this$0, <Application,Lcom/android/server/devicestate/DeviceStateManagerService> > 1,
9 = invokevirtual < Application, Lcom/android/server/SystemService, getContext()Landroid/content/Context; > 7 @6 exception:8,
invokevirtual < Application, Landroid/content/Context, enforceCallingOrSelfPermission(Ljava/lang/String;Ljava/lang/String;)V > 9,10,11 @14 exception:12,
conditional branch(eq, to iindex=-1) 2,13,
18 = invokestatic < Application, Landroid/os/Binder, clearCallingIdentity()J > @19 exception:17,
19 = getfield < Application, Lcom/android/server/devicestate/DeviceStateManagerService$BinderService, this$0, <Application,Lcom/android/server/devicestate/DeviceStateManagerService> > 1,
invokestatic < Application, Lcom/android/server/devicestate/DeviceStateManagerService, -$$Nest$mrequestBaseStateOverrideInternal(Lcom/android/server/devicestate/DeviceStateManagerService;IIILandroid/os/IBinder;)V > 19,3,4,6,2 @25 exception:20,
invokevirtual < Application, Lcom/android/server/devicestate/DeviceStateManagerService, requestBaseStateOverrideInternal(IIILandroid/os/IBinder;)V > 1,2,3,4,5 @0 exception:6,
6 = getfield < Application, Lcom/android/server/devicestate/DeviceStateManagerService, mLock, <Application,Ljava/lang/Object> > 1,
monitorenter 6,
8 = invokevirtual < Application, Lcom/android/server/devicestate/DeviceStateManagerService, getStateLocked(I)Ljava/util/Optional; > 1,2 @3 exception:7,
10 = invokevirtual < Application, Ljava/util/Optional, isPresent()Z > 8 @7 exception:9,
conditional branch(eq, to iindex=-1) 10,11,
26 = getfield < Application, Lcom/android/server/devicestate/DeviceStateManagerService, mProcessRecords, <Application,Landroid/util/SparseArray> > 1,
28 = invokevirtual < Application, Landroid/util/SparseArray, get(I)Ljava/lang/Object; > 26,4 @15 exception:27,
29 = checkcast <Application,Lcom/android/server/devicestate/DeviceStateManagerService$ProcessRecord>28 <Application,Lcom/android/server/devicestate/DeviceStateManagerService$ProcessRecord>,
conditional branch(eq, to iindex=-1) 29,11,
44 = getfield < Application, Lcom/android/server/devicestate/DeviceStateManagerService, mOverrideRequestController, <Application,Lcom/android/server/devicestate/OverrideRequestController> > 1,
47 = invokevirtual < Application, Lcom/android/server/devicestate/OverrideRequestController, hasRequest(Landroid/os/IBinder;I)Z > 44,5,45 @26 exception:46,
conditional branch(ne, to iindex=-1) 47,11,
59 = new <Application,Lcom/android/server/devicestate/OverrideRequest>@32,
invokespecial < Application, Lcom/android/server/devicestate/OverrideRequest, <init>(Landroid/os/IBinder;IIII)V > 59,5,4,2,3,45 @40 exception:60,
61 = getfield < Application, Lcom/android/server/devicestate/DeviceStateManagerService, mOverrideRequestController, <Application,Lcom/android/server/devicestate/OverrideRequestController> > 1,
invokevirtual < Application, Lcom/android/server/devicestate/OverrideRequestController, addBaseStateRequest(Lcom/android/server/devicestate/OverrideRequest;)V > 61,59 @45 exception:62,
monitorexit 6,
return,
return,
invokestatic < Application, Landroid/os/Binder, restoreCallingIdentity(J)V > 18 @28 exception:24,
return,","depth : 0
-----
depth : 1
-----
depth : 2
-----
","public void requestBaseStateOverride(IBinder p1, int p2, int p3){
	if (p1 == 0) {
		long v4 = Binder.clearCallingIdentity();
		Optional v7 = DeviceStateManagerService.getStateLocked(p2);
		boolean v8 = v7.isPresent();
		if (v8 == 0) {
			Object v9 = this.mProcessRecords.get(p4);
			if (v9 == 0) {
				boolean v10 = this.mOverrideRequestController.hasRequest(p5, 1);
				if (v10 != 0) {
					OverrideRequest v11 = new OverrideRequest(p5,p4,p2,p3,1);
					this.mOverrideRequestController.addBaseStateRequest(v11);
					Binder.restoreCallingIdentity(v4);
					return;
				}
			}
		}
	}
}
","SYS_OR_SIG"

"Lcom/android/server/devicestate/DeviceStateManagerService$BinderService","cancelBaseStateOverride()V","0","3 = invokestatic < Application, Landroid/os/Binder, getCallingPid()I > @0 exception:2,
4 = getfield < Application, Lcom/android/server/devicestate/DeviceStateManagerService$BinderService, this$0, <Application,Lcom/android/server/devicestate/DeviceStateManagerService> > 1,
6 = invokevirtual < Application, Lcom/android/server/SystemService, getContext()Landroid/content/Context; > 4 @6 exception:5,
invokevirtual < Application, Landroid/content/Context, enforceCallingOrSelfPermission(Ljava/lang/String;Ljava/lang/String;)V > 6,7,8 @14 exception:9,
11 = invokestatic < Application, Landroid/os/Binder, clearCallingIdentity()J > @17 exception:10,
12 = getfield < Application, Lcom/android/server/devicestate/DeviceStateManagerService$BinderService, this$0, <Application,Lcom/android/server/devicestate/DeviceStateManagerService> > 1,
invokestatic < Application, Lcom/android/server/devicestate/DeviceStateManagerService, -$$Nest$mcancelBaseStateOverrideInternal(Lcom/android/server/devicestate/DeviceStateManagerService;I)V > 12,3 @23 exception:13,
invokestatic < Application, Landroid/os/Binder, restoreCallingIdentity(J)V > 11 @26 exception:17,
return,","depth : 0
-----
","public void cancelBaseStateOverride(){
	long v4 = Binder.clearCallingIdentity();
	DeviceStateManagerService.-$$Nest$mcancelBaseStateOverrideInternal(this.this$0, v1);
	Binder.restoreCallingIdentity(v4);
	return;
}
","SYS_OR_SIG"
"Lcom/android/server/devicestate/DeviceStateManagerService$BinderService","cancelBaseStateOverride()V","1","3 = invokestatic < Application, Landroid/os/Binder, getCallingPid()I > @0 exception:2,
4 = getfield < Application, Lcom/android/server/devicestate/DeviceStateManagerService$BinderService, this$0, <Application,Lcom/android/server/devicestate/DeviceStateManagerService> > 1,
6 = invokevirtual < Application, Lcom/android/server/SystemService, getContext()Landroid/content/Context; > 4 @6 exception:5,
invokevirtual < Application, Landroid/content/Context, enforceCallingOrSelfPermission(Ljava/lang/String;Ljava/lang/String;)V > 6,7,8 @14 exception:9,
11 = invokestatic < Application, Landroid/os/Binder, clearCallingIdentity()J > @17 exception:10,
12 = getfield < Application, Lcom/android/server/devicestate/DeviceStateManagerService$BinderService, this$0, <Application,Lcom/android/server/devicestate/DeviceStateManagerService> > 1,
invokestatic < Application, Lcom/android/server/devicestate/DeviceStateManagerService, -$$Nest$mcancelBaseStateOverrideInternal(Lcom/android/server/devicestate/DeviceStateManagerService;I)V > 12,3 @23 exception:13,
invokevirtual < Application, Lcom/android/server/devicestate/DeviceStateManagerService, cancelBaseStateOverrideInternal(I)V > 1,2 @0 exception:3,
return,
invokestatic < Application, Landroid/os/Binder, restoreCallingIdentity(J)V > 11 @26 exception:17,
return,","depth : 0
-----
depth : 1
-----
","public void cancelBaseStateOverride(){
	long v4 = Binder.clearCallingIdentity();
	this.this$0.cancelBaseStateOverrideInternal(v1);
	Binder.restoreCallingIdentity(v4);
	return;
}
","SYS_OR_SIG"
"Lcom/android/server/devicestate/DeviceStateManagerService$BinderService","cancelBaseStateOverride()V","2","3 = invokestatic < Application, Landroid/os/Binder, getCallingPid()I > @0 exception:2,
4 = getfield < Application, Lcom/android/server/devicestate/DeviceStateManagerService$BinderService, this$0, <Application,Lcom/android/server/devicestate/DeviceStateManagerService> > 1,
6 = invokevirtual < Application, Lcom/android/server/SystemService, getContext()Landroid/content/Context; > 4 @6 exception:5,
invokevirtual < Application, Landroid/content/Context, enforceCallingOrSelfPermission(Ljava/lang/String;Ljava/lang/String;)V > 6,7,8 @14 exception:9,
11 = invokestatic < Application, Landroid/os/Binder, clearCallingIdentity()J > @17 exception:10,
12 = getfield < Application, Lcom/android/server/devicestate/DeviceStateManagerService$BinderService, this$0, <Application,Lcom/android/server/devicestate/DeviceStateManagerService> > 1,
invokestatic < Application, Lcom/android/server/devicestate/DeviceStateManagerService, -$$Nest$mcancelBaseStateOverrideInternal(Lcom/android/server/devicestate/DeviceStateManagerService;I)V > 12,3 @23 exception:13,
invokevirtual < Application, Lcom/android/server/devicestate/DeviceStateManagerService, cancelBaseStateOverrideInternal(I)V > 1,2 @0 exception:3,
3 = getfield < Application, Lcom/android/server/devicestate/DeviceStateManagerService, mLock, <Application,Ljava/lang/Object> > 1,
monitorenter 3,
4 = getfield < Application, Lcom/android/server/devicestate/DeviceStateManagerService, mProcessRecords, <Application,Landroid/util/SparseArray> > 1,
6 = invokevirtual < Application, Landroid/util/SparseArray, get(I)Ljava/lang/Object; > 4,2 @5 exception:5,
7 = checkcast <Application,Lcom/android/server/devicestate/DeviceStateManagerService$ProcessRecord>6 <Application,Lcom/android/server/devicestate/DeviceStateManagerService$ProcessRecord>,
conditional branch(eq, to iindex=-1) 7,8,
23 = getfield < Application, Lcom/android/server/devicestate/DeviceStateManagerService, mDeviceStateProviderListener, <Application,Lcom/android/server/devicestate/DeviceStateManagerService$DeviceStateProviderListener> > 1,
24 = getfield < Application, Lcom/android/server/devicestate/DeviceStateManagerService$DeviceStateProviderListener, mCurrentBaseState, <Primordial,I> > 23,
invokevirtual < Application, Lcom/android/server/devicestate/DeviceStateManagerService, setBaseState(I)V > 1,24 @17 exception:25,
monitorexit 3,
return,
return,
invokestatic < Application, Landroid/os/Binder, restoreCallingIdentity(J)V > 11 @26 exception:17,
return,","depth : 0
-----
depth : 1
-----
depth : 2
-----
","public void cancelBaseStateOverride(){
	long v4 = Binder.clearCallingIdentity();
	Object v7 = this.mProcessRecords.get(p2);
	if (v7 == 0) {
		DeviceStateManagerService.setBaseState(DeviceStateManagerService$DeviceStateProviderListener.mCurrentBaseState);
		Binder.restoreCallingIdentity(v4);
		return;
	}
}
","SYS_OR_SIG"

"Lcom/android/server/devicestate/DeviceStateManagerService$BinderService","cancelStateRequest()V","0","3 = invokestatic < Application, Landroid/os/Binder, getCallingPid()I > @0 exception:2,
4 = getfield < Application, Lcom/android/server/devicestate/DeviceStateManagerService$BinderService, this$0, <Application,Lcom/android/server/devicestate/DeviceStateManagerService> > 1,
invokestatic < Application, Lcom/android/server/devicestate/DeviceStateManagerService, -$$Nest$massertCanControlDeviceState(Lcom/android/server/devicestate/DeviceStateManagerService;I)V > 4,3 @6 exception:5,
7 = invokestatic < Application, Landroid/os/Binder, clearCallingIdentity()J > @9 exception:6,
8 = getfield < Application, Lcom/android/server/devicestate/DeviceStateManagerService$BinderService, this$0, <Application,Lcom/android/server/devicestate/DeviceStateManagerService> > 1,
invokestatic < Application, Lcom/android/server/devicestate/DeviceStateManagerService, -$$Nest$mcancelStateRequestInternal(Lcom/android/server/devicestate/DeviceStateManagerService;I)V > 8,3 @15 exception:9,
invokestatic < Application, Landroid/os/Binder, restoreCallingIdentity(J)V > 7 @18 exception:13,
return,","depth : 0
-----
","public void cancelStateRequest(){
	int v1 = Binder.getCallingPid();
	DeviceStateManagerService.-$$Nest$massertCanControlDeviceState(this.this$0, v1);
	long v3 = Binder.clearCallingIdentity();
	DeviceStateManagerService.-$$Nest$mcancelStateRequestInternal(this.this$0, v1);
	Binder.restoreCallingIdentity(v3);
	return;
}
","SYS_OR_SIG"
"Lcom/android/server/devicestate/DeviceStateManagerService$BinderService","cancelStateRequest()V","1","3 = invokestatic < Application, Landroid/os/Binder, getCallingPid()I > @0 exception:2,
4 = getfield < Application, Lcom/android/server/devicestate/DeviceStateManagerService$BinderService, this$0, <Application,Lcom/android/server/devicestate/DeviceStateManagerService> > 1,
invokestatic < Application, Lcom/android/server/devicestate/DeviceStateManagerService, -$$Nest$massertCanControlDeviceState(Lcom/android/server/devicestate/DeviceStateManagerService;I)V > 4,3 @6 exception:5,
invokevirtual < Application, Lcom/android/server/devicestate/DeviceStateManagerService, assertCanControlDeviceState(I)V > 1,2 @0 exception:3,
return,
7 = invokestatic < Application, Landroid/os/Binder, clearCallingIdentity()J > @9 exception:6,
8 = getfield < Application, Lcom/android/server/devicestate/DeviceStateManagerService$BinderService, this$0, <Application,Lcom/android/server/devicestate/DeviceStateManagerService> > 1,
invokestatic < Application, Lcom/android/server/devicestate/DeviceStateManagerService, -$$Nest$mcancelStateRequestInternal(Lcom/android/server/devicestate/DeviceStateManagerService;I)V > 8,3 @15 exception:9,
invokevirtual < Application, Lcom/android/server/devicestate/DeviceStateManagerService, cancelStateRequestInternal(I)V > 1,2 @0 exception:3,
return,
invokestatic < Application, Landroid/os/Binder, restoreCallingIdentity(J)V > 7 @18 exception:13,
return,","depth : 0
-----
depth : 1
-----
depth : 1
-----
","public void cancelStateRequest(){
	int v1 = Binder.getCallingPid();
	this.this$0.assertCanControlDeviceState(v1);
	long v4 = Binder.clearCallingIdentity();
	this.this$0.cancelStateRequestInternal(v1);
	Binder.restoreCallingIdentity(v4);
	return;
}
","SYS_OR_SIG"
"Lcom/android/server/devicestate/DeviceStateManagerService$BinderService","cancelStateRequest()V","2","3 = invokestatic < Application, Landroid/os/Binder, getCallingPid()I > @0 exception:2,
4 = getfield < Application, Lcom/android/server/devicestate/DeviceStateManagerService$BinderService, this$0, <Application,Lcom/android/server/devicestate/DeviceStateManagerService> > 1,
invokestatic < Application, Lcom/android/server/devicestate/DeviceStateManagerService, -$$Nest$massertCanControlDeviceState(Lcom/android/server/devicestate/DeviceStateManagerService;I)V > 4,3 @6 exception:5,
invokevirtual < Application, Lcom/android/server/devicestate/DeviceStateManagerService, assertCanControlDeviceState(I)V > 1,2 @0 exception:3,
3 = getfield < Application, Lcom/android/server/devicestate/DeviceStateManagerService, mActivityTaskManagerInternal, <Application,Lcom/android/server/wm/ActivityTaskManagerInternal> > 1,
5 = invokevirtual < Application, Lcom/android/server/wm/ActivityTaskManagerInternal, getTopApp()Lcom/android/server/wm/WindowProcessController; > 3 @2 exception:4,
conditional branch(eq, to iindex=-1) 5,6,
8 = invokevirtual < Application, Lcom/android/server/wm/WindowProcessController, getPid()I > 5 @8 exception:7,
conditional branch(eq, to iindex=-1) 8,2,
13 = invokevirtual < Application, Lcom/android/server/SystemService, getContext()Landroid/content/Context; > 1 @14 exception:12,
invokevirtual < Application, Landroid/content/Context, enforceCallingOrSelfPermission(Ljava/lang/String;Ljava/lang/String;)V > 13,14,15 @22 exception:16,
return,
return,
7 = invokestatic < Application, Landroid/os/Binder, clearCallingIdentity()J > @9 exception:6,
8 = getfield < Application, Lcom/android/server/devicestate/DeviceStateManagerService$BinderService, this$0, <Application,Lcom/android/server/devicestate/DeviceStateManagerService> > 1,
invokestatic < Application, Lcom/android/server/devicestate/DeviceStateManagerService, -$$Nest$mcancelStateRequestInternal(Lcom/android/server/devicestate/DeviceStateManagerService;I)V > 8,3 @15 exception:9,
invokevirtual < Application, Lcom/android/server/devicestate/DeviceStateManagerService, cancelStateRequestInternal(I)V > 1,2 @0 exception:3,
3 = getfield < Application, Lcom/android/server/devicestate/DeviceStateManagerService, mLock, <Application,Ljava/lang/Object> > 1,
monitorenter 3,
4 = getfield < Application, Lcom/android/server/devicestate/DeviceStateManagerService, mProcessRecords, <Application,Landroid/util/SparseArray> > 1,
6 = invokevirtual < Application, Landroid/util/SparseArray, get(I)Ljava/lang/Object; > 4,2 @5 exception:5,
7 = checkcast <Application,Lcom/android/server/devicestate/DeviceStateManagerService$ProcessRecord>6 <Application,Lcom/android/server/devicestate/DeviceStateManagerService$ProcessRecord>,
conditional branch(eq, to iindex=-1) 7,8,
23 = getfield < Application, Lcom/android/server/devicestate/DeviceStateManagerService, mActiveOverride, <Application,Ljava/util/Optional> > 1,
24 = getfield < Application, Lcom/android/server/devicestate/DeviceStateManagerService, mOverrideRequestController, <Application,Lcom/android/server/devicestate/OverrideRequestController> > 1,
26 = invokestatic < Application, Ljava/util/Objects, requireNonNull(Ljava/lang/Object;)Ljava/lang/Object; > 24 @17 exception:25,
27 = new <Application,Lcom/android/server/devicestate/DeviceStateManagerService$$ExternalSyntheticLambda3>@20,
invokespecial < Application, Lcom/android/server/devicestate/DeviceStateManagerService$$ExternalSyntheticLambda3, <init>(Lcom/android/server/devicestate/OverrideRequestController;)V > 27,24 @22 exception:28,
invokevirtual < Application, Ljava/util/Optional, ifPresent(Ljava/util/function/Consumer;)V > 23,27 @25 exception:29,
monitorexit 3,
return,
return,
invokestatic < Application, Landroid/os/Binder, restoreCallingIdentity(J)V > 7 @18 exception:13,
return,","depth : 0
-----
depth : 1
-----
depth : 2
-----
depth : 1
-----
depth : 2
-----
","public void cancelStateRequest(){
	int v1 = Binder.getCallingPid();
	long v8 = Binder.clearCallingIdentity();
	Object v11 = this.mProcessRecords.get(p2);
	if (v11 == 0) {
		Object v12 = Objects.requireNonNull(this.mOverrideRequestController);
		DeviceStateManagerService$$ExternalSyntheticLambda3 v13 = new DeviceStateManagerService$$ExternalSyntheticLambda3(this.mOverrideRequestController);
		this.mActiveOverride.ifPresent(v13);
		Binder.restoreCallingIdentity(v8);
		return;
	}
}
","SYS_OR_SIG"
"Lcom/android/server/devicestate/DeviceStateManagerService$BinderService","cancelStateRequest()V","2","3 = invokestatic < Application, Landroid/os/Binder, getCallingPid()I > @0 exception:2,
4 = getfield < Application, Lcom/android/server/devicestate/DeviceStateManagerService$BinderService, this$0, <Application,Lcom/android/server/devicestate/DeviceStateManagerService> > 1,
invokestatic < Application, Lcom/android/server/devicestate/DeviceStateManagerService, -$$Nest$massertCanControlDeviceState(Lcom/android/server/devicestate/DeviceStateManagerService;I)V > 4,3 @6 exception:5,
invokevirtual < Application, Lcom/android/server/devicestate/DeviceStateManagerService, assertCanControlDeviceState(I)V > 1,2 @0 exception:3,
3 = getfield < Application, Lcom/android/server/devicestate/DeviceStateManagerService, mActivityTaskManagerInternal, <Application,Lcom/android/server/wm/ActivityTaskManagerInternal> > 1,
5 = invokevirtual < Application, Lcom/android/server/wm/ActivityTaskManagerInternal, getTopApp()Lcom/android/server/wm/WindowProcessController; > 3 @2 exception:4,
conditional branch(eq, to iindex=-1) 5,6,
13 = invokevirtual < Application, Lcom/android/server/SystemService, getContext()Landroid/content/Context; > 1 @14 exception:12,
invokevirtual < Application, Landroid/content/Context, enforceCallingOrSelfPermission(Ljava/lang/String;Ljava/lang/String;)V > 13,14,15 @22 exception:16,
return,
return,
7 = invokestatic < Application, Landroid/os/Binder, clearCallingIdentity()J > @9 exception:6,
8 = getfield < Application, Lcom/android/server/devicestate/DeviceStateManagerService$BinderService, this$0, <Application,Lcom/android/server/devicestate/DeviceStateManagerService> > 1,
invokestatic < Application, Lcom/android/server/devicestate/DeviceStateManagerService, -$$Nest$mcancelStateRequestInternal(Lcom/android/server/devicestate/DeviceStateManagerService;I)V > 8,3 @15 exception:9,
invokevirtual < Application, Lcom/android/server/devicestate/DeviceStateManagerService, cancelStateRequestInternal(I)V > 1,2 @0 exception:3,
3 = getfield < Application, Lcom/android/server/devicestate/DeviceStateManagerService, mLock, <Application,Ljava/lang/Object> > 1,
monitorenter 3,
4 = getfield < Application, Lcom/android/server/devicestate/DeviceStateManagerService, mProcessRecords, <Application,Landroid/util/SparseArray> > 1,
6 = invokevirtual < Application, Landroid/util/SparseArray, get(I)Ljava/lang/Object; > 4,2 @5 exception:5,
7 = checkcast <Application,Lcom/android/server/devicestate/DeviceStateManagerService$ProcessRecord>6 <Application,Lcom/android/server/devicestate/DeviceStateManagerService$ProcessRecord>,
conditional branch(eq, to iindex=-1) 7,8,
23 = getfield < Application, Lcom/android/server/devicestate/DeviceStateManagerService, mActiveOverride, <Application,Ljava/util/Optional> > 1,
24 = getfield < Application, Lcom/android/server/devicestate/DeviceStateManagerService, mOverrideRequestController, <Application,Lcom/android/server/devicestate/OverrideRequestController> > 1,
26 = invokestatic < Application, Ljava/util/Objects, requireNonNull(Ljava/lang/Object;)Ljava/lang/Object; > 24 @17 exception:25,
27 = new <Application,Lcom/android/server/devicestate/DeviceStateManagerService$$ExternalSyntheticLambda3>@20,
invokespecial < Application, Lcom/android/server/devicestate/DeviceStateManagerService$$ExternalSyntheticLambda3, <init>(Lcom/android/server/devicestate/OverrideRequestController;)V > 27,24 @22 exception:28,
invokevirtual < Application, Ljava/util/Optional, ifPresent(Ljava/util/function/Consumer;)V > 23,27 @25 exception:29,
monitorexit 3,
return,
return,
invokestatic < Application, Landroid/os/Binder, restoreCallingIdentity(J)V > 7 @18 exception:13,
return,","depth : 0
-----
depth : 1
-----
depth : 2
-----
depth : 1
-----
depth : 2
-----
","public void cancelStateRequest(){
	int v1 = Binder.getCallingPid();
	long v7 = Binder.clearCallingIdentity();
	Object v10 = this.mProcessRecords.get(p2);
	if (v10 == 0) {
		Object v11 = Objects.requireNonNull(this.mOverrideRequestController);
		DeviceStateManagerService$$ExternalSyntheticLambda3 v12 = new DeviceStateManagerService$$ExternalSyntheticLambda3(this.mOverrideRequestController);
		this.mActiveOverride.ifPresent(v12);
		Binder.restoreCallingIdentity(v7);
		return;
	}
}
","SYS_OR_SIG"

"Lcom/android/server/devicestate/DeviceStateManagerService$BinderService","registerCallback(Landroid/hardware/devicestate/IDeviceStateManagerCallback;)V","0","conditional branch(eq, to iindex=-1) 2,3,
8 = invokestatic < Application, Landroid/os/Binder, getCallingPid()I > @2 exception:7,
10 = invokestatic < Application, Landroid/os/Binder, clearCallingIdentity()J > @6 exception:9,
11 = getfield < Application, Lcom/android/server/devicestate/DeviceStateManagerService$BinderService, this$0, <Application,Lcom/android/server/devicestate/DeviceStateManagerService> > 1,
invokestatic < Application, Lcom/android/server/devicestate/DeviceStateManagerService, -$$Nest$mregisterProcess(Lcom/android/server/devicestate/DeviceStateManagerService;ILandroid/hardware/devicestate/IDeviceStateManagerCallback;)V > 11,8,2 @12 exception:12,
invokestatic < Application, Landroid/os/Binder, restoreCallingIdentity(J)V > 10 @15 exception:16,
return,","depth : 0
-----
","public void registerCallback(IDeviceStateManagerCallback p1){
	if (p1 == 0) {
		int v1 = Binder.getCallingPid();
		long v2 = Binder.clearCallingIdentity();
		DeviceStateManagerService.-$$Nest$mregisterProcess(this.this$0, v1, p1);
		Binder.restoreCallingIdentity(v2);
		return;
	}
}
","NONE"
"Lcom/android/server/devicestate/DeviceStateManagerService$BinderService","registerCallback(Landroid/hardware/devicestate/IDeviceStateManagerCallback;)V","1","conditional branch(eq, to iindex=-1) 2,3,
8 = invokestatic < Application, Landroid/os/Binder, getCallingPid()I > @2 exception:7,
10 = invokestatic < Application, Landroid/os/Binder, clearCallingIdentity()J > @6 exception:9,
11 = getfield < Application, Lcom/android/server/devicestate/DeviceStateManagerService$BinderService, this$0, <Application,Lcom/android/server/devicestate/DeviceStateManagerService> > 1,
invokestatic < Application, Lcom/android/server/devicestate/DeviceStateManagerService, -$$Nest$mregisterProcess(Lcom/android/server/devicestate/DeviceStateManagerService;ILandroid/hardware/devicestate/IDeviceStateManagerCallback;)V > 11,8,2 @12 exception:12,
invokevirtual < Application, Lcom/android/server/devicestate/DeviceStateManagerService, registerProcess(ILandroid/hardware/devicestate/IDeviceStateManagerCallback;)V > 1,2,3 @0 exception:4,
return,
invokestatic < Application, Landroid/os/Binder, restoreCallingIdentity(J)V > 10 @15 exception:16,
return,","depth : 0
-----
depth : 1
-----
","public void registerCallback(IDeviceStateManagerCallback p1){
	if (p1 == 0) {
		int v1 = Binder.getCallingPid();
		long v2 = Binder.clearCallingIdentity();
		this.this$0.registerProcess(v1, p1);
		Binder.restoreCallingIdentity(v2);
		return;
	}
}
","NONE"
"Lcom/android/server/devicestate/DeviceStateManagerService$BinderService","registerCallback(Landroid/hardware/devicestate/IDeviceStateManagerCallback;)V","2","conditional branch(eq, to iindex=-1) 2,3,
8 = invokestatic < Application, Landroid/os/Binder, getCallingPid()I > @2 exception:7,
10 = invokestatic < Application, Landroid/os/Binder, clearCallingIdentity()J > @6 exception:9,
11 = getfield < Application, Lcom/android/server/devicestate/DeviceStateManagerService$BinderService, this$0, <Application,Lcom/android/server/devicestate/DeviceStateManagerService> > 1,
invokestatic < Application, Lcom/android/server/devicestate/DeviceStateManagerService, -$$Nest$mregisterProcess(Lcom/android/server/devicestate/DeviceStateManagerService;ILandroid/hardware/devicestate/IDeviceStateManagerCallback;)V > 11,8,2 @12 exception:12,
invokevirtual < Application, Lcom/android/server/devicestate/DeviceStateManagerService, registerProcess(ILandroid/hardware/devicestate/IDeviceStateManagerCallback;)V > 1,2,3 @0 exception:4,
4 = getfield < Application, Lcom/android/server/devicestate/DeviceStateManagerService, mLock, <Application,Ljava/lang/Object> > 1,
monitorenter 4,
5 = getfield < Application, Lcom/android/server/devicestate/DeviceStateManagerService, mProcessRecords, <Application,Landroid/util/SparseArray> > 1,
7 = invokevirtual < Application, Landroid/util/SparseArray, contains(I)Z > 5,2 @5 exception:6,
conditional branch(ne, to iindex=-1) 7,8,
12 = new <Application,Lcom/android/server/devicestate/DeviceStateManagerService$ProcessRecord>@11,
13 = new <Application,Lcom/android/server/devicestate/DeviceStateManagerService$$ExternalSyntheticLambda2>@13,
invokespecial < Application, Lcom/android/server/devicestate/DeviceStateManagerService$$ExternalSyntheticLambda2, <init>(Lcom/android/server/devicestate/DeviceStateManagerService;)V > 13,1 @15 exception:14,
15 = getfield < Application, Lcom/android/server/devicestate/DeviceStateManagerService, mHandler, <Application,Landroid/os/Handler> > 1,
invokespecial < Application, Lcom/android/server/devicestate/DeviceStateManagerService$ProcessRecord, <init>(Landroid/hardware/devicestate/IDeviceStateManagerCallback;ILcom/android/server/devicestate/DeviceStateManagerService$ProcessRecord$DeathListener;Landroid/os/Handler;)V > 12,3,2,13,15 @20 exception:16,
18 = invokeinterface < Application, Landroid/hardware/devicestate/IDeviceStateManagerCallback, asBinder()Landroid/os/IBinder; > 3 @23 exception:17,
invokeinterface < Application, Landroid/os/IBinder, linkToDeath(Landroid/os/IBinder$DeathRecipient;I)V > 18,12,8 @28 exception:19,
26 = getfield < Application, Lcom/android/server/devicestate/DeviceStateManagerService, mProcessRecords, <Application,Landroid/util/SparseArray> > 1,
invokevirtual < Application, Landroid/util/SparseArray, put(ILjava/lang/Object;)V > 26,2,12 @33 exception:27,
28 = getfield < Application, Lcom/android/server/devicestate/DeviceStateManagerService, mCommittedState, <Application,Ljava/util/Optional> > 1,
30 = invokevirtual < Application, Ljava/util/Optional, isPresent()Z > 28 @38 exception:29,
conditional branch(eq, to iindex=-1) 30,8,
32 = invokevirtual < Application, Lcom/android/server/devicestate/DeviceStateManagerService, getDeviceStateInfoLocked()Landroid/hardware/devicestate/DeviceStateInfo; > 1 @44 exception:31,
goto (from iindex= 23 to iindex = 2),
33 = phi  32,8,
conditional branch(eq, to iindex=-1) 33,8,
invokevirtual < Application, Lcom/android/server/devicestate/DeviceStateManagerService$ProcessRecord, notifyDeviceStateInfoAsync(Landroid/hardware/devicestate/DeviceStateInfo;)V > 12,33 @52 exception:36,
monitorexit 4,
return,
return,
invokestatic < Application, Landroid/os/Binder, restoreCallingIdentity(J)V > 10 @15 exception:16,
return,","depth : 0
-----
depth : 1
-----
depth : 2
-----
","public void registerCallback(IDeviceStateManagerCallback p1){
	if (p1 == 0) {
		int v1 = Binder.getCallingPid();
		long v2 = Binder.clearCallingIdentity();
		boolean v5 = this.mProcessRecords.contains(p2);
		if (v5 != 0) {
			DeviceStateManagerService$ProcessRecord v6 = new DeviceStateManagerService$ProcessRecord(p3,p2,v7,this.mHandler);
			DeviceStateManagerService$$ExternalSyntheticLambda2 v7 = new DeviceStateManagerService$$ExternalSyntheticLambda2(DeviceStateManagerService);
			IBinder v10 = p3.asBinder();
			v10.linkToDeath(v6, 0);
			this.mProcessRecords.put(p2, v6);
			boolean v13 = this.mCommittedState.isPresent();
			if (v13 == 0) {
				DeviceStateInfo v14 = DeviceStateManagerService.getDeviceStateInfoLocked();
				if ( == 0) {
					v6.notifyDeviceStateInfoAsync();
					Binder.restoreCallingIdentity(v2);
					return;
				}
			}
		}
	}
}
","NONE"
"Lcom/android/server/devicestate/DeviceStateManagerService$BinderService","registerCallback(Landroid/hardware/devicestate/IDeviceStateManagerCallback;)V","2","conditional branch(eq, to iindex=-1) 2,3,
8 = invokestatic < Application, Landroid/os/Binder, getCallingPid()I > @2 exception:7,
10 = invokestatic < Application, Landroid/os/Binder, clearCallingIdentity()J > @6 exception:9,
11 = getfield < Application, Lcom/android/server/devicestate/DeviceStateManagerService$BinderService, this$0, <Application,Lcom/android/server/devicestate/DeviceStateManagerService> > 1,
invokestatic < Application, Lcom/android/server/devicestate/DeviceStateManagerService, -$$Nest$mregisterProcess(Lcom/android/server/devicestate/DeviceStateManagerService;ILandroid/hardware/devicestate/IDeviceStateManagerCallback;)V > 11,8,2 @12 exception:12,
invokevirtual < Application, Lcom/android/server/devicestate/DeviceStateManagerService, registerProcess(ILandroid/hardware/devicestate/IDeviceStateManagerCallback;)V > 1,2,3 @0 exception:4,
4 = getfield < Application, Lcom/android/server/devicestate/DeviceStateManagerService, mLock, <Application,Ljava/lang/Object> > 1,
monitorenter 4,
5 = getfield < Application, Lcom/android/server/devicestate/DeviceStateManagerService, mProcessRecords, <Application,Landroid/util/SparseArray> > 1,
7 = invokevirtual < Application, Landroid/util/SparseArray, contains(I)Z > 5,2 @5 exception:6,
conditional branch(ne, to iindex=-1) 7,8,
12 = new <Application,Lcom/android/server/devicestate/DeviceStateManagerService$ProcessRecord>@11,
13 = new <Application,Lcom/android/server/devicestate/DeviceStateManagerService$$ExternalSyntheticLambda2>@13,
invokespecial < Application, Lcom/android/server/devicestate/DeviceStateManagerService$$ExternalSyntheticLambda2, <init>(Lcom/android/server/devicestate/DeviceStateManagerService;)V > 13,1 @15 exception:14,
15 = getfield < Application, Lcom/android/server/devicestate/DeviceStateManagerService, mHandler, <Application,Landroid/os/Handler> > 1,
invokespecial < Application, Lcom/android/server/devicestate/DeviceStateManagerService$ProcessRecord, <init>(Landroid/hardware/devicestate/IDeviceStateManagerCallback;ILcom/android/server/devicestate/DeviceStateManagerService$ProcessRecord$DeathListener;Landroid/os/Handler;)V > 12,3,2,13,15 @20 exception:16,
18 = invokeinterface < Application, Landroid/hardware/devicestate/IDeviceStateManagerCallback, asBinder()Landroid/os/IBinder; > 3 @23 exception:17,
invokeinterface < Application, Landroid/os/IBinder, linkToDeath(Landroid/os/IBinder$DeathRecipient;I)V > 18,12,8 @28 exception:19,
26 = getfield < Application, Lcom/android/server/devicestate/DeviceStateManagerService, mProcessRecords, <Application,Landroid/util/SparseArray> > 1,
invokevirtual < Application, Landroid/util/SparseArray, put(ILjava/lang/Object;)V > 26,2,12 @33 exception:27,
28 = getfield < Application, Lcom/android/server/devicestate/DeviceStateManagerService, mCommittedState, <Application,Ljava/util/Optional> > 1,
30 = invokevirtual < Application, Ljava/util/Optional, isPresent()Z > 28 @38 exception:29,
conditional branch(eq, to iindex=-1) 30,8,
32 = invokevirtual < Application, Lcom/android/server/devicestate/DeviceStateManagerService, getDeviceStateInfoLocked()Landroid/hardware/devicestate/DeviceStateInfo; > 1 @44 exception:31,
goto (from iindex= 23 to iindex = 2),
33 = phi  32,8,
conditional branch(eq, to iindex=-1) 33,8,
monitorexit 4,
return,
return,
invokestatic < Application, Landroid/os/Binder, restoreCallingIdentity(J)V > 10 @15 exception:16,
return,","depth : 0
-----
depth : 1
-----
depth : 2
-----
","public void registerCallback(IDeviceStateManagerCallback p1){
	if (p1 == 0) {
		int v1 = Binder.getCallingPid();
		long v2 = Binder.clearCallingIdentity();
		boolean v5 = this.mProcessRecords.contains(p2);
		if (v5 != 0) {
			DeviceStateManagerService$ProcessRecord v6 = new DeviceStateManagerService$ProcessRecord(p3,p2,v7,this.mHandler);
			DeviceStateManagerService$$ExternalSyntheticLambda2 v7 = new DeviceStateManagerService$$ExternalSyntheticLambda2(DeviceStateManagerService);
			IBinder v10 = p3.asBinder();
			v10.linkToDeath(v6, 0);
			this.mProcessRecords.put(p2, v6);
			boolean v13 = this.mCommittedState.isPresent();
			if (v13 == 0) {
				DeviceStateInfo v14 = DeviceStateManagerService.getDeviceStateInfoLocked();
				if ( == 0) {
					Binder.restoreCallingIdentity(v2);
					return;
				}
			}
		}
	}
}
","NONE"
"Lcom/android/server/devicestate/DeviceStateManagerService$BinderService","registerCallback(Landroid/hardware/devicestate/IDeviceStateManagerCallback;)V","2","conditional branch(eq, to iindex=-1) 2,3,
8 = invokestatic < Application, Landroid/os/Binder, getCallingPid()I > @2 exception:7,
10 = invokestatic < Application, Landroid/os/Binder, clearCallingIdentity()J > @6 exception:9,
11 = getfield < Application, Lcom/android/server/devicestate/DeviceStateManagerService$BinderService, this$0, <Application,Lcom/android/server/devicestate/DeviceStateManagerService> > 1,
invokestatic < Application, Lcom/android/server/devicestate/DeviceStateManagerService, -$$Nest$mregisterProcess(Lcom/android/server/devicestate/DeviceStateManagerService;ILandroid/hardware/devicestate/IDeviceStateManagerCallback;)V > 11,8,2 @12 exception:12,
invokevirtual < Application, Lcom/android/server/devicestate/DeviceStateManagerService, registerProcess(ILandroid/hardware/devicestate/IDeviceStateManagerCallback;)V > 1,2,3 @0 exception:4,
4 = getfield < Application, Lcom/android/server/devicestate/DeviceStateManagerService, mLock, <Application,Ljava/lang/Object> > 1,
monitorenter 4,
5 = getfield < Application, Lcom/android/server/devicestate/DeviceStateManagerService, mProcessRecords, <Application,Landroid/util/SparseArray> > 1,
7 = invokevirtual < Application, Landroid/util/SparseArray, contains(I)Z > 5,2 @5 exception:6,
conditional branch(ne, to iindex=-1) 7,8,
12 = new <Application,Lcom/android/server/devicestate/DeviceStateManagerService$ProcessRecord>@11,
13 = new <Application,Lcom/android/server/devicestate/DeviceStateManagerService$$ExternalSyntheticLambda2>@13,
invokespecial < Application, Lcom/android/server/devicestate/DeviceStateManagerService$$ExternalSyntheticLambda2, <init>(Lcom/android/server/devicestate/DeviceStateManagerService;)V > 13,1 @15 exception:14,
15 = getfield < Application, Lcom/android/server/devicestate/DeviceStateManagerService, mHandler, <Application,Landroid/os/Handler> > 1,
invokespecial < Application, Lcom/android/server/devicestate/DeviceStateManagerService$ProcessRecord, <init>(Landroid/hardware/devicestate/IDeviceStateManagerCallback;ILcom/android/server/devicestate/DeviceStateManagerService$ProcessRecord$DeathListener;Landroid/os/Handler;)V > 12,3,2,13,15 @20 exception:16,
18 = invokeinterface < Application, Landroid/hardware/devicestate/IDeviceStateManagerCallback, asBinder()Landroid/os/IBinder; > 3 @23 exception:17,
invokeinterface < Application, Landroid/os/IBinder, linkToDeath(Landroid/os/IBinder$DeathRecipient;I)V > 18,12,8 @28 exception:19,
26 = getfield < Application, Lcom/android/server/devicestate/DeviceStateManagerService, mProcessRecords, <Application,Landroid/util/SparseArray> > 1,
invokevirtual < Application, Landroid/util/SparseArray, put(ILjava/lang/Object;)V > 26,2,12 @33 exception:27,
28 = getfield < Application, Lcom/android/server/devicestate/DeviceStateManagerService, mCommittedState, <Application,Ljava/util/Optional> > 1,
30 = invokevirtual < Application, Ljava/util/Optional, isPresent()Z > 28 @38 exception:29,
conditional branch(eq, to iindex=-1) 30,8,
33 = phi  32,8,
conditional branch(eq, to iindex=-1) 33,8,
invokevirtual < Application, Lcom/android/server/devicestate/DeviceStateManagerService$ProcessRecord, notifyDeviceStateInfoAsync(Landroid/hardware/devicestate/DeviceStateInfo;)V > 12,33 @52 exception:36,
monitorexit 4,
return,
return,
invokestatic < Application, Landroid/os/Binder, restoreCallingIdentity(J)V > 10 @15 exception:16,
return,","depth : 0
-----
depth : 1
-----
depth : 2
-----
","public void registerCallback(IDeviceStateManagerCallback p1){
	if (p1 == 0) {
		int v1 = Binder.getCallingPid();
		long v2 = Binder.clearCallingIdentity();
		boolean v5 = this.mProcessRecords.contains(p2);
		if (v5 != 0) {
			DeviceStateManagerService$ProcessRecord v6 = new DeviceStateManagerService$ProcessRecord(p3,p2,v7,this.mHandler);
			DeviceStateManagerService$$ExternalSyntheticLambda2 v7 = new DeviceStateManagerService$$ExternalSyntheticLambda2(DeviceStateManagerService);
			IBinder v10 = p3.asBinder();
			v10.linkToDeath(v6, 0);
			this.mProcessRecords.put(p2, v6);
			boolean v13 = this.mCommittedState.isPresent();
			if (v13 == 0) {
				if ( == 0) {
					v6.notifyDeviceStateInfoAsync();
					Binder.restoreCallingIdentity(v2);
					return;
				}
			}
		}
	}
}
","NONE"

"Lcom/android/server/devicestate/DeviceStateManagerService$BinderService","requestState(Landroid/os/IBinder;II)V","0","6 = invokestatic < Application, Landroid/os/Binder, getCallingPid()I > @0 exception:5,
7 = getfield < Application, Lcom/android/server/devicestate/DeviceStateManagerService$BinderService, this$0, <Application,Lcom/android/server/devicestate/DeviceStateManagerService> > 1,
invokestatic < Application, Lcom/android/server/devicestate/DeviceStateManagerService, -$$Nest$massertCanRequestDeviceState(Lcom/android/server/devicestate/DeviceStateManagerService;II)V > 7,6,3 @6 exception:8,
conditional branch(eq, to iindex=-1) 2,9,
14 = invokestatic < Application, Landroid/os/Binder, clearCallingIdentity()J > @11 exception:13,
15 = getfield < Application, Lcom/android/server/devicestate/DeviceStateManagerService$BinderService, this$0, <Application,Lcom/android/server/devicestate/DeviceStateManagerService> > 1,
invokestatic < Application, Lcom/android/server/devicestate/DeviceStateManagerService, -$$Nest$mrequestStateInternal(Lcom/android/server/devicestate/DeviceStateManagerService;IIILandroid/os/IBinder;)V > 15,3,4,6,2 @17 exception:16,
invokestatic < Application, Landroid/os/Binder, restoreCallingIdentity(J)V > 14 @20 exception:20,
return,","depth : 0
-----
","public void requestState(IBinder p1, int p2, int p3){
	int v1 = Binder.getCallingPid();
	DeviceStateManagerService.-$$Nest$massertCanRequestDeviceState(this.this$0, v1, p2);
	if (p1 == 0) {
		long v3 = Binder.clearCallingIdentity();
		DeviceStateManagerService.-$$Nest$mrequestStateInternal(this.this$0, p2, p3, v1, p1);
		Binder.restoreCallingIdentity(v3);
		return;
	}
}
","SYS_OR_SIG"
"Lcom/android/server/devicestate/DeviceStateManagerService$BinderService","requestState(Landroid/os/IBinder;II)V","1","6 = invokestatic < Application, Landroid/os/Binder, getCallingPid()I > @0 exception:5,
7 = getfield < Application, Lcom/android/server/devicestate/DeviceStateManagerService$BinderService, this$0, <Application,Lcom/android/server/devicestate/DeviceStateManagerService> > 1,
invokestatic < Application, Lcom/android/server/devicestate/DeviceStateManagerService, -$$Nest$massertCanRequestDeviceState(Lcom/android/server/devicestate/DeviceStateManagerService;II)V > 7,6,3 @6 exception:8,
invokevirtual < Application, Lcom/android/server/devicestate/DeviceStateManagerService, assertCanRequestDeviceState(II)V > 1,2,3 @0 exception:4,
return,
conditional branch(eq, to iindex=-1) 2,9,
14 = invokestatic < Application, Landroid/os/Binder, clearCallingIdentity()J > @11 exception:13,
15 = getfield < Application, Lcom/android/server/devicestate/DeviceStateManagerService$BinderService, this$0, <Application,Lcom/android/server/devicestate/DeviceStateManagerService> > 1,
invokestatic < Application, Lcom/android/server/devicestate/DeviceStateManagerService, -$$Nest$mrequestStateInternal(Lcom/android/server/devicestate/DeviceStateManagerService;IIILandroid/os/IBinder;)V > 15,3,4,6,2 @17 exception:16,
invokevirtual < Application, Lcom/android/server/devicestate/DeviceStateManagerService, requestStateInternal(IIILandroid/os/IBinder;)V > 1,2,3,4,5 @0 exception:6,
return,
invokestatic < Application, Landroid/os/Binder, restoreCallingIdentity(J)V > 14 @20 exception:20,
return,","depth : 0
-----
depth : 1
-----
depth : 1
-----
","public void requestState(IBinder p1, int p2, int p3){
	int v1 = Binder.getCallingPid();
	this.this$0.assertCanRequestDeviceState(v1, p2);
	if (p1 == 0) {
		long v4 = Binder.clearCallingIdentity();
		this.this$0.requestStateInternal(p2, p3, v1, p1);
		Binder.restoreCallingIdentity(v4);
		return;
	}
}
","SYS_OR_SIG"
"Lcom/android/server/devicestate/DeviceStateManagerService$BinderService","requestState(Landroid/os/IBinder;II)V","2","6 = invokestatic < Application, Landroid/os/Binder, getCallingPid()I > @0 exception:5,
7 = getfield < Application, Lcom/android/server/devicestate/DeviceStateManagerService$BinderService, this$0, <Application,Lcom/android/server/devicestate/DeviceStateManagerService> > 1,
invokestatic < Application, Lcom/android/server/devicestate/DeviceStateManagerService, -$$Nest$massertCanRequestDeviceState(Lcom/android/server/devicestate/DeviceStateManagerService;II)V > 7,6,3 @6 exception:8,
invokevirtual < Application, Lcom/android/server/devicestate/DeviceStateManagerService, assertCanRequestDeviceState(II)V > 1,2,3 @0 exception:4,
4 = getfield < Application, Lcom/android/server/devicestate/DeviceStateManagerService, mActivityTaskManagerInternal, <Application,Lcom/android/server/wm/ActivityTaskManagerInternal> > 1,
6 = invokevirtual < Application, Lcom/android/server/wm/ActivityTaskManagerInternal, getTopApp()Lcom/android/server/wm/WindowProcessController; > 4 @2 exception:5,
conditional branch(eq, to iindex=-1) 6,7,
9 = invokevirtual < Application, Lcom/android/server/wm/WindowProcessController, getPid()I > 6 @8 exception:8,
conditional branch(ne, to iindex=-1) 9,2,
11 = invokevirtual < Application, Lcom/android/server/devicestate/DeviceStateManagerService, isStateAvailableForAppRequests(I)Z > 1,3 @14 exception:10,
conditional branch(ne, to iindex=-1) 11,7,
17 = invokevirtual < Application, Lcom/android/server/SystemService, getContext()Landroid/content/Context; > 1 @20 exception:16,
invokevirtual < Application, Landroid/content/Context, enforceCallingOrSelfPermission(Ljava/lang/String;Ljava/lang/String;)V > 17,18,19 @28 exception:20,
return,
return,
conditional branch(eq, to iindex=-1) 2,9,
14 = invokestatic < Application, Landroid/os/Binder, clearCallingIdentity()J > @11 exception:13,
15 = getfield < Application, Lcom/android/server/devicestate/DeviceStateManagerService$BinderService, this$0, <Application,Lcom/android/server/devicestate/DeviceStateManagerService> > 1,
invokestatic < Application, Lcom/android/server/devicestate/DeviceStateManagerService, -$$Nest$mrequestStateInternal(Lcom/android/server/devicestate/DeviceStateManagerService;IIILandroid/os/IBinder;)V > 15,3,4,6,2 @17 exception:16,
invokevirtual < Application, Lcom/android/server/devicestate/DeviceStateManagerService, requestStateInternal(IIILandroid/os/IBinder;)V > 1,2,3,4,5 @0 exception:6,
6 = getfield < Application, Lcom/android/server/devicestate/DeviceStateManagerService, mLock, <Application,Ljava/lang/Object> > 1,
monitorenter 6,
7 = getfield < Application, Lcom/android/server/devicestate/DeviceStateManagerService, mProcessRecords, <Application,Landroid/util/SparseArray> > 1,
9 = invokevirtual < Application, Landroid/util/SparseArray, get(I)Ljava/lang/Object; > 7,4 @5 exception:8,
10 = checkcast <Application,Lcom/android/server/devicestate/DeviceStateManagerService$ProcessRecord>9 <Application,Lcom/android/server/devicestate/DeviceStateManagerService$ProcessRecord>,
conditional branch(eq, to iindex=-1) 10,11,
26 = getfield < Application, Lcom/android/server/devicestate/DeviceStateManagerService, mOverrideRequestController, <Application,Lcom/android/server/devicestate/OverrideRequestController> > 1,
28 = invokevirtual < Application, Lcom/android/server/devicestate/OverrideRequestController, hasRequest(Landroid/os/IBinder;I)Z > 26,5,11 @16 exception:27,
conditional branch(ne, to iindex=-1) 28,11,
41 = invokevirtual < Application, Lcom/android/server/devicestate/DeviceStateManagerService, getStateLocked(I)Ljava/util/Optional; > 1,2 @22 exception:40,
43 = invokevirtual < Application, Ljava/util/Optional, isPresent()Z > 41 @26 exception:42,
conditional branch(eq, to iindex=-1) 43,11,
58 = new <Application,Lcom/android/server/devicestate/OverrideRequest>@32,
invokespecial < Application, Lcom/android/server/devicestate/OverrideRequest, <init>(Landroid/os/IBinder;IIII)V > 58,5,4,2,3,11 @40 exception:59,
60 = getfield < Application, Lcom/android/server/devicestate/DeviceStateManagerService, mOverrideRequestController, <Application,Lcom/android/server/devicestate/OverrideRequestController> > 1,
invokevirtual < Application, Lcom/android/server/devicestate/OverrideRequestController, addRequest(Lcom/android/server/devicestate/OverrideRequest;)V > 60,58 @45 exception:61,
monitorexit 6,
return,
return,
invokestatic < Application, Landroid/os/Binder, restoreCallingIdentity(J)V > 14 @20 exception:20,
return,","depth : 0
-----
depth : 1
-----
depth : 2
-----
depth : 1
-----
depth : 2
-----
","public void requestState(IBinder p1, int p2, int p3){
	int v1 = Binder.getCallingPid();
	if (p1 == 0) {
		long v9 = Binder.clearCallingIdentity();
		Object v12 = this.mProcessRecords.get(p4);
		if (v12 == 0) {
			boolean v13 = this.mOverrideRequestController.hasRequest(p5, 0);
			if (v13 != 0) {
				Optional v14 = DeviceStateManagerService.getStateLocked(p2);
				boolean v15 = v14.isPresent();
				if (v15 == 0) {
					OverrideRequest v16 = new OverrideRequest(p5,p4,p2,p3,0);
					this.mOverrideRequestController.addRequest(v16);
					Binder.restoreCallingIdentity(v9);
					return;
				}
			}
		}
	}
}
","SYS_OR_SIG"
"Lcom/android/server/devicestate/DeviceStateManagerService$BinderService","requestState(Landroid/os/IBinder;II)V","2","6 = invokestatic < Application, Landroid/os/Binder, getCallingPid()I > @0 exception:5,
7 = getfield < Application, Lcom/android/server/devicestate/DeviceStateManagerService$BinderService, this$0, <Application,Lcom/android/server/devicestate/DeviceStateManagerService> > 1,
invokestatic < Application, Lcom/android/server/devicestate/DeviceStateManagerService, -$$Nest$massertCanRequestDeviceState(Lcom/android/server/devicestate/DeviceStateManagerService;II)V > 7,6,3 @6 exception:8,
invokevirtual < Application, Lcom/android/server/devicestate/DeviceStateManagerService, assertCanRequestDeviceState(II)V > 1,2,3 @0 exception:4,
4 = getfield < Application, Lcom/android/server/devicestate/DeviceStateManagerService, mActivityTaskManagerInternal, <Application,Lcom/android/server/wm/ActivityTaskManagerInternal> > 1,
6 = invokevirtual < Application, Lcom/android/server/wm/ActivityTaskManagerInternal, getTopApp()Lcom/android/server/wm/WindowProcessController; > 4 @2 exception:5,
conditional branch(eq, to iindex=-1) 6,7,
9 = invokevirtual < Application, Lcom/android/server/wm/WindowProcessController, getPid()I > 6 @8 exception:8,
conditional branch(ne, to iindex=-1) 9,2,
11 = invokevirtual < Application, Lcom/android/server/devicestate/DeviceStateManagerService, isStateAvailableForAppRequests(I)Z > 1,3 @14 exception:10,
conditional branch(ne, to iindex=-1) 11,7,
return,
return,
conditional branch(eq, to iindex=-1) 2,9,
14 = invokestatic < Application, Landroid/os/Binder, clearCallingIdentity()J > @11 exception:13,
15 = getfield < Application, Lcom/android/server/devicestate/DeviceStateManagerService$BinderService, this$0, <Application,Lcom/android/server/devicestate/DeviceStateManagerService> > 1,
invokestatic < Application, Lcom/android/server/devicestate/DeviceStateManagerService, -$$Nest$mrequestStateInternal(Lcom/android/server/devicestate/DeviceStateManagerService;IIILandroid/os/IBinder;)V > 15,3,4,6,2 @17 exception:16,
invokevirtual < Application, Lcom/android/server/devicestate/DeviceStateManagerService, requestStateInternal(IIILandroid/os/IBinder;)V > 1,2,3,4,5 @0 exception:6,
6 = getfield < Application, Lcom/android/server/devicestate/DeviceStateManagerService, mLock, <Application,Ljava/lang/Object> > 1,
monitorenter 6,
7 = getfield < Application, Lcom/android/server/devicestate/DeviceStateManagerService, mProcessRecords, <Application,Landroid/util/SparseArray> > 1,
9 = invokevirtual < Application, Landroid/util/SparseArray, get(I)Ljava/lang/Object; > 7,4 @5 exception:8,
10 = checkcast <Application,Lcom/android/server/devicestate/DeviceStateManagerService$ProcessRecord>9 <Application,Lcom/android/server/devicestate/DeviceStateManagerService$ProcessRecord>,
conditional branch(eq, to iindex=-1) 10,11,
26 = getfield < Application, Lcom/android/server/devicestate/DeviceStateManagerService, mOverrideRequestController, <Application,Lcom/android/server/devicestate/OverrideRequestController> > 1,
28 = invokevirtual < Application, Lcom/android/server/devicestate/OverrideRequestController, hasRequest(Landroid/os/IBinder;I)Z > 26,5,11 @16 exception:27,
conditional branch(ne, to iindex=-1) 28,11,
41 = invokevirtual < Application, Lcom/android/server/devicestate/DeviceStateManagerService, getStateLocked(I)Ljava/util/Optional; > 1,2 @22 exception:40,
43 = invokevirtual < Application, Ljava/util/Optional, isPresent()Z > 41 @26 exception:42,
conditional branch(eq, to iindex=-1) 43,11,
58 = new <Application,Lcom/android/server/devicestate/OverrideRequest>@32,
invokespecial < Application, Lcom/android/server/devicestate/OverrideRequest, <init>(Landroid/os/IBinder;IIII)V > 58,5,4,2,3,11 @40 exception:59,
60 = getfield < Application, Lcom/android/server/devicestate/DeviceStateManagerService, mOverrideRequestController, <Application,Lcom/android/server/devicestate/OverrideRequestController> > 1,
invokevirtual < Application, Lcom/android/server/devicestate/OverrideRequestController, addRequest(Lcom/android/server/devicestate/OverrideRequest;)V > 60,58 @45 exception:61,
monitorexit 6,
return,
return,
invokestatic < Application, Landroid/os/Binder, restoreCallingIdentity(J)V > 14 @20 exception:20,
return,","depth : 0
-----
depth : 1
-----
depth : 2
-----
depth : 1
-----
depth : 2
-----
","public void requestState(IBinder p1, int p2, int p3){
	int v1 = Binder.getCallingPid();
	boolean v6 = DeviceStateManagerService.isStateAvailableForAppRequests(p3);
	if (v6 != 0) {
		if (p1 == 0) {
			long v7 = Binder.clearCallingIdentity();
			Object v10 = this.mProcessRecords.get(p4);
			if (v10 == 0) {
				boolean v11 = this.mOverrideRequestController.hasRequest(p5, 0);
				if (v11 != 0) {
					Optional v12 = DeviceStateManagerService.getStateLocked(p2);
					boolean v13 = v12.isPresent();
					if (v13 == 0) {
						OverrideRequest v14 = new OverrideRequest(p5,p4,p2,p3,0);
						this.mOverrideRequestController.addRequest(v14);
						Binder.restoreCallingIdentity(v7);
						return;
					}
				}
			}
		}
	}
}
","SYS_OR_SIG"
"Lcom/android/server/devicestate/DeviceStateManagerService$BinderService","requestState(Landroid/os/IBinder;II)V","2","6 = invokestatic < Application, Landroid/os/Binder, getCallingPid()I > @0 exception:5,
7 = getfield < Application, Lcom/android/server/devicestate/DeviceStateManagerService$BinderService, this$0, <Application,Lcom/android/server/devicestate/DeviceStateManagerService> > 1,
invokestatic < Application, Lcom/android/server/devicestate/DeviceStateManagerService, -$$Nest$massertCanRequestDeviceState(Lcom/android/server/devicestate/DeviceStateManagerService;II)V > 7,6,3 @6 exception:8,
invokevirtual < Application, Lcom/android/server/devicestate/DeviceStateManagerService, assertCanRequestDeviceState(II)V > 1,2,3 @0 exception:4,
4 = getfield < Application, Lcom/android/server/devicestate/DeviceStateManagerService, mActivityTaskManagerInternal, <Application,Lcom/android/server/wm/ActivityTaskManagerInternal> > 1,
6 = invokevirtual < Application, Lcom/android/server/wm/ActivityTaskManagerInternal, getTopApp()Lcom/android/server/wm/WindowProcessController; > 4 @2 exception:5,
conditional branch(eq, to iindex=-1) 6,7,
9 = invokevirtual < Application, Lcom/android/server/wm/WindowProcessController, getPid()I > 6 @8 exception:8,
conditional branch(ne, to iindex=-1) 9,2,
17 = invokevirtual < Application, Lcom/android/server/SystemService, getContext()Landroid/content/Context; > 1 @20 exception:16,
invokevirtual < Application, Landroid/content/Context, enforceCallingOrSelfPermission(Ljava/lang/String;Ljava/lang/String;)V > 17,18,19 @28 exception:20,
return,
return,
conditional branch(eq, to iindex=-1) 2,9,
14 = invokestatic < Application, Landroid/os/Binder, clearCallingIdentity()J > @11 exception:13,
15 = getfield < Application, Lcom/android/server/devicestate/DeviceStateManagerService$BinderService, this$0, <Application,Lcom/android/server/devicestate/DeviceStateManagerService> > 1,
invokestatic < Application, Lcom/android/server/devicestate/DeviceStateManagerService, -$$Nest$mrequestStateInternal(Lcom/android/server/devicestate/DeviceStateManagerService;IIILandroid/os/IBinder;)V > 15,3,4,6,2 @17 exception:16,
invokevirtual < Application, Lcom/android/server/devicestate/DeviceStateManagerService, requestStateInternal(IIILandroid/os/IBinder;)V > 1,2,3,4,5 @0 exception:6,
6 = getfield < Application, Lcom/android/server/devicestate/DeviceStateManagerService, mLock, <Application,Ljava/lang/Object> > 1,
monitorenter 6,
7 = getfield < Application, Lcom/android/server/devicestate/DeviceStateManagerService, mProcessRecords, <Application,Landroid/util/SparseArray> > 1,
9 = invokevirtual < Application, Landroid/util/SparseArray, get(I)Ljava/lang/Object; > 7,4 @5 exception:8,
10 = checkcast <Application,Lcom/android/server/devicestate/DeviceStateManagerService$ProcessRecord>9 <Application,Lcom/android/server/devicestate/DeviceStateManagerService$ProcessRecord>,
conditional branch(eq, to iindex=-1) 10,11,
26 = getfield < Application, Lcom/android/server/devicestate/DeviceStateManagerService, mOverrideRequestController, <Application,Lcom/android/server/devicestate/OverrideRequestController> > 1,
28 = invokevirtual < Application, Lcom/android/server/devicestate/OverrideRequestController, hasRequest(Landroid/os/IBinder;I)Z > 26,5,11 @16 exception:27,
conditional branch(ne, to iindex=-1) 28,11,
41 = invokevirtual < Application, Lcom/android/server/devicestate/DeviceStateManagerService, getStateLocked(I)Ljava/util/Optional; > 1,2 @22 exception:40,
43 = invokevirtual < Application, Ljava/util/Optional, isPresent()Z > 41 @26 exception:42,
conditional branch(eq, to iindex=-1) 43,11,
58 = new <Application,Lcom/android/server/devicestate/OverrideRequest>@32,
invokespecial < Application, Lcom/android/server/devicestate/OverrideRequest, <init>(Landroid/os/IBinder;IIII)V > 58,5,4,2,3,11 @40 exception:59,
60 = getfield < Application, Lcom/android/server/devicestate/DeviceStateManagerService, mOverrideRequestController, <Application,Lcom/android/server/devicestate/OverrideRequestController> > 1,
invokevirtual < Application, Lcom/android/server/devicestate/OverrideRequestController, addRequest(Lcom/android/server/devicestate/OverrideRequest;)V > 60,58 @45 exception:61,
monitorexit 6,
return,
return,
invokestatic < Application, Landroid/os/Binder, restoreCallingIdentity(J)V > 14 @20 exception:20,
return,","depth : 0
-----
depth : 1
-----
depth : 2
-----
depth : 1
-----
depth : 2
-----
","public void requestState(IBinder p1, int p2, int p3){
	int v1 = Binder.getCallingPid();
	if (p1 == 0) {
		long v8 = Binder.clearCallingIdentity();
		Object v11 = this.mProcessRecords.get(p4);
		if (v11 == 0) {
			boolean v12 = this.mOverrideRequestController.hasRequest(p5, 0);
			if (v12 != 0) {
				Optional v13 = DeviceStateManagerService.getStateLocked(p2);
				boolean v14 = v13.isPresent();
				if (v14 == 0) {
					OverrideRequest v15 = new OverrideRequest(p5,p4,p2,p3,0);
					this.mOverrideRequestController.addRequest(v15);
					Binder.restoreCallingIdentity(v8);
					return;
				}
			}
		}
	}
}
","SYS_OR_SIG"

