"Class","Method","Depth","Trace Instruction(s) ...","Java Code Representation","Code Merged","Access Control Level"
"Lcom/android/server/soundtrigger/SoundTriggerService$SoundTriggerServiceStub","attachAsMiddleman(Landroid/media/permission/Identity;Landroid/media/permission/Identity;Landroid/os/IBinder;)Lcom/android/internal/app/ISoundTriggerSession;","0","5 = getfield < Application, Lcom/android/server/soundtrigger/SoundTriggerService$SoundTriggerServiceStub, this$0, <Application,Lcom/android/server/soundtrigger/SoundTriggerService> > 1,
6 = getfield < Application, Lcom/android/server/soundtrigger/SoundTriggerService, mContext, <Application,Landroid/content/Context> > 5,
9 = invokestatic < Application, Landroid/media/permission/PermissionUtil, establishIdentityIndirect(Landroid/content/Context;Ljava/lang/String;Landroid/media/permission/Identity;Landroid/media/permission/Identity;)Landroid/media/permission/SafeCloseable; > 6,7,3,2 @6 exception:8,
10 = new <Application,Lcom/android/server/soundtrigger/SoundTriggerService$SoundTriggerSessionStub>@10,
11 = getfield < Application, Lcom/android/server/soundtrigger/SoundTriggerService$SoundTriggerServiceStub, this$0, <Application,Lcom/android/server/soundtrigger/SoundTriggerService> > 1,
invokespecial < Application, Lcom/android/server/soundtrigger/SoundTriggerService$SoundTriggerSessionStub, <init>(Lcom/android/server/soundtrigger/SoundTriggerService;Landroid/os/IBinder;)V > 10,11,4 @14 exception:12,
conditional branch(eq, to iindex=-1) 9,16,
invokeinterface < Application, Landroid/media/permission/SafeCloseable, close()V > 9 @19 exception:22,
return 10,","depth : 0
-----
","public ISoundTriggerSession attachAsMiddleman(Identity p1, Identity p2, IBinder p3){
	SafeCloseable v1 = PermissionUtil.establishIdentityIndirect(SoundTriggerService.mContext, ""android.permission.SOUNDTRIGGER_DELEGATE_IDENTITY"", p2, p1);
	SoundTriggerService$SoundTriggerSessionStub v2 = new SoundTriggerService$SoundTriggerSessionStub(this.this$0,p3);
	if (v1 == 0) {
		v1.close();
		return v2;
	}
}
","SYS_OR_SIG"
"Lcom/android/server/soundtrigger/SoundTriggerService$SoundTriggerServiceStub","attachAsMiddleman(Landroid/media/permission/Identity;Landroid/media/permission/Identity;Landroid/os/IBinder;)Lcom/android/internal/app/ISoundTriggerSession;","1","5 = getfield < Application, Lcom/android/server/soundtrigger/SoundTriggerService$SoundTriggerServiceStub, this$0, <Application,Lcom/android/server/soundtrigger/SoundTriggerService> > 1,
6 = getfield < Application, Lcom/android/server/soundtrigger/SoundTriggerService, mContext, <Application,Landroid/content/Context> > 5,
9 = invokestatic < Application, Landroid/media/permission/PermissionUtil, establishIdentityIndirect(Landroid/content/Context;Ljava/lang/String;Landroid/media/permission/Identity;Landroid/media/permission/Identity;)Landroid/media/permission/SafeCloseable; > 6,7,3,2 @6 exception:8,
6 = invokestatic < Application, Ljava/util/Objects, requireNonNull(Ljava/lang/Object;)Ljava/lang/Object; > 1 @0 exception:5,
8 = invokestatic < Application, Ljava/util/Objects, requireNonNull(Ljava/lang/Object;)Ljava/lang/Object; > 2 @3 exception:7,
10 = invokestatic < Application, Ljava/util/Objects, requireNonNull(Ljava/lang/Object;)Ljava/lang/Object; > 3 @6 exception:9,
12 = invokestatic < Application, Ljava/util/Objects, requireNonNull(Ljava/lang/Object;)Ljava/lang/Object; > 4 @9 exception:11,
14 = invokestatic < Application, Landroid/os/Binder, getCallingPid()I > @12 exception:13,
putfield 3.< Application, Landroid/media/permission/Identity, pid, <Primordial,I> > = 14,
16 = invokestatic < Application, Landroid/os/Binder, getCallingUid()I > @18 exception:15,
putfield 3.< Application, Landroid/media/permission/Identity, uid, <Primordial,I> > = 16,
17 = getfield < Application, Landroid/media/permission/Identity, pid, <Primordial,I> > 3,
18 = getfield < Application, Landroid/media/permission/Identity, uid, <Primordial,I> > 3,
20 = new <Application,[Ljava/lang/Object>@2919 ,
arraystore 20[21] = 2,
24 = invokestatic < Application, Ljava/lang/String, format(Ljava/lang/String;[Ljava/lang/Object;)Ljava/lang/String; > 22,20 @36 exception:23,
invokevirtual < Application, Landroid/content/Context, enforcePermission(Ljava/lang/String;IILjava/lang/String;)V > 1,2,17,18,24 @40 exception:25,
26 = new <Application,Landroid/media/permission/CompositeSafeCloseable>@43,
28 = new <Application,[Landroid/media/permission/SafeCloseable>@4627 ,
30 = invokestatic < Application, Landroid/media/permission/IdentityContext, create(Landroid/media/permission/Identity;)Landroid/media/permission/SafeCloseable; > 4 @48 exception:29,
arraystore 28[21] = 30,
32 = invokestatic < Application, Landroid/media/permission/ClearCallingIdentityContext, create()Landroid/media/permission/SafeCloseable; > @54 exception:31,
arraystore 28[19] = 32,
invokespecial < Application, Landroid/media/permission/CompositeSafeCloseable, <init>([Landroid/media/permission/SafeCloseable;)V > 26,28 @60 exception:33,
return 26,
10 = new <Application,Lcom/android/server/soundtrigger/SoundTriggerService$SoundTriggerSessionStub>@10,
11 = getfield < Application, Lcom/android/server/soundtrigger/SoundTriggerService$SoundTriggerServiceStub, this$0, <Application,Lcom/android/server/soundtrigger/SoundTriggerService> > 1,
invokespecial < Application, Lcom/android/server/soundtrigger/SoundTriggerService$SoundTriggerSessionStub, <init>(Lcom/android/server/soundtrigger/SoundTriggerService;Landroid/os/IBinder;)V > 10,11,4 @14 exception:12,
conditional branch(eq, to iindex=-1) 9,16,
invokeinterface < Application, Landroid/media/permission/SafeCloseable, close()V > 9 @19 exception:22,
return 10,","depth : 0
-----
depth : 1
-----
","public ISoundTriggerSession attachAsMiddleman(Identity p1, Identity p2, IBinder p3){
	CompositeSafeCloseable v11 = new CompositeSafeCloseable(v12);
	SafeCloseable v12 = new SafeCloseable(2);
	SafeCloseable v13 = IdentityContext.create(p1);
	SafeCloseable v14 = ClearCallingIdentityContext.create();
	SafeCloseable v1 = v11;
	SoundTriggerService$SoundTriggerSessionStub v16 = new SoundTriggerService$SoundTriggerSessionStub(this.this$0,p3);
	if (v1 == 0) {
		v1.close();
		return v16;
	}
}
","SYS_OR_SIG"
"Lcom/android/server/soundtrigger/SoundTriggerService$SoundTriggerServiceStub","attachAsMiddleman(Landroid/media/permission/Identity;Landroid/media/permission/Identity;Landroid/os/IBinder;)Lcom/android/internal/app/ISoundTriggerSession;","1","5 = getfield < Application, Lcom/android/server/soundtrigger/SoundTriggerService$SoundTriggerServiceStub, this$0, <Application,Lcom/android/server/soundtrigger/SoundTriggerService> > 1,
6 = getfield < Application, Lcom/android/server/soundtrigger/SoundTriggerService, mContext, <Application,Landroid/content/Context> > 5,
9 = invokestatic < Application, Landroid/media/permission/PermissionUtil, establishIdentityIndirect(Landroid/content/Context;Ljava/lang/String;Landroid/media/permission/Identity;Landroid/media/permission/Identity;)Landroid/media/permission/SafeCloseable; > 6,7,3,2 @6 exception:8,
6 = invokestatic < Application, Ljava/util/Objects, requireNonNull(Ljava/lang/Object;)Ljava/lang/Object; > 1 @0 exception:5,
8 = invokestatic < Application, Ljava/util/Objects, requireNonNull(Ljava/lang/Object;)Ljava/lang/Object; > 2 @3 exception:7,
10 = invokestatic < Application, Ljava/util/Objects, requireNonNull(Ljava/lang/Object;)Ljava/lang/Object; > 3 @6 exception:9,
12 = invokestatic < Application, Ljava/util/Objects, requireNonNull(Ljava/lang/Object;)Ljava/lang/Object; > 4 @9 exception:11,
14 = invokestatic < Application, Landroid/os/Binder, getCallingPid()I > @12 exception:13,
putfield 3.< Application, Landroid/media/permission/Identity, pid, <Primordial,I> > = 14,
16 = invokestatic < Application, Landroid/os/Binder, getCallingUid()I > @18 exception:15,
putfield 3.< Application, Landroid/media/permission/Identity, uid, <Primordial,I> > = 16,
17 = getfield < Application, Landroid/media/permission/Identity, pid, <Primordial,I> > 3,
18 = getfield < Application, Landroid/media/permission/Identity, uid, <Primordial,I> > 3,
20 = new <Application,[Ljava/lang/Object>@2919 ,
arraystore 20[21] = 2,
24 = invokestatic < Application, Ljava/lang/String, format(Ljava/lang/String;[Ljava/lang/Object;)Ljava/lang/String; > 22,20 @36 exception:23,
invokevirtual < Application, Landroid/content/Context, enforcePermission(Ljava/lang/String;IILjava/lang/String;)V > 1,2,17,18,24 @40 exception:25,
26 = new <Application,Landroid/media/permission/CompositeSafeCloseable>@43,
28 = new <Application,[Landroid/media/permission/SafeCloseable>@4627 ,
30 = invokestatic < Application, Landroid/media/permission/IdentityContext, create(Landroid/media/permission/Identity;)Landroid/media/permission/SafeCloseable; > 4 @48 exception:29,
arraystore 28[21] = 30,
32 = invokestatic < Application, Landroid/media/permission/ClearCallingIdentityContext, create()Landroid/media/permission/SafeCloseable; > @54 exception:31,
arraystore 28[19] = 32,
invokespecial < Application, Landroid/media/permission/CompositeSafeCloseable, <init>([Landroid/media/permission/SafeCloseable;)V > 26,28 @60 exception:33,
return 26,
10 = new <Application,Lcom/android/server/soundtrigger/SoundTriggerService$SoundTriggerSessionStub>@10,
11 = getfield < Application, Lcom/android/server/soundtrigger/SoundTriggerService$SoundTriggerServiceStub, this$0, <Application,Lcom/android/server/soundtrigger/SoundTriggerService> > 1,
invokespecial < Application, Lcom/android/server/soundtrigger/SoundTriggerService$SoundTriggerSessionStub, <init>(Lcom/android/server/soundtrigger/SoundTriggerService;Landroid/os/IBinder;)V > 10,11,4 @14 exception:12,
conditional branch(eq, to iindex=-1) 9,16,
return 10,","depth : 0
-----
depth : 1
-----
","public ISoundTriggerSession attachAsMiddleman(Identity p1, Identity p2, IBinder p3){
	CompositeSafeCloseable v11 = new CompositeSafeCloseable(v12);
	SafeCloseable v12 = new SafeCloseable(2);
	SafeCloseable v13 = IdentityContext.create(p1);
	SafeCloseable v14 = ClearCallingIdentityContext.create();
	SafeCloseable v1 = v11;
	SoundTriggerService$SoundTriggerSessionStub v16 = new SoundTriggerService$SoundTriggerSessionStub(this.this$0,p3);
	if (v1 == 0) {
		return v16;
	}
}
","SYS_OR_SIG"
"Lcom/android/server/soundtrigger/SoundTriggerService$SoundTriggerServiceStub","attachAsMiddleman(Landroid/media/permission/Identity;Landroid/media/permission/Identity;Landroid/os/IBinder;)Lcom/android/internal/app/ISoundTriggerSession;","2","5 = getfield < Application, Lcom/android/server/soundtrigger/SoundTriggerService$SoundTriggerServiceStub, this$0, <Application,Lcom/android/server/soundtrigger/SoundTriggerService> > 1,
6 = getfield < Application, Lcom/android/server/soundtrigger/SoundTriggerService, mContext, <Application,Landroid/content/Context> > 5,
9 = invokestatic < Application, Landroid/media/permission/PermissionUtil, establishIdentityIndirect(Landroid/content/Context;Ljava/lang/String;Landroid/media/permission/Identity;Landroid/media/permission/Identity;)Landroid/media/permission/SafeCloseable; > 6,7,3,2 @6 exception:8,
6 = invokestatic < Application, Ljava/util/Objects, requireNonNull(Ljava/lang/Object;)Ljava/lang/Object; > 1 @0 exception:5,
8 = invokestatic < Application, Ljava/util/Objects, requireNonNull(Ljava/lang/Object;)Ljava/lang/Object; > 2 @3 exception:7,
10 = invokestatic < Application, Ljava/util/Objects, requireNonNull(Ljava/lang/Object;)Ljava/lang/Object; > 3 @6 exception:9,
12 = invokestatic < Application, Ljava/util/Objects, requireNonNull(Ljava/lang/Object;)Ljava/lang/Object; > 4 @9 exception:11,
14 = invokestatic < Application, Landroid/os/Binder, getCallingPid()I > @12 exception:13,
putfield 3.< Application, Landroid/media/permission/Identity, pid, <Primordial,I> > = 14,
16 = invokestatic < Application, Landroid/os/Binder, getCallingUid()I > @18 exception:15,
putfield 3.< Application, Landroid/media/permission/Identity, uid, <Primordial,I> > = 16,
17 = getfield < Application, Landroid/media/permission/Identity, pid, <Primordial,I> > 3,
18 = getfield < Application, Landroid/media/permission/Identity, uid, <Primordial,I> > 3,
20 = new <Application,[Ljava/lang/Object>@2919 ,
arraystore 20[21] = 2,
24 = invokestatic < Application, Ljava/lang/String, format(Ljava/lang/String;[Ljava/lang/Object;)Ljava/lang/String; > 22,20 @36 exception:23,
invokevirtual < Application, Landroid/content/Context, enforcePermission(Ljava/lang/String;IILjava/lang/String;)V > 1,2,17,18,24 @40 exception:25,
26 = new <Application,Landroid/media/permission/CompositeSafeCloseable>@43,
28 = new <Application,[Landroid/media/permission/SafeCloseable>@4627 ,
30 = invokestatic < Application, Landroid/media/permission/IdentityContext, create(Landroid/media/permission/Identity;)Landroid/media/permission/SafeCloseable; > 4 @48 exception:29,
2 = new <Application,Landroid/media/permission/IdentityContext>@0,
invokespecial < Application, Landroid/media/permission/IdentityContext, <init>(Landroid/media/permission/Identity;)V > 2,1 @2 exception:3,
return 2,
arraystore 28[21] = 30,
32 = invokestatic < Application, Landroid/media/permission/ClearCallingIdentityContext, create()Landroid/media/permission/SafeCloseable; > @54 exception:31,
1 = new <Application,Landroid/media/permission/ClearCallingIdentityContext>@0,
invokespecial < Application, Landroid/media/permission/ClearCallingIdentityContext, <init>()V > 1 @2 exception:2,
return 1,
arraystore 28[19] = 32,
invokespecial < Application, Landroid/media/permission/CompositeSafeCloseable, <init>([Landroid/media/permission/SafeCloseable;)V > 26,28 @60 exception:33,
return 26,
10 = new <Application,Lcom/android/server/soundtrigger/SoundTriggerService$SoundTriggerSessionStub>@10,
11 = getfield < Application, Lcom/android/server/soundtrigger/SoundTriggerService$SoundTriggerServiceStub, this$0, <Application,Lcom/android/server/soundtrigger/SoundTriggerService> > 1,
invokespecial < Application, Lcom/android/server/soundtrigger/SoundTriggerService$SoundTriggerSessionStub, <init>(Lcom/android/server/soundtrigger/SoundTriggerService;Landroid/os/IBinder;)V > 10,11,4 @14 exception:12,
conditional branch(eq, to iindex=-1) 9,16,
invokeinterface < Application, Landroid/media/permission/SafeCloseable, close()V > 9 @19 exception:22,
return 10,","depth : 0
-----
depth : 1
-----
depth : 2
-----
depth : 2
-----
","public ISoundTriggerSession attachAsMiddleman(Identity p1, Identity p2, IBinder p3){
	CompositeSafeCloseable v11 = new CompositeSafeCloseable(v12);
	SafeCloseable v12 = new SafeCloseable(2);
	IdentityContext v14 = new IdentityContext(p4);
	SafeCloseable v13 = v14;
	ClearCallingIdentityContext v17 = new ClearCallingIdentityContext();
	SafeCloseable v16 = v17;
	SafeCloseable v1 = v11;
	SoundTriggerService$SoundTriggerSessionStub v20 = new SoundTriggerService$SoundTriggerSessionStub(this.this$0,p3);
	if (v1 == 0) {
		v1.close();
		return v20;
	}
}
","SYS_OR_SIG"
"Lcom/android/server/soundtrigger/SoundTriggerService$SoundTriggerServiceStub","attachAsMiddleman(Landroid/media/permission/Identity;Landroid/media/permission/Identity;Landroid/os/IBinder;)Lcom/android/internal/app/ISoundTriggerSession;","2","5 = getfield < Application, Lcom/android/server/soundtrigger/SoundTriggerService$SoundTriggerServiceStub, this$0, <Application,Lcom/android/server/soundtrigger/SoundTriggerService> > 1,
6 = getfield < Application, Lcom/android/server/soundtrigger/SoundTriggerService, mContext, <Application,Landroid/content/Context> > 5,
9 = invokestatic < Application, Landroid/media/permission/PermissionUtil, establishIdentityIndirect(Landroid/content/Context;Ljava/lang/String;Landroid/media/permission/Identity;Landroid/media/permission/Identity;)Landroid/media/permission/SafeCloseable; > 6,7,3,2 @6 exception:8,
6 = invokestatic < Application, Ljava/util/Objects, requireNonNull(Ljava/lang/Object;)Ljava/lang/Object; > 1 @0 exception:5,
8 = invokestatic < Application, Ljava/util/Objects, requireNonNull(Ljava/lang/Object;)Ljava/lang/Object; > 2 @3 exception:7,
10 = invokestatic < Application, Ljava/util/Objects, requireNonNull(Ljava/lang/Object;)Ljava/lang/Object; > 3 @6 exception:9,
12 = invokestatic < Application, Ljava/util/Objects, requireNonNull(Ljava/lang/Object;)Ljava/lang/Object; > 4 @9 exception:11,
14 = invokestatic < Application, Landroid/os/Binder, getCallingPid()I > @12 exception:13,
putfield 3.< Application, Landroid/media/permission/Identity, pid, <Primordial,I> > = 14,
16 = invokestatic < Application, Landroid/os/Binder, getCallingUid()I > @18 exception:15,
putfield 3.< Application, Landroid/media/permission/Identity, uid, <Primordial,I> > = 16,
17 = getfield < Application, Landroid/media/permission/Identity, pid, <Primordial,I> > 3,
18 = getfield < Application, Landroid/media/permission/Identity, uid, <Primordial,I> > 3,
20 = new <Application,[Ljava/lang/Object>@2919 ,
arraystore 20[21] = 2,
24 = invokestatic < Application, Ljava/lang/String, format(Ljava/lang/String;[Ljava/lang/Object;)Ljava/lang/String; > 22,20 @36 exception:23,
invokevirtual < Application, Landroid/content/Context, enforcePermission(Ljava/lang/String;IILjava/lang/String;)V > 1,2,17,18,24 @40 exception:25,
26 = new <Application,Landroid/media/permission/CompositeSafeCloseable>@43,
28 = new <Application,[Landroid/media/permission/SafeCloseable>@4627 ,
30 = invokestatic < Application, Landroid/media/permission/IdentityContext, create(Landroid/media/permission/Identity;)Landroid/media/permission/SafeCloseable; > 4 @48 exception:29,
2 = new <Application,Landroid/media/permission/IdentityContext>@0,
invokespecial < Application, Landroid/media/permission/IdentityContext, <init>(Landroid/media/permission/Identity;)V > 2,1 @2 exception:3,
return 2,
arraystore 28[21] = 30,
32 = invokestatic < Application, Landroid/media/permission/ClearCallingIdentityContext, create()Landroid/media/permission/SafeCloseable; > @54 exception:31,
1 = new <Application,Landroid/media/permission/ClearCallingIdentityContext>@0,
invokespecial < Application, Landroid/media/permission/ClearCallingIdentityContext, <init>()V > 1 @2 exception:2,
return 1,
arraystore 28[19] = 32,
invokespecial < Application, Landroid/media/permission/CompositeSafeCloseable, <init>([Landroid/media/permission/SafeCloseable;)V > 26,28 @60 exception:33,
return 26,
10 = new <Application,Lcom/android/server/soundtrigger/SoundTriggerService$SoundTriggerSessionStub>@10,
11 = getfield < Application, Lcom/android/server/soundtrigger/SoundTriggerService$SoundTriggerServiceStub, this$0, <Application,Lcom/android/server/soundtrigger/SoundTriggerService> > 1,
invokespecial < Application, Lcom/android/server/soundtrigger/SoundTriggerService$SoundTriggerSessionStub, <init>(Lcom/android/server/soundtrigger/SoundTriggerService;Landroid/os/IBinder;)V > 10,11,4 @14 exception:12,
conditional branch(eq, to iindex=-1) 9,16,
return 10,","depth : 0
-----
depth : 1
-----
depth : 2
-----
depth : 2
-----
","public ISoundTriggerSession attachAsMiddleman(Identity p1, Identity p2, IBinder p3){
	CompositeSafeCloseable v11 = new CompositeSafeCloseable(v12);
	SafeCloseable v12 = new SafeCloseable(2);
	IdentityContext v14 = new IdentityContext(p4);
	SafeCloseable v13 = v14;
	ClearCallingIdentityContext v17 = new ClearCallingIdentityContext();
	SafeCloseable v16 = v17;
	SafeCloseable v1 = v11;
	SoundTriggerService$SoundTriggerSessionStub v20 = new SoundTriggerService$SoundTriggerSessionStub(this.this$0,p3);
	if (v1 == 0) {
		return v20;
	}
}
","SYS_OR_SIG"

"Lcom/android/server/soundtrigger/SoundTriggerService$SoundTriggerServiceStub","attachAsOriginator(Landroid/media/permission/Identity;Landroid/os/IBinder;)Lcom/android/internal/app/ISoundTriggerSession;","0","5 = invokestatic < Application, Landroid/media/permission/PermissionUtil, establishIdentityDirect(Landroid/media/permission/Identity;)Landroid/media/permission/SafeCloseable; > 2 @0 exception:4,
6 = new <Application,Lcom/android/server/soundtrigger/SoundTriggerService$SoundTriggerSessionStub>@4,
7 = getfield < Application, Lcom/android/server/soundtrigger/SoundTriggerService$SoundTriggerServiceStub, this$0, <Application,Lcom/android/server/soundtrigger/SoundTriggerService> > 1,
invokespecial < Application, Lcom/android/server/soundtrigger/SoundTriggerService$SoundTriggerSessionStub, <init>(Lcom/android/server/soundtrigger/SoundTriggerService;Landroid/os/IBinder;)V > 6,7,3 @8 exception:8,
conditional branch(eq, to iindex=-1) 5,12,
invokeinterface < Application, Landroid/media/permission/SafeCloseable, close()V > 5 @13 exception:18,
return 6,","depth : 0
-----
","public ISoundTriggerSession attachAsOriginator(Identity p1, IBinder p2){
	SafeCloseable v1 = PermissionUtil.establishIdentityDirect(p1);
	SoundTriggerService$SoundTriggerSessionStub v2 = new SoundTriggerService$SoundTriggerSessionStub(this.this$0,p2);
	if (v1 == 0) {
		v1.close();
		return v2;
	}
}
","NONE"
"Lcom/android/server/soundtrigger/SoundTriggerService$SoundTriggerServiceStub","attachAsOriginator(Landroid/media/permission/Identity;Landroid/os/IBinder;)Lcom/android/internal/app/ISoundTriggerSession;","1","5 = invokestatic < Application, Landroid/media/permission/PermissionUtil, establishIdentityDirect(Landroid/media/permission/Identity;)Landroid/media/permission/SafeCloseable; > 2 @0 exception:4,
3 = invokestatic < Application, Ljava/util/Objects, requireNonNull(Ljava/lang/Object;)Ljava/lang/Object; > 1 @0 exception:2,
5 = invokestatic < Application, Landroid/os/Binder, getCallingUid()I > @3 exception:4,
putfield 1.< Application, Landroid/media/permission/Identity, uid, <Primordial,I> > = 5,
7 = invokestatic < Application, Landroid/os/Binder, getCallingPid()I > @9 exception:6,
putfield 1.< Application, Landroid/media/permission/Identity, pid, <Primordial,I> > = 7,
8 = new <Application,Landroid/media/permission/CompositeSafeCloseable>@15,
10 = new <Application,[Landroid/media/permission/SafeCloseable>@189 ,
12 = invokestatic < Application, Landroid/media/permission/IdentityContext, create(Landroid/media/permission/Identity;)Landroid/media/permission/SafeCloseable; > 1 @20 exception:11,
arraystore 10[13] = 12,
15 = invokestatic < Application, Landroid/media/permission/ClearCallingIdentityContext, create()Landroid/media/permission/SafeCloseable; > @27 exception:14,
arraystore 10[16] = 15,
invokespecial < Application, Landroid/media/permission/CompositeSafeCloseable, <init>([Landroid/media/permission/SafeCloseable;)V > 8,10 @34 exception:17,
return 8,
6 = new <Application,Lcom/android/server/soundtrigger/SoundTriggerService$SoundTriggerSessionStub>@4,
7 = getfield < Application, Lcom/android/server/soundtrigger/SoundTriggerService$SoundTriggerServiceStub, this$0, <Application,Lcom/android/server/soundtrigger/SoundTriggerService> > 1,
invokespecial < Application, Lcom/android/server/soundtrigger/SoundTriggerService$SoundTriggerSessionStub, <init>(Lcom/android/server/soundtrigger/SoundTriggerService;Landroid/os/IBinder;)V > 6,7,3 @8 exception:8,
conditional branch(eq, to iindex=-1) 5,12,
invokeinterface < Application, Landroid/media/permission/SafeCloseable, close()V > 5 @13 exception:18,
return 6,","depth : 0
-----
depth : 1
-----
","public ISoundTriggerSession attachAsOriginator(Identity p1, IBinder p2){
	Object v2 = Objects.requireNonNull(p1);
	int v3 = Binder.getCallingUid();
	Identity.uid = v3;
	int v4 = Binder.getCallingPid();
	Identity.pid = v4;
	CompositeSafeCloseable v5 = new CompositeSafeCloseable(v6);
	SafeCloseable v6 = new SafeCloseable(2);
	SafeCloseable v7 = IdentityContext.create(p1);
	SafeCloseable v8 = ClearCallingIdentityContext.create();
	SafeCloseable v1 = v5;
	SoundTriggerService$SoundTriggerSessionStub v10 = new SoundTriggerService$SoundTriggerSessionStub(this.this$0,p2);
	if (v1 == 0) {
		v1.close();
		return v10;
	}
}
","NONE"
"Lcom/android/server/soundtrigger/SoundTriggerService$SoundTriggerServiceStub","attachAsOriginator(Landroid/media/permission/Identity;Landroid/os/IBinder;)Lcom/android/internal/app/ISoundTriggerSession;","1","5 = invokestatic < Application, Landroid/media/permission/PermissionUtil, establishIdentityDirect(Landroid/media/permission/Identity;)Landroid/media/permission/SafeCloseable; > 2 @0 exception:4,
3 = invokestatic < Application, Ljava/util/Objects, requireNonNull(Ljava/lang/Object;)Ljava/lang/Object; > 1 @0 exception:2,
5 = invokestatic < Application, Landroid/os/Binder, getCallingUid()I > @3 exception:4,
putfield 1.< Application, Landroid/media/permission/Identity, uid, <Primordial,I> > = 5,
7 = invokestatic < Application, Landroid/os/Binder, getCallingPid()I > @9 exception:6,
putfield 1.< Application, Landroid/media/permission/Identity, pid, <Primordial,I> > = 7,
8 = new <Application,Landroid/media/permission/CompositeSafeCloseable>@15,
10 = new <Application,[Landroid/media/permission/SafeCloseable>@189 ,
12 = invokestatic < Application, Landroid/media/permission/IdentityContext, create(Landroid/media/permission/Identity;)Landroid/media/permission/SafeCloseable; > 1 @20 exception:11,
arraystore 10[13] = 12,
15 = invokestatic < Application, Landroid/media/permission/ClearCallingIdentityContext, create()Landroid/media/permission/SafeCloseable; > @27 exception:14,
arraystore 10[16] = 15,
invokespecial < Application, Landroid/media/permission/CompositeSafeCloseable, <init>([Landroid/media/permission/SafeCloseable;)V > 8,10 @34 exception:17,
return 8,
6 = new <Application,Lcom/android/server/soundtrigger/SoundTriggerService$SoundTriggerSessionStub>@4,
7 = getfield < Application, Lcom/android/server/soundtrigger/SoundTriggerService$SoundTriggerServiceStub, this$0, <Application,Lcom/android/server/soundtrigger/SoundTriggerService> > 1,
invokespecial < Application, Lcom/android/server/soundtrigger/SoundTriggerService$SoundTriggerSessionStub, <init>(Lcom/android/server/soundtrigger/SoundTriggerService;Landroid/os/IBinder;)V > 6,7,3 @8 exception:8,
conditional branch(eq, to iindex=-1) 5,12,
return 6,","depth : 0
-----
depth : 1
-----
","public ISoundTriggerSession attachAsOriginator(Identity p1, IBinder p2){
	Object v2 = Objects.requireNonNull(p1);
	int v3 = Binder.getCallingUid();
	Identity.uid = v3;
	int v4 = Binder.getCallingPid();
	Identity.pid = v4;
	CompositeSafeCloseable v5 = new CompositeSafeCloseable(v6);
	SafeCloseable v6 = new SafeCloseable(2);
	SafeCloseable v7 = IdentityContext.create(p1);
	SafeCloseable v8 = ClearCallingIdentityContext.create();
	SafeCloseable v1 = v5;
	SoundTriggerService$SoundTriggerSessionStub v10 = new SoundTriggerService$SoundTriggerSessionStub(this.this$0,p2);
	if (v1 == 0) {
		return v10;
	}
}
","NONE"
"Lcom/android/server/soundtrigger/SoundTriggerService$SoundTriggerServiceStub","attachAsOriginator(Landroid/media/permission/Identity;Landroid/os/IBinder;)Lcom/android/internal/app/ISoundTriggerSession;","2","5 = invokestatic < Application, Landroid/media/permission/PermissionUtil, establishIdentityDirect(Landroid/media/permission/Identity;)Landroid/media/permission/SafeCloseable; > 2 @0 exception:4,
3 = invokestatic < Application, Ljava/util/Objects, requireNonNull(Ljava/lang/Object;)Ljava/lang/Object; > 1 @0 exception:2,
5 = invokestatic < Application, Landroid/os/Binder, getCallingUid()I > @3 exception:4,
putfield 1.< Application, Landroid/media/permission/Identity, uid, <Primordial,I> > = 5,
7 = invokestatic < Application, Landroid/os/Binder, getCallingPid()I > @9 exception:6,
putfield 1.< Application, Landroid/media/permission/Identity, pid, <Primordial,I> > = 7,
8 = new <Application,Landroid/media/permission/CompositeSafeCloseable>@15,
10 = new <Application,[Landroid/media/permission/SafeCloseable>@189 ,
12 = invokestatic < Application, Landroid/media/permission/IdentityContext, create(Landroid/media/permission/Identity;)Landroid/media/permission/SafeCloseable; > 1 @20 exception:11,
2 = new <Application,Landroid/media/permission/IdentityContext>@0,
invokespecial < Application, Landroid/media/permission/IdentityContext, <init>(Landroid/media/permission/Identity;)V > 2,1 @2 exception:3,
return 2,
arraystore 10[13] = 12,
15 = invokestatic < Application, Landroid/media/permission/ClearCallingIdentityContext, create()Landroid/media/permission/SafeCloseable; > @27 exception:14,
1 = new <Application,Landroid/media/permission/ClearCallingIdentityContext>@0,
invokespecial < Application, Landroid/media/permission/ClearCallingIdentityContext, <init>()V > 1 @2 exception:2,
return 1,
arraystore 10[16] = 15,
invokespecial < Application, Landroid/media/permission/CompositeSafeCloseable, <init>([Landroid/media/permission/SafeCloseable;)V > 8,10 @34 exception:17,
return 8,
6 = new <Application,Lcom/android/server/soundtrigger/SoundTriggerService$SoundTriggerSessionStub>@4,
7 = getfield < Application, Lcom/android/server/soundtrigger/SoundTriggerService$SoundTriggerServiceStub, this$0, <Application,Lcom/android/server/soundtrigger/SoundTriggerService> > 1,
invokespecial < Application, Lcom/android/server/soundtrigger/SoundTriggerService$SoundTriggerSessionStub, <init>(Lcom/android/server/soundtrigger/SoundTriggerService;Landroid/os/IBinder;)V > 6,7,3 @8 exception:8,
conditional branch(eq, to iindex=-1) 5,12,
invokeinterface < Application, Landroid/media/permission/SafeCloseable, close()V > 5 @13 exception:18,
return 6,","depth : 0
-----
depth : 1
-----
depth : 2
-----
depth : 2
-----
","public ISoundTriggerSession attachAsOriginator(Identity p1, IBinder p2){
	Object v2 = Objects.requireNonNull(p1);
	int v3 = Binder.getCallingUid();
	Identity.uid = v3;
	int v4 = Binder.getCallingPid();
	Identity.pid = v4;
	CompositeSafeCloseable v5 = new CompositeSafeCloseable(v6);
	SafeCloseable v6 = new SafeCloseable(2);
	IdentityContext v8 = new IdentityContext(p1);
	SafeCloseable v7 = v8;
	ClearCallingIdentityContext v11 = new ClearCallingIdentityContext();
	SafeCloseable v10 = v11;
	SafeCloseable v1 = v5;
	SoundTriggerService$SoundTriggerSessionStub v14 = new SoundTriggerService$SoundTriggerSessionStub(this.this$0,p2);
	if (v1 == 0) {
		v1.close();
		return v14;
	}
}
","NONE"
"Lcom/android/server/soundtrigger/SoundTriggerService$SoundTriggerServiceStub","attachAsOriginator(Landroid/media/permission/Identity;Landroid/os/IBinder;)Lcom/android/internal/app/ISoundTriggerSession;","2","5 = invokestatic < Application, Landroid/media/permission/PermissionUtil, establishIdentityDirect(Landroid/media/permission/Identity;)Landroid/media/permission/SafeCloseable; > 2 @0 exception:4,
3 = invokestatic < Application, Ljava/util/Objects, requireNonNull(Ljava/lang/Object;)Ljava/lang/Object; > 1 @0 exception:2,
5 = invokestatic < Application, Landroid/os/Binder, getCallingUid()I > @3 exception:4,
putfield 1.< Application, Landroid/media/permission/Identity, uid, <Primordial,I> > = 5,
7 = invokestatic < Application, Landroid/os/Binder, getCallingPid()I > @9 exception:6,
putfield 1.< Application, Landroid/media/permission/Identity, pid, <Primordial,I> > = 7,
8 = new <Application,Landroid/media/permission/CompositeSafeCloseable>@15,
10 = new <Application,[Landroid/media/permission/SafeCloseable>@189 ,
12 = invokestatic < Application, Landroid/media/permission/IdentityContext, create(Landroid/media/permission/Identity;)Landroid/media/permission/SafeCloseable; > 1 @20 exception:11,
2 = new <Application,Landroid/media/permission/IdentityContext>@0,
invokespecial < Application, Landroid/media/permission/IdentityContext, <init>(Landroid/media/permission/Identity;)V > 2,1 @2 exception:3,
return 2,
arraystore 10[13] = 12,
15 = invokestatic < Application, Landroid/media/permission/ClearCallingIdentityContext, create()Landroid/media/permission/SafeCloseable; > @27 exception:14,
1 = new <Application,Landroid/media/permission/ClearCallingIdentityContext>@0,
invokespecial < Application, Landroid/media/permission/ClearCallingIdentityContext, <init>()V > 1 @2 exception:2,
return 1,
arraystore 10[16] = 15,
invokespecial < Application, Landroid/media/permission/CompositeSafeCloseable, <init>([Landroid/media/permission/SafeCloseable;)V > 8,10 @34 exception:17,
return 8,
6 = new <Application,Lcom/android/server/soundtrigger/SoundTriggerService$SoundTriggerSessionStub>@4,
7 = getfield < Application, Lcom/android/server/soundtrigger/SoundTriggerService$SoundTriggerServiceStub, this$0, <Application,Lcom/android/server/soundtrigger/SoundTriggerService> > 1,
invokespecial < Application, Lcom/android/server/soundtrigger/SoundTriggerService$SoundTriggerSessionStub, <init>(Lcom/android/server/soundtrigger/SoundTriggerService;Landroid/os/IBinder;)V > 6,7,3 @8 exception:8,
conditional branch(eq, to iindex=-1) 5,12,
return 6,","depth : 0
-----
depth : 1
-----
depth : 2
-----
depth : 2
-----
","public ISoundTriggerSession attachAsOriginator(Identity p1, IBinder p2){
	Object v2 = Objects.requireNonNull(p1);
	int v3 = Binder.getCallingUid();
	Identity.uid = v3;
	int v4 = Binder.getCallingPid();
	Identity.pid = v4;
	CompositeSafeCloseable v5 = new CompositeSafeCloseable(v6);
	SafeCloseable v6 = new SafeCloseable(2);
	IdentityContext v8 = new IdentityContext(p1);
	SafeCloseable v7 = v8;
	ClearCallingIdentityContext v11 = new ClearCallingIdentityContext();
	SafeCloseable v10 = v11;
	SafeCloseable v1 = v5;
	SoundTriggerService$SoundTriggerSessionStub v14 = new SoundTriggerService$SoundTriggerSessionStub(this.this$0,p2);
	if (v1 == 0) {
		return v14;
	}
}
","NONE"

