"Class","Method","Depth","Trace Instruction(s) ...","Java Code Representation","Code Merged","Access Control Level"
"Lcom/android/server/vibrator/VibratorManagerService","cancelVibrate(ILandroid/os/IBinder;)V","0","invokestatic < Application, Landroid/os/Trace, traceBegin(JLjava/lang/String;)V > 5,4 @5 exception:6,
7 = getfield < Application, Lcom/android/server/vibrator/VibratorManagerService, mContext, <Application,Landroid/content/Context> > 1,
invokevirtual < Application, Landroid/content/Context, enforceCallingOrSelfPermission(Ljava/lang/String;Ljava/lang/String;)V > 7,8,4 @14 exception:9,
10 = getfield < Application, Lcom/android/server/vibrator/VibratorManagerService, mLock, <Application,Ljava/lang/Object> > 1,
monitorenter 10,
11 = new <Application,Lcom/android/server/vibrator/Vibration$EndInfo>@20,
12 = getstatic < Application, Lcom/android/server/vibrator/Vibration$Status, CANCELLED_BY_USER, <Application,Lcom/android/server/vibrator/Vibration$Status> >,
invokespecial < Application, Lcom/android/server/vibrator/Vibration$EndInfo, <init>(Lcom/android/server/vibrator/Vibration$Status;)V > 11,12 @24 exception:13,
15 = invokestatic < Application, Landroid/os/Binder, clearCallingIdentity()J > @27 exception:14,
16 = getfield < Application, Lcom/android/server/vibrator/VibratorManagerService, mNextVibration, <Application,Lcom/android/server/vibrator/VibrationStepConductor> > 1,
conditional branch(eq, to iindex=-1) 16,17,
19 = invokevirtual < Application, Lcom/android/server/vibrator/VibrationStepConductor, getVibration()Lcom/android/server/vibrator/Vibration; > 16 @35 exception:18,
21 = invokevirtual < Application, Lcom/android/server/vibrator/VibratorManagerService, shouldCancelVibration(Lcom/android/server/vibrator/Vibration;ILandroid/os/IBinder;)Z > 1,19,2,3 @39 exception:20,
conditional branch(eq, to iindex=-1) 21,17,
invokevirtual < Application, Lcom/android/server/vibrator/VibratorManagerService, clearNextVibrationLocked(Lcom/android/server/vibrator/Vibration$EndInfo;)V > 1,11 @45 exception:22,
26 = getfield < Application, Lcom/android/server/vibrator/VibratorManagerService, mCurrentVibration, <Application,Lcom/android/server/vibrator/VibrationStepConductor> > 1,
conditional branch(eq, to iindex=-1) 26,17,
28 = invokevirtual < Application, Lcom/android/server/vibrator/VibrationStepConductor, getVibration()Lcom/android/server/vibrator/Vibration; > 26 @53 exception:27,
30 = invokevirtual < Application, Lcom/android/server/vibrator/VibratorManagerService, shouldCancelVibration(Lcom/android/server/vibrator/Vibration;ILandroid/os/IBinder;)Z > 1,28,2,3 @57 exception:29,
conditional branch(eq, to iindex=-1) 30,17,
31 = getfield < Application, Lcom/android/server/vibrator/VibratorManagerService, mCurrentVibration, <Application,Lcom/android/server/vibrator/VibrationStepConductor> > 1,
invokevirtual < Application, Lcom/android/server/vibrator/VibrationStepConductor, notifyCancelled(Lcom/android/server/vibrator/Vibration$EndInfo;Z)V > 31,11,17 @65 exception:32,
37 = getfield < Application, Lcom/android/server/vibrator/VibratorManagerService, mCurrentExternalVibration, <Application,Lcom/android/server/vibrator/VibratorManagerService$ExternalVibrationHolder> > 1,
conditional branch(eq, to iindex=-1) 37,17,
38 = getfield < Application, Lcom/android/server/vibrator/VibratorManagerService$ExternalVibrationHolder, externalVibration, <Application,Landroid/os/ExternalVibration> > 37,
40 = invokevirtual < Application, Landroid/os/ExternalVibration, getVibrationAttributes()Landroid/os/VibrationAttributes; > 38 @74 exception:39,
42 = invokevirtual < Application, Lcom/android/server/vibrator/VibratorManagerService, shouldCancelVibration(Landroid/os/VibrationAttributes;I)Z > 1,40,2 @78 exception:41,
conditional branch(eq, to iindex=-1) 42,17,
43 = getfield < Application, Lcom/android/server/vibrator/VibratorManagerService, mCurrentExternalVibration, <Application,Lcom/android/server/vibrator/VibratorManagerService$ExternalVibrationHolder> > 1,
invokevirtual < Application, Lcom/android/server/vibrator/VibratorManagerService$ExternalVibrationHolder, mute()V > 43 @86 exception:44,
invokevirtual < Application, Lcom/android/server/vibrator/VibratorManagerService, endExternalVibrateLocked(Lcom/android/server/vibrator/Vibration$EndInfo;Z)V > 1,11,17 @89 exception:45,
invokestatic < Application, Landroid/os/Binder, restoreCallingIdentity(J)V > 15 @92 exception:57,
monitorexit 10,
invokestatic < Application, Landroid/os/Trace, traceEnd(J)V > 5 @96 exception:75,
return,","depth : 0
-----
","public void cancelVibrate(int p1, IBinder p2){
	Vibration$EndInfo v3 = new Vibration$EndInfo(Vibration$Status.CANCELLED_BY_USER);
	long v5 = Binder.clearCallingIdentity();
	if (this.mNextVibration == 0) {
		Vibration v6 = this.mNextVibration.getVibration();
		boolean v7 = p0.shouldCancelVibration(v6, p1, p2);
		if (v7 == 0) {
			p0.clearNextVibrationLocked(v3);
			if (this.mCurrentVibration == 0) {
				Vibration v9 = this.mCurrentVibration.getVibration();
				boolean v10 = p0.shouldCancelVibration(v9, p1, p2);
				if (v10 == 0) {
					this.mCurrentVibration.notifyCancelled(v3, 0);
					if (this.mCurrentExternalVibration == 0) {
						VibrationAttributes v12 = VibratorManagerService$ExternalVibrationHolder.externalVibration.getVibrationAttributes();
						boolean v13 = p0.shouldCancelVibration(v12, p1);
						if (v13 == 0) {
							this.mCurrentExternalVibration.mute();
							p0.endExternalVibrateLocked(v3, 0);
							Binder.restoreCallingIdentity(v5);
							Trace.traceEnd(8388608);
							return;
						}
					}
				}
			}
		}
	}
}
","NORMAL"
"Lcom/android/server/vibrator/VibratorManagerService","cancelVibrate(ILandroid/os/IBinder;)V","1","invokestatic < Application, Landroid/os/Trace, traceBegin(JLjava/lang/String;)V > 5,4 @5 exception:6,
7 = getfield < Application, Lcom/android/server/vibrator/VibratorManagerService, mContext, <Application,Landroid/content/Context> > 1,
invokevirtual < Application, Landroid/content/Context, enforceCallingOrSelfPermission(Ljava/lang/String;Ljava/lang/String;)V > 7,8,4 @14 exception:9,
10 = getfield < Application, Lcom/android/server/vibrator/VibratorManagerService, mLock, <Application,Ljava/lang/Object> > 1,
monitorenter 10,
11 = new <Application,Lcom/android/server/vibrator/Vibration$EndInfo>@20,
12 = getstatic < Application, Lcom/android/server/vibrator/Vibration$Status, CANCELLED_BY_USER, <Application,Lcom/android/server/vibrator/Vibration$Status> >,
invokespecial < Application, Lcom/android/server/vibrator/Vibration$EndInfo, <init>(Lcom/android/server/vibrator/Vibration$Status;)V > 11,12 @24 exception:13,
15 = invokestatic < Application, Landroid/os/Binder, clearCallingIdentity()J > @27 exception:14,
16 = getfield < Application, Lcom/android/server/vibrator/VibratorManagerService, mNextVibration, <Application,Lcom/android/server/vibrator/VibrationStepConductor> > 1,
conditional branch(eq, to iindex=-1) 16,17,
19 = invokevirtual < Application, Lcom/android/server/vibrator/VibrationStepConductor, getVibration()Lcom/android/server/vibrator/Vibration; > 16 @35 exception:18,
2 = getfield < Application, Lcom/android/server/vibrator/VibrationStepConductor, mVibration, <Application,Lcom/android/server/vibrator/Vibration> > 1,
return 2,
21 = invokevirtual < Application, Lcom/android/server/vibrator/VibratorManagerService, shouldCancelVibration(Lcom/android/server/vibrator/Vibration;ILandroid/os/IBinder;)Z > 1,19,2,3 @39 exception:20,
5 = getfield < Application, Lcom/android/server/vibrator/Vibration, token, <Application,Landroid/os/IBinder> > 2,
conditional branch(ne, to iindex=-1) 5,4,
6 = getfield < Application, Lcom/android/server/vibrator/Vibration, attrs, <Application,Landroid/os/VibrationAttributes> > 2,
8 = invokevirtual < Application, Lcom/android/server/vibrator/VibratorManagerService, shouldCancelVibration(Landroid/os/VibrationAttributes;I)Z > 1,6,3 @6 exception:7,
conditional branch(eq, to iindex=-1) 8,9,
goto (from iindex= 7 to iindex = 2),
13 = phi  12,9,
return 13,
conditional branch(eq, to iindex=-1) 21,17,
invokevirtual < Application, Lcom/android/server/vibrator/VibratorManagerService, clearNextVibrationLocked(Lcom/android/server/vibrator/Vibration$EndInfo;)V > 1,11 @45 exception:22,
3 = getfield < Application, Lcom/android/server/vibrator/VibratorManagerService, mNextVibration, <Application,Lcom/android/server/vibrator/VibrationStepConductor> > 1,
conditional branch(eq, to iindex=-1) 3,4,
6 = invokevirtual < Application, Lcom/android/server/vibrator/VibrationStepConductor, getVibration()Lcom/android/server/vibrator/Vibration; > 3 @4 exception:5,
invokevirtual < Application, Lcom/android/server/vibrator/VibratorManagerService, endVibrationLocked(Lcom/android/server/vibrator/Vibration;Lcom/android/server/vibrator/Vibration$EndInfo;Z)V > 1,6,2,7 @9 exception:8,
putfield 1.< Application, Lcom/android/server/vibrator/VibratorManagerService, mNextVibration, <Application,Lcom/android/server/vibrator/VibrationStepConductor> > = 4,
return,
26 = getfield < Application, Lcom/android/server/vibrator/VibratorManagerService, mCurrentVibration, <Application,Lcom/android/server/vibrator/VibrationStepConductor> > 1,
conditional branch(eq, to iindex=-1) 26,17,
28 = invokevirtual < Application, Lcom/android/server/vibrator/VibrationStepConductor, getVibration()Lcom/android/server/vibrator/Vibration; > 26 @53 exception:27,
2 = getfield < Application, Lcom/android/server/vibrator/VibrationStepConductor, mVibration, <Application,Lcom/android/server/vibrator/Vibration> > 1,
return 2,
30 = invokevirtual < Application, Lcom/android/server/vibrator/VibratorManagerService, shouldCancelVibration(Lcom/android/server/vibrator/Vibration;ILandroid/os/IBinder;)Z > 1,28,2,3 @57 exception:29,
5 = getfield < Application, Lcom/android/server/vibrator/Vibration, token, <Application,Landroid/os/IBinder> > 2,
conditional branch(ne, to iindex=-1) 5,4,
6 = getfield < Application, Lcom/android/server/vibrator/Vibration, attrs, <Application,Landroid/os/VibrationAttributes> > 2,
8 = invokevirtual < Application, Lcom/android/server/vibrator/VibratorManagerService, shouldCancelVibration(Landroid/os/VibrationAttributes;I)Z > 1,6,3 @6 exception:7,
conditional branch(eq, to iindex=-1) 8,9,
goto (from iindex= 7 to iindex = 2),
13 = phi  12,9,
return 13,
conditional branch(eq, to iindex=-1) 30,17,
31 = getfield < Application, Lcom/android/server/vibrator/VibratorManagerService, mCurrentVibration, <Application,Lcom/android/server/vibrator/VibrationStepConductor> > 1,
invokevirtual < Application, Lcom/android/server/vibrator/VibrationStepConductor, notifyCancelled(Lcom/android/server/vibrator/Vibration$EndInfo;Z)V > 31,11,17 @65 exception:32,
4 = getstatic < Application, Landroid/os/Build, IS_DEBUGGABLE, <Primordial,Z> >,
conditional branch(eq, to iindex=-1) 4,5,
invokestatic < Application, Lcom/android/server/vibrator/VibrationStepConductor, expectIsVibrationThread(Z)V > 5 @5 exception:6,
conditional branch(eq, to iindex=-1) 2,5,
8 = getfield < Application, Lcom/android/server/vibrator/Vibration$EndInfo, status, <Application,Lcom/android/server/vibrator/Vibration$Status> > 2,
10 = invokevirtual < Application, Ljava/lang/Enum, name()Ljava/lang/String; > 8 @12 exception:9,
13 = invokevirtual < Application, Ljava/lang/String, startsWith(Ljava/lang/String;)Z > 10,11 @18 exception:12,
conditional branch(ne, to iindex=-1) 13,5,
17 = new <Application,Ljava/lang/StringBuilder>@26,
invokespecial < Application, Ljava/lang/StringBuilder, <init>()V > 17 @28 exception:18,
21 = invokevirtual < Application, Ljava/lang/StringBuilder, append(Ljava/lang/String;)Ljava/lang/StringBuilder; > 17,19 @33 exception:20,
23 = invokevirtual < Application, Ljava/lang/StringBuilder, append(Ljava/lang/Object;)Ljava/lang/StringBuilder; > 17,2 @36 exception:22,
26 = invokevirtual < Application, Ljava/lang/StringBuilder, append(Ljava/lang/String;)Ljava/lang/StringBuilder; > 17,24 @41 exception:25,
28 = invokevirtual < Application, Ljava/lang/StringBuilder, toString()Ljava/lang/String; > 17 @44 exception:27,
30 = invokestatic < Application, Landroid/util/Slog, w(Ljava/lang/String;Ljava/lang/String;)I > 16,28 @48 exception:29,
31 = new <Application,Lcom/android/server/vibrator/Vibration$EndInfo>@51,
32 = getstatic < Application, Lcom/android/server/vibrator/Vibration$Status, CANCELLED_BY_UNKNOWN_REASON, <Application,Lcom/android/server/vibrator/Vibration$Status> >,
invokespecial < Application, Lcom/android/server/vibrator/Vibration$EndInfo, <init>(Lcom/android/server/vibrator/Vibration$Status;)V > 31,32 @55 exception:33,
36 = phi  2,31,
39 = getfield < Application, Lcom/android/server/vibrator/VibrationStepConductor, mLock, <Application,Ljava/lang/Object> > 1,
monitorenter 39,
conditional branch(eq, to iindex=-1) 3,5,
40 = getfield < Application, Lcom/android/server/vibrator/VibrationStepConductor, mSignalCancelImmediate, <Primordial,Z> > 1,
conditional branch(ne, to iindex=-1) 40,5,
42 = getfield < Application, Lcom/android/server/vibrator/VibrationStepConductor, mSignalCancel, <Application,Lcom/android/server/vibrator/Vibration$EndInfo> > 1,
conditional branch(eq, to iindex=-1) 42,5,
43 = getfield < Application, Lcom/android/server/vibrator/VibrationStepConductor, mSignalCancelImmediate, <Primordial,Z> > 1,
44 = binaryop(or) 3 , 43,
putfield 1.< Application, Lcom/android/server/vibrator/VibrationStepConductor, mSignalCancelImmediate, <Primordial,Z> > = 44,
conditional branch(ne, to iindex=-1) 42,5,
putfield 1.< Application, Lcom/android/server/vibrator/VibrationStepConductor, mSignalCancel, <Application,Lcom/android/server/vibrator/Vibration$EndInfo> > = 36,
45 = getfield < Application, Lcom/android/server/vibrator/VibrationStepConductor, mLock, <Application,Ljava/lang/Object> > 1,
invokevirtual < Application, Ljava/lang/Object, notify()V > 45 @84 exception:46,
monitorexit 39,
return,
37 = getfield < Application, Lcom/android/server/vibrator/VibratorManagerService, mCurrentExternalVibration, <Application,Lcom/android/server/vibrator/VibratorManagerService$ExternalVibrationHolder> > 1,
conditional branch(eq, to iindex=-1) 37,17,
38 = getfield < Application, Lcom/android/server/vibrator/VibratorManagerService$ExternalVibrationHolder, externalVibration, <Application,Landroid/os/ExternalVibration> > 37,
40 = invokevirtual < Application, Landroid/os/ExternalVibration, getVibrationAttributes()Landroid/os/VibrationAttributes; > 38 @74 exception:39,
2 = new <Application,Landroid/os/VibrationAttributes$Builder>@0,
3 = getfield < Application, Landroid/os/ExternalVibration, mAttrs, <Application,Landroid/media/AudioAttributes> > 1,
invokespecial < Application, Landroid/os/VibrationAttributes$Builder, <init>(Landroid/media/AudioAttributes;)V > 2,3 @4 exception:4,
6 = invokevirtual < Application, Landroid/os/VibrationAttributes$Builder, build()Landroid/os/VibrationAttributes; > 2 @7 exception:5,
return 6,
42 = invokevirtual < Application, Lcom/android/server/vibrator/VibratorManagerService, shouldCancelVibration(Landroid/os/VibrationAttributes;I)Z > 1,40,2 @78 exception:41,
5 = invokevirtual < Application, Landroid/os/VibrationAttributes, getUsage()I > 2 @0 exception:4,
conditional branch(ne, to iindex=-1) 5,7,
9 = invokevirtual < Application, Landroid/os/VibrationAttributes, getUsage()I > 2 @16 exception:8,
10 = binaryop(and) 9 , 3,
12 = invokevirtual < Application, Landroid/os/VibrationAttributes, getUsage()I > 2 @21 exception:11,
conditional branch(ne, to iindex=-1) 10,12,
goto (from iindex= 17 to iindex = 2),
13 = phi  6,7,
return 13,
conditional branch(eq, to iindex=-1) 42,17,
43 = getfield < Application, Lcom/android/server/vibrator/VibratorManagerService, mCurrentExternalVibration, <Application,Lcom/android/server/vibrator/VibratorManagerService$ExternalVibrationHolder> > 1,
invokevirtual < Application, Lcom/android/server/vibrator/VibratorManagerService$ExternalVibrationHolder, mute()V > 43 @86 exception:44,
2 = getfield < Application, Lcom/android/server/vibrator/VibratorManagerService$ExternalVibrationHolder, externalVibration, <Application,Landroid/os/ExternalVibration> > 1,
4 = invokevirtual < Application, Landroid/os/ExternalVibration, mute()Z > 2 @2 exception:3,
return,
invokevirtual < Application, Lcom/android/server/vibrator/VibratorManagerService, endExternalVibrateLocked(Lcom/android/server/vibrator/Vibration$EndInfo;Z)V > 1,11,17 @89 exception:45,
invokestatic < Application, Landroid/os/Trace, traceBegin(JLjava/lang/String;)V > 4,5 @5 exception:6,
7 = getfield < Application, Lcom/android/server/vibrator/VibratorManagerService, mCurrentExternalVibration, <Application,Lcom/android/server/vibrator/VibratorManagerService$ExternalVibrationHolder> > 1,
conditional branch(ne, to iindex=-1) 7,8,
invokevirtual < Application, Lcom/android/server/vibrator/VibratorManagerService$ExternalVibrationHolder, unlinkToDeath()V > 7 @16 exception:9,
conditional branch(ne, to iindex=-1) 3,8,
10 = getfield < Application, Lcom/android/server/vibrator/VibratorManagerService, mCurrentExternalVibration, <Application,Lcom/android/server/vibrator/VibratorManagerService$ExternalVibrationHolder> > 1,
11 = getfield < Application, Lcom/android/server/vibrator/VibratorManagerService$ExternalVibrationHolder, stats, <Application,Lcom/android/server/vibrator/VibrationStats> > 10,
invokevirtual < Application, Lcom/android/server/vibrator/VibratorManagerService, setExternalControl(ZLcom/android/server/vibrator/VibrationStats;)V > 1,8,11 @26 exception:12,
16 = getfield < Application, Lcom/android/server/vibrator/VibratorManagerService, mCurrentExternalVibration, <Application,Lcom/android/server/vibrator/VibratorManagerService$ExternalVibrationHolder> > 1,
invokevirtual < Application, Lcom/android/server/vibrator/VibratorManagerService, endVibrationAndWriteStatsLocked(Lcom/android/server/vibrator/VibratorManagerService$ExternalVibrationHolder;Lcom/android/server/vibrator/Vibration$EndInfo;)V > 1,16,2 @31 exception:17,
putfield 1.< Application, Lcom/android/server/vibrator/VibratorManagerService, mCurrentExternalVibration, <Application,Lcom/android/server/vibrator/VibratorManagerService$ExternalVibrationHolder> > = 8,
invokestatic < Application, Landroid/os/Trace, traceEnd(J)V > 4 @37 exception:24,
return,
invokestatic < Application, Landroid/os/Binder, restoreCallingIdentity(J)V > 15 @92 exception:57,
monitorexit 10,
invokestatic < Application, Landroid/os/Trace, traceEnd(J)V > 5 @96 exception:75,
return,","depth : 0
-----
depth : 1
-----
depth : 1
-----
depth : 1
-----
depth : 1
-----
depth : 1
-----
depth : 1
-----
depth : 1
-----
depth : 1
-----
depth : 1
-----
depth : 1
-----
","public void cancelVibrate(int p1, IBinder p2){
	Vibration$EndInfo v3 = new Vibration$EndInfo(Vibration$Status.CANCELLED_BY_USER);
	long v5 = Binder.clearCallingIdentity();
	if (this.mNextVibration == 0) {
		Vibration v6 = this.mVibration;
		if (Vibration.token != p2) {
			boolean v8 = VibratorManagerService.shouldCancelVibration(Vibration.attrs, p1);
			if (v8 == 0) {
				boolean v7 = ;
				if (v7 == 0) {
					if (this.mNextVibration == 0) {
						Vibration v10 = this.mNextVibration.getVibration();
						VibratorManagerService.endVibrationLocked(v10, v3, 1);
						this.mNextVibration = 0;
						if (this.mCurrentVibration == 0) {
							Vibration v12 = this.mVibration;
							if (Vibration.token != p2) {
								boolean v14 = VibratorManagerService.shouldCancelVibration(Vibration.attrs, p1);
								if (v14 == 0) {
									boolean v13 = ;
									if (v13 == 0) {
										if (Build.IS_DEBUGGABLE == 0) {
											VibrationStepConductor.expectIsVibrationThread(0);
											if (v3 == 0) {
												String v17 = Vibration$EndInfo.status.name();
												boolean v18 = v17.startsWith(""CANCEL"");
												if (v18 != 0) {
													Vibration$EndInfo v26 = new Vibration$EndInfo(Vibration$Status.CANCELLED_BY_UNKNOWN_REASON);
													if (0 == 0) {
														if (this.mSignalCancelImmediate != 0) {
															if (this.mSignalCancel == 0) {
																this.mSignalCancelImmediate = (0 | this.mSignalCancelImmediate);
																if (this.mSignalCancel != 0) {
																	this.mSignalCancel = ;
																	this.mLock.notify();
																	if (this.mCurrentExternalVibration == 0) {
																		VibrationAttributes$Builder v30 = new VibrationAttributes$Builder(this.mAttrs);
																		VibrationAttributes v32 = v30.build();
																		VibrationAttributes v29 = v32;
																		int v34 = v29.getUsage();
																		if (v34 != 0) {
																			int v35 = v29.getUsage();
																			int v36 = v29.getUsage();
																			if ((v35 & p1) != v36) {
																				boolean v33 = ;
																				if (v33 == 0) {
																					boolean v38 = this.externalVibration.mute();
																					Trace.traceBegin(8388608, ""endExternalVibrateLocked"");
																					if (this.mCurrentExternalVibration != 0) {
																						this.mCurrentExternalVibration.unlinkToDeath();
																						if (0 != 0) {
																							VibratorManagerService.setExternalControl(0, VibratorManagerService$ExternalVibrationHolder.stats);
																							VibratorManagerService.endVibrationAndWriteStatsLocked(this.mCurrentExternalVibration, v3);
																							this.mCurrentExternalVibration = 0;
																							Trace.traceEnd(8388608);
																							Binder.restoreCallingIdentity(v5);
																							Trace.traceEnd(8388608);
																							return;
																						}
																					}
																				}
																			}
																		}
																	}
																}
															}
														}
													}
												}
											}
										}
									}
								}
							}
						}
					}
				}
			}
		}
	}
}
","NORMAL"
"Lcom/android/server/vibrator/VibratorManagerService","cancelVibrate(ILandroid/os/IBinder;)V","1","invokestatic < Application, Landroid/os/Trace, traceBegin(JLjava/lang/String;)V > 5,4 @5 exception:6,
7 = getfield < Application, Lcom/android/server/vibrator/VibratorManagerService, mContext, <Application,Landroid/content/Context> > 1,
invokevirtual < Application, Landroid/content/Context, enforceCallingOrSelfPermission(Ljava/lang/String;Ljava/lang/String;)V > 7,8,4 @14 exception:9,
10 = getfield < Application, Lcom/android/server/vibrator/VibratorManagerService, mLock, <Application,Ljava/lang/Object> > 1,
monitorenter 10,
11 = new <Application,Lcom/android/server/vibrator/Vibration$EndInfo>@20,
12 = getstatic < Application, Lcom/android/server/vibrator/Vibration$Status, CANCELLED_BY_USER, <Application,Lcom/android/server/vibrator/Vibration$Status> >,
invokespecial < Application, Lcom/android/server/vibrator/Vibration$EndInfo, <init>(Lcom/android/server/vibrator/Vibration$Status;)V > 11,12 @24 exception:13,
15 = invokestatic < Application, Landroid/os/Binder, clearCallingIdentity()J > @27 exception:14,
16 = getfield < Application, Lcom/android/server/vibrator/VibratorManagerService, mNextVibration, <Application,Lcom/android/server/vibrator/VibrationStepConductor> > 1,
conditional branch(eq, to iindex=-1) 16,17,
19 = invokevirtual < Application, Lcom/android/server/vibrator/VibrationStepConductor, getVibration()Lcom/android/server/vibrator/Vibration; > 16 @35 exception:18,
2 = getfield < Application, Lcom/android/server/vibrator/VibrationStepConductor, mVibration, <Application,Lcom/android/server/vibrator/Vibration> > 1,
return 2,
21 = invokevirtual < Application, Lcom/android/server/vibrator/VibratorManagerService, shouldCancelVibration(Lcom/android/server/vibrator/Vibration;ILandroid/os/IBinder;)Z > 1,19,2,3 @39 exception:20,
5 = getfield < Application, Lcom/android/server/vibrator/Vibration, token, <Application,Landroid/os/IBinder> > 2,
conditional branch(ne, to iindex=-1) 5,4,
6 = getfield < Application, Lcom/android/server/vibrator/Vibration, attrs, <Application,Landroid/os/VibrationAttributes> > 2,
8 = invokevirtual < Application, Lcom/android/server/vibrator/VibratorManagerService, shouldCancelVibration(Landroid/os/VibrationAttributes;I)Z > 1,6,3 @6 exception:7,
conditional branch(eq, to iindex=-1) 8,9,
goto (from iindex= 7 to iindex = 2),
13 = phi  12,9,
return 13,
conditional branch(eq, to iindex=-1) 21,17,
invokevirtual < Application, Lcom/android/server/vibrator/VibratorManagerService, clearNextVibrationLocked(Lcom/android/server/vibrator/Vibration$EndInfo;)V > 1,11 @45 exception:22,
3 = getfield < Application, Lcom/android/server/vibrator/VibratorManagerService, mNextVibration, <Application,Lcom/android/server/vibrator/VibrationStepConductor> > 1,
conditional branch(eq, to iindex=-1) 3,4,
6 = invokevirtual < Application, Lcom/android/server/vibrator/VibrationStepConductor, getVibration()Lcom/android/server/vibrator/Vibration; > 3 @4 exception:5,
invokevirtual < Application, Lcom/android/server/vibrator/VibratorManagerService, endVibrationLocked(Lcom/android/server/vibrator/Vibration;Lcom/android/server/vibrator/Vibration$EndInfo;Z)V > 1,6,2,7 @9 exception:8,
putfield 1.< Application, Lcom/android/server/vibrator/VibratorManagerService, mNextVibration, <Application,Lcom/android/server/vibrator/VibrationStepConductor> > = 4,
return,
26 = getfield < Application, Lcom/android/server/vibrator/VibratorManagerService, mCurrentVibration, <Application,Lcom/android/server/vibrator/VibrationStepConductor> > 1,
conditional branch(eq, to iindex=-1) 26,17,
28 = invokevirtual < Application, Lcom/android/server/vibrator/VibrationStepConductor, getVibration()Lcom/android/server/vibrator/Vibration; > 26 @53 exception:27,
2 = getfield < Application, Lcom/android/server/vibrator/VibrationStepConductor, mVibration, <Application,Lcom/android/server/vibrator/Vibration> > 1,
return 2,
30 = invokevirtual < Application, Lcom/android/server/vibrator/VibratorManagerService, shouldCancelVibration(Lcom/android/server/vibrator/Vibration;ILandroid/os/IBinder;)Z > 1,28,2,3 @57 exception:29,
5 = getfield < Application, Lcom/android/server/vibrator/Vibration, token, <Application,Landroid/os/IBinder> > 2,
conditional branch(ne, to iindex=-1) 5,4,
6 = getfield < Application, Lcom/android/server/vibrator/Vibration, attrs, <Application,Landroid/os/VibrationAttributes> > 2,
8 = invokevirtual < Application, Lcom/android/server/vibrator/VibratorManagerService, shouldCancelVibration(Landroid/os/VibrationAttributes;I)Z > 1,6,3 @6 exception:7,
conditional branch(eq, to iindex=-1) 8,9,
goto (from iindex= 7 to iindex = 2),
13 = phi  12,9,
return 13,
conditional branch(eq, to iindex=-1) 30,17,
31 = getfield < Application, Lcom/android/server/vibrator/VibratorManagerService, mCurrentVibration, <Application,Lcom/android/server/vibrator/VibrationStepConductor> > 1,
invokevirtual < Application, Lcom/android/server/vibrator/VibrationStepConductor, notifyCancelled(Lcom/android/server/vibrator/Vibration$EndInfo;Z)V > 31,11,17 @65 exception:32,
4 = getstatic < Application, Landroid/os/Build, IS_DEBUGGABLE, <Primordial,Z> >,
conditional branch(eq, to iindex=-1) 4,5,
invokestatic < Application, Lcom/android/server/vibrator/VibrationStepConductor, expectIsVibrationThread(Z)V > 5 @5 exception:6,
conditional branch(eq, to iindex=-1) 2,5,
8 = getfield < Application, Lcom/android/server/vibrator/Vibration$EndInfo, status, <Application,Lcom/android/server/vibrator/Vibration$Status> > 2,
10 = invokevirtual < Application, Ljava/lang/Enum, name()Ljava/lang/String; > 8 @12 exception:9,
13 = invokevirtual < Application, Ljava/lang/String, startsWith(Ljava/lang/String;)Z > 10,11 @18 exception:12,
conditional branch(ne, to iindex=-1) 13,5,
17 = new <Application,Ljava/lang/StringBuilder>@26,
invokespecial < Application, Ljava/lang/StringBuilder, <init>()V > 17 @28 exception:18,
21 = invokevirtual < Application, Ljava/lang/StringBuilder, append(Ljava/lang/String;)Ljava/lang/StringBuilder; > 17,19 @33 exception:20,
23 = invokevirtual < Application, Ljava/lang/StringBuilder, append(Ljava/lang/Object;)Ljava/lang/StringBuilder; > 17,2 @36 exception:22,
26 = invokevirtual < Application, Ljava/lang/StringBuilder, append(Ljava/lang/String;)Ljava/lang/StringBuilder; > 17,24 @41 exception:25,
28 = invokevirtual < Application, Ljava/lang/StringBuilder, toString()Ljava/lang/String; > 17 @44 exception:27,
30 = invokestatic < Application, Landroid/util/Slog, w(Ljava/lang/String;Ljava/lang/String;)I > 16,28 @48 exception:29,
31 = new <Application,Lcom/android/server/vibrator/Vibration$EndInfo>@51,
32 = getstatic < Application, Lcom/android/server/vibrator/Vibration$Status, CANCELLED_BY_UNKNOWN_REASON, <Application,Lcom/android/server/vibrator/Vibration$Status> >,
invokespecial < Application, Lcom/android/server/vibrator/Vibration$EndInfo, <init>(Lcom/android/server/vibrator/Vibration$Status;)V > 31,32 @55 exception:33,
36 = phi  2,31,
39 = getfield < Application, Lcom/android/server/vibrator/VibrationStepConductor, mLock, <Application,Ljava/lang/Object> > 1,
monitorenter 39,
conditional branch(eq, to iindex=-1) 3,5,
40 = getfield < Application, Lcom/android/server/vibrator/VibrationStepConductor, mSignalCancelImmediate, <Primordial,Z> > 1,
conditional branch(ne, to iindex=-1) 40,5,
42 = getfield < Application, Lcom/android/server/vibrator/VibrationStepConductor, mSignalCancel, <Application,Lcom/android/server/vibrator/Vibration$EndInfo> > 1,
conditional branch(eq, to iindex=-1) 42,5,
43 = getfield < Application, Lcom/android/server/vibrator/VibrationStepConductor, mSignalCancelImmediate, <Primordial,Z> > 1,
44 = binaryop(or) 3 , 43,
putfield 1.< Application, Lcom/android/server/vibrator/VibrationStepConductor, mSignalCancelImmediate, <Primordial,Z> > = 44,
conditional branch(ne, to iindex=-1) 42,5,
putfield 1.< Application, Lcom/android/server/vibrator/VibrationStepConductor, mSignalCancel, <Application,Lcom/android/server/vibrator/Vibration$EndInfo> > = 36,
45 = getfield < Application, Lcom/android/server/vibrator/VibrationStepConductor, mLock, <Application,Ljava/lang/Object> > 1,
invokevirtual < Application, Ljava/lang/Object, notify()V > 45 @84 exception:46,
monitorexit 39,
return,
37 = getfield < Application, Lcom/android/server/vibrator/VibratorManagerService, mCurrentExternalVibration, <Application,Lcom/android/server/vibrator/VibratorManagerService$ExternalVibrationHolder> > 1,
conditional branch(eq, to iindex=-1) 37,17,
38 = getfield < Application, Lcom/android/server/vibrator/VibratorManagerService$ExternalVibrationHolder, externalVibration, <Application,Landroid/os/ExternalVibration> > 37,
40 = invokevirtual < Application, Landroid/os/ExternalVibration, getVibrationAttributes()Landroid/os/VibrationAttributes; > 38 @74 exception:39,
2 = new <Application,Landroid/os/VibrationAttributes$Builder>@0,
3 = getfield < Application, Landroid/os/ExternalVibration, mAttrs, <Application,Landroid/media/AudioAttributes> > 1,
invokespecial < Application, Landroid/os/VibrationAttributes$Builder, <init>(Landroid/media/AudioAttributes;)V > 2,3 @4 exception:4,
6 = invokevirtual < Application, Landroid/os/VibrationAttributes$Builder, build()Landroid/os/VibrationAttributes; > 2 @7 exception:5,
return 6,
42 = invokevirtual < Application, Lcom/android/server/vibrator/VibratorManagerService, shouldCancelVibration(Landroid/os/VibrationAttributes;I)Z > 1,40,2 @78 exception:41,
5 = invokevirtual < Application, Landroid/os/VibrationAttributes, getUsage()I > 2 @0 exception:4,
conditional branch(ne, to iindex=-1) 5,7,
9 = invokevirtual < Application, Landroid/os/VibrationAttributes, getUsage()I > 2 @16 exception:8,
10 = binaryop(and) 9 , 3,
12 = invokevirtual < Application, Landroid/os/VibrationAttributes, getUsage()I > 2 @21 exception:11,
conditional branch(ne, to iindex=-1) 10,12,
13 = phi  6,7,
return 13,
conditional branch(eq, to iindex=-1) 42,17,
43 = getfield < Application, Lcom/android/server/vibrator/VibratorManagerService, mCurrentExternalVibration, <Application,Lcom/android/server/vibrator/VibratorManagerService$ExternalVibrationHolder> > 1,
invokevirtual < Application, Lcom/android/server/vibrator/VibratorManagerService$ExternalVibrationHolder, mute()V > 43 @86 exception:44,
2 = getfield < Application, Lcom/android/server/vibrator/VibratorManagerService$ExternalVibrationHolder, externalVibration, <Application,Landroid/os/ExternalVibration> > 1,
4 = invokevirtual < Application, Landroid/os/ExternalVibration, mute()Z > 2 @2 exception:3,
return,
invokevirtual < Application, Lcom/android/server/vibrator/VibratorManagerService, endExternalVibrateLocked(Lcom/android/server/vibrator/Vibration$EndInfo;Z)V > 1,11,17 @89 exception:45,
invokestatic < Application, Landroid/os/Trace, traceBegin(JLjava/lang/String;)V > 4,5 @5 exception:6,
7 = getfield < Application, Lcom/android/server/vibrator/VibratorManagerService, mCurrentExternalVibration, <Application,Lcom/android/server/vibrator/VibratorManagerService$ExternalVibrationHolder> > 1,
conditional branch(ne, to iindex=-1) 7,8,
invokevirtual < Application, Lcom/android/server/vibrator/VibratorManagerService$ExternalVibrationHolder, unlinkToDeath()V > 7 @16 exception:9,
conditional branch(ne, to iindex=-1) 3,8,
10 = getfield < Application, Lcom/android/server/vibrator/VibratorManagerService, mCurrentExternalVibration, <Application,Lcom/android/server/vibrator/VibratorManagerService$ExternalVibrationHolder> > 1,
11 = getfield < Application, Lcom/android/server/vibrator/VibratorManagerService$ExternalVibrationHolder, stats, <Application,Lcom/android/server/vibrator/VibrationStats> > 10,
invokevirtual < Application, Lcom/android/server/vibrator/VibratorManagerService, setExternalControl(ZLcom/android/server/vibrator/VibrationStats;)V > 1,8,11 @26 exception:12,
16 = getfield < Application, Lcom/android/server/vibrator/VibratorManagerService, mCurrentExternalVibration, <Application,Lcom/android/server/vibrator/VibratorManagerService$ExternalVibrationHolder> > 1,
invokevirtual < Application, Lcom/android/server/vibrator/VibratorManagerService, endVibrationAndWriteStatsLocked(Lcom/android/server/vibrator/VibratorManagerService$ExternalVibrationHolder;Lcom/android/server/vibrator/Vibration$EndInfo;)V > 1,16,2 @31 exception:17,
putfield 1.< Application, Lcom/android/server/vibrator/VibratorManagerService, mCurrentExternalVibration, <Application,Lcom/android/server/vibrator/VibratorManagerService$ExternalVibrationHolder> > = 8,
invokestatic < Application, Landroid/os/Trace, traceEnd(J)V > 4 @37 exception:24,
return,
invokestatic < Application, Landroid/os/Binder, restoreCallingIdentity(J)V > 15 @92 exception:57,
monitorexit 10,
invokestatic < Application, Landroid/os/Trace, traceEnd(J)V > 5 @96 exception:75,
return,","depth : 0
-----
depth : 1
-----
depth : 1
-----
depth : 1
-----
depth : 1
-----
depth : 1
-----
depth : 1
-----
depth : 1
-----
depth : 1
-----
depth : 1
-----
depth : 1
-----
","public void cancelVibrate(int p1, IBinder p2){
	Vibration$EndInfo v3 = new Vibration$EndInfo(Vibration$Status.CANCELLED_BY_USER);
	long v5 = Binder.clearCallingIdentity();
	if (this.mNextVibration == 0) {
		Vibration v6 = this.mVibration;
		if (Vibration.token != p2) {
			boolean v8 = VibratorManagerService.shouldCancelVibration(Vibration.attrs, p1);
			if (v8 == 0) {
				boolean v7 = ;
				if (v7 == 0) {
					if (this.mNextVibration == 0) {
						Vibration v10 = this.mNextVibration.getVibration();
						VibratorManagerService.endVibrationLocked(v10, v3, 1);
						this.mNextVibration = 0;
						if (this.mCurrentVibration == 0) {
							Vibration v12 = this.mVibration;
							if (Vibration.token != p2) {
								boolean v14 = VibratorManagerService.shouldCancelVibration(Vibration.attrs, p1);
								if (v14 == 0) {
									boolean v13 = ;
									if (v13 == 0) {
										if (Build.IS_DEBUGGABLE == 0) {
											VibrationStepConductor.expectIsVibrationThread(0);
											if (v3 == 0) {
												String v17 = Vibration$EndInfo.status.name();
												boolean v18 = v17.startsWith(""CANCEL"");
												if (v18 != 0) {
													Vibration$EndInfo v26 = new Vibration$EndInfo(Vibration$Status.CANCELLED_BY_UNKNOWN_REASON);
													if (0 == 0) {
														if (this.mSignalCancelImmediate != 0) {
															if (this.mSignalCancel == 0) {
																this.mSignalCancelImmediate = (0 | this.mSignalCancelImmediate);
																if (this.mSignalCancel != 0) {
																	this.mSignalCancel = ;
																	this.mLock.notify();
																	if (this.mCurrentExternalVibration == 0) {
																		VibrationAttributes$Builder v30 = new VibrationAttributes$Builder(this.mAttrs);
																		VibrationAttributes v32 = v30.build();
																		VibrationAttributes v29 = v32;
																		int v34 = v29.getUsage();
																		if (v34 != 0) {
																			int v35 = v29.getUsage();
																			int v36 = v29.getUsage();
																			if ((v35 & p1) != v36) {
																				boolean v33 = ;
																				if (v33 == 0) {
																					boolean v38 = this.externalVibration.mute();
																					Trace.traceBegin(8388608, ""endExternalVibrateLocked"");
																					if (this.mCurrentExternalVibration != 0) {
																						this.mCurrentExternalVibration.unlinkToDeath();
																						if (0 != 0) {
																							VibratorManagerService.setExternalControl(0, VibratorManagerService$ExternalVibrationHolder.stats);
																							VibratorManagerService.endVibrationAndWriteStatsLocked(this.mCurrentExternalVibration, v3);
																							this.mCurrentExternalVibration = 0;
																							Trace.traceEnd(8388608);
																							Binder.restoreCallingIdentity(v5);
																							Trace.traceEnd(8388608);
																							return;
																						}
																					}
																				}
																			}
																		}
																	}
																}
															}
														}
													}
												}
											}
										}
									}
								}
							}
						}
					}
				}
			}
		}
	}
}
","NORMAL"
"Lcom/android/server/vibrator/VibratorManagerService","cancelVibrate(ILandroid/os/IBinder;)V","2","invokestatic < Application, Landroid/os/Trace, traceBegin(JLjava/lang/String;)V > 5,4 @5 exception:6,
7 = getfield < Application, Lcom/android/server/vibrator/VibratorManagerService, mContext, <Application,Landroid/content/Context> > 1,
invokevirtual < Application, Landroid/content/Context, enforceCallingOrSelfPermission(Ljava/lang/String;Ljava/lang/String;)V > 7,8,4 @14 exception:9,
10 = getfield < Application, Lcom/android/server/vibrator/VibratorManagerService, mLock, <Application,Ljava/lang/Object> > 1,
monitorenter 10,
11 = new <Application,Lcom/android/server/vibrator/Vibration$EndInfo>@20,
12 = getstatic < Application, Lcom/android/server/vibrator/Vibration$Status, CANCELLED_BY_USER, <Application,Lcom/android/server/vibrator/Vibration$Status> >,
invokespecial < Application, Lcom/android/server/vibrator/Vibration$EndInfo, <init>(Lcom/android/server/vibrator/Vibration$Status;)V > 11,12 @24 exception:13,
15 = invokestatic < Application, Landroid/os/Binder, clearCallingIdentity()J > @27 exception:14,
16 = getfield < Application, Lcom/android/server/vibrator/VibratorManagerService, mNextVibration, <Application,Lcom/android/server/vibrator/VibrationStepConductor> > 1,
conditional branch(eq, to iindex=-1) 16,17,
19 = invokevirtual < Application, Lcom/android/server/vibrator/VibrationStepConductor, getVibration()Lcom/android/server/vibrator/Vibration; > 16 @35 exception:18,
2 = getfield < Application, Lcom/android/server/vibrator/VibrationStepConductor, mVibration, <Application,Lcom/android/server/vibrator/Vibration> > 1,
return 2,
21 = invokevirtual < Application, Lcom/android/server/vibrator/VibratorManagerService, shouldCancelVibration(Lcom/android/server/vibrator/Vibration;ILandroid/os/IBinder;)Z > 1,19,2,3 @39 exception:20,
5 = getfield < Application, Lcom/android/server/vibrator/Vibration, token, <Application,Landroid/os/IBinder> > 2,
conditional branch(ne, to iindex=-1) 5,4,
6 = getfield < Application, Lcom/android/server/vibrator/Vibration, attrs, <Application,Landroid/os/VibrationAttributes> > 2,
8 = invokevirtual < Application, Lcom/android/server/vibrator/VibratorManagerService, shouldCancelVibration(Landroid/os/VibrationAttributes;I)Z > 1,6,3 @6 exception:7,
5 = invokevirtual < Application, Landroid/os/VibrationAttributes, getUsage()I > 2 @0 exception:4,
conditional branch(ne, to iindex=-1) 5,7,
9 = invokevirtual < Application, Landroid/os/VibrationAttributes, getUsage()I > 2 @16 exception:8,
10 = binaryop(and) 9 , 3,
12 = invokevirtual < Application, Landroid/os/VibrationAttributes, getUsage()I > 2 @21 exception:11,
conditional branch(ne, to iindex=-1) 10,12,
goto (from iindex= 17 to iindex = 2),
13 = phi  6,7,
return 13,
conditional branch(eq, to iindex=-1) 8,9,
goto (from iindex= 7 to iindex = 2),
13 = phi  12,9,
return 13,
conditional branch(eq, to iindex=-1) 21,17,
invokevirtual < Application, Lcom/android/server/vibrator/VibratorManagerService, clearNextVibrationLocked(Lcom/android/server/vibrator/Vibration$EndInfo;)V > 1,11 @45 exception:22,
3 = getfield < Application, Lcom/android/server/vibrator/VibratorManagerService, mNextVibration, <Application,Lcom/android/server/vibrator/VibrationStepConductor> > 1,
conditional branch(eq, to iindex=-1) 3,4,
6 = invokevirtual < Application, Lcom/android/server/vibrator/VibrationStepConductor, getVibration()Lcom/android/server/vibrator/Vibration; > 3 @4 exception:5,
2 = getfield < Application, Lcom/android/server/vibrator/VibrationStepConductor, mVibration, <Application,Lcom/android/server/vibrator/Vibration> > 1,
return 2,
invokevirtual < Application, Lcom/android/server/vibrator/VibratorManagerService, endVibrationLocked(Lcom/android/server/vibrator/Vibration;Lcom/android/server/vibrator/Vibration$EndInfo;Z)V > 1,6,2,7 @9 exception:8,
invokevirtual < Application, Lcom/android/server/vibrator/Vibration, end(Lcom/android/server/vibrator/Vibration$EndInfo;)V > 2,3 @0 exception:5,
6 = getfield < Application, Lcom/android/server/vibrator/Vibration, uid, <Primordial,I> > 2,
7 = getfield < Application, Lcom/android/server/vibrator/Vibration, attrs, <Application,Landroid/os/VibrationAttributes> > 2,
8 = getfield < Application, Lcom/android/server/vibrator/Vibration$EndInfo, status, <Application,Lcom/android/server/vibrator/Vibration$Status> > 3,
invokevirtual < Application, Lcom/android/server/vibrator/VibratorManagerService, logVibrationStatus(ILandroid/os/VibrationAttributes;Lcom/android/server/vibrator/Vibration$Status;)V > 1,6,7,8 @9 exception:9,
10 = getfield < Application, Lcom/android/server/vibrator/VibratorManagerService, mVibratorManagerRecords, <Application,Lcom/android/server/vibrator/VibratorManagerService$VibratorManagerRecords> > 1,
invokevirtual < Application, Lcom/android/server/vibrator/VibratorManagerService$VibratorManagerRecords, record(Lcom/android/server/vibrator/Vibration;)V > 10,2 @14 exception:11,
conditional branch(eq, to iindex=-1) 4,12,
13 = getfield < Application, Lcom/android/server/vibrator/VibratorManagerService, mFrameworkStatsLogger, <Application,Lcom/android/server/vibrator/VibratorFrameworkStatsLogger> > 1,
15 = invokestatic < Application, Landroid/os/SystemClock, uptimeMillis()J > @21 exception:14,
17 = invokevirtual < Application, Lcom/android/server/vibrator/Vibration, getStatsInfo(J)Lcom/android/server/vibrator/VibrationStats$StatsInfo; > 2,15 @25 exception:16,
invokevirtual < Application, Lcom/android/server/vibrator/VibratorFrameworkStatsLogger, writeVibrationReportedAsync(Lcom/android/server/vibrator/VibrationStats$StatsInfo;)V > 13,17 @29 exception:18,
return,
putfield 1.< Application, Lcom/android/server/vibrator/VibratorManagerService, mNextVibration, <Application,Lcom/android/server/vibrator/VibrationStepConductor> > = 4,
return,
26 = getfield < Application, Lcom/android/server/vibrator/VibratorManagerService, mCurrentVibration, <Application,Lcom/android/server/vibrator/VibrationStepConductor> > 1,
conditional branch(eq, to iindex=-1) 26,17,
28 = invokevirtual < Application, Lcom/android/server/vibrator/VibrationStepConductor, getVibration()Lcom/android/server/vibrator/Vibration; > 26 @53 exception:27,
30 = invokevirtual < Application, Lcom/android/server/vibrator/VibratorManagerService, shouldCancelVibration(Lcom/android/server/vibrator/Vibration;ILandroid/os/IBinder;)Z > 1,28,2,3 @57 exception:29,
5 = getfield < Application, Lcom/android/server/vibrator/Vibration, token, <Application,Landroid/os/IBinder> > 2,
conditional branch(ne, to iindex=-1) 5,4,
6 = getfield < Application, Lcom/android/server/vibrator/Vibration, attrs, <Application,Landroid/os/VibrationAttributes> > 2,
8 = invokevirtual < Application, Lcom/android/server/vibrator/VibratorManagerService, shouldCancelVibration(Landroid/os/VibrationAttributes;I)Z > 1,6,3 @6 exception:7,
5 = invokevirtual < Application, Landroid/os/VibrationAttributes, getUsage()I > 2 @0 exception:4,
conditional branch(ne, to iindex=-1) 5,7,
9 = invokevirtual < Application, Landroid/os/VibrationAttributes, getUsage()I > 2 @16 exception:8,
10 = binaryop(and) 9 , 3,
12 = invokevirtual < Application, Landroid/os/VibrationAttributes, getUsage()I > 2 @21 exception:11,
conditional branch(ne, to iindex=-1) 10,12,
goto (from iindex= 17 to iindex = 2),
13 = phi  6,7,
return 13,
conditional branch(eq, to iindex=-1) 8,9,
goto (from iindex= 7 to iindex = 2),
13 = phi  12,9,
return 13,
conditional branch(eq, to iindex=-1) 30,17,
31 = getfield < Application, Lcom/android/server/vibrator/VibratorManagerService, mCurrentVibration, <Application,Lcom/android/server/vibrator/VibrationStepConductor> > 1,
invokevirtual < Application, Lcom/android/server/vibrator/VibrationStepConductor, notifyCancelled(Lcom/android/server/vibrator/Vibration$EndInfo;Z)V > 31,11,17 @65 exception:32,
4 = getstatic < Application, Landroid/os/Build, IS_DEBUGGABLE, <Primordial,Z> >,
conditional branch(eq, to iindex=-1) 4,5,
invokestatic < Application, Lcom/android/server/vibrator/VibrationStepConductor, expectIsVibrationThread(Z)V > 5 @5 exception:6,
3 = invokestatic < Application, Ljava/lang/Thread, currentThread()Ljava/lang/Thread; > @0 exception:2,
4 = instanceof 3 <Application,Lcom/android/server/vibrator/VibrationThread>,
conditional branch(eq, to iindex=-1) 4,1,
5 = new <Application,Ljava/lang/StringBuilder>@8,
invokespecial < Application, Ljava/lang/StringBuilder, <init>()V > 5 @10 exception:6,
9 = invokevirtual < Application, Ljava/lang/StringBuilder, append(Ljava/lang/String;)Ljava/lang/StringBuilder; > 5,7 @15 exception:8,
11 = invokevirtual < Application, Ljava/lang/StringBuilder, append(Z)Ljava/lang/StringBuilder; > 5,1 @18 exception:10,
13 = invokevirtual < Application, Ljava/lang/StringBuilder, toString()Ljava/lang/String; > 5 @21 exception:12,
16 = invokestatic < Application, Landroid/util/Slog, wtfStack(Ljava/lang/String;Ljava/lang/String;)I > 14,13 @27 exception:15,
return,
conditional branch(eq, to iindex=-1) 2,5,
8 = getfield < Application, Lcom/android/server/vibrator/Vibration$EndInfo, status, <Application,Lcom/android/server/vibrator/Vibration$Status> > 2,
10 = invokevirtual < Application, Ljava/lang/Enum, name()Ljava/lang/String; > 8 @12 exception:9,
13 = invokevirtual < Application, Ljava/lang/String, startsWith(Ljava/lang/String;)Z > 10,11 @18 exception:12,
conditional branch(ne, to iindex=-1) 13,5,
17 = new <Application,Ljava/lang/StringBuilder>@26,
invokespecial < Application, Ljava/lang/StringBuilder, <init>()V > 17 @28 exception:18,
21 = invokevirtual < Application, Ljava/lang/StringBuilder, append(Ljava/lang/String;)Ljava/lang/StringBuilder; > 17,19 @33 exception:20,
23 = invokevirtual < Application, Ljava/lang/StringBuilder, append(Ljava/lang/Object;)Ljava/lang/StringBuilder; > 17,2 @36 exception:22,
26 = invokevirtual < Application, Ljava/lang/StringBuilder, append(Ljava/lang/String;)Ljava/lang/StringBuilder; > 17,24 @41 exception:25,
28 = invokevirtual < Application, Ljava/lang/StringBuilder, toString()Ljava/lang/String; > 17 @44 exception:27,
30 = invokestatic < Application, Landroid/util/Slog, w(Ljava/lang/String;Ljava/lang/String;)I > 16,28 @48 exception:29,
31 = new <Application,Lcom/android/server/vibrator/Vibration$EndInfo>@51,
32 = getstatic < Application, Lcom/android/server/vibrator/Vibration$Status, CANCELLED_BY_UNKNOWN_REASON, <Application,Lcom/android/server/vibrator/Vibration$Status> >,
invokespecial < Application, Lcom/android/server/vibrator/Vibration$EndInfo, <init>(Lcom/android/server/vibrator/Vibration$Status;)V > 31,32 @55 exception:33,
36 = phi  2,31,
39 = getfield < Application, Lcom/android/server/vibrator/VibrationStepConductor, mLock, <Application,Ljava/lang/Object> > 1,
monitorenter 39,
conditional branch(eq, to iindex=-1) 3,5,
40 = getfield < Application, Lcom/android/server/vibrator/VibrationStepConductor, mSignalCancelImmediate, <Primordial,Z> > 1,
conditional branch(ne, to iindex=-1) 40,5,
42 = getfield < Application, Lcom/android/server/vibrator/VibrationStepConductor, mSignalCancel, <Application,Lcom/android/server/vibrator/Vibration$EndInfo> > 1,
conditional branch(eq, to iindex=-1) 42,5,
43 = getfield < Application, Lcom/android/server/vibrator/VibrationStepConductor, mSignalCancelImmediate, <Primordial,Z> > 1,
44 = binaryop(or) 3 , 43,
putfield 1.< Application, Lcom/android/server/vibrator/VibrationStepConductor, mSignalCancelImmediate, <Primordial,Z> > = 44,
conditional branch(ne, to iindex=-1) 42,5,
putfield 1.< Application, Lcom/android/server/vibrator/VibrationStepConductor, mSignalCancel, <Application,Lcom/android/server/vibrator/Vibration$EndInfo> > = 36,
45 = getfield < Application, Lcom/android/server/vibrator/VibrationStepConductor, mLock, <Application,Ljava/lang/Object> > 1,
invokevirtual < Application, Ljava/lang/Object, notify()V > 45 @84 exception:46,
monitorexit 39,
return,
37 = getfield < Application, Lcom/android/server/vibrator/VibratorManagerService, mCurrentExternalVibration, <Application,Lcom/android/server/vibrator/VibratorManagerService$ExternalVibrationHolder> > 1,
conditional branch(eq, to iindex=-1) 37,17,
38 = getfield < Application, Lcom/android/server/vibrator/VibratorManagerService$ExternalVibrationHolder, externalVibration, <Application,Landroid/os/ExternalVibration> > 37,
40 = invokevirtual < Application, Landroid/os/ExternalVibration, getVibrationAttributes()Landroid/os/VibrationAttributes; > 38 @74 exception:39,
2 = new <Application,Landroid/os/VibrationAttributes$Builder>@0,
3 = getfield < Application, Landroid/os/ExternalVibration, mAttrs, <Application,Landroid/media/AudioAttributes> > 1,
invokespecial < Application, Landroid/os/VibrationAttributes$Builder, <init>(Landroid/media/AudioAttributes;)V > 2,3 @4 exception:4,
6 = invokevirtual < Application, Landroid/os/VibrationAttributes$Builder, build()Landroid/os/VibrationAttributes; > 2 @7 exception:5,
2 = new <Application,Landroid/os/VibrationAttributes>@0,
3 = getfield < Application, Landroid/os/VibrationAttributes$Builder, mUsage, <Primordial,I> > 1,
4 = getfield < Application, Landroid/os/VibrationAttributes$Builder, mOriginalAudioUsage, <Primordial,I> > 1,
5 = getfield < Application, Landroid/os/VibrationAttributes$Builder, mFlags, <Primordial,I> > 1,
invokespecial < Application, Landroid/os/VibrationAttributes, <init>(IIILandroid/os/VibrationAttributes-IA;)V > 2,3,4,5,6 @9 exception:7,
return 2,
return 6,
42 = invokevirtual < Application, Lcom/android/server/vibrator/VibratorManagerService, shouldCancelVibration(Landroid/os/VibrationAttributes;I)Z > 1,40,2 @78 exception:41,
5 = invokevirtual < Application, Landroid/os/VibrationAttributes, getUsage()I > 2 @0 exception:4,
2 = getfield < Application, Landroid/os/VibrationAttributes, mUsage, <Primordial,I> > 1,
return 2,
conditional branch(ne, to iindex=-1) 5,7,
9 = invokevirtual < Application, Landroid/os/VibrationAttributes, getUsage()I > 2 @16 exception:8,
2 = getfield < Application, Landroid/os/VibrationAttributes, mUsage, <Primordial,I> > 1,
return 2,
10 = binaryop(and) 9 , 3,
12 = invokevirtual < Application, Landroid/os/VibrationAttributes, getUsage()I > 2 @21 exception:11,
2 = getfield < Application, Landroid/os/VibrationAttributes, mUsage, <Primordial,I> > 1,
return 2,
conditional branch(ne, to iindex=-1) 10,12,
goto (from iindex= 17 to iindex = 2),
13 = phi  6,7,
return 13,
conditional branch(eq, to iindex=-1) 42,17,
43 = getfield < Application, Lcom/android/server/vibrator/VibratorManagerService, mCurrentExternalVibration, <Application,Lcom/android/server/vibrator/VibratorManagerService$ExternalVibrationHolder> > 1,
invokevirtual < Application, Lcom/android/server/vibrator/VibratorManagerService$ExternalVibrationHolder, mute()V > 43 @86 exception:44,
2 = getfield < Application, Lcom/android/server/vibrator/VibratorManagerService$ExternalVibrationHolder, externalVibration, <Application,Landroid/os/ExternalVibration> > 1,
4 = invokevirtual < Application, Landroid/os/ExternalVibration, mute()Z > 2 @2 exception:3,
2 = getfield < Application, Landroid/os/ExternalVibration, mController, <Application,Landroid/os/IExternalVibrationController> > 1,
4 = invokeinterface < Application, Landroid/os/IExternalVibrationController, mute()Z > 2 @2 exception:3,
5 = getCaughtException ,
6 = new <Application,Ljava/lang/StringBuilder>@9,
invokespecial < Application, Ljava/lang/StringBuilder, <init>()V > 6 @11 exception:7,
10 = invokevirtual < Application, Ljava/lang/StringBuilder, append(Ljava/lang/String;)Ljava/lang/StringBuilder; > 6,8 @16 exception:9,
12 = invokevirtual < Application, Ljava/lang/StringBuilder, append(Ljava/lang/Object;)Ljava/lang/StringBuilder; > 10,1 @20 exception:11,
14 = invokevirtual < Application, Ljava/lang/StringBuilder, toString()Ljava/lang/String; > 12 @24 exception:13,
17 = invokestatic < Application, Landroid/util/Slog, wtf(Ljava/lang/String;Ljava/lang/String;Ljava/lang/Throwable;)I > 15,14,5 @30 exception:16,
return 18,
return,
invokevirtual < Application, Lcom/android/server/vibrator/VibratorManagerService, endExternalVibrateLocked(Lcom/android/server/vibrator/Vibration$EndInfo;Z)V > 1,11,17 @89 exception:45,
invokestatic < Application, Landroid/os/Trace, traceBegin(JLjava/lang/String;)V > 4,5 @5 exception:6,
7 = getfield < Application, Lcom/android/server/vibrator/VibratorManagerService, mCurrentExternalVibration, <Application,Lcom/android/server/vibrator/VibratorManagerService$ExternalVibrationHolder> > 1,
conditional branch(ne, to iindex=-1) 7,8,
invokevirtual < Application, Lcom/android/server/vibrator/VibratorManagerService$ExternalVibrationHolder, unlinkToDeath()V > 7 @16 exception:9,
2 = getfield < Application, Lcom/android/server/vibrator/VibratorManagerService$ExternalVibrationHolder, externalVibration, <Application,Landroid/os/ExternalVibration> > 1,
invokevirtual < Application, Landroid/os/ExternalVibration, unlinkToDeath(Landroid/os/IBinder$DeathRecipient;)V > 2,1 @2 exception:3,
return,
conditional branch(ne, to iindex=-1) 3,8,
10 = getfield < Application, Lcom/android/server/vibrator/VibratorManagerService, mCurrentExternalVibration, <Application,Lcom/android/server/vibrator/VibratorManagerService$ExternalVibrationHolder> > 1,
11 = getfield < Application, Lcom/android/server/vibrator/VibratorManagerService$ExternalVibrationHolder, stats, <Application,Lcom/android/server/vibrator/VibrationStats> > 10,
invokevirtual < Application, Lcom/android/server/vibrator/VibratorManagerService, setExternalControl(ZLcom/android/server/vibrator/VibrationStats;)V > 1,8,11 @26 exception:12,
16 = phi  15,4,
5 = getfield < Application, Lcom/android/server/vibrator/VibratorManagerService, mVibrators, <Application,Landroid/util/SparseArray> > 1,
7 = invokevirtual < Application, Landroid/util/SparseArray, size()I > 5 @3 exception:6,
conditional branch(ge, to iindex=-1) 16,7,
return,
16 = getfield < Application, Lcom/android/server/vibrator/VibratorManagerService, mCurrentExternalVibration, <Application,Lcom/android/server/vibrator/VibratorManagerService$ExternalVibrationHolder> > 1,
invokevirtual < Application, Lcom/android/server/vibrator/VibratorManagerService, endVibrationAndWriteStatsLocked(Lcom/android/server/vibrator/VibratorManagerService$ExternalVibrationHolder;Lcom/android/server/vibrator/Vibration$EndInfo;)V > 1,16,2 @31 exception:17,
invokevirtual < Application, Lcom/android/server/vibrator/VibratorManagerService$ExternalVibrationHolder, end(Lcom/android/server/vibrator/Vibration$EndInfo;)V > 2,3 @0 exception:4,
5 = getfield < Application, Lcom/android/server/vibrator/VibratorManagerService$ExternalVibrationHolder, externalVibration, <Application,Landroid/os/ExternalVibration> > 2,
7 = invokevirtual < Application, Landroid/os/ExternalVibration, getUid()I > 5 @5 exception:6,
8 = getfield < Application, Lcom/android/server/vibrator/VibratorManagerService$ExternalVibrationHolder, externalVibration, <Application,Landroid/os/ExternalVibration> > 2,
10 = invokevirtual < Application, Landroid/os/ExternalVibration, getVibrationAttributes()Landroid/os/VibrationAttributes; > 8 @11 exception:9,
11 = getfield < Application, Lcom/android/server/vibrator/Vibration$EndInfo, status, <Application,Lcom/android/server/vibrator/Vibration$Status> > 3,
invokevirtual < Application, Lcom/android/server/vibrator/VibratorManagerService, logVibrationStatus(ILandroid/os/VibrationAttributes;Lcom/android/server/vibrator/Vibration$Status;)V > 1,7,10,11 @17 exception:12,
13 = getfield < Application, Lcom/android/server/vibrator/VibratorManagerService, mVibratorManagerRecords, <Application,Lcom/android/server/vibrator/VibratorManagerService$VibratorManagerRecords> > 1,
invokevirtual < Application, Lcom/android/server/vibrator/VibratorManagerService$VibratorManagerRecords, record(Lcom/android/server/vibrator/VibratorManagerService$ExternalVibrationHolder;)V > 13,2 @22 exception:14,
15 = getfield < Application, Lcom/android/server/vibrator/VibratorManagerService, mFrameworkStatsLogger, <Application,Lcom/android/server/vibrator/VibratorFrameworkStatsLogger> > 1,
17 = invokestatic < Application, Landroid/os/SystemClock, uptimeMillis()J > @27 exception:16,
19 = invokevirtual < Application, Lcom/android/server/vibrator/VibratorManagerService$ExternalVibrationHolder, getStatsInfo(J)Lcom/android/server/vibrator/VibrationStats$StatsInfo; > 2,17 @31 exception:18,
invokevirtual < Application, Lcom/android/server/vibrator/VibratorFrameworkStatsLogger, writeVibrationReportedAsync(Lcom/android/server/vibrator/VibrationStats$StatsInfo;)V > 15,19 @35 exception:20,
return,
putfield 1.< Application, Lcom/android/server/vibrator/VibratorManagerService, mCurrentExternalVibration, <Application,Lcom/android/server/vibrator/VibratorManagerService$ExternalVibrationHolder> > = 8,
invokestatic < Application, Landroid/os/Trace, traceEnd(J)V > 4 @37 exception:24,
return,
invokestatic < Application, Landroid/os/Binder, restoreCallingIdentity(J)V > 15 @92 exception:57,
monitorexit 10,
invokestatic < Application, Landroid/os/Trace, traceEnd(J)V > 5 @96 exception:75,
return,","depth : 0
-----
depth : 1
-----
depth : 1
-----
depth : 2
-----
depth : 1
-----
depth : 2
-----
depth : 2
-----
depth : 1
-----
depth : 2
-----
depth : 1
-----
depth : 2
-----
depth : 1
-----
depth : 2
-----
depth : 1
-----
depth : 2
-----
depth : 2
-----
depth : 2
-----
depth : 1
-----
depth : 2
-----
depth : 1
-----
depth : 2
-----
depth : 2
-----
depth : 2
-----
","public void cancelVibrate(int p1, IBinder p2){
	Vibration$EndInfo v3 = new Vibration$EndInfo(Vibration$Status.CANCELLED_BY_USER);
	long v5 = Binder.clearCallingIdentity();
	if (this.mNextVibration == 0) {
		Vibration v6 = this.mVibration;
		if (Vibration.token != p2) {
			int v9 = Vibration.attrs.getUsage();
			if (v9 != 0) {
				int v10 = Vibration.attrs.getUsage();
				int v11 = Vibration.attrs.getUsage();
				if ((v10 & p2) != v11) {
					boolean v8 = ;
					if (v8 == 0) {
						boolean v7 = ;
						if (v7 == 0) {
							if (this.mNextVibration == 0) {
								Vibration v13 = this.mVibration;
								v13.end(p1);
								VibratorManagerService.logVibrationStatus(Vibration.uid, Vibration.attrs, Vibration$EndInfo.status);
								this.mVibratorManagerRecords.record(v13);
								if (1 == 0) {
									long v18 = SystemClock.uptimeMillis();
									VibrationStats$StatsInfo v19 = v13.getStatsInfo(v18);
									this.mFrameworkStatsLogger.writeVibrationReportedAsync(v19);
									this.mNextVibration = 0;
									if (this.mCurrentVibration == 0) {
										Vibration v21 = this.mCurrentVibration.getVibration();
										if (Vibration.token != p2) {
											int v24 = Vibration.attrs.getUsage();
											if (v24 != 0) {
												int v25 = Vibration.attrs.getUsage();
												int v26 = Vibration.attrs.getUsage();
												if ((v25 & p2) != v26) {
													boolean v23 = ;
													if (v23 == 0) {
														boolean v22 = ;
														if (v22 == 0) {
															if (Build.IS_DEBUGGABLE == 0) {
																Thread v29 = Thread.currentThread();
																if (v29 instanceof VibrationThread == 0) {
																	if (v3 == 0) {
																		String v36 = Vibration$EndInfo.status.name();
																		boolean v37 = v36.startsWith(""CANCEL"");
																		if (v37 != 0) {
																			Vibration$EndInfo v45 = new Vibration$EndInfo(Vibration$Status.CANCELLED_BY_UNKNOWN_REASON);
																			if (0 == 0) {
																				if (this.mSignalCancelImmediate != 0) {
																					if (this.mSignalCancel == 0) {
																						this.mSignalCancelImmediate = (0 | this.mSignalCancelImmediate);
																						if (this.mSignalCancel != 0) {
																							this.mSignalCancel = ;
																							this.mLock.notify();
																							if (this.mCurrentExternalVibration == 0) {
																								VibrationAttributes$Builder v49 = new VibrationAttributes$Builder(this.mAttrs);
																								VibrationAttributes v52 = new VibrationAttributes(this.mUsage,this.mOriginalAudioUsage,this.mFlags,0);
																								VibrationAttributes v51 = v52;
																								VibrationAttributes v48 = v51;
																								int v55 = this.mUsage;
																								if (v55 != 0) {
																									int v56 = this.mUsage;
																									int v57 = this.mUsage;
																									if ((v56 & p1) != v57) {
																										boolean v54 = ;
																										if (v54 == 0) {
																											boolean v60 = this.mController.mute();
																											boolean v59 = 0;
																											Trace.traceBegin(8388608, ""endExternalVibrateLocked"");
																											if (this.mCurrentExternalVibration != 0) {
																												this.externalVibration.unlinkToDeath(VibratorManagerService$ExternalVibrationHolder);
																												if (0 != 0) {
																													int v72 = this.mVibrators.size();
																													if ( >= v72) {
																														this.mCurrentExternalVibration.end(p1);
																														int v75 = VibratorManagerService$ExternalVibrationHolder.externalVibration.getUid();
																														VibrationAttributes v76 = VibratorManagerService$ExternalVibrationHolder.externalVibration.getVibrationAttributes();
																														VibratorManagerService.logVibrationStatus(v75, v76, Vibration$EndInfo.status);
																														this.mVibratorManagerRecords.record(this.mCurrentExternalVibration);
																														long v79 = SystemClock.uptimeMillis();
																														VibrationStats$StatsInfo v80 = this.mCurrentExternalVibration.getStatsInfo(v79);
																														this.mFrameworkStatsLogger.writeVibrationReportedAsync(v80);
																														this.mCurrentExternalVibration = 0;
																														Trace.traceEnd(8388608);
																														Binder.restoreCallingIdentity(v5);
																														Trace.traceEnd(8388608);
																														return;
																													}
																												}
																											}
																										}
																									}
																								}
																							}
																						}
																					}
																				}
																			}
																		}
																	}
																}
															}
														}
													}
												}
											}
										}
									}
								}
							}
						}
					}
				}
			}
		}
	}
}
","NORMAL"
"Lcom/android/server/vibrator/VibratorManagerService","cancelVibrate(ILandroid/os/IBinder;)V","2","invokestatic < Application, Landroid/os/Trace, traceBegin(JLjava/lang/String;)V > 5,4 @5 exception:6,
7 = getfield < Application, Lcom/android/server/vibrator/VibratorManagerService, mContext, <Application,Landroid/content/Context> > 1,
invokevirtual < Application, Landroid/content/Context, enforceCallingOrSelfPermission(Ljava/lang/String;Ljava/lang/String;)V > 7,8,4 @14 exception:9,
10 = getfield < Application, Lcom/android/server/vibrator/VibratorManagerService, mLock, <Application,Ljava/lang/Object> > 1,
monitorenter 10,
11 = new <Application,Lcom/android/server/vibrator/Vibration$EndInfo>@20,
12 = getstatic < Application, Lcom/android/server/vibrator/Vibration$Status, CANCELLED_BY_USER, <Application,Lcom/android/server/vibrator/Vibration$Status> >,
invokespecial < Application, Lcom/android/server/vibrator/Vibration$EndInfo, <init>(Lcom/android/server/vibrator/Vibration$Status;)V > 11,12 @24 exception:13,
15 = invokestatic < Application, Landroid/os/Binder, clearCallingIdentity()J > @27 exception:14,
16 = getfield < Application, Lcom/android/server/vibrator/VibratorManagerService, mNextVibration, <Application,Lcom/android/server/vibrator/VibrationStepConductor> > 1,
conditional branch(eq, to iindex=-1) 16,17,
19 = invokevirtual < Application, Lcom/android/server/vibrator/VibrationStepConductor, getVibration()Lcom/android/server/vibrator/Vibration; > 16 @35 exception:18,
2 = getfield < Application, Lcom/android/server/vibrator/VibrationStepConductor, mVibration, <Application,Lcom/android/server/vibrator/Vibration> > 1,
return 2,
21 = invokevirtual < Application, Lcom/android/server/vibrator/VibratorManagerService, shouldCancelVibration(Lcom/android/server/vibrator/Vibration;ILandroid/os/IBinder;)Z > 1,19,2,3 @39 exception:20,
5 = getfield < Application, Lcom/android/server/vibrator/Vibration, token, <Application,Landroid/os/IBinder> > 2,
conditional branch(ne, to iindex=-1) 5,4,
6 = getfield < Application, Lcom/android/server/vibrator/Vibration, attrs, <Application,Landroid/os/VibrationAttributes> > 2,
8 = invokevirtual < Application, Lcom/android/server/vibrator/VibratorManagerService, shouldCancelVibration(Landroid/os/VibrationAttributes;I)Z > 1,6,3 @6 exception:7,
5 = invokevirtual < Application, Landroid/os/VibrationAttributes, getUsage()I > 2 @0 exception:4,
conditional branch(ne, to iindex=-1) 5,7,
9 = invokevirtual < Application, Landroid/os/VibrationAttributes, getUsage()I > 2 @16 exception:8,
10 = binaryop(and) 9 , 3,
12 = invokevirtual < Application, Landroid/os/VibrationAttributes, getUsage()I > 2 @21 exception:11,
conditional branch(ne, to iindex=-1) 10,12,
13 = phi  6,7,
return 13,
conditional branch(eq, to iindex=-1) 8,9,
goto (from iindex= 7 to iindex = 2),
13 = phi  12,9,
return 13,
conditional branch(eq, to iindex=-1) 21,17,
invokevirtual < Application, Lcom/android/server/vibrator/VibratorManagerService, clearNextVibrationLocked(Lcom/android/server/vibrator/Vibration$EndInfo;)V > 1,11 @45 exception:22,
3 = getfield < Application, Lcom/android/server/vibrator/VibratorManagerService, mNextVibration, <Application,Lcom/android/server/vibrator/VibrationStepConductor> > 1,
conditional branch(eq, to iindex=-1) 3,4,
6 = invokevirtual < Application, Lcom/android/server/vibrator/VibrationStepConductor, getVibration()Lcom/android/server/vibrator/Vibration; > 3 @4 exception:5,
2 = getfield < Application, Lcom/android/server/vibrator/VibrationStepConductor, mVibration, <Application,Lcom/android/server/vibrator/Vibration> > 1,
return 2,
invokevirtual < Application, Lcom/android/server/vibrator/VibratorManagerService, endVibrationLocked(Lcom/android/server/vibrator/Vibration;Lcom/android/server/vibrator/Vibration$EndInfo;Z)V > 1,6,2,7 @9 exception:8,
invokevirtual < Application, Lcom/android/server/vibrator/Vibration, end(Lcom/android/server/vibrator/Vibration$EndInfo;)V > 2,3 @0 exception:5,
6 = getfield < Application, Lcom/android/server/vibrator/Vibration, uid, <Primordial,I> > 2,
7 = getfield < Application, Lcom/android/server/vibrator/Vibration, attrs, <Application,Landroid/os/VibrationAttributes> > 2,
8 = getfield < Application, Lcom/android/server/vibrator/Vibration$EndInfo, status, <Application,Lcom/android/server/vibrator/Vibration$Status> > 3,
invokevirtual < Application, Lcom/android/server/vibrator/VibratorManagerService, logVibrationStatus(ILandroid/os/VibrationAttributes;Lcom/android/server/vibrator/Vibration$Status;)V > 1,6,7,8 @9 exception:9,
10 = getfield < Application, Lcom/android/server/vibrator/VibratorManagerService, mVibratorManagerRecords, <Application,Lcom/android/server/vibrator/VibratorManagerService$VibratorManagerRecords> > 1,
invokevirtual < Application, Lcom/android/server/vibrator/VibratorManagerService$VibratorManagerRecords, record(Lcom/android/server/vibrator/Vibration;)V > 10,2 @14 exception:11,
conditional branch(eq, to iindex=-1) 4,12,
13 = getfield < Application, Lcom/android/server/vibrator/VibratorManagerService, mFrameworkStatsLogger, <Application,Lcom/android/server/vibrator/VibratorFrameworkStatsLogger> > 1,
15 = invokestatic < Application, Landroid/os/SystemClock, uptimeMillis()J > @21 exception:14,
17 = invokevirtual < Application, Lcom/android/server/vibrator/Vibration, getStatsInfo(J)Lcom/android/server/vibrator/VibrationStats$StatsInfo; > 2,15 @25 exception:16,
invokevirtual < Application, Lcom/android/server/vibrator/VibratorFrameworkStatsLogger, writeVibrationReportedAsync(Lcom/android/server/vibrator/VibrationStats$StatsInfo;)V > 13,17 @29 exception:18,
return,
putfield 1.< Application, Lcom/android/server/vibrator/VibratorManagerService, mNextVibration, <Application,Lcom/android/server/vibrator/VibrationStepConductor> > = 4,
return,
26 = getfield < Application, Lcom/android/server/vibrator/VibratorManagerService, mCurrentVibration, <Application,Lcom/android/server/vibrator/VibrationStepConductor> > 1,
conditional branch(eq, to iindex=-1) 26,17,
28 = invokevirtual < Application, Lcom/android/server/vibrator/VibrationStepConductor, getVibration()Lcom/android/server/vibrator/Vibration; > 26 @53 exception:27,
30 = invokevirtual < Application, Lcom/android/server/vibrator/VibratorManagerService, shouldCancelVibration(Lcom/android/server/vibrator/Vibration;ILandroid/os/IBinder;)Z > 1,28,2,3 @57 exception:29,
5 = getfield < Application, Lcom/android/server/vibrator/Vibration, token, <Application,Landroid/os/IBinder> > 2,
conditional branch(ne, to iindex=-1) 5,4,
6 = getfield < Application, Lcom/android/server/vibrator/Vibration, attrs, <Application,Landroid/os/VibrationAttributes> > 2,
8 = invokevirtual < Application, Lcom/android/server/vibrator/VibratorManagerService, shouldCancelVibration(Landroid/os/VibrationAttributes;I)Z > 1,6,3 @6 exception:7,
5 = invokevirtual < Application, Landroid/os/VibrationAttributes, getUsage()I > 2 @0 exception:4,
conditional branch(ne, to iindex=-1) 5,7,
9 = invokevirtual < Application, Landroid/os/VibrationAttributes, getUsage()I > 2 @16 exception:8,
10 = binaryop(and) 9 , 3,
12 = invokevirtual < Application, Landroid/os/VibrationAttributes, getUsage()I > 2 @21 exception:11,
conditional branch(ne, to iindex=-1) 10,12,
goto (from iindex= 17 to iindex = 2),
13 = phi  6,7,
return 13,
conditional branch(eq, to iindex=-1) 8,9,
goto (from iindex= 7 to iindex = 2),
13 = phi  12,9,
return 13,
conditional branch(eq, to iindex=-1) 30,17,
31 = getfield < Application, Lcom/android/server/vibrator/VibratorManagerService, mCurrentVibration, <Application,Lcom/android/server/vibrator/VibrationStepConductor> > 1,
invokevirtual < Application, Lcom/android/server/vibrator/VibrationStepConductor, notifyCancelled(Lcom/android/server/vibrator/Vibration$EndInfo;Z)V > 31,11,17 @65 exception:32,
4 = getstatic < Application, Landroid/os/Build, IS_DEBUGGABLE, <Primordial,Z> >,
conditional branch(eq, to iindex=-1) 4,5,
invokestatic < Application, Lcom/android/server/vibrator/VibrationStepConductor, expectIsVibrationThread(Z)V > 5 @5 exception:6,
3 = invokestatic < Application, Ljava/lang/Thread, currentThread()Ljava/lang/Thread; > @0 exception:2,
4 = instanceof 3 <Application,Lcom/android/server/vibrator/VibrationThread>,
conditional branch(eq, to iindex=-1) 4,1,
5 = new <Application,Ljava/lang/StringBuilder>@8,
invokespecial < Application, Ljava/lang/StringBuilder, <init>()V > 5 @10 exception:6,
9 = invokevirtual < Application, Ljava/lang/StringBuilder, append(Ljava/lang/String;)Ljava/lang/StringBuilder; > 5,7 @15 exception:8,
11 = invokevirtual < Application, Ljava/lang/StringBuilder, append(Z)Ljava/lang/StringBuilder; > 5,1 @18 exception:10,
13 = invokevirtual < Application, Ljava/lang/StringBuilder, toString()Ljava/lang/String; > 5 @21 exception:12,
16 = invokestatic < Application, Landroid/util/Slog, wtfStack(Ljava/lang/String;Ljava/lang/String;)I > 14,13 @27 exception:15,
return,
conditional branch(eq, to iindex=-1) 2,5,
8 = getfield < Application, Lcom/android/server/vibrator/Vibration$EndInfo, status, <Application,Lcom/android/server/vibrator/Vibration$Status> > 2,
10 = invokevirtual < Application, Ljava/lang/Enum, name()Ljava/lang/String; > 8 @12 exception:9,
13 = invokevirtual < Application, Ljava/lang/String, startsWith(Ljava/lang/String;)Z > 10,11 @18 exception:12,
conditional branch(ne, to iindex=-1) 13,5,
17 = new <Application,Ljava/lang/StringBuilder>@26,
invokespecial < Application, Ljava/lang/StringBuilder, <init>()V > 17 @28 exception:18,
21 = invokevirtual < Application, Ljava/lang/StringBuilder, append(Ljava/lang/String;)Ljava/lang/StringBuilder; > 17,19 @33 exception:20,
23 = invokevirtual < Application, Ljava/lang/StringBuilder, append(Ljava/lang/Object;)Ljava/lang/StringBuilder; > 17,2 @36 exception:22,
26 = invokevirtual < Application, Ljava/lang/StringBuilder, append(Ljava/lang/String;)Ljava/lang/StringBuilder; > 17,24 @41 exception:25,
28 = invokevirtual < Application, Ljava/lang/StringBuilder, toString()Ljava/lang/String; > 17 @44 exception:27,
30 = invokestatic < Application, Landroid/util/Slog, w(Ljava/lang/String;Ljava/lang/String;)I > 16,28 @48 exception:29,
31 = new <Application,Lcom/android/server/vibrator/Vibration$EndInfo>@51,
32 = getstatic < Application, Lcom/android/server/vibrator/Vibration$Status, CANCELLED_BY_UNKNOWN_REASON, <Application,Lcom/android/server/vibrator/Vibration$Status> >,
invokespecial < Application, Lcom/android/server/vibrator/Vibration$EndInfo, <init>(Lcom/android/server/vibrator/Vibration$Status;)V > 31,32 @55 exception:33,
36 = phi  2,31,
39 = getfield < Application, Lcom/android/server/vibrator/VibrationStepConductor, mLock, <Application,Ljava/lang/Object> > 1,
monitorenter 39,
conditional branch(eq, to iindex=-1) 3,5,
40 = getfield < Application, Lcom/android/server/vibrator/VibrationStepConductor, mSignalCancelImmediate, <Primordial,Z> > 1,
conditional branch(ne, to iindex=-1) 40,5,
42 = getfield < Application, Lcom/android/server/vibrator/VibrationStepConductor, mSignalCancel, <Application,Lcom/android/server/vibrator/Vibration$EndInfo> > 1,
conditional branch(eq, to iindex=-1) 42,5,
43 = getfield < Application, Lcom/android/server/vibrator/VibrationStepConductor, mSignalCancelImmediate, <Primordial,Z> > 1,
44 = binaryop(or) 3 , 43,
putfield 1.< Application, Lcom/android/server/vibrator/VibrationStepConductor, mSignalCancelImmediate, <Primordial,Z> > = 44,
conditional branch(ne, to iindex=-1) 42,5,
putfield 1.< Application, Lcom/android/server/vibrator/VibrationStepConductor, mSignalCancel, <Application,Lcom/android/server/vibrator/Vibration$EndInfo> > = 36,
45 = getfield < Application, Lcom/android/server/vibrator/VibrationStepConductor, mLock, <Application,Ljava/lang/Object> > 1,
invokevirtual < Application, Ljava/lang/Object, notify()V > 45 @84 exception:46,
monitorexit 39,
return,
37 = getfield < Application, Lcom/android/server/vibrator/VibratorManagerService, mCurrentExternalVibration, <Application,Lcom/android/server/vibrator/VibratorManagerService$ExternalVibrationHolder> > 1,
conditional branch(eq, to iindex=-1) 37,17,
38 = getfield < Application, Lcom/android/server/vibrator/VibratorManagerService$ExternalVibrationHolder, externalVibration, <Application,Landroid/os/ExternalVibration> > 37,
40 = invokevirtual < Application, Landroid/os/ExternalVibration, getVibrationAttributes()Landroid/os/VibrationAttributes; > 38 @74 exception:39,
2 = new <Application,Landroid/os/VibrationAttributes$Builder>@0,
3 = getfield < Application, Landroid/os/ExternalVibration, mAttrs, <Application,Landroid/media/AudioAttributes> > 1,
invokespecial < Application, Landroid/os/VibrationAttributes$Builder, <init>(Landroid/media/AudioAttributes;)V > 2,3 @4 exception:4,
6 = invokevirtual < Application, Landroid/os/VibrationAttributes$Builder, build()Landroid/os/VibrationAttributes; > 2 @7 exception:5,
2 = new <Application,Landroid/os/VibrationAttributes>@0,
3 = getfield < Application, Landroid/os/VibrationAttributes$Builder, mUsage, <Primordial,I> > 1,
4 = getfield < Application, Landroid/os/VibrationAttributes$Builder, mOriginalAudioUsage, <Primordial,I> > 1,
5 = getfield < Application, Landroid/os/VibrationAttributes$Builder, mFlags, <Primordial,I> > 1,
invokespecial < Application, Landroid/os/VibrationAttributes, <init>(IIILandroid/os/VibrationAttributes-IA;)V > 2,3,4,5,6 @9 exception:7,
return 2,
return 6,
42 = invokevirtual < Application, Lcom/android/server/vibrator/VibratorManagerService, shouldCancelVibration(Landroid/os/VibrationAttributes;I)Z > 1,40,2 @78 exception:41,
5 = invokevirtual < Application, Landroid/os/VibrationAttributes, getUsage()I > 2 @0 exception:4,
2 = getfield < Application, Landroid/os/VibrationAttributes, mUsage, <Primordial,I> > 1,
return 2,
conditional branch(ne, to iindex=-1) 5,7,
9 = invokevirtual < Application, Landroid/os/VibrationAttributes, getUsage()I > 2 @16 exception:8,
2 = getfield < Application, Landroid/os/VibrationAttributes, mUsage, <Primordial,I> > 1,
return 2,
10 = binaryop(and) 9 , 3,
12 = invokevirtual < Application, Landroid/os/VibrationAttributes, getUsage()I > 2 @21 exception:11,
2 = getfield < Application, Landroid/os/VibrationAttributes, mUsage, <Primordial,I> > 1,
return 2,
conditional branch(ne, to iindex=-1) 10,12,
goto (from iindex= 17 to iindex = 2),
13 = phi  6,7,
return 13,
conditional branch(eq, to iindex=-1) 42,17,
43 = getfield < Application, Lcom/android/server/vibrator/VibratorManagerService, mCurrentExternalVibration, <Application,Lcom/android/server/vibrator/VibratorManagerService$ExternalVibrationHolder> > 1,
invokevirtual < Application, Lcom/android/server/vibrator/VibratorManagerService$ExternalVibrationHolder, mute()V > 43 @86 exception:44,
2 = getfield < Application, Lcom/android/server/vibrator/VibratorManagerService$ExternalVibrationHolder, externalVibration, <Application,Landroid/os/ExternalVibration> > 1,
4 = invokevirtual < Application, Landroid/os/ExternalVibration, mute()Z > 2 @2 exception:3,
2 = getfield < Application, Landroid/os/ExternalVibration, mController, <Application,Landroid/os/IExternalVibrationController> > 1,
4 = invokeinterface < Application, Landroid/os/IExternalVibrationController, mute()Z > 2 @2 exception:3,
5 = getCaughtException ,
6 = new <Application,Ljava/lang/StringBuilder>@9,
invokespecial < Application, Ljava/lang/StringBuilder, <init>()V > 6 @11 exception:7,
10 = invokevirtual < Application, Ljava/lang/StringBuilder, append(Ljava/lang/String;)Ljava/lang/StringBuilder; > 6,8 @16 exception:9,
12 = invokevirtual < Application, Ljava/lang/StringBuilder, append(Ljava/lang/Object;)Ljava/lang/StringBuilder; > 10,1 @20 exception:11,
14 = invokevirtual < Application, Ljava/lang/StringBuilder, toString()Ljava/lang/String; > 12 @24 exception:13,
17 = invokestatic < Application, Landroid/util/Slog, wtf(Ljava/lang/String;Ljava/lang/String;Ljava/lang/Throwable;)I > 15,14,5 @30 exception:16,
return 18,
return,
invokevirtual < Application, Lcom/android/server/vibrator/VibratorManagerService, endExternalVibrateLocked(Lcom/android/server/vibrator/Vibration$EndInfo;Z)V > 1,11,17 @89 exception:45,
invokestatic < Application, Landroid/os/Trace, traceBegin(JLjava/lang/String;)V > 4,5 @5 exception:6,
7 = getfield < Application, Lcom/android/server/vibrator/VibratorManagerService, mCurrentExternalVibration, <Application,Lcom/android/server/vibrator/VibratorManagerService$ExternalVibrationHolder> > 1,
conditional branch(ne, to iindex=-1) 7,8,
invokevirtual < Application, Lcom/android/server/vibrator/VibratorManagerService$ExternalVibrationHolder, unlinkToDeath()V > 7 @16 exception:9,
2 = getfield < Application, Lcom/android/server/vibrator/VibratorManagerService$ExternalVibrationHolder, externalVibration, <Application,Landroid/os/ExternalVibration> > 1,
invokevirtual < Application, Landroid/os/ExternalVibration, unlinkToDeath(Landroid/os/IBinder$DeathRecipient;)V > 2,1 @2 exception:3,
return,
conditional branch(ne, to iindex=-1) 3,8,
10 = getfield < Application, Lcom/android/server/vibrator/VibratorManagerService, mCurrentExternalVibration, <Application,Lcom/android/server/vibrator/VibratorManagerService$ExternalVibrationHolder> > 1,
11 = getfield < Application, Lcom/android/server/vibrator/VibratorManagerService$ExternalVibrationHolder, stats, <Application,Lcom/android/server/vibrator/VibrationStats> > 10,
invokevirtual < Application, Lcom/android/server/vibrator/VibratorManagerService, setExternalControl(ZLcom/android/server/vibrator/VibrationStats;)V > 1,8,11 @26 exception:12,
16 = phi  15,4,
5 = getfield < Application, Lcom/android/server/vibrator/VibratorManagerService, mVibrators, <Application,Landroid/util/SparseArray> > 1,
7 = invokevirtual < Application, Landroid/util/SparseArray, size()I > 5 @3 exception:6,
conditional branch(ge, to iindex=-1) 16,7,
return,
16 = getfield < Application, Lcom/android/server/vibrator/VibratorManagerService, mCurrentExternalVibration, <Application,Lcom/android/server/vibrator/VibratorManagerService$ExternalVibrationHolder> > 1,
invokevirtual < Application, Lcom/android/server/vibrator/VibratorManagerService, endVibrationAndWriteStatsLocked(Lcom/android/server/vibrator/VibratorManagerService$ExternalVibrationHolder;Lcom/android/server/vibrator/Vibration$EndInfo;)V > 1,16,2 @31 exception:17,
invokevirtual < Application, Lcom/android/server/vibrator/VibratorManagerService$ExternalVibrationHolder, end(Lcom/android/server/vibrator/Vibration$EndInfo;)V > 2,3 @0 exception:4,
5 = getfield < Application, Lcom/android/server/vibrator/VibratorManagerService$ExternalVibrationHolder, externalVibration, <Application,Landroid/os/ExternalVibration> > 2,
7 = invokevirtual < Application, Landroid/os/ExternalVibration, getUid()I > 5 @5 exception:6,
8 = getfield < Application, Lcom/android/server/vibrator/VibratorManagerService$ExternalVibrationHolder, externalVibration, <Application,Landroid/os/ExternalVibration> > 2,
10 = invokevirtual < Application, Landroid/os/ExternalVibration, getVibrationAttributes()Landroid/os/VibrationAttributes; > 8 @11 exception:9,
11 = getfield < Application, Lcom/android/server/vibrator/Vibration$EndInfo, status, <Application,Lcom/android/server/vibrator/Vibration$Status> > 3,
invokevirtual < Application, Lcom/android/server/vibrator/VibratorManagerService, logVibrationStatus(ILandroid/os/VibrationAttributes;Lcom/android/server/vibrator/Vibration$Status;)V > 1,7,10,11 @17 exception:12,
13 = getfield < Application, Lcom/android/server/vibrator/VibratorManagerService, mVibratorManagerRecords, <Application,Lcom/android/server/vibrator/VibratorManagerService$VibratorManagerRecords> > 1,
invokevirtual < Application, Lcom/android/server/vibrator/VibratorManagerService$VibratorManagerRecords, record(Lcom/android/server/vibrator/VibratorManagerService$ExternalVibrationHolder;)V > 13,2 @22 exception:14,
15 = getfield < Application, Lcom/android/server/vibrator/VibratorManagerService, mFrameworkStatsLogger, <Application,Lcom/android/server/vibrator/VibratorFrameworkStatsLogger> > 1,
17 = invokestatic < Application, Landroid/os/SystemClock, uptimeMillis()J > @27 exception:16,
19 = invokevirtual < Application, Lcom/android/server/vibrator/VibratorManagerService$ExternalVibrationHolder, getStatsInfo(J)Lcom/android/server/vibrator/VibrationStats$StatsInfo; > 2,17 @31 exception:18,
invokevirtual < Application, Lcom/android/server/vibrator/VibratorFrameworkStatsLogger, writeVibrationReportedAsync(Lcom/android/server/vibrator/VibrationStats$StatsInfo;)V > 15,19 @35 exception:20,
return,
putfield 1.< Application, Lcom/android/server/vibrator/VibratorManagerService, mCurrentExternalVibration, <Application,Lcom/android/server/vibrator/VibratorManagerService$ExternalVibrationHolder> > = 8,
invokestatic < Application, Landroid/os/Trace, traceEnd(J)V > 4 @37 exception:24,
return,
invokestatic < Application, Landroid/os/Binder, restoreCallingIdentity(J)V > 15 @92 exception:57,
monitorexit 10,
invokestatic < Application, Landroid/os/Trace, traceEnd(J)V > 5 @96 exception:75,
return,","depth : 0
-----
depth : 1
-----
depth : 1
-----
depth : 2
-----
depth : 1
-----
depth : 2
-----
depth : 2
-----
depth : 1
-----
depth : 2
-----
depth : 1
-----
depth : 2
-----
depth : 1
-----
depth : 2
-----
depth : 1
-----
depth : 2
-----
depth : 2
-----
depth : 2
-----
depth : 1
-----
depth : 2
-----
depth : 1
-----
depth : 2
-----
depth : 2
-----
depth : 2
-----
","public void cancelVibrate(int p1, IBinder p2){
	Vibration$EndInfo v3 = new Vibration$EndInfo(Vibration$Status.CANCELLED_BY_USER);
	long v5 = Binder.clearCallingIdentity();
	if (this.mNextVibration == 0) {
		Vibration v6 = this.mVibration;
		if (Vibration.token != p2) {
			int v9 = Vibration.attrs.getUsage();
			if (v9 != 0) {
				int v10 = Vibration.attrs.getUsage();
				int v11 = Vibration.attrs.getUsage();
				if ((v10 & p2) != v11) {
					boolean v8 = ;
					if (v8 == 0) {
						boolean v7 = ;
						if (v7 == 0) {
							if (this.mNextVibration == 0) {
								Vibration v13 = this.mVibration;
								v13.end(p1);
								VibratorManagerService.logVibrationStatus(Vibration.uid, Vibration.attrs, Vibration$EndInfo.status);
								this.mVibratorManagerRecords.record(v13);
								if (1 == 0) {
									long v18 = SystemClock.uptimeMillis();
									VibrationStats$StatsInfo v19 = v13.getStatsInfo(v18);
									this.mFrameworkStatsLogger.writeVibrationReportedAsync(v19);
									this.mNextVibration = 0;
									if (this.mCurrentVibration == 0) {
										Vibration v21 = this.mCurrentVibration.getVibration();
										if (Vibration.token != p2) {
											int v24 = Vibration.attrs.getUsage();
											if (v24 != 0) {
												int v25 = Vibration.attrs.getUsage();
												int v26 = Vibration.attrs.getUsage();
												if ((v25 & p2) != v26) {
													boolean v23 = ;
													if (v23 == 0) {
														boolean v22 = ;
														if (v22 == 0) {
															if (Build.IS_DEBUGGABLE == 0) {
																Thread v29 = Thread.currentThread();
																if (v29 instanceof VibrationThread == 0) {
																	if (v3 == 0) {
																		String v36 = Vibration$EndInfo.status.name();
																		boolean v37 = v36.startsWith(""CANCEL"");
																		if (v37 != 0) {
																			Vibration$EndInfo v45 = new Vibration$EndInfo(Vibration$Status.CANCELLED_BY_UNKNOWN_REASON);
																			if (0 == 0) {
																				if (this.mSignalCancelImmediate != 0) {
																					if (this.mSignalCancel == 0) {
																						this.mSignalCancelImmediate = (0 | this.mSignalCancelImmediate);
																						if (this.mSignalCancel != 0) {
																							this.mSignalCancel = ;
																							this.mLock.notify();
																							if (this.mCurrentExternalVibration == 0) {
																								VibrationAttributes$Builder v49 = new VibrationAttributes$Builder(this.mAttrs);
																								VibrationAttributes v52 = new VibrationAttributes(this.mUsage,this.mOriginalAudioUsage,this.mFlags,0);
																								VibrationAttributes v51 = v52;
																								VibrationAttributes v48 = v51;
																								int v55 = this.mUsage;
																								if (v55 != 0) {
																									int v56 = this.mUsage;
																									int v57 = this.mUsage;
																									if ((v56 & p1) != v57) {
																										boolean v54 = ;
																										if (v54 == 0) {
																											boolean v60 = this.mController.mute();
																											boolean v59 = 0;
																											Trace.traceBegin(8388608, ""endExternalVibrateLocked"");
																											if (this.mCurrentExternalVibration != 0) {
																												this.externalVibration.unlinkToDeath(VibratorManagerService$ExternalVibrationHolder);
																												if (0 != 0) {
																													int v72 = this.mVibrators.size();
																													if ( >= v72) {
																														this.mCurrentExternalVibration.end(p1);
																														int v75 = VibratorManagerService$ExternalVibrationHolder.externalVibration.getUid();
																														VibrationAttributes v76 = VibratorManagerService$ExternalVibrationHolder.externalVibration.getVibrationAttributes();
																														VibratorManagerService.logVibrationStatus(v75, v76, Vibration$EndInfo.status);
																														this.mVibratorManagerRecords.record(this.mCurrentExternalVibration);
																														long v79 = SystemClock.uptimeMillis();
																														VibrationStats$StatsInfo v80 = this.mCurrentExternalVibration.getStatsInfo(v79);
																														this.mFrameworkStatsLogger.writeVibrationReportedAsync(v80);
																														this.mCurrentExternalVibration = 0;
																														Trace.traceEnd(8388608);
																														Binder.restoreCallingIdentity(v5);
																														Trace.traceEnd(8388608);
																														return;
																													}
																												}
																											}
																										}
																									}
																								}
																							}
																						}
																					}
																				}
																			}
																		}
																	}
																}
															}
														}
													}
												}
											}
										}
									}
								}
							}
						}
					}
				}
			}
		}
	}
}
","NORMAL"
"Lcom/android/server/vibrator/VibratorManagerService","cancelVibrate(ILandroid/os/IBinder;)V","2","invokestatic < Application, Landroid/os/Trace, traceBegin(JLjava/lang/String;)V > 5,4 @5 exception:6,
7 = getfield < Application, Lcom/android/server/vibrator/VibratorManagerService, mContext, <Application,Landroid/content/Context> > 1,
invokevirtual < Application, Landroid/content/Context, enforceCallingOrSelfPermission(Ljava/lang/String;Ljava/lang/String;)V > 7,8,4 @14 exception:9,
10 = getfield < Application, Lcom/android/server/vibrator/VibratorManagerService, mLock, <Application,Ljava/lang/Object> > 1,
monitorenter 10,
11 = new <Application,Lcom/android/server/vibrator/Vibration$EndInfo>@20,
12 = getstatic < Application, Lcom/android/server/vibrator/Vibration$Status, CANCELLED_BY_USER, <Application,Lcom/android/server/vibrator/Vibration$Status> >,
invokespecial < Application, Lcom/android/server/vibrator/Vibration$EndInfo, <init>(Lcom/android/server/vibrator/Vibration$Status;)V > 11,12 @24 exception:13,
15 = invokestatic < Application, Landroid/os/Binder, clearCallingIdentity()J > @27 exception:14,
16 = getfield < Application, Lcom/android/server/vibrator/VibratorManagerService, mNextVibration, <Application,Lcom/android/server/vibrator/VibrationStepConductor> > 1,
conditional branch(eq, to iindex=-1) 16,17,
19 = invokevirtual < Application, Lcom/android/server/vibrator/VibrationStepConductor, getVibration()Lcom/android/server/vibrator/Vibration; > 16 @35 exception:18,
2 = getfield < Application, Lcom/android/server/vibrator/VibrationStepConductor, mVibration, <Application,Lcom/android/server/vibrator/Vibration> > 1,
return 2,
21 = invokevirtual < Application, Lcom/android/server/vibrator/VibratorManagerService, shouldCancelVibration(Lcom/android/server/vibrator/Vibration;ILandroid/os/IBinder;)Z > 1,19,2,3 @39 exception:20,
5 = getfield < Application, Lcom/android/server/vibrator/Vibration, token, <Application,Landroid/os/IBinder> > 2,
conditional branch(ne, to iindex=-1) 5,4,
6 = getfield < Application, Lcom/android/server/vibrator/Vibration, attrs, <Application,Landroid/os/VibrationAttributes> > 2,
8 = invokevirtual < Application, Lcom/android/server/vibrator/VibratorManagerService, shouldCancelVibration(Landroid/os/VibrationAttributes;I)Z > 1,6,3 @6 exception:7,
5 = invokevirtual < Application, Landroid/os/VibrationAttributes, getUsage()I > 2 @0 exception:4,
conditional branch(ne, to iindex=-1) 5,7,
9 = invokevirtual < Application, Landroid/os/VibrationAttributes, getUsage()I > 2 @16 exception:8,
10 = binaryop(and) 9 , 3,
12 = invokevirtual < Application, Landroid/os/VibrationAttributes, getUsage()I > 2 @21 exception:11,
conditional branch(ne, to iindex=-1) 10,12,
goto (from iindex= 17 to iindex = 2),
13 = phi  6,7,
return 13,
conditional branch(eq, to iindex=-1) 8,9,
goto (from iindex= 7 to iindex = 2),
13 = phi  12,9,
return 13,
conditional branch(eq, to iindex=-1) 21,17,
invokevirtual < Application, Lcom/android/server/vibrator/VibratorManagerService, clearNextVibrationLocked(Lcom/android/server/vibrator/Vibration$EndInfo;)V > 1,11 @45 exception:22,
3 = getfield < Application, Lcom/android/server/vibrator/VibratorManagerService, mNextVibration, <Application,Lcom/android/server/vibrator/VibrationStepConductor> > 1,
conditional branch(eq, to iindex=-1) 3,4,
6 = invokevirtual < Application, Lcom/android/server/vibrator/VibrationStepConductor, getVibration()Lcom/android/server/vibrator/Vibration; > 3 @4 exception:5,
2 = getfield < Application, Lcom/android/server/vibrator/VibrationStepConductor, mVibration, <Application,Lcom/android/server/vibrator/Vibration> > 1,
return 2,
invokevirtual < Application, Lcom/android/server/vibrator/VibratorManagerService, endVibrationLocked(Lcom/android/server/vibrator/Vibration;Lcom/android/server/vibrator/Vibration$EndInfo;Z)V > 1,6,2,7 @9 exception:8,
invokevirtual < Application, Lcom/android/server/vibrator/Vibration, end(Lcom/android/server/vibrator/Vibration$EndInfo;)V > 2,3 @0 exception:5,
6 = getfield < Application, Lcom/android/server/vibrator/Vibration, uid, <Primordial,I> > 2,
7 = getfield < Application, Lcom/android/server/vibrator/Vibration, attrs, <Application,Landroid/os/VibrationAttributes> > 2,
8 = getfield < Application, Lcom/android/server/vibrator/Vibration$EndInfo, status, <Application,Lcom/android/server/vibrator/Vibration$Status> > 3,
invokevirtual < Application, Lcom/android/server/vibrator/VibratorManagerService, logVibrationStatus(ILandroid/os/VibrationAttributes;Lcom/android/server/vibrator/Vibration$Status;)V > 1,6,7,8 @9 exception:9,
10 = getfield < Application, Lcom/android/server/vibrator/VibratorManagerService, mVibratorManagerRecords, <Application,Lcom/android/server/vibrator/VibratorManagerService$VibratorManagerRecords> > 1,
invokevirtual < Application, Lcom/android/server/vibrator/VibratorManagerService$VibratorManagerRecords, record(Lcom/android/server/vibrator/Vibration;)V > 10,2 @14 exception:11,
conditional branch(eq, to iindex=-1) 4,12,
13 = getfield < Application, Lcom/android/server/vibrator/VibratorManagerService, mFrameworkStatsLogger, <Application,Lcom/android/server/vibrator/VibratorFrameworkStatsLogger> > 1,
15 = invokestatic < Application, Landroid/os/SystemClock, uptimeMillis()J > @21 exception:14,
17 = invokevirtual < Application, Lcom/android/server/vibrator/Vibration, getStatsInfo(J)Lcom/android/server/vibrator/VibrationStats$StatsInfo; > 2,15 @25 exception:16,
invokevirtual < Application, Lcom/android/server/vibrator/VibratorFrameworkStatsLogger, writeVibrationReportedAsync(Lcom/android/server/vibrator/VibrationStats$StatsInfo;)V > 13,17 @29 exception:18,
return,
putfield 1.< Application, Lcom/android/server/vibrator/VibratorManagerService, mNextVibration, <Application,Lcom/android/server/vibrator/VibrationStepConductor> > = 4,
return,
26 = getfield < Application, Lcom/android/server/vibrator/VibratorManagerService, mCurrentVibration, <Application,Lcom/android/server/vibrator/VibrationStepConductor> > 1,
conditional branch(eq, to iindex=-1) 26,17,
28 = invokevirtual < Application, Lcom/android/server/vibrator/VibrationStepConductor, getVibration()Lcom/android/server/vibrator/Vibration; > 26 @53 exception:27,
30 = invokevirtual < Application, Lcom/android/server/vibrator/VibratorManagerService, shouldCancelVibration(Lcom/android/server/vibrator/Vibration;ILandroid/os/IBinder;)Z > 1,28,2,3 @57 exception:29,
5 = getfield < Application, Lcom/android/server/vibrator/Vibration, token, <Application,Landroid/os/IBinder> > 2,
conditional branch(ne, to iindex=-1) 5,4,
6 = getfield < Application, Lcom/android/server/vibrator/Vibration, attrs, <Application,Landroid/os/VibrationAttributes> > 2,
8 = invokevirtual < Application, Lcom/android/server/vibrator/VibratorManagerService, shouldCancelVibration(Landroid/os/VibrationAttributes;I)Z > 1,6,3 @6 exception:7,
5 = invokevirtual < Application, Landroid/os/VibrationAttributes, getUsage()I > 2 @0 exception:4,
conditional branch(ne, to iindex=-1) 5,7,
9 = invokevirtual < Application, Landroid/os/VibrationAttributes, getUsage()I > 2 @16 exception:8,
10 = binaryop(and) 9 , 3,
12 = invokevirtual < Application, Landroid/os/VibrationAttributes, getUsage()I > 2 @21 exception:11,
conditional branch(ne, to iindex=-1) 10,12,
13 = phi  6,7,
return 13,
conditional branch(eq, to iindex=-1) 8,9,
goto (from iindex= 7 to iindex = 2),
13 = phi  12,9,
return 13,
conditional branch(eq, to iindex=-1) 30,17,
31 = getfield < Application, Lcom/android/server/vibrator/VibratorManagerService, mCurrentVibration, <Application,Lcom/android/server/vibrator/VibrationStepConductor> > 1,
invokevirtual < Application, Lcom/android/server/vibrator/VibrationStepConductor, notifyCancelled(Lcom/android/server/vibrator/Vibration$EndInfo;Z)V > 31,11,17 @65 exception:32,
4 = getstatic < Application, Landroid/os/Build, IS_DEBUGGABLE, <Primordial,Z> >,
conditional branch(eq, to iindex=-1) 4,5,
invokestatic < Application, Lcom/android/server/vibrator/VibrationStepConductor, expectIsVibrationThread(Z)V > 5 @5 exception:6,
3 = invokestatic < Application, Ljava/lang/Thread, currentThread()Ljava/lang/Thread; > @0 exception:2,
4 = instanceof 3 <Application,Lcom/android/server/vibrator/VibrationThread>,
conditional branch(eq, to iindex=-1) 4,1,
5 = new <Application,Ljava/lang/StringBuilder>@8,
invokespecial < Application, Ljava/lang/StringBuilder, <init>()V > 5 @10 exception:6,
9 = invokevirtual < Application, Ljava/lang/StringBuilder, append(Ljava/lang/String;)Ljava/lang/StringBuilder; > 5,7 @15 exception:8,
11 = invokevirtual < Application, Ljava/lang/StringBuilder, append(Z)Ljava/lang/StringBuilder; > 5,1 @18 exception:10,
13 = invokevirtual < Application, Ljava/lang/StringBuilder, toString()Ljava/lang/String; > 5 @21 exception:12,
16 = invokestatic < Application, Landroid/util/Slog, wtfStack(Ljava/lang/String;Ljava/lang/String;)I > 14,13 @27 exception:15,
return,
conditional branch(eq, to iindex=-1) 2,5,
8 = getfield < Application, Lcom/android/server/vibrator/Vibration$EndInfo, status, <Application,Lcom/android/server/vibrator/Vibration$Status> > 2,
10 = invokevirtual < Application, Ljava/lang/Enum, name()Ljava/lang/String; > 8 @12 exception:9,
13 = invokevirtual < Application, Ljava/lang/String, startsWith(Ljava/lang/String;)Z > 10,11 @18 exception:12,
conditional branch(ne, to iindex=-1) 13,5,
17 = new <Application,Ljava/lang/StringBuilder>@26,
invokespecial < Application, Ljava/lang/StringBuilder, <init>()V > 17 @28 exception:18,
21 = invokevirtual < Application, Ljava/lang/StringBuilder, append(Ljava/lang/String;)Ljava/lang/StringBuilder; > 17,19 @33 exception:20,
23 = invokevirtual < Application, Ljava/lang/StringBuilder, append(Ljava/lang/Object;)Ljava/lang/StringBuilder; > 17,2 @36 exception:22,
26 = invokevirtual < Application, Ljava/lang/StringBuilder, append(Ljava/lang/String;)Ljava/lang/StringBuilder; > 17,24 @41 exception:25,
28 = invokevirtual < Application, Ljava/lang/StringBuilder, toString()Ljava/lang/String; > 17 @44 exception:27,
30 = invokestatic < Application, Landroid/util/Slog, w(Ljava/lang/String;Ljava/lang/String;)I > 16,28 @48 exception:29,
31 = new <Application,Lcom/android/server/vibrator/Vibration$EndInfo>@51,
32 = getstatic < Application, Lcom/android/server/vibrator/Vibration$Status, CANCELLED_BY_UNKNOWN_REASON, <Application,Lcom/android/server/vibrator/Vibration$Status> >,
invokespecial < Application, Lcom/android/server/vibrator/Vibration$EndInfo, <init>(Lcom/android/server/vibrator/Vibration$Status;)V > 31,32 @55 exception:33,
36 = phi  2,31,
39 = getfield < Application, Lcom/android/server/vibrator/VibrationStepConductor, mLock, <Application,Ljava/lang/Object> > 1,
monitorenter 39,
conditional branch(eq, to iindex=-1) 3,5,
40 = getfield < Application, Lcom/android/server/vibrator/VibrationStepConductor, mSignalCancelImmediate, <Primordial,Z> > 1,
conditional branch(ne, to iindex=-1) 40,5,
42 = getfield < Application, Lcom/android/server/vibrator/VibrationStepConductor, mSignalCancel, <Application,Lcom/android/server/vibrator/Vibration$EndInfo> > 1,
conditional branch(eq, to iindex=-1) 42,5,
43 = getfield < Application, Lcom/android/server/vibrator/VibrationStepConductor, mSignalCancelImmediate, <Primordial,Z> > 1,
44 = binaryop(or) 3 , 43,
putfield 1.< Application, Lcom/android/server/vibrator/VibrationStepConductor, mSignalCancelImmediate, <Primordial,Z> > = 44,
conditional branch(ne, to iindex=-1) 42,5,
putfield 1.< Application, Lcom/android/server/vibrator/VibrationStepConductor, mSignalCancel, <Application,Lcom/android/server/vibrator/Vibration$EndInfo> > = 36,
45 = getfield < Application, Lcom/android/server/vibrator/VibrationStepConductor, mLock, <Application,Ljava/lang/Object> > 1,
invokevirtual < Application, Ljava/lang/Object, notify()V > 45 @84 exception:46,
monitorexit 39,
return,
37 = getfield < Application, Lcom/android/server/vibrator/VibratorManagerService, mCurrentExternalVibration, <Application,Lcom/android/server/vibrator/VibratorManagerService$ExternalVibrationHolder> > 1,
conditional branch(eq, to iindex=-1) 37,17,
38 = getfield < Application, Lcom/android/server/vibrator/VibratorManagerService$ExternalVibrationHolder, externalVibration, <Application,Landroid/os/ExternalVibration> > 37,
40 = invokevirtual < Application, Landroid/os/ExternalVibration, getVibrationAttributes()Landroid/os/VibrationAttributes; > 38 @74 exception:39,
2 = new <Application,Landroid/os/VibrationAttributes$Builder>@0,
3 = getfield < Application, Landroid/os/ExternalVibration, mAttrs, <Application,Landroid/media/AudioAttributes> > 1,
invokespecial < Application, Landroid/os/VibrationAttributes$Builder, <init>(Landroid/media/AudioAttributes;)V > 2,3 @4 exception:4,
6 = invokevirtual < Application, Landroid/os/VibrationAttributes$Builder, build()Landroid/os/VibrationAttributes; > 2 @7 exception:5,
2 = new <Application,Landroid/os/VibrationAttributes>@0,
3 = getfield < Application, Landroid/os/VibrationAttributes$Builder, mUsage, <Primordial,I> > 1,
4 = getfield < Application, Landroid/os/VibrationAttributes$Builder, mOriginalAudioUsage, <Primordial,I> > 1,
5 = getfield < Application, Landroid/os/VibrationAttributes$Builder, mFlags, <Primordial,I> > 1,
invokespecial < Application, Landroid/os/VibrationAttributes, <init>(IIILandroid/os/VibrationAttributes-IA;)V > 2,3,4,5,6 @9 exception:7,
return 2,
return 6,
42 = invokevirtual < Application, Lcom/android/server/vibrator/VibratorManagerService, shouldCancelVibration(Landroid/os/VibrationAttributes;I)Z > 1,40,2 @78 exception:41,
5 = invokevirtual < Application, Landroid/os/VibrationAttributes, getUsage()I > 2 @0 exception:4,
2 = getfield < Application, Landroid/os/VibrationAttributes, mUsage, <Primordial,I> > 1,
return 2,
conditional branch(ne, to iindex=-1) 5,7,
9 = invokevirtual < Application, Landroid/os/VibrationAttributes, getUsage()I > 2 @16 exception:8,
2 = getfield < Application, Landroid/os/VibrationAttributes, mUsage, <Primordial,I> > 1,
return 2,
10 = binaryop(and) 9 , 3,
12 = invokevirtual < Application, Landroid/os/VibrationAttributes, getUsage()I > 2 @21 exception:11,
2 = getfield < Application, Landroid/os/VibrationAttributes, mUsage, <Primordial,I> > 1,
return 2,
conditional branch(ne, to iindex=-1) 10,12,
goto (from iindex= 17 to iindex = 2),
13 = phi  6,7,
return 13,
conditional branch(eq, to iindex=-1) 42,17,
43 = getfield < Application, Lcom/android/server/vibrator/VibratorManagerService, mCurrentExternalVibration, <Application,Lcom/android/server/vibrator/VibratorManagerService$ExternalVibrationHolder> > 1,
invokevirtual < Application, Lcom/android/server/vibrator/VibratorManagerService$ExternalVibrationHolder, mute()V > 43 @86 exception:44,
2 = getfield < Application, Lcom/android/server/vibrator/VibratorManagerService$ExternalVibrationHolder, externalVibration, <Application,Landroid/os/ExternalVibration> > 1,
4 = invokevirtual < Application, Landroid/os/ExternalVibration, mute()Z > 2 @2 exception:3,
2 = getfield < Application, Landroid/os/ExternalVibration, mController, <Application,Landroid/os/IExternalVibrationController> > 1,
4 = invokeinterface < Application, Landroid/os/IExternalVibrationController, mute()Z > 2 @2 exception:3,
5 = getCaughtException ,
6 = new <Application,Ljava/lang/StringBuilder>@9,
invokespecial < Application, Ljava/lang/StringBuilder, <init>()V > 6 @11 exception:7,
10 = invokevirtual < Application, Ljava/lang/StringBuilder, append(Ljava/lang/String;)Ljava/lang/StringBuilder; > 6,8 @16 exception:9,
12 = invokevirtual < Application, Ljava/lang/StringBuilder, append(Ljava/lang/Object;)Ljava/lang/StringBuilder; > 10,1 @20 exception:11,
14 = invokevirtual < Application, Ljava/lang/StringBuilder, toString()Ljava/lang/String; > 12 @24 exception:13,
17 = invokestatic < Application, Landroid/util/Slog, wtf(Ljava/lang/String;Ljava/lang/String;Ljava/lang/Throwable;)I > 15,14,5 @30 exception:16,
return 18,
return,
invokevirtual < Application, Lcom/android/server/vibrator/VibratorManagerService, endExternalVibrateLocked(Lcom/android/server/vibrator/Vibration$EndInfo;Z)V > 1,11,17 @89 exception:45,
invokestatic < Application, Landroid/os/Trace, traceBegin(JLjava/lang/String;)V > 4,5 @5 exception:6,
7 = getfield < Application, Lcom/android/server/vibrator/VibratorManagerService, mCurrentExternalVibration, <Application,Lcom/android/server/vibrator/VibratorManagerService$ExternalVibrationHolder> > 1,
conditional branch(ne, to iindex=-1) 7,8,
invokevirtual < Application, Lcom/android/server/vibrator/VibratorManagerService$ExternalVibrationHolder, unlinkToDeath()V > 7 @16 exception:9,
2 = getfield < Application, Lcom/android/server/vibrator/VibratorManagerService$ExternalVibrationHolder, externalVibration, <Application,Landroid/os/ExternalVibration> > 1,
invokevirtual < Application, Landroid/os/ExternalVibration, unlinkToDeath(Landroid/os/IBinder$DeathRecipient;)V > 2,1 @2 exception:3,
return,
conditional branch(ne, to iindex=-1) 3,8,
10 = getfield < Application, Lcom/android/server/vibrator/VibratorManagerService, mCurrentExternalVibration, <Application,Lcom/android/server/vibrator/VibratorManagerService$ExternalVibrationHolder> > 1,
11 = getfield < Application, Lcom/android/server/vibrator/VibratorManagerService$ExternalVibrationHolder, stats, <Application,Lcom/android/server/vibrator/VibrationStats> > 10,
invokevirtual < Application, Lcom/android/server/vibrator/VibratorManagerService, setExternalControl(ZLcom/android/server/vibrator/VibrationStats;)V > 1,8,11 @26 exception:12,
16 = phi  15,4,
5 = getfield < Application, Lcom/android/server/vibrator/VibratorManagerService, mVibrators, <Application,Landroid/util/SparseArray> > 1,
7 = invokevirtual < Application, Landroid/util/SparseArray, size()I > 5 @3 exception:6,
conditional branch(ge, to iindex=-1) 16,7,
return,
16 = getfield < Application, Lcom/android/server/vibrator/VibratorManagerService, mCurrentExternalVibration, <Application,Lcom/android/server/vibrator/VibratorManagerService$ExternalVibrationHolder> > 1,
invokevirtual < Application, Lcom/android/server/vibrator/VibratorManagerService, endVibrationAndWriteStatsLocked(Lcom/android/server/vibrator/VibratorManagerService$ExternalVibrationHolder;Lcom/android/server/vibrator/Vibration$EndInfo;)V > 1,16,2 @31 exception:17,
invokevirtual < Application, Lcom/android/server/vibrator/VibratorManagerService$ExternalVibrationHolder, end(Lcom/android/server/vibrator/Vibration$EndInfo;)V > 2,3 @0 exception:4,
5 = getfield < Application, Lcom/android/server/vibrator/VibratorManagerService$ExternalVibrationHolder, externalVibration, <Application,Landroid/os/ExternalVibration> > 2,
7 = invokevirtual < Application, Landroid/os/ExternalVibration, getUid()I > 5 @5 exception:6,
8 = getfield < Application, Lcom/android/server/vibrator/VibratorManagerService$ExternalVibrationHolder, externalVibration, <Application,Landroid/os/ExternalVibration> > 2,
10 = invokevirtual < Application, Landroid/os/ExternalVibration, getVibrationAttributes()Landroid/os/VibrationAttributes; > 8 @11 exception:9,
11 = getfield < Application, Lcom/android/server/vibrator/Vibration$EndInfo, status, <Application,Lcom/android/server/vibrator/Vibration$Status> > 3,
invokevirtual < Application, Lcom/android/server/vibrator/VibratorManagerService, logVibrationStatus(ILandroid/os/VibrationAttributes;Lcom/android/server/vibrator/Vibration$Status;)V > 1,7,10,11 @17 exception:12,
13 = getfield < Application, Lcom/android/server/vibrator/VibratorManagerService, mVibratorManagerRecords, <Application,Lcom/android/server/vibrator/VibratorManagerService$VibratorManagerRecords> > 1,
invokevirtual < Application, Lcom/android/server/vibrator/VibratorManagerService$VibratorManagerRecords, record(Lcom/android/server/vibrator/VibratorManagerService$ExternalVibrationHolder;)V > 13,2 @22 exception:14,
15 = getfield < Application, Lcom/android/server/vibrator/VibratorManagerService, mFrameworkStatsLogger, <Application,Lcom/android/server/vibrator/VibratorFrameworkStatsLogger> > 1,
17 = invokestatic < Application, Landroid/os/SystemClock, uptimeMillis()J > @27 exception:16,
19 = invokevirtual < Application, Lcom/android/server/vibrator/VibratorManagerService$ExternalVibrationHolder, getStatsInfo(J)Lcom/android/server/vibrator/VibrationStats$StatsInfo; > 2,17 @31 exception:18,
invokevirtual < Application, Lcom/android/server/vibrator/VibratorFrameworkStatsLogger, writeVibrationReportedAsync(Lcom/android/server/vibrator/VibrationStats$StatsInfo;)V > 15,19 @35 exception:20,
return,
putfield 1.< Application, Lcom/android/server/vibrator/VibratorManagerService, mCurrentExternalVibration, <Application,Lcom/android/server/vibrator/VibratorManagerService$ExternalVibrationHolder> > = 8,
invokestatic < Application, Landroid/os/Trace, traceEnd(J)V > 4 @37 exception:24,
return,
invokestatic < Application, Landroid/os/Binder, restoreCallingIdentity(J)V > 15 @92 exception:57,
monitorexit 10,
invokestatic < Application, Landroid/os/Trace, traceEnd(J)V > 5 @96 exception:75,
return,","depth : 0
-----
depth : 1
-----
depth : 1
-----
depth : 2
-----
depth : 1
-----
depth : 2
-----
depth : 2
-----
depth : 1
-----
depth : 2
-----
depth : 1
-----
depth : 2
-----
depth : 1
-----
depth : 2
-----
depth : 1
-----
depth : 2
-----
depth : 2
-----
depth : 2
-----
depth : 1
-----
depth : 2
-----
depth : 1
-----
depth : 2
-----
depth : 2
-----
depth : 2
-----
","public void cancelVibrate(int p1, IBinder p2){
	Vibration$EndInfo v3 = new Vibration$EndInfo(Vibration$Status.CANCELLED_BY_USER);
	long v5 = Binder.clearCallingIdentity();
	if (this.mNextVibration == 0) {
		Vibration v6 = this.mVibration;
		if (Vibration.token != p2) {
			int v9 = Vibration.attrs.getUsage();
			if (v9 != 0) {
				int v10 = Vibration.attrs.getUsage();
				int v11 = Vibration.attrs.getUsage();
				if ((v10 & p2) != v11) {
					boolean v8 = ;
					if (v8 == 0) {
						boolean v7 = ;
						if (v7 == 0) {
							if (this.mNextVibration == 0) {
								Vibration v13 = this.mVibration;
								v13.end(p1);
								VibratorManagerService.logVibrationStatus(Vibration.uid, Vibration.attrs, Vibration$EndInfo.status);
								this.mVibratorManagerRecords.record(v13);
								if (1 == 0) {
									long v18 = SystemClock.uptimeMillis();
									VibrationStats$StatsInfo v19 = v13.getStatsInfo(v18);
									this.mFrameworkStatsLogger.writeVibrationReportedAsync(v19);
									this.mNextVibration = 0;
									if (this.mCurrentVibration == 0) {
										Vibration v21 = this.mCurrentVibration.getVibration();
										if (Vibration.token != p2) {
											int v24 = Vibration.attrs.getUsage();
											if (v24 != 0) {
												int v25 = Vibration.attrs.getUsage();
												int v26 = Vibration.attrs.getUsage();
												if ((v25 & p2) != v26) {
													boolean v23 = ;
													if (v23 == 0) {
														boolean v22 = ;
														if (v22 == 0) {
															if (Build.IS_DEBUGGABLE == 0) {
																Thread v29 = Thread.currentThread();
																if (v29 instanceof VibrationThread == 0) {
																	if (v3 == 0) {
																		String v36 = Vibration$EndInfo.status.name();
																		boolean v37 = v36.startsWith(""CANCEL"");
																		if (v37 != 0) {
																			Vibration$EndInfo v45 = new Vibration$EndInfo(Vibration$Status.CANCELLED_BY_UNKNOWN_REASON);
																			if (0 == 0) {
																				if (this.mSignalCancelImmediate != 0) {
																					if (this.mSignalCancel == 0) {
																						this.mSignalCancelImmediate = (0 | this.mSignalCancelImmediate);
																						if (this.mSignalCancel != 0) {
																							this.mSignalCancel = ;
																							this.mLock.notify();
																							if (this.mCurrentExternalVibration == 0) {
																								VibrationAttributes$Builder v49 = new VibrationAttributes$Builder(this.mAttrs);
																								VibrationAttributes v52 = new VibrationAttributes(this.mUsage,this.mOriginalAudioUsage,this.mFlags,0);
																								VibrationAttributes v51 = v52;
																								VibrationAttributes v48 = v51;
																								int v55 = this.mUsage;
																								if (v55 != 0) {
																									int v56 = this.mUsage;
																									int v57 = this.mUsage;
																									if ((v56 & p1) != v57) {
																										boolean v54 = ;
																										if (v54 == 0) {
																											boolean v60 = this.mController.mute();
																											boolean v59 = 0;
																											Trace.traceBegin(8388608, ""endExternalVibrateLocked"");
																											if (this.mCurrentExternalVibration != 0) {
																												this.externalVibration.unlinkToDeath(VibratorManagerService$ExternalVibrationHolder);
																												if (0 != 0) {
																													int v72 = this.mVibrators.size();
																													if ( >= v72) {
																														this.mCurrentExternalVibration.end(p1);
																														int v75 = VibratorManagerService$ExternalVibrationHolder.externalVibration.getUid();
																														VibrationAttributes v76 = VibratorManagerService$ExternalVibrationHolder.externalVibration.getVibrationAttributes();
																														VibratorManagerService.logVibrationStatus(v75, v76, Vibration$EndInfo.status);
																														this.mVibratorManagerRecords.record(this.mCurrentExternalVibration);
																														long v79 = SystemClock.uptimeMillis();
																														VibrationStats$StatsInfo v80 = this.mCurrentExternalVibration.getStatsInfo(v79);
																														this.mFrameworkStatsLogger.writeVibrationReportedAsync(v80);
																														this.mCurrentExternalVibration = 0;
																														Trace.traceEnd(8388608);
																														Binder.restoreCallingIdentity(v5);
																														Trace.traceEnd(8388608);
																														return;
																													}
																												}
																											}
																										}
																									}
																								}
																							}
																						}
																					}
																				}
																			}
																		}
																	}
																}
															}
														}
													}
												}
											}
										}
									}
								}
							}
						}
					}
				}
			}
		}
	}
}
","NORMAL"

"Lcom/android/server/vibrator/VibratorManagerService","registerVibratorStateListener(ILandroid/os/IVibratorStateListener;)Z","0","4 = getfield < Application, Lcom/android/server/vibrator/VibratorManagerService, mContext, <Application,Landroid/content/Context> > 1,
invokevirtual < Application, Landroid/content/Context, enforceCallingOrSelfPermission(Ljava/lang/String;Ljava/lang/String;)V > 4,5,6 @6 exception:7,
8 = getfield < Application, Lcom/android/server/vibrator/VibratorManagerService, mVibrators, <Application,Landroid/util/SparseArray> > 1,
10 = invokevirtual < Application, Landroid/util/SparseArray, get(I)Ljava/lang/Object; > 8,2 @11 exception:9,
11 = checkcast <Application,Lcom/android/server/vibrator/VibratorController>10 <Application,Lcom/android/server/vibrator/VibratorController>,
conditional branch(ne, to iindex=-1) 11,12,
return 12,","depth : 0
-----
","public boolean registerVibratorStateListener(int p1, IVibratorStateListener p2){
	Object v2 = this.mVibrators.get(p1);
	if (v2 != 0) {
		return 0;
	}
}
","SYS_OR_SIG"
"Lcom/android/server/vibrator/VibratorManagerService","registerVibratorStateListener(ILandroid/os/IVibratorStateListener;)Z","0","4 = getfield < Application, Lcom/android/server/vibrator/VibratorManagerService, mContext, <Application,Landroid/content/Context> > 1,
invokevirtual < Application, Landroid/content/Context, enforceCallingOrSelfPermission(Ljava/lang/String;Ljava/lang/String;)V > 4,5,6 @6 exception:7,
8 = getfield < Application, Lcom/android/server/vibrator/VibratorManagerService, mVibrators, <Application,Landroid/util/SparseArray> > 1,
10 = invokevirtual < Application, Landroid/util/SparseArray, get(I)Ljava/lang/Object; > 8,2 @11 exception:9,
11 = checkcast <Application,Lcom/android/server/vibrator/VibratorController>10 <Application,Lcom/android/server/vibrator/VibratorController>,
conditional branch(ne, to iindex=-1) 11,12,
14 = invokevirtual < Application, Lcom/android/server/vibrator/VibratorController, registerVibratorStateListener(Landroid/os/IVibratorStateListener;)Z > 11,3 @21 exception:13,
return 14,","depth : 0
-----
","public boolean registerVibratorStateListener(int p1, IVibratorStateListener p2){
	Object v2 = this.mVibrators.get(p1);
	if (v2 != 0) {
		boolean v3 = v2.registerVibratorStateListener(p2);
		return v3;
	}
}
","SYS_OR_SIG"
"Lcom/android/server/vibrator/VibratorManagerService","registerVibratorStateListener(ILandroid/os/IVibratorStateListener;)Z","1","4 = getfield < Application, Lcom/android/server/vibrator/VibratorManagerService, mContext, <Application,Landroid/content/Context> > 1,
invokevirtual < Application, Landroid/content/Context, enforceCallingOrSelfPermission(Ljava/lang/String;Ljava/lang/String;)V > 4,5,6 @6 exception:7,
8 = getfield < Application, Lcom/android/server/vibrator/VibratorManagerService, mVibrators, <Application,Landroid/util/SparseArray> > 1,
10 = invokevirtual < Application, Landroid/util/SparseArray, get(I)Ljava/lang/Object; > 8,2 @11 exception:9,
11 = checkcast <Application,Lcom/android/server/vibrator/VibratorController>10 <Application,Lcom/android/server/vibrator/VibratorController>,
conditional branch(ne, to iindex=-1) 11,12,
14 = invokevirtual < Application, Lcom/android/server/vibrator/VibratorController, registerVibratorStateListener(Landroid/os/IVibratorStateListener;)Z > 11,3 @21 exception:13,
4 = invokestatic < Application, Landroid/os/Binder, clearCallingIdentity()J > @0 exception:3,
5 = getfield < Application, Lcom/android/server/vibrator/VibratorController, mLock, <Application,Ljava/lang/Object> > 1,
monitorenter 5,
6 = getfield < Application, Lcom/android/server/vibrator/VibratorController, mVibratorStateListeners, <Application,Landroid/os/RemoteCallbackList> > 1,
8 = invokevirtual < Application, Landroid/os/RemoteCallbackList, register(Landroid/os/IInterface;)Z > 6,2 @9 exception:7,
conditional branch(ne, to iindex=-1) 8,9,
monitorexit 5,
invokestatic < Application, Landroid/os/Binder, restoreCallingIdentity(J)V > 4 @17 exception:24,
return 9,
return 14,","depth : 0
-----
depth : 1
-----
","public boolean registerVibratorStateListener(int p1, IVibratorStateListener p2){
	Object v2 = this.mVibrators.get(p1);
	if (v2 != 0) {
		long v4 = Binder.clearCallingIdentity();
		boolean v5 = this.mVibratorStateListeners.register(p2);
		if (v5 != 0) {
			Binder.restoreCallingIdentity(v4);
			boolean v3 = 0;
			return v3;
		}
	}
}
","SYS_OR_SIG"
"Lcom/android/server/vibrator/VibratorManagerService","registerVibratorStateListener(ILandroid/os/IVibratorStateListener;)Z","1","4 = getfield < Application, Lcom/android/server/vibrator/VibratorManagerService, mContext, <Application,Landroid/content/Context> > 1,
invokevirtual < Application, Landroid/content/Context, enforceCallingOrSelfPermission(Ljava/lang/String;Ljava/lang/String;)V > 4,5,6 @6 exception:7,
8 = getfield < Application, Lcom/android/server/vibrator/VibratorManagerService, mVibrators, <Application,Landroid/util/SparseArray> > 1,
10 = invokevirtual < Application, Landroid/util/SparseArray, get(I)Ljava/lang/Object; > 8,2 @11 exception:9,
11 = checkcast <Application,Lcom/android/server/vibrator/VibratorController>10 <Application,Lcom/android/server/vibrator/VibratorController>,
conditional branch(ne, to iindex=-1) 11,12,
14 = invokevirtual < Application, Lcom/android/server/vibrator/VibratorController, registerVibratorStateListener(Landroid/os/IVibratorStateListener;)Z > 11,3 @21 exception:13,
4 = invokestatic < Application, Landroid/os/Binder, clearCallingIdentity()J > @0 exception:3,
5 = getfield < Application, Lcom/android/server/vibrator/VibratorController, mLock, <Application,Ljava/lang/Object> > 1,
monitorenter 5,
6 = getfield < Application, Lcom/android/server/vibrator/VibratorController, mVibratorStateListeners, <Application,Landroid/os/RemoteCallbackList> > 1,
8 = invokevirtual < Application, Landroid/os/RemoteCallbackList, register(Landroid/os/IInterface;)Z > 6,2 @9 exception:7,
conditional branch(ne, to iindex=-1) 8,9,
10 = getfield < Application, Lcom/android/server/vibrator/VibratorController, mIsVibrating, <Primordial,Z> > 1,
invokevirtual < Application, Lcom/android/server/vibrator/VibratorController, notifyStateListener(Landroid/os/IVibratorStateListener;Z)V > 1,2,10 @23 exception:11,
monitorexit 5,
invokestatic < Application, Landroid/os/Binder, restoreCallingIdentity(J)V > 4 @28 exception:13,
return 12,
return 14,","depth : 0
-----
depth : 1
-----
","public boolean registerVibratorStateListener(int p1, IVibratorStateListener p2){
	Object v2 = this.mVibrators.get(p1);
	if (v2 != 0) {
		long v4 = Binder.clearCallingIdentity();
		boolean v5 = this.mVibratorStateListeners.register(p2);
		if (v5 != 0) {
			VibratorController.notifyStateListener(p2, this.mIsVibrating);
			Binder.restoreCallingIdentity(v4);
			boolean v3 = 1;
			return v3;
		}
	}
}
","SYS_OR_SIG"
"Lcom/android/server/vibrator/VibratorManagerService","registerVibratorStateListener(ILandroid/os/IVibratorStateListener;)Z","2","4 = getfield < Application, Lcom/android/server/vibrator/VibratorManagerService, mContext, <Application,Landroid/content/Context> > 1,
invokevirtual < Application, Landroid/content/Context, enforceCallingOrSelfPermission(Ljava/lang/String;Ljava/lang/String;)V > 4,5,6 @6 exception:7,
8 = getfield < Application, Lcom/android/server/vibrator/VibratorManagerService, mVibrators, <Application,Landroid/util/SparseArray> > 1,
10 = invokevirtual < Application, Landroid/util/SparseArray, get(I)Ljava/lang/Object; > 8,2 @11 exception:9,
11 = checkcast <Application,Lcom/android/server/vibrator/VibratorController>10 <Application,Lcom/android/server/vibrator/VibratorController>,
conditional branch(ne, to iindex=-1) 11,12,
14 = invokevirtual < Application, Lcom/android/server/vibrator/VibratorController, registerVibratorStateListener(Landroid/os/IVibratorStateListener;)Z > 11,3 @21 exception:13,
4 = invokestatic < Application, Landroid/os/Binder, clearCallingIdentity()J > @0 exception:3,
5 = getfield < Application, Lcom/android/server/vibrator/VibratorController, mLock, <Application,Ljava/lang/Object> > 1,
monitorenter 5,
6 = getfield < Application, Lcom/android/server/vibrator/VibratorController, mVibratorStateListeners, <Application,Landroid/os/RemoteCallbackList> > 1,
8 = invokevirtual < Application, Landroid/os/RemoteCallbackList, register(Landroid/os/IInterface;)Z > 6,2 @9 exception:7,
conditional branch(ne, to iindex=-1) 8,9,
10 = getfield < Application, Lcom/android/server/vibrator/VibratorController, mIsVibrating, <Primordial,Z> > 1,
invokevirtual < Application, Lcom/android/server/vibrator/VibratorController, notifyStateListener(Landroid/os/IVibratorStateListener;Z)V > 1,2,10 @23 exception:11,
invokeinterface < Application, Landroid/os/IVibratorStateListener, onVibrating(Z)V > 2,3 @0 exception:4,
goto (from iindex= 1 to iindex = 9),
return,
monitorexit 5,
invokestatic < Application, Landroid/os/Binder, restoreCallingIdentity(J)V > 4 @28 exception:13,
return 12,
return 14,","depth : 0
-----
depth : 1
-----
depth : 2
-----
","public boolean registerVibratorStateListener(int p1, IVibratorStateListener p2){
	Object v2 = this.mVibrators.get(p1);
	if (v2 != 0) {
		long v4 = Binder.clearCallingIdentity();
		boolean v5 = this.mVibratorStateListeners.register(p2);
		if (v5 != 0) {
			p1.onVibrating(this.mIsVibrating);
			Binder.restoreCallingIdentity(v4);
			boolean v3 = 1;
			return v3;
		}
	}
}
","SYS_OR_SIG"

"Lcom/android/server/vibrator/VibratorManagerService","unregisterVibratorStateListener(ILandroid/os/IVibratorStateListener;)Z","0","4 = getfield < Application, Lcom/android/server/vibrator/VibratorManagerService, mContext, <Application,Landroid/content/Context> > 1,
invokevirtual < Application, Landroid/content/Context, enforceCallingOrSelfPermission(Ljava/lang/String;Ljava/lang/String;)V > 4,5,6 @6 exception:7,
8 = getfield < Application, Lcom/android/server/vibrator/VibratorManagerService, mVibrators, <Application,Landroid/util/SparseArray> > 1,
10 = invokevirtual < Application, Landroid/util/SparseArray, get(I)Ljava/lang/Object; > 8,2 @11 exception:9,
11 = checkcast <Application,Lcom/android/server/vibrator/VibratorController>10 <Application,Lcom/android/server/vibrator/VibratorController>,
conditional branch(ne, to iindex=-1) 11,12,
return 12,","depth : 0
-----
","public boolean unregisterVibratorStateListener(int p1, IVibratorStateListener p2){
	Object v2 = this.mVibrators.get(p1);
	if (v2 != 0) {
		return 0;
	}
}
","SYS_OR_SIG"
"Lcom/android/server/vibrator/VibratorManagerService","unregisterVibratorStateListener(ILandroid/os/IVibratorStateListener;)Z","0","4 = getfield < Application, Lcom/android/server/vibrator/VibratorManagerService, mContext, <Application,Landroid/content/Context> > 1,
invokevirtual < Application, Landroid/content/Context, enforceCallingOrSelfPermission(Ljava/lang/String;Ljava/lang/String;)V > 4,5,6 @6 exception:7,
8 = getfield < Application, Lcom/android/server/vibrator/VibratorManagerService, mVibrators, <Application,Landroid/util/SparseArray> > 1,
10 = invokevirtual < Application, Landroid/util/SparseArray, get(I)Ljava/lang/Object; > 8,2 @11 exception:9,
11 = checkcast <Application,Lcom/android/server/vibrator/VibratorController>10 <Application,Lcom/android/server/vibrator/VibratorController>,
conditional branch(ne, to iindex=-1) 11,12,
14 = invokevirtual < Application, Lcom/android/server/vibrator/VibratorController, unregisterVibratorStateListener(Landroid/os/IVibratorStateListener;)Z > 11,3 @21 exception:13,
return 14,","depth : 0
-----
","public boolean unregisterVibratorStateListener(int p1, IVibratorStateListener p2){
	Object v2 = this.mVibrators.get(p1);
	if (v2 != 0) {
		boolean v3 = v2.unregisterVibratorStateListener(p2);
		return v3;
	}
}
","SYS_OR_SIG"
"Lcom/android/server/vibrator/VibratorManagerService","unregisterVibratorStateListener(ILandroid/os/IVibratorStateListener;)Z","1","4 = getfield < Application, Lcom/android/server/vibrator/VibratorManagerService, mContext, <Application,Landroid/content/Context> > 1,
invokevirtual < Application, Landroid/content/Context, enforceCallingOrSelfPermission(Ljava/lang/String;Ljava/lang/String;)V > 4,5,6 @6 exception:7,
8 = getfield < Application, Lcom/android/server/vibrator/VibratorManagerService, mVibrators, <Application,Landroid/util/SparseArray> > 1,
10 = invokevirtual < Application, Landroid/util/SparseArray, get(I)Ljava/lang/Object; > 8,2 @11 exception:9,
11 = checkcast <Application,Lcom/android/server/vibrator/VibratorController>10 <Application,Lcom/android/server/vibrator/VibratorController>,
conditional branch(ne, to iindex=-1) 11,12,
14 = invokevirtual < Application, Lcom/android/server/vibrator/VibratorController, unregisterVibratorStateListener(Landroid/os/IVibratorStateListener;)Z > 11,3 @21 exception:13,
4 = invokestatic < Application, Landroid/os/Binder, clearCallingIdentity()J > @0 exception:3,
5 = getfield < Application, Lcom/android/server/vibrator/VibratorController, mVibratorStateListeners, <Application,Landroid/os/RemoteCallbackList> > 1,
7 = invokevirtual < Application, Landroid/os/RemoteCallbackList, unregister(Landroid/os/IInterface;)Z > 5,2 @6 exception:6,
invokestatic < Application, Landroid/os/Binder, restoreCallingIdentity(J)V > 4 @10 exception:12,
return 7,
return 14,","depth : 0
-----
depth : 1
-----
","public boolean unregisterVibratorStateListener(int p1, IVibratorStateListener p2){
	Object v2 = this.mVibrators.get(p1);
	if (v2 != 0) {
		long v4 = Binder.clearCallingIdentity();
		boolean v5 = this.mVibratorStateListeners.unregister(p2);
		Binder.restoreCallingIdentity(v4);
		boolean v3 = v5;
		return v3;
	}
}
","SYS_OR_SIG"

"Lcom/android/server/vibrator/VibratorManagerService","getVibratorInfo(I)Landroid/os/VibratorInfo;","0","3 = getfield < Application, Lcom/android/server/vibrator/VibratorManagerService, mVibrators, <Application,Landroid/util/SparseArray> > 1,
5 = invokevirtual < Application, Landroid/util/SparseArray, get(I)Ljava/lang/Object; > 3,2 @2 exception:4,
6 = checkcast <Application,Lcom/android/server/vibrator/VibratorController>5 <Application,Lcom/android/server/vibrator/VibratorController>,
conditional branch(ne, to iindex=-1) 6,7,
return 7,","depth : 0
-----
","public VibratorInfo getVibratorInfo(int p1){
	Object v1 = this.mVibrators.get(p1);
	if (v1 != 0) {
		return 0;
	}
}
","NONE"
"Lcom/android/server/vibrator/VibratorManagerService","getVibratorInfo(I)Landroid/os/VibratorInfo;","0","3 = getfield < Application, Lcom/android/server/vibrator/VibratorManagerService, mVibrators, <Application,Landroid/util/SparseArray> > 1,
5 = invokevirtual < Application, Landroid/util/SparseArray, get(I)Ljava/lang/Object; > 3,2 @2 exception:4,
6 = checkcast <Application,Lcom/android/server/vibrator/VibratorController>5 <Application,Lcom/android/server/vibrator/VibratorController>,
conditional branch(ne, to iindex=-1) 6,7,
9 = invokevirtual < Application, Lcom/android/server/vibrator/VibratorController, getVibratorInfo()Landroid/os/VibratorInfo; > 6 @12 exception:8,
10 = getfield < Application, Lcom/android/server/vibrator/VibratorManagerService, mLock, <Application,Ljava/lang/Object> > 1,
monitorenter 10,
11 = getfield < Application, Lcom/android/server/vibrator/VibratorManagerService, mServiceReady, <Primordial,Z> > 1,
conditional branch(eq, to iindex=-1) 11,7,
monitorexit 10,
13 = invokevirtual < Application, Lcom/android/server/vibrator/VibratorController, isVibratorInfoLoadSuccessful()Z > 6 @26 exception:12,
conditional branch(eq, to iindex=-1) 13,7,
14 = phi  7,9,
return 14,","depth : 0
-----
","public VibratorInfo getVibratorInfo(int p1){
	Object v1 = this.mVibrators.get(p1);
	if (v1 != 0) {
		VibratorInfo v2 = v1.getVibratorInfo();
		if (this.mServiceReady == 0) {
			boolean v3 = v1.isVibratorInfoLoadSuccessful();
			if (v3 == 0) {
				return ;
			}
		}
	}
}
","NONE"
"Lcom/android/server/vibrator/VibratorManagerService","getVibratorInfo(I)Landroid/os/VibratorInfo;","1","3 = getfield < Application, Lcom/android/server/vibrator/VibratorManagerService, mVibrators, <Application,Landroid/util/SparseArray> > 1,
5 = invokevirtual < Application, Landroid/util/SparseArray, get(I)Ljava/lang/Object; > 3,2 @2 exception:4,
6 = checkcast <Application,Lcom/android/server/vibrator/VibratorController>5 <Application,Lcom/android/server/vibrator/VibratorController>,
conditional branch(ne, to iindex=-1) 6,7,
9 = invokevirtual < Application, Lcom/android/server/vibrator/VibratorController, getVibratorInfo()Landroid/os/VibratorInfo; > 6 @12 exception:8,
2 = getfield < Application, Lcom/android/server/vibrator/VibratorController, mVibratorInfo, <Application,Landroid/os/VibratorInfo> > 1,
return 2,
10 = getfield < Application, Lcom/android/server/vibrator/VibratorManagerService, mLock, <Application,Ljava/lang/Object> > 1,
monitorenter 10,
11 = getfield < Application, Lcom/android/server/vibrator/VibratorManagerService, mServiceReady, <Primordial,Z> > 1,
conditional branch(eq, to iindex=-1) 11,7,
monitorexit 10,
13 = invokevirtual < Application, Lcom/android/server/vibrator/VibratorController, isVibratorInfoLoadSuccessful()Z > 6 @26 exception:12,
2 = getfield < Application, Lcom/android/server/vibrator/VibratorController, mVibratorInfoLoadSuccessful, <Primordial,Z> > 1,
return 2,
conditional branch(eq, to iindex=-1) 13,7,
14 = phi  7,9,
return 14,","depth : 0
-----
depth : 1
-----
depth : 1
-----
","public VibratorInfo getVibratorInfo(int p1){
	Object v1 = this.mVibrators.get(p1);
	if (v1 != 0) {
		VibratorInfo v2 = this.mVibratorInfo;
		if (this.mServiceReady == 0) {
			boolean v3 = this.mVibratorInfoLoadSuccessful;
			if (v3 == 0) {
				return ;
			}
		}
	}
}
","NONE"

"Lcom/android/server/vibrator/VibratorManagerService","setAlwaysOnEffect(ILjava/lang/String;ILandroid/os/CombinedVibration;Landroid/os/VibrationAttributes;)Z","0","invokestatic < Application, Landroid/os/Trace, traceBegin(JLjava/lang/String;)V > 8,7 @10 exception:9,
10 = getfield < Application, Lcom/android/server/vibrator/VibratorManagerService, mContext, <Application,Landroid/content/Context> > 1,
invokevirtual < Application, Landroid/content/Context, enforceCallingOrSelfPermission(Ljava/lang/String;Ljava/lang/String;)V > 10,11,7 @19 exception:12,
conditional branch(ne, to iindex=-1) 5,14,
16 = invokestatic < Application, Lcom/android/server/vibrator/VibratorManagerService, isEffectValid(Landroid/os/CombinedVibration;)Z > 5 @49 exception:15,
conditional branch(ne, to iindex=-1) 16,14,
18 = invokevirtual < Application, Lcom/android/server/vibrator/VibratorManagerService, fixupVibrationAttributes(Landroid/os/VibrationAttributes;Landroid/os/CombinedVibration;)Landroid/os/VibrationAttributes; > 1,6,5 @62 exception:17,
19 = getfield < Application, Lcom/android/server/vibrator/VibratorManagerService, mLock, <Application,Ljava/lang/Object> > 1,
monitorenter 19,
21 = invokevirtual < Application, Lcom/android/server/vibrator/VibratorManagerService, fixupAlwaysOnEffectsLocked(Landroid/os/CombinedVibration;)Landroid/util/SparseArray; > 1,5 @69 exception:20,
conditional branch(ne, to iindex=-1) 21,14,
22 = new <Application,Lcom/android/server/vibrator/VibratorManagerService$AlwaysOnVibration>@80,
invokespecial < Application, Lcom/android/server/vibrator/VibratorManagerService$AlwaysOnVibration, <init>(IILjava/lang/String;Landroid/os/VibrationAttributes;Landroid/util/SparseArray;)V > 22,4,2,3,18,21 @87 exception:23,
24 = getfield < Application, Lcom/android/server/vibrator/VibratorManagerService, mAlwaysOnEffects, <Application,Landroid/util/SparseArray> > 1,
invokevirtual < Application, Landroid/util/SparseArray, put(ILjava/lang/Object;)V > 24,4,22 @92 exception:25,
invokevirtual < Application, Lcom/android/server/vibrator/VibratorManagerService, updateAlwaysOnLocked(Lcom/android/server/vibrator/VibratorManagerService$AlwaysOnVibration;)V > 1,22 @95 exception:26,
monitorexit 19,
invokestatic < Application, Landroid/os/Trace, traceEnd(J)V > 8 @99 exception:27,
return 13,","depth : 0
-----
","public boolean setAlwaysOnEffect(int p1, String p2, int p3, CombinedVibration p4, VibrationAttributes p5){
	if (p4 != 0) {
		boolean v3 = VibratorManagerService.isEffectValid(p4);
		if (v3 != 0) {
			VibrationAttributes v4 = p0.fixupVibrationAttributes(p5, p4);
			SparseArray v5 = p0.fixupAlwaysOnEffectsLocked(p4);
			if (v5 != 0) {
				VibratorManagerService$AlwaysOnVibration v6 = new VibratorManagerService$AlwaysOnVibration(p3,p1,p2,v4,v5);
				this.mAlwaysOnEffects.put(p3, v6);
				p0.updateAlwaysOnLocked(v6);
				Trace.traceEnd(8388608);
				return 1;
			}
		}
	}
}
","SYS_OR_SIG"
"Lcom/android/server/vibrator/VibratorManagerService","setAlwaysOnEffect(ILjava/lang/String;ILandroid/os/CombinedVibration;Landroid/os/VibrationAttributes;)Z","1","invokestatic < Application, Landroid/os/Trace, traceBegin(JLjava/lang/String;)V > 8,7 @10 exception:9,
10 = getfield < Application, Lcom/android/server/vibrator/VibratorManagerService, mContext, <Application,Landroid/content/Context> > 1,
invokevirtual < Application, Landroid/content/Context, enforceCallingOrSelfPermission(Ljava/lang/String;Ljava/lang/String;)V > 10,11,7 @19 exception:12,
conditional branch(ne, to iindex=-1) 5,14,
16 = invokestatic < Application, Lcom/android/server/vibrator/VibratorManagerService, isEffectValid(Landroid/os/CombinedVibration;)Z > 5 @49 exception:15,
conditional branch(ne, to iindex=-1) 16,14,
18 = invokevirtual < Application, Lcom/android/server/vibrator/VibratorManagerService, fixupVibrationAttributes(Landroid/os/VibrationAttributes;Landroid/os/CombinedVibration;)Landroid/os/VibrationAttributes; > 1,6,5 @62 exception:17,
conditional branch(ne, to iindex=-1) 2,4,
5 = getstatic < Application, Lcom/android/server/vibrator/VibratorManagerService, DEFAULT_ATTRIBUTES, <Application,Landroid/os/VibrationAttributes> >,
6 = phi  2,5,
8 = invokevirtual < Application, Landroid/os/VibrationAttributes, getUsage()I > 6 @4 exception:7,
conditional branch(ne, to iindex=-1) 8,4,
conditional branch(eq, to iindex=-1) 3,4,
10 = invokevirtual < Application, Landroid/os/CombinedVibration, isHapticFeedbackCandidate()Z > 3 @12 exception:9,
conditional branch(eq, to iindex=-1) 10,4,
12 = phi  8,8,8,11,
17 = invokevirtual < Application, Landroid/os/VibrationAttributes, getFlags()I > 6 @20 exception:16,
19 = binaryop(and) 17 , 18,
conditional branch(eq, to iindex=-1) 19,4,
22 = invokevirtual < Application, Lcom/android/server/vibrator/VibratorManagerService, hasPermission(Ljava/lang/String;)Z > 1,20 @30 exception:21,
conditional branch(ne, to iindex=-1) 22,4,
25 = invokevirtual < Application, Lcom/android/server/vibrator/VibratorManagerService, hasPermission(Ljava/lang/String;)Z > 1,23 @38 exception:24,
conditional branch(ne, to iindex=-1) 25,4,
28 = invokevirtual < Application, Lcom/android/server/vibrator/VibratorManagerService, hasPermission(Ljava/lang/String;)Z > 1,26 @46 exception:27,
conditional branch(ne, to iindex=-1) 28,4,
30 = binaryop(and) 17 , 29,
33 = phi  17,17,17,17,30,
37 = invokevirtual < Application, Landroid/os/VibrationAttributes, getUsage()I > 6 @54 exception:36,
conditional branch(ne, to iindex=-1) 12,37,
39 = invokevirtual < Application, Landroid/os/VibrationAttributes, getFlags()I > 6 @60 exception:38,
conditional branch(ne, to iindex=-1) 33,39,
43 = new <Application,Landroid/os/VibrationAttributes$Builder>@67,
invokespecial < Application, Landroid/os/VibrationAttributes$Builder, <init>(Landroid/os/VibrationAttributes;)V > 43,6 @69 exception:44,
46 = invokevirtual < Application, Landroid/os/VibrationAttributes$Builder, setUsage(I)Landroid/os/VibrationAttributes$Builder; > 43,12 @72 exception:45,
48 = invokevirtual < Application, Landroid/os/VibrationAttributes, getFlags()I > 6 @76 exception:47,
50 = invokevirtual < Application, Landroid/os/VibrationAttributes$Builder, setFlags(II)Landroid/os/VibrationAttributes$Builder; > 46,33,48 @80 exception:49,
52 = invokevirtual < Application, Landroid/os/VibrationAttributes$Builder, build()Landroid/os/VibrationAttributes; > 50 @84 exception:51,
return 52,
19 = getfield < Application, Lcom/android/server/vibrator/VibratorManagerService, mLock, <Application,Ljava/lang/Object> > 1,
monitorenter 19,
21 = invokevirtual < Application, Lcom/android/server/vibrator/VibratorManagerService, fixupAlwaysOnEffectsLocked(Landroid/os/CombinedVibration;)Landroid/util/SparseArray; > 1,5 @69 exception:20,
invokestatic < Application, Landroid/os/Trace, traceBegin(JLjava/lang/String;)V > 3,4 @5 exception:5,
6 = instanceof 2 <Application,Landroid/os/CombinedVibration$Mono>,
conditional branch(eq, to iindex=-1) 6,7,
13 = checkcast <Application,Landroid/os/CombinedVibration$Mono>2 <Application,Landroid/os/CombinedVibration$Mono>,
15 = invokevirtual < Application, Landroid/os/CombinedVibration$Mono, getEffect()Landroid/os/VibrationEffect; > 13 @15 exception:14,
16 = new <Application,Lcom/android/server/vibrator/VibratorManagerService$$ExternalSyntheticLambda2>@19,
invokespecial < Application, Lcom/android/server/vibrator/VibratorManagerService$$ExternalSyntheticLambda2, <init>(Landroid/os/VibrationEffect;)V > 16,15 @21 exception:17,
19 = invokevirtual < Application, Lcom/android/server/vibrator/VibratorManagerService, transformAllVibratorsLocked(Ljava/util/function/Function;)Landroid/util/SparseArray; > 1,16 @24 exception:18,
goto (from iindex= 13 to iindex = 11),
21 = phi  19,12,
24 = new <Application,Landroid/util/SparseArray>@39,
invokespecial < Application, Landroid/util/SparseArray, <init>()V > 24 @41 exception:25,
48 = phi  47,7,
27 = invokevirtual < Application, Landroid/util/SparseArray, size()I > 21 @45 exception:26,
conditional branch(ge, to iindex=-1) 48,27,
52 = invokevirtual < Application, Landroid/util/SparseArray, size()I > 24 @102 exception:51,
conditional branch(ne, to iindex=-1) 52,7,
invokestatic < Application, Landroid/os/Trace, traceEnd(J)V > 3 @108 exception:54,
return 7,
conditional branch(ne, to iindex=-1) 21,14,
22 = new <Application,Lcom/android/server/vibrator/VibratorManagerService$AlwaysOnVibration>@80,
invokespecial < Application, Lcom/android/server/vibrator/VibratorManagerService$AlwaysOnVibration, <init>(IILjava/lang/String;Landroid/os/VibrationAttributes;Landroid/util/SparseArray;)V > 22,4,2,3,18,21 @87 exception:23,
24 = getfield < Application, Lcom/android/server/vibrator/VibratorManagerService, mAlwaysOnEffects, <Application,Landroid/util/SparseArray> > 1,
invokevirtual < Application, Landroid/util/SparseArray, put(ILjava/lang/Object;)V > 24,4,22 @92 exception:25,
invokevirtual < Application, Lcom/android/server/vibrator/VibratorManagerService, updateAlwaysOnLocked(Lcom/android/server/vibrator/VibratorManagerService$AlwaysOnVibration;)V > 1,22 @95 exception:26,
41 = phi  40,3,
4 = getfield < Application, Lcom/android/server/vibrator/VibratorManagerService$AlwaysOnVibration, effects, <Application,Landroid/util/SparseArray> > 2,
6 = invokevirtual < Application, Landroid/util/SparseArray, size()I > 4 @4 exception:5,
conditional branch(ge, to iindex=-1) 41,6,
return,
monitorexit 19,
invokestatic < Application, Landroid/os/Trace, traceEnd(J)V > 8 @99 exception:27,
return 13,","depth : 0
-----
depth : 1
-----
depth : 1
-----
depth : 1
-----
","public boolean setAlwaysOnEffect(int p1, String p2, int p3, CombinedVibration p4, VibrationAttributes p5){
	if (p4 != 0) {
		boolean v3 = VibratorManagerService.isEffectValid(p4);
		if (v3 != 0) {
			if (p5 != 0) {
				int v5 = .getUsage();
				if (v5 != 0) {
					if (p4 == 0) {
						boolean v6 = p4.isHapticFeedbackCandidate();
						if (v6 == 0) {
							int v7 = .getFlags();
							if ((v7 & 3) == 0) {
								if (v8 != 0) {
									if (v9 != 0) {
										if (v10 != 0) {
											int v11 = .getUsage();
											if ( != v11) {
												int v12 = .getFlags();
												if ( != v12) {
													VibrationAttributes$Builder v13 = new VibrationAttributes$Builder();
													VibrationAttributes$Builder v15 = v13.setUsage();
													int v16 = .getFlags();
													VibrationAttributes$Builder v17 = v15.setFlags(, v16);
													VibrationAttributes v18 = v17.build();
													VibrationAttributes v4 = v18;
													Trace.traceBegin(8388608, ""fixupAlwaysOnEffectsLocked"");
													if (p4 instanceof CombinedVibration$Mono == 0) {
														VibrationEffect v21 = p4.getEffect();
														VibratorManagerService$$ExternalSyntheticLambda2 v22 = new VibratorManagerService$$ExternalSyntheticLambda2(v21);
														SparseArray v24 = VibratorManagerService.transformAllVibratorsLocked(v22);
														SparseArray v25 = new SparseArray();
														int v27 = .size();
														if ( >= v27) {
															int v28 = v25.size();
															if (v28 != 0) {
																Trace.traceEnd(8388608);
																SparseArray v19 = 0;
																if (v19 != 0) {
																	VibratorManagerService$AlwaysOnVibration v30 = new VibratorManagerService$AlwaysOnVibration(p3,p1,p2,v4,v19);
																	this.mAlwaysOnEffects.put(p3, v30);
																	int v34 = VibratorManagerService$AlwaysOnVibration.effects.size();
																	if ( >= v34) {
																		Trace.traceEnd(8388608);
																		return 1;
																	}
																}
															}
														}
													}
												}
											}
										}
									}
								}
							}
						}
					}
				}
			}
		}
	}
}
","SYS_OR_SIG"
"Lcom/android/server/vibrator/VibratorManagerService","setAlwaysOnEffect(ILjava/lang/String;ILandroid/os/CombinedVibration;Landroid/os/VibrationAttributes;)Z","1","invokestatic < Application, Landroid/os/Trace, traceBegin(JLjava/lang/String;)V > 8,7 @10 exception:9,
10 = getfield < Application, Lcom/android/server/vibrator/VibratorManagerService, mContext, <Application,Landroid/content/Context> > 1,
invokevirtual < Application, Landroid/content/Context, enforceCallingOrSelfPermission(Ljava/lang/String;Ljava/lang/String;)V > 10,11,7 @19 exception:12,
conditional branch(ne, to iindex=-1) 5,14,
16 = invokestatic < Application, Lcom/android/server/vibrator/VibratorManagerService, isEffectValid(Landroid/os/CombinedVibration;)Z > 5 @49 exception:15,
conditional branch(ne, to iindex=-1) 16,14,
18 = invokevirtual < Application, Lcom/android/server/vibrator/VibratorManagerService, fixupVibrationAttributes(Landroid/os/VibrationAttributes;Landroid/os/CombinedVibration;)Landroid/os/VibrationAttributes; > 1,6,5 @62 exception:17,
conditional branch(ne, to iindex=-1) 2,4,
5 = getstatic < Application, Lcom/android/server/vibrator/VibratorManagerService, DEFAULT_ATTRIBUTES, <Application,Landroid/os/VibrationAttributes> >,
6 = phi  2,5,
8 = invokevirtual < Application, Landroid/os/VibrationAttributes, getUsage()I > 6 @4 exception:7,
conditional branch(ne, to iindex=-1) 8,4,
conditional branch(eq, to iindex=-1) 3,4,
10 = invokevirtual < Application, Landroid/os/CombinedVibration, isHapticFeedbackCandidate()Z > 3 @12 exception:9,
conditional branch(eq, to iindex=-1) 10,4,
12 = phi  8,8,8,11,
17 = invokevirtual < Application, Landroid/os/VibrationAttributes, getFlags()I > 6 @20 exception:16,
19 = binaryop(and) 17 , 18,
conditional branch(eq, to iindex=-1) 19,4,
22 = invokevirtual < Application, Lcom/android/server/vibrator/VibratorManagerService, hasPermission(Ljava/lang/String;)Z > 1,20 @30 exception:21,
conditional branch(ne, to iindex=-1) 22,4,
25 = invokevirtual < Application, Lcom/android/server/vibrator/VibratorManagerService, hasPermission(Ljava/lang/String;)Z > 1,23 @38 exception:24,
conditional branch(ne, to iindex=-1) 25,4,
28 = invokevirtual < Application, Lcom/android/server/vibrator/VibratorManagerService, hasPermission(Ljava/lang/String;)Z > 1,26 @46 exception:27,
conditional branch(ne, to iindex=-1) 28,4,
30 = binaryop(and) 17 , 29,
33 = phi  17,17,17,17,30,
37 = invokevirtual < Application, Landroid/os/VibrationAttributes, getUsage()I > 6 @54 exception:36,
conditional branch(ne, to iindex=-1) 12,37,
39 = invokevirtual < Application, Landroid/os/VibrationAttributes, getFlags()I > 6 @60 exception:38,
conditional branch(ne, to iindex=-1) 33,39,
43 = new <Application,Landroid/os/VibrationAttributes$Builder>@67,
invokespecial < Application, Landroid/os/VibrationAttributes$Builder, <init>(Landroid/os/VibrationAttributes;)V > 43,6 @69 exception:44,
46 = invokevirtual < Application, Landroid/os/VibrationAttributes$Builder, setUsage(I)Landroid/os/VibrationAttributes$Builder; > 43,12 @72 exception:45,
48 = invokevirtual < Application, Landroid/os/VibrationAttributes, getFlags()I > 6 @76 exception:47,
50 = invokevirtual < Application, Landroid/os/VibrationAttributes$Builder, setFlags(II)Landroid/os/VibrationAttributes$Builder; > 46,33,48 @80 exception:49,
52 = invokevirtual < Application, Landroid/os/VibrationAttributes$Builder, build()Landroid/os/VibrationAttributes; > 50 @84 exception:51,
return 52,
19 = getfield < Application, Lcom/android/server/vibrator/VibratorManagerService, mLock, <Application,Ljava/lang/Object> > 1,
monitorenter 19,
21 = invokevirtual < Application, Lcom/android/server/vibrator/VibratorManagerService, fixupAlwaysOnEffectsLocked(Landroid/os/CombinedVibration;)Landroid/util/SparseArray; > 1,5 @69 exception:20,
invokestatic < Application, Landroid/os/Trace, traceBegin(JLjava/lang/String;)V > 3,4 @5 exception:5,
6 = instanceof 2 <Application,Landroid/os/CombinedVibration$Mono>,
conditional branch(eq, to iindex=-1) 6,7,
13 = checkcast <Application,Landroid/os/CombinedVibration$Mono>2 <Application,Landroid/os/CombinedVibration$Mono>,
15 = invokevirtual < Application, Landroid/os/CombinedVibration$Mono, getEffect()Landroid/os/VibrationEffect; > 13 @15 exception:14,
16 = new <Application,Lcom/android/server/vibrator/VibratorManagerService$$ExternalSyntheticLambda2>@19,
invokespecial < Application, Lcom/android/server/vibrator/VibratorManagerService$$ExternalSyntheticLambda2, <init>(Landroid/os/VibrationEffect;)V > 16,15 @21 exception:17,
19 = invokevirtual < Application, Lcom/android/server/vibrator/VibratorManagerService, transformAllVibratorsLocked(Ljava/util/function/Function;)Landroid/util/SparseArray; > 1,16 @24 exception:18,
goto (from iindex= 13 to iindex = 11),
21 = phi  19,12,
24 = new <Application,Landroid/util/SparseArray>@39,
invokespecial < Application, Landroid/util/SparseArray, <init>()V > 24 @41 exception:25,
48 = phi  47,7,
27 = invokevirtual < Application, Landroid/util/SparseArray, size()I > 21 @45 exception:26,
conditional branch(ge, to iindex=-1) 48,27,
52 = invokevirtual < Application, Landroid/util/SparseArray, size()I > 24 @102 exception:51,
conditional branch(ne, to iindex=-1) 52,7,
invokestatic < Application, Landroid/os/Trace, traceEnd(J)V > 3 @108 exception:54,
return 7,
conditional branch(ne, to iindex=-1) 21,14,
monitorexit 19,
invokestatic < Application, Landroid/os/Trace, traceEnd(J)V > 8 @76 exception:35,
return 14,","depth : 0
-----
depth : 1
-----
depth : 1
-----
","public boolean setAlwaysOnEffect(int p1, String p2, int p3, CombinedVibration p4, VibrationAttributes p5){
	if (p4 != 0) {
		boolean v3 = VibratorManagerService.isEffectValid(p4);
		if (v3 != 0) {
			if (p5 != 0) {
				int v5 = .getUsage();
				if (v5 != 0) {
					if (p4 == 0) {
						boolean v6 = p4.isHapticFeedbackCandidate();
						if (v6 == 0) {
							int v7 = .getFlags();
							if ((v7 & 3) == 0) {
								if (v8 != 0) {
									if (v9 != 0) {
										if (v10 != 0) {
											int v11 = .getUsage();
											if ( != v11) {
												int v12 = .getFlags();
												if ( != v12) {
													VibrationAttributes$Builder v13 = new VibrationAttributes$Builder();
													VibrationAttributes$Builder v15 = v13.setUsage();
													int v16 = .getFlags();
													VibrationAttributes$Builder v17 = v15.setFlags(, v16);
													VibrationAttributes v18 = v17.build();
													VibrationAttributes v4 = v18;
													Trace.traceBegin(8388608, ""fixupAlwaysOnEffectsLocked"");
													if (p4 instanceof CombinedVibration$Mono == 0) {
														VibrationEffect v21 = p4.getEffect();
														VibratorManagerService$$ExternalSyntheticLambda2 v22 = new VibratorManagerService$$ExternalSyntheticLambda2(v21);
														SparseArray v24 = VibratorManagerService.transformAllVibratorsLocked(v22);
														SparseArray v25 = new SparseArray();
														int v27 = .size();
														if ( >= v27) {
															int v28 = v25.size();
															if (v28 != 0) {
																Trace.traceEnd(8388608);
																SparseArray v19 = 0;
																if (v19 != 0) {
																	Trace.traceEnd(8388608);
																	return 0;
																}
															}
														}
													}
												}
											}
										}
									}
								}
							}
						}
					}
				}
			}
		}
	}
}
","SYS_OR_SIG"
"Lcom/android/server/vibrator/VibratorManagerService","setAlwaysOnEffect(ILjava/lang/String;ILandroid/os/CombinedVibration;Landroid/os/VibrationAttributes;)Z","2","invokestatic < Application, Landroid/os/Trace, traceBegin(JLjava/lang/String;)V > 8,7 @10 exception:9,
10 = getfield < Application, Lcom/android/server/vibrator/VibratorManagerService, mContext, <Application,Landroid/content/Context> > 1,
invokevirtual < Application, Landroid/content/Context, enforceCallingOrSelfPermission(Ljava/lang/String;Ljava/lang/String;)V > 10,11,7 @19 exception:12,
conditional branch(ne, to iindex=-1) 5,14,
16 = invokestatic < Application, Lcom/android/server/vibrator/VibratorManagerService, isEffectValid(Landroid/os/CombinedVibration;)Z > 5 @49 exception:15,
conditional branch(ne, to iindex=-1) 16,14,
18 = invokevirtual < Application, Lcom/android/server/vibrator/VibratorManagerService, fixupVibrationAttributes(Landroid/os/VibrationAttributes;Landroid/os/CombinedVibration;)Landroid/os/VibrationAttributes; > 1,6,5 @62 exception:17,
conditional branch(ne, to iindex=-1) 2,4,
5 = getstatic < Application, Lcom/android/server/vibrator/VibratorManagerService, DEFAULT_ATTRIBUTES, <Application,Landroid/os/VibrationAttributes> >,
6 = phi  2,5,
8 = invokevirtual < Application, Landroid/os/VibrationAttributes, getUsage()I > 6 @4 exception:7,
2 = getfield < Application, Landroid/os/VibrationAttributes, mUsage, <Primordial,I> > 1,
return 2,
conditional branch(ne, to iindex=-1) 8,4,
conditional branch(eq, to iindex=-1) 3,4,
10 = invokevirtual < Application, Landroid/os/CombinedVibration, isHapticFeedbackCandidate()Z > 3 @12 exception:9,
conditional branch(eq, to iindex=-1) 10,4,
12 = phi  8,8,8,11,
17 = invokevirtual < Application, Landroid/os/VibrationAttributes, getFlags()I > 6 @20 exception:16,
2 = getfield < Application, Landroid/os/VibrationAttributes, mFlags, <Primordial,I> > 1,
return 2,
19 = binaryop(and) 17 , 18,
conditional branch(eq, to iindex=-1) 19,4,
22 = invokevirtual < Application, Lcom/android/server/vibrator/VibratorManagerService, hasPermission(Ljava/lang/String;)Z > 1,20 @30 exception:21,
conditional branch(ne, to iindex=-1) 22,4,
25 = invokevirtual < Application, Lcom/android/server/vibrator/VibratorManagerService, hasPermission(Ljava/lang/String;)Z > 1,23 @38 exception:24,
conditional branch(ne, to iindex=-1) 25,4,
28 = invokevirtual < Application, Lcom/android/server/vibrator/VibratorManagerService, hasPermission(Ljava/lang/String;)Z > 1,26 @46 exception:27,
conditional branch(ne, to iindex=-1) 28,4,
30 = binaryop(and) 17 , 29,
33 = phi  17,17,17,17,30,
37 = invokevirtual < Application, Landroid/os/VibrationAttributes, getUsage()I > 6 @54 exception:36,
2 = getfield < Application, Landroid/os/VibrationAttributes, mUsage, <Primordial,I> > 1,
return 2,
conditional branch(ne, to iindex=-1) 12,37,
39 = invokevirtual < Application, Landroid/os/VibrationAttributes, getFlags()I > 6 @60 exception:38,
2 = getfield < Application, Landroid/os/VibrationAttributes, mFlags, <Primordial,I> > 1,
return 2,
conditional branch(ne, to iindex=-1) 33,39,
43 = new <Application,Landroid/os/VibrationAttributes$Builder>@67,
invokespecial < Application, Landroid/os/VibrationAttributes$Builder, <init>(Landroid/os/VibrationAttributes;)V > 43,6 @69 exception:44,
46 = invokevirtual < Application, Landroid/os/VibrationAttributes$Builder, setUsage(I)Landroid/os/VibrationAttributes$Builder; > 43,12 @72 exception:45,
putfield 1.< Application, Landroid/os/VibrationAttributes$Builder, mOriginalAudioUsage, <Primordial,I> > = 3,
putfield 1.< Application, Landroid/os/VibrationAttributes$Builder, mUsage, <Primordial,I> > = 2,
return 1,
48 = invokevirtual < Application, Landroid/os/VibrationAttributes, getFlags()I > 6 @76 exception:47,
2 = getfield < Application, Landroid/os/VibrationAttributes, mFlags, <Primordial,I> > 1,
return 2,
50 = invokevirtual < Application, Landroid/os/VibrationAttributes$Builder, setFlags(II)Landroid/os/VibrationAttributes$Builder; > 46,33,48 @80 exception:49,
5 = binaryop(and) 3 , 4,
6 = getfield < Application, Landroid/os/VibrationAttributes$Builder, mFlags, <Primordial,I> > 1,
7 = bitnot 5,
8 = binaryop(and) 6 , 7,
9 = binaryop(and) 2 , 5,
10 = binaryop(or) 8 , 9,
putfield 1.< Application, Landroid/os/VibrationAttributes$Builder, mFlags, <Primordial,I> > = 10,
return 1,
52 = invokevirtual < Application, Landroid/os/VibrationAttributes$Builder, build()Landroid/os/VibrationAttributes; > 50 @84 exception:51,
2 = new <Application,Landroid/os/VibrationAttributes>@0,
3 = getfield < Application, Landroid/os/VibrationAttributes$Builder, mUsage, <Primordial,I> > 1,
4 = getfield < Application, Landroid/os/VibrationAttributes$Builder, mOriginalAudioUsage, <Primordial,I> > 1,
5 = getfield < Application, Landroid/os/VibrationAttributes$Builder, mFlags, <Primordial,I> > 1,
invokespecial < Application, Landroid/os/VibrationAttributes, <init>(IIILandroid/os/VibrationAttributes-IA;)V > 2,3,4,5,6 @9 exception:7,
return 2,
return 52,
19 = getfield < Application, Lcom/android/server/vibrator/VibratorManagerService, mLock, <Application,Ljava/lang/Object> > 1,
monitorenter 19,
21 = invokevirtual < Application, Lcom/android/server/vibrator/VibratorManagerService, fixupAlwaysOnEffectsLocked(Landroid/os/CombinedVibration;)Landroid/util/SparseArray; > 1,5 @69 exception:20,
invokestatic < Application, Landroid/os/Trace, traceBegin(JLjava/lang/String;)V > 3,4 @5 exception:5,
6 = instanceof 2 <Application,Landroid/os/CombinedVibration$Mono>,
conditional branch(eq, to iindex=-1) 6,7,
13 = checkcast <Application,Landroid/os/CombinedVibration$Mono>2 <Application,Landroid/os/CombinedVibration$Mono>,
15 = invokevirtual < Application, Landroid/os/CombinedVibration$Mono, getEffect()Landroid/os/VibrationEffect; > 13 @15 exception:14,
2 = getfield < Application, Landroid/os/CombinedVibration$Mono, mEffect, <Application,Landroid/os/VibrationEffect> > 1,
return 2,
16 = new <Application,Lcom/android/server/vibrator/VibratorManagerService$$ExternalSyntheticLambda2>@19,
invokespecial < Application, Lcom/android/server/vibrator/VibratorManagerService$$ExternalSyntheticLambda2, <init>(Landroid/os/VibrationEffect;)V > 16,15 @21 exception:17,
19 = invokevirtual < Application, Lcom/android/server/vibrator/VibratorManagerService, transformAllVibratorsLocked(Ljava/util/function/Function;)Landroid/util/SparseArray; > 1,16 @24 exception:18,
3 = new <Application,Landroid/util/SparseArray>@0,
4 = getfield < Application, Lcom/android/server/vibrator/VibratorManagerService, mVibrators, <Application,Landroid/util/SparseArray> > 1,
6 = invokevirtual < Application, Landroid/util/SparseArray, size()I > 4 @4 exception:5,
invokespecial < Application, Landroid/util/SparseArray, <init>(I)V > 3,6 @8 exception:7,
24 = phi  23,8,
9 = getfield < Application, Lcom/android/server/vibrator/VibratorManagerService, mVibrators, <Application,Landroid/util/SparseArray> > 1,
11 = invokevirtual < Application, Landroid/util/SparseArray, size()I > 9 @14 exception:10,
conditional branch(ge, to iindex=-1) 24,11,
return 3,
goto (from iindex= 13 to iindex = 11),
21 = phi  19,12,
24 = new <Application,Landroid/util/SparseArray>@39,
invokespecial < Application, Landroid/util/SparseArray, <init>()V > 24 @41 exception:25,
48 = phi  47,7,
27 = invokevirtual < Application, Landroid/util/SparseArray, size()I > 21 @45 exception:26,
conditional branch(ge, to iindex=-1) 48,27,
52 = invokevirtual < Application, Landroid/util/SparseArray, size()I > 24 @102 exception:51,
conditional branch(ne, to iindex=-1) 52,7,
invokestatic < Application, Landroid/os/Trace, traceEnd(J)V > 3 @108 exception:54,
return 7,
conditional branch(ne, to iindex=-1) 21,14,
22 = new <Application,Lcom/android/server/vibrator/VibratorManagerService$AlwaysOnVibration>@80,
invokespecial < Application, Lcom/android/server/vibrator/VibratorManagerService$AlwaysOnVibration, <init>(IILjava/lang/String;Landroid/os/VibrationAttributes;Landroid/util/SparseArray;)V > 22,4,2,3,18,21 @87 exception:23,
24 = getfield < Application, Lcom/android/server/vibrator/VibratorManagerService, mAlwaysOnEffects, <Application,Landroid/util/SparseArray> > 1,
invokevirtual < Application, Landroid/util/SparseArray, put(ILjava/lang/Object;)V > 24,4,22 @92 exception:25,
invokevirtual < Application, Lcom/android/server/vibrator/VibratorManagerService, updateAlwaysOnLocked(Lcom/android/server/vibrator/VibratorManagerService$AlwaysOnVibration;)V > 1,22 @95 exception:26,
monitorexit 19,
invokestatic < Application, Landroid/os/Trace, traceEnd(J)V > 8 @99 exception:27,
return 13,","depth : 0
-----
depth : 1
-----
depth : 2
-----
depth : 2
-----
depth : 2
-----
depth : 2
-----
depth : 2
-----
depth : 2
-----
depth : 2
-----
depth : 2
-----
depth : 1
-----
depth : 2
-----
depth : 2
-----
","public boolean setAlwaysOnEffect(int p1, String p2, int p3, CombinedVibration p4, VibrationAttributes p5){
	if (p4 != 0) {
		boolean v3 = VibratorManagerService.isEffectValid(p4);
		if (v3 != 0) {
			if (p5 != 0) {
				int v5 = this.mUsage;
				if (v5 != 0) {
					if (p4 == 0) {
						boolean v6 = p4.isHapticFeedbackCandidate();
						if (v6 == 0) {
							int v7 = this.mFlags;
							if ((v7 & 3) == 0) {
								if (v8 != 0) {
									if (v9 != 0) {
										if (v10 != 0) {
											int v11 = this.mUsage;
											if ( != v11) {
												int v12 = this.mFlags;
												if ( != v12) {
													VibrationAttributes$Builder v13 = new VibrationAttributes$Builder();
													this.mOriginalAudioUsage = 0;
													this.mUsage = ;
													VibrationAttributes$Builder v15 = VibrationAttributes$Builder;
													int v16 = this.mFlags;
													this.mFlags = ((this.mFlags & (~(v16 & 3))) | ( & (v16 & 3)));
													VibrationAttributes$Builder v17 = VibrationAttributes$Builder;
													VibrationAttributes v19 = new VibrationAttributes(this.mUsage,this.mOriginalAudioUsage,this.mFlags,0);
													VibrationAttributes v18 = v19;
													VibrationAttributes v4 = v18;
													Trace.traceBegin(8388608, ""fixupAlwaysOnEffectsLocked"");
													if (p4 instanceof CombinedVibration$Mono == 0) {
														VibrationEffect v23 = this.mEffect;
														VibratorManagerService$$ExternalSyntheticLambda2 v24 = new VibratorManagerService$$ExternalSyntheticLambda2(v23);
														SparseArray v27 = new SparseArray(v28);
														int v28 = this.mVibrators.size();
														int v30 = this.mVibrators.size();
														if ( >= v30) {
															SparseArray v26 = v27;
															SparseArray v31 = new SparseArray();
															int v33 = .size();
															if ( >= v33) {
																int v34 = v31.size();
																if (v34 != 0) {
																	Trace.traceEnd(8388608);
																	SparseArray v21 = 0;
																	if (v21 != 0) {
																		VibratorManagerService$AlwaysOnVibration v36 = new VibratorManagerService$AlwaysOnVibration(p3,p1,p2,v4,v21);
																		this.mAlwaysOnEffects.put(p3, v36);
																		p0.updateAlwaysOnLocked(v36);
																		Trace.traceEnd(8388608);
																		return 1;
																	}
																}
															}
														}
													}
												}
											}
										}
									}
								}
							}
						}
					}
				}
			}
		}
	}
}
","SYS_OR_SIG"
"Lcom/android/server/vibrator/VibratorManagerService","setAlwaysOnEffect(ILjava/lang/String;ILandroid/os/CombinedVibration;Landroid/os/VibrationAttributes;)Z","2","invokestatic < Application, Landroid/os/Trace, traceBegin(JLjava/lang/String;)V > 8,7 @10 exception:9,
10 = getfield < Application, Lcom/android/server/vibrator/VibratorManagerService, mContext, <Application,Landroid/content/Context> > 1,
invokevirtual < Application, Landroid/content/Context, enforceCallingOrSelfPermission(Ljava/lang/String;Ljava/lang/String;)V > 10,11,7 @19 exception:12,
conditional branch(ne, to iindex=-1) 5,14,
16 = invokestatic < Application, Lcom/android/server/vibrator/VibratorManagerService, isEffectValid(Landroid/os/CombinedVibration;)Z > 5 @49 exception:15,
conditional branch(ne, to iindex=-1) 16,14,
18 = invokevirtual < Application, Lcom/android/server/vibrator/VibratorManagerService, fixupVibrationAttributes(Landroid/os/VibrationAttributes;Landroid/os/CombinedVibration;)Landroid/os/VibrationAttributes; > 1,6,5 @62 exception:17,
conditional branch(ne, to iindex=-1) 2,4,
5 = getstatic < Application, Lcom/android/server/vibrator/VibratorManagerService, DEFAULT_ATTRIBUTES, <Application,Landroid/os/VibrationAttributes> >,
6 = phi  2,5,
8 = invokevirtual < Application, Landroid/os/VibrationAttributes, getUsage()I > 6 @4 exception:7,
2 = getfield < Application, Landroid/os/VibrationAttributes, mUsage, <Primordial,I> > 1,
return 2,
conditional branch(ne, to iindex=-1) 8,4,
conditional branch(eq, to iindex=-1) 3,4,
10 = invokevirtual < Application, Landroid/os/CombinedVibration, isHapticFeedbackCandidate()Z > 3 @12 exception:9,
conditional branch(eq, to iindex=-1) 10,4,
12 = phi  8,8,8,11,
17 = invokevirtual < Application, Landroid/os/VibrationAttributes, getFlags()I > 6 @20 exception:16,
2 = getfield < Application, Landroid/os/VibrationAttributes, mFlags, <Primordial,I> > 1,
return 2,
19 = binaryop(and) 17 , 18,
conditional branch(eq, to iindex=-1) 19,4,
22 = invokevirtual < Application, Lcom/android/server/vibrator/VibratorManagerService, hasPermission(Ljava/lang/String;)Z > 1,20 @30 exception:21,
conditional branch(ne, to iindex=-1) 22,4,
25 = invokevirtual < Application, Lcom/android/server/vibrator/VibratorManagerService, hasPermission(Ljava/lang/String;)Z > 1,23 @38 exception:24,
conditional branch(ne, to iindex=-1) 25,4,
28 = invokevirtual < Application, Lcom/android/server/vibrator/VibratorManagerService, hasPermission(Ljava/lang/String;)Z > 1,26 @46 exception:27,
conditional branch(ne, to iindex=-1) 28,4,
30 = binaryop(and) 17 , 29,
33 = phi  17,17,17,17,30,
37 = invokevirtual < Application, Landroid/os/VibrationAttributes, getUsage()I > 6 @54 exception:36,
2 = getfield < Application, Landroid/os/VibrationAttributes, mUsage, <Primordial,I> > 1,
return 2,
conditional branch(ne, to iindex=-1) 12,37,
39 = invokevirtual < Application, Landroid/os/VibrationAttributes, getFlags()I > 6 @60 exception:38,
2 = getfield < Application, Landroid/os/VibrationAttributes, mFlags, <Primordial,I> > 1,
return 2,
conditional branch(ne, to iindex=-1) 33,39,
43 = new <Application,Landroid/os/VibrationAttributes$Builder>@67,
invokespecial < Application, Landroid/os/VibrationAttributes$Builder, <init>(Landroid/os/VibrationAttributes;)V > 43,6 @69 exception:44,
46 = invokevirtual < Application, Landroid/os/VibrationAttributes$Builder, setUsage(I)Landroid/os/VibrationAttributes$Builder; > 43,12 @72 exception:45,
putfield 1.< Application, Landroid/os/VibrationAttributes$Builder, mOriginalAudioUsage, <Primordial,I> > = 3,
putfield 1.< Application, Landroid/os/VibrationAttributes$Builder, mUsage, <Primordial,I> > = 2,
return 1,
48 = invokevirtual < Application, Landroid/os/VibrationAttributes, getFlags()I > 6 @76 exception:47,
2 = getfield < Application, Landroid/os/VibrationAttributes, mFlags, <Primordial,I> > 1,
return 2,
50 = invokevirtual < Application, Landroid/os/VibrationAttributes$Builder, setFlags(II)Landroid/os/VibrationAttributes$Builder; > 46,33,48 @80 exception:49,
5 = binaryop(and) 3 , 4,
6 = getfield < Application, Landroid/os/VibrationAttributes$Builder, mFlags, <Primordial,I> > 1,
7 = bitnot 5,
8 = binaryop(and) 6 , 7,
9 = binaryop(and) 2 , 5,
10 = binaryop(or) 8 , 9,
putfield 1.< Application, Landroid/os/VibrationAttributes$Builder, mFlags, <Primordial,I> > = 10,
return 1,
52 = invokevirtual < Application, Landroid/os/VibrationAttributes$Builder, build()Landroid/os/VibrationAttributes; > 50 @84 exception:51,
2 = new <Application,Landroid/os/VibrationAttributes>@0,
3 = getfield < Application, Landroid/os/VibrationAttributes$Builder, mUsage, <Primordial,I> > 1,
4 = getfield < Application, Landroid/os/VibrationAttributes$Builder, mOriginalAudioUsage, <Primordial,I> > 1,
5 = getfield < Application, Landroid/os/VibrationAttributes$Builder, mFlags, <Primordial,I> > 1,
invokespecial < Application, Landroid/os/VibrationAttributes, <init>(IIILandroid/os/VibrationAttributes-IA;)V > 2,3,4,5,6 @9 exception:7,
return 2,
return 52,
19 = getfield < Application, Lcom/android/server/vibrator/VibratorManagerService, mLock, <Application,Ljava/lang/Object> > 1,
monitorenter 19,
21 = invokevirtual < Application, Lcom/android/server/vibrator/VibratorManagerService, fixupAlwaysOnEffectsLocked(Landroid/os/CombinedVibration;)Landroid/util/SparseArray; > 1,5 @69 exception:20,
invokestatic < Application, Landroid/os/Trace, traceBegin(JLjava/lang/String;)V > 3,4 @5 exception:5,
6 = instanceof 2 <Application,Landroid/os/CombinedVibration$Mono>,
conditional branch(eq, to iindex=-1) 6,7,
13 = checkcast <Application,Landroid/os/CombinedVibration$Mono>2 <Application,Landroid/os/CombinedVibration$Mono>,
15 = invokevirtual < Application, Landroid/os/CombinedVibration$Mono, getEffect()Landroid/os/VibrationEffect; > 13 @15 exception:14,
2 = getfield < Application, Landroid/os/CombinedVibration$Mono, mEffect, <Application,Landroid/os/VibrationEffect> > 1,
return 2,
16 = new <Application,Lcom/android/server/vibrator/VibratorManagerService$$ExternalSyntheticLambda2>@19,
invokespecial < Application, Lcom/android/server/vibrator/VibratorManagerService$$ExternalSyntheticLambda2, <init>(Landroid/os/VibrationEffect;)V > 16,15 @21 exception:17,
19 = invokevirtual < Application, Lcom/android/server/vibrator/VibratorManagerService, transformAllVibratorsLocked(Ljava/util/function/Function;)Landroid/util/SparseArray; > 1,16 @24 exception:18,
3 = new <Application,Landroid/util/SparseArray>@0,
4 = getfield < Application, Lcom/android/server/vibrator/VibratorManagerService, mVibrators, <Application,Landroid/util/SparseArray> > 1,
6 = invokevirtual < Application, Landroid/util/SparseArray, size()I > 4 @4 exception:5,
invokespecial < Application, Landroid/util/SparseArray, <init>(I)V > 3,6 @8 exception:7,
24 = phi  23,8,
9 = getfield < Application, Lcom/android/server/vibrator/VibratorManagerService, mVibrators, <Application,Landroid/util/SparseArray> > 1,
11 = invokevirtual < Application, Landroid/util/SparseArray, size()I > 9 @14 exception:10,
conditional branch(ge, to iindex=-1) 24,11,
return 3,
goto (from iindex= 13 to iindex = 11),
21 = phi  19,12,
24 = new <Application,Landroid/util/SparseArray>@39,
invokespecial < Application, Landroid/util/SparseArray, <init>()V > 24 @41 exception:25,
48 = phi  47,7,
27 = invokevirtual < Application, Landroid/util/SparseArray, size()I > 21 @45 exception:26,
conditional branch(ge, to iindex=-1) 48,27,
52 = invokevirtual < Application, Landroid/util/SparseArray, size()I > 24 @102 exception:51,
conditional branch(ne, to iindex=-1) 52,7,
invokestatic < Application, Landroid/os/Trace, traceEnd(J)V > 3 @112 exception:53,
return 24,
conditional branch(ne, to iindex=-1) 21,14,
22 = new <Application,Lcom/android/server/vibrator/VibratorManagerService$AlwaysOnVibration>@80,
invokespecial < Application, Lcom/android/server/vibrator/VibratorManagerService$AlwaysOnVibration, <init>(IILjava/lang/String;Landroid/os/VibrationAttributes;Landroid/util/SparseArray;)V > 22,4,2,3,18,21 @87 exception:23,
24 = getfield < Application, Lcom/android/server/vibrator/VibratorManagerService, mAlwaysOnEffects, <Application,Landroid/util/SparseArray> > 1,
invokevirtual < Application, Landroid/util/SparseArray, put(ILjava/lang/Object;)V > 24,4,22 @92 exception:25,
invokevirtual < Application, Lcom/android/server/vibrator/VibratorManagerService, updateAlwaysOnLocked(Lcom/android/server/vibrator/VibratorManagerService$AlwaysOnVibration;)V > 1,22 @95 exception:26,
monitorexit 19,
invokestatic < Application, Landroid/os/Trace, traceEnd(J)V > 8 @99 exception:27,
return 13,","depth : 0
-----
depth : 1
-----
depth : 2
-----
depth : 2
-----
depth : 2
-----
depth : 2
-----
depth : 2
-----
depth : 2
-----
depth : 2
-----
depth : 2
-----
depth : 1
-----
depth : 2
-----
depth : 2
-----
","public boolean setAlwaysOnEffect(int p1, String p2, int p3, CombinedVibration p4, VibrationAttributes p5){
	if (p4 != 0) {
		boolean v3 = VibratorManagerService.isEffectValid(p4);
		if (v3 != 0) {
			if (p5 != 0) {
				int v5 = this.mUsage;
				if (v5 != 0) {
					if (p4 == 0) {
						boolean v6 = p4.isHapticFeedbackCandidate();
						if (v6 == 0) {
							int v7 = this.mFlags;
							if ((v7 & 3) == 0) {
								if (v8 != 0) {
									if (v9 != 0) {
										if (v10 != 0) {
											int v11 = this.mUsage;
											if ( != v11) {
												int v12 = this.mFlags;
												if ( != v12) {
													VibrationAttributes$Builder v13 = new VibrationAttributes$Builder();
													this.mOriginalAudioUsage = 0;
													this.mUsage = ;
													VibrationAttributes$Builder v15 = VibrationAttributes$Builder;
													int v16 = this.mFlags;
													this.mFlags = ((this.mFlags & (~(v16 & 3))) | ( & (v16 & 3)));
													VibrationAttributes$Builder v17 = VibrationAttributes$Builder;
													VibrationAttributes v19 = new VibrationAttributes(this.mUsage,this.mOriginalAudioUsage,this.mFlags,0);
													VibrationAttributes v18 = v19;
													VibrationAttributes v4 = v18;
													Trace.traceBegin(8388608, ""fixupAlwaysOnEffectsLocked"");
													if (p4 instanceof CombinedVibration$Mono == 0) {
														VibrationEffect v23 = this.mEffect;
														VibratorManagerService$$ExternalSyntheticLambda2 v24 = new VibratorManagerService$$ExternalSyntheticLambda2(v23);
														SparseArray v27 = new SparseArray(v28);
														int v28 = this.mVibrators.size();
														int v30 = this.mVibrators.size();
														if ( >= v30) {
															SparseArray v26 = v27;
															SparseArray v31 = new SparseArray();
															int v33 = .size();
															if ( >= v33) {
																int v34 = v31.size();
																if (v34 != 0) {
																	Trace.traceEnd(8388608);
																	SparseArray v21 = v31;
																	if (v21 != 0) {
																		VibratorManagerService$AlwaysOnVibration v36 = new VibratorManagerService$AlwaysOnVibration(p3,p1,p2,v4,v21);
																		this.mAlwaysOnEffects.put(p3, v36);
																		p0.updateAlwaysOnLocked(v36);
																		Trace.traceEnd(8388608);
																		return 1;
																	}
																}
															}
														}
													}
												}
											}
										}
									}
								}
							}
						}
					}
				}
			}
		}
	}
}
","SYS_OR_SIG"
"Lcom/android/server/vibrator/VibratorManagerService","setAlwaysOnEffect(ILjava/lang/String;ILandroid/os/CombinedVibration;Landroid/os/VibrationAttributes;)Z","2","invokestatic < Application, Landroid/os/Trace, traceBegin(JLjava/lang/String;)V > 8,7 @10 exception:9,
10 = getfield < Application, Lcom/android/server/vibrator/VibratorManagerService, mContext, <Application,Landroid/content/Context> > 1,
invokevirtual < Application, Landroid/content/Context, enforceCallingOrSelfPermission(Ljava/lang/String;Ljava/lang/String;)V > 10,11,7 @19 exception:12,
conditional branch(ne, to iindex=-1) 5,14,
16 = invokestatic < Application, Lcom/android/server/vibrator/VibratorManagerService, isEffectValid(Landroid/os/CombinedVibration;)Z > 5 @49 exception:15,
conditional branch(ne, to iindex=-1) 16,14,
18 = invokevirtual < Application, Lcom/android/server/vibrator/VibratorManagerService, fixupVibrationAttributes(Landroid/os/VibrationAttributes;Landroid/os/CombinedVibration;)Landroid/os/VibrationAttributes; > 1,6,5 @62 exception:17,
conditional branch(ne, to iindex=-1) 2,4,
5 = getstatic < Application, Lcom/android/server/vibrator/VibratorManagerService, DEFAULT_ATTRIBUTES, <Application,Landroid/os/VibrationAttributes> >,
6 = phi  2,5,
8 = invokevirtual < Application, Landroid/os/VibrationAttributes, getUsage()I > 6 @4 exception:7,
2 = getfield < Application, Landroid/os/VibrationAttributes, mUsage, <Primordial,I> > 1,
return 2,
conditional branch(ne, to iindex=-1) 8,4,
conditional branch(eq, to iindex=-1) 3,4,
10 = invokevirtual < Application, Landroid/os/CombinedVibration, isHapticFeedbackCandidate()Z > 3 @12 exception:9,
conditional branch(eq, to iindex=-1) 10,4,
12 = phi  8,8,8,11,
17 = invokevirtual < Application, Landroid/os/VibrationAttributes, getFlags()I > 6 @20 exception:16,
2 = getfield < Application, Landroid/os/VibrationAttributes, mFlags, <Primordial,I> > 1,
return 2,
19 = binaryop(and) 17 , 18,
conditional branch(eq, to iindex=-1) 19,4,
22 = invokevirtual < Application, Lcom/android/server/vibrator/VibratorManagerService, hasPermission(Ljava/lang/String;)Z > 1,20 @30 exception:21,
conditional branch(ne, to iindex=-1) 22,4,
25 = invokevirtual < Application, Lcom/android/server/vibrator/VibratorManagerService, hasPermission(Ljava/lang/String;)Z > 1,23 @38 exception:24,
conditional branch(ne, to iindex=-1) 25,4,
28 = invokevirtual < Application, Lcom/android/server/vibrator/VibratorManagerService, hasPermission(Ljava/lang/String;)Z > 1,26 @46 exception:27,
conditional branch(ne, to iindex=-1) 28,4,
33 = phi  17,17,17,17,30,
37 = invokevirtual < Application, Landroid/os/VibrationAttributes, getUsage()I > 6 @54 exception:36,
2 = getfield < Application, Landroid/os/VibrationAttributes, mUsage, <Primordial,I> > 1,
return 2,
conditional branch(ne, to iindex=-1) 12,37,
39 = invokevirtual < Application, Landroid/os/VibrationAttributes, getFlags()I > 6 @60 exception:38,
2 = getfield < Application, Landroid/os/VibrationAttributes, mFlags, <Primordial,I> > 1,
return 2,
conditional branch(ne, to iindex=-1) 33,39,
43 = new <Application,Landroid/os/VibrationAttributes$Builder>@67,
invokespecial < Application, Landroid/os/VibrationAttributes$Builder, <init>(Landroid/os/VibrationAttributes;)V > 43,6 @69 exception:44,
46 = invokevirtual < Application, Landroid/os/VibrationAttributes$Builder, setUsage(I)Landroid/os/VibrationAttributes$Builder; > 43,12 @72 exception:45,
putfield 1.< Application, Landroid/os/VibrationAttributes$Builder, mOriginalAudioUsage, <Primordial,I> > = 3,
putfield 1.< Application, Landroid/os/VibrationAttributes$Builder, mUsage, <Primordial,I> > = 2,
return 1,
48 = invokevirtual < Application, Landroid/os/VibrationAttributes, getFlags()I > 6 @76 exception:47,
2 = getfield < Application, Landroid/os/VibrationAttributes, mFlags, <Primordial,I> > 1,
return 2,
50 = invokevirtual < Application, Landroid/os/VibrationAttributes$Builder, setFlags(II)Landroid/os/VibrationAttributes$Builder; > 46,33,48 @80 exception:49,
5 = binaryop(and) 3 , 4,
6 = getfield < Application, Landroid/os/VibrationAttributes$Builder, mFlags, <Primordial,I> > 1,
7 = bitnot 5,
8 = binaryop(and) 6 , 7,
9 = binaryop(and) 2 , 5,
10 = binaryop(or) 8 , 9,
putfield 1.< Application, Landroid/os/VibrationAttributes$Builder, mFlags, <Primordial,I> > = 10,
return 1,
52 = invokevirtual < Application, Landroid/os/VibrationAttributes$Builder, build()Landroid/os/VibrationAttributes; > 50 @84 exception:51,
2 = new <Application,Landroid/os/VibrationAttributes>@0,
3 = getfield < Application, Landroid/os/VibrationAttributes$Builder, mUsage, <Primordial,I> > 1,
4 = getfield < Application, Landroid/os/VibrationAttributes$Builder, mOriginalAudioUsage, <Primordial,I> > 1,
5 = getfield < Application, Landroid/os/VibrationAttributes$Builder, mFlags, <Primordial,I> > 1,
invokespecial < Application, Landroid/os/VibrationAttributes, <init>(IIILandroid/os/VibrationAttributes-IA;)V > 2,3,4,5,6 @9 exception:7,
return 2,
return 52,
19 = getfield < Application, Lcom/android/server/vibrator/VibratorManagerService, mLock, <Application,Ljava/lang/Object> > 1,
monitorenter 19,
21 = invokevirtual < Application, Lcom/android/server/vibrator/VibratorManagerService, fixupAlwaysOnEffectsLocked(Landroid/os/CombinedVibration;)Landroid/util/SparseArray; > 1,5 @69 exception:20,
invokestatic < Application, Landroid/os/Trace, traceBegin(JLjava/lang/String;)V > 3,4 @5 exception:5,
6 = instanceof 2 <Application,Landroid/os/CombinedVibration$Mono>,
conditional branch(eq, to iindex=-1) 6,7,
13 = checkcast <Application,Landroid/os/CombinedVibration$Mono>2 <Application,Landroid/os/CombinedVibration$Mono>,
15 = invokevirtual < Application, Landroid/os/CombinedVibration$Mono, getEffect()Landroid/os/VibrationEffect; > 13 @15 exception:14,
2 = getfield < Application, Landroid/os/CombinedVibration$Mono, mEffect, <Application,Landroid/os/VibrationEffect> > 1,
return 2,
16 = new <Application,Lcom/android/server/vibrator/VibratorManagerService$$ExternalSyntheticLambda2>@19,
invokespecial < Application, Lcom/android/server/vibrator/VibratorManagerService$$ExternalSyntheticLambda2, <init>(Landroid/os/VibrationEffect;)V > 16,15 @21 exception:17,
19 = invokevirtual < Application, Lcom/android/server/vibrator/VibratorManagerService, transformAllVibratorsLocked(Ljava/util/function/Function;)Landroid/util/SparseArray; > 1,16 @24 exception:18,
3 = new <Application,Landroid/util/SparseArray>@0,
4 = getfield < Application, Lcom/android/server/vibrator/VibratorManagerService, mVibrators, <Application,Landroid/util/SparseArray> > 1,
6 = invokevirtual < Application, Landroid/util/SparseArray, size()I > 4 @4 exception:5,
invokespecial < Application, Landroid/util/SparseArray, <init>(I)V > 3,6 @8 exception:7,
24 = phi  23,8,
9 = getfield < Application, Lcom/android/server/vibrator/VibratorManagerService, mVibrators, <Application,Landroid/util/SparseArray> > 1,
11 = invokevirtual < Application, Landroid/util/SparseArray, size()I > 9 @14 exception:10,
conditional branch(ge, to iindex=-1) 24,11,
return 3,
goto (from iindex= 13 to iindex = 11),
21 = phi  19,12,
24 = new <Application,Landroid/util/SparseArray>@39,
invokespecial < Application, Landroid/util/SparseArray, <init>()V > 24 @41 exception:25,
48 = phi  47,7,
27 = invokevirtual < Application, Landroid/util/SparseArray, size()I > 21 @45 exception:26,
conditional branch(ge, to iindex=-1) 48,27,
52 = invokevirtual < Application, Landroid/util/SparseArray, size()I > 24 @102 exception:51,
conditional branch(ne, to iindex=-1) 52,7,
invokestatic < Application, Landroid/os/Trace, traceEnd(J)V > 3 @108 exception:54,
return 7,
conditional branch(ne, to iindex=-1) 21,14,
22 = new <Application,Lcom/android/server/vibrator/VibratorManagerService$AlwaysOnVibration>@80,
invokespecial < Application, Lcom/android/server/vibrator/VibratorManagerService$AlwaysOnVibration, <init>(IILjava/lang/String;Landroid/os/VibrationAttributes;Landroid/util/SparseArray;)V > 22,4,2,3,18,21 @87 exception:23,
24 = getfield < Application, Lcom/android/server/vibrator/VibratorManagerService, mAlwaysOnEffects, <Application,Landroid/util/SparseArray> > 1,
invokevirtual < Application, Landroid/util/SparseArray, put(ILjava/lang/Object;)V > 24,4,22 @92 exception:25,
invokevirtual < Application, Lcom/android/server/vibrator/VibratorManagerService, updateAlwaysOnLocked(Lcom/android/server/vibrator/VibratorManagerService$AlwaysOnVibration;)V > 1,22 @95 exception:26,
monitorexit 19,
invokestatic < Application, Landroid/os/Trace, traceEnd(J)V > 8 @99 exception:27,
return 13,","depth : 0
-----
depth : 1
-----
depth : 2
-----
depth : 2
-----
depth : 2
-----
depth : 2
-----
depth : 2
-----
depth : 2
-----
depth : 2
-----
depth : 2
-----
depth : 1
-----
depth : 2
-----
depth : 2
-----
","public boolean setAlwaysOnEffect(int p1, String p2, int p3, CombinedVibration p4, VibrationAttributes p5){
	if (p4 != 0) {
		boolean v3 = VibratorManagerService.isEffectValid(p4);
		if (v3 != 0) {
			if (p5 != 0) {
				int v5 = this.mUsage;
				if (v5 != 0) {
					if (p4 == 0) {
						boolean v6 = p4.isHapticFeedbackCandidate();
						if (v6 == 0) {
							int v7 = this.mFlags;
							if ((v7 & 3) == 0) {
								if (v8 != 0) {
									if (v9 != 0) {
										if (v10 != 0) {
											int v11 = this.mUsage;
											if ( != v11) {
												int v12 = this.mFlags;
												if ( != v12) {
													VibrationAttributes$Builder v13 = new VibrationAttributes$Builder();
													this.mOriginalAudioUsage = 0;
													this.mUsage = ;
													VibrationAttributes$Builder v15 = VibrationAttributes$Builder;
													int v16 = this.mFlags;
													this.mFlags = ((this.mFlags & (~(v16 & 3))) | ( & (v16 & 3)));
													VibrationAttributes$Builder v17 = VibrationAttributes$Builder;
													VibrationAttributes v19 = new VibrationAttributes(this.mUsage,this.mOriginalAudioUsage,this.mFlags,0);
													VibrationAttributes v18 = v19;
													VibrationAttributes v4 = v18;
													Trace.traceBegin(8388608, ""fixupAlwaysOnEffectsLocked"");
													if (p4 instanceof CombinedVibration$Mono == 0) {
														VibrationEffect v23 = this.mEffect;
														VibratorManagerService$$ExternalSyntheticLambda2 v24 = new VibratorManagerService$$ExternalSyntheticLambda2(v23);
														SparseArray v27 = new SparseArray(v28);
														int v28 = this.mVibrators.size();
														int v30 = this.mVibrators.size();
														if ( >= v30) {
															SparseArray v26 = v27;
															SparseArray v31 = new SparseArray();
															int v33 = .size();
															if ( >= v33) {
																int v34 = v31.size();
																if (v34 != 0) {
																	Trace.traceEnd(8388608);
																	SparseArray v21 = 0;
																	if (v21 != 0) {
																		VibratorManagerService$AlwaysOnVibration v36 = new VibratorManagerService$AlwaysOnVibration(p3,p1,p2,v4,v21);
																		this.mAlwaysOnEffects.put(p3, v36);
																		p0.updateAlwaysOnLocked(v36);
																		Trace.traceEnd(8388608);
																		return 1;
																	}
																}
															}
														}
													}
												}
											}
										}
									}
								}
							}
						}
					}
				}
			}
		}
	}
}
","SYS_OR_SIG"

"Lcom/android/server/vibrator/VibratorManagerService","isVibrating(I)Z","0","3 = getfield < Application, Lcom/android/server/vibrator/VibratorManagerService, mContext, <Application,Landroid/content/Context> > 1,
invokevirtual < Application, Landroid/content/Context, enforceCallingOrSelfPermission(Ljava/lang/String;Ljava/lang/String;)V > 3,4,5 @6 exception:6,
7 = getfield < Application, Lcom/android/server/vibrator/VibratorManagerService, mVibrators, <Application,Landroid/util/SparseArray> > 1,
9 = invokevirtual < Application, Landroid/util/SparseArray, get(I)Ljava/lang/Object; > 7,2 @11 exception:8,
10 = checkcast <Application,Lcom/android/server/vibrator/VibratorController>9 <Application,Lcom/android/server/vibrator/VibratorController>,
conditional branch(eq, to iindex=-1) 10,11,
13 = invokevirtual < Application, Lcom/android/server/vibrator/VibratorController, isVibrating()Z > 10 @19 exception:12,
conditional branch(eq, to iindex=-1) 13,11,
goto (from iindex= 13 to iindex = 2),
18 = phi  17,11,
return 18,","depth : 0
-----
","public boolean isVibrating(int p1){
	Object v2 = this.mVibrators.get(p1);
	if (v2 == 0) {
		boolean v3 = v2.isVibrating();
		if (v3 == 0) {
			return ;
		}
	}
}
","SYS_OR_SIG"
"Lcom/android/server/vibrator/VibratorManagerService","isVibrating(I)Z","0","3 = getfield < Application, Lcom/android/server/vibrator/VibratorManagerService, mContext, <Application,Landroid/content/Context> > 1,
invokevirtual < Application, Landroid/content/Context, enforceCallingOrSelfPermission(Ljava/lang/String;Ljava/lang/String;)V > 3,4,5 @6 exception:6,
7 = getfield < Application, Lcom/android/server/vibrator/VibratorManagerService, mVibrators, <Application,Landroid/util/SparseArray> > 1,
9 = invokevirtual < Application, Landroid/util/SparseArray, get(I)Ljava/lang/Object; > 7,2 @11 exception:8,
10 = checkcast <Application,Lcom/android/server/vibrator/VibratorController>9 <Application,Lcom/android/server/vibrator/VibratorController>,
conditional branch(eq, to iindex=-1) 10,11,
13 = invokevirtual < Application, Lcom/android/server/vibrator/VibratorController, isVibrating()Z > 10 @19 exception:12,
conditional branch(eq, to iindex=-1) 13,11,
18 = phi  17,11,
return 18,","depth : 0
-----
","public boolean isVibrating(int p1){
	Object v2 = this.mVibrators.get(p1);
	if (v2 == 0) {
		boolean v3 = v2.isVibrating();
		if (v3 == 0) {
			return ;
		}
	}
}
","SYS_OR_SIG"
"Lcom/android/server/vibrator/VibratorManagerService","isVibrating(I)Z","0","3 = getfield < Application, Lcom/android/server/vibrator/VibratorManagerService, mContext, <Application,Landroid/content/Context> > 1,
invokevirtual < Application, Landroid/content/Context, enforceCallingOrSelfPermission(Ljava/lang/String;Ljava/lang/String;)V > 3,4,5 @6 exception:6,
7 = getfield < Application, Lcom/android/server/vibrator/VibratorManagerService, mVibrators, <Application,Landroid/util/SparseArray> > 1,
9 = invokevirtual < Application, Landroid/util/SparseArray, get(I)Ljava/lang/Object; > 7,2 @11 exception:8,
10 = checkcast <Application,Lcom/android/server/vibrator/VibratorController>9 <Application,Lcom/android/server/vibrator/VibratorController>,
conditional branch(eq, to iindex=-1) 10,11,
18 = phi  17,11,
return 18,","depth : 0
-----
","public boolean isVibrating(int p1){
	Object v2 = this.mVibrators.get(p1);
	if (v2 == 0) {
		return ;
	}
}
","SYS_OR_SIG"
"Lcom/android/server/vibrator/VibratorManagerService","isVibrating(I)Z","1","3 = getfield < Application, Lcom/android/server/vibrator/VibratorManagerService, mContext, <Application,Landroid/content/Context> > 1,
invokevirtual < Application, Landroid/content/Context, enforceCallingOrSelfPermission(Ljava/lang/String;Ljava/lang/String;)V > 3,4,5 @6 exception:6,
7 = getfield < Application, Lcom/android/server/vibrator/VibratorManagerService, mVibrators, <Application,Landroid/util/SparseArray> > 1,
9 = invokevirtual < Application, Landroid/util/SparseArray, get(I)Ljava/lang/Object; > 7,2 @11 exception:8,
10 = checkcast <Application,Lcom/android/server/vibrator/VibratorController>9 <Application,Lcom/android/server/vibrator/VibratorController>,
conditional branch(eq, to iindex=-1) 10,11,
13 = invokevirtual < Application, Lcom/android/server/vibrator/VibratorController, isVibrating()Z > 10 @19 exception:12,
2 = getfield < Application, Lcom/android/server/vibrator/VibratorController, mIsVibrating, <Primordial,Z> > 1,
return 2,
conditional branch(eq, to iindex=-1) 13,11,
goto (from iindex= 13 to iindex = 2),
18 = phi  17,11,
return 18,","depth : 0
-----
depth : 1
-----
","public boolean isVibrating(int p1){
	Object v2 = this.mVibrators.get(p1);
	if (v2 == 0) {
		boolean v3 = this.mIsVibrating;
		if (v3 == 0) {
			return ;
		}
	}
}
","SYS_OR_SIG"
"Lcom/android/server/vibrator/VibratorManagerService","isVibrating(I)Z","1","3 = getfield < Application, Lcom/android/server/vibrator/VibratorManagerService, mContext, <Application,Landroid/content/Context> > 1,
invokevirtual < Application, Landroid/content/Context, enforceCallingOrSelfPermission(Ljava/lang/String;Ljava/lang/String;)V > 3,4,5 @6 exception:6,
7 = getfield < Application, Lcom/android/server/vibrator/VibratorManagerService, mVibrators, <Application,Landroid/util/SparseArray> > 1,
9 = invokevirtual < Application, Landroid/util/SparseArray, get(I)Ljava/lang/Object; > 7,2 @11 exception:8,
10 = checkcast <Application,Lcom/android/server/vibrator/VibratorController>9 <Application,Lcom/android/server/vibrator/VibratorController>,
conditional branch(eq, to iindex=-1) 10,11,
13 = invokevirtual < Application, Lcom/android/server/vibrator/VibratorController, isVibrating()Z > 10 @19 exception:12,
2 = getfield < Application, Lcom/android/server/vibrator/VibratorController, mIsVibrating, <Primordial,Z> > 1,
return 2,
conditional branch(eq, to iindex=-1) 13,11,
18 = phi  17,11,
return 18,","depth : 0
-----
depth : 1
-----
","public boolean isVibrating(int p1){
	Object v2 = this.mVibrators.get(p1);
	if (v2 == 0) {
		boolean v3 = this.mIsVibrating;
		if (v3 == 0) {
			return ;
		}
	}
}
","SYS_OR_SIG"

"Lcom/android/server/vibrator/VibratorManagerService","vibrate(IILjava/lang/String;Landroid/os/CombinedVibration;Landroid/os/VibrationAttributes;Ljava/lang/String;Landroid/os/IBinder;)V","0","10 = invokevirtual < Application, Lcom/android/server/vibrator/VibratorManagerService, vibrateInternal(IILjava/lang/String;Landroid/os/CombinedVibration;Landroid/os/VibrationAttributes;Ljava/lang/String;Landroid/os/IBinder;)Lcom/android/server/vibrator/Vibration; > 1,2,3,4,5,6,7,8 @0 exception:9,
return,","depth : 0
-----
","public void vibrate(int p1, int p2, String p3, CombinedVibration p4, VibrationAttributes p5, String p6, IBinder p7){
	Vibration v1 = p0.vibrateInternal(p1, p2, p3, p4, p5, p6, p7);
	return;
}
","NORMAL"
"Lcom/android/server/vibrator/VibratorManagerService","vibrate(IILjava/lang/String;Landroid/os/CombinedVibration;Landroid/os/VibrationAttributes;Ljava/lang/String;Landroid/os/IBinder;)V","1","10 = invokevirtual < Application, Lcom/android/server/vibrator/VibratorManagerService, vibrateInternal(IILjava/lang/String;Landroid/os/CombinedVibration;Landroid/os/VibrationAttributes;Ljava/lang/String;Landroid/os/IBinder;)Lcom/android/server/vibrator/Vibration; > 1,2,3,4,5,6,7,8 @0 exception:9,
9 = new <Application,Ljava/lang/StringBuilder>@3,
invokespecial < Application, Ljava/lang/StringBuilder, <init>()V > 9 @5 exception:10,
13 = invokevirtual < Application, Ljava/lang/StringBuilder, append(Ljava/lang/String;)Ljava/lang/StringBuilder; > 9,11 @10 exception:12,
15 = invokevirtual < Application, Ljava/lang/StringBuilder, append(Ljava/lang/String;)Ljava/lang/StringBuilder; > 9,7 @15 exception:14,
17 = invokevirtual < Application, Ljava/lang/StringBuilder, toString()Ljava/lang/String; > 9 @18 exception:16,
invokestatic < Application, Landroid/os/Trace, traceBegin(JLjava/lang/String;)V > 18,17 @25 exception:19,
20 = getfield < Application, Lcom/android/server/vibrator/VibratorManagerService, mContext, <Application,Landroid/content/Context> > 1,
invokevirtual < Application, Landroid/content/Context, enforceCallingOrSelfPermission(Ljava/lang/String;Ljava/lang/String;)V > 20,21,22 @34 exception:23,
conditional branch(ne, to iindex=-1) 8,24,
invokevirtual < Application, Lcom/android/server/vibrator/VibratorManagerService, enforceUpdateAppOpsStatsPermission(I)V > 1,2 @51 exception:25,
27 = invokestatic < Application, Lcom/android/server/vibrator/VibratorManagerService, isEffectValid(Landroid/os/CombinedVibration;)Z > 5 @54 exception:26,
conditional branch(ne, to iindex=-1) 27,24,
invokestatic < Application, Landroid/os/Trace, traceEnd(J)V > 18 @60 exception:158,
return 24,
return,","depth : 0
-----
depth : 1
-----
","public void vibrate(int p1, int p2, String p3, CombinedVibration p4, VibrationAttributes p5, String p6, IBinder p7){
	if (p7 != 0) {
		boolean v10 = VibratorManagerService.isEffectValid(p4);
		if (v10 != 0) {
			Trace.traceEnd(8388608);
			Vibration v1 = 0;
			return;
		}
	}
}
","NORMAL"

"Lcom/android/server/vibrator/VibratorManagerService","getVibratorIds()[I","0","2 = getfield < Application, Lcom/android/server/vibrator/VibratorManagerService, mVibratorIds, <Primordial,[I> > 1,
3 = arraylength 2,
5 = invokestatic < Application, Ljava/util/Arrays, copyOf([II)[I > 2,3 @3 exception:4,
return 5,","depth : 0
-----
","public [I getVibratorIds(){
	[I v1 = Arrays.copyOf(this.mVibratorIds, this.mVibratorIds.length);
	return v1;
}
","NONE"

