"Class","Method","Depth","Trace Instruction(s) ...","Java Code Representation","Code Merged","Access Control Level"
"Lcom/android/server/lights/LightsService$LightsManagerBinderService","closeSession(Landroid/os/IBinder;)V","0","3 = getfield < Application, Lcom/android/server/lights/LightsService$LightsManagerBinderService, this$0, <Application,Lcom/android/server/lights/LightsService> > 1,
5 = invokevirtual < Application, Lcom/android/server/SystemService, getContext()Landroid/content/Context; > 3 @2 exception:4,
invokevirtual < Application, Landroid/content/Context, enforceCallingOrSelfPermission(Ljava/lang/String;Ljava/lang/String;)V > 5,6,7 @10 exception:8,
10 = invokestatic < Application, Lcom/android/internal/util/Preconditions, checkNotNull(Ljava/lang/Object;)Ljava/lang/Object; > 2 @13 exception:9,
invokevirtual < Application, Lcom/android/server/lights/LightsService$LightsManagerBinderService, closeSessionInternal(Landroid/os/IBinder;)V > 1,2 @16 exception:11,
return,","depth : 0
-----
","public void closeSession(IBinder p1){
	Object v3 = Preconditions.checkNotNull(p1);
	p0.closeSessionInternal(p1);
	return;
}
","SYS_OR_SIG"
"Lcom/android/server/lights/LightsService$LightsManagerBinderService","closeSession(Landroid/os/IBinder;)V","1","3 = getfield < Application, Lcom/android/server/lights/LightsService$LightsManagerBinderService, this$0, <Application,Lcom/android/server/lights/LightsService> > 1,
5 = invokevirtual < Application, Lcom/android/server/SystemService, getContext()Landroid/content/Context; > 3 @2 exception:4,
invokevirtual < Application, Landroid/content/Context, enforceCallingOrSelfPermission(Ljava/lang/String;Ljava/lang/String;)V > 5,6,7 @10 exception:8,
10 = invokestatic < Application, Lcom/android/internal/util/Preconditions, checkNotNull(Ljava/lang/Object;)Ljava/lang/Object; > 2 @13 exception:9,
invokevirtual < Application, Lcom/android/server/lights/LightsService$LightsManagerBinderService, closeSessionInternal(Landroid/os/IBinder;)V > 1,2 @16 exception:11,
3 = getfield < Application, Lcom/android/server/lights/LightsService$LightsManagerBinderService, this$0, <Application,Lcom/android/server/lights/LightsService> > 1,
monitorenter 3,
5 = invokevirtual < Application, Lcom/android/server/lights/LightsService$LightsManagerBinderService, getSessionLocked(Landroid/os/IBinder;)Lcom/android/server/lights/LightsService$LightsManagerBinderService$Session; > 1,2 @3 exception:4,
conditional branch(eq, to iindex=-1) 5,6,
7 = getfield < Application, Lcom/android/server/lights/LightsService$LightsManagerBinderService, mSessions, <Application,Ljava/util/List> > 1,
9 = invokeinterface < Application, Ljava/util/List, remove(Ljava/lang/Object;)Z > 7,5 @11 exception:8,
invokevirtual < Application, Lcom/android/server/lights/LightsService$LightsManagerBinderService, invalidateLightStatesLocked()V > 1 @14 exception:10,
monitorexit 3,
return,
return,","depth : 0
-----
depth : 1
-----
","public void closeSession(IBinder p1){
	Object v3 = Preconditions.checkNotNull(p1);
	LightsService$LightsManagerBinderService$Session v5 = LightsService$LightsManagerBinderService.getSessionLocked(p1);
	if (v5 == 0) {
		boolean v6 = this.mSessions.remove(v5);
		LightsService$LightsManagerBinderService.invalidateLightStatesLocked();
		return;
	}
}
","SYS_OR_SIG"
"Lcom/android/server/lights/LightsService$LightsManagerBinderService","closeSession(Landroid/os/IBinder;)V","2","3 = getfield < Application, Lcom/android/server/lights/LightsService$LightsManagerBinderService, this$0, <Application,Lcom/android/server/lights/LightsService> > 1,
5 = invokevirtual < Application, Lcom/android/server/SystemService, getContext()Landroid/content/Context; > 3 @2 exception:4,
invokevirtual < Application, Landroid/content/Context, enforceCallingOrSelfPermission(Ljava/lang/String;Ljava/lang/String;)V > 5,6,7 @10 exception:8,
10 = invokestatic < Application, Lcom/android/internal/util/Preconditions, checkNotNull(Ljava/lang/Object;)Ljava/lang/Object; > 2 @13 exception:9,
invokevirtual < Application, Lcom/android/server/lights/LightsService$LightsManagerBinderService, closeSessionInternal(Landroid/os/IBinder;)V > 1,2 @16 exception:11,
3 = getfield < Application, Lcom/android/server/lights/LightsService$LightsManagerBinderService, this$0, <Application,Lcom/android/server/lights/LightsService> > 1,
monitorenter 3,
5 = invokevirtual < Application, Lcom/android/server/lights/LightsService$LightsManagerBinderService, getSessionLocked(Landroid/os/IBinder;)Lcom/android/server/lights/LightsService$LightsManagerBinderService$Session; > 1,2 @3 exception:4,
16 = phi  15,3,
4 = getfield < Application, Lcom/android/server/lights/LightsService$LightsManagerBinderService, mSessions, <Application,Ljava/util/List> > 1,
6 = invokeinterface < Application, Ljava/util/List, size()I > 4 @3 exception:5,
conditional branch(ge, to iindex=-1) 16,6,
7 = getfield < Application, Lcom/android/server/lights/LightsService$LightsManagerBinderService, mSessions, <Application,Ljava/util/List> > 1,
9 = invokeinterface < Application, Ljava/util/List, get(I)Ljava/lang/Object; > 7,16 @11 exception:8,
10 = checkcast <Application,Lcom/android/server/lights/LightsService$LightsManagerBinderService$Session>9 <Application,Lcom/android/server/lights/LightsService$LightsManagerBinderService$Session>,
11 = getfield < Application, Lcom/android/server/lights/LightsService$LightsManagerBinderService$Session, mToken, <Application,Landroid/os/IBinder> > 10,
13 = invokevirtual < Application, Ljava/lang/Object, equals(Ljava/lang/Object;)Z > 2,11 @19 exception:12,
conditional branch(eq, to iindex=-1) 13,3,
17 = getfield < Application, Lcom/android/server/lights/LightsService$LightsManagerBinderService, mSessions, <Application,Ljava/util/List> > 1,
19 = invokeinterface < Application, Ljava/util/List, get(I)Ljava/lang/Object; > 17,16 @27 exception:18,
20 = checkcast <Application,Lcom/android/server/lights/LightsService$LightsManagerBinderService$Session>19 <Application,Lcom/android/server/lights/LightsService$LightsManagerBinderService$Session>,
return 20,
conditional branch(eq, to iindex=-1) 5,6,
7 = getfield < Application, Lcom/android/server/lights/LightsService$LightsManagerBinderService, mSessions, <Application,Ljava/util/List> > 1,
9 = invokeinterface < Application, Ljava/util/List, remove(Ljava/lang/Object;)Z > 7,5 @11 exception:8,
invokevirtual < Application, Lcom/android/server/lights/LightsService$LightsManagerBinderService, invalidateLightStatesLocked()V > 1 @14 exception:10,
2 = new <Application,Ljava/util/HashMap>@0,
invokespecial < Application, Ljava/util/HashMap, <init>()V > 2 @2 exception:3,
4 = getfield < Application, Lcom/android/server/lights/LightsService$LightsManagerBinderService, mSessions, <Application,Ljava/util/List> > 1,
6 = invokeinterface < Application, Ljava/util/List, size()I > 4 @7 exception:5,
8 = binaryop(add) 6 , 7,
32 = phi  31,8,
conditional branch(lt, to iindex=-1) 32,9,
67 = phi  9,65,
37 = getfield < Application, Lcom/android/server/lights/LightsService$LightsManagerBinderService, this$0, <Application,Lcom/android/server/lights/LightsService> > 1,
39 = invokestatic < Application, Lcom/android/server/lights/LightsService, -$$Nest$fgetmLightsById(Lcom/android/server/lights/LightsService;)Landroid/util/SparseArray; > 37 @57 exception:38,
41 = invokevirtual < Application, Landroid/util/SparseArray, size()I > 39 @61 exception:40,
conditional branch(ge, to iindex=-1) 67,41,
return,
monitorexit 3,
return,
return,","depth : 0
-----
depth : 1
-----
depth : 2
-----
depth : 2
-----
","public void closeSession(IBinder p1){
	Object v3 = Preconditions.checkNotNull(p1);
	int v6 = this.mSessions.size();
	if ( >= v6) {
		Object v7 = this.mSessions.get();
		boolean v8 = p1.equals(LightsService$LightsManagerBinderService$Session.mToken);
		if (v8 == 0) {
			Object v9 = this.mSessions.get();
			LightsService$LightsManagerBinderService$Session v5 = v9;
			if (v5 == 0) {
				boolean v10 = this.mSessions.remove(v5);
				HashMap v12 = new HashMap();
				int v14 = this.mSessions.size();
				if ( < 0) {
					SparseArray v15 = LightsService.-$$Nest$fgetmLightsById(this.this$0);
					int v16 = v15.size();
					if ( >= v16) {
						return;
					}
				}
			}
		}
	}
}
","SYS_OR_SIG"
"Lcom/android/server/lights/LightsService$LightsManagerBinderService","closeSession(Landroid/os/IBinder;)V","2","3 = getfield < Application, Lcom/android/server/lights/LightsService$LightsManagerBinderService, this$0, <Application,Lcom/android/server/lights/LightsService> > 1,
5 = invokevirtual < Application, Lcom/android/server/SystemService, getContext()Landroid/content/Context; > 3 @2 exception:4,
invokevirtual < Application, Landroid/content/Context, enforceCallingOrSelfPermission(Ljava/lang/String;Ljava/lang/String;)V > 5,6,7 @10 exception:8,
10 = invokestatic < Application, Lcom/android/internal/util/Preconditions, checkNotNull(Ljava/lang/Object;)Ljava/lang/Object; > 2 @13 exception:9,
invokevirtual < Application, Lcom/android/server/lights/LightsService$LightsManagerBinderService, closeSessionInternal(Landroid/os/IBinder;)V > 1,2 @16 exception:11,
3 = getfield < Application, Lcom/android/server/lights/LightsService$LightsManagerBinderService, this$0, <Application,Lcom/android/server/lights/LightsService> > 1,
monitorenter 3,
5 = invokevirtual < Application, Lcom/android/server/lights/LightsService$LightsManagerBinderService, getSessionLocked(Landroid/os/IBinder;)Lcom/android/server/lights/LightsService$LightsManagerBinderService$Session; > 1,2 @3 exception:4,
16 = phi  15,3,
4 = getfield < Application, Lcom/android/server/lights/LightsService$LightsManagerBinderService, mSessions, <Application,Ljava/util/List> > 1,
6 = invokeinterface < Application, Ljava/util/List, size()I > 4 @3 exception:5,
conditional branch(ge, to iindex=-1) 16,6,
return 3,
conditional branch(eq, to iindex=-1) 5,6,
7 = getfield < Application, Lcom/android/server/lights/LightsService$LightsManagerBinderService, mSessions, <Application,Ljava/util/List> > 1,
9 = invokeinterface < Application, Ljava/util/List, remove(Ljava/lang/Object;)Z > 7,5 @11 exception:8,
invokevirtual < Application, Lcom/android/server/lights/LightsService$LightsManagerBinderService, invalidateLightStatesLocked()V > 1 @14 exception:10,
2 = new <Application,Ljava/util/HashMap>@0,
invokespecial < Application, Ljava/util/HashMap, <init>()V > 2 @2 exception:3,
4 = getfield < Application, Lcom/android/server/lights/LightsService$LightsManagerBinderService, mSessions, <Application,Ljava/util/List> > 1,
6 = invokeinterface < Application, Ljava/util/List, size()I > 4 @7 exception:5,
8 = binaryop(add) 6 , 7,
32 = phi  31,8,
conditional branch(lt, to iindex=-1) 32,9,
67 = phi  9,65,
37 = getfield < Application, Lcom/android/server/lights/LightsService$LightsManagerBinderService, this$0, <Application,Lcom/android/server/lights/LightsService> > 1,
39 = invokestatic < Application, Lcom/android/server/lights/LightsService, -$$Nest$fgetmLightsById(Lcom/android/server/lights/LightsService;)Landroid/util/SparseArray; > 37 @57 exception:38,
41 = invokevirtual < Application, Landroid/util/SparseArray, size()I > 39 @61 exception:40,
conditional branch(ge, to iindex=-1) 67,41,
return,
monitorexit 3,
return,
return,","depth : 0
-----
depth : 1
-----
depth : 2
-----
depth : 2
-----
","public void closeSession(IBinder p1){
	Object v3 = Preconditions.checkNotNull(p1);
	int v6 = this.mSessions.size();
	if ( >= v6) {
		LightsService$LightsManagerBinderService$Session v5 = 0;
		if (v5 == 0) {
			boolean v7 = this.mSessions.remove(v5);
			HashMap v9 = new HashMap();
			int v11 = this.mSessions.size();
			if ( < 0) {
				SparseArray v12 = LightsService.-$$Nest$fgetmLightsById(this.this$0);
				int v13 = v12.size();
				if ( >= v13) {
					return;
				}
			}
		}
	}
}
","SYS_OR_SIG"

"Lcom/android/server/lights/LightsService$LightsManagerBinderService","setLightStates(Landroid/os/IBinder;[I[Landroid/hardware/lights/LightState;)V","0","5 = getfield < Application, Lcom/android/server/lights/LightsService$LightsManagerBinderService, this$0, <Application,Lcom/android/server/lights/LightsService> > 1,
7 = invokevirtual < Application, Lcom/android/server/SystemService, getContext()Landroid/content/Context; > 5 @2 exception:6,
invokevirtual < Application, Landroid/content/Context, enforceCallingOrSelfPermission(Ljava/lang/String;Ljava/lang/String;)V > 7,8,9 @11 exception:10,
11 = arraylength 3,
12 = arraylength 4,
conditional branch(ne, to iindex=-1) 11,12,
goto (from iindex= 12 to iindex = 2),
15 = phi  13,14,
invokestatic < Application, Lcom/android/internal/util/Preconditions, checkState(Z)V > 15 @23 exception:16,
17 = getfield < Application, Lcom/android/server/lights/LightsService$LightsManagerBinderService, this$0, <Application,Lcom/android/server/lights/LightsService> > 1,
monitorenter 17,
19 = invokestatic < Application, Lcom/android/internal/util/Preconditions, checkNotNull(Ljava/lang/Object;)Ljava/lang/Object; > 2 @29 exception:18,
20 = checkcast <Application,Landroid/os/IBinder>19 <Application,Landroid/os/IBinder>,
22 = invokevirtual < Application, Lcom/android/server/lights/LightsService$LightsManagerBinderService, getSessionLocked(Landroid/os/IBinder;)Lcom/android/server/lights/LightsService$LightsManagerBinderService$Session; > 1,20 @35 exception:21,
conditional branch(eq, to iindex=-1) 22,14,
goto (from iindex= 23 to iindex = 2),
23 = phi  13,14,
invokestatic < Application, Lcom/android/internal/util/Preconditions, checkState(ZLjava/lang/String;)V > 23,24 @46 exception:25,
invokevirtual < Application, Lcom/android/server/lights/LightsService$LightsManagerBinderService, checkRequestIsValid([I)V > 1,3 @49 exception:26,
35 = phi  32,14,
27 = arraylength 3,
conditional branch(ge, to iindex=-1) 35,27,
invokevirtual < Application, Lcom/android/server/lights/LightsService$LightsManagerBinderService, invalidateLightStatesLocked()V > 1 @65 exception:37,
monitorexit 17,
return,","depth : 0
-----
","public void setLightStates(IBinder p1, [I p2, LightState p3){
	if (p2.length != p3.length) {
		Preconditions.checkState();
		Object v4 = Preconditions.checkNotNull(p1);
		LightsService$LightsManagerBinderService$Session v5 = p0.getSessionLocked(v4);
		if (v5 == 0) {
			Preconditions.checkState(, ""not registered"");
			p0.checkRequestIsValid(p2);
			if ( >= p2.length) {
				p0.invalidateLightStatesLocked();
				return;
			}
		}
	}
}
","SYS_OR_SIG"
"Lcom/android/server/lights/LightsService$LightsManagerBinderService","setLightStates(Landroid/os/IBinder;[I[Landroid/hardware/lights/LightState;)V","1","5 = getfield < Application, Lcom/android/server/lights/LightsService$LightsManagerBinderService, this$0, <Application,Lcom/android/server/lights/LightsService> > 1,
7 = invokevirtual < Application, Lcom/android/server/SystemService, getContext()Landroid/content/Context; > 5 @2 exception:6,
invokevirtual < Application, Landroid/content/Context, enforceCallingOrSelfPermission(Ljava/lang/String;Ljava/lang/String;)V > 7,8,9 @11 exception:10,
11 = arraylength 3,
12 = arraylength 4,
conditional branch(ne, to iindex=-1) 11,12,
goto (from iindex= 12 to iindex = 2),
15 = phi  13,14,
invokestatic < Application, Lcom/android/internal/util/Preconditions, checkState(Z)V > 15 @23 exception:16,
17 = getfield < Application, Lcom/android/server/lights/LightsService$LightsManagerBinderService, this$0, <Application,Lcom/android/server/lights/LightsService> > 1,
monitorenter 17,
19 = invokestatic < Application, Lcom/android/internal/util/Preconditions, checkNotNull(Ljava/lang/Object;)Ljava/lang/Object; > 2 @29 exception:18,
20 = checkcast <Application,Landroid/os/IBinder>19 <Application,Landroid/os/IBinder>,
22 = invokevirtual < Application, Lcom/android/server/lights/LightsService$LightsManagerBinderService, getSessionLocked(Landroid/os/IBinder;)Lcom/android/server/lights/LightsService$LightsManagerBinderService$Session; > 1,20 @35 exception:21,
16 = phi  15,3,
4 = getfield < Application, Lcom/android/server/lights/LightsService$LightsManagerBinderService, mSessions, <Application,Ljava/util/List> > 1,
6 = invokeinterface < Application, Ljava/util/List, size()I > 4 @3 exception:5,
conditional branch(ge, to iindex=-1) 16,6,
7 = getfield < Application, Lcom/android/server/lights/LightsService$LightsManagerBinderService, mSessions, <Application,Ljava/util/List> > 1,
9 = invokeinterface < Application, Ljava/util/List, get(I)Ljava/lang/Object; > 7,16 @11 exception:8,
10 = checkcast <Application,Lcom/android/server/lights/LightsService$LightsManagerBinderService$Session>9 <Application,Lcom/android/server/lights/LightsService$LightsManagerBinderService$Session>,
11 = getfield < Application, Lcom/android/server/lights/LightsService$LightsManagerBinderService$Session, mToken, <Application,Landroid/os/IBinder> > 10,
13 = invokevirtual < Application, Ljava/lang/Object, equals(Ljava/lang/Object;)Z > 2,11 @19 exception:12,
conditional branch(eq, to iindex=-1) 13,3,
17 = getfield < Application, Lcom/android/server/lights/LightsService$LightsManagerBinderService, mSessions, <Application,Ljava/util/List> > 1,
19 = invokeinterface < Application, Ljava/util/List, get(I)Ljava/lang/Object; > 17,16 @27 exception:18,
20 = checkcast <Application,Lcom/android/server/lights/LightsService$LightsManagerBinderService$Session>19 <Application,Lcom/android/server/lights/LightsService$LightsManagerBinderService$Session>,
return 20,
conditional branch(eq, to iindex=-1) 22,14,
goto (from iindex= 23 to iindex = 2),
23 = phi  13,14,
invokestatic < Application, Lcom/android/internal/util/Preconditions, checkState(ZLjava/lang/String;)V > 23,24 @46 exception:25,
invokevirtual < Application, Lcom/android/server/lights/LightsService$LightsManagerBinderService, checkRequestIsValid([I)V > 1,3 @49 exception:26,
3 = arraylength 2,
33 = phi  32,4,
conditional branch(ge, to iindex=-1) 33,3,
return,
35 = phi  32,14,
27 = arraylength 3,
conditional branch(ge, to iindex=-1) 35,27,
invokevirtual < Application, Lcom/android/server/lights/LightsService$LightsManagerBinderService, invalidateLightStatesLocked()V > 1 @65 exception:37,
2 = new <Application,Ljava/util/HashMap>@0,
invokespecial < Application, Ljava/util/HashMap, <init>()V > 2 @2 exception:3,
4 = getfield < Application, Lcom/android/server/lights/LightsService$LightsManagerBinderService, mSessions, <Application,Ljava/util/List> > 1,
6 = invokeinterface < Application, Ljava/util/List, size()I > 4 @7 exception:5,
8 = binaryop(add) 6 , 7,
32 = phi  31,8,
conditional branch(lt, to iindex=-1) 32,9,
67 = phi  9,65,
37 = getfield < Application, Lcom/android/server/lights/LightsService$LightsManagerBinderService, this$0, <Application,Lcom/android/server/lights/LightsService> > 1,
39 = invokestatic < Application, Lcom/android/server/lights/LightsService, -$$Nest$fgetmLightsById(Lcom/android/server/lights/LightsService;)Landroid/util/SparseArray; > 37 @57 exception:38,
41 = invokevirtual < Application, Landroid/util/SparseArray, size()I > 39 @61 exception:40,
conditional branch(ge, to iindex=-1) 67,41,
return,
monitorexit 17,
return,","depth : 0
-----
depth : 1
-----
depth : 1
-----
depth : 1
-----
","public void setLightStates(IBinder p1, [I p2, LightState p3){
	if (p2.length != p3.length) {
		Preconditions.checkState();
		Object v4 = Preconditions.checkNotNull(p1);
		int v6 = this.mSessions.size();
		if ( >= v6) {
			Object v7 = this.mSessions.get();
			boolean v8 = v4.equals(LightsService$LightsManagerBinderService$Session.mToken);
			if (v8 == 0) {
				Object v9 = this.mSessions.get();
				LightsService$LightsManagerBinderService$Session v5 = v9;
				if (v5 == 0) {
					Preconditions.checkState(, ""not registered"");
					if ( >= p2.length) {
						if ( >= p2.length) {
							HashMap v13 = new HashMap();
							int v15 = this.mSessions.size();
							if ( < 0) {
								SparseArray v16 = LightsService.-$$Nest$fgetmLightsById(this.this$0);
								int v17 = v16.size();
								if ( >= v17) {
									return;
								}
							}
						}
					}
				}
			}
		}
	}
}
","SYS_OR_SIG"
"Lcom/android/server/lights/LightsService$LightsManagerBinderService","setLightStates(Landroid/os/IBinder;[I[Landroid/hardware/lights/LightState;)V","1","5 = getfield < Application, Lcom/android/server/lights/LightsService$LightsManagerBinderService, this$0, <Application,Lcom/android/server/lights/LightsService> > 1,
7 = invokevirtual < Application, Lcom/android/server/SystemService, getContext()Landroid/content/Context; > 5 @2 exception:6,
invokevirtual < Application, Landroid/content/Context, enforceCallingOrSelfPermission(Ljava/lang/String;Ljava/lang/String;)V > 7,8,9 @11 exception:10,
11 = arraylength 3,
12 = arraylength 4,
conditional branch(ne, to iindex=-1) 11,12,
goto (from iindex= 12 to iindex = 2),
15 = phi  13,14,
invokestatic < Application, Lcom/android/internal/util/Preconditions, checkState(Z)V > 15 @23 exception:16,
17 = getfield < Application, Lcom/android/server/lights/LightsService$LightsManagerBinderService, this$0, <Application,Lcom/android/server/lights/LightsService> > 1,
monitorenter 17,
19 = invokestatic < Application, Lcom/android/internal/util/Preconditions, checkNotNull(Ljava/lang/Object;)Ljava/lang/Object; > 2 @29 exception:18,
20 = checkcast <Application,Landroid/os/IBinder>19 <Application,Landroid/os/IBinder>,
22 = invokevirtual < Application, Lcom/android/server/lights/LightsService$LightsManagerBinderService, getSessionLocked(Landroid/os/IBinder;)Lcom/android/server/lights/LightsService$LightsManagerBinderService$Session; > 1,20 @35 exception:21,
16 = phi  15,3,
4 = getfield < Application, Lcom/android/server/lights/LightsService$LightsManagerBinderService, mSessions, <Application,Ljava/util/List> > 1,
6 = invokeinterface < Application, Ljava/util/List, size()I > 4 @3 exception:5,
conditional branch(ge, to iindex=-1) 16,6,
7 = getfield < Application, Lcom/android/server/lights/LightsService$LightsManagerBinderService, mSessions, <Application,Ljava/util/List> > 1,
9 = invokeinterface < Application, Ljava/util/List, get(I)Ljava/lang/Object; > 7,16 @11 exception:8,
10 = checkcast <Application,Lcom/android/server/lights/LightsService$LightsManagerBinderService$Session>9 <Application,Lcom/android/server/lights/LightsService$LightsManagerBinderService$Session>,
11 = getfield < Application, Lcom/android/server/lights/LightsService$LightsManagerBinderService$Session, mToken, <Application,Landroid/os/IBinder> > 10,
13 = invokevirtual < Application, Ljava/lang/Object, equals(Ljava/lang/Object;)Z > 2,11 @19 exception:12,
conditional branch(eq, to iindex=-1) 13,3,
17 = getfield < Application, Lcom/android/server/lights/LightsService$LightsManagerBinderService, mSessions, <Application,Ljava/util/List> > 1,
19 = invokeinterface < Application, Ljava/util/List, get(I)Ljava/lang/Object; > 17,16 @27 exception:18,
20 = checkcast <Application,Lcom/android/server/lights/LightsService$LightsManagerBinderService$Session>19 <Application,Lcom/android/server/lights/LightsService$LightsManagerBinderService$Session>,
return 20,
conditional branch(eq, to iindex=-1) 22,14,
23 = phi  13,14,
invokestatic < Application, Lcom/android/internal/util/Preconditions, checkState(ZLjava/lang/String;)V > 23,24 @46 exception:25,
invokevirtual < Application, Lcom/android/server/lights/LightsService$LightsManagerBinderService, checkRequestIsValid([I)V > 1,3 @49 exception:26,
3 = arraylength 2,
33 = phi  32,4,
conditional branch(ge, to iindex=-1) 33,3,
return,
35 = phi  32,14,
27 = arraylength 3,
conditional branch(ge, to iindex=-1) 35,27,
invokevirtual < Application, Lcom/android/server/lights/LightsService$LightsManagerBinderService, invalidateLightStatesLocked()V > 1 @65 exception:37,
2 = new <Application,Ljava/util/HashMap>@0,
invokespecial < Application, Ljava/util/HashMap, <init>()V > 2 @2 exception:3,
4 = getfield < Application, Lcom/android/server/lights/LightsService$LightsManagerBinderService, mSessions, <Application,Ljava/util/List> > 1,
6 = invokeinterface < Application, Ljava/util/List, size()I > 4 @7 exception:5,
8 = binaryop(add) 6 , 7,
32 = phi  31,8,
conditional branch(lt, to iindex=-1) 32,9,
67 = phi  9,65,
37 = getfield < Application, Lcom/android/server/lights/LightsService$LightsManagerBinderService, this$0, <Application,Lcom/android/server/lights/LightsService> > 1,
39 = invokestatic < Application, Lcom/android/server/lights/LightsService, -$$Nest$fgetmLightsById(Lcom/android/server/lights/LightsService;)Landroid/util/SparseArray; > 37 @57 exception:38,
41 = invokevirtual < Application, Landroid/util/SparseArray, size()I > 39 @61 exception:40,
conditional branch(ge, to iindex=-1) 67,41,
return,
monitorexit 17,
return,","depth : 0
-----
depth : 1
-----
depth : 1
-----
depth : 1
-----
","public void setLightStates(IBinder p1, [I p2, LightState p3){
	if (p2.length != p3.length) {
		Preconditions.checkState();
		Object v4 = Preconditions.checkNotNull(p1);
		int v6 = this.mSessions.size();
		if ( >= v6) {
			Object v7 = this.mSessions.get();
			boolean v8 = v4.equals(LightsService$LightsManagerBinderService$Session.mToken);
			if (v8 == 0) {
				Object v9 = this.mSessions.get();
				LightsService$LightsManagerBinderService$Session v5 = v9;
				if (v5 == 0) {
					Preconditions.checkState(, ""not registered"");
					if ( >= p2.length) {
						if ( >= p2.length) {
							HashMap v13 = new HashMap();
							int v15 = this.mSessions.size();
							if ( < 0) {
								SparseArray v16 = LightsService.-$$Nest$fgetmLightsById(this.this$0);
								int v17 = v16.size();
								if ( >= v17) {
									return;
								}
							}
						}
					}
				}
			}
		}
	}
}
","SYS_OR_SIG"
"Lcom/android/server/lights/LightsService$LightsManagerBinderService","setLightStates(Landroid/os/IBinder;[I[Landroid/hardware/lights/LightState;)V","2","5 = getfield < Application, Lcom/android/server/lights/LightsService$LightsManagerBinderService, this$0, <Application,Lcom/android/server/lights/LightsService> > 1,
7 = invokevirtual < Application, Lcom/android/server/SystemService, getContext()Landroid/content/Context; > 5 @2 exception:6,
invokevirtual < Application, Landroid/content/Context, enforceCallingOrSelfPermission(Ljava/lang/String;Ljava/lang/String;)V > 7,8,9 @11 exception:10,
11 = arraylength 3,
12 = arraylength 4,
conditional branch(ne, to iindex=-1) 11,12,
goto (from iindex= 12 to iindex = 2),
15 = phi  13,14,
invokestatic < Application, Lcom/android/internal/util/Preconditions, checkState(Z)V > 15 @23 exception:16,
17 = getfield < Application, Lcom/android/server/lights/LightsService$LightsManagerBinderService, this$0, <Application,Lcom/android/server/lights/LightsService> > 1,
monitorenter 17,
19 = invokestatic < Application, Lcom/android/internal/util/Preconditions, checkNotNull(Ljava/lang/Object;)Ljava/lang/Object; > 2 @29 exception:18,
20 = checkcast <Application,Landroid/os/IBinder>19 <Application,Landroid/os/IBinder>,
22 = invokevirtual < Application, Lcom/android/server/lights/LightsService$LightsManagerBinderService, getSessionLocked(Landroid/os/IBinder;)Lcom/android/server/lights/LightsService$LightsManagerBinderService$Session; > 1,20 @35 exception:21,
16 = phi  15,3,
4 = getfield < Application, Lcom/android/server/lights/LightsService$LightsManagerBinderService, mSessions, <Application,Ljava/util/List> > 1,
6 = invokeinterface < Application, Ljava/util/List, size()I > 4 @3 exception:5,
conditional branch(ge, to iindex=-1) 16,6,
7 = getfield < Application, Lcom/android/server/lights/LightsService$LightsManagerBinderService, mSessions, <Application,Ljava/util/List> > 1,
9 = invokeinterface < Application, Ljava/util/List, get(I)Ljava/lang/Object; > 7,16 @11 exception:8,
10 = checkcast <Application,Lcom/android/server/lights/LightsService$LightsManagerBinderService$Session>9 <Application,Lcom/android/server/lights/LightsService$LightsManagerBinderService$Session>,
11 = getfield < Application, Lcom/android/server/lights/LightsService$LightsManagerBinderService$Session, mToken, <Application,Landroid/os/IBinder> > 10,
13 = invokevirtual < Application, Ljava/lang/Object, equals(Ljava/lang/Object;)Z > 2,11 @19 exception:12,
conditional branch(eq, to iindex=-1) 13,3,
17 = getfield < Application, Lcom/android/server/lights/LightsService$LightsManagerBinderService, mSessions, <Application,Ljava/util/List> > 1,
19 = invokeinterface < Application, Ljava/util/List, get(I)Ljava/lang/Object; > 17,16 @27 exception:18,
20 = checkcast <Application,Lcom/android/server/lights/LightsService$LightsManagerBinderService$Session>19 <Application,Lcom/android/server/lights/LightsService$LightsManagerBinderService$Session>,
return 20,
conditional branch(eq, to iindex=-1) 22,14,
goto (from iindex= 23 to iindex = 2),
23 = phi  13,14,
invokestatic < Application, Lcom/android/internal/util/Preconditions, checkState(ZLjava/lang/String;)V > 23,24 @46 exception:25,
invokevirtual < Application, Lcom/android/server/lights/LightsService$LightsManagerBinderService, checkRequestIsValid([I)V > 1,3 @49 exception:26,
3 = arraylength 2,
33 = phi  32,4,
conditional branch(ge, to iindex=-1) 33,3,
return,
35 = phi  32,14,
27 = arraylength 3,
conditional branch(ge, to iindex=-1) 35,27,
invokevirtual < Application, Lcom/android/server/lights/LightsService$LightsManagerBinderService, invalidateLightStatesLocked()V > 1 @65 exception:37,
2 = new <Application,Ljava/util/HashMap>@0,
invokespecial < Application, Ljava/util/HashMap, <init>()V > 2 @2 exception:3,
4 = getfield < Application, Lcom/android/server/lights/LightsService$LightsManagerBinderService, mSessions, <Application,Ljava/util/List> > 1,
6 = invokeinterface < Application, Ljava/util/List, size()I > 4 @7 exception:5,
8 = binaryop(add) 6 , 7,
32 = phi  31,8,
conditional branch(lt, to iindex=-1) 32,9,
67 = phi  9,65,
37 = getfield < Application, Lcom/android/server/lights/LightsService$LightsManagerBinderService, this$0, <Application,Lcom/android/server/lights/LightsService> > 1,
39 = invokestatic < Application, Lcom/android/server/lights/LightsService, -$$Nest$fgetmLightsById(Lcom/android/server/lights/LightsService;)Landroid/util/SparseArray; > 37 @57 exception:38,
2 = getfield < Application, Lcom/android/server/lights/LightsService, mLightsById, <Application,Landroid/util/SparseArray> > 1,
return 2,
41 = invokevirtual < Application, Landroid/util/SparseArray, size()I > 39 @61 exception:40,
conditional branch(ge, to iindex=-1) 67,41,
return,
monitorexit 17,
return,","depth : 0
-----
depth : 1
-----
depth : 1
-----
depth : 1
-----
depth : 2
-----
","public void setLightStates(IBinder p1, [I p2, LightState p3){
	if (p2.length != p3.length) {
		Preconditions.checkState();
		Object v4 = Preconditions.checkNotNull(p1);
		int v6 = this.mSessions.size();
		if ( >= v6) {
			Object v7 = this.mSessions.get();
			boolean v8 = v4.equals(LightsService$LightsManagerBinderService$Session.mToken);
			if (v8 == 0) {
				Object v9 = this.mSessions.get();
				LightsService$LightsManagerBinderService$Session v5 = v9;
				if (v5 == 0) {
					Preconditions.checkState(, ""not registered"");
					if ( >= p2.length) {
						if ( >= p2.length) {
							HashMap v13 = new HashMap();
							int v15 = this.mSessions.size();
							if ( < 0) {
								SparseArray v16 = this.mLightsById;
								int v17 = v16.size();
								if ( >= v17) {
									return;
								}
							}
						}
					}
				}
			}
		}
	}
}
","SYS_OR_SIG"
"Lcom/android/server/lights/LightsService$LightsManagerBinderService","setLightStates(Landroid/os/IBinder;[I[Landroid/hardware/lights/LightState;)V","2","5 = getfield < Application, Lcom/android/server/lights/LightsService$LightsManagerBinderService, this$0, <Application,Lcom/android/server/lights/LightsService> > 1,
7 = invokevirtual < Application, Lcom/android/server/SystemService, getContext()Landroid/content/Context; > 5 @2 exception:6,
invokevirtual < Application, Landroid/content/Context, enforceCallingOrSelfPermission(Ljava/lang/String;Ljava/lang/String;)V > 7,8,9 @11 exception:10,
11 = arraylength 3,
12 = arraylength 4,
conditional branch(ne, to iindex=-1) 11,12,
goto (from iindex= 12 to iindex = 2),
15 = phi  13,14,
invokestatic < Application, Lcom/android/internal/util/Preconditions, checkState(Z)V > 15 @23 exception:16,
17 = getfield < Application, Lcom/android/server/lights/LightsService$LightsManagerBinderService, this$0, <Application,Lcom/android/server/lights/LightsService> > 1,
monitorenter 17,
19 = invokestatic < Application, Lcom/android/internal/util/Preconditions, checkNotNull(Ljava/lang/Object;)Ljava/lang/Object; > 2 @29 exception:18,
20 = checkcast <Application,Landroid/os/IBinder>19 <Application,Landroid/os/IBinder>,
22 = invokevirtual < Application, Lcom/android/server/lights/LightsService$LightsManagerBinderService, getSessionLocked(Landroid/os/IBinder;)Lcom/android/server/lights/LightsService$LightsManagerBinderService$Session; > 1,20 @35 exception:21,
16 = phi  15,3,
4 = getfield < Application, Lcom/android/server/lights/LightsService$LightsManagerBinderService, mSessions, <Application,Ljava/util/List> > 1,
6 = invokeinterface < Application, Ljava/util/List, size()I > 4 @3 exception:5,
conditional branch(ge, to iindex=-1) 16,6,
7 = getfield < Application, Lcom/android/server/lights/LightsService$LightsManagerBinderService, mSessions, <Application,Ljava/util/List> > 1,
9 = invokeinterface < Application, Ljava/util/List, get(I)Ljava/lang/Object; > 7,16 @11 exception:8,
10 = checkcast <Application,Lcom/android/server/lights/LightsService$LightsManagerBinderService$Session>9 <Application,Lcom/android/server/lights/LightsService$LightsManagerBinderService$Session>,
11 = getfield < Application, Lcom/android/server/lights/LightsService$LightsManagerBinderService$Session, mToken, <Application,Landroid/os/IBinder> > 10,
13 = invokevirtual < Application, Ljava/lang/Object, equals(Ljava/lang/Object;)Z > 2,11 @19 exception:12,
conditional branch(eq, to iindex=-1) 13,3,
17 = getfield < Application, Lcom/android/server/lights/LightsService$LightsManagerBinderService, mSessions, <Application,Ljava/util/List> > 1,
19 = invokeinterface < Application, Ljava/util/List, get(I)Ljava/lang/Object; > 17,16 @27 exception:18,
20 = checkcast <Application,Lcom/android/server/lights/LightsService$LightsManagerBinderService$Session>19 <Application,Lcom/android/server/lights/LightsService$LightsManagerBinderService$Session>,
return 20,
conditional branch(eq, to iindex=-1) 22,14,
23 = phi  13,14,
invokestatic < Application, Lcom/android/internal/util/Preconditions, checkState(ZLjava/lang/String;)V > 23,24 @46 exception:25,
invokevirtual < Application, Lcom/android/server/lights/LightsService$LightsManagerBinderService, checkRequestIsValid([I)V > 1,3 @49 exception:26,
3 = arraylength 2,
33 = phi  32,4,
conditional branch(ge, to iindex=-1) 33,3,
return,
35 = phi  32,14,
27 = arraylength 3,
conditional branch(ge, to iindex=-1) 35,27,
invokevirtual < Application, Lcom/android/server/lights/LightsService$LightsManagerBinderService, invalidateLightStatesLocked()V > 1 @65 exception:37,
2 = new <Application,Ljava/util/HashMap>@0,
invokespecial < Application, Ljava/util/HashMap, <init>()V > 2 @2 exception:3,
4 = getfield < Application, Lcom/android/server/lights/LightsService$LightsManagerBinderService, mSessions, <Application,Ljava/util/List> > 1,
6 = invokeinterface < Application, Ljava/util/List, size()I > 4 @7 exception:5,
8 = binaryop(add) 6 , 7,
32 = phi  31,8,
conditional branch(lt, to iindex=-1) 32,9,
67 = phi  9,65,
37 = getfield < Application, Lcom/android/server/lights/LightsService$LightsManagerBinderService, this$0, <Application,Lcom/android/server/lights/LightsService> > 1,
39 = invokestatic < Application, Lcom/android/server/lights/LightsService, -$$Nest$fgetmLightsById(Lcom/android/server/lights/LightsService;)Landroid/util/SparseArray; > 37 @57 exception:38,
2 = getfield < Application, Lcom/android/server/lights/LightsService, mLightsById, <Application,Landroid/util/SparseArray> > 1,
return 2,
41 = invokevirtual < Application, Landroid/util/SparseArray, size()I > 39 @61 exception:40,
conditional branch(ge, to iindex=-1) 67,41,
return,
monitorexit 17,
return,","depth : 0
-----
depth : 1
-----
depth : 1
-----
depth : 1
-----
depth : 2
-----
","public void setLightStates(IBinder p1, [I p2, LightState p3){
	if (p2.length != p3.length) {
		Preconditions.checkState();
		Object v4 = Preconditions.checkNotNull(p1);
		int v6 = this.mSessions.size();
		if ( >= v6) {
			Object v7 = this.mSessions.get();
			boolean v8 = v4.equals(LightsService$LightsManagerBinderService$Session.mToken);
			if (v8 == 0) {
				Object v9 = this.mSessions.get();
				LightsService$LightsManagerBinderService$Session v5 = v9;
				if (v5 == 0) {
					Preconditions.checkState(, ""not registered"");
					if ( >= p2.length) {
						if ( >= p2.length) {
							HashMap v13 = new HashMap();
							int v15 = this.mSessions.size();
							if ( < 0) {
								SparseArray v16 = this.mLightsById;
								int v17 = v16.size();
								if ( >= v17) {
									return;
								}
							}
						}
					}
				}
			}
		}
	}
}
","SYS_OR_SIG"
"Lcom/android/server/lights/LightsService$LightsManagerBinderService","setLightStates(Landroid/os/IBinder;[I[Landroid/hardware/lights/LightState;)V","2","5 = getfield < Application, Lcom/android/server/lights/LightsService$LightsManagerBinderService, this$0, <Application,Lcom/android/server/lights/LightsService> > 1,
7 = invokevirtual < Application, Lcom/android/server/SystemService, getContext()Landroid/content/Context; > 5 @2 exception:6,
invokevirtual < Application, Landroid/content/Context, enforceCallingOrSelfPermission(Ljava/lang/String;Ljava/lang/String;)V > 7,8,9 @11 exception:10,
11 = arraylength 3,
12 = arraylength 4,
conditional branch(ne, to iindex=-1) 11,12,
15 = phi  13,14,
invokestatic < Application, Lcom/android/internal/util/Preconditions, checkState(Z)V > 15 @23 exception:16,
17 = getfield < Application, Lcom/android/server/lights/LightsService$LightsManagerBinderService, this$0, <Application,Lcom/android/server/lights/LightsService> > 1,
monitorenter 17,
19 = invokestatic < Application, Lcom/android/internal/util/Preconditions, checkNotNull(Ljava/lang/Object;)Ljava/lang/Object; > 2 @29 exception:18,
20 = checkcast <Application,Landroid/os/IBinder>19 <Application,Landroid/os/IBinder>,
22 = invokevirtual < Application, Lcom/android/server/lights/LightsService$LightsManagerBinderService, getSessionLocked(Landroid/os/IBinder;)Lcom/android/server/lights/LightsService$LightsManagerBinderService$Session; > 1,20 @35 exception:21,
16 = phi  15,3,
4 = getfield < Application, Lcom/android/server/lights/LightsService$LightsManagerBinderService, mSessions, <Application,Ljava/util/List> > 1,
6 = invokeinterface < Application, Ljava/util/List, size()I > 4 @3 exception:5,
conditional branch(ge, to iindex=-1) 16,6,
7 = getfield < Application, Lcom/android/server/lights/LightsService$LightsManagerBinderService, mSessions, <Application,Ljava/util/List> > 1,
9 = invokeinterface < Application, Ljava/util/List, get(I)Ljava/lang/Object; > 7,16 @11 exception:8,
10 = checkcast <Application,Lcom/android/server/lights/LightsService$LightsManagerBinderService$Session>9 <Application,Lcom/android/server/lights/LightsService$LightsManagerBinderService$Session>,
11 = getfield < Application, Lcom/android/server/lights/LightsService$LightsManagerBinderService$Session, mToken, <Application,Landroid/os/IBinder> > 10,
13 = invokevirtual < Application, Ljava/lang/Object, equals(Ljava/lang/Object;)Z > 2,11 @19 exception:12,
conditional branch(eq, to iindex=-1) 13,3,
17 = getfield < Application, Lcom/android/server/lights/LightsService$LightsManagerBinderService, mSessions, <Application,Ljava/util/List> > 1,
19 = invokeinterface < Application, Ljava/util/List, get(I)Ljava/lang/Object; > 17,16 @27 exception:18,
20 = checkcast <Application,Lcom/android/server/lights/LightsService$LightsManagerBinderService$Session>19 <Application,Lcom/android/server/lights/LightsService$LightsManagerBinderService$Session>,
return 20,
conditional branch(eq, to iindex=-1) 22,14,
goto (from iindex= 23 to iindex = 2),
23 = phi  13,14,
invokestatic < Application, Lcom/android/internal/util/Preconditions, checkState(ZLjava/lang/String;)V > 23,24 @46 exception:25,
invokevirtual < Application, Lcom/android/server/lights/LightsService$LightsManagerBinderService, checkRequestIsValid([I)V > 1,3 @49 exception:26,
3 = arraylength 2,
33 = phi  32,4,
conditional branch(ge, to iindex=-1) 33,3,
return,
35 = phi  32,14,
27 = arraylength 3,
conditional branch(ge, to iindex=-1) 35,27,
invokevirtual < Application, Lcom/android/server/lights/LightsService$LightsManagerBinderService, invalidateLightStatesLocked()V > 1 @65 exception:37,
2 = new <Application,Ljava/util/HashMap>@0,
invokespecial < Application, Ljava/util/HashMap, <init>()V > 2 @2 exception:3,
4 = getfield < Application, Lcom/android/server/lights/LightsService$LightsManagerBinderService, mSessions, <Application,Ljava/util/List> > 1,
6 = invokeinterface < Application, Ljava/util/List, size()I > 4 @7 exception:5,
8 = binaryop(add) 6 , 7,
32 = phi  31,8,
conditional branch(lt, to iindex=-1) 32,9,
67 = phi  9,65,
37 = getfield < Application, Lcom/android/server/lights/LightsService$LightsManagerBinderService, this$0, <Application,Lcom/android/server/lights/LightsService> > 1,
39 = invokestatic < Application, Lcom/android/server/lights/LightsService, -$$Nest$fgetmLightsById(Lcom/android/server/lights/LightsService;)Landroid/util/SparseArray; > 37 @57 exception:38,
2 = getfield < Application, Lcom/android/server/lights/LightsService, mLightsById, <Application,Landroid/util/SparseArray> > 1,
return 2,
41 = invokevirtual < Application, Landroid/util/SparseArray, size()I > 39 @61 exception:40,
conditional branch(ge, to iindex=-1) 67,41,
return,
monitorexit 17,
return,","depth : 0
-----
depth : 1
-----
depth : 1
-----
depth : 1
-----
depth : 2
-----
","public void setLightStates(IBinder p1, [I p2, LightState p3){
	if (p2.length != p3.length) {
		Preconditions.checkState();
		Object v4 = Preconditions.checkNotNull(p1);
		int v6 = this.mSessions.size();
		if ( >= v6) {
			Object v7 = this.mSessions.get();
			boolean v8 = v4.equals(LightsService$LightsManagerBinderService$Session.mToken);
			if (v8 == 0) {
				Object v9 = this.mSessions.get();
				LightsService$LightsManagerBinderService$Session v5 = v9;
				if (v5 == 0) {
					Preconditions.checkState(, ""not registered"");
					if ( >= p2.length) {
						if ( >= p2.length) {
							HashMap v13 = new HashMap();
							int v15 = this.mSessions.size();
							if ( < 0) {
								SparseArray v16 = this.mLightsById;
								int v17 = v16.size();
								if ( >= v17) {
									return;
								}
							}
						}
					}
				}
			}
		}
	}
}
","SYS_OR_SIG"

"Lcom/android/server/lights/LightsService$LightsManagerBinderService","getLights()Ljava/util/List;","0","2 = getfield < Application, Lcom/android/server/lights/LightsService$LightsManagerBinderService, this$0, <Application,Lcom/android/server/lights/LightsService> > 1,
4 = invokevirtual < Application, Lcom/android/server/SystemService, getContext()Landroid/content/Context; > 2 @2 exception:3,
invokevirtual < Application, Landroid/content/Context, enforceCallingOrSelfPermission(Ljava/lang/String;Ljava/lang/String;)V > 4,5,6 @10 exception:7,
8 = getfield < Application, Lcom/android/server/lights/LightsService$LightsManagerBinderService, this$0, <Application,Lcom/android/server/lights/LightsService> > 1,
monitorenter 8,
9 = new <Application,Ljava/util/ArrayList>@16,
invokespecial < Application, Ljava/util/ArrayList, <init>()V > 9 @18 exception:10,
45 = phi  44,11,
12 = getfield < Application, Lcom/android/server/lights/LightsService$LightsManagerBinderService, this$0, <Application,Lcom/android/server/lights/LightsService> > 1,
14 = invokestatic < Application, Lcom/android/server/lights/LightsService, -$$Nest$fgetmLightsById(Lcom/android/server/lights/LightsService;)Landroid/util/SparseArray; > 12 @24 exception:13,
16 = invokevirtual < Application, Landroid/util/SparseArray, size()I > 14 @28 exception:15,
conditional branch(ge, to iindex=-1) 45,16,
monitorexit 8,
return 9,","depth : 0
-----
","public List getLights(){
	ArrayList v3 = new ArrayList();
	SparseArray v5 = LightsService.-$$Nest$fgetmLightsById(this.this$0);
	int v6 = v5.size();
	if ( >= v6) {
		return v3;
	}
}
","SYS_OR_SIG"
"Lcom/android/server/lights/LightsService$LightsManagerBinderService","getLights()Ljava/util/List;","1","2 = getfield < Application, Lcom/android/server/lights/LightsService$LightsManagerBinderService, this$0, <Application,Lcom/android/server/lights/LightsService> > 1,
4 = invokevirtual < Application, Lcom/android/server/SystemService, getContext()Landroid/content/Context; > 2 @2 exception:3,
invokevirtual < Application, Landroid/content/Context, enforceCallingOrSelfPermission(Ljava/lang/String;Ljava/lang/String;)V > 4,5,6 @10 exception:7,
8 = getfield < Application, Lcom/android/server/lights/LightsService$LightsManagerBinderService, this$0, <Application,Lcom/android/server/lights/LightsService> > 1,
monitorenter 8,
9 = new <Application,Ljava/util/ArrayList>@16,
invokespecial < Application, Ljava/util/ArrayList, <init>()V > 9 @18 exception:10,
45 = phi  44,11,
12 = getfield < Application, Lcom/android/server/lights/LightsService$LightsManagerBinderService, this$0, <Application,Lcom/android/server/lights/LightsService> > 1,
14 = invokestatic < Application, Lcom/android/server/lights/LightsService, -$$Nest$fgetmLightsById(Lcom/android/server/lights/LightsService;)Landroid/util/SparseArray; > 12 @24 exception:13,
2 = getfield < Application, Lcom/android/server/lights/LightsService, mLightsById, <Application,Landroid/util/SparseArray> > 1,
return 2,
16 = invokevirtual < Application, Landroid/util/SparseArray, size()I > 14 @28 exception:15,
conditional branch(ge, to iindex=-1) 45,16,
monitorexit 8,
return 9,","depth : 0
-----
depth : 1
-----
","public List getLights(){
	ArrayList v3 = new ArrayList();
	SparseArray v5 = this.mLightsById;
	int v6 = v5.size();
	if ( >= v6) {
		return v3;
	}
}
","SYS_OR_SIG"

"Lcom/android/server/lights/LightsService$LightsManagerBinderService","getLightState(I)Landroid/hardware/lights/LightState;","0","3 = getfield < Application, Lcom/android/server/lights/LightsService$LightsManagerBinderService, this$0, <Application,Lcom/android/server/lights/LightsService> > 1,
5 = invokevirtual < Application, Lcom/android/server/SystemService, getContext()Landroid/content/Context; > 3 @2 exception:4,
invokevirtual < Application, Landroid/content/Context, enforceCallingOrSelfPermission(Ljava/lang/String;Ljava/lang/String;)V > 5,6,7 @10 exception:8,
9 = getfield < Application, Lcom/android/server/lights/LightsService$LightsManagerBinderService, this$0, <Application,Lcom/android/server/lights/LightsService> > 1,
monitorenter 9,
10 = getfield < Application, Lcom/android/server/lights/LightsService$LightsManagerBinderService, this$0, <Application,Lcom/android/server/lights/LightsService> > 1,
12 = invokestatic < Application, Lcom/android/server/lights/LightsService, -$$Nest$fgetmLightsById(Lcom/android/server/lights/LightsService;)Landroid/util/SparseArray; > 10 @18 exception:11,
14 = invokevirtual < Application, Landroid/util/SparseArray, get(I)Ljava/lang/Object; > 12,2 @22 exception:13,
15 = checkcast <Application,Lcom/android/server/lights/LightsService$LightImpl>14 <Application,Lcom/android/server/lights/LightsService$LightImpl>,
conditional branch(eq, to iindex=-1) 15,16,
18 = invokestatic < Application, Lcom/android/server/lights/LightsService$LightImpl, -$$Nest$misSystemLight(Lcom/android/server/lights/LightsService$LightImpl;)Z > 15 @30 exception:17,
conditional branch(ne, to iindex=-1) 18,16,
33 = new <Application,Landroid/hardware/lights/LightState>@36,
35 = invokestatic < Application, Lcom/android/server/lights/LightsService$LightImpl, -$$Nest$mgetColor(Lcom/android/server/lights/LightsService$LightImpl;)I > 15 @38 exception:34,
invokespecial < Application, Landroid/hardware/lights/LightState, <init>(I)V > 33,35 @42 exception:36,
monitorexit 9,
return 33,","depth : 0
-----
","public LightState getLightState(int p1){
	SparseArray v3 = LightsService.-$$Nest$fgetmLightsById(this.this$0);
	Object v4 = v3.get(p1);
	if (v4 == 0) {
		boolean v5 = LightsService$LightImpl.-$$Nest$misSystemLight(v4);
		if (v5 != 0) {
			LightState v6 = new LightState(v7);
			int v7 = LightsService$LightImpl.-$$Nest$mgetColor(v4);
			return v6;
		}
	}
}
","SYS_OR_SIG"
"Lcom/android/server/lights/LightsService$LightsManagerBinderService","getLightState(I)Landroid/hardware/lights/LightState;","1","3 = getfield < Application, Lcom/android/server/lights/LightsService$LightsManagerBinderService, this$0, <Application,Lcom/android/server/lights/LightsService> > 1,
5 = invokevirtual < Application, Lcom/android/server/SystemService, getContext()Landroid/content/Context; > 3 @2 exception:4,
invokevirtual < Application, Landroid/content/Context, enforceCallingOrSelfPermission(Ljava/lang/String;Ljava/lang/String;)V > 5,6,7 @10 exception:8,
9 = getfield < Application, Lcom/android/server/lights/LightsService$LightsManagerBinderService, this$0, <Application,Lcom/android/server/lights/LightsService> > 1,
monitorenter 9,
10 = getfield < Application, Lcom/android/server/lights/LightsService$LightsManagerBinderService, this$0, <Application,Lcom/android/server/lights/LightsService> > 1,
12 = invokestatic < Application, Lcom/android/server/lights/LightsService, -$$Nest$fgetmLightsById(Lcom/android/server/lights/LightsService;)Landroid/util/SparseArray; > 10 @18 exception:11,
2 = getfield < Application, Lcom/android/server/lights/LightsService, mLightsById, <Application,Landroid/util/SparseArray> > 1,
return 2,
14 = invokevirtual < Application, Landroid/util/SparseArray, get(I)Ljava/lang/Object; > 12,2 @22 exception:13,
15 = checkcast <Application,Lcom/android/server/lights/LightsService$LightImpl>14 <Application,Lcom/android/server/lights/LightsService$LightImpl>,
conditional branch(eq, to iindex=-1) 15,16,
18 = invokestatic < Application, Lcom/android/server/lights/LightsService$LightImpl, -$$Nest$misSystemLight(Lcom/android/server/lights/LightsService$LightImpl;)Z > 15 @30 exception:17,
3 = invokevirtual < Application, Lcom/android/server/lights/LightsService$LightImpl, isSystemLight()Z > 1 @0 exception:2,
return 3,
conditional branch(ne, to iindex=-1) 18,16,
33 = new <Application,Landroid/hardware/lights/LightState>@36,
35 = invokestatic < Application, Lcom/android/server/lights/LightsService$LightImpl, -$$Nest$mgetColor(Lcom/android/server/lights/LightsService$LightImpl;)I > 15 @38 exception:34,
3 = invokevirtual < Application, Lcom/android/server/lights/LightsService$LightImpl, getColor()I > 1 @0 exception:2,
return 3,
invokespecial < Application, Landroid/hardware/lights/LightState, <init>(I)V > 33,35 @42 exception:36,
monitorexit 9,
return 33,","depth : 0
-----
depth : 1
-----
depth : 1
-----
depth : 1
-----
","public LightState getLightState(int p1){
	SparseArray v3 = this.mLightsById;
	Object v4 = v3.get(p1);
	if (v4 == 0) {
		boolean v6 = v4.isSystemLight();
		boolean v5 = v6;
		if (v5 != 0) {
			LightState v7 = new LightState(v8);
			int v9 = v4.getColor();
			int v8 = v9;
			return v7;
		}
	}
}
","SYS_OR_SIG"
"Lcom/android/server/lights/LightsService$LightsManagerBinderService","getLightState(I)Landroid/hardware/lights/LightState;","2","3 = getfield < Application, Lcom/android/server/lights/LightsService$LightsManagerBinderService, this$0, <Application,Lcom/android/server/lights/LightsService> > 1,
5 = invokevirtual < Application, Lcom/android/server/SystemService, getContext()Landroid/content/Context; > 3 @2 exception:4,
invokevirtual < Application, Landroid/content/Context, enforceCallingOrSelfPermission(Ljava/lang/String;Ljava/lang/String;)V > 5,6,7 @10 exception:8,
9 = getfield < Application, Lcom/android/server/lights/LightsService$LightsManagerBinderService, this$0, <Application,Lcom/android/server/lights/LightsService> > 1,
monitorenter 9,
10 = getfield < Application, Lcom/android/server/lights/LightsService$LightsManagerBinderService, this$0, <Application,Lcom/android/server/lights/LightsService> > 1,
12 = invokestatic < Application, Lcom/android/server/lights/LightsService, -$$Nest$fgetmLightsById(Lcom/android/server/lights/LightsService;)Landroid/util/SparseArray; > 10 @18 exception:11,
2 = getfield < Application, Lcom/android/server/lights/LightsService, mLightsById, <Application,Landroid/util/SparseArray> > 1,
return 2,
14 = invokevirtual < Application, Landroid/util/SparseArray, get(I)Ljava/lang/Object; > 12,2 @22 exception:13,
15 = checkcast <Application,Lcom/android/server/lights/LightsService$LightImpl>14 <Application,Lcom/android/server/lights/LightsService$LightImpl>,
conditional branch(eq, to iindex=-1) 15,16,
18 = invokestatic < Application, Lcom/android/server/lights/LightsService$LightImpl, -$$Nest$misSystemLight(Lcom/android/server/lights/LightsService$LightImpl;)Z > 15 @30 exception:17,
3 = invokevirtual < Application, Lcom/android/server/lights/LightsService$LightImpl, isSystemLight()Z > 1 @0 exception:2,
2 = getfield < Application, Lcom/android/server/lights/LightsService$LightImpl, mHwLight, <Application,Landroid/hardware/light/HwLight> > 1,
3 = getfield < Application, Landroid/hardware/light/HwLight, type, <Primordial,B> > 2,
conditional branch(lt, to iindex=-1) 3,4,
conditional branch(ge, to iindex=-1) 3,5,
goto (from iindex= 6 to iindex = 2),
7 = phi  6,4,
return 7,
return 3,
conditional branch(ne, to iindex=-1) 18,16,
33 = new <Application,Landroid/hardware/lights/LightState>@36,
35 = invokestatic < Application, Lcom/android/server/lights/LightsService$LightImpl, -$$Nest$mgetColor(Lcom/android/server/lights/LightsService$LightImpl;)I > 15 @38 exception:34,
3 = invokevirtual < Application, Lcom/android/server/lights/LightsService$LightImpl, getColor()I > 1 @0 exception:2,
2 = getfield < Application, Lcom/android/server/lights/LightsService$LightImpl, mColor, <Primordial,I> > 1,
return 2,
return 3,
invokespecial < Application, Landroid/hardware/lights/LightState, <init>(I)V > 33,35 @42 exception:36,
monitorexit 9,
return 33,","depth : 0
-----
depth : 1
-----
depth : 1
-----
depth : 2
-----
depth : 1
-----
depth : 2
-----
","public LightState getLightState(int p1){
	SparseArray v3 = this.mLightsById;
	Object v4 = v3.get(p1);
	if (v4 == 0) {
		if (HwLight.type < 0) {
			if (HwLight.type >= 8) {
				boolean v6 = ;
				boolean v5 = v6;
				if (v5 != 0) {
					LightState v7 = new LightState(v8);
					int v9 = this.mColor;
					int v8 = v9;
					return v7;
				}
			}
		}
	}
}
","SYS_OR_SIG"

"Lcom/android/server/lights/LightsService$LightsManagerBinderService","openSession(Landroid/os/IBinder;I)V","0","4 = getfield < Application, Lcom/android/server/lights/LightsService$LightsManagerBinderService, this$0, <Application,Lcom/android/server/lights/LightsService> > 1,
6 = invokevirtual < Application, Lcom/android/server/SystemService, getContext()Landroid/content/Context; > 4 @2 exception:5,
invokevirtual < Application, Landroid/content/Context, enforceCallingOrSelfPermission(Ljava/lang/String;Ljava/lang/String;)V > 6,7,8 @11 exception:9,
11 = invokestatic < Application, Lcom/android/internal/util/Preconditions, checkNotNull(Ljava/lang/Object;)Ljava/lang/Object; > 2 @14 exception:10,
12 = getfield < Application, Lcom/android/server/lights/LightsService$LightsManagerBinderService, this$0, <Application,Lcom/android/server/lights/LightsService> > 1,
monitorenter 12,
14 = invokevirtual < Application, Lcom/android/server/lights/LightsService$LightsManagerBinderService, getSessionLocked(Landroid/os/IBinder;)Lcom/android/server/lights/LightsService$LightsManagerBinderService$Session; > 1,2 @20 exception:13,
conditional branch(ne, to iindex=-1) 14,15,
goto (from iindex= 14 to iindex = 2),
17 = phi  16,15,
invokestatic < Application, Lcom/android/internal/util/Preconditions, checkState(ZLjava/lang/String;)V > 17,18 @32 exception:19,
20 = new <Application,Lcom/android/server/lights/LightsService$LightsManagerBinderService$$ExternalSyntheticLambda0>@35,
invokespecial < Application, Lcom/android/server/lights/LightsService$LightsManagerBinderService$$ExternalSyntheticLambda0, <init>(Lcom/android/server/lights/LightsService$LightsManagerBinderService;Landroid/os/IBinder;)V > 20,1,2 @37 exception:21,
invokeinterface < Application, Landroid/os/IBinder, linkToDeath(Landroid/os/IBinder$DeathRecipient;I)V > 2,20,15 @40 exception:22,
31 = getfield < Application, Lcom/android/server/lights/LightsService$LightsManagerBinderService, mSessions, <Application,Ljava/util/List> > 1,
32 = new <Application,Lcom/android/server/lights/LightsService$LightsManagerBinderService$Session>@45,
invokespecial < Application, Lcom/android/server/lights/LightsService$LightsManagerBinderService$Session, <init>(Lcom/android/server/lights/LightsService$LightsManagerBinderService;Landroid/os/IBinder;I)V > 32,1,2,3 @47 exception:33,
35 = invokeinterface < Application, Ljava/util/List, add(Ljava/lang/Object;)Z > 31,32 @50 exception:34,
36 = getfield < Application, Lcom/android/server/lights/LightsService$LightsManagerBinderService, mSessions, <Application,Ljava/util/List> > 1,
invokestatic < Application, Ljava/util/Collections, sort(Ljava/util/List;)V > 36 @55 exception:37,
monitorexit 12,
return,","depth : 0
-----
","public void openSession(IBinder p1, int p2){
	Object v3 = Preconditions.checkNotNull(p1);
	LightsService$LightsManagerBinderService$Session v4 = p0.getSessionLocked(p1);
	if (v4 != 0) {
		Preconditions.checkState(, ""already registered"");
		LightsService$LightsManagerBinderService$$ExternalSyntheticLambda0 v6 = new LightsService$LightsManagerBinderService$$ExternalSyntheticLambda0(p0,p1);
		p1.linkToDeath(v6, 0);
		LightsService$LightsManagerBinderService$Session v9 = new LightsService$LightsManagerBinderService$Session(p0,p1,p2);
		boolean v11 = this.mSessions.add(v9);
		Collections.sort(this.mSessions);
		return;
	}
}
","SYS_OR_SIG"
"Lcom/android/server/lights/LightsService$LightsManagerBinderService","openSession(Landroid/os/IBinder;I)V","1","4 = getfield < Application, Lcom/android/server/lights/LightsService$LightsManagerBinderService, this$0, <Application,Lcom/android/server/lights/LightsService> > 1,
6 = invokevirtual < Application, Lcom/android/server/SystemService, getContext()Landroid/content/Context; > 4 @2 exception:5,
invokevirtual < Application, Landroid/content/Context, enforceCallingOrSelfPermission(Ljava/lang/String;Ljava/lang/String;)V > 6,7,8 @11 exception:9,
11 = invokestatic < Application, Lcom/android/internal/util/Preconditions, checkNotNull(Ljava/lang/Object;)Ljava/lang/Object; > 2 @14 exception:10,
12 = getfield < Application, Lcom/android/server/lights/LightsService$LightsManagerBinderService, this$0, <Application,Lcom/android/server/lights/LightsService> > 1,
monitorenter 12,
14 = invokevirtual < Application, Lcom/android/server/lights/LightsService$LightsManagerBinderService, getSessionLocked(Landroid/os/IBinder;)Lcom/android/server/lights/LightsService$LightsManagerBinderService$Session; > 1,2 @20 exception:13,
16 = phi  15,3,
4 = getfield < Application, Lcom/android/server/lights/LightsService$LightsManagerBinderService, mSessions, <Application,Ljava/util/List> > 1,
6 = invokeinterface < Application, Ljava/util/List, size()I > 4 @3 exception:5,
conditional branch(ge, to iindex=-1) 16,6,
7 = getfield < Application, Lcom/android/server/lights/LightsService$LightsManagerBinderService, mSessions, <Application,Ljava/util/List> > 1,
9 = invokeinterface < Application, Ljava/util/List, get(I)Ljava/lang/Object; > 7,16 @11 exception:8,
10 = checkcast <Application,Lcom/android/server/lights/LightsService$LightsManagerBinderService$Session>9 <Application,Lcom/android/server/lights/LightsService$LightsManagerBinderService$Session>,
11 = getfield < Application, Lcom/android/server/lights/LightsService$LightsManagerBinderService$Session, mToken, <Application,Landroid/os/IBinder> > 10,
13 = invokevirtual < Application, Ljava/lang/Object, equals(Ljava/lang/Object;)Z > 2,11 @19 exception:12,
conditional branch(eq, to iindex=-1) 13,3,
17 = getfield < Application, Lcom/android/server/lights/LightsService$LightsManagerBinderService, mSessions, <Application,Ljava/util/List> > 1,
19 = invokeinterface < Application, Ljava/util/List, get(I)Ljava/lang/Object; > 17,16 @27 exception:18,
20 = checkcast <Application,Lcom/android/server/lights/LightsService$LightsManagerBinderService$Session>19 <Application,Lcom/android/server/lights/LightsService$LightsManagerBinderService$Session>,
return 20,
conditional branch(ne, to iindex=-1) 14,15,
goto (from iindex= 14 to iindex = 2),
17 = phi  16,15,
invokestatic < Application, Lcom/android/internal/util/Preconditions, checkState(ZLjava/lang/String;)V > 17,18 @32 exception:19,
20 = new <Application,Lcom/android/server/lights/LightsService$LightsManagerBinderService$$ExternalSyntheticLambda0>@35,
invokespecial < Application, Lcom/android/server/lights/LightsService$LightsManagerBinderService$$ExternalSyntheticLambda0, <init>(Lcom/android/server/lights/LightsService$LightsManagerBinderService;Landroid/os/IBinder;)V > 20,1,2 @37 exception:21,
invokeinterface < Application, Landroid/os/IBinder, linkToDeath(Landroid/os/IBinder$DeathRecipient;I)V > 2,20,15 @40 exception:22,
31 = getfield < Application, Lcom/android/server/lights/LightsService$LightsManagerBinderService, mSessions, <Application,Ljava/util/List> > 1,
32 = new <Application,Lcom/android/server/lights/LightsService$LightsManagerBinderService$Session>@45,
invokespecial < Application, Lcom/android/server/lights/LightsService$LightsManagerBinderService$Session, <init>(Lcom/android/server/lights/LightsService$LightsManagerBinderService;Landroid/os/IBinder;I)V > 32,1,2,3 @47 exception:33,
35 = invokeinterface < Application, Ljava/util/List, add(Ljava/lang/Object;)Z > 31,32 @50 exception:34,
36 = getfield < Application, Lcom/android/server/lights/LightsService$LightsManagerBinderService, mSessions, <Application,Ljava/util/List> > 1,
invokestatic < Application, Ljava/util/Collections, sort(Ljava/util/List;)V > 36 @55 exception:37,
monitorexit 12,
return,","depth : 0
-----
depth : 1
-----
","public void openSession(IBinder p1, int p2){
	Object v3 = Preconditions.checkNotNull(p1);
	int v5 = this.mSessions.size();
	if ( >= v5) {
		Object v6 = this.mSessions.get();
		boolean v7 = p1.equals(LightsService$LightsManagerBinderService$Session.mToken);
		if (v7 == 0) {
			Object v8 = this.mSessions.get();
			LightsService$LightsManagerBinderService$Session v4 = v8;
			if (v4 != 0) {
				Preconditions.checkState(, ""already registered"");
				LightsService$LightsManagerBinderService$$ExternalSyntheticLambda0 v10 = new LightsService$LightsManagerBinderService$$ExternalSyntheticLambda0(p0,p1);
				p1.linkToDeath(v10, 0);
				LightsService$LightsManagerBinderService$Session v13 = new LightsService$LightsManagerBinderService$Session(p0,p1,p2);
				boolean v15 = this.mSessions.add(v13);
				Collections.sort(this.mSessions);
				return;
			}
		}
	}
}
","SYS_OR_SIG"
"Lcom/android/server/lights/LightsService$LightsManagerBinderService","openSession(Landroid/os/IBinder;I)V","1","4 = getfield < Application, Lcom/android/server/lights/LightsService$LightsManagerBinderService, this$0, <Application,Lcom/android/server/lights/LightsService> > 1,
6 = invokevirtual < Application, Lcom/android/server/SystemService, getContext()Landroid/content/Context; > 4 @2 exception:5,
invokevirtual < Application, Landroid/content/Context, enforceCallingOrSelfPermission(Ljava/lang/String;Ljava/lang/String;)V > 6,7,8 @11 exception:9,
11 = invokestatic < Application, Lcom/android/internal/util/Preconditions, checkNotNull(Ljava/lang/Object;)Ljava/lang/Object; > 2 @14 exception:10,
12 = getfield < Application, Lcom/android/server/lights/LightsService$LightsManagerBinderService, this$0, <Application,Lcom/android/server/lights/LightsService> > 1,
monitorenter 12,
14 = invokevirtual < Application, Lcom/android/server/lights/LightsService$LightsManagerBinderService, getSessionLocked(Landroid/os/IBinder;)Lcom/android/server/lights/LightsService$LightsManagerBinderService$Session; > 1,2 @20 exception:13,
16 = phi  15,3,
4 = getfield < Application, Lcom/android/server/lights/LightsService$LightsManagerBinderService, mSessions, <Application,Ljava/util/List> > 1,
6 = invokeinterface < Application, Ljava/util/List, size()I > 4 @3 exception:5,
conditional branch(ge, to iindex=-1) 16,6,
7 = getfield < Application, Lcom/android/server/lights/LightsService$LightsManagerBinderService, mSessions, <Application,Ljava/util/List> > 1,
9 = invokeinterface < Application, Ljava/util/List, get(I)Ljava/lang/Object; > 7,16 @11 exception:8,
10 = checkcast <Application,Lcom/android/server/lights/LightsService$LightsManagerBinderService$Session>9 <Application,Lcom/android/server/lights/LightsService$LightsManagerBinderService$Session>,
11 = getfield < Application, Lcom/android/server/lights/LightsService$LightsManagerBinderService$Session, mToken, <Application,Landroid/os/IBinder> > 10,
13 = invokevirtual < Application, Ljava/lang/Object, equals(Ljava/lang/Object;)Z > 2,11 @19 exception:12,
conditional branch(eq, to iindex=-1) 13,3,
17 = getfield < Application, Lcom/android/server/lights/LightsService$LightsManagerBinderService, mSessions, <Application,Ljava/util/List> > 1,
19 = invokeinterface < Application, Ljava/util/List, get(I)Ljava/lang/Object; > 17,16 @27 exception:18,
20 = checkcast <Application,Lcom/android/server/lights/LightsService$LightsManagerBinderService$Session>19 <Application,Lcom/android/server/lights/LightsService$LightsManagerBinderService$Session>,
return 20,
conditional branch(ne, to iindex=-1) 14,15,
17 = phi  16,15,
invokestatic < Application, Lcom/android/internal/util/Preconditions, checkState(ZLjava/lang/String;)V > 17,18 @32 exception:19,
20 = new <Application,Lcom/android/server/lights/LightsService$LightsManagerBinderService$$ExternalSyntheticLambda0>@35,
invokespecial < Application, Lcom/android/server/lights/LightsService$LightsManagerBinderService$$ExternalSyntheticLambda0, <init>(Lcom/android/server/lights/LightsService$LightsManagerBinderService;Landroid/os/IBinder;)V > 20,1,2 @37 exception:21,
invokeinterface < Application, Landroid/os/IBinder, linkToDeath(Landroid/os/IBinder$DeathRecipient;I)V > 2,20,15 @40 exception:22,
31 = getfield < Application, Lcom/android/server/lights/LightsService$LightsManagerBinderService, mSessions, <Application,Ljava/util/List> > 1,
32 = new <Application,Lcom/android/server/lights/LightsService$LightsManagerBinderService$Session>@45,
invokespecial < Application, Lcom/android/server/lights/LightsService$LightsManagerBinderService$Session, <init>(Lcom/android/server/lights/LightsService$LightsManagerBinderService;Landroid/os/IBinder;I)V > 32,1,2,3 @47 exception:33,
35 = invokeinterface < Application, Ljava/util/List, add(Ljava/lang/Object;)Z > 31,32 @50 exception:34,
36 = getfield < Application, Lcom/android/server/lights/LightsService$LightsManagerBinderService, mSessions, <Application,Ljava/util/List> > 1,
invokestatic < Application, Ljava/util/Collections, sort(Ljava/util/List;)V > 36 @55 exception:37,
monitorexit 12,
return,","depth : 0
-----
depth : 1
-----
","public void openSession(IBinder p1, int p2){
	Object v3 = Preconditions.checkNotNull(p1);
	int v5 = this.mSessions.size();
	if ( >= v5) {
		Object v6 = this.mSessions.get();
		boolean v7 = p1.equals(LightsService$LightsManagerBinderService$Session.mToken);
		if (v7 == 0) {
			Object v8 = this.mSessions.get();
			LightsService$LightsManagerBinderService$Session v4 = v8;
			if (v4 != 0) {
				Preconditions.checkState(, ""already registered"");
				LightsService$LightsManagerBinderService$$ExternalSyntheticLambda0 v10 = new LightsService$LightsManagerBinderService$$ExternalSyntheticLambda0(p0,p1);
				p1.linkToDeath(v10, 0);
				LightsService$LightsManagerBinderService$Session v13 = new LightsService$LightsManagerBinderService$Session(p0,p1,p2);
				boolean v15 = this.mSessions.add(v13);
				Collections.sort(this.mSessions);
				return;
			}
		}
	}
}
","SYS_OR_SIG"

